Workbook
Name \a: Model!$A$1
Name \b: Model!$D$15
Name \p: Model!$A$1:$N$60
Name Print_Area_MI: Model!$A$1:$N$111
Name wrn.Model: Model!$A$1:$N$343
Name wrn.Summary: 'Summary_to delete'!$B$3:$K$32
Name Kestrel_EBITDA: Model!$E$85
Name Kestrel_Rev: Model!$E$75
Name Osprey_Rev: 'Summary_to delete'!$C$6:$K$6
Name Osprey_EBITDA: 'Summary_to delete'!$C$10:$K$10
Name TEV: Assump_CapStructure!$D$72
Name EqPP: Assump_CapStructure!$D$80
Name MinCash: Assump_CapStructure!$F$19
Name TaxRate: Assump_CapStructure!$F$23
Name SweepPct: Assump_CapStructure!$F$18
Name Case_Op: Assump_CapStructure!$K$5
Name Case_Fin: Assump_CapStructure!$K$15
Name IS_Rev: Model!$B$75:$M$75
Name IS_EBITDA: Model!$B$85:$M$85
Name IS_NI: Model!$F$110:$M$110
Name BS_Check: Model!$B$156:$M$156
Name CF_Cash: Model!$F$209:$M$209
Name Debt_Total: Model!$E$62:$M$62
Name Pfd_End: 'Debt Schedules'!$F$103:$M$103
Name IRR_Common: Model!$D$242:$H$242
Name IRR_Strip: Model!$D$282:$H$282
Name MoIC_Common: Model!$D$243:$H$243
Name Rollover: Model!$K$17
Name SponsorEq: Model!$K$20
Name TotalEq: Model!$E$331
Name Goodwill: Model!$D$325
Name NWC: Model!$B$306:$M$306
Name Capex_Row: Model!$B$35:$M$35
Name DA_Row: Model!$B$88:$M$88
Name Hist_Rev: Model!$B$75:$E$75
Name Proj_Rev: Model!$F$75:$M$75
Name FYE_Label: Assump_CapStructure!$F$9
Name Units: Assump_CapStructure!$F$11
Name Exit_Mults: Model!$D$214:$H$214
Name ExitEBITDA: Model!$D$213
Name Osprey_IRR: 'Summary_to delete'!$C$22

Sheet Notes
A1: =Assump_CapStructure!$F$7 -> Project Kestrel
B5: Model Notes
B7: ="(1) Equity amounts reflect the upsized sponsor equity ticket of $"&TEXT(Model!$K$18+Model!$K$19,"#,##0")&"k (90% preferred / 10% common) plus seller rollover." -> (1) Equity amounts reflect the upsized sponsor equity ticket of $14,239k (90% preferred / 10% common) plus seller rollover.
B8: ="(2) Debt amounts reflect full draw of the $"&TEXT(Model!$K$8,"#,##0")&"k term loan A at close; the $8.0M revolver is undrawn at close." -> (2) Debt amounts reflect full draw of the $23,607k term loan A at close; the $8.0M revolver is undrawn at close.
B9: (3) FY2026E reflects management estimates from the LOI; FY2026E is treated as a full year of ownership (closing 31-Jul-2026 stub period ignored).
B10: (4) Closing balance sheet reflects balances as of 31-Jul-2026 (sponsor estimate) adjusted for the transaction.
B11: (5) Although the Company is structured as a flow-through entity, taxes are reflected at 26% for conservatism ("No Taxes" operating cases switch the rate off).
B12: (6) Reflects 50% excess cash flow sweep (switch on Assump_CapStructure); sweep applied to revolver, then term loans, then mezzanine, then the seller note.
B13: (7) Equity returns are net of the 10% Management Equity Incentive Program (MEIP), which participates in common profits only.
B14: (8) Interest and preferred accretion are computed on beginning-of-period balances to avoid circular references (no iteration required).
B15: (9) Returns exhibits hold the entry multiple fixed (per tab) and vary the exit multiple; net debt at exit is the base-case net debt from the Model tab.
B16: (10) Preferred equity accretion is a memo item for returns and is not booked on the projected balance sheet; intangible assets are held flat pending PPA.
B17: (11) Sources and Uses-DETAIL / -SUMMARY carry a stale LTM 7/31/26 EBITDA input used only for the "x LTM EBITDA" column.
B20: Prepared by: Halvern Capital Partners - for internal discussion purposes only. All figures illustrative.

Sheet Sources and Uses-Live
A1: =Assump_CapStructure!$F$7 -> Project Kestrel
A2: ="Prepared by: "&Assump_CapStructure!$F$8 -> Prepared by: Halvern
A3: =Assump_CapStructure!$F$11 -> ($ in 000s)
B5: Transaction Summary
B6: =Assump_CapStructure!$F$11 -> ($ in 000s)
B8: Total Enterprise Value | E8: =Assump_CapStructure!$D$72 -> 55083 | I8: =E8/Model!$E$85 -> 7 | J8: x FY2025A Adj. EBITDA
B9: Investor Entry Multiple (FY2025A) | E9: =Assump_CapStructure!$D$73 -> 7
B10: Investor Entry Multiple (FY2026E) | E10: =Assump_CapStructure!$D$74 -> 6.2977588
B11: Operating Case: | E11: =CHOOSE(Assump_CapStructure!$K$5,"Management Case","Case II - No Growth, No Taxes","Case III - Downside Case, No Taxes","Upside Case","Flat Case") -> Management Case
B12: Financing Case: | E12: =CHOOSE(Assump_CapStructure!$K$15,"Base Case - Senior + Mezz","Senior Only","Senior + Seller Note Upsized","All Equity","Unitranche","Case 6","Case 7","Case 8","Case 9","Case 10") -> Base Case - Senior + Mezz | I12: NO | J12: Revolver drawn at close?
B13: Step Up in Basis | E13: =IF(Assump_CapStructure!$F$22=1,"Yes","No") -> Yes
B14: Rollover % of Proceeds | E14: =Model!$K$17/Assump_CapStructure!$D$80 -> 0.1834509
B15: Exit: | E15: 5 Years
B17: (1) Fixed Charge Coverage = (EBITDA - Mgmt Fee - Capex - Cash Taxes) / (Scheduled Principal + Cash Interest).
B19: Sources and Uses of Funds ($ in 000's)
B20: Uses | E20: Amount | F20: % of Total | G20: x FY2026E EBITDA | I20: Sources | L20: Amount | M20: % of Total | N20: x EBITDA | O20: Pricing
B21: Cash Consideration | E21: =Model!$D$7-Model!$K$13 -> 35472.8 | F21: =E21/$E$28 -> 0.60551354 | G21: =E21/Model!$F$85 -> 4.0556821 | I21: Revolver (undrawn) (1) | L21: =Model!$K$7 -> 0 | M21: =L21/$L$28 -> 0 | N21: =L21/Model!$F$85 -> 0 | O21: ="Base + "&TEXT(Assump_CapStructure!$U$36,"0.00%") -> Base + 3.00%
B22: Repay Existing Debt | E22: =Model!$D$8 -> 6842 | F22: =E22/$E$28 -> 0.11679156 | G22: =E22/Model!$F$85 -> 0.7822607 | I22: Term Loan A (2) | L22: =Model!$K$8 -> 23607 | M22: =L22/$L$28 -> 0.40296673 | N22: =L22/Model!$F$85 -> 2.6990395 | O22: ="Base + "&TEXT(Assump_CapStructure!$U$37,"0.00%") -> Base + 3.25%
B23: Seller Note | E23: =Model!$K$13 -> 4000 | F23: =E23/$E$28 -> 0.068279194 | G23: =E23/Model!$F$85 -> 0.45732867 | I23: Mezzanine Debt | L23: =Model!$K$12 -> 7869 | M23: =L23/$L$28 -> 0.13432224 | N23: =L23/Model!$F$85 -> 0.89967983 | O23: =TEXT(Assump_CapStructure!$U$41,"0.00%")&" cash + "&TEXT(Assump_CapStructure!$V$41,"0.00%")&" PIK" -> 11.00% cash + 2.00% PIK
B24: Rollover Equity | E24: =Model!$K$17 -> 8868.2 | F24: =E24/$E$28 -> 0.15137839 | G24: =E24/Model!$F$85 -> 1.0139205 | I24: Seller Note | L24: =Model!$K$13 -> 4000 | M24: =L24/$L$28 -> 0.068279194 | N24: =L24/Model!$F$85 -> 0.45732867 | O24: =TEXT(Assump_CapStructure!$V$42,"0.00%")&" PIK" -> 6.00% PIK
B25: Purchase Price | E25: =SUM(E21:E24) -> 55183 | F25: =E25/$E$28 -> 0.94196269 | G25: =E25/Model!$F$85 -> 6.3091921 | I25: Rollover Equity | L25: =Model!$K$17 -> 8868.2 | M25: =L25/$L$28 -> 0.15137839 | N25: =L25/Model!$F$85 -> 1.0139205
B26: Cash on Balance Sheet at Close | E26: =Model!$D$13 -> 1000 | F26: =E26/$E$28 -> 0.017069798 | G26: =E26/Model!$F$85 -> 0.11433217 | I26: Sponsor Preferred Equity (3)(4) | L26: =Model!$K$18 -> 12814.92 | M26: =L26/$L$28 -> 0.2187481 | N26: =L26/Model!$F$85 -> 1.4651576 | O26: =TEXT(Assump_CapStructure!$F$28,"0.00%")&" accreting" -> 8.00% accreting
B27: Transaction Costs / Excess Cash | E27: =Model!$D$14 -> 2400 | F27: =E27/$E$28 -> 0.040967516 | G27: =E27/Model!$F$85 -> 0.2743972 | I27: Sponsor Common Equity (3)(4) | L27: =Model!$K$19 -> 1423.88 | M27: =L27/$L$28 -> 0.024305345 | N27: =L27/Model!$F$85 -> 0.16279529
B28: Total Uses | E28: =E25+SUM(E26:E27) -> 58583 | F28: =E28/$E$28 -> 1 | G28: =E28/Model!$F$85 -> 6.6979214 | I28: Total Sources | L28: =SUM(L21:L27) -> 58583 | M28: =SUM(M21:M27) -> 1 | N28: =L28/Model!$F$85 -> 6.6979214
B30: Check: Total Sources - Total Uses (must be 0) | E30: =L28-E28 -> 0
B32: (1) $8.0M revolving credit facility, undrawn at close; commitment fee on the unused portion.
B33: ="(2) Senior leverage of "&TEXT(Model!$M$8,"0.0x")&" FY2025A Adj. EBITDA; full draw of the term loan A at close." -> (2) Senior leverage of 3.0x FY2025A Adj. EBITDA; full draw of the term loan A at close.
B34: (3) Sponsor equity is 90% preferred (8% accreting) / 10% common; common is subject to 10% MEIP dilution.
B35: (4) Sponsor equity may be syndicated to a co-investor consortium; Halvern retains control.

Sheet Live Sheet
A1: =Assump_CapStructure!$F$7 -> Project Kestrel
A2: ="Prepared by: "&Assump_CapStructure!$F$8 -> Prepared by: Halvern
A3: =Assump_CapStructure!$F$11 -> ($ in 000s)
B5: Transaction Summary
B6: =Assump_CapStructure!$F$11 -> ($ in 000s)
B8: Total Enterprise Value | E8: =Assump_CapStructure!$D$72 -> 55083 | I8: =E8/Model!$E$85 -> 7 | J8: x FY2025A Adj. EBITDA
B9: Investor Entry Multiple (FY2025A) | E9: =Assump_CapStructure!$D$73 -> 7
B10: Investor Entry Multiple (FY2026E) | E10: =Assump_CapStructure!$D$74 -> 6.2977588
B11: Operating Case: | E11: =CHOOSE(Assump_CapStructure!$K$5,"Management Case","Case II - No Growth, No Taxes","Case III - Downside Case, No Taxes","Upside Case","Flat Case") -> Management Case
B12: Financing Case: | E12: =CHOOSE(Assump_CapStructure!$K$15,"Base Case - Senior + Mezz","Senior Only","Senior + Seller Note Upsized","All Equity","Unitranche","Case 6","Case 7","Case 8","Case 9","Case 10") -> Base Case - Senior + Mezz | I12: NO | J12: Revolver drawn at close?
B13: Step Up in Basis | E13: =IF(Assump_CapStructure!$F$22=1,"Yes","No") -> Yes
B14: Rollover % of Proceeds | E14: =Model!$K$17/Assump_CapStructure!$D$80 -> 0.1834509
B15: Exit: | E15: 5 Years
B17: (1) Fixed Charge Coverage = (EBITDA - Mgmt Fee - Capex - Cash Taxes) / (Scheduled Principal + Cash Interest).
B19: Sources and Uses of Funds ($ in 000's)
B20: Uses | E20: Amount | F20: % of Total | G20: x FY2026E EBITDA | I20: Sources | L20: Amount | M20: % of Total | N20: x EBITDA | O20: Pricing
B21: Cash Consideration | E21: =Model!$D$7-Model!$K$13 -> 35472.8 | F21: =E21/$E$28 -> 0.60551354 | G21: =E21/Model!$F$85 -> 4.0556821 | I21: Revolver (undrawn) (1) | L21: =Model!$K$7 -> 0 | M21: =L21/$L$28 -> 0 | N21: =L21/Model!$F$85 -> 0 | O21: ="Base + "&TEXT(Assump_CapStructure!$U$36,"0.00%") -> Base + 3.00%
B22: Repay Existing Debt | E22: =Model!$D$8 -> 6842 | F22: =E22/$E$28 -> 0.11679156 | G22: =E22/Model!$F$85 -> 0.7822607 | I22: Term Loan A (2) | L22: =Model!$K$8 -> 23607 | M22: =L22/$L$28 -> 0.40296673 | N22: =L22/Model!$F$85 -> 2.6990395 | O22: ="Base + "&TEXT(Assump_CapStructure!$U$37,"0.00%") -> Base + 3.25%
B23: Seller Note | E23: =Model!$K$13 -> 4000 | F23: =E23/$E$28 -> 0.068279194 | G23: =E23/Model!$F$85 -> 0.45732867 | I23: Mezzanine Debt | L23: =Model!$K$12 -> 7869 | M23: =L23/$L$28 -> 0.13432224 | N23: =L23/Model!$F$85 -> 0.89967983 | O23: =TEXT(Assump_CapStructure!$U$41,"0.00%")&" cash + "&TEXT(Assump_CapStructure!$V$41,"0.00%")&" PIK" -> 11.00% cash + 2.00% PIK
B24: Rollover Equity | E24: =Model!$K$17 -> 8868.2 | F24: =E24/$E$28 -> 0.15137839 | G24: =E24/Model!$F$85 -> 1.0139205 | I24: Seller Note | L24: =Model!$K$13 -> 4000 | M24: =L24/$L$28 -> 0.068279194 | N24: =L24/Model!$F$85 -> 0.45732867 | O24: =TEXT(Assump_CapStructure!$V$42,"0.00%")&" PIK" -> 6.00% PIK
B25: Purchase Price | E25: =SUM(E21:E24) -> 55183 | F25: =E25/$E$28 -> 0.94196269 | G25: =E25/Model!$F$85 -> 6.3091921 | I25: Rollover Equity | L25: =Model!$K$17 -> 8868.2 | M25: =L25/$L$28 -> 0.15137839 | N25: =L25/Model!$F$85 -> 1.0139205
B26: Cash on Balance Sheet at Close | E26: =Model!$D$13 -> 1000 | F26: =E26/$E$28 -> 0.017069798 | G26: =E26/Model!$F$85 -> 0.11433217 | I26: Sponsor Preferred Equity (3)(4) | L26: =Model!$K$18 -> 12814.92 | M26: =L26/$L$28 -> 0.2187481 | N26: =L26/Model!$F$85 -> 1.4651576 | O26: =TEXT(Assump_CapStructure!$F$28,"0.00%")&" accreting" -> 8.00% accreting
B27: Transaction Costs / Excess Cash | E27: =Model!$D$14 -> 2400 | F27: =E27/$E$28 -> 0.040967516 | G27: =E27/Model!$F$85 -> 0.2743972 | I27: Sponsor Common Equity (3)(4) | L27: =Model!$K$19 -> 1423.88 | M27: =L27/$L$28 -> 0.024305345 | N27: =L27/Model!$F$85 -> 0.16279529
B28: Total Uses | E28: =E25+SUM(E26:E27) -> 58583 | F28: =E28/$E$28 -> 1 | G28: =E28/Model!$F$85 -> 6.6979214 | I28: Total Sources | L28: =SUM(L21:L27) -> 58583 | M28: =SUM(M21:M27) -> 1 | N28: =L28/Model!$F$85 -> 6.6979214
B30: Check: Total Sources - Total Uses (must be 0) | E30: =L28-E28 -> 0
B32: Illustrative Five Year Gross Return Profile - IRR and Multiple of Invested Capital
B34: Returns Inputs (linked to Model / Assump_CapStructure)
B35: FY2025A Adj. EBITDA | E35: =Model!$E$85 -> 7869
B36: FY2030E EBITDA (exit year 5) | E36: =Model!$J$85 -> 11754.676
B37: FY2028E EBITDA (exit year 3) | E37: =Model!$H$85 -> 10300.977
B38: Debt raised at close (base case, fixed) | E38: =Model!$K$16 -> 35476
B39: Transaction costs + cash to B/S + cash acquired | E39: =Model!$D$14+Model!$D$13+Assump_CapStructure!$D$79 -> 3500
B40: Net debt at FY2030E (excl. seller note; from Model) | E40: =Model!$J$62-Model!$J$61-Model!$J$51 -> 3755.4841
B41: Seller note accreted balance at FY2030E | E41: =Model!$J$61 -> 5352.9023
B42: Net debt at FY2028E (excl. seller note; from Model) | E42: =Model!$H$62-Model!$H$61-Model!$H$51 -> 16536.503
B43: Seller note accreted balance at FY2028E | E43: =Model!$H$61 -> 4764.064
B44: Cumulative goodwill step-up tax savings through FY2028E | E44: =Model!$H$328 -> 2074.696
B45: Preferred % of equity account | E45: =Assump_CapStructure!$F$31 -> 0.9
B46: Preferred accretion rate | E46: =Assump_CapStructure!$F$28 -> 0.08
B47: MEIP % of common profits | E47: =Assump_CapStructure!$F$29 -> 0.1
B48: Sponsor carried interest | E48: =Assump_CapStructure!$F$30 -> 0.2
B50: Gross Returns - Common Equity (net of MEIP)
B51: Exit Multiple (x exit-year EBITDA) | F51: 6 | G51: 6.5 | H51: 7 | I51: 7.5 | J51: 8
B52: Sale Price (Enterprise Value at exit) | F52: =F51*$E$36 -> 70528.058 | G52: =G51*$E$36 -> 76405.396 | H52: =H51*$E$36 -> 82282.734 | I52: =I51*$E$36 -> 88160.072 | J52: =J51*$E$36 -> 94037.41
B53: Entry Multiple | C53: Purchase Price | D53: Total Equity at Entry | E53: Pfd Accreted at Exit | F53: Common Equity Proceeds (net of MEIP)
B54: 6 | C54: =B54*$E$35 -> 47214 | D54: =C54+$E$39-$E$38 -> 15238 | E54: =D54*$E$45*(1+$E$46)^5 -> 20150.659 | F54: =(MIN((F$52-$E$40-$E$41)-MIN((F$52-$E$40-$E$41),$E54),($D54*(1-$E$45)))+(1-$E$47)*MAX(0,(F$52-$E$40-$E$41)-MIN((F$52-$E$40-$E$41),$E54)-($D54*(1-$E$45)))) -> 37294.491 | G54: =(MIN((G$52-$E$40-$E$41)-MIN((G$52-$E$40-$E$41),$E54),($D54*(1-$E$45)))+(1-$E$47)*MAX(0,(G$52-$E$40-$E$41)-MIN((G$52-$E$40-$E$41),$E54)-($D54*(1-$E$45)))) -> 42584.095 | H54: =(MIN((H$52-$E$40-$E$41)-MIN((H$52-$E$40-$E$41),$E54),($D54*(1-$E$45)))+(1-$E$47)*MAX(0,(H$52-$E$40-$E$41)-MIN((H$52-$E$40-$E$41),$E54)-($D54*(1-$E$45)))) -> 47873.699 | I54: =(MIN((I$52-$E$40-$E$41)-MIN((I$52-$E$40-$E$41),$E54),($D54*(1-$E$45)))+(1-$E$47)*MAX(0,(I$52-$E$40-$E$41)-MIN((I$52-$E$40-$E$41),$E54)-($D54*(1-$E$45)))) -> 53163.304 | J54: =(MIN((J$52-$E$40-$E$41)-MIN((J$52-$E$40-$E$41),$E54),($D54*(1-$E$45)))+(1-$E$47)*MAX(0,(J$52-$E$40-$E$41)-MIN((J$52-$E$40-$E$41),$E54)-($D54*(1-$E$45)))) -> 58452.908
B55: 6.5 | C55: =B55*$E$35 -> 51148.5 | D55: =C55+$E$39-$E$38 -> 19172.5 | E55: =D55*$E$45*(1+$E$46)^5 -> 25353.623 | F55: =(MIN((F$52-$E$40-$E$41)-MIN((F$52-$E$40-$E$41),$E55),($D55*(1-$E$45)))+(1-$E$47)*MAX(0,(F$52-$E$40-$E$41)-MIN((F$52-$E$40-$E$41),$E55)-($D55*(1-$E$45)))) -> 32651.168 | G55: =(MIN((G$52-$E$40-$E$41)-MIN((G$52-$E$40-$E$41),$E55),($D55*(1-$E$45)))+(1-$E$47)*MAX(0,(G$52-$E$40-$E$41)-MIN((G$52-$E$40-$E$41),$E55)-($D55*(1-$E$45)))) -> 37940.772 | H55: =(MIN((H$52-$E$40-$E$41)-MIN((H$52-$E$40-$E$41),$E55),($D55*(1-$E$45)))+(1-$E$47)*MAX(0,(H$52-$E$40-$E$41)-MIN((H$52-$E$40-$E$41),$E55)-($D55*(1-$E$45)))) -> 43230.377 | I55: =(MIN((I$52-$E$40-$E$41)-MIN((I$52-$E$40-$E$41),$E55),($D55*(1-$E$45)))+(1-$E$47)*MAX(0,(I$52-$E$40-$E$41)-MIN((I$52-$E$40-$E$41),$E55)-($D55*(1-$E$45)))) -> 48519.981 | J55: =(MIN((J$52-$E$40-$E$41)-MIN((J$52-$E$40-$E$41),$E55),($D55*(1-$E$45)))+(1-$E$47)*MAX(0,(J$52-$E$40-$E$41)-MIN((J$52-$E$40-$E$41),$E55)-($D55*(1-$E$45)))) -> 53809.585
B56: 7 | C56: =B56*$E$35 -> 55083 | D56: =C56+$E$39-$E$38 -> 23107 | E56: =D56*$E$45*(1+$E$46)^5 -> 30556.587 | F56: =(MIN((F$52-$E$40-$E$41)-MIN((F$52-$E$40-$E$41),$E56),($D56*(1-$E$45)))+(1-$E$47)*MAX(0,(F$52-$E$40-$E$41)-MIN((F$52-$E$40-$E$41),$E56)-($D56*(1-$E$45)))) -> 28007.845 | G56: =(MIN((G$52-$E$40-$E$41)-MIN((G$52-$E$40-$E$41),$E56),($D56*(1-$E$45)))+(1-$E$47)*MAX(0,(G$52-$E$40-$E$41)-MIN((G$52-$E$40-$E$41),$E56)-($D56*(1-$E$45)))) -> 33297.45 | H56: =(MIN((H$52-$E$40-$E$41)-MIN((H$52-$E$40-$E$41),$E56),($D56*(1-$E$45)))+(1-$E$47)*MAX(0,(H$52-$E$40-$E$41)-MIN((H$52-$E$40-$E$41),$E56)-($D56*(1-$E$45)))) -> 38587.054 | I56: =(MIN((I$52-$E$40-$E$41)-MIN((I$52-$E$40-$E$41),$E56),($D56*(1-$E$45)))+(1-$E$47)*MAX(0,(I$52-$E$40-$E$41)-MIN((I$52-$E$40-$E$41),$E56)-($D56*(1-$E$45)))) -> 43876.658 | J56: =(MIN((J$52-$E$40-$E$41)-MIN((J$52-$E$40-$E$41),$E56),($D56*(1-$E$45)))+(1-$E$47)*MAX(0,(J$52-$E$40-$E$41)-MIN((J$52-$E$40-$E$41),$E56)-($D56*(1-$E$45)))) -> 49166.263
B57: 7.5 | C57: =B57*$E$35 -> 59017.5 | D57: =C57+$E$39-$E$38 -> 27041.5 | E57: =D57*$E$45*(1+$E$46)^5 -> 35759.552 | F57: =(MIN((F$52-$E$40-$E$41)-MIN((F$52-$E$40-$E$41),$E57),($D57*(1-$E$45)))+(1-$E$47)*MAX(0,(F$52-$E$40-$E$41)-MIN((F$52-$E$40-$E$41),$E57)-($D57*(1-$E$45)))) -> 23364.523 | G57: =(MIN((G$52-$E$40-$E$41)-MIN((G$52-$E$40-$E$41),$E57),($D57*(1-$E$45)))+(1-$E$47)*MAX(0,(G$52-$E$40-$E$41)-MIN((G$52-$E$40-$E$41),$E57)-($D57*(1-$E$45)))) -> 28654.127 | H57: =(MIN((H$52-$E$40-$E$41)-MIN((H$52-$E$40-$E$41),$E57),($D57*(1-$E$45)))+(1-$E$47)*MAX(0,(H$52-$E$40-$E$41)-MIN((H$52-$E$40-$E$41),$E57)-($D57*(1-$E$45)))) -> 33943.731 | I57: =(MIN((I$52-$E$40-$E$41)-MIN((I$52-$E$40-$E$41),$E57),($D57*(1-$E$45)))+(1-$E$47)*MAX(0,(I$52-$E$40-$E$41)-MIN((I$52-$E$40-$E$41),$E57)-($D57*(1-$E$45)))) -> 39233.335 | J57: =(MIN((J$52-$E$40-$E$41)-MIN((J$52-$E$40-$E$41),$E57),($D57*(1-$E$45)))+(1-$E$47)*MAX(0,(J$52-$E$40-$E$41)-MIN((J$52-$E$40-$E$41),$E57)-($D57*(1-$E$45)))) -> 44522.94
B58: 8 | C58: =B58*$E$35 -> 62952 | D58: =C58+$E$39-$E$38 -> 30976 | E58: =D58*$E$45*(1+$E$46)^5 -> 40962.516 | F58: =(MIN((F$52-$E$40-$E$41)-MIN((F$52-$E$40-$E$41),$E58),($D58*(1-$E$45)))+(1-$E$47)*MAX(0,(F$52-$E$40-$E$41)-MIN((F$52-$E$40-$E$41),$E58)-($D58*(1-$E$45)))) -> 18721.2 | G58: =(MIN((G$52-$E$40-$E$41)-MIN((G$52-$E$40-$E$41),$E58),($D58*(1-$E$45)))+(1-$E$47)*MAX(0,(G$52-$E$40-$E$41)-MIN((G$52-$E$40-$E$41),$E58)-($D58*(1-$E$45)))) -> 24010.804 | H58: =(MIN((H$52-$E$40-$E$41)-MIN((H$52-$E$40-$E$41),$E58),($D58*(1-$E$45)))+(1-$E$47)*MAX(0,(H$52-$E$40-$E$41)-MIN((H$52-$E$40-$E$41),$E58)-($D58*(1-$E$45)))) -> 29300.408 | I58: =(MIN((I$52-$E$40-$E$41)-MIN((I$52-$E$40-$E$41),$E58),($D58*(1-$E$45)))+(1-$E$47)*MAX(0,(I$52-$E$40-$E$41)-MIN((I$52-$E$40-$E$41),$E58)-($D58*(1-$E$45)))) -> 34590.013 | J58: =(MIN((J$52-$E$40-$E$41)-MIN((J$52-$E$40-$E$41),$E58),($D58*(1-$E$45)))+(1-$E$47)*MAX(0,(J$52-$E$40-$E$41)-MIN((J$52-$E$40-$E$41),$E58)-($D58*(1-$E$45)))) -> 39879.617
B59: IRR | F59: Exit multiple ->
B60: =B54 -> 6 | F60: =IF(($D54*(1-$E$45))<=0,0,(F54/($D54*(1-$E$45)))^(1/5)-1) -> 0.89558535 | G60: =IF(($D54*(1-$E$45))<=0,0,(G54/($D54*(1-$E$45)))^(1/5)-1) -> 0.9465425 | H60: =IF(($D54*(1-$E$45))<=0,0,(H54/($D54*(1-$E$45)))^(1/5)-1) -> 0.99266276 | I60: =IF(($D54*(1-$E$45))<=0,0,(I54/($D54*(1-$E$45)))^(1/5)-1) -> 1.0348706 | J60: =IF(($D54*(1-$E$45))<=0,0,(J54/($D54*(1-$E$45)))^(1/5)-1) -> 1.0738418
B61: =B55 -> 6.5 | F61: =IF(($D55*(1-$E$45))<=0,0,(F55/($D55*(1-$E$45)))^(1/5)-1) -> 0.76296624 | G61: =IF(($D55*(1-$E$45))<=0,0,(G55/($D55*(1-$E$45)))^(1/5)-1) -> 0.81670949 | H61: =IF(($D55*(1-$E$45))<=0,0,(H55/($D55*(1-$E$45)))^(1/5)-1) -> 0.86475618 | I61: =IF(($D55*(1-$E$45))<=0,0,(I55/($D55*(1-$E$45)))^(1/5)-1) -> 0.90830758 | J61: =IF(($D55*(1-$E$45))<=0,0,(J55/($D55*(1-$E$45)))^(1/5)-1) -> 0.94821185
B62: =B56 -> 7 | F62: =IF(($D56*(1-$E$45))<=0,0,(F56/($D56*(1-$E$45)))^(1/5)-1) -> 0.64705168 | G62: =IF(($D56*(1-$E$45))<=0,0,(G56/($D56*(1-$E$45)))^(1/5)-1) -> 0.70503572 | H62: =IF(($D56*(1-$E$45))<=0,0,(H56/($D56*(1-$E$45)))^(1/5)-1) -> 0.75606106 | I62: =IF(($D56*(1-$E$45))<=0,0,(I56/($D56*(1-$E$45)))^(1/5)-1) -> 0.80176438 | J62: =IF(($D56*(1-$E$45))<=0,0,(J56/($D56*(1-$E$45)))^(1/5)-1) -> 0.84325205
B63: =B57 -> 7.5 | F63: =IF(($D57*(1-$E$45))<=0,0,(F57/($D57*(1-$E$45)))^(1/5)-1) -> 0.53923605 | G63: =IF(($D57*(1-$E$45))<=0,0,(G57/($D57*(1-$E$45)))^(1/5)-1) -> 0.60336087 | H63: =IF(($D57*(1-$E$45))<=0,0,(H57/($D57*(1-$E$45)))^(1/5)-1) -> 0.65861565 | I63: =IF(($D57*(1-$E$45))<=0,0,(I57/($D57*(1-$E$45)))^(1/5)-1) -> 0.70735917 | J63: =IF(($D57*(1-$E$45))<=0,0,(J57/($D57*(1-$E$45)))^(1/5)-1) -> 0.75109864
B64: =B58 -> 8 | F64: =IF(($D58*(1-$E$45))<=0,0,(F58/($D58*(1-$E$45)))^(1/5)-1) -> 0.43305107 | G64: =IF(($D58*(1-$E$45))<=0,0,(G58/($D58*(1-$E$45)))^(1/5)-1) -> 0.50617791 | H64: =IF(($D58*(1-$E$45))<=0,0,(H58/($D58*(1-$E$45)))^(1/5)-1) -> 0.56736328 | I64: =IF(($D58*(1-$E$45))<=0,0,(I58/($D58*(1-$E$45)))^(1/5)-1) -> 0.62026137 | J64: =IF(($D58*(1-$E$45))<=0,0,(J58/($D58*(1-$E$45)))^(1/5)-1) -> 0.66703658
B65: MoIC
B66: =B54 -> 6 | F66: =IF(($D54*(1-$E$45))<=0,0,F54/($D54*(1-$E$45))) -> 24.474663 | G66: =IF(($D54*(1-$E$45))<=0,0,G54/($D54*(1-$E$45))) -> 27.945987 | H66: =IF(($D54*(1-$E$45))<=0,0,H54/($D54*(1-$E$45))) -> 31.417312 | I66: =IF(($D54*(1-$E$45))<=0,0,I54/($D54*(1-$E$45))) -> 34.888636 | J66: =IF(($D54*(1-$E$45))<=0,0,J54/($D54*(1-$E$45))) -> 38.359961
B67: =B55 -> 6.5 | F67: =IF(($D55*(1-$E$45))<=0,0,F55/($D55*(1-$E$45))) -> 17.030209 | G67: =IF(($D55*(1-$E$45))<=0,0,G55/($D55*(1-$E$45))) -> 19.789163 | H67: =IF(($D55*(1-$E$45))<=0,0,H55/($D55*(1-$E$45))) -> 22.548117 | I67: =IF(($D55*(1-$E$45))<=0,0,I55/($D55*(1-$E$45))) -> 25.307071 | J67: =IF(($D55*(1-$E$45))<=0,0,J55/($D55*(1-$E$45))) -> 28.066024
B68: =B56 -> 7 | F68: =IF(($D56*(1-$E$45))<=0,0,F56/($D56*(1-$E$45))) -> 12.120935 | G68: =IF(($D56*(1-$E$45))<=0,0,G56/($D56*(1-$E$45))) -> 14.410114 | H68: =IF(($D56*(1-$E$45))<=0,0,H56/($D56*(1-$E$45))) -> 16.699292 | I68: =IF(($D56*(1-$E$45))<=0,0,I56/($D56*(1-$E$45))) -> 18.98847 | J68: =IF(($D56*(1-$E$45))<=0,0,J56/($D56*(1-$E$45))) -> 21.277649
B69: =B57 -> 7.5 | F69: =IF(($D57*(1-$E$45))<=0,0,F57/($D57*(1-$E$45))) -> 8.6402465 | G69: =IF(($D57*(1-$E$45))<=0,0,G57/($D57*(1-$E$45))) -> 10.596353 | H69: =IF(($D57*(1-$E$45))<=0,0,H57/($D57*(1-$E$45))) -> 12.552459 | I69: =IF(($D57*(1-$E$45))<=0,0,I57/($D57*(1-$E$45))) -> 14.508565 | J69: =IF(($D57*(1-$E$45))<=0,0,J57/($D57*(1-$E$45))) -> 16.464671
B70: =B58 -> 8 | F70: =IF(($D58*(1-$E$45))<=0,0,F58/($D58*(1-$E$45))) -> 6.0437758 | G70: =IF(($D58*(1-$E$45))<=0,0,G58/($D58*(1-$E$45))) -> 7.7514218 | H70: =IF(($D58*(1-$E$45))<=0,0,H58/($D58*(1-$E$45))) -> 9.4590678 | I70: =IF(($D58*(1-$E$45))<=0,0,I58/($D58*(1-$E$45))) -> 11.166714 | J70: =IF(($D58*(1-$E$45))<=0,0,J58/($D58*(1-$E$45))) -> 12.87436
B73: Gross Returns - Preferred Equity (8% accreting)
B74: Exit Multiple (x exit-year EBITDA) | F74: 6 | G74: 6.5 | H74: 7 | I74: 7.5 | J74: 8
B75: Sale Price (Enterprise Value at exit) | F75: =F74*$E$36 -> 70528.058 | G75: =G74*$E$36 -> 76405.396 | H75: =H74*$E$36 -> 82282.734 | I75: =I74*$E$36 -> 88160.072 | J75: =J74*$E$36 -> 94037.41
B76: Entry Multiple | C76: Purchase Price | D76: Total Equity at Entry | E76: Pfd Accreted at Exit | F76: Preferred Equity Proceeds
B77: 6 | C77: =B77*$E$35 -> 47214 | D77: =C77+$E$39-$E$38 -> 15238 | E77: =D77*$E$45*(1+$E$46)^5 -> 20150.659 | F77: =MIN((F$75-$E$40-$E$41),$E77) -> 20150.659 | G77: =MIN((G$75-$E$40-$E$41),$E77) -> 20150.659 | H77: =MIN((H$75-$E$40-$E$41),$E77) -> 20150.659 | I77: =MIN((I$75-$E$40-$E$41),$E77) -> 20150.659 | J77: =MIN((J$75-$E$40-$E$41),$E77) -> 20150.659
B78: 6.5 | C78: =B78*$E$35 -> 51148.5 | D78: =C78+$E$39-$E$38 -> 19172.5 | E78: =D78*$E$45*(1+$E$46)^5 -> 25353.623 | F78: =MIN((F$75-$E$40-$E$41),$E78) -> 25353.623 | G78: =MIN((G$75-$E$40-$E$41),$E78) -> 25353.623 | H78: =MIN((H$75-$E$40-$E$41),$E78) -> 25353.623 | I78: =MIN((I$75-$E$40-$E$41),$E78) -> 25353.623 | J78: =MIN((J$75-$E$40-$E$41),$E78) -> 25353.623
B79: 7 | C79: =B79*$E$35 -> 55083 | D79: =C79+$E$39-$E$38 -> 23107 | E79: =D79*$E$45*(1+$E$46)^5 -> 30556.587 | F79: =MIN((F$75-$E$40-$E$41),$E79) -> 30556.587 | G79: =MIN((G$75-$E$40-$E$41),$E79) -> 30556.587 | H79: =MIN((H$75-$E$40-$E$41),$E79) -> 30556.587 | I79: =MIN((I$75-$E$40-$E$41),$E79) -> 30556.587 | J79: =MIN((J$75-$E$40-$E$41),$E79) -> 30556.587
B80: 7.5 | C80: =B80*$E$35 -> 59017.5 | D80: =C80+$E$39-$E$38 -> 27041.5 | E80: =D80*$E$45*(1+$E$46)^5 -> 35759.552 | F80: =MIN((F$75-$E$40-$E$41),$E80) -> 35759.552 | G80: =MIN((G$75-$E$40-$E$41),$E80) -> 35759.552 | H80: =MIN((H$75-$E$40-$E$41),$E80) -> 35759.552 | I80: =MIN((I$75-$E$40-$E$41),$E80) -> 35759.552 | J80: =MIN((J$75-$E$40-$E$41),$E80) -> 35759.552
B81: 8 | C81: =B81*$E$35 -> 62952 | D81: =C81+$E$39-$E$38 -> 30976 | E81: =D81*$E$45*(1+$E$46)^5 -> 40962.516 | F81: =MIN((F$75-$E$40-$E$41),$E81) -> 40962.516 | G81: =MIN((G$75-$E$40-$E$41),$E81) -> 40962.516 | H81: =MIN((H$75-$E$40-$E$41),$E81) -> 40962.516 | I81: =MIN((I$75-$E$40-$E$41),$E81) -> 40962.516 | J81: =MIN((J$75-$E$40-$E$41),$E81) -> 40962.516
B82: IRR | F82: Exit multiple ->
B83: =B77 -> 6 | F83: =IF(($D77*$E$45)<=0,0,(F77/($D77*$E$45))^(1/5)-1) -> 0.08 | G83: =IF(($D77*$E$45)<=0,0,(G77/($D77*$E$45))^(1/5)-1) -> 0.08 | H83: =IF(($D77*$E$45)<=0,0,(H77/($D77*$E$45))^(1/5)-1) -> 0.08 | I83: =IF(($D77*$E$45)<=0,0,(I77/($D77*$E$45))^(1/5)-1) -> 0.08 | J83: =IF(($D77*$E$45)<=0,0,(J77/($D77*$E$45))^(1/5)-1) -> 0.08
B84: =B78 -> 6.5 | F84: =IF(($D78*$E$45)<=0,0,(F78/($D78*$E$45))^(1/5)-1) -> 0.08 | G84: =IF(($D78*$E$45)<=0,0,(G78/($D78*$E$45))^(1/5)-1) -> 0.08 | H84: =IF(($D78*$E$45)<=0,0,(H78/($D78*$E$45))^(1/5)-1) -> 0.08 | I84: =IF(($D78*$E$45)<=0,0,(I78/($D78*$E$45))^(1/5)-1) -> 0.08 | J84: =IF(($D78*$E$45)<=0,0,(J78/($D78*$E$45))^(1/5)-1) -> 0.08
B85: =B79 -> 7 | F85: =IF(($D79*$E$45)<=0,0,(F79/($D79*$E$45))^(1/5)-1) -> 0.08 | G85: =IF(($D79*$E$45)<=0,0,(G79/($D79*$E$45))^(1/5)-1) -> 0.08 | H85: =IF(($D79*$E$45)<=0,0,(H79/($D79*$E$45))^(1/5)-1) -> 0.08 | I85: =IF(($D79*$E$45)<=0,0,(I79/($D79*$E$45))^(1/5)-1) -> 0.08 | J85: =IF(($D79*$E$45)<=0,0,(J79/($D79*$E$45))^(1/5)-1) -> 0.08
B86: =B80 -> 7.5 | F86: =IF(($D80*$E$45)<=0,0,(F80/($D80*$E$45))^(1/5)-1) -> 0.08 | G86: =IF(($D80*$E$45)<=0,0,(G80/($D80*$E$45))^(1/5)-1) -> 0.08 | H86: =IF(($D80*$E$45)<=0,0,(H80/($D80*$E$45))^(1/5)-1) -> 0.08 | I86: =IF(($D80*$E$45)<=0,0,(I80/($D80*$E$45))^(1/5)-1) -> 0.08 | J86: =IF(($D80*$E$45)<=0,0,(J80/($D80*$E$45))^(1/5)-1) -> 0.08
B87: =B81 -> 8 | F87: =IF(($D81*$E$45)<=0,0,(F81/($D81*$E$45))^(1/5)-1) -> 0.08 | G87: =IF(($D81*$E$45)<=0,0,(G81/($D81*$E$45))^(1/5)-1) -> 0.08 | H87: =IF(($D81*$E$45)<=0,0,(H81/($D81*$E$45))^(1/5)-1) -> 0.08 | I87: =IF(($D81*$E$45)<=0,0,(I81/($D81*$E$45))^(1/5)-1) -> 0.08 | J87: =IF(($D81*$E$45)<=0,0,(J81/($D81*$E$45))^(1/5)-1) -> 0.08
B88: MoIC
B89: =B77 -> 6 | F89: =IF(($D77*$E$45)<=0,0,F77/($D77*$E$45)) -> 1.4693281 | G89: =IF(($D77*$E$45)<=0,0,G77/($D77*$E$45)) -> 1.4693281 | H89: =IF(($D77*$E$45)<=0,0,H77/($D77*$E$45)) -> 1.4693281 | I89: =IF(($D77*$E$45)<=0,0,I77/($D77*$E$45)) -> 1.4693281 | J89: =IF(($D77*$E$45)<=0,0,J77/($D77*$E$45)) -> 1.4693281
B90: =B78 -> 6.5 | F90: =IF(($D78*$E$45)<=0,0,F78/($D78*$E$45)) -> 1.4693281 | G90: =IF(($D78*$E$45)<=0,0,G78/($D78*$E$45)) -> 1.4693281 | H90: =IF(($D78*$E$45)<=0,0,H78/($D78*$E$45)) -> 1.4693281 | I90: =IF(($D78*$E$45)<=0,0,I78/($D78*$E$45)) -> 1.4693281 | J90: =IF(($D78*$E$45)<=0,0,J78/($D78*$E$45)) -> 1.4693281
B91: =B79 -> 7 | F91: =IF(($D79*$E$45)<=0,0,F79/($D79*$E$45)) -> 1.4693281 | G91: =IF(($D79*$E$45)<=0,0,G79/($D79*$E$45)) -> 1.4693281 | H91: =IF(($D79*$E$45)<=0,0,H79/($D79*$E$45)) -> 1.4693281 | I91: =IF(($D79*$E$45)<=0,0,I79/($D79*$E$45)) -> 1.4693281 | J91: =IF(($D79*$E$45)<=0,0,J79/($D79*$E$45)) -> 1.4693281
B92: =B80 -> 7.5 | F92: =IF(($D80*$E$45)<=0,0,F80/($D80*$E$45)) -> 1.4693281 | G92: =IF(($D80*$E$45)<=0,0,G80/($D80*$E$45)) -> 1.4693281 | H92: =IF(($D80*$E$45)<=0,0,H80/($D80*$E$45)) -> 1.4693281 | I92: =IF(($D80*$E$45)<=0,0,I80/($D80*$E$45)) -> 1.4693281 | J92: =IF(($D80*$E$45)<=0,0,J80/($D80*$E$45)) -> 1.4693281
B93: =B81 -> 8 | F93: =IF(($D81*$E$45)<=0,0,F81/($D81*$E$45)) -> 1.4693281 | G93: =IF(($D81*$E$45)<=0,0,G81/($D81*$E$45)) -> 1.4693281 | H93: =IF(($D81*$E$45)<=0,0,H81/($D81*$E$45)) -> 1.4693281 | I93: =IF(($D81*$E$45)<=0,0,I81/($D81*$E$45)) -> 1.4693281 | J93: =IF(($D81*$E$45)<=0,0,J81/($D81*$E$45)) -> 1.4693281
B96: Illustrative Gross Returns for Strip Investment of Common and Preferred
B97: Strip proportions: | C97: Common | D97: =1-$E$45 -> 0.1 | E97: Preferred | F97: =$E$45 -> 0.9
B99: Strip IRR & MoIC (weighted Common + Preferred)
B100: Exit Multiple (x exit-year EBITDA) | F100: 6 | G100: 6.5 | H100: 7 | I100: 7.5 | J100: 8
B101: Sale Price (Enterprise Value at exit) | F101: =F100*$E$36 -> 70528.058 | G101: =G100*$E$36 -> 76405.396 | H101: =H100*$E$36 -> 82282.734 | I101: =I100*$E$36 -> 88160.072 | J101: =J100*$E$36 -> 94037.41
B102: Entry Multiple | C102: Purchase Price | D102: Total Equity at Entry | E102: Pfd Accreted at Exit | F102: Strip Proceeds (Common + Preferred)
B103: 6 | C103: =B103*$E$35 -> 47214 | D103: =C103+$E$39-$E$38 -> 15238 | E103: =D103*$E$45*(1+$E$46)^5 -> 20150.659 | F103: =MIN((F$101-$E$40-$E$41),$E103)+(MIN((F$101-$E$40-$E$41)-MIN((F$101-$E$40-$E$41),$E103),($D103*(1-$E$45)))+(1-$E$47)*MAX(0,(F$101-$E$40-$E$41)-MIN((F$101-$E$40-$E$41),$E103)-($D103*(1-$E$45)))) -> 57445.15 | G103: =MIN((G$101-$E$40-$E$41),$E103)+(MIN((G$101-$E$40-$E$41)-MIN((G$101-$E$40-$E$41),$E103),($D103*(1-$E$45)))+(1-$E$47)*MAX(0,(G$101-$E$40-$E$41)-MIN((G$101-$E$40-$E$41),$E103)-($D103*(1-$E$45)))) -> 62734.754 | H103: =MIN((H$101-$E$40-$E$41),$E103)+(MIN((H$101-$E$40-$E$41)-MIN((H$101-$E$40-$E$41),$E103),($D103*(1-$E$45)))+(1-$E$47)*MAX(0,(H$101-$E$40-$E$41)-MIN((H$101-$E$40-$E$41),$E103)-($D103*(1-$E$45)))) -> 68024.359 | I103: =MIN((I$101-$E$40-$E$41),$E103)+(MIN((I$101-$E$40-$E$41)-MIN((I$101-$E$40-$E$41),$E103),($D103*(1-$E$45)))+(1-$E$47)*MAX(0,(I$101-$E$40-$E$41)-MIN((I$101-$E$40-$E$41),$E103)-($D103*(1-$E$45)))) -> 73313.963 | J103: =MIN((J$101-$E$40-$E$41),$E103)+(MIN((J$101-$E$40-$E$41)-MIN((J$101-$E$40-$E$41),$E103),($D103*(1-$E$45)))+(1-$E$47)*MAX(0,(J$101-$E$40-$E$41)-MIN((J$101-$E$40-$E$41),$E103)-($D103*(1-$E$45)))) -> 78603.567
B104: 6.5 | C104: =B104*$E$35 -> 51148.5 | D104: =C104+$E$39-$E$38 -> 19172.5 | E104: =D104*$E$45*(1+$E$46)^5 -> 25353.623 | F104: =MIN((F$101-$E$40-$E$41),$E104)+(MIN((F$101-$E$40-$E$41)-MIN((F$101-$E$40-$E$41),$E104),($D104*(1-$E$45)))+(1-$E$47)*MAX(0,(F$101-$E$40-$E$41)-MIN((F$101-$E$40-$E$41),$E104)-($D104*(1-$E$45)))) -> 58004.791 | G104: =MIN((G$101-$E$40-$E$41),$E104)+(MIN((G$101-$E$40-$E$41)-MIN((G$101-$E$40-$E$41),$E104),($D104*(1-$E$45)))+(1-$E$47)*MAX(0,(G$101-$E$40-$E$41)-MIN((G$101-$E$40-$E$41),$E104)-($D104*(1-$E$45)))) -> 63294.396 | H104: =MIN((H$101-$E$40-$E$41),$E104)+(MIN((H$101-$E$40-$E$41)-MIN((H$101-$E$40-$E$41),$E104),($D104*(1-$E$45)))+(1-$E$47)*MAX(0,(H$101-$E$40-$E$41)-MIN((H$101-$E$40-$E$41),$E104)-($D104*(1-$E$45)))) -> 68584 | I104: =MIN((I$101-$E$40-$E$41),$E104)+(MIN((I$101-$E$40-$E$41)-MIN((I$101-$E$40-$E$41),$E104),($D104*(1-$E$45)))+(1-$E$47)*MAX(0,(I$101-$E$40-$E$41)-MIN((I$101-$E$40-$E$41),$E104)-($D104*(1-$E$45)))) -> 73873.604 | J104: =MIN((J$101-$E$40-$E$41),$E104)+(MIN((J$101-$E$40-$E$41)-MIN((J$101-$E$40-$E$41),$E104),($D104*(1-$E$45)))+(1-$E$47)*MAX(0,(J$101-$E$40-$E$41)-MIN((J$101-$E$40-$E$41),$E104)-($D104*(1-$E$45)))) -> 79163.209
B105: 7 | C105: =B105*$E$35 -> 55083 | D105: =C105+$E$39-$E$38 -> 23107 | E105: =D105*$E$45*(1+$E$46)^5 -> 30556.587 | F105: =MIN((F$101-$E$40-$E$41),$E105)+(MIN((F$101-$E$40-$E$41)-MIN((F$101-$E$40-$E$41),$E105),($D105*(1-$E$45)))+(1-$E$47)*MAX(0,(F$101-$E$40-$E$41)-MIN((F$101-$E$40-$E$41),$E105)-($D105*(1-$E$45)))) -> 58564.433 | G105: =MIN((G$101-$E$40-$E$41),$E105)+(MIN((G$101-$E$40-$E$41)-MIN((G$101-$E$40-$E$41),$E105),($D105*(1-$E$45)))+(1-$E$47)*MAX(0,(G$101-$E$40-$E$41)-MIN((G$101-$E$40-$E$41),$E105)-($D105*(1-$E$45)))) -> 63854.037 | H105: =MIN((H$101-$E$40-$E$41),$E105)+(MIN((H$101-$E$40-$E$41)-MIN((H$101-$E$40-$E$41),$E105),($D105*(1-$E$45)))+(1-$E$47)*MAX(0,(H$101-$E$40-$E$41)-MIN((H$101-$E$40-$E$41),$E105)-($D105*(1-$E$45)))) -> 69143.641 | I105: =MIN((I$101-$E$40-$E$41),$E105)+(MIN((I$101-$E$40-$E$41)-MIN((I$101-$E$40-$E$41),$E105),($D105*(1-$E$45)))+(1-$E$47)*MAX(0,(I$101-$E$40-$E$41)-MIN((I$101-$E$40-$E$41),$E105)-($D105*(1-$E$45)))) -> 74433.246 | J105: =MIN((J$101-$E$40-$E$41),$E105)+(MIN((J$101-$E$40-$E$41)-MIN((J$101-$E$40-$E$41),$E105),($D105*(1-$E$45)))+(1-$E$47)*MAX(0,(J$101-$E$40-$E$41)-MIN((J$101-$E$40-$E$41),$E105)-($D105*(1-$E$45)))) -> 79722.85
B106: 7.5 | C106: =B106*$E$35 -> 59017.5 | D106: =C106+$E$39-$E$38 -> 27041.5 | E106: =D106*$E$45*(1+$E$46)^5 -> 35759.552 | F106: =MIN((F$101-$E$40-$E$41),$E106)+(MIN((F$101-$E$40-$E$41)-MIN((F$101-$E$40-$E$41),$E106),($D106*(1-$E$45)))+(1-$E$47)*MAX(0,(F$101-$E$40-$E$41)-MIN((F$101-$E$40-$E$41),$E106)-($D106*(1-$E$45)))) -> 59124.074 | G106: =MIN((G$101-$E$40-$E$41),$E106)+(MIN((G$101-$E$40-$E$41)-MIN((G$101-$E$40-$E$41),$E106),($D106*(1-$E$45)))+(1-$E$47)*MAX(0,(G$101-$E$40-$E$41)-MIN((G$101-$E$40-$E$41),$E106)-($D106*(1-$E$45)))) -> 64413.679 | H106: =MIN((H$101-$E$40-$E$41),$E106)+(MIN((H$101-$E$40-$E$41)-MIN((H$101-$E$40-$E$41),$E106),($D106*(1-$E$45)))+(1-$E$47)*MAX(0,(H$101-$E$40-$E$41)-MIN((H$101-$E$40-$E$41),$E106)-($D106*(1-$E$45)))) -> 69703.283 | I106: =MIN((I$101-$E$40-$E$41),$E106)+(MIN((I$101-$E$40-$E$41)-MIN((I$101-$E$40-$E$41),$E106),($D106*(1-$E$45)))+(1-$E$47)*MAX(0,(I$101-$E$40-$E$41)-MIN((I$101-$E$40-$E$41),$E106)-($D106*(1-$E$45)))) -> 74992.887 | J106: =MIN((J$101-$E$40-$E$41),$E106)+(MIN((J$101-$E$40-$E$41)-MIN((J$101-$E$40-$E$41),$E106),($D106*(1-$E$45)))+(1-$E$47)*MAX(0,(J$101-$E$40-$E$41)-MIN((J$101-$E$40-$E$41),$E106)-($D106*(1-$E$45)))) -> 80282.491
B107: 8 | C107: =B107*$E$35 -> 62952 | D107: =C107+$E$39-$E$38 -> 30976 | E107: =D107*$E$45*(1+$E$46)^5 -> 40962.516 | F107: =MIN((F$101-$E$40-$E$41),$E107)+(MIN((F$101-$E$40-$E$41)-MIN((F$101-$E$40-$E$41),$E107),($D107*(1-$E$45)))+(1-$E$47)*MAX(0,(F$101-$E$40-$E$41)-MIN((F$101-$E$40-$E$41),$E107)-($D107*(1-$E$45)))) -> 59683.716 | G107: =MIN((G$101-$E$40-$E$41),$E107)+(MIN((G$101-$E$40-$E$41)-MIN((G$101-$E$40-$E$41),$E107),($D107*(1-$E$45)))+(1-$E$47)*MAX(0,(G$101-$E$40-$E$41)-MIN((G$101-$E$40-$E$41),$E107)-($D107*(1-$E$45)))) -> 64973.32 | H107: =MIN((H$101-$E$40-$E$41),$E107)+(MIN((H$101-$E$40-$E$41)-MIN((H$101-$E$40-$E$41),$E107),($D107*(1-$E$45)))+(1-$E$47)*MAX(0,(H$101-$E$40-$E$41)-MIN((H$101-$E$40-$E$41),$E107)-($D107*(1-$E$45)))) -> 70262.924 | I107: =MIN((I$101-$E$40-$E$41),$E107)+(MIN((I$101-$E$40-$E$41)-MIN((I$101-$E$40-$E$41),$E107),($D107*(1-$E$45)))+(1-$E$47)*MAX(0,(I$101-$E$40-$E$41)-MIN((I$101-$E$40-$E$41),$E107)-($D107*(1-$E$45)))) -> 75552.529 | J107: =MIN((J$101-$E$40-$E$41),$E107)+(MIN((J$101-$E$40-$E$41)-MIN((J$101-$E$40-$E$41),$E107),($D107*(1-$E$45)))+(1-$E$47)*MAX(0,(J$101-$E$40-$E$41)-MIN((J$101-$E$40-$E$41),$E107)-($D107*(1-$E$45)))) -> 80842.133
B108: IRR | F108: Exit multiple ->
B109: =B103 -> 6 | F109: =IF($D103<=0,0,(F103/$D103)^(1/5)-1) -> 0.30396243 | G109: =IF($D103<=0,0,(G103/$D103)^(1/5)-1) -> 0.32713788 | H109: =IF($D103<=0,0,(H103/$D103)^(1/5)-1) -> 0.34879919 | I109: =IF($D103<=0,0,(I103/$D103)^(1/5)-1) -> 0.36915225 | J109: =IF($D103<=0,0,(J103/$D103)^(1/5)-1) -> 0.38836244
B110: =B104 -> 6.5 | F110: =IF($D104<=0,0,(F104/$D104)^(1/5)-1) -> 0.2478346 | G110: =IF($D104<=0,0,(G104/$D104)^(1/5)-1) -> 0.26980579 | H110: =IF($D104<=0,0,(H104/$D104)^(1/5)-1) -> 0.29035382 | I110: =IF($D104<=0,0,(I104/$D104)^(1/5)-1) -> 0.30967069 | J110: =IF($D104<=0,0,(J104/$D104)^(1/5)-1) -> 0.32791088
B111: =B105 -> 7 | F111: =IF($D105<=0,0,(F105/$D105)^(1/5)-1) -> 0.20442032 | G111: =IF($D105<=0,0,(G105/$D105)^(1/5)-1) -> 0.22543127 | H111: =IF($D105<=0,0,(H105/$D105)^(1/5)-1) -> 0.24509284 | I111: =IF($D105<=0,0,(I105/$D105)^(1/5)-1) -> 0.26358563 | J111: =IF($D105<=0,0,(J105/$D105)^(1/5)-1) -> 0.28105522
B112: =B106 -> 7.5 | F112: =IF($D106<=0,0,(F106/$D106)^(1/5)-1) -> 0.16935591 | G112: =IF($D106<=0,0,(G106/$D106)^(1/5)-1) -> 0.18956853 | H112: =IF($D106<=0,0,(H106/$D106)^(1/5)-1) -> 0.20849398 | I112: =IF($D106<=0,0,(I106/$D106)^(1/5)-1) -> 0.22630319 | J112: =IF($D106<=0,0,(J106/$D106)^(1/5)-1) -> 0.24313419
B113: =B107 -> 8 | F113: =IF($D107<=0,0,(F107/$D107)^(1/5)-1) -> 0.14016079 | G113: =IF($D107<=0,0,(G107/$D107)^(1/5)-1) -> 0.15969009 | H113: =IF($D107<=0,0,(H107/$D107)^(1/5)-1) -> 0.17798613 | I113: =IF($D107<=0,0,(I107/$D107)^(1/5)-1) -> 0.19521142 | J113: =IF($D107<=0,0,(J107/$D107)^(1/5)-1) -> 0.2114974
...

Sheet Returns  Exhibit-7.5x
A1: =Assump_CapStructure!$F$7 -> Project Kestrel
A2: ="Prepared by: "&Assump_CapStructure!$F$8 -> Prepared by: Halvern
A3: =Assump_CapStructure!$F$11 -> ($ in 000s)
B5: ="Deal Overview and Returns Summary @ "&TEXT($E$7,"0.0x")&" Entry Multiple" -> Deal Overview and Returns Summary @ 7.5x Entry Multiple
B7: Entry Multiple (x FY2025A Adj. EBITDA) | E7: 7.5
B9: Returns Inputs (linked to Model / Assump_CapStructure)
B10: FY2025A Adj. EBITDA | E10: =Model!$E$85 -> 7869
B11: FY2030E EBITDA (exit year 5) | E11: =Model!$J$85 -> 11754.676
B12: FY2028E EBITDA (exit year 3) | E12: =Model!$H$85 -> 10300.977
B13: Debt raised at close (base case, fixed) | E13: =Model!$K$16 -> 35476
B14: Transaction costs + cash to B/S + cash acquired | E14: =Model!$D$14+Model!$D$13+Assump_CapStructure!$D$79 -> 3500
B15: Net debt at FY2030E (excl. seller note; from Model) | E15: =Model!$J$62-Model!$J$61-Model!$J$51 -> 3755.4841
B16: Seller note accreted balance at FY2030E | E16: =Model!$J$61 -> 5352.9023
B17: Net debt at FY2028E (excl. seller note; from Model) | E17: =Model!$H$62-Model!$H$61-Model!$H$51 -> 16536.503
B18: Seller note accreted balance at FY2028E | E18: =Model!$H$61 -> 4764.064
B19: Cumulative goodwill step-up tax savings through FY2028E | E19: =Model!$H$328 -> 2074.696
B20: Preferred % of equity account | E20: =Assump_CapStructure!$F$31 -> 0.9
B21: Preferred accretion rate | E21: =Assump_CapStructure!$F$28 -> 0.08
B22: MEIP % of common profits | E22: =Assump_CapStructure!$F$29 -> 0.1
B23: Sponsor carried interest | E23: =Assump_CapStructure!$F$30 -> 0.2
B25: Purchase Price (Transaction Value) | E25: =$E$7*$E$10 -> 59017.5
B26: Total Equity at Entry (Sponsor + Rollover) | E26: =E25+$E$14-$E$13 -> 27041.5
B27: Preferred Accreted at Exit (year 5) | E27: =E26*$E$20*(1+$E$21)^5 -> 35759.552
B28: Common Equity Invested | E28: =E26*(1-$E$20) -> 2704.15
B30: Five-Year Gross Return Profile (Sponsor + Rollover strip, net of MEIP) (1)
C31: Rev. CAGR | D31: Exit multiple ->
B32: Exit-year EBITDA by case | D32: 6 | E32: 6.5 | F32: 7 | G32: 7.5 | H32: 8
B33: 15% Rev CAGR Case | C33: 0.15 | D33: Exit EBITDA: | E33: =$E$10*(1+C33)^5 -> 15827.37
B34: IRR | D34: =IF(D35<=0,-1,D35^(1/5)-1) -> 0.24570673 | E34: =IF(E35<=0,-1,E35^(1/5)-1) -> 0.26685204 | F34: =IF(F35<=0,-1,F35^(1/5)-1) -> 0.28667313 | G34: =IF(G35<=0,-1,G35^(1/5)-1) -> 0.30534314 | H34: =IF(H35<=0,-1,H35^(1/5)-1) -> 0.32300236
B35: MoIC | D35: =IF($E$26<=0,0,((D$32*$E33-$E$15-$E$16)-$E$22*MAX(0,(D$32*$E33-$E$15-$E$16)-MIN((D$32*$E33-$E$15-$E$16),$E$27)-$E$28))/$E$26) -> 2.9997086 | E35: =IF($E$26<=0,0,((E$32*$E33-$E$15-$E$16)-$E$22*MAX(0,(E$32*$E33-$E$15-$E$16)-MIN((E$32*$E33-$E$15-$E$16),$E$27)-$E$28))/$E$26) -> 3.2630932 | F35: =IF($E$26<=0,0,((F$32*$E33-$E$15-$E$16)-$E$22*MAX(0,(F$32*$E33-$E$15-$E$16)-MIN((F$32*$E33-$E$15-$E$16),$E$27)-$E$28))/$E$26) -> 3.5264779 | G35: =IF($E$26<=0,0,((G$32*$E33-$E$15-$E$16)-$E$22*MAX(0,(G$32*$E33-$E$15-$E$16)-MIN((G$32*$E33-$E$15-$E$16),$E$27)-$E$28))/$E$26) -> 3.7898625 | H35: =IF($E$26<=0,0,((H$32*$E33-$E$15-$E$16)-$E$22*MAX(0,(H$32*$E33-$E$15-$E$16)-MIN((H$32*$E33-$E$15-$E$16),$E$27)-$E$28))/$E$26) -> 4.0532472
B37: 10% Rev CAGR Case | C37: 0.1 | D37: Exit EBITDA: | E37: =$E$10*(1+C37)^5 -> 12673.103
B38: IRR | D38: =IF(D39<=0,-1,D39^(1/5)-1) -> 0.18834679 | E38: =IF(E39<=0,-1,E39^(1/5)-1) -> 0.20878232 | F38: =IF(F39<=0,-1,F39^(1/5)-1) -> 0.22792264 | G38: =IF(G39<=0,-1,G39^(1/5)-1) -> 0.245939 | H38: =IF(H39<=0,-1,H39^(1/5)-1) -> 0.2629698
B39: MoIC | D39: =IF($E$26<=0,0,((D$32*$E37-$E$15-$E$16)-$E$22*MAX(0,(D$32*$E37-$E$15-$E$16)-MIN((D$32*$E37-$E$15-$E$16),$E$27)-$E$28))/$E$26) -> 2.3698234 | E39: =IF($E$26<=0,0,((E$32*$E37-$E$15-$E$16)-$E$22*MAX(0,(E$32*$E37-$E$15-$E$16)-MIN((E$32*$E37-$E$15-$E$16),$E$27)-$E$28))/$E$26) -> 2.5807176 | F39: =IF($E$26<=0,0,((F$32*$E37-$E$15-$E$16)-$E$22*MAX(0,(F$32*$E37-$E$15-$E$16)-MIN((F$32*$E37-$E$15-$E$16),$E$27)-$E$28))/$E$26) -> 2.7916119 | G39: =IF($E$26<=0,0,((G$32*$E37-$E$15-$E$16)-$E$22*MAX(0,(G$32*$E37-$E$15-$E$16)-MIN((G$32*$E37-$E$15-$E$16),$E$27)-$E$28))/$E$26) -> 3.0025061 | H39: =IF($E$26<=0,0,((H$32*$E37-$E$15-$E$16)-$E$22*MAX(0,(H$32*$E37-$E$15-$E$16)-MIN((H$32*$E37-$E$15-$E$16),$E$27)-$E$28))/$E$26) -> 3.2134003
B41: 5% Rev CAGR Case | C41: 0.05 | D41: Exit EBITDA: | E41: =$E$10*(1+C41)^5 -> 10043.06
B42: IRR | D42: =IF(D43<=0,-1,D43^(1/5)-1) -> 0.13026811 | E42: =IF(E43<=0,-1,E43^(1/5)-1) -> 0.15004485 | F42: =IF(F43<=0,-1,F43^(1/5)-1) -> 0.16854795 | G42: =IF(G43<=0,-1,G43^(1/5)-1) -> 0.18594831 | H42: =IF(H43<=0,-1,H43^(1/5)-1) -> 0.20238362
B43: MoIC | D43: =IF($E$26<=0,0,((D$32*$E41-$E$15-$E$16)-$E$22*MAX(0,(D$32*$E41-$E$15-$E$16)-MIN((D$32*$E41-$E$15-$E$16),$E$27)-$E$28))/$E$26) -> 1.8446219 | E43: =IF($E$26<=0,0,((E$32*$E41-$E$15-$E$16)-$E$22*MAX(0,(E$32*$E41-$E$15-$E$16)-MIN((E$32*$E41-$E$15-$E$16),$E$27)-$E$28))/$E$26) -> 2.0117494 | F43: =IF($E$26<=0,0,((F$32*$E41-$E$15-$E$16)-$E$22*MAX(0,(F$32*$E41-$E$15-$E$16)-MIN((F$32*$E41-$E$15-$E$16),$E$27)-$E$28))/$E$26) -> 2.1788768 | G43: =IF($E$26<=0,0,((G$32*$E41-$E$15-$E$16)-$E$22*MAX(0,(G$32*$E41-$E$15-$E$16)-MIN((G$32*$E41-$E$15-$E$16),$E$27)-$E$28))/$E$26) -> 2.3460043 | H43: =IF($E$26<=0,0,((H$32*$E41-$E$15-$E$16)-$E$22*MAX(0,(H$32*$E41-$E$15-$E$16)-MIN((H$32*$E41-$E$15-$E$16),$E$27)-$E$28))/$E$26) -> 2.5131317
B45: Flat Rev CAGR Case | C45: 0 | D45: Exit EBITDA: | E45: =$E$10*(1+C45)^5 -> 7869
B46: IRR | D46: =IF(D47<=0,-1,D47^(1/5)-1) -> 0.07100534 | E46: =IF(E47<=0,-1,E47^(1/5)-1) -> 0.090396726 | F46: =IF(F47<=0,-1,F47^(1/5)-1) -> 0.10832396 | G46: =IF(G47<=0,-1,G47^(1/5)-1) -> 0.12516115 | H46: =IF(H47<=0,-1,H47^(1/5)-1) -> 0.14104696
B47: MoIC | D47: =IF($E$26<=0,0,((D$32*$E45-$E$15-$E$16)-$E$22*MAX(0,(D$32*$E45-$E$15-$E$16)-MIN((D$32*$E45-$E$15-$E$16),$E$27)-$E$28))/$E$26) -> 1.4091531 | E47: =IF($E$26<=0,0,((E$32*$E45-$E$15-$E$16)-$E$22*MAX(0,(E$32*$E45-$E$15-$E$16)-MIN((E$32*$E45-$E$15-$E$16),$E$27)-$E$28))/$E$26) -> 1.541426 | F47: =IF($E$26<=0,0,((F$32*$E45-$E$15-$E$16)-$E$22*MAX(0,(F$32*$E45-$E$15-$E$16)-MIN((F$32*$E45-$E$15-$E$16),$E$27)-$E$28))/$E$26) -> 1.6723748 | G47: =IF($E$26<=0,0,((G$32*$E45-$E$15-$E$16)-$E$22*MAX(0,(G$32*$E45-$E$15-$E$16)-MIN((G$32*$E45-$E$15-$E$16),$E$27)-$E$28))/$E$26) -> 1.8033235 | H47: =IF($E$26<=0,0,((H$32*$E45-$E$15-$E$16)-$E$22*MAX(0,(H$32*$E45-$E$15-$E$16)-MIN((H$32*$E45-$E$15-$E$16),$E$27)-$E$28))/$E$26) -> 1.9342722
B49: Management Case | C49: =($E$11/$E$10)^(1/5)-1 -> 0.083573126 | D49: Exit EBITDA: | E49: =$E$11 -> 11754.676
B50: IRR | D50: =IF(D51<=0,-1,D51^(1/5)-1) -> 0.16935591 | E50: =IF(E51<=0,-1,E51^(1/5)-1) -> 0.18956853 | F50: =IF(F51<=0,-1,F51^(1/5)-1) -> 0.20849398 | G50: =IF(G51<=0,-1,G51^(1/5)-1) -> 0.22630319 | H50: =IF(H51<=0,-1,H51^(1/5)-1) -> 0.24313419
B51: MoIC | D51: =IF($E$26<=0,0,((D$32*$E49-$E$15-$E$16)-$E$22*MAX(0,(D$32*$E49-$E$15-$E$16)-MIN((D$32*$E49-$E$15-$E$16),$E$27)-$E$28))/$E$26) -> 2.1864199 | E51: =IF($E$26<=0,0,((E$32*$E49-$E$15-$E$16)-$E$22*MAX(0,(E$32*$E49-$E$15-$E$16)-MIN((E$32*$E49-$E$15-$E$16),$E$27)-$E$28))/$E$26) -> 2.3820305 | F51: =IF($E$26<=0,0,((F$32*$E49-$E$15-$E$16)-$E$22*MAX(0,(F$32*$E49-$E$15-$E$16)-MIN((F$32*$E49-$E$15-$E$16),$E$27)-$E$28))/$E$26) -> 2.5776411 | G51: =IF($E$26<=0,0,((G$32*$E49-$E$15-$E$16)-$E$22*MAX(0,(G$32*$E49-$E$15-$E$16)-MIN((G$32*$E49-$E$15-$E$16),$E$27)-$E$28))/$E$26) -> 2.7732517 | H51: =IF($E$26<=0,0,((H$32*$E49-$E$15-$E$16)-$E$22*MAX(0,(H$32*$E49-$E$15-$E$16)-MIN((H$32*$E49-$E$15-$E$16),$E$27)-$E$28))/$E$26) -> 2.9688624
B53: ="(1) Returns net of transaction expenses of $"&TEXT(Model!$D$14,"#,##0")&"k and net of the 10% MEIP; margin held at the FY2025A adj. EBITDA margin for the CAGR cases." -> (1) Returns net of transaction expenses of $2,400k and net of the 10% MEIP; margin held at the FY2025A adj. EBITDA margin for the CAGR cases.
B54: (2) Net debt at exit approximated as base-case (management case) net debt from the Model tab for every case.

Sheet Returns  Exhibit-6.5x
A1: =Assump_CapStructure!$F$7 -> Project Kestrel
A2: ="Prepared by: "&Assump_CapStructure!$F$8 -> Prepared by: Halvern
A3: =Assump_CapStructure!$F$11 -> ($ in 000s)
B5: ="Deal Overview and Returns Summary @ "&TEXT($E$7,"0.0x")&" Entry Multiple" -> Deal Overview and Returns Summary @ 6.5x Entry Multiple
B7: Entry Multiple (x FY2025A Adj. EBITDA) | E7: 6.5
B9: Returns Inputs (linked to Model / Assump_CapStructure)
B10: FY2025A Adj. EBITDA | E10: =Model!$E$85 -> 7869
B11: FY2030E EBITDA (exit year 5) | E11: =Model!$J$85 -> 11754.676
B12: FY2028E EBITDA (exit year 3) | E12: =Model!$H$85 -> 10300.977
B13: Debt raised at close (base case, fixed) | E13: =Model!$K$16 -> 35476
B14: Transaction costs + cash to B/S + cash acquired | E14: =Model!$D$14+Model!$D$13+Assump_CapStructure!$D$79 -> 3500
B15: Net debt at FY2030E (excl. seller note; from Model) | E15: =Model!$J$62-Model!$J$61-Model!$J$51 -> 3755.4841
B16: Seller note accreted balance at FY2030E | E16: =Model!$J$61 -> 5352.9023
B17: Net debt at FY2028E (excl. seller note; from Model) | E17: =Model!$H$62-Model!$H$61-Model!$H$51 -> 16536.503
B18: Seller note accreted balance at FY2028E | E18: =Model!$H$61 -> 4764.064
B19: Cumulative goodwill step-up tax savings through FY2028E | E19: =Model!$H$328 -> 2074.696
B20: Preferred % of equity account | E20: =Assump_CapStructure!$F$31 -> 0.9
B21: Preferred accretion rate | E21: =Assump_CapStructure!$F$28 -> 0.08
B22: MEIP % of common profits | E22: =Assump_CapStructure!$F$29 -> 0.1
B23: Sponsor carried interest | E23: =Assump_CapStructure!$F$30 -> 0.2
B25: Purchase Price (Transaction Value) | E25: =$E$7*$E$10 -> 51148.5
B26: Total Equity at Entry (Sponsor + Rollover) | E26: =E25+$E$14-$E$13 -> 19172.5
B27: Preferred Accreted at Exit (year 5) | E27: =E26*$E$20*(1+$E$21)^5 -> 25353.623
B28: Common Equity Invested | E28: =E26*(1-$E$20) -> 1917.25
B30: Five-Year Gross Return Profile (Sponsor + Rollover strip, net of MEIP) (1)
C31: Rev. CAGR | D31: Exit multiple ->
B32: Exit-year EBITDA by case | D32: 6 | E32: 6.5 | F32: 7 | G32: 7.5 | H32: 8
B33: 15% Rev CAGR Case | C33: 0.15 | D33: Exit EBITDA: | E33: =$E$10*(1+C33)^5 -> 15827.37
B34: IRR | D34: =IF(D35<=0,-1,D35^(1/5)-1) -> 0.33069755 | E34: =IF(E35<=0,-1,E35^(1/5)-1) -> 0.35359106 | F34: =IF(F35<=0,-1,F35^(1/5)-1) -> 0.375033 | G34: =IF(G35<=0,-1,G35^(1/5)-1) -> 0.39521534 | H34: =IF(H35<=0,-1,H35^(1/5)-1) -> 0.41429326
B35: MoIC | D35: =IF($E$26<=0,0,((D$32*$E33-$E$15-$E$16)-$E$22*MAX(0,(D$32*$E33-$E$15-$E$16)-MIN((D$32*$E33-$E$15-$E$16),$E$27)-$E$28))/$E$26) -> 4.1725042 | E35: =IF($E$26<=0,0,((E$32*$E33-$E$15-$E$16)-$E$22*MAX(0,(E$32*$E33-$E$15-$E$16)-MIN((E$32*$E33-$E$15-$E$16),$E$27)-$E$28))/$E$26) -> 4.5439902 | F35: =IF($E$26<=0,0,((F$32*$E33-$E$15-$E$16)-$E$22*MAX(0,(F$32*$E33-$E$15-$E$16)-MIN((F$32*$E33-$E$15-$E$16),$E$27)-$E$28))/$E$26) -> 4.9154763 | G35: =IF($E$26<=0,0,((G$32*$E33-$E$15-$E$16)-$E$22*MAX(0,(G$32*$E33-$E$15-$E$16)-MIN((G$32*$E33-$E$15-$E$16),$E$27)-$E$28))/$E$26) -> 5.2869623 | H35: =IF($E$26<=0,0,((H$32*$E33-$E$15-$E$16)-$E$22*MAX(0,(H$32*$E33-$E$15-$E$16)-MIN((H$32*$E33-$E$15-$E$16),$E$27)-$E$28))/$E$26) -> 5.6584484
B37: 10% Rev CAGR Case | C37: 0.1 | D37: Exit EBITDA: | E37: =$E$10*(1+C37)^5 -> 12673.103
B38: IRR | D38: =IF(D39<=0,-1,D39^(1/5)-1) -> 0.26847853 | E38: =IF(E39<=0,-1,E39^(1/5)-1) -> 0.29066671 | F38: =IF(F39<=0,-1,F39^(1/5)-1) -> 0.31142637 | G38: =IF(G39<=0,-1,G39^(1/5)-1) -> 0.33094913 | H38: =IF(H39<=0,-1,H39^(1/5)-1) -> 0.34938939
B39: MoIC | D39: =IF($E$26<=0,0,((D$32*$E37-$E$15-$E$16)-$E$22*MAX(0,(D$32*$E37-$E$15-$E$16)-MIN((D$32*$E37-$E$15-$E$16),$E$27)-$E$28))/$E$26) -> 3.2840942 | E39: =IF($E$26<=0,0,((E$32*$E37-$E$15-$E$16)-$E$22*MAX(0,(E$32*$E37-$E$15-$E$16)-MIN((E$32*$E37-$E$15-$E$16),$E$27)-$E$28))/$E$26) -> 3.5815461 | F39: =IF($E$26<=0,0,((F$32*$E37-$E$15-$E$16)-$E$22*MAX(0,(F$32*$E37-$E$15-$E$16)-MIN((F$32*$E37-$E$15-$E$16),$E$27)-$E$28))/$E$26) -> 3.878998 | G39: =IF($E$26<=0,0,((G$32*$E37-$E$15-$E$16)-$E$22*MAX(0,(G$32*$E37-$E$15-$E$16)-MIN((G$32*$E37-$E$15-$E$16),$E$27)-$E$28))/$E$26) -> 4.1764499 | H39: =IF($E$26<=0,0,((H$32*$E37-$E$15-$E$16)-$E$22*MAX(0,(H$32*$E37-$E$15-$E$16)-MIN((H$32*$E37-$E$15-$E$16),$E$27)-$E$28))/$E$26) -> 4.4739018
B41: 5% Rev CAGR Case | C41: 0.05 | D41: Exit EBITDA: | E41: =$E$10*(1+C41)^5 -> 10043.06
B42: IRR | D42: =IF(D43<=0,-1,D43^(1/5)-1) -> 0.20525977 | E42: =IF(E43<=0,-1,E43^(1/5)-1) -> 0.22681602 | F42: =IF(F43<=0,-1,F43^(1/5)-1) -> 0.24695575 | G42: =IF(G43<=0,-1,G43^(1/5)-1) -> 0.26587262 | H42: =IF(H43<=0,-1,H43^(1/5)-1) -> 0.28372198
B43: MoIC | D43: =IF($E$26<=0,0,((D$32*$E41-$E$15-$E$16)-$E$22*MAX(0,(D$32*$E41-$E$15-$E$16)-MIN((D$32*$E41-$E$15-$E$16),$E$27)-$E$28))/$E$26) -> 2.5433335 | E43: =IF($E$26<=0,0,((E$32*$E41-$E$15-$E$16)-$E$22*MAX(0,(E$32*$E41-$E$15-$E$16)-MIN((E$32*$E41-$E$15-$E$16),$E$27)-$E$28))/$E$26) -> 2.7790553 | F43: =IF($E$26<=0,0,((F$32*$E41-$E$15-$E$16)-$E$22*MAX(0,(F$32*$E41-$E$15-$E$16)-MIN((F$32*$E41-$E$15-$E$16),$E$27)-$E$28))/$E$26) -> 3.0147772 | G43: =IF($E$26<=0,0,((G$32*$E41-$E$15-$E$16)-$E$22*MAX(0,(G$32*$E41-$E$15-$E$16)-MIN((G$32*$E41-$E$15-$E$16),$E$27)-$E$28))/$E$26) -> 3.250499 | H43: =IF($E$26<=0,0,((H$32*$E41-$E$15-$E$16)-$E$22*MAX(0,(H$32*$E41-$E$15-$E$16)-MIN((H$32*$E41-$E$15-$E$16),$E$27)-$E$28))/$E$26) -> 3.4862208
B45: Flat Rev CAGR Case | C45: 0 | D45: Exit EBITDA: | E45: =$E$10*(1+C45)^5 -> 7869
B46: IRR | D46: =IF(D47<=0,-1,D47^(1/5)-1) -> 0.1406609 | E46: =IF(E47<=0,-1,E47^(1/5)-1) -> 0.16169112 | F46: =IF(F47<=0,-1,F47^(1/5)-1) -> 0.18130031 | G46: =IF(G47<=0,-1,G47^(1/5)-1) -> 0.19968781 | H46: =IF(H47<=0,-1,H47^(1/5)-1) -> 0.21701257
B47: MoIC | D47: =IF($E$26<=0,0,((D$32*$E45-$E$15-$E$16)-$E$22*MAX(0,(D$32*$E45-$E$15-$E$16)-MIN((D$32*$E45-$E$15-$E$16),$E$27)-$E$28))/$E$26) -> 1.9310022 | E47: =IF($E$26<=0,0,((E$32*$E45-$E$15-$E$16)-$E$22*MAX(0,(E$32*$E45-$E$15-$E$16)-MIN((E$32*$E45-$E$15-$E$16),$E$27)-$E$28))/$E$26) -> 2.1156964 | F47: =IF($E$26<=0,0,((F$32*$E45-$E$15-$E$16)-$E$22*MAX(0,(F$32*$E45-$E$15-$E$16)-MIN((F$32*$E45-$E$15-$E$16),$E$27)-$E$28))/$E$26) -> 2.3003906 | G47: =IF($E$26<=0,0,((G$32*$E45-$E$15-$E$16)-$E$22*MAX(0,(G$32*$E45-$E$15-$E$16)-MIN((G$32*$E45-$E$15-$E$16),$E$27)-$E$28))/$E$26) -> 2.4850849 | H47: =IF($E$26<=0,0,((H$32*$E45-$E$15-$E$16)-$E$22*MAX(0,(H$32*$E45-$E$15-$E$16)-MIN((H$32*$E45-$E$15-$E$16),$E$27)-$E$28))/$E$26) -> 2.6697791
B49: Management Case | C49: =($E$11/$E$10)^(1/5)-1 -> 0.083573126 | D49: Exit EBITDA: | E49: =$E$11 -> 11754.676
B50: IRR | D50: =IF(D51<=0,-1,D51^(1/5)-1) -> 0.2478346 | E50: =IF(E51<=0,-1,E51^(1/5)-1) -> 0.26980579 | F50: =IF(F51<=0,-1,F51^(1/5)-1) -> 0.29035382 | G50: =IF(G51<=0,-1,G51^(1/5)-1) -> 0.30967069 | H50: =IF(H51<=0,-1,H51^(1/5)-1) -> 0.32791088
B51: MoIC | D51: =IF($E$26<=0,0,((D$32*$E49-$E$15-$E$16)-$E$22*MAX(0,(D$32*$E49-$E$15-$E$16)-MIN((D$32*$E49-$E$15-$E$16),$E$27)-$E$28))/$E$26) -> 3.0254162 | E51: =IF($E$26<=0,0,((E$32*$E49-$E$15-$E$16)-$E$22*MAX(0,(E$32*$E49-$E$15-$E$16)-MIN((E$32*$E49-$E$15-$E$16),$E$27)-$E$28))/$E$26) -> 3.3013115 | F51: =IF($E$26<=0,0,((F$32*$E49-$E$15-$E$16)-$E$22*MAX(0,(F$32*$E49-$E$15-$E$16)-MIN((F$32*$E49-$E$15-$E$16),$E$27)-$E$28))/$E$26) -> 3.5772069 | G51: =IF($E$26<=0,0,((G$32*$E49-$E$15-$E$16)-$E$22*MAX(0,(G$32*$E49-$E$15-$E$16)-MIN((G$32*$E49-$E$15-$E$16),$E$27)-$E$28))/$E$26) -> 3.8531023 | H51: =IF($E$26<=0,0,((H$32*$E49-$E$15-$E$16)-$E$22*MAX(0,(H$32*$E49-$E$15-$E$16)-MIN((H$32*$E49-$E$15-$E$16),$E$27)-$E$28))/$E$26) -> 4.1289977
B53: ="(1) Returns net of transaction expenses of $"&TEXT(Model!$D$14,"#,##0")&"k and net of the 10% MEIP; margin held at the FY2025A adj. EBITDA margin for the CAGR cases." -> (1) Returns net of transaction expenses of $2,400k and net of the 10% MEIP; margin held at the FY2025A adj. EBITDA margin for the CAGR cases.
B54: (2) Net debt at exit approximated as base-case (management case) net debt from the Model tab for every case.

Sheet Returns  Exhibit-8.5x
A1: =Assump_CapStructure!$F$7 -> Project Kestrel
A2: ="Prepared by: "&Assump_CapStructure!$F$8 -> Prepared by: Halvern
A3: =Assump_CapStructure!$F$11 -> ($ in 000s)
B5: ="Deal Overview and Returns Summary @ "&TEXT($E$7,"0.0x")&" Entry Multiple" -> Deal Overview and Returns Summary @ 8.5x Entry Multiple
B7: Entry Multiple (x FY2025A Adj. EBITDA) | E7: 8.5
B9: Returns Inputs (linked to Model / Assump_CapStructure)
B10: FY2025A Adj. EBITDA | E10: =Model!$E$85 -> 7869
B11: FY2030E EBITDA (exit year 5) | E11: =Model!$J$85 -> 11754.676
B12: FY2028E EBITDA (exit year 3) | E12: =Model!$H$85 -> 10300.977
B13: Debt raised at close (base case, fixed) | E13: =Model!$K$16 -> 35476
B14: Transaction costs + cash to B/S + cash acquired | E14: =Model!$D$14+Model!$D$13+Assump_CapStructure!$D$79 -> 3500
B15: Net debt at FY2030E (excl. seller note; from Model) | E15: =Model!$J$62-Model!$J$61-Model!$J$51 -> 3755.4841
B16: Seller note accreted balance at FY2030E | E16: =Model!$J$61 -> 5352.9023
B17: Net debt at FY2028E (excl. seller note; from Model) | E17: =Model!$H$62-Model!$H$61-Model!$H$51 -> 16536.503
B18: Seller note accreted balance at FY2028E | E18: =Model!$H$61 -> 4764.064
B19: Cumulative goodwill step-up tax savings through FY2028E | E19: =Model!$H$328 -> 2074.696
B20: Preferred % of equity account | E20: =Assump_CapStructure!$F$31 -> 0.9
B21: Preferred accretion rate | E21: =Assump_CapStructure!$F$28 -> 0.08
B22: MEIP % of common profits | E22: =Assump_CapStructure!$F$29 -> 0.1
B23: Sponsor carried interest | E23: =Assump_CapStructure!$F$30 -> 0.2
B25: Purchase Price (Transaction Value) | E25: =$E$7*$E$10 -> 66886.5
B26: Total Equity at Entry (Sponsor + Rollover) | E26: =E25+$E$14-$E$13 -> 34910.5
B27: Preferred Accreted at Exit (year 5) | E27: =E26*$E$20*(1+$E$21)^5 -> 46165.48
B28: Common Equity Invested | E28: =E26*(1-$E$20) -> 3491.05
B30: Five-Year Gross Return Profile (Sponsor + Rollover strip, net of MEIP) (1)
C31: Rev. CAGR | D31: Exit multiple ->
B32: Exit-year EBITDA by case | D32: 6 | E32: 6.5 | F32: 7 | G32: 7.5 | H32: 8
B33: 15% Rev CAGR Case | C33: 0.15 | D33: Exit EBITDA: | E33: =$E$10*(1+C33)^5 -> 15827.37
B34: IRR | D34: =IF(D35<=0,-1,D35^(1/5)-1) -> 0.18691899 | E34: =IF(E35<=0,-1,E35^(1/5)-1) -> 0.20680107 | F34: =IF(F35<=0,-1,F35^(1/5)-1) -> 0.22545319 | G34: =IF(G35<=0,-1,G35^(1/5)-1) -> 0.24303434 | H34: =IF(H35<=0,-1,H35^(1/5)-1) -> 0.25967368
B35: MoIC | D35: =IF($E$26<=0,0,((D$32*$E33-$E$15-$E$16)-$E$22*MAX(0,(D$32*$E33-$E$15-$E$16)-MIN((D$32*$E33-$E$15-$E$16),$E$27)-$E$28))/$E$26) -> 2.3556209 | E35: =IF($E$26<=0,0,((E$32*$E33-$E$15-$E$16)-$E$22*MAX(0,(E$32*$E33-$E$15-$E$16)-MIN((E$32*$E33-$E$15-$E$16),$E$27)-$E$28))/$E$26) -> 2.5596373 | F35: =IF($E$26<=0,0,((F$32*$E33-$E$15-$E$16)-$E$22*MAX(0,(F$32*$E33-$E$15-$E$16)-MIN((F$32*$E33-$E$15-$E$16),$E$27)-$E$28))/$E$26) -> 2.7636538 | G35: =IF($E$26<=0,0,((G$32*$E33-$E$15-$E$16)-$E$22*MAX(0,(G$32*$E33-$E$15-$E$16)-MIN((G$32*$E33-$E$15-$E$16),$E$27)-$E$28))/$E$26) -> 2.9676702 | H35: =IF($E$26<=0,0,((H$32*$E33-$E$15-$E$16)-$E$22*MAX(0,(H$32*$E33-$E$15-$E$16)-MIN((H$32*$E33-$E$15-$E$16),$E$27)-$E$28))/$E$26) -> 3.1716867
B37: 10% Rev CAGR Case | C37: 0.1 | D37: Exit EBITDA: | E37: =$E$10*(1+C37)^5 -> 12673.103
B38: IRR | D38: =IF(D39<=0,-1,D39^(1/5)-1) -> 0.13308403 | E38: =IF(E39<=0,-1,E39^(1/5)-1) -> 0.15224568 | F38: =IF(F39<=0,-1,F39^(1/5)-1) -> 0.17021148 | G38: =IF(G39<=0,-1,G39^(1/5)-1) -> 0.18713728 | H38: =IF(H39<=0,-1,H39^(1/5)-1) -> 0.20314946
B39: MoIC | D39: =IF($E$26<=0,0,((D$32*$E37-$E$15-$E$16)-$E$22*MAX(0,(D$32*$E37-$E$15-$E$16)-MIN((D$32*$E37-$E$15-$E$16),$E$27)-$E$28))/$E$26) -> 1.8677149 | E39: =IF($E$26<=0,0,((E$32*$E37-$E$15-$E$16)-$E$22*MAX(0,(E$32*$E37-$E$15-$E$16)-MIN((E$32*$E37-$E$15-$E$16),$E$27)-$E$28))/$E$26) -> 2.0310726 | F39: =IF($E$26<=0,0,((F$32*$E37-$E$15-$E$16)-$E$22*MAX(0,(F$32*$E37-$E$15-$E$16)-MIN((F$32*$E37-$E$15-$E$16),$E$27)-$E$28))/$E$26) -> 2.1944302 | G39: =IF($E$26<=0,0,((G$32*$E37-$E$15-$E$16)-$E$22*MAX(0,(G$32*$E37-$E$15-$E$16)-MIN((G$32*$E37-$E$15-$E$16),$E$27)-$E$28))/$E$26) -> 2.3577878 | H39: =IF($E$26<=0,0,((H$32*$E37-$E$15-$E$16)-$E$22*MAX(0,(H$32*$E37-$E$15-$E$16)-MIN((H$32*$E37-$E$15-$E$16),$E$27)-$E$28))/$E$26) -> 2.5211455
B41: 5% Rev CAGR Case | C41: 0.05 | D41: Exit EBITDA: | E41: =$E$10*(1+C41)^5 -> 10043.06
B42: IRR | D42: =IF(D43<=0,-1,D43^(1/5)-1) -> 0.078757653 | E42: =IF(E43<=0,-1,E43^(1/5)-1) -> 0.097232553 | F42: =IF(F43<=0,-1,F43^(1/5)-1) -> 0.11454094 | G42: =IF(G43<=0,-1,G43^(1/5)-1) -> 0.1308365 | H42: =IF(H43<=0,-1,H43^(1/5)-1) -> 0.14624355
B43: MoIC | D43: =IF($E$26<=0,0,((D$32*$E41-$E$15-$E$16)-$E$22*MAX(0,(D$32*$E41-$E$15-$E$16)-MIN((D$32*$E41-$E$15-$E$16),$E$27)-$E$28))/$E$26) -> 1.4608965 | E43: =IF($E$26<=0,0,((E$32*$E41-$E$15-$E$16)-$E$22*MAX(0,(E$32*$E41-$E$15-$E$16)-MIN((E$32*$E41-$E$15-$E$16),$E$27)-$E$28))/$E$26) -> 1.5903526 | F43: =IF($E$26<=0,0,((F$32*$E41-$E$15-$E$16)-$E$22*MAX(0,(F$32*$E41-$E$15-$E$16)-MIN((F$32*$E41-$E$15-$E$16),$E$27)-$E$28))/$E$26) -> 1.7198087 | G43: =IF($E$26<=0,0,((G$32*$E41-$E$15-$E$16)-$E$22*MAX(0,(G$32*$E41-$E$15-$E$16)-MIN((G$32*$E41-$E$15-$E$16),$E$27)-$E$28))/$E$26) -> 1.8492648 | H43: =IF($E$26<=0,0,((H$32*$E41-$E$15-$E$16)-$E$22*MAX(0,(H$32*$E41-$E$15-$E$16)-MIN((H$32*$E41-$E$15-$E$16),$E$27)-$E$28))/$E$26) -> 1.9787209
B45: Flat Rev CAGR Case | C45: 0 | D45: Exit EBITDA: | E45: =$E$10*(1+C45)^5 -> 7869
B46: IRR | D46: =IF(D47<=0,-1,D47^(1/5)-1) -> 0.017669077 | E46: =IF(E47<=0,-1,E47^(1/5)-1) -> 0.037866663 | F46: =IF(F47<=0,-1,F47^(1/5)-1) -> 0.056604373 | G46: =IF(G47<=0,-1,G47^(1/5)-1) -> 0.073991362 | H46: =IF(H47<=0,-1,H47^(1/5)-1) -> 0.088823632
B47: MoIC | D47: =IF($E$26<=0,0,((D$32*$E45-$E$15-$E$16)-$E$22*MAX(0,(D$32*$E45-$E$15-$E$16)-MIN((D$32*$E45-$E$15-$E$16),$E$27)-$E$28))/$E$26) -> 1.091523 | E47: =IF($E$26<=0,0,((E$32*$E45-$E$15-$E$16)-$E$22*MAX(0,(E$32*$E45-$E$15-$E$16)-MIN((E$32*$E45-$E$15-$E$16),$E$27)-$E$28))/$E$26) -> 1.2042255 | F47: =IF($E$26<=0,0,((F$32*$E45-$E$15-$E$16)-$E$22*MAX(0,(F$32*$E45-$E$15-$E$16)-MIN((F$32*$E45-$E$15-$E$16),$E$27)-$E$28))/$E$26) -> 1.316928 | G47: =IF($E$26<=0,0,((G$32*$E45-$E$15-$E$16)-$E$22*MAX(0,(G$32*$E45-$E$15-$E$16)-MIN((G$32*$E45-$E$15-$E$16),$E$27)-$E$28))/$E$26) -> 1.4289069 | H47: =IF($E$26<=0,0,((H$32*$E45-$E$15-$E$16)-$E$22*MAX(0,(H$32*$E45-$E$15-$E$16)-MIN((H$32*$E45-$E$15-$E$16),$E$27)-$E$28))/$E$26) -> 1.5303392
B49: Management Case | C49: =($E$11/$E$10)^(1/5)-1 -> 0.083573126 | D49: Exit EBITDA: | E49: =$E$11 -> 11754.676
B50: IRR | D50: =IF(D51<=0,-1,D51^(1/5)-1) -> 0.11529722 | E50: =IF(E51<=0,-1,E51^(1/5)-1) -> 0.13422899 | F50: =IF(F51<=0,-1,F51^(1/5)-1) -> 0.15197517 | G50: =IF(G51<=0,-1,G51^(1/5)-1) -> 0.16869075 | H50: =IF(H51<=0,-1,H51^(1/5)-1) -> 0.18450135
B51: MoIC | D51: =IF($E$26<=0,0,((D$32*$E49-$E$15-$E$16)-$E$22*MAX(0,(D$32*$E49-$E$15-$E$16)-MIN((D$32*$E49-$E$15-$E$16),$E$27)-$E$28))/$E$26) -> 1.7256515 | E51: =IF($E$26<=0,0,((E$32*$E49-$E$15-$E$16)-$E$22*MAX(0,(E$32*$E49-$E$15-$E$16)-MIN((E$32*$E49-$E$15-$E$16),$E$27)-$E$28))/$E$26) -> 1.8771705 | F51: =IF($E$26<=0,0,((F$32*$E49-$E$15-$E$16)-$E$22*MAX(0,(F$32*$E49-$E$15-$E$16)-MIN((F$32*$E49-$E$15-$E$16),$E$27)-$E$28))/$E$26) -> 2.0286895 | G51: =IF($E$26<=0,0,((G$32*$E49-$E$15-$E$16)-$E$22*MAX(0,(G$32*$E49-$E$15-$E$16)-MIN((G$32*$E49-$E$15-$E$16),$E$27)-$E$28))/$E$26) -> 2.1802085 | H51: =IF($E$26<=0,0,((H$32*$E49-$E$15-$E$16)-$E$22*MAX(0,(H$32*$E49-$E$15-$E$16)-MIN((H$32*$E49-$E$15-$E$16),$E$27)-$E$28))/$E$26) -> 2.3317275
B53: ="(1) Returns net of transaction expenses of $"&TEXT(Model!$D$14,"#,##0")&"k and net of the 10% MEIP; margin held at the FY2025A adj. EBITDA margin for the CAGR cases." -> (1) Returns net of transaction expenses of $2,400k and net of the 10% MEIP; margin held at the FY2025A adj. EBITDA margin for the CAGR cases.
B54: (2) Net debt at exit approximated as base-case (management case) net debt from the Model tab for every case.

Sheet Sources and Uses-DETAIL
A1: =Assump_CapStructure!$F$7 -> Project Kestrel
A2: ="Prepared by: "&Assump_CapStructure!$F$8 -> Prepared by: Halvern
A3: =Assump_CapStructure!$F$11 -> ($ in 000s)
B5: Transaction Summary
B6: =Assump_CapStructure!$F$11 -> ($ in 000s)
B8: Total Enterprise Value | E8: =Assump_CapStructure!$D$72 -> 55083 | I8: =E8/Model!$E$85 -> 7 | J8: x FY2025A Adj. EBITDA
B9: Investor Entry Multiple (FY2025A) | E9: =Assump_CapStructure!$D$73 -> 7
B10: Investor Entry Multiple (FY2026E) | E10: =Assump_CapStructure!$D$74 -> 6.2977588
B11: Operating Case: | E11: =CHOOSE(Assump_CapStructure!$K$5,"Management Case","Case II - No Growth, No Taxes","Case III - Downside Case, No Taxes","Upside Case","Flat Case") -> Management Case
B12: Financing Case: | E12: =CHOOSE(Assump_CapStructure!$K$15,"Base Case - Senior + Mezz","Senior Only","Senior + Seller Note Upsized","All Equity","Unitranche","Case 6","Case 7","Case 8","Case 9","Case 10") -> Base Case - Senior + Mezz | I12: NO | J12: Revolver drawn at close?
B13: Step Up in Basis | E13: =IF(Assump_CapStructure!$F$22=1,"Yes","No") -> Yes
B14: Rollover % of Proceeds | E14: =Model!$K$17/Assump_CapStructure!$D$80 -> 0.1834509
B15: Exit: | E15: 5 Years
B17: (1) Fixed Charge Coverage = (EBITDA - Mgmt Fee - Capex - Cash Taxes) / (Scheduled Principal + Cash Interest).
B19: LTM 7/31/26 Estimated Adj. EBITDA (per QoE; for x LTM column) | E19: 8214
B21: Sources and Uses of Funds ($ in 000's) - FINAL FOR CLOSING | U21: LOI vs. Final
B22: Uses | E22: Amount | F22: % of Total | G22: x LTM EBITDA | I22: Sources | L22: Amount | M22: % of Total | N22: x LTM EBITDA | O22: Pricing | W22: LOI | X22: Final | Y22: Delta | Z22: % chg
B23: Cash Consideration (incl. payoff of existing debt) | E23: =Consideration!$H$22+Model!$D$8 -> 42314.8 | F23: =E23/$E$29 -> 0.72230511 | G23: =E23/$E$19 -> 5.1515461 | I23: Revolver (undrawn) (2) | L23: =Model!$K$7 -> 0 | M23: =L23/$L$29 -> 0 | N23: =L23/$E$19 -> 0 | O23: ="Base + "&TEXT(Assump_CapStructure!$U$36,"0.00%") -> Base + 3.00% | U23: Cash Consideration | W23: 40125 | X23: =E23 -> 42314.8 | Y23: =X23-W23 -> 2189.8 | Z23: =IF(W23=0,0,X23/W23-1) -> 0.054574455
B24: Seller Note | E24: =Model!$K$13 -> 4000 | F24: =E24/$E$29 -> 0.068279194 | G24: =E24/$E$19 -> 0.48697346 | I24: Term Loan A (3) | L24: =Model!$K$8 -> 23607 | M24: =L24/$L$29 -> 0.40296673 | N24: =L24/$E$19 -> 2.8739956 | O24: ="Base + "&TEXT(Assump_CapStructure!$U$37,"0.00%") -> Base + 3.25% | U24: Seller Note | W24: 4000 | X24: =E24 -> 4000 | Y24: =X24-W24 -> 0 | Z24: =IF(W24=0,0,X24/W24-1) -> 0
B25: Rollover Equity | E25: =Model!$K$17 -> 8868.2 | F25: =E25/$E$29 -> 0.15137839 | G25: =E25/$E$19 -> 1.0796445 | I25: Mezzanine Debt | L25: =Model!$K$12 -> 7869 | M25: =L25/$L$29 -> 0.13432224 | N25: =L25/$E$19 -> 0.95799854 | O25: =TEXT(Assump_CapStructure!$U$41,"0.00%")&" cash + "&TEXT(Assump_CapStructure!$V$41,"0.00%")&" PIK" -> 11.00% cash + 2.00% PIK | U25: Rollover Equity | W25: 8650 | X25: =E25 -> 8868.2 | Y25: =X25-W25 -> 218.2 | Z25: =IF(W25=0,0,X25/W25-1) -> 0.025225434
B26: Purchase Price | E26: =SUM(E23:E25) -> 55183 | F26: =E26/$E$29 -> 0.94196269 | G26: =E26/$E$19 -> 6.7181641 | I26: Seller Note | L26: =Model!$K$13 -> 4000 | M26: =L26/$L$29 -> 0.068279194 | N26: =L26/$E$19 -> 0.48697346 | O26: =TEXT(Assump_CapStructure!$V$42,"0.00%")&" PIK" -> 6.00% PIK | U26: Transaction Costs | W26: 2150 | X26: =E27 -> 2400 | Y26: =X26-W26 -> 250 | Z26: =IF(W26=0,0,X26/W26-1) -> 0.11627907
B27: Transaction Costs (1) | E27: =Model!$D$14 -> 2400 | F27: =E27/$E$29 -> 0.040967516 | G27: =E27/$E$19 -> 0.29218408 | I27: Rollover Equity | L27: =Model!$K$17 -> 8868.2 | M27: =L27/$L$29 -> 0.15137839 | N27: =L27/$E$19 -> 1.0796445 | U27: Cash on Balance Sheet | W27: 750 | X27: =E28 -> 1000 | Y27: =X27-W27 -> 250 | Z27: =IF(W27=0,0,X27/W27-1) -> 0.33333333
B28: Cash on Balance Sheet at Close (6) | E28: =Model!$D$13 -> 1000 | F28: =E28/$E$29 -> 0.017069798 | G28: =E28/$E$19 -> 0.12174336 | I28: Sponsor Equity (5) | L28: =Model!$K$18+Model!$K$19 -> 14238.8 | M28: =L28/$L$29 -> 0.24305345 | N28: =L28/$E$19 -> 1.7334794 | U28: Total Uses | W28: =SUM(W23:W27) -> 55675 | X28: =E29 -> 58583 | Y28: =X28-W28 -> 2908 | Z28: =IF(W28=0,0,X28/W28-1) -> 0.052231702
B29: Total Uses | E29: =E26+SUM(E27:E28) -> 58583 | F29: =E29/$E$29 -> 1 | G29: =E29/$E$19 -> 7.1320916 | I29: Total Sources | L29: =SUM(L23:L28) -> 58583 | M29: =SUM(M23:M28) -> 1 | N29: =L29/$E$19 -> 7.1320916
B31: Check: Total Sources - Total Uses (must be 0) | E31: =L29-E29 -> 0
B32: ="LTM EBITDA is 7/31/26 estimated adjusted EBITDA of $"&TEXT($E$19,"#,##0")&"k." -> LTM EBITDA is 7/31/26 estimated adjusted EBITDA of $8,214k.
B34: (1) Purchaser fees and expenses including the bank / M&A fee, legal, accounting and diligence, and financing fees.
B35: (2) $8.0M revolver, undrawn at close.
B36: (3) Reflects full draw of the term loan A at close.
B37: (4) Sponsor common equity subject to 10% MEIP dilution.
B38: (5) Reflects upsized sponsor equity ticket and seller rollover of 20% of consideration ex seller note.
B39: (6) Excess cash left in the business for liquidity (minimum cash $1.0M).
B41: Uses of Excess Cash from Closing:
B42: Incremental transaction cost estimate vs LOI | E42: =Model!$D$14-M26 -> 2399.9317
B43: Excess cash for liquidity | E43: =Model!$D$13 -> 1000
B44: Investment available for an add-on acquisition | E44: 0
B45: Total (incl. $100k cash left by seller) | E45: =SUM(E42:E44)+Assump_CapStructure!$D$79 -> 3499.9317

Sheet Sources and Uses-SUMMARY
A1: =Assump_CapStructure!$F$7 -> Project Kestrel
A2: ="Prepared by: "&Assump_CapStructure!$F$8 -> Prepared by: Halvern
A3: =Assump_CapStructure!$F$11 -> ($ in 000s)
B5: Transaction Summary
B6: =Assump_CapStructure!$F$11 -> ($ in 000s)
B8: Total Enterprise Value | E8: =Assump_CapStructure!$D$72 -> 55083 | I8: =E8/Model!$E$85 -> 7 | J8: x FY2025A Adj. EBITDA
B9: Investor Entry Multiple (FY2025A) | E9: =Assump_CapStructure!$D$73 -> 7
B10: Investor Entry Multiple (FY2026E) | E10: =Assump_CapStructure!$D$74 -> 6.2977588
B11: Operating Case: | E11: =CHOOSE(Assump_CapStructure!$K$5,"Management Case","Case II - No Growth, No Taxes","Case III - Downside Case, No Taxes","Upside Case","Flat Case") -> Management Case
B12: Financing Case: | E12: =CHOOSE(Assump_CapStructure!$K$15,"Base Case - Senior + Mezz","Senior Only","Senior + Seller Note Upsized","All Equity","Unitranche","Case 6","Case 7","Case 8","Case 9","Case 10") -> Base Case - Senior + Mezz | I12: NO | J12: Revolver drawn at close?
B13: Step Up in Basis | E13: =IF(Assump_CapStructure!$F$22=1,"Yes","No") -> Yes
B14: Rollover % of Proceeds | E14: =Model!$K$17/Assump_CapStructure!$D$80 -> 0.1834509
B15: Exit: | E15: 5 Years
B17: (1) Fixed Charge Coverage = (EBITDA - Mgmt Fee - Capex - Cash Taxes) / (Scheduled Principal + Cash Interest).
B19: LTM 7/31/26 Estimated Adj. EBITDA (per QoE; for x LTM column) | E19: 8214
B21: Sources and Uses of Funds ($ in 000's) - FINAL FOR CLOSING | U21: LOI vs. Final
B22: Uses | E22: Amount | F22: % of Total | G22: x LTM EBITDA | I22: Sources | L22: Amount | M22: % of Total | N22: x LTM EBITDA | O22: Pricing | W22: LOI | X22: Final | Y22: Delta | Z22: % chg
B23: Cash Consideration (incl. payoff of existing debt) | E23: =Consideration!$H$22+Model!$D$8 -> 42314.8 | F23: =E23/$E$29 -> 0.72230511 | G23: =E23/$E$19 -> 5.1515461 | I23: Revolver (undrawn) (2) | L23: =Model!$K$7 -> 0 | M23: =L23/$L$29 -> 0 | N23: =L23/$E$19 -> 0 | O23: ="Base + "&TEXT(Assump_CapStructure!$U$36,"0.00%") -> Base + 3.00% | U23: Cash Consideration | W23: 40125 | X23: =E23 -> 42314.8 | Y23: =X23-W23 -> 2189.8 | Z23: =IF(W23=0,0,X23/W23-1) -> 0.054574455
B24: Seller Note | E24: =Model!$K$13 -> 4000 | F24: =E24/$E$29 -> 0.068279194 | G24: =E24/$E$19 -> 0.48697346 | I24: Term Loan A (3) | L24: =Model!$K$8 -> 23607 | M24: =L24/$L$29 -> 0.40296673 | N24: =L24/$E$19 -> 2.8739956 | O24: ="Base + "&TEXT(Assump_CapStructure!$U$37,"0.00%") -> Base + 3.25% | U24: Seller Note | W24: 4000 | X24: =E24 -> 4000 | Y24: =X24-W24 -> 0 | Z24: =IF(W24=0,0,X24/W24-1) -> 0
B25: Rollover Equity | E25: =Model!$K$17 -> 8868.2 | F25: =E25/$E$29 -> 0.15137839 | G25: =E25/$E$19 -> 1.0796445 | I25: Mezzanine Debt | L25: =Model!$K$12 -> 7869 | M25: =L25/$L$29 -> 0.13432224 | N25: =L25/$E$19 -> 0.95799854 | O25: =TEXT(Assump_CapStructure!$U$41,"0.00%")&" cash + "&TEXT(Assump_CapStructure!$V$41,"0.00%")&" PIK" -> 11.00% cash + 2.00% PIK | U25: Rollover Equity | W25: 8650 | X25: =E25 -> 8868.2 | Y25: =X25-W25 -> 218.2 | Z25: =IF(W25=0,0,X25/W25-1) -> 0.025225434
B26: Purchase Price | E26: =SUM(E23:E25) -> 55183 | F26: =E26/$E$29 -> 0.94196269 | G26: =E26/$E$19 -> 6.7181641 | I26: Seller Note | L26: =Model!$K$13 -> 4000 | M26: =L26/$L$29 -> 0.068279194 | N26: =L26/$E$19 -> 0.48697346 | O26: =TEXT(Assump_CapStructure!$V$42,"0.00%")&" PIK" -> 6.00% PIK | U26: Transaction Costs | W26: 2150 | X26: =E27 -> 2400 | Y26: =X26-W26 -> 250 | Z26: =IF(W26=0,0,X26/W26-1) -> 0.11627907
B27: Transaction Costs (1) | E27: =Model!$D$14 -> 2400 | F27: =E27/$E$29 -> 0.040967516 | G27: =E27/$E$19 -> 0.29218408 | I27: Rollover Equity | L27: =Model!$K$17 -> 8868.2 | M27: =L27/$L$29 -> 0.15137839 | N27: =L27/$E$19 -> 1.0796445 | U27: Cash on Balance Sheet | W27: 750 | X27: =E28 -> 1000 | Y27: =X27-W27 -> 250 | Z27: =IF(W27=0,0,X27/W27-1) -> 0.33333333
B28: Cash on Balance Sheet at Close (6) | E28: =Model!$D$13 -> 1000 | F28: =E28/$E$29 -> 0.017069798 | G28: =E28/$E$19 -> 0.12174336 | I28: Sponsor Equity (5) | L28: =Model!$K$18+Model!$K$19 -> 14238.8 | M28: =L28/$L$29 -> 0.24305345 | N28: =L28/$E$19 -> 1.7334794 | U28: Total Uses | W28: =SUM(W23:W27) -> 55675 | X28: =E29 -> 58583 | Y28: =X28-W28 -> 2908 | Z28: =IF(W28=0,0,X28/W28-1) -> 0.052231702
B29: Total Uses | E29: =E26+SUM(E27:E28) -> 58583 | F29: =E29/$E$29 -> 1 | G29: =E29/$E$19 -> 7.1320916 | I29: Total Sources | L29: =SUM(L23:L28) -> 58583 | M29: =SUM(M23:M28) -> 1 | N29: =L29/$E$19 -> 7.1320916
B31: Check: Total Sources - Total Uses (must be 0) | E31: =L29-E29 -> 0
B32: ="LTM EBITDA is 7/31/26 estimated adjusted EBITDA of $"&TEXT($E$19,"#,##0")&"k." -> LTM EBITDA is 7/31/26 estimated adjusted EBITDA of $8,214k.
B34: (1) Purchaser fees and expenses including the bank / M&A fee, legal, accounting and diligence, and financing fees.
B35: (2) $8.0M revolver, undrawn at close.
B36: (3) Reflects full draw of the term loan A at close.
B37: (4) Sponsor common equity subject to 10% MEIP dilution.
B38: (5) Reflects upsized sponsor equity ticket and seller rollover of 20% of consideration ex seller note.
B39: (6) Excess cash left in the business for liquidity (minimum cash $1.0M).
B41: Total Uses | E41: =E29 -> 58583
B42: LOI Total Uses | E42: =W28 -> 55675
B43: % change vs LOI | E43: =E41/E42-1 -> 0.052231702

Sheet Consideration
A1: =Assump_CapStructure!$F$7 -> Project Kestrel
A2: ="Prepared by: "&Assump_CapStructure!$F$8 -> Prepared by: Halvern
A3: =Assump_CapStructure!$F$11 -> ($ in 000s)
B5: Consideration Summary
B6: Consideration to Seller - Updated for Overcapitalization / Purchase Price
C7: Thomas | D7: Gregory | E7: Anne | H7: Total | M7: Accreted @ 8% / 5 yrs
C8: Marlbeck | D8: Marlbeck | E8: Marlbeck-Holt
B10: Current Ownership % | C10: 0.55 | D10: 0.3 | E10: 0.15 | H10: =SUM(C10:E10) -> 1
B11: Consideration ex Seller Note (1) | C11: =C10*$H$11 -> 24387.55 | D11: =D10*$H$11 -> 13302.3 | E11: =E10*$H$11 -> 6651.15 | H11: =Assump_CapStructure!$D$80-Model!$K$13 -> 44341
B12: Memo: Seller Note allocated by ownership (4) | C12: =C10*$H$12 -> 2200 | D12: =D10*$H$12 -> 1200 | E12: =E10*$H$12 -> 600 | H12: =Model!$K$13 -> 4000
B13: Rollover % of Consideration ex Note | C13: 0.2 | D13: 0.2 | E13: 0.2 | H13: =H14/H11 -> 0.2
B14: Rollover $ Amount | C14: =C13*C11 -> 4877.51 | D14: =D13*D11 -> 2660.46 | E14: =E13*E11 -> 1330.23 | H14: =SUM(C14:E14) -> 8868.2
B15: Newco Equity Account | C15: =C14 -> 4877.51 | D15: =D14 -> 2660.46 | E15: =E14 -> 1330.23 | H15: =Model!$K$20 -> 23107 | M15: =H15*(1+Assump_CapStructure!$F$28)^5 -> 33951.764
B16: Sponsor Equity Check | H16: =H15-H14 -> 14238.8
B17: Newco Ownership % (2) | C17: =C14/$H$15 -> 0.21108365 | D17: =D14/$H$15 -> 0.11513654 | E17: =E14/$H$15 -> 0.057568269 | H17: =SUM(C17:E17) -> 0.38378846
B18: LOI Ownership | C18: 0.184 | D18: 0.101 | E18: 0.05 | H18: =SUM(C18:E18) -> 0.335
B19: Check vs LOI Ownership | C19: =C17-C18 -> 0.027083654 | D19: =D17-D18 -> 0.014136539 | E19: =E17-E18 -> 0.0075682694 | H19: =H17-H18 -> 0.048788462
B21: Gross Consideration Summary (3) | I21: % of Total
B22: Cash proceeds | C22: =C11-C14 -> 19510.04 | D22: =D11-D14 -> 10641.84 | E22: =E11-E14 -> 5320.92 | H22: =H11-H14 -> 35472.8 | I22: =H22/$H$25 -> 0.7338036
B23: Rollover equity | C23: =C14 -> 4877.51 | D23: =D14 -> 2660.46 | E23: =E14 -> 1330.23 | H23: =H14 -> 8868.2 | I23: =H23/$H$25 -> 0.1834509
B24: Seller Note (4) | C24: =C12 -> 2200 | D24: =D12 -> 1200 | E24: =E12 -> 600 | H24: =H12 -> 4000 | I24: =H24/$H$25 -> 0.082745496
B25: Total Consideration | C25: =SUM(C22:C24) -> 26587.55 | D25: =SUM(D22:D24) -> 14502.3 | E25: =SUM(E22:E24) -> 7251.15 | H25: =SUM(H22:H24) -> 48341 | I25: =H25/$H$25 -> 1
B27: (1) Equity purchase price less the seller note; allocated by current ownership.
B28: (2) Rollover $ divided by the total Newco equity account (sponsor + rollover), pre-MEIP.
B29: (3) Gross of transaction expenses borne by the sellers and of any closing working capital adjustment.
B30: (4) Seller note: 6% PIK, 6-year maturity, subordinated to senior and mezzanine debt.
B32: For Purchase Agreement Schedules 1.1 and 1.3
B34: Rollover % of consideration ("a") | C34: =C13 -> 0.2 | D34: =D13 -> 0.2 | E34: =E13 -> 0.2
B35: Contributed membership interest ("b" = a x current ownership) | C35: =C34*C10 -> 0.11 | D35: =D34*D10 -> 0.06 | E35: =E34*E10 -> 0.03 | H35: =SUM(C35:E35) -> 0.2
B36: Purchased membership interest (current ownership - b) | C36: =C10-C35 -> 0.44 | D36: =D10-D35 -> 0.24 | E36: =E10-E35 -> 0.12 | H36: =SUM(C36:E36) -> 0.8
B38: ROLLOVER EQUITY IMPACT WITH PROPOSED OVERCAPITALIZATION
C39: Same Rollover $ from LOI | D39: Same Ownership % from LOI
B40: LOI Newco Equity Account (sponsor check per LOI + rollover) | C40: =13875.25+$H$14 -> 22743.45 | D40: =13875.25+$H$14 -> 22743.45
B41: Rollover $ | C41: =$H$14 -> 8868.2 | D41: =$H$18*$H$15 -> 7740.845
B42: Newco Equity Account (proposed) | C42: =$H$15 -> 23107 | D42: =$H$15 -> 23107
B43: Sponsor Equity Check | C43: =C42-C41 -> 14238.8 | D43: =D42-D41 -> 15366.155
B44: Newco Ownership % | C44: =C41/C42 -> 0.38378846 | D44: =D41/D42 -> 0.335
B45: Ownership delta vs LOI | C45: =C44-$H$18 -> 0.048788462 | D45: =D44-$H$18 -> 0
B46: Dilution vs LOI | C46: =C45/$H$18 -> 0.1456372 | D46: =D45/$H$18 -> 0
B47: Rollover required to dilution-protect (6) | C47: =$H$18*C42 -> 7740.845 | D47: =$H$18*D42 -> 7740.845
B48: Incremental rollover required | C48: =C47-C41 -> -1127.355 | D48: =D47-D41 -> 0
B50: ="(6) Keeps Newco Equity Account at $"&TEXT(H15,"#,##0")&"k and solves for the rollover that holds LOI ownership." -> (6) Keeps Newco Equity Account at $23,107k and solves for the rollover that holds LOI ownership.

Sheet Model-->
A1: Model -->

Sheet Model
A1: =Assump_CapStructure!$F$7 -> Project Kestrel | M1: ="Operating Case Running: "&CHOOSE(Assump_CapStructure!$K$5,"Management Case","Case II - No Growth, No Taxes","Case III - Downside Case, No Taxes","Upside Case","Flat Case") -> Operating Case Running: Management Case
A2: ="Prepared by: "&Assump_CapStructure!$F$8 -> Prepared by: Halvern | M2: ="Capital Structure Case: "&CHOOSE(Assump_CapStructure!$K$15,"Base Case - Senior + Mezz","Senior Only","Senior + Seller Note Upsized","All Equity","Unitranche","Case 6","Case 7","Case 8","Case 9","Case 10") -> Capital Structure Case: Base Case - Senior + Mezz
A3: =Assump_CapStructure!$F$11 -> ($ in 000s)
A5: TRANSACTION SUMMARY - USES AND SOURCES OF FUNDS
A6: USES OF FUNDS | D6: Amount | E6: % of Total | F6: x EBITDA | H6: SOURCES OF FUNDS | K6: Amount | L6: % of Total | M6: x EBITDA | N6: Pricing
A7: Cash Consideration to Shareholders | B7: (incl. seller-note portion) | D7: =Assump_CapStructure!D53 -> 39472.8 | E7: =IF($D$15=0,0,D7/$D$15) -> 0.67379274 | F7: =D7/$E$85 -> 5.0162409 | H7: Revolver | K7: =Assump_CapStructure!D36 -> 0 | L7: =IF(K7>0,(ROUND(K7/$K$21,2)*100&"%"),"-") -> - | M7: =K7/$E$85 -> 0 | N7: =IF(K7>0,IF(Assump_CapStructure!$W$36="L +","Base + "&TEXT(Assump_CapStructure!$U$36,"0.00%"),TEXT(Assump_CapStructure!$U$36,"0.00%")&" Fixed")&IF(Assump_CapStructure!$V$36>0," + "&TEXT(Assump_CapStructure!$V$36,"0.00%")&" PIK",""),"-") -> -
A8: Repay Existing Debt | D8: =Assump_CapStructure!D54 -> 6842 | E8: =IF($D$15=0,0,D8/$D$15) -> 0.11679156 | F8: =D8/$E$85 -> 0.86948786 | H8: Term Loan A | K8: =Assump_CapStructure!D37 -> 23607 | L8: =IF(K8>0,(ROUND(K8/$K$21,2)*100&"%"),"-") -> 40% | M8: =K8/$E$85 -> 3 | N8: =IF(K8>0,IF(Assump_CapStructure!$W$37="L +","Base + "&TEXT(Assump_CapStructure!$U$37,"0.00%"),TEXT(Assump_CapStructure!$U$37,"0.00%")&" Fixed")&IF(Assump_CapStructure!$V$37>0," + "&TEXT(Assump_CapStructure!$V$37,"0.00%")&" PIK",""),"-") -> Base + 3.25%
A9: Rollover Equity | D9: =Assump_CapStructure!D55 -> 8868.2 | E9: =IF($D$15=0,0,D9/$D$15) -> 0.15137839 | F9: =D9/$E$85 -> 1.1269793 | H9: Term Loan B | K9: =Assump_CapStructure!D38 -> 0 | L9: =IF(K9>0,(ROUND(K9/$K$21,2)*100&"%"),"-") -> - | M9: =K9/$E$85 -> 0 | N9: =IF(K9>0,IF(Assump_CapStructure!$W$38="L +","Base + "&TEXT(Assump_CapStructure!$U$38,"0.00%"),TEXT(Assump_CapStructure!$U$38,"0.00%")&" Fixed")&IF(Assump_CapStructure!$V$38>0," + "&TEXT(Assump_CapStructure!$V$38,"0.00%")&" PIK",""),"-") -> -
A10: Earnout | D10: =Assump_CapStructure!D56 -> 0 | E10: =IF($D$15=0,0,D10/$D$15) -> 0 | F10: =D10/$E$85 -> 0 | H10: Second Lien | K10: =Assump_CapStructure!D39 -> 0 | L10: =IF(K10>0,(ROUND(K10/$K$21,2)*100&"%"),"-") -> - | M10: =K10/$E$85 -> 0 | N10: =IF(K10>0,IF(Assump_CapStructure!$W$39="L +","Base + "&TEXT(Assump_CapStructure!$U$39,"0.00%"),TEXT(Assump_CapStructure!$U$39,"0.00%")&" Fixed")&IF(Assump_CapStructure!$V$39>0," + "&TEXT(Assump_CapStructure!$V$39,"0.00%")&" PIK",""),"-") -> -
A11: Rollover Debt | D11: =Assump_CapStructure!D57 -> 0 | E11: =IF($D$15=0,0,D11/$D$15) -> 0 | F11: =D11/$E$85 -> 0 | H11: Senior Notes | K11: =Assump_CapStructure!D40 -> 0 | L11: =IF(K11>0,(ROUND(K11/$K$21,2)*100&"%"),"-") -> - | M11: =K11/$E$85 -> 0 | N11: =IF(K11>0,IF(Assump_CapStructure!$W$40="L +","Base + "&TEXT(Assump_CapStructure!$U$40,"0.00%"),TEXT(Assump_CapStructure!$U$40,"0.00%")&" Fixed")&IF(Assump_CapStructure!$V$40>0," + "&TEXT(Assump_CapStructure!$V$40,"0.00%")&" PIK",""),"-") -> -
A12: Purchase Price | D12: =SUM(D7:D11) -> 55183 | E12: =IF($D$15=0,0,D12/$D$15) -> 0.94196269 | F12: =D12/$E$85 -> 7.0127081 | H12: Mezzanine Debt | K12: =Assump_CapStructure!D41 -> 7869 | L12: =IF(K12>0,(ROUND(K12/$K$21,2)*100&"%"),"-") -> 13% | M12: =K12/$E$85 -> 1 | N12: =IF(K12>0,IF(Assump_CapStructure!$W$41="L +","Base + "&TEXT(Assump_CapStructure!$U$41,"0.00%"),TEXT(Assump_CapStructure!$U$41,"0.00%")&" Fixed")&IF(Assump_CapStructure!$V$41>0," + "&TEXT(Assump_CapStructure!$V$41,"0.00%")&" PIK",""),"-") -> 11.00% Fixed + 2.00% PIK
A13: Cash on Balance Sheet at Close | D13: =Assump_CapStructure!D59 -> 1000 | E13: =IF($D$15=0,0,D13/$D$15) -> 0.017069798 | F13: =D13/$E$85 -> 0.12708095 | H13: Seller Note | K13: =Assump_CapStructure!D42 -> 4000 | L13: =IF(K13>0,(ROUND(K13/$K$21,2)*100&"%"),"-") -> 7% | M13: =K13/$E$85 -> 0.5083238 | N13: =IF(K13>0,IF(Assump_CapStructure!$W$42="L +","Base + "&TEXT(Assump_CapStructure!$U$42,"0.00%"),TEXT(Assump_CapStructure!$U$42,"0.00%")&" Fixed")&IF(Assump_CapStructure!$V$42>0," + "&TEXT(Assump_CapStructure!$V$42,"0.00%")&" PIK",""),"-") -> 0.00% Fixed + 6.00% PIK
A14: Transaction Costs | D14: =Assump_CapStructure!D64 -> 2400 | E14: =IF($D$15=0,0,D14/$D$15) -> 0.040967516 | F14: =D14/$E$85 -> 0.30499428 | H14: Subordinated Notes | K14: =Assump_CapStructure!D43 -> 0 | L14: =IF(K14>0,(ROUND(K14/$K$21,2)*100&"%"),"-") -> - | M14: =K14/$E$85 -> 0 | N14: =IF(K14>0,IF(Assump_CapStructure!$W$43="L +","Base + "&TEXT(Assump_CapStructure!$U$43,"0.00%"),TEXT(Assump_CapStructure!$U$43,"0.00%")&" Fixed")&IF(Assump_CapStructure!$V$43>0," + "&TEXT(Assump_CapStructure!$V$43,"0.00%")&" PIK",""),"-") -> -
A15: Total Uses | D15: =D12+D13+D14 -> 58583 | E15: =IF($D$15=0,0,D15/$D$15) -> 1 | F15: =D15/$E$85 -> 7.4447833 | H15: Other | K15: =Assump_CapStructure!D44 -> 0 | L15: =IF(K15>0,(ROUND(K15/$K$21,2)*100&"%"),"-") -> - | M15: =K15/$E$85 -> 0 | N15: =IF(K15>0,IF(Assump_CapStructure!$W$44="L +","Base + "&TEXT(Assump_CapStructure!$U$44,"0.00%"),TEXT(Assump_CapStructure!$U$44,"0.00%")&" Fixed")&IF(Assump_CapStructure!$V$44>0," + "&TEXT(Assump_CapStructure!$V$44,"0.00%")&" PIK",""),"-") -> -
H16: Total Debt | K16: =SUM(K7:K15) -> 35476 | L16: =IF(K16>0,(ROUND(K16/$K$21,2)*100&"%"),"-") -> 61% | M16: =K16/$E$85 -> 4.5083238
H17: Rollover Equity | K17: =Assump_CapStructure!D45 -> 8868.2 | L17: =IF(K17>0,(ROUND(K17/$K$21,2)*100&"%"),"-") -> 15% | M17: =K17/$E$85 -> 1.1269793
H18: Sponsor Preferred Equity | K18: =Assump_CapStructure!D46 -> 12814.92 | L18: =IF(K18>0,(ROUND(K18/$K$21,2)*100&"%"),"-") -> 22% | M18: =K18/$E$85 -> 1.6285322 | N18: =TEXT(Assump_CapStructure!$F$28,"0.00%")&" accreting" -> 8.00% accreting
H19: Sponsor Common Equity | K19: =Assump_CapStructure!D47 -> 1423.88 | L19: =IF(K19>0,(ROUND(K19/$K$21,2)*100&"%"),"-") -> 2% | M19: =K19/$E$85 -> 0.18094802
H20: Total Equity | K20: =SUM(K17:K19) -> 23107 | L20: =IF(K20>0,(ROUND(K20/$K$21,2)*100&"%"),"-") -> 39% | M20: =K20/$E$85 -> 2.9364595
H21: Total Sources | K21: =K16+K20 -> 58583 | L21: =IF(K21>0,(ROUND(K21/$K$21,2)*100&"%"),"-") -> 100% | M21: =K21/$E$85 -> 7.4447833
A23: Check: Total Sources - Total Uses (must be 0) | D23: =K21-D15 -> 0
A26: FINANCIAL SUMMARY
A27: Pro Forma for the Transaction
B29: =C29-1 -> 2022 | C29: =D29-1 -> 2023 | D29: =E29-1 -> 2024 | E29: =F29-1 -> 2025 | F29: =Assump_CapStructure!$F$10 -> 2026 | G29: =F29+1 -> 2027 | H29: =G29+1 -> 2028 | I29: =H29+1 -> 2029 | J29: =I29+1 -> 2030 | K29: =J29+1 -> 2031 | L29: =K29+1 -> 2032 | M29: =L29+1 -> 2033
A30: ="FYE "&Assump_CapStructure!$F$9 -> FYE September 30, | B30: ="FY"&TEXT(B29,"0")&IF(B29<Assump_CapStructure!$F$10,"A","E") -> FY2022A | C30: ="FY"&TEXT(C29,"0")&IF(C29<Assump_CapStructure!$F$10,"A","E") -> FY2023A | D30: ="FY"&TEXT(D29,"0")&IF(D29<Assump_CapStructure!$F$10,"A","E") -> FY2024A | E30: ="FY"&TEXT(E29,"0")&IF(E29<Assump_CapStructure!$F$10,"A","E") -> FY2025A | F30: ="FY"&TEXT(F29,"0")&IF(F29<Assump_CapStructure!$F$10,"A","E") -> FY2026E | G30: ="FY"&TEXT(G29,"0")&IF(G29<Assump_CapStructure!$F$10,"A","E") -> FY2027E | H30: ="FY"&TEXT(H29,"0")&IF(H29<Assump_CapStructure!$F$10,"A","E") -> FY2028E | I30: ="FY"&TEXT(I29,"0")&IF(I29<Assump_CapStructure!$F$10,"A","E") -> FY2029E | ... M30: ="FY"&TEXT(M29,"0")&IF(M29<Assump_CapStructure!$F$10,"A","E") -> FY2033E | N30: CAGR FY25-30
A31: Revenue | B31: =B75 -> 35245 | C31: =C75 -> 38240 | D31: =D75 -> 40516 | E31: =E75 -> 42624 | F31: =F75 -> 46033.92 | G31: =G75 -> 49348.362 | H31: =H75 -> 52556.006 | I31: =I75 -> 55709.366 | ... M31: =M75 -> 67068.656 | N31: =(J31/E31)^(1/5)-1 -> 0.066363557
A32: % Growth | C32: =IF(B31=0,0,C31/B31-1) -> 0.084976592 | D32: =IF(C31=0,0,D31/C31-1) -> 0.059518828 | E32: =IF(D31=0,0,E31/D31-1) -> 0.052028828 | F32: =IF(E31=0,0,F31/E31-1) -> 0.08 | G32: =IF(F31=0,0,G31/F31-1) -> 0.072 | H32: =IF(G31=0,0,H31/G31-1) -> 0.065 | I32: =IF(H31=0,0,I31/H31-1) -> 0.06 | J32: =IF(I31=0,0,J31/I31-1) -> 0.055 | ... M32: =IF(L31=0,0,M31/L31-1) -> 0.04
A33: Adj. EBITDA | B33: =B85 -> 6287 | C33: =C85 -> 6961 | D33: =D85 -> 7923 | E33: =E85 -> 7869 | F33: =F85 -> 8746.4448 | G33: =G85 -> 9524.2339 | H33: =H85 -> 10300.977 | I33: =I85 -> 11030.454 | ... M33: =M85 -> 13547.869 | N33: =(J33/E33)^(1/5)-1 -> 0.083573126
A34: % Margin | B34: =B33/B31 -> 0.17837991 | C34: =C33/C31 -> 0.18203452 | D34: =D33/D31 -> 0.19555237 | E34: =E33/E31 -> 0.1846143 | F34: =F33/F31 -> 0.19 | G34: =G33/G31 -> 0.193 | H34: =H33/H31 -> 0.196 | I34: =I33/I31 -> 0.198 | ... M34: =M33/M31 -> 0.202
A35: Capex | B35: =Assump_Operating!B128 -> 1058 | C35: =Assump_Operating!C128 -> 1032 | D35: =Assump_Operating!D128 -> 1116 | E35: =Assump_Operating!E128 -> 1175 | F35: =Assump_Operating!F128 -> 1288.9498 | G35: =Assump_Operating!G128 -> 1381.7541 | H35: =Assump_Operating!H128 -> 1471.5682 | I35: =Assump_Operating!I128 -> 1559.8623 | ... M35: =Assump_Operating!M128 -> 1877.9224
A36: % of Revenue | B36: =B35/B31 -> 0.030018442 | C36: =C35/C31 -> 0.026987448 | D36: =D35/D31 -> 0.027544674 | E36: =E35/E31 -> 0.027566629 | F36: =F35/F31 -> 0.028 | G36: =G35/G31 -> 0.028 | H36: =H35/H31 -> 0.028 | I36: =I35/I31 -> 0.028 | ... M36: =M35/M31 -> 0.028
A37: Net Working Capital | B37: =B306 -> 4535 | C37: =C306 -> 5102 | D37: =D306 -> 5053 | E37: =E306 -> 5128 | F37: =F306 -> 5667.8476 | G37: =G306 -> 5999.9496 | H37: =H306 -> 6453.0136 | I37: =I306 -> 6884.6856 | ... M37: =M306 -> 8066.8894
A38: % of Revenue | B38: =B37/B31 -> 0.12867073 | C38: =C37/C31 -> 0.1334205 | D38: =D37/D31 -> 0.12471616 | E38: =E37/E31 -> 0.12030781 | F38: =F37/F31 -> 0.12312329 | G38: =G37/G31 -> 0.12158356 | H38: =H37/H31 -> 0.12278356 | I38: =I37/I31 -> 0.12358219 | ... M38: =M37/M31 -> 0.12027808
A40: FREE CASH FLOW
A41: EBITDA | F41: =F85 -> 8746.4448 | G41: =G85 -> 9524.2339 | H41: =H85 -> 10300.977 | I41: =I85 -> 11030.454 | J41: =J85 -> 11754.676 | K41: =K85 -> 12342.41 | L41: =L85 -> 13026.797 | M41: =M85 -> 13547.869
A42: Other (management fee) | F42: =-F93 -> 0 | G42: =-G93 -> 0 | H42: =-H93 -> 0 | I42: =-I93 -> 0 | J42: =-J93 -> 0 | K42: =-K93 -> 0 | L42: =-L93 -> 0 | M42: =-M93 -> 0
A43: Capex | F43: =-F35 -> -1288.9498 | G43: =-G35 -> -1381.7541 | H43: =-H35 -> -1471.5682 | I43: =-I35 -> -1559.8623 | J43: =-J35 -> -1645.6547 | K43: =-K35 -> -1727.9374 | L43: =-L35 -> -1805.6946 | M43: =-M35 -> -1877.9224
A44: (Inc)/Dec in Working Capital | F44: =F179 -> -356.84757 | G44: =G179 -> -332.10207 | H44: =H179 -> -453.06393 | I44: =I179 -> -431.67199 | J44: =J179 -> -425.43488 | K44: =K179 -> -141.99005 | L44: =L179 -> -449.65851 | M44: =M179 -> -165.12035
A45: Cash Interest, net | F45: =-('Debt Schedules'!F116-F106) -> -2665.115 | G45: =-('Debt Schedules'!G116-G106) -> -2428.3218 | H45: =-('Debt Schedules'!H116-H106) -> -2135.0824 | I45: =-('Debt Schedules'!I116-I106) -> -1791.4986 | J45: =-('Debt Schedules'!J116-J106) -> -1393.9077 | K45: =-('Debt Schedules'!K116-K106) -> -936.93423 | L45: =-('Debt Schedules'!L116-L106) -> -294.53899 | M45: =-('Debt Schedules'!M116-M106) -> 34.769477
A46: Cash Taxes | F46: =-F109 -> -338.3035 | G46: =-G109 -> -574.26513 | H46: =-H109 -> -825.13958 | I46: =-I109 -> -1076.9407 | J46: =-J109 -> -1341.775 | K46: =-K109 -> -1712.4468 | L46: =-L109 -> -2062.3308 | M46: =-M109 -> -2340.2946
A47: Cash Available for Debt Service | F47: =SUM(F41:F46) -> 4097.229 | G47: =SUM(G41:G46) -> 4807.7908 | H47: =SUM(H41:H46) -> 5416.1231 | I47: =SUM(I41:I46) -> 6170.481 | J47: =SUM(J41:J46) -> 6947.904 | K47: =SUM(K41:K46) -> 7823.1016 | L47: =SUM(L41:L46) -> 8414.5738 | M47: =SUM(M41:M46) -> 9199.3008
A48: Cumulative | F48: =SUM($F47:F47) -> 4097.229 | G48: =SUM($F47:G47) -> 8905.0197 | H48: =SUM($F47:H47) -> 14321.143 | I48: =SUM($F47:I47) -> 20491.624 | J48: =SUM($F47:J47) -> 27439.528 | K48: =SUM($F47:K47) -> 35262.629 | L48: =SUM($F47:L47) -> 43677.203 | M48: =SUM($F47:M47) -> 52876.504
A50: DEBT BALANCES (END OF PERIOD) | E50: Closing
A51: Cash | E51: =E116 -> 1100 | F51: =F116 -> 1918.2645 | G51: =G116 -> 2682.6776 | H51: =H116 -> 3369.0503 | I51: =I116 -> 4089.4156 | J51: =J116 -> 4838.3098 | K51: =K116 -> 6830.7057 | L51: =L116 -> 8122.6397 | M51: =M116 -> 15436.396
A52: Revolver | E52: =$K$7 -> 0 | F52: ='Debt Schedules'!F12 -> 0 | G52: ='Debt Schedules'!G12 -> 0 | H52: ='Debt Schedules'!H12 -> 0 | I52: ='Debt Schedules'!I12 -> 0 | J52: ='Debt Schedules'!J12 -> 0 | K52: ='Debt Schedules'!K12 -> 0 | L52: ='Debt Schedules'!L12 -> 0 | M52: ='Debt Schedules'!M12 -> 0
A53: Term Loan A (incl. Term Loan B) | E53: =$K$8+$K$9 -> 23607 | F53: ='Debt Schedules'!F25+'Debt Schedules'!F35 -> 20328.036 | G53: ='Debt Schedules'!G25+'Debt Schedules'!G35 -> 16284.658 | H53: ='Debt Schedules'!H25+'Debt Schedules'!H35 -> 11554.908 | I53: ='Debt Schedules'!I25+'Debt Schedules'!I35 -> 6104.7919 | J53: ='Debt Schedules'!J25+'Debt Schedules'!J35 -> 0 | K53: ='Debt Schedules'!K25+'Debt Schedules'!K35 -> 0 | L53: ='Debt Schedules'!L25+'Debt Schedules'!L35 -> 0 | M53: ='Debt Schedules'!M25+'Debt Schedules'!M35 -> 0
A54: Second Lien | E54: =$K$10 -> 0 | F54: ='Debt Schedules'!F45 -> 0 | G54: ='Debt Schedules'!G45 -> 0 | H54: ='Debt Schedules'!H45 -> 0 | I54: ='Debt Schedules'!I45 -> 0 | J54: ='Debt Schedules'!J45 -> 0 | K54: ='Debt Schedules'!K45 -> 0 | L54: ='Debt Schedules'!L45 -> 0 | M54: ='Debt Schedules'!M45 -> 0
A55: Total Secured Debt | E55: =SUM(E52:E54) -> 23607 | F55: =SUM(F52:F54) -> 20328.036 | G55: =SUM(G52:G54) -> 16284.658 | H55: =SUM(H52:H54) -> 11554.908 | I55: =SUM(I52:I54) -> 6104.7919 | J55: =SUM(J52:J54) -> 0 | K55: =SUM(K52:K54) -> 0 | L55: =SUM(L52:L54) -> 0 | M55: =SUM(M52:M54) -> 0
A56: Senior Notes | E56: =$K$11 -> 0 | F56: ='Debt Schedules'!F55 -> 0 | G56: ='Debt Schedules'!G55 -> 0 | H56: ='Debt Schedules'!H55 -> 0 | I56: ='Debt Schedules'!I55 -> 0 | J56: ='Debt Schedules'!J55 -> 0 | K56: ='Debt Schedules'!K55 -> 0 | L56: ='Debt Schedules'!L55 -> 0 | M56: ='Debt Schedules'!M55 -> 0
A57: Total Senior Debt | E57: =E55+E56 -> 23607 | F57: =F55+F56 -> 20328.036 | G57: =G55+G56 -> 16284.658 | H57: =H55+H56 -> 11554.908 | I57: =I55+I56 -> 6104.7919 | J57: =J55+J56 -> 0 | K57: =K55+K56 -> 0 | L57: =L55+L56 -> 0 | M57: =M55+M56 -> 0
A58: % Cumulative Paydown | E58: =IF($E57=0,0,1-E57/$E57) -> 0 | F58: =IF($E57=0,0,1-F57/$E57) -> 0.13889797 | G58: =IF($E57=0,0,1-G57/$E57) -> 0.31017673 | H58: =IF($E57=0,0,1-H57/$E57) -> 0.51053045 | I58: =IF($E57=0,0,1-I57/$E57) -> 0.74139908 | J58: =IF($E57=0,0,1-J57/$E57) -> 1 | K58: =IF($E57=0,0,1-K57/$E57) -> 1 | L58: =IF($E57=0,0,1-L57/$E57) -> 1 | M58: =IF($E57=0,0,1-M57/$E57) -> 1
A59: Mezzanine Debt (incl. sub. notes / other) | E59: =$K$12+$K$14+$K$15 -> 7869 | F59: ='Debt Schedules'!F65+'Debt Schedules'!F85+'Debt Schedules'!F95 -> 8026.38 | G59: ='Debt Schedules'!G65+'Debt Schedules'!G85+'Debt Schedules'!G95 -> 8186.9076 | H59: ='Debt Schedules'!H65+'Debt Schedules'!H85+'Debt Schedules'!H95 -> 8350.6458 | I59: ='Debt Schedules'!I65+'Debt Schedules'!I85+'Debt Schedules'!I95 -> 8517.6587 | J59: ='Debt Schedules'!J65+'Debt Schedules'!J85+'Debt Schedules'!J95 -> 8593.7939 | K59: ='Debt Schedules'!K65+'Debt Schedules'!K85+'Debt Schedules'!K95 -> 2934.9641 | L59: ='Debt Schedules'!L65+'Debt Schedules'!L85+'Debt Schedules'!L95 -> 58.699281 | M59: ='Debt Schedules'!M65+'Debt Schedules'!M85+'Debt Schedules'!M95 -> 1.1739856
A60: % Cumulative Paydown | E60: =IF($E59=0,0,1-E59/$E59) -> 0 | F60: =IF($E59=0,0,1-F59/$E59) -> -0.02 | G60: =IF($E59=0,0,1-G59/$E59) -> -0.0404 | H60: =IF($E59=0,0,1-H59/$E59) -> -0.061208 | I60: =IF($E59=0,0,1-I59/$E59) -> -0.08243216 | J60: =IF($E59=0,0,1-J59/$E59) -> -0.092107498 | K60: =IF($E59=0,0,1-K59/$E59) -> 0.62702198 | L60: =IF($E59=0,0,1-L59/$E59) -> 0.99254044 | M60: =IF($E59=0,0,1-M59/$E59) -> 0.99985081
A61: Seller Note (accreted) | E61: =$K$13 -> 4000 | F61: ='Debt Schedules'!F75 -> 4240 | G61: ='Debt Schedules'!G75 -> 4494.4 | H61: ='Debt Schedules'!H75 -> 4764.064 | I61: ='Debt Schedules'!I75 -> 5049.9078 | J61: ='Debt Schedules'!J75 -> 5352.9023 | K61: ='Debt Schedules'!K75 -> 5674.0764 | L61: ='Debt Schedules'!L75 -> 1826.8454 | M61: ='Debt Schedules'!M75 -> 109.61072
A62: Total Debt | E62: =E57+E59+E61 -> 35476 | F62: =F57+F59+F61 -> 32594.416 | G62: =G57+G59+G61 -> 28965.965 | H62: =H57+H59+H61 -> 24669.617 | I62: =I57+I59+I61 -> 19672.358 | J62: =J57+J59+J61 -> 13946.696 | K62: =K57+K59+K61 -> 8609.0405 | L62: =L57+L59+L61 -> 1885.5446 | M62: =M57+M59+M61 -> 110.78471
A63: % Cumulative Paydown | E63: =IF($E62=0,0,1-E62/$E62) -> 0 | F63: =IF($E62=0,0,1-F62/$E62) -> 0.081226307 | G63: =IF($E62=0,0,1-G62/$E62) -> 0.18350531 | H63: =IF($E62=0,0,1-H62/$E62) -> 0.30461108 | I63: =IF($E62=0,0,1-I62/$E62) -> 0.44547417 | J63: =IF($E62=0,0,1-J62/$E62) -> 0.60686954 | K63: =IF($E62=0,0,1-K62/$E62) -> 0.75732776 | L63: =IF($E62=0,0,1-L62/$E62) -> 0.94685013 | M63: =IF($E62=0,0,1-M62/$E62) -> 0.99687719
A65: CREDIT STATISTICS
A66: Total Senior Debt / EBITDA | F66: =F57/F85 -> 2.3241484 | G66: =G57/G85 -> 1.7098129 | H66: =H57/H85 -> 1.1217293 | I66: =I57/I85 -> 0.55344881 | J66: =J57/J85 -> 0 | K66: =K57/K85 -> 0 | L66: =L57/L85 -> 0 | M66: =M57/M85 -> 0
A67: Total Debt / EBITDA | F67: =F62/F85 -> 3.7265902 | G67: =G62/G85 -> 3.0412909 | H67: =H62/H85 -> 2.3948813 | I67: =I62/I85 -> 1.7834586 | J67: =J62/J85 -> 1.1864807 | K67: =K62/K85 -> 0.69751697 | L67: =L62/L85 -> 0.14474354 | M67: =M62/M85 -> 0.0081772794
A68: (EBITDA - Mgmt Fee - Capex - Taxes) / (Principal + Cash Interest) (1) | F68: =IF((-F194+'Debt Schedules'!F116)=0,0,(F85-F93-F35-F109)/(-F194+'Debt Schedules'!F116)) -> 1.4134312 | G68: =IF((-G194+'Debt Schedules'!G116)=0,0,(G85-G93-G35-G109)/(-G194+'Debt Schedules'!G116)) -> 1.574021 | H68: =IF((-H194+'Debt Schedules'!H116)=0,0,(H85-H93-H35-H109)/(-H194+'Debt Schedules'!H116)) -> 1.7698344 | I68: =IF((-I194+'Debt Schedules'!I116)=0,0,(I85-I93-I35-I109)/(-I194+'Debt Schedules'!I116)) -> 2.0052255 | J68: =IF((-J194+'Debt Schedules'!J116)=0,0,(J85-J93-J35-J109)/(-J194+'Debt Schedules'!J116)) -> 2.3099045 | K68: =IF((-K194+'Debt Schedules'!K116)=0,0,(K85-K93-K35-K109)/(-K194+'Debt Schedules'!K116)) -> 9.0346791 | L68: =IF((-L194+'Debt Schedules'!L116)=0,0,(L85-L93-L35-L109)/(-L194+'Debt Schedules'!L116)) -> 25.24148 | M68: =IF((-M194+'Debt Schedules'!M116)=0,0,(M85-M93-M35-M109)/(-M194+'Debt Schedules'!M116)) -> 200.82372
A69: EBITDA / Cash Interest | F69: =IF('Debt Schedules'!F116=0,0,F85/'Debt Schedules'!F116) -> 3.2683367 | G69: =IF('Debt Schedules'!G116=0,0,G85/'Debt Schedules'!G116) -> 3.8914061 | H69: =IF('Debt Schedules'!H116=0,0,H85/'Debt Schedules'!H116) -> 4.7647594 | I69: =IF('Debt Schedules'!I116=0,0,I85/'Debt Schedules'!I116) -> 6.0434585 | J69: =IF('Debt Schedules'!J116=0,0,J85/'Debt Schedules'!J116) -> 8.1925433 | K69: =IF('Debt Schedules'!K116=0,0,K85/'Debt Schedules'!K116) -> 12.52633 | L69: =IF('Debt Schedules'!L116=0,0,L85/'Debt Schedules'!L116) -> 35.901719 | M69: =IF('Debt Schedules'!M116=0,0,M85/'Debt Schedules'!M116) -> 291.62218
A70: (EBITDA - Capex) / Cash Interest | F70: =IF('Debt Schedules'!F116=0,0,(F85-F35)/'Debt Schedules'!F116) -> 2.7866871 | G70: =IF('Debt Schedules'!G116=0,0,(G85-G35)/'Debt Schedules'!G116) -> 3.3268498 | H70: =IF('Debt Schedules'!H116=0,0,(H85-H35)/'Debt Schedules'!H116) -> 4.0840795 | I70: =IF('Debt Schedules'!I116=0,0,(I85-I35)/'Debt Schedules'!I116) -> 5.188828 | J70: =IF('Debt Schedules'!J116=0,0,(J85-J35)/'Debt Schedules'!J116) -> 7.0455872 | K70: =IF('Debt Schedules'!K116=0,0,(K85-K35)/'Debt Schedules'!K116) -> 10.772644 | L70: =IF('Debt Schedules'!L116=0,0,(L85-L35)/'Debt Schedules'!L116) -> 30.925243 | M70: =IF('Debt Schedules'!M116=0,0,(M85-M35)/'Debt Schedules'!M116) -> 251.1993
A71: (1) FY2026E reflects projection from CIM; Fixed Charge Coverage per the senior credit agreement definition.
A73: HISTORICAL AND PROJECTED INCOME STATEMENT
A74: Fiscal Year Ended September 30, | B74: =Model!B30 -> FY2022A | C74: =Model!C30 -> FY2023A | D74: =Model!D30 -> FY2024A | E74: =Model!E30 -> FY2025A | F74: =Model!F30 -> FY2026E | G74: =Model!G30 -> FY2027E | H74: =Model!H30 -> FY2028E | I74: =Model!I30 -> FY2029E | ... M74: =Model!M30 -> FY2033E
A75: Total Revenue | B75: =Assump_Operating!B24 -> 35245 | C75: =Assump_Operating!C24 -> 38240 | D75: =Assump_Operating!D24 -> 40516 | E75: =Assump_Operating!E24 -> 42624 | F75: =Assump_Operating!F24 -> 46033.92 | G75: =Assump_Operating!G24 -> 49348.362 | H75: =Assump_Operating!H24 -> 52556.006 | I75: =Assump_Operating!I24 -> 55709.366 | ... M75: =Assump_Operating!M24 -> 67068.656
A76: % Growth | C76: =C75/B75-1 -> 0.084976592 | D76: =D75/C75-1 -> 0.059518828 | E76: =E75/D75-1 -> 0.052028828 | F76: =F75/E75-1 -> 0.08 | G76: =G75/F75-1 -> 0.072 | H76: =H75/G75-1 -> 0.065 | I76: =I75/H75-1 -> 0.06 | J76: =J75/I75-1 -> 0.055 | ... M76: =M75/L75-1 -> 0.04
A77: Total COGS (excl. Depreciation) | B77: =Assump_Operating!B43 -> 23240 | C77: =Assump_Operating!C43 -> 25026 | D77: =Assump_Operating!D43 -> 26224 | E77: =Assump_Operating!E43 -> 28098 | F77: =Assump_Operating!F43 -> 29922.048 | G77: =Assump_Operating!G43 -> 31977.739 | H77: =Assump_Operating!H43 -> 33951.18 | I77: =Assump_Operating!I43 -> 35932.541 | ... M77: =Assump_Operating!M43 -> 43125.146
A78: % of Revenue | B78: =B77/B75 -> 0.65938431 | C78: =C77/C75 -> 0.65444561 | D78: =D77/D75 -> 0.64725047 | E78: =E77/E75 -> 0.65920608 | F78: =F77/F75 -> 0.65 | G78: =G77/G75 -> 0.648 | H78: =H77/H75 -> 0.646 | I78: =I77/I75 -> 0.645 | ... M78: =M77/M75 -> 0.643
B79: ______ | C79: ______ | D79: ______ | E79: ______ | F79: ______ | G79: ______ | H79: ______ | I79: ______ | J79: ______ | K79: ______ | L79: ______ | M79: ______
A80: Gross Profit | B80: =B75-B77 -> 12005 | C80: =C75-C77 -> 13214 | D80: =D75-D77 -> 14292 | E80: =E75-E77 -> 14526 | F80: =F75-F77 -> 16111.872 | G80: =G75-G77 -> 17370.624 | H80: =H75-H77 -> 18604.826 | I80: =I75-I77 -> 19776.825 | ... M80: =M75-M77 -> 23943.51
A81: % Margin | B81: =B80/B75 -> 0.34061569 | C81: =C80/C75 -> 0.34555439 | D81: =D80/D75 -> 0.35274953 | E81: =E80/E75 -> 0.34079392 | F81: =F80/F75 -> 0.35 | G81: =G80/G75 -> 0.352 | H81: =H80/H75 -> 0.354 | I81: =I80/I75 -> 0.355 | ... M81: =M80/M75 -> 0.357
A82: SG&A (excl. Amortization) | B82: =Assump_Operating!B62 -> 5718 | C82: =Assump_Operating!C62 -> 6253 | D82: =Assump_Operating!D62 -> 6369 | E82: =Assump_Operating!E62 -> 6657 | F82: =Assump_Operating!F62 -> 7365.4272 | G82: =Assump_Operating!G62 -> 7846.3896 | H82: =Assump_Operating!H62 -> 8303.8489 | I82: =Assump_Operating!I62 -> 8746.3705 | ... M82: =Assump_Operating!M62 -> 10395.642
A83: % of Revenue | B83: =B82/B75 -> 0.16223578 | C83: =C82/C75 -> 0.16351987 | D83: =D82/D75 -> 0.15719716 | E83: =E82/E75 -> 0.15617962 | F83: =F82/F75 -> 0.16 | G83: =G82/G75 -> 0.159 | H83: =H82/H75 -> 0.158 | I83: =I82/I75 -> 0.157 | ... M83: =M82/M75 -> 0.155
B84: ______ | C84: ______ | D84: ______ | E84: ______ | F84: ______ | G84: ______ | H84: ______ | I84: ______ | J84: ______ | K84: ______ | L84: ______ | M84: ______
A85: EBITDA | B85: =B80-B82 -> 6287 | C85: =C80-C82 -> 6961 | D85: =D80-D82 -> 7923 | E85: =E80-E82 -> 7869 | F85: =F80-F82 -> 8746.4448 | G85: =G80-G82 -> 9524.2339 | H85: =H80-H82 -> 10300.977 | I85: =I80-I82 -> 11030.454 | ... M85: =M80-M82 -> 13547.869
A86: % Margin | B86: =B85/B75 -> 0.17837991 | C86: =C85/C75 -> 0.18203452 | D86: =D85/D75 -> 0.19555237 | E86: =E85/E75 -> 0.1846143 | F86: =F85/F75 -> 0.19 | G86: =G85/G75 -> 0.193 | H86: =H85/H75 -> 0.196 | I86: =I85/I75 -> 0.198 | ... M86: =M85/M75 -> 0.202
A87: % Growth | C87: =C85/B85-1 -> 0.10720534 | D87: =D85/C85-1 -> 0.13819853 | E87: =E85/D85-1 -> -0.0068156002 | F87: =F85/E85-1 -> 0.11150652 | G87: =G85/F85-1 -> 0.088926316 | H87: =H85/G85-1 -> 0.081554404 | I87: =I85/H85-1 -> 0.070816327 | J87: =J85/I85-1 -> 0.065656566 | ... M87: =M85/L85-1 -> 0.04
A88: Depreciation & Amortization | B88: =Assump_Operating!B100 -> 976 | C88: =Assump_Operating!C100 -> 1015 | D88: =Assump_Operating!D100 -> 1104 | E88: =Assump_Operating!E100 -> 1153 | F88: =Assump_Operating!F100 -> 1242.9158 | G88: =Assump_Operating!G100 -> 1332.4058 | H88: =Assump_Operating!H100 -> 1419.0122 | I88: =Assump_Operating!I100 -> 1504.1529 | ... M88: =Assump_Operating!M100 -> 1810.8537
A89: % of Revenue | B89: =B88/B75 -> 0.027691871 | C89: =C88/C75 -> 0.026542887 | D89: =D88/D75 -> 0.027248494 | E89: =E88/E75 -> 0.027050488 | F89: =F88/F75 -> 0.027 | G89: =G88/G75 -> 0.027 | H89: =H88/H75 -> 0.027 | I89: =I88/I75 -> 0.027 | ... M89: =M88/M75 -> 0.027
A90: Amort. of Transaction Fees | F90: =IF(F$29-Assump_CapStructure!$F$10<Assump_CapStructure!$F$27,$D$14/Assump_CapStructure!$F$27,0) -> 480 | G90: =IF(G$29-Assump_CapStructure!$F$10<Assump_CapStructure!$F$27,$D$14/Assump_CapStructure!$F$27,0) -> 480 | H90: =IF(H$29-Assump_CapStructure!$F$10<Assump_CapStructure!$F$27,$D$14/Assump_CapStructure!$F$27,0) -> 480 | I90: =IF(I$29-Assump_CapStructure!$F$10<Assump_CapStructure!$F$27,$D$14/Assump_CapStructure!$F$27,0) -> 480 | J90: =IF(J$29-Assump_CapStructure!$F$10<Assump_CapStructure!$F$27,$D$14/Assump_CapStructure!$F$27,0) -> 480 | K90: =IF(K$29-Assump_CapStructure!$F$10<Assump_CapStructure!$F$27,$D$14/Assump_CapStructure!$F$27,0) -> 0 | L90: =IF(L$29-Assump_CapStructure!$F$10<Assump_CapStructure!$F$27,$D$14/Assump_CapStructure!$F$27,0) -> 0 | M90: =IF(M$29-Assump_CapStructure!$F$10<Assump_CapStructure!$F$27,$D$14/Assump_CapStructure!$F$27,0) -> 0
A91: Adj. EBIT | B91: =B85-B88-B90 -> 5311 | C91: =C85-C88-C90 -> 5946 | D91: =D85-D88-D90 -> 6819 | E91: =E85-E88-E90 -> 6716 | F91: =F85-F88-F90 -> 7023.529 | G91: =G85-G88-G90 -> 7711.8281 | H91: =H85-H88-H90 -> 8401.965 | I91: =I85-I88-I90 -> 9046.3016 | ... M91: =M85-M88-M90 -> 11737.015
A92: % Margin | B92: =B91/B75 -> 0.15068804 | C92: =C91/C75 -> 0.15549163 | D92: =D91/D75 -> 0.16830388 | E92: =E91/E75 -> 0.15756381 | F92: =F91/F75 -> 0.15257291 | G92: =G91/G75 -> 0.15627323 | H92: =H91/H75 -> 0.15986689 | I92: =I91/I75 -> 0.16238385 | ... M92: =M91/M75 -> 0.175
A93: Other Expenses (Management Fee) | F93: =Assump_CapStructure!$F$20*Assump_CapStructure!$F$21 -> 0 | G93: =Assump_CapStructure!$F$20*Assump_CapStructure!$F$21 -> 0 | H93: =Assump_CapStructure!$F$20*Assump_CapStructure!$F$21 -> 0 | I93: =Assump_CapStructure!$F$20*Assump_CapStructure!$F$21 -> 0 | J93: =Assump_CapStructure!$F$20*Assump_CapStructure!$F$21 -> 0 | K93: =Assump_CapStructure!$F$20*Assump_CapStructure!$F$21 -> 0 | L93: =Assump_CapStructure!$F$20*Assump_CapStructure!$F$21 -> 0 | M93: =Assump_CapStructure!$F$20*Assump_CapStructure!$F$21 -> 0
A94: Interest Expense:
A95: Revolver | F95: ='Debt Schedules'!F13 -> 0 | G95: ='Debt Schedules'!G13 -> 0 | H95: ='Debt Schedules'!H13 -> 0 | I95: ='Debt Schedules'!I13 -> 0 | J95: ='Debt Schedules'!J13 -> 0 | K95: ='Debt Schedules'!K13 -> 0 | L95: ='Debt Schedules'!L13 -> 0 | M95: ='Debt Schedules'!M13 -> 0
A96: Revolver Commitment Fee | F96: ='Debt Schedules'!F18 -> 40 | G96: ='Debt Schedules'!G18 -> 40 | H96: ='Debt Schedules'!H18 -> 40 | I96: ='Debt Schedules'!I18 -> 40 | J96: ='Debt Schedules'!J18 -> 40 | K96: ='Debt Schedules'!K18 -> 40 | L96: ='Debt Schedules'!L18 -> 40 | M96: ='Debt Schedules'!M18 -> 40
A97: Term Loan A | F97: ='Debt Schedules'!F26 -> 1770.525 | G97: ='Debt Schedules'!G26 -> 1524.6027 | H97: ='Debt Schedules'!H26 -> 1221.3493 | I97: ='Debt Schedules'!I26 -> 866.61807 | J97: ='Debt Schedules'!J26 -> 457.85939 | K97: ='Debt Schedules'!K26 -> 0 | L97: ='Debt Schedules'!L26 -> 0 | M97: ='Debt Schedules'!M26 -> 0
A98: Term Loan B | F98: ='Debt Schedules'!F36 -> 0 | G98: ='Debt Schedules'!G36 -> 0 | H98: ='Debt Schedules'!H36 -> 0 | I98: ='Debt Schedules'!I36 -> 0 | J98: ='Debt Schedules'!J36 -> 0 | K98: ='Debt Schedules'!K36 -> 0 | L98: ='Debt Schedules'!L36 -> 0 | M98: ='Debt Schedules'!M36 -> 0
A99: Second Lien | F99: ='Debt Schedules'!F46 -> 0 | G99: ='Debt Schedules'!G46 -> 0 | H99: ='Debt Schedules'!H46 -> 0 | I99: ='Debt Schedules'!I46 -> 0 | J99: ='Debt Schedules'!J46 -> 0 | K99: ='Debt Schedules'!K46 -> 0 | L99: ='Debt Schedules'!L46 -> 0 | M99: ='Debt Schedules'!M46 -> 0
A100: Senior Notes / Sub. Notes / Other | F100: ='Debt Schedules'!F58+'Debt Schedules'!F88+'Debt Schedules'!F98 -> 0 | G100: ='Debt Schedules'!G58+'Debt Schedules'!G88+'Debt Schedules'!G98 -> 0 | H100: ='Debt Schedules'!H58+'Debt Schedules'!H88+'Debt Schedules'!H98 -> 0 | I100: ='Debt Schedules'!I58+'Debt Schedules'!I88+'Debt Schedules'!I98 -> 0 | J100: ='Debt Schedules'!J58+'Debt Schedules'!J88+'Debt Schedules'!J98 -> 0 | K100: ='Debt Schedules'!K58+'Debt Schedules'!K88+'Debt Schedules'!K98 -> 0 | L100: ='Debt Schedules'!L58+'Debt Schedules'!L88+'Debt Schedules'!L98 -> 0 | M100: ='Debt Schedules'!M58+'Debt Schedules'!M88+'Debt Schedules'!M98 -> 0
A101: Mezzanine (cash) | F101: ='Debt Schedules'!F66 -> 865.59 | G101: ='Debt Schedules'!G66 -> 882.9018 | H101: ='Debt Schedules'!H66 -> 900.55984 | I101: ='Debt Schedules'!I66 -> 918.57103 | J101: ='Debt Schedules'!J66 -> 936.94245 | K101: ='Debt Schedules'!K66 -> 945.31733 | L101: ='Debt Schedules'!L66 -> 322.84605 | M101: ='Debt Schedules'!M66 -> 6.4569209
A102: Mezzanine (PIK) | F102: ='Debt Schedules'!F67 -> 157.38 | G102: ='Debt Schedules'!G67 -> 160.5276 | H102: ='Debt Schedules'!H67 -> 163.73815 | I102: ='Debt Schedules'!I67 -> 167.01292 | J102: ='Debt Schedules'!J67 -> 170.35317 | K102: ='Debt Schedules'!K67 -> 171.87588 | L102: ='Debt Schedules'!L67 -> 58.699281 | M102: ='Debt Schedules'!M67 -> 1.1739856
A103: Seller Note (PIK) | F103: ='Debt Schedules'!F78 -> 240 | G103: ='Debt Schedules'!G78 -> 254.4 | H103: ='Debt Schedules'!H78 -> 269.664 | I103: ='Debt Schedules'!I78 -> 285.84384 | J103: ='Debt Schedules'!J78 -> 302.99447 | K103: ='Debt Schedules'!K78 -> 321.17414 | L103: ='Debt Schedules'!L78 -> 340.44459 | M103: ='Debt Schedules'!M78 -> 109.61072
A104: Memo: Preferred Equity Accretion (excluded from total) | F104: ='Debt Schedules'!F102 -> 1663.704 | G104: ='Debt Schedules'!G102 -> 1796.8003 | H104: ='Debt Schedules'!H102 -> 1940.5443 | I104: ='Debt Schedules'!I102 -> 2095.7879 | J104: ='Debt Schedules'!J102 -> 2263.4509 | K104: ='Debt Schedules'!K102 -> 2444.527 | L104: ='Debt Schedules'!L102 -> 2640.0892 | M104: ='Debt Schedules'!M102 -> 2851.2963
A105: Total Interest Expense | F105: =SUM(F95:F103) -> 3073.495 | G105: =SUM(G95:G103) -> 2862.4321 | H105: =SUM(H95:H103) -> 2595.3113 | I105: =SUM(I95:I103) -> 2278.0459 | J105: =SUM(J95:J103) -> 1908.1495 | K105: =SUM(K95:K103) -> 1478.3673 | L105: =SUM(L95:L103) -> 761.98992 | M105: =SUM(M95:M103) -> 157.24163
A106: Less: Interest on Cash Balance | F106: =F208*Assump_CapStructure!$F$26 -> 11 | G106: =G208*Assump_CapStructure!$F$26 -> 19.182645 | H106: =H208*Assump_CapStructure!$F$26 -> 26.826776 | I106: =I208*Assump_CapStructure!$F$26 -> 33.690503 | J106: =J208*Assump_CapStructure!$F$26 -> 40.894156 | K106: =K208*Assump_CapStructure!$F$26 -> 48.383098 | L106: =L208*Assump_CapStructure!$F$26 -> 68.307057 | M106: =M208*Assump_CapStructure!$F$26 -> 81.226397
A107: Net Interest Expense | F107: =F105-F106 -> 3062.495 | G107: =G105-G106 -> 2843.2494 | H107: =H105-H106 -> 2568.4846 | I107: =I105-I106 -> 2244.3554 | J107: =J105-J106 -> 1867.2553 | K107: =K105-K106 -> 1429.9842 | L107: =L105-L106 -> 693.68286 | M107: =M105-M106 -> 76.01523
A108: Pre Tax Income (Before NOL Utilization) | F108: =F91-F93-F107 -> 3961.034 | G108: =G91-G93-G107 -> 4868.5787 | H108: =H91-H93-H107 -> 5833.4804 | I108: =I91-I93-I107 -> 6801.9463 | J108: =J91-J93-J107 -> 7820.5396 | K108: =K91-K93-K107 -> 9246.2005 | L108: =L91-L93-L107 -> 10591.908 | M108: =M91-M93-M107 -> 11661
A109: Less: Income Taxes | F109: =F315 -> 338.3035 | G109: =G315 -> 574.26513 | H109: =H315 -> 825.13958 | I109: =I315 -> 1076.9407 | J109: =J315 -> 1341.775 | K109: =K315 -> 1712.4468 | L109: =L315 -> 2062.3308 | M109: =M315 -> 2340.2946
...

Sheet Assump_CapStructure
A1: =$F$7 -> Project Kestrel | U1: ="Operating Case Running: "&CHOOSE(Assump_CapStructure!$K$5,"Management Case","Case II - No Growth, No Taxes","Case III - Downside Case, No Taxes","Upside Case","Flat Case") -> Operating Case Running: Management Case
A2: ="Prepared by: "&$F$8 -> Prepared by: Halvern | U2: ="Capital Structure Case: "&CHOOSE(Assump_CapStructure!$K$15,"Base Case - Senior + Mezz","Senior Only","Senior + Seller Note Upsized","All Equity","Unitranche","Case 6","Case 7","Case 8","Case 9","Case 10") -> Capital Structure Case: Base Case - Senior + Mezz
A3: =$F$11 -> ($ in 000s)
C5: GENERAL ASSUMPTIONS | J5: Operating Case (1-5): | K5: 1
C7: Project Name | F7: Project Kestrel | I7: Operating Cases
C8: Model Prepared by | F8: Halvern | H8: 1 | I8: Management Case | M8: Ownership Matrix (common)
C9: Fiscal Year End | F9: September 30, | H9: 2 | I9: Case II - No Growth, No Taxes | N9: Pre-MEIP | O9: Post-MEIP | P9: Post-Warrant
C10: First Projected Year | F10: 2026 | H10: 3 | I10: Case III - Downside Case, No Taxes | M10: Sponsor | N10: =1-N11 -> 0.61621154 | O10: =N10*(1-O12) -> 0.55459038 | P10: =O10*(1-P13) -> 0.52686086
C11: Currency / Units | F11: ($ in 000s) | H11: 4 | I11: Upside Case | M11: Rollover | N11: =Model!E335 -> 0.38378846 | O11: =N11*(1-O12) -> 0.34540962 | P11: =O11*(1-P13) -> 0.32813914
H12: 5 | I12: Flat Case | M12: MEIP | N12: 0 | O12: =$F$29 -> 0.1 | P12: =O12*(1-P13) -> 0.095
M13: Warrant | N13: 0 | O13: 0 | P13: 0.05
M14: Total | N14: =SUM(N10:N13) -> 1 | O14: =SUM(O10:O13) -> 1 | P14: =SUM(P10:P13) -> 1
J15: Financing Case (1-10): | K15: 1
C16: OTHER ASSUMPTIONS
C17: Debt Cash Flow Sweep? (1=Yes, 0=No) | F17: 1 | I17: Financing Cases
C18: Excess Cash Flow Sweep % | F18: 0.5 | H18: 1 | I18: Base Case - Senior + Mezz
C19: Minimum Cash Balance | F19: 1000 | H19: 2 | I19: Senior Only
C20: Management Fee Switch (1=Yes, 0=No) | F20: 0 | H20: 3 | I20: Senior + Seller Note Upsized
C21: Management Fee (annual) | F21: 250 | H21: 4 | I21: All Equity
C22: Goodwill Step Up Switch (1=Yes, 0=No) | F22: 1 | H22: 5 | I22: Unitranche
C23: Tax Rate | F23: 0.26 | H23: 6 | I23: Case 6
C24: Company's Existing NOL | F24: 0 | H24: 7 | I24: Case 7
C25: Base Rate (L) | F25: 0.0425 | H25: 8 | I25: Case 8
C26: Interest Rate on Cash Balance | F26: 0.01 | H26: 9 | I26: Case 9
C27: Transaction Fee Amortization (yrs) | F27: 5 | H27: 10 | I27: Case 10
C28: Preferred Equity Accretion Rate | F28: 0.08
C29: MEIP % of Common | F29: 0.1
C30: Sponsor Carried Interest | F30: 0.2
C31: Preferred % of Equity Account | F31: 0.9
C33: SOURCES OF FUNDS
C34: Tranche | D34: Selected | E34: x EBITDA | F34: % of Total | J34: Case 1 | K34: Case 2 | L34: Case 3 | M34: Case 4 | N34: Case 5 | O34: Case 6 | P34: Case 7 | Q34: Case 8 | R34: Case 9 | S34: Case 10 | U34: Cash Rate / Spread | V34: PIK Rate | W34: Basis | X34: Amort. % / yr | Y34: Term (yrs) | Z34: Commit. Fee
J35: Base Case - Senior + Mezz | K35: Senior Only | L35: Senior + Seller Note Upsized | M35: All Equity | N35: Unitranche | O35: Case 6 | P35: Case 7 | Q35: Case 8 | R35: Case 9 | S35: Case 10
C36: Revolver | D36: =CHOOSE($K$15,J36,K36,L36,M36,N36,O36,P36,Q36,R36,S36) -> 0 | E36: =IF(D36>0,D36/Model!$E$85,"-") -> - | F36: =IF($D$48>0,D36/$D$48,0) -> 0 | J36: 0 | K36: 0 | L36: 0 | M36: 0 | N36: 0 | O36: 0 | P36: 0 | Q36: 0 | R36: 1500 | S36: 0 | U36: 0.03 | V36: 0 | W36: L + | X36: 0 | Y36: 5 | Z36: 0.005
C37: Term Loan A | D37: =CHOOSE($K$15,J37,K37,L37,M37,N37,O37,P37,Q37,R37,S37) -> 23607 | E37: =IF(D37>0,D37/Model!$E$85,"-") -> 3 | F37: =IF($D$48>0,D37/$D$48,0) -> 0.40296673 | J37: 23607 | K37: 27542 | L37: 23607 | M37: 0 | N37: 0 | O37: 19672 | P37: 23607 | Q37: 23607 | R37: 23607 | S37: 21640 | U37: 0.0325 | V37: 0 | W37: L + | X37: 0.1 | Y37: 6 | Z37: 0
C38: Term Loan B | D38: =CHOOSE($K$15,J38,K38,L38,M38,N38,O38,P38,Q38,R38,S38) -> 0 | E38: =IF(D38>0,D38/Model!$E$85,"-") -> - | F38: =IF($D$48>0,D38/$D$48,0) -> 0 | J38: 0 | K38: 0 | L38: 0 | M38: 0 | N38: 31476 | O38: 0 | P38: 0 | Q38: 0 | R38: 0 | S38: 0 | U38: 0.0475 | V38: 0 | W38: L + | X38: 0.01 | Y38: 7 | Z38: 0
C39: Second Lien | D39: =CHOOSE($K$15,J39,K39,L39,M39,N39,O39,P39,Q39,R39,S39) -> 0 | E39: =IF(D39>0,D39/Model!$E$85,"-") -> - | F39: =IF($D$48>0,D39/$D$48,0) -> 0 | J39: 0 | K39: 0 | L39: 0 | M39: 0 | N39: 0 | O39: 0 | P39: 5902 | Q39: 0 | R39: 0 | S39: 0 | U39: 0.075 | V39: 0 | W39: L + | X39: 0 | Y39: 8 | Z39: 0
C40: Senior Notes | D40: =CHOOSE($K$15,J40,K40,L40,M40,N40,O40,P40,Q40,R40,S40) -> 0 | E40: =IF(D40>0,D40/Model!$E$85,"-") -> - | F40: =IF($D$48>0,D40/$D$48,0) -> 0 | J40: 0 | K40: 0 | L40: 0 | M40: 0 | N40: 0 | O40: 0 | P40: 0 | Q40: 7869 | R40: 0 | S40: 0 | U40: 0.09 | V40: 0 | W40: Fixed | X40: 0 | Y40: 8 | Z40: 0
C41: Mezzanine Debt | D41: =CHOOSE($K$15,J41,K41,L41,M41,N41,O41,P41,Q41,R41,S41) -> 7869 | E41: =IF(D41>0,D41/Model!$E$85,"-") -> 1 | F41: =IF($D$48>0,D41/$D$48,0) -> 0.13432224 | J41: 7869 | K41: 0 | L41: 7869 | M41: 0 | N41: 0 | O41: 11804 | P41: 7869 | Q41: 0 | R41: 7869 | S41: 7869 | U41: 0.11 | V41: 0.02 | W41: Fixed | X41: 0 | Y41: 8 | Z41: 0
C42: Seller Note | D42: =CHOOSE($K$15,J42,K42,L42,M42,N42,O42,P42,Q42,R42,S42) -> 4000 | E42: =IF(D42>0,D42/Model!$E$85,"-") -> 0.5083238 | F42: =IF($D$48>0,D42/$D$48,0) -> 0.068279194 | J42: 4000 | K42: 4000 | L42: 7500 | M42: 0 | N42: 4000 | O42: 4000 | P42: 4000 | Q42: 4000 | R42: 4000 | S42: 4000 | U42: 0 | V42: 0.06 | W42: Fixed | X42: 0 | Y42: 6 | Z42: 0
C43: Subordinated Notes | D43: =CHOOSE($K$15,J43,K43,L43,M43,N43,O43,P43,Q43,R43,S43) -> 0 | E43: =IF(D43>0,D43/Model!$E$85,"-") -> - | F43: =IF($D$48>0,D43/$D$48,0) -> 0 | J43: 0 | K43: 0 | L43: 0 | M43: 0 | N43: 0 | O43: 0 | P43: 0 | Q43: 0 | R43: 3934 | S43: 0 | U43: 0.1 | V43: 0.03 | W43: Fixed | X43: 0 | Y43: 8 | Z43: 0
C44: Other Debt | D44: =CHOOSE($K$15,J44,K44,L44,M44,N44,O44,P44,Q44,R44,S44) -> 0 | E44: =IF(D44>0,D44/Model!$E$85,"-") -> - | F44: =IF($D$48>0,D44/$D$48,0) -> 0 | J44: 0 | K44: 0 | L44: 0 | M44: 0 | N44: 0 | O44: 0 | P44: 0 | Q44: 0 | R44: 0 | S44: 350 | U44: 0.08 | V44: 0 | W44: Fixed | X44: 0.2 | Y44: 5 | Z44: 0
C45: Rollover Equity | D45: =CHOOSE($K$15,J45,K45,L45,M45,N45,O45,P45,Q45,R45,S45) -> 8868.2 | E45: =IF(D45>0,D45/Model!$E$85,"-") -> 1.1269793 | F45: =IF($D$48>0,D45/$D$48,0) -> 0.15137839 | J45: =Consideration!H14 -> 8868.2 | K45: =Consideration!H14 -> 8868.2 | L45: =Consideration!H14 -> 8868.2 | M45: =Consideration!H14 -> 8868.2 | N45: =Consideration!H14 -> 8868.2 | O45: =Consideration!H14 -> 8868.2 | P45: =Consideration!H14 -> 8868.2 | Q45: =Consideration!H14 -> 8868.2 | R45: =Consideration!H14 -> 8868.2 | S45: =Consideration!H14 -> 8868.2
C46: Sponsor Preferred Equity | D46: =CHOOSE($K$15,J46,K46,L46,M46,N46,O46,P46,Q46,R46,S46) -> 12814.92 | E46: =IF(D46>0,D46/Model!$E$85,"-") -> 1.6285322 | F46: =IF($D$48>0,D46/$D$48,0) -> 0.2187481 | J46: =$F$31*(J65-SUM(J36:J45)) -> 12814.92 | K46: =$F$31*(K65-SUM(K36:K45)) -> 16252.02 | L46: =$F$31*(L65-SUM(L36:L45)) -> 9664.92 | M46: =$F$31*(M65-SUM(M36:M45)) -> 44063.82 | N46: =$F$31*(N65-SUM(N36:N45)) -> 12864.42 | O46: =$F$31*(O65-SUM(O36:O45)) -> 12837.42 | P46: =$F$31*(P65-SUM(P36:P45)) -> 7570.62 | Q46: =$F$31*(Q65-SUM(Q36:Q45)) -> 12846.42 | ... S46: =$F$31*(S65-SUM(S36:S45)) -> 14261.22
C47: Sponsor Common Equity | D47: =CHOOSE($K$15,J47,K47,L47,M47,N47,O47,P47,Q47,R47,S47) -> 1423.88 | E47: =IF(D47>0,D47/Model!$E$85,"-") -> 0.18094802 | F47: =IF($D$48>0,D47/$D$48,0) -> 0.024305345 | J47: =J65-SUM(J36:J46) -> 1423.88 | K47: =K65-SUM(K36:K46) -> 1805.78 | L47: =L65-SUM(L36:L46) -> 1073.88 | M47: =M65-SUM(M36:M46) -> 4895.98 | N47: =N65-SUM(N36:N46) -> 1429.38 | O47: =O65-SUM(O36:O46) -> 1426.38 | P47: =P65-SUM(P36:P46) -> 841.18 | Q47: =Q65-SUM(Q36:Q46) -> 1427.38 | ... S47: =S65-SUM(S36:S46) -> 1584.58
C48: Total Sources | D48: =SUM(D36:D47) -> 58583 | E48: =D48/Model!$E$85 -> 7.4447833 | F48: =SUM(F36:F47) -> 1 | J48: =SUM(J36:J47) -> 58583 | K48: =SUM(K36:K47) -> 58468 | L48: =SUM(L36:L47) -> 58583 | M48: =SUM(M36:M47) -> 57828 | N48: =SUM(N36:N47) -> 58638 | O48: =SUM(O36:O47) -> 58608 | P48: =SUM(P36:P47) -> 58658 | Q48: =SUM(Q36:Q47) -> 58618 | ... S48: =SUM(S36:S47) -> 58573
C49: Check: Sources - Uses (must be 0) | D49: =D48-D65 -> 0 | J49: =J48-J65 -> 0 | K49: =K48-K65 -> 0 | L49: =L48-L65 -> 0 | M49: =M48-M65 -> 0 | N49: =N48-N65 -> 0 | O49: =O48-O65 -> 0 | P49: =P48-P65 -> 0 | Q49: =Q48-Q65 -> 0 | ... S49: =S48-S65 -> 0
C50: Revolver Size (commitment) | D50: 8000
C52: USES OF FUNDS
C53: Cash Consideration to Shareholders (incl. seller-note portion) | D53: =CHOOSE($K$15,J53,K53,L53,M53,N53,O53,P53,Q53,R53,S53) -> 39472.8 | J53: =$D$80-J55 -> 39472.8 | K53: =$D$80-K55 -> 39472.8 | L53: =$D$80-L55 -> 39472.8 | M53: =$D$80-M55 -> 39472.8 | N53: =$D$80-N55 -> 39472.8 | O53: =$D$80-O55 -> 39472.8 | P53: =$D$80-P55 -> 39472.8 | Q53: =$D$80-Q55 -> 39472.8 | ... S53: =$D$80-S55 -> 39472.8
C54: Repay Existing Debt | D54: =CHOOSE($K$15,J54,K54,L54,M54,N54,O54,P54,Q54,R54,S54) -> 6842 | J54: =$D$78 -> 6842 | K54: =$D$78 -> 6842 | L54: =$D$78 -> 6842 | M54: =$D$78 -> 6842 | N54: =$D$78 -> 6842 | O54: =$D$78 -> 6842 | P54: =$D$78 -> 6842 | Q54: =$D$78 -> 6842 | ... S54: =$D$78 -> 6842
C55: Rollover Equity | D55: =CHOOSE($K$15,J55,K55,L55,M55,N55,O55,P55,Q55,R55,S55) -> 8868.2 | J55: =J45 -> 8868.2 | K55: =K45 -> 8868.2 | L55: =L45 -> 8868.2 | M55: =M45 -> 8868.2 | N55: =N45 -> 8868.2 | O55: =O45 -> 8868.2 | P55: =P45 -> 8868.2 | Q55: =Q45 -> 8868.2 | ... S55: =S45 -> 8868.2
C56: Earnout | D56: =CHOOSE($K$15,J56,K56,L56,M56,N56,O56,P56,Q56,R56,S56) -> 0 | J56: 0 | K56: 0 | L56: 0 | M56: 0 | N56: 0 | O56: 0 | P56: 0 | Q56: 0 | R56: 0 | S56: 0
C57: Rollover Debt | D57: =CHOOSE($K$15,J57,K57,L57,M57,N57,O57,P57,Q57,R57,S57) -> 0 | J57: 0 | K57: 0 | L57: 0 | M57: 0 | N57: 0 | O57: 0 | P57: 0 | Q57: 0 | R57: 0 | S57: 0
C58: Purchase Price | D58: =CHOOSE($K$15,J58,K58,L58,M58,N58,O58,P58,Q58,R58,S58) -> 55183 | J58: =SUM(J53:J57) -> 55183 | K58: =SUM(K53:K57) -> 55183 | L58: =SUM(L53:L57) -> 55183 | M58: =SUM(M53:M57) -> 55183 | N58: =SUM(N53:N57) -> 55183 | O58: =SUM(O53:O57) -> 55183 | P58: =SUM(P53:P57) -> 55183 | Q58: =SUM(Q53:Q57) -> 55183 | ... S58: =SUM(S53:S57) -> 55183
C59: Cash to Balance Sheet | D59: =CHOOSE($K$15,J59,K59,L59,M59,N59,O59,P59,Q59,R59,S59) -> 1000 | J59: 1000 | K59: 1000 | L59: 1000 | M59: 1000 | N59: 1000 | O59: 1000 | P59: 1000 | Q59: 1000 | R59: 1000 | S59: 1000
C60: Transaction Costs: Bank / M&A Fee | D60: =CHOOSE($K$15,J60,K60,L60,M60,N60,O60,P60,Q60,R60,S60) -> 550 | J60: 550 | K60: 550 | L60: 550 | M60: 550 | N60: 550 | O60: 550 | P60: 550 | Q60: 550 | R60: 550 | S60: 550
C61: Transaction Costs: Legal | D61: =CHOOSE($K$15,J61,K61,L61,M61,N61,O61,P61,Q61,R61,S61) -> 612 | J61: 612 | K61: 612 | L61: 612 | M61: 612 | N61: 612 | O61: 612 | P61: 612 | Q61: 612 | R61: 612 | S61: 612
C62: Transaction Costs: Accounting & Diligence | D62: =CHOOSE($K$15,J62,K62,L62,M62,N62,O62,P62,Q62,R62,S62) -> 483 | J62: 483 | K62: 483 | L62: 483 | M62: 483 | N62: 483 | O62: 483 | P62: 483 | Q62: 483 | R62: 483 | S62: 483
C63: Transaction Costs: Financing Fees | D63: =CHOOSE($K$15,J63,K63,L63,M63,N63,O63,P63,Q63,R63,S63) -> 755 | J63: 755 | K63: 640 | L63: 755 | M63: 0 | N63: 810 | O63: 780 | P63: 830 | Q63: 790 | R63: 815 | S63: 745
C64: Total Transaction Costs | D64: =CHOOSE($K$15,J64,K64,L64,M64,N64,O64,P64,Q64,R64,S64) -> 2400 | J64: =SUM(J60:J63) -> 2400 | K64: =SUM(K60:K63) -> 2285 | L64: =SUM(L60:L63) -> 2400 | M64: =SUM(M60:M63) -> 1645 | N64: =SUM(N60:N63) -> 2455 | O64: =SUM(O60:O63) -> 2425 | P64: =SUM(P60:P63) -> 2475 | Q64: =SUM(Q60:Q63) -> 2435 | ... S64: =SUM(S60:S63) -> 2390
C65: Total Uses | D65: =CHOOSE($K$15,J65,K65,L65,M65,N65,O65,P65,Q65,R65,S65) -> 58583 | J65: =J58+J59+J64 -> 58583 | K65: =K58+K59+K64 -> 58468 | L65: =L58+L59+L64 -> 58583 | M65: =M58+M59+M64 -> 57828 | N65: =N58+N59+N64 -> 58638 | O65: =O58+O59+O64 -> 58608 | P65: =P58+P59+P64 -> 58658 | Q65: =Q58+Q59+Q64 -> 58618 | ... S65: =S58+S59+S64 -> 58573
C68: PURCHASE PRICE CALCULATION
C69: Transaction Value (hardcoded input) | D69: 55750
C70: Purchase Multiple (alternate input, x FY2025A Adj. EBITDA) | D70: 7
C71: Use Multiple? (1=Yes, 0=Hardcoded Value) | D71: 1
C72: Transaction Value (before fees) | D72: =IF(D71=1,D70*Model!$E$85,D69) -> 55083
C73: x FY2025A Adj. EBITDA | D73: =D72/Model!$E$85 -> 7
C74: x FY2026E Adj. EBITDA | D74: =D72/Model!$F$85 -> 6.2977588
C75: EBITDA / Transaction Value | D75: =Model!$E$85/D72 -> 0.14285714
C76: (EBITDA - Capex) / Transaction Value | D76: =(Model!$E$85-Model!$E$35)/D72 -> 0.1215257
C77: (EBITDA - Capex - Change in WC) / Transaction Value | D77: =(Model!$E$85-Model!$E$35-Model!$E$307)/D72 -> 0.12016412
C78: Less: Existing Debt (repaid at close) | D78: 6842
C79: Plus: Cash and Equivalents (left by seller) | D79: 100
C80: Equity Purchase Price | D80: =D72-D78+D79 -> 48341
C83: ADJ. OCF CALCULATION & LEVERAGE / PURCHASE PRICE RATIOS
C84: FY2026E Adj. EBITDA | D84: =Model!$F$85 -> 8746.4448
C85: Less: Maintenance CapEx | D85: =-Model!$F$35 -> -1288.9498
C86: Adj. OCF | D86: =D84+D85 -> 7457.495
C88: Current Capital Structure Leverage | D88: Amount | E88: x EBITDA | F88: x Adj. OCF
C89: Revolver | D89: =D36 -> 0 | E89: =D89/Model!$E$85 -> 0 | F89: =D89/$D$86 -> 0
C90: Term Loan | D90: =D37+D38 -> 23607 | E90: =D90/Model!$E$85 -> 3 | F90: =D90/$D$86 -> 3.1655402
C91: Senior Debt | D91: =D89+D90+D39+D40 -> 23607 | E91: =D91/Model!$E$85 -> 3 | F91: =D91/$D$86 -> 3.1655402
C92: Mezzanine | D92: =D41+D43+D44 -> 7869 | E92: =D92/Model!$E$85 -> 1 | F92: =D92/$D$86 -> 1.0551801
C93: Total Leverage excl. Seller Note | D93: =D91+D92 -> 31476 | E93: =D93/Model!$E$85 -> 4 | F93: =D93/$D$86 -> 4.2207202
C94: Seller Note | D94: =D42 -> 4000 | E94: =D94/Model!$E$85 -> 0.5083238 | F94: =D94/$D$86 -> 0.53637314
C95: Total Leverage incl. Seller Note | D95: =D93+D94 -> 35476 | E95: =D95/Model!$E$85 -> 4.5083238 | F95: =D95/$D$86 -> 4.7570933
C96: Purchase Price Multiple | D96: =D72 -> 55083 | E96: =D96/Model!$E$85 -> 7 | F96: =D96/$D$86 -> 7.3862604
C97: Based on Adj. OCF (Purchase Price / Adj. OCF) | D97: =D72/D86 -> 7.3862604
C100: (1) Sponsor common equity is the plug in each financing case; preferred = 90% of the total sponsor ticket.
C101: (2) Rollover equity in every case links to the Consideration tab (sellers roll 20% of consideration ex seller note).
C102: TO UPDATE: Case 6-10 pricing grids once final term sheets are received.

Sheet Debt Schedules
A1: =Assump_CapStructure!$F$7 -> Project Kestrel | M1: ="Operating Case Running: "&CHOOSE(Assump_CapStructure!$K$5,"Management Case","Case II - No Growth, No Taxes","Case III - Downside Case, No Taxes","Upside Case","Flat Case") -> Operating Case Running: Management Case
A2: ="Prepared by: "&Assump_CapStructure!$F$8 -> Prepared by: Halvern | M2: ="Capital Structure Case: "&CHOOSE(Assump_CapStructure!$K$15,"Base Case - Senior + Mezz","Senior Only","Senior + Seller Note Upsized","All Equity","Unitranche","Case 6","Case 7","Case 8","Case 9","Case 10") -> Capital Structure Case: Base Case - Senior + Mezz
A3: =Assump_CapStructure!$F$11 -> ($ in 000s)
A5: Fiscal Year Ended September 30, | E5: Closing | F5: =Model!F30 -> FY2026E | G5: =Model!G30 -> FY2027E | H5: =Model!H30 -> FY2028E | I5: =Model!I30 -> FY2029E | J5: =Model!J30 -> FY2030E | K5: =Model!K30 -> FY2031E | L5: =Model!L30 -> FY2032E | M5: =Model!M30 -> FY2033E
A7: REVOLVER
A8: Beginning Balance | F8: =Model!$K$7 -> 0 | G8: =F12 -> 0 | H8: =G12 -> 0 | I8: =H12 -> 0 | J8: =I12 -> 0 | K8: =J12 -> 0 | L8: =K12 -> 0 | M8: =L12 -> 0
A9: Mandatory Redemption | F9: =-MIN(F8,Model!$K$7*Assump_CapStructure!$X$36) -> 0 | G9: =-MIN(G8,Model!$K$7*Assump_CapStructure!$X$36) -> 0 | H9: =-MIN(H8,Model!$K$7*Assump_CapStructure!$X$36) -> 0 | I9: =-MIN(I8,Model!$K$7*Assump_CapStructure!$X$36) -> 0 | J9: =-MIN(J8,Model!$K$7*Assump_CapStructure!$X$36) -> 0 | K9: =-MIN(K8,Model!$K$7*Assump_CapStructure!$X$36) -> 0 | L9: =-MIN(L8,Model!$K$7*Assump_CapStructure!$X$36) -> 0 | M9: =-MIN(M8,Model!$K$7*Assump_CapStructure!$X$36) -> 0
A10: Borrowings / (Repayments) | F10: =Model!F198 -> 0 | G10: =Model!G198 -> 0 | H10: =Model!H198 -> 0 | I10: =Model!I198 -> 0 | J10: =Model!J198 -> 0 | K10: =Model!K198 -> 0 | L10: =Model!L198 -> 0 | M10: =Model!M198 -> 0
A11: PIK Interest (accretes to balance) | B11: =Assump_CapStructure!$V$36 -> 0 | F11: =F8*Assump_CapStructure!$V$36 -> 0 | G11: =G8*Assump_CapStructure!$V$36 -> 0 | H11: =H8*Assump_CapStructure!$V$36 -> 0 | I11: =I8*Assump_CapStructure!$V$36 -> 0 | J11: =J8*Assump_CapStructure!$V$36 -> 0 | K11: =K8*Assump_CapStructure!$V$36 -> 0 | L11: =L8*Assump_CapStructure!$V$36 -> 0 | M11: =M8*Assump_CapStructure!$V$36 -> 0
A12: Ending Balance | E12: =Model!$K$7 -> 0 | F12: =SUM(F8:F11) -> 0 | G12: =SUM(G8:G11) -> 0 | H12: =SUM(H8:H11) -> 0 | I12: =SUM(I8:I11) -> 0 | J12: =SUM(J8:J11) -> 0 | K12: =SUM(K8:K11) -> 0 | L12: =SUM(L8:L11) -> 0 | M12: =SUM(M8:M11) -> 0
A13: Cash Interest | B13: =Assump_CapStructure!$U$36 -> 0.03 | F13: =F8*(IF(Assump_CapStructure!$W$36="L +",Assump_CapStructure!$F$25,0)+Assump_CapStructure!$U$36) -> 0 | G13: =G8*(IF(Assump_CapStructure!$W$36="L +",Assump_CapStructure!$F$25,0)+Assump_CapStructure!$U$36) -> 0 | H13: =H8*(IF(Assump_CapStructure!$W$36="L +",Assump_CapStructure!$F$25,0)+Assump_CapStructure!$U$36) -> 0 | I13: =I8*(IF(Assump_CapStructure!$W$36="L +",Assump_CapStructure!$F$25,0)+Assump_CapStructure!$U$36) -> 0 | J13: =J8*(IF(Assump_CapStructure!$W$36="L +",Assump_CapStructure!$F$25,0)+Assump_CapStructure!$U$36) -> 0 | K13: =K8*(IF(Assump_CapStructure!$W$36="L +",Assump_CapStructure!$F$25,0)+Assump_CapStructure!$U$36) -> 0 | L13: =L8*(IF(Assump_CapStructure!$W$36="L +",Assump_CapStructure!$F$25,0)+Assump_CapStructure!$U$36) -> 0 | M13: =M8*(IF(Assump_CapStructure!$W$36="L +",Assump_CapStructure!$F$25,0)+Assump_CapStructure!$U$36) -> 0
A14: PIK Interest | F14: =F11 -> 0 | G14: =G11 -> 0 | H14: =H11 -> 0 | I14: =I11 -> 0 | J14: =J11 -> 0 | K14: =K11 -> 0 | L14: =L11 -> 0 | M14: =M11 -> 0
A15: Total Interest | F15: =F13+F14 -> 0 | G15: =G13+G14 -> 0 | H15: =H13+H14 -> 0 | I15: =I13+I14 -> 0 | J15: =J13+J14 -> 0 | K15: =K13+K14 -> 0 | L15: =L13+L14 -> 0 | M15: =M13+M14 -> 0
A16: Revolving Credit Facility: Revolver Outstanding | F16: =F12 -> 0 | G16: =G12 -> 0 | H16: =H12 -> 0 | I16: =I12 -> 0 | J16: =J12 -> 0 | K16: =K12 -> 0 | L16: =L12 -> 0 | M16: =M12 -> 0
A17: Unused Revolver | F17: =Assump_CapStructure!$D$50-F12 -> 8000 | G17: =Assump_CapStructure!$D$50-G12 -> 8000 | H17: =Assump_CapStructure!$D$50-H12 -> 8000 | I17: =Assump_CapStructure!$D$50-I12 -> 8000 | J17: =Assump_CapStructure!$D$50-J12 -> 8000 | K17: =Assump_CapStructure!$D$50-K12 -> 8000 | L17: =Assump_CapStructure!$D$50-L12 -> 8000 | M17: =Assump_CapStructure!$D$50-M12 -> 8000
A18: Unused Commitment Fee | F18: =(Assump_CapStructure!$D$50-F8)*Assump_CapStructure!$Z$36 -> 40 | G18: =(Assump_CapStructure!$D$50-G8)*Assump_CapStructure!$Z$36 -> 40 | H18: =(Assump_CapStructure!$D$50-H8)*Assump_CapStructure!$Z$36 -> 40 | I18: =(Assump_CapStructure!$D$50-I8)*Assump_CapStructure!$Z$36 -> 40 | J18: =(Assump_CapStructure!$D$50-J8)*Assump_CapStructure!$Z$36 -> 40 | K18: =(Assump_CapStructure!$D$50-K8)*Assump_CapStructure!$Z$36 -> 40 | L18: =(Assump_CapStructure!$D$50-L8)*Assump_CapStructure!$Z$36 -> 40 | M18: =(Assump_CapStructure!$D$50-M8)*Assump_CapStructure!$Z$36 -> 40
A20: TERM LOAN A
A21: Beginning Balance | F21: =Model!$K$8 -> 23607 | G21: =F25 -> 20328.036 | H21: =G25 -> 16284.658 | I21: =H25 -> 11554.908 | J21: =I25 -> 6104.7919 | K21: =J25 -> 0 | L21: =K25 -> 0 | M21: =L25 -> 0
A22: Mandatory Redemption | F22: =-MIN(F21,Model!$K$8*Assump_CapStructure!$X$37) -> -2360.7 | G22: =-MIN(G21,Model!$K$8*Assump_CapStructure!$X$37) -> -2360.7 | H22: =-MIN(H21,Model!$K$8*Assump_CapStructure!$X$37) -> -2360.7 | I22: =-MIN(I21,Model!$K$8*Assump_CapStructure!$X$37) -> -2360.7 | J22: =-MIN(J21,Model!$K$8*Assump_CapStructure!$X$37) -> -2360.7 | K22: =-MIN(K21,Model!$K$8*Assump_CapStructure!$X$37) -> 0 | L22: =-MIN(L21,Model!$K$8*Assump_CapStructure!$X$37) -> 0 | M22: =-MIN(M21,Model!$K$8*Assump_CapStructure!$X$37) -> 0
A23: Voluntary Redemption (from Model sweep) | F23: =Model!F199 -> -918.26448 | G23: =Model!G199 -> -1682.6776 | H23: =Model!H199 -> -2369.0503 | I23: =Model!I199 -> -3089.4156 | J23: =Model!J199 -> -3744.0919 | K23: =Model!K199 -> 0 | L23: =Model!L199 -> 0 | M23: =Model!M199 -> 0
A24: PIK Interest (accretes to balance) | B24: =Assump_CapStructure!$V$37 -> 0 | F24: =F21*Assump_CapStructure!$V$37 -> 0 | G24: =G21*Assump_CapStructure!$V$37 -> 0 | H24: =H21*Assump_CapStructure!$V$37 -> 0 | I24: =I21*Assump_CapStructure!$V$37 -> 0 | J24: =J21*Assump_CapStructure!$V$37 -> 0 | K24: =K21*Assump_CapStructure!$V$37 -> 0 | L24: =L21*Assump_CapStructure!$V$37 -> 0 | M24: =M21*Assump_CapStructure!$V$37 -> 0
A25: Ending Balance | E25: =Model!$K$8 -> 23607 | F25: =SUM(F21:F24) -> 20328.036 | G25: =SUM(G21:G24) -> 16284.658 | H25: =SUM(H21:H24) -> 11554.908 | I25: =SUM(I21:I24) -> 6104.7919 | J25: =SUM(J21:J24) -> 0 | K25: =SUM(K21:K24) -> 0 | L25: =SUM(L21:L24) -> 0 | M25: =SUM(M21:M24) -> 0
A26: Cash Interest | B26: =Assump_CapStructure!$U$37 -> 0.0325 | F26: =F21*(IF(Assump_CapStructure!$W$37="L +",Assump_CapStructure!$F$25,0)+Assump_CapStructure!$U$37) -> 1770.525 | G26: =G21*(IF(Assump_CapStructure!$W$37="L +",Assump_CapStructure!$F$25,0)+Assump_CapStructure!$U$37) -> 1524.6027 | H26: =H21*(IF(Assump_CapStructure!$W$37="L +",Assump_CapStructure!$F$25,0)+Assump_CapStructure!$U$37) -> 1221.3493 | I26: =I21*(IF(Assump_CapStructure!$W$37="L +",Assump_CapStructure!$F$25,0)+Assump_CapStructure!$U$37) -> 866.61807 | J26: =J21*(IF(Assump_CapStructure!$W$37="L +",Assump_CapStructure!$F$25,0)+Assump_CapStructure!$U$37) -> 457.85939 | K26: =K21*(IF(Assump_CapStructure!$W$37="L +",Assump_CapStructure!$F$25,0)+Assump_CapStructure!$U$37) -> 0 | L26: =L21*(IF(Assump_CapStructure!$W$37="L +",Assump_CapStructure!$F$25,0)+Assump_CapStructure!$U$37) -> 0 | M26: =M21*(IF(Assump_CapStructure!$W$37="L +",Assump_CapStructure!$F$25,0)+Assump_CapStructure!$U$37) -> 0
A27: PIK Interest | F27: =F24 -> 0 | G27: =G24 -> 0 | H27: =H24 -> 0 | I27: =I24 -> 0 | J27: =J24 -> 0 | K27: =K24 -> 0 | L27: =L24 -> 0 | M27: =M24 -> 0
A28: Total Interest | F28: =F26+F27 -> 1770.525 | G28: =G26+G27 -> 1524.6027 | H28: =H26+H27 -> 1221.3493 | I28: =I26+I27 -> 866.61807 | J28: =J26+J27 -> 457.85939 | K28: =K26+K27 -> 0 | L28: =L26+L27 -> 0 | M28: =M26+M27 -> 0
A30: TERM LOAN B
A31: Beginning Balance | F31: =Model!$K$9 -> 0 | G31: =F35 -> 0 | H31: =G35 -> 0 | I31: =H35 -> 0 | J31: =I35 -> 0 | K31: =J35 -> 0 | L31: =K35 -> 0 | M31: =L35 -> 0
A32: Mandatory Redemption | F32: =-MIN(F31,Model!$K$9*Assump_CapStructure!$X$38) -> 0 | G32: =-MIN(G31,Model!$K$9*Assump_CapStructure!$X$38) -> 0 | H32: =-MIN(H31,Model!$K$9*Assump_CapStructure!$X$38) -> 0 | I32: =-MIN(I31,Model!$K$9*Assump_CapStructure!$X$38) -> 0 | J32: =-MIN(J31,Model!$K$9*Assump_CapStructure!$X$38) -> 0 | K32: =-MIN(K31,Model!$K$9*Assump_CapStructure!$X$38) -> 0 | L32: =-MIN(L31,Model!$K$9*Assump_CapStructure!$X$38) -> 0 | M32: =-MIN(M31,Model!$K$9*Assump_CapStructure!$X$38) -> 0
A33: Voluntary Redemption (from Model sweep) | F33: =Model!F200 -> 0 | G33: =Model!G200 -> 0 | H33: =Model!H200 -> 0 | I33: =Model!I200 -> 0 | J33: =Model!J200 -> 0 | K33: =Model!K200 -> 0 | L33: =Model!L200 -> 0 | M33: =Model!M200 -> 0
A34: PIK Interest (accretes to balance) | B34: =Assump_CapStructure!$V$38 -> 0 | F34: =F31*Assump_CapStructure!$V$38 -> 0 | G34: =G31*Assump_CapStructure!$V$38 -> 0 | H34: =H31*Assump_CapStructure!$V$38 -> 0 | I34: =I31*Assump_CapStructure!$V$38 -> 0 | J34: =J31*Assump_CapStructure!$V$38 -> 0 | K34: =K31*Assump_CapStructure!$V$38 -> 0 | L34: =L31*Assump_CapStructure!$V$38 -> 0 | M34: =M31*Assump_CapStructure!$V$38 -> 0
A35: Ending Balance | E35: =Model!$K$9 -> 0 | F35: =SUM(F31:F34) -> 0 | G35: =SUM(G31:G34) -> 0 | H35: =SUM(H31:H34) -> 0 | I35: =SUM(I31:I34) -> 0 | J35: =SUM(J31:J34) -> 0 | K35: =SUM(K31:K34) -> 0 | L35: =SUM(L31:L34) -> 0 | M35: =SUM(M31:M34) -> 0
A36: Cash Interest | B36: =Assump_CapStructure!$U$38 -> 0.0475 | F36: =F31*(IF(Assump_CapStructure!$W$38="L +",Assump_CapStructure!$F$25,0)+Assump_CapStructure!$U$38) -> 0 | G36: =G31*(IF(Assump_CapStructure!$W$38="L +",Assump_CapStructure!$F$25,0)+Assump_CapStructure!$U$38) -> 0 | H36: =H31*(IF(Assump_CapStructure!$W$38="L +",Assump_CapStructure!$F$25,0)+Assump_CapStructure!$U$38) -> 0 | I36: =I31*(IF(Assump_CapStructure!$W$38="L +",Assump_CapStructure!$F$25,0)+Assump_CapStructure!$U$38) -> 0 | J36: =J31*(IF(Assump_CapStructure!$W$38="L +",Assump_CapStructure!$F$25,0)+Assump_CapStructure!$U$38) -> 0 | K36: =K31*(IF(Assump_CapStructure!$W$38="L +",Assump_CapStructure!$F$25,0)+Assump_CapStructure!$U$38) -> 0 | L36: =L31*(IF(Assump_CapStructure!$W$38="L +",Assump_CapStructure!$F$25,0)+Assump_CapStructure!$U$38) -> 0 | M36: =M31*(IF(Assump_CapStructure!$W$38="L +",Assump_CapStructure!$F$25,0)+Assump_CapStructure!$U$38) -> 0
A37: PIK Interest | F37: =F34 -> 0 | G37: =G34 -> 0 | H37: =H34 -> 0 | I37: =I34 -> 0 | J37: =J34 -> 0 | K37: =K34 -> 0 | L37: =L34 -> 0 | M37: =M34 -> 0
A38: Total Interest | F38: =F36+F37 -> 0 | G38: =G36+G37 -> 0 | H38: =H36+H37 -> 0 | I38: =I36+I37 -> 0 | J38: =J36+J37 -> 0 | K38: =K36+K37 -> 0 | L38: =L36+L37 -> 0 | M38: =M36+M37 -> 0
A40: SECOND LIEN
A41: Beginning Balance | F41: =Model!$K$10 -> 0 | G41: =F45 -> 0 | H41: =G45 -> 0 | I41: =H45 -> 0 | J41: =I45 -> 0 | K41: =J45 -> 0 | L41: =K45 -> 0 | M41: =L45 -> 0
A42: Mandatory Redemption | F42: =-MIN(F41,Model!$K$10*Assump_CapStructure!$X$39) -> 0 | G42: =-MIN(G41,Model!$K$10*Assump_CapStructure!$X$39) -> 0 | H42: =-MIN(H41,Model!$K$10*Assump_CapStructure!$X$39) -> 0 | I42: =-MIN(I41,Model!$K$10*Assump_CapStructure!$X$39) -> 0 | J42: =-MIN(J41,Model!$K$10*Assump_CapStructure!$X$39) -> 0 | K42: =-MIN(K41,Model!$K$10*Assump_CapStructure!$X$39) -> 0 | L42: =-MIN(L41,Model!$K$10*Assump_CapStructure!$X$39) -> 0 | M42: =-MIN(M41,Model!$K$10*Assump_CapStructure!$X$39) -> 0
A43: Voluntary Redemption (from Model sweep) | F43: =Model!F201 -> 0 | G43: =Model!G201 -> 0 | H43: =Model!H201 -> 0 | I43: =Model!I201 -> 0 | J43: =Model!J201 -> 0 | K43: =Model!K201 -> 0 | L43: =Model!L201 -> 0 | M43: =Model!M201 -> 0
A44: PIK Interest (accretes to balance) | B44: =Assump_CapStructure!$V$39 -> 0 | F44: =F41*Assump_CapStructure!$V$39 -> 0 | G44: =G41*Assump_CapStructure!$V$39 -> 0 | H44: =H41*Assump_CapStructure!$V$39 -> 0 | I44: =I41*Assump_CapStructure!$V$39 -> 0 | J44: =J41*Assump_CapStructure!$V$39 -> 0 | K44: =K41*Assump_CapStructure!$V$39 -> 0 | L44: =L41*Assump_CapStructure!$V$39 -> 0 | M44: =M41*Assump_CapStructure!$V$39 -> 0
A45: Ending Balance | E45: =Model!$K$10 -> 0 | F45: =SUM(F41:F44) -> 0 | G45: =SUM(G41:G44) -> 0 | H45: =SUM(H41:H44) -> 0 | I45: =SUM(I41:I44) -> 0 | J45: =SUM(J41:J44) -> 0 | K45: =SUM(K41:K44) -> 0 | L45: =SUM(L41:L44) -> 0 | M45: =SUM(M41:M44) -> 0
A46: Cash Interest | B46: =Assump_CapStructure!$U$39 -> 0.075 | F46: =F41*(IF(Assump_CapStructure!$W$39="L +",Assump_CapStructure!$F$25,0)+Assump_CapStructure!$U$39) -> 0 | G46: =G41*(IF(Assump_CapStructure!$W$39="L +",Assump_CapStructure!$F$25,0)+Assump_CapStructure!$U$39) -> 0 | H46: =H41*(IF(Assump_CapStructure!$W$39="L +",Assump_CapStructure!$F$25,0)+Assump_CapStructure!$U$39) -> 0 | I46: =I41*(IF(Assump_CapStructure!$W$39="L +",Assump_CapStructure!$F$25,0)+Assump_CapStructure!$U$39) -> 0 | J46: =J41*(IF(Assump_CapStructure!$W$39="L +",Assump_CapStructure!$F$25,0)+Assump_CapStructure!$U$39) -> 0 | K46: =K41*(IF(Assump_CapStructure!$W$39="L +",Assump_CapStructure!$F$25,0)+Assump_CapStructure!$U$39) -> 0 | L46: =L41*(IF(Assump_CapStructure!$W$39="L +",Assump_CapStructure!$F$25,0)+Assump_CapStructure!$U$39) -> 0 | M46: =M41*(IF(Assump_CapStructure!$W$39="L +",Assump_CapStructure!$F$25,0)+Assump_CapStructure!$U$39) -> 0
A47: PIK Interest | F47: =F44 -> 0 | G47: =G44 -> 0 | H47: =H44 -> 0 | I47: =I44 -> 0 | J47: =J44 -> 0 | K47: =K44 -> 0 | L47: =L44 -> 0 | M47: =M44 -> 0
A48: Total Interest | F48: =F46+F47 -> 0 | G48: =G46+G47 -> 0 | H48: =H46+H47 -> 0 | I48: =I46+I47 -> 0 | J48: =J46+J47 -> 0 | K48: =K46+K47 -> 0 | L48: =L46+L47 -> 0 | M48: =M46+M47 -> 0
A50: SENIOR NOTES
A51: Beginning Balance | F51: =Model!$K$11 -> 0 | G51: =F55 -> 0 | H51: =G55 -> 0 | I51: =H55 -> 0 | J51: =I55 -> 0 | K51: =J55 -> 0 | L51: =K55 -> 0 | M51: =L55 -> 0
A52: Mandatory Redemption | F52: =-MIN(F51,Model!$K$11*Assump_CapStructure!$X$40) -> 0 | G52: =-MIN(G51,Model!$K$11*Assump_CapStructure!$X$40) -> 0 | H52: =-MIN(H51,Model!$K$11*Assump_CapStructure!$X$40) -> 0 | I52: =-MIN(I51,Model!$K$11*Assump_CapStructure!$X$40) -> 0 | J52: =-MIN(J51,Model!$K$11*Assump_CapStructure!$X$40) -> 0 | K52: =-MIN(K51,Model!$K$11*Assump_CapStructure!$X$40) -> 0 | L52: =-MIN(L51,Model!$K$11*Assump_CapStructure!$X$40) -> 0 | M52: =-MIN(M51,Model!$K$11*Assump_CapStructure!$X$40) -> 0
A53: Voluntary Redemption (from Model sweep) | F53: =Model!F202 -> 0 | G53: =Model!G202 -> 0 | H53: =Model!H202 -> 0 | I53: =Model!I202 -> 0 | J53: =Model!J202 -> 0 | K53: =Model!K202 -> 0 | L53: =Model!L202 -> 0 | M53: =Model!M202 -> 0
A54: PIK Interest (accretes to balance) | B54: =Assump_CapStructure!$V$40 -> 0 | F54: =F51*Assump_CapStructure!$V$40 -> 0 | G54: =G51*Assump_CapStructure!$V$40 -> 0 | H54: =H51*Assump_CapStructure!$V$40 -> 0 | I54: =I51*Assump_CapStructure!$V$40 -> 0 | J54: =J51*Assump_CapStructure!$V$40 -> 0 | K54: =K51*Assump_CapStructure!$V$40 -> 0 | L54: =L51*Assump_CapStructure!$V$40 -> 0 | M54: =M51*Assump_CapStructure!$V$40 -> 0
A55: Ending Balance | E55: =Model!$K$11 -> 0 | F55: =SUM(F51:F54) -> 0 | G55: =SUM(G51:G54) -> 0 | H55: =SUM(H51:H54) -> 0 | I55: =SUM(I51:I54) -> 0 | J55: =SUM(J51:J54) -> 0 | K55: =SUM(K51:K54) -> 0 | L55: =SUM(L51:L54) -> 0 | M55: =SUM(M51:M54) -> 0
A56: Cash Interest | B56: =Assump_CapStructure!$U$40 -> 0.09 | F56: =F51*(IF(Assump_CapStructure!$W$40="L +",Assump_CapStructure!$F$25,0)+Assump_CapStructure!$U$40) -> 0 | G56: =G51*(IF(Assump_CapStructure!$W$40="L +",Assump_CapStructure!$F$25,0)+Assump_CapStructure!$U$40) -> 0 | H56: =H51*(IF(Assump_CapStructure!$W$40="L +",Assump_CapStructure!$F$25,0)+Assump_CapStructure!$U$40) -> 0 | I56: =I51*(IF(Assump_CapStructure!$W$40="L +",Assump_CapStructure!$F$25,0)+Assump_CapStructure!$U$40) -> 0 | J56: =J51*(IF(Assump_CapStructure!$W$40="L +",Assump_CapStructure!$F$25,0)+Assump_CapStructure!$U$40) -> 0 | K56: =K51*(IF(Assump_CapStructure!$W$40="L +",Assump_CapStructure!$F$25,0)+Assump_CapStructure!$U$40) -> 0 | L56: =L51*(IF(Assump_CapStructure!$W$40="L +",Assump_CapStructure!$F$25,0)+Assump_CapStructure!$U$40) -> 0 | M56: =M51*(IF(Assump_CapStructure!$W$40="L +",Assump_CapStructure!$F$25,0)+Assump_CapStructure!$U$40) -> 0
A57: PIK Interest | F57: =F54 -> 0 | G57: =G54 -> 0 | H57: =H54 -> 0 | I57: =I54 -> 0 | J57: =J54 -> 0 | K57: =K54 -> 0 | L57: =L54 -> 0 | M57: =M54 -> 0
A58: Total Interest | F58: =F56+F57 -> 0 | G58: =G56+G57 -> 0 | H58: =H56+H57 -> 0 | I58: =I56+I57 -> 0 | J58: =J56+J57 -> 0 | K58: =K56+K57 -> 0 | L58: =L56+L57 -> 0 | M58: =M56+M57 -> 0
A60: MEZZANINE DEBT
A61: Beginning Balance | F61: =Model!$K$12 -> 7869 | G61: =F65 -> 8026.38 | H61: =G65 -> 8186.9076 | I61: =H65 -> 8350.6458 | J61: =I65 -> 8517.6587 | K61: =J65 -> 8593.7939 | L61: =K65 -> 2934.9641 | M61: =L65 -> 58.699281
A62: Mandatory Redemption | F62: =-MIN(F61,Model!$K$12*Assump_CapStructure!$X$41) -> 0 | G62: =-MIN(G61,Model!$K$12*Assump_CapStructure!$X$41) -> 0 | H62: =-MIN(H61,Model!$K$12*Assump_CapStructure!$X$41) -> 0 | I62: =-MIN(I61,Model!$K$12*Assump_CapStructure!$X$41) -> 0 | J62: =-MIN(J61,Model!$K$12*Assump_CapStructure!$X$41) -> 0 | K62: =-MIN(K61,Model!$K$12*Assump_CapStructure!$X$41) -> 0 | L62: =-MIN(L61,Model!$K$12*Assump_CapStructure!$X$41) -> 0 | M62: =-MIN(M61,Model!$K$12*Assump_CapStructure!$X$41) -> 0
A63: Voluntary Redemption (from Model sweep) | F63: =Model!F203 -> 0 | G63: =Model!G203 -> 0 | H63: =Model!H203 -> 0 | I63: =Model!I203 -> 0 | J63: =Model!J203 -> -94.217935 | K63: =Model!K203 -> -5830.7057 | L63: =Model!L203 -> -2934.9641 | M63: =Model!M203 -> -58.699281
A64: PIK Interest (accretes to balance) | B64: =Assump_CapStructure!$V$41 -> 0.02 | F64: =F61*Assump_CapStructure!$V$41 -> 157.38 | G64: =G61*Assump_CapStructure!$V$41 -> 160.5276 | H64: =H61*Assump_CapStructure!$V$41 -> 163.73815 | I64: =I61*Assump_CapStructure!$V$41 -> 167.01292 | J64: =J61*Assump_CapStructure!$V$41 -> 170.35317 | K64: =K61*Assump_CapStructure!$V$41 -> 171.87588 | L64: =L61*Assump_CapStructure!$V$41 -> 58.699281 | M64: =M61*Assump_CapStructure!$V$41 -> 1.1739856
A65: Ending Balance | E65: =Model!$K$12 -> 7869 | F65: =SUM(F61:F64) -> 8026.38 | G65: =SUM(G61:G64) -> 8186.9076 | H65: =SUM(H61:H64) -> 8350.6458 | I65: =SUM(I61:I64) -> 8517.6587 | J65: =SUM(J61:J64) -> 8593.7939 | K65: =SUM(K61:K64) -> 2934.9641 | L65: =SUM(L61:L64) -> 58.699281 | M65: =SUM(M61:M64) -> 1.1739856
A66: Cash Interest | B66: =Assump_CapStructure!$U$41 -> 0.11 | F66: =F61*(IF(Assump_CapStructure!$W$41="L +",Assump_CapStructure!$F$25,0)+Assump_CapStructure!$U$41) -> 865.59 | G66: =G61*(IF(Assump_CapStructure!$W$41="L +",Assump_CapStructure!$F$25,0)+Assump_CapStructure!$U$41) -> 882.9018 | H66: =H61*(IF(Assump_CapStructure!$W$41="L +",Assump_CapStructure!$F$25,0)+Assump_CapStructure!$U$41) -> 900.55984 | I66: =I61*(IF(Assump_CapStructure!$W$41="L +",Assump_CapStructure!$F$25,0)+Assump_CapStructure!$U$41) -> 918.57103 | J66: =J61*(IF(Assump_CapStructure!$W$41="L +",Assump_CapStructure!$F$25,0)+Assump_CapStructure!$U$41) -> 936.94245 | K66: =K61*(IF(Assump_CapStructure!$W$41="L +",Assump_CapStructure!$F$25,0)+Assump_CapStructure!$U$41) -> 945.31733 | L66: =L61*(IF(Assump_CapStructure!$W$41="L +",Assump_CapStructure!$F$25,0)+Assump_CapStructure!$U$41) -> 322.84605 | M66: =M61*(IF(Assump_CapStructure!$W$41="L +",Assump_CapStructure!$F$25,0)+Assump_CapStructure!$U$41) -> 6.4569209
A67: PIK Interest | F67: =F64 -> 157.38 | G67: =G64 -> 160.5276 | H67: =H64 -> 163.73815 | I67: =I64 -> 167.01292 | J67: =J64 -> 170.35317 | K67: =K64 -> 171.87588 | L67: =L64 -> 58.699281 | M67: =M64 -> 1.1739856
A68: Total Interest | F68: =F66+F67 -> 1022.97 | G68: =G66+G67 -> 1043.4294 | H68: =H66+H67 -> 1064.298 | I68: =I66+I67 -> 1085.5839 | J68: =J66+J67 -> 1107.2956 | K68: =K66+K67 -> 1117.1932 | L68: =L66+L67 -> 381.54533 | M68: =M66+M67 -> 7.6309066
A70: SELLER NOTE
A71: Beginning Balance | F71: =Model!$K$13 -> 4000 | G71: =F75 -> 4240 | H71: =G75 -> 4494.4 | I71: =H75 -> 4764.064 | J71: =I75 -> 5049.9078 | K71: =J75 -> 5352.9023 | L71: =K75 -> 5674.0764 | M71: =L75 -> 1826.8454
A72: Mandatory Redemption | F72: =-MIN(F71,Model!$K$13*Assump_CapStructure!$X$42) -> 0 | G72: =-MIN(G71,Model!$K$13*Assump_CapStructure!$X$42) -> 0 | H72: =-MIN(H71,Model!$K$13*Assump_CapStructure!$X$42) -> 0 | I72: =-MIN(I71,Model!$K$13*Assump_CapStructure!$X$42) -> 0 | J72: =-MIN(J71,Model!$K$13*Assump_CapStructure!$X$42) -> 0 | K72: =-MIN(K71,Model!$K$13*Assump_CapStructure!$X$42) -> 0 | L72: =-MIN(L71,Model!$K$13*Assump_CapStructure!$X$42) -> 0 | M72: =-MIN(M71,Model!$K$13*Assump_CapStructure!$X$42) -> 0
A73: Voluntary Redemption (from Model sweep) | F73: =Model!F204 -> 0 | G73: =Model!G204 -> 0 | H73: =Model!H204 -> 0 | I73: =Model!I204 -> 0 | J73: =Model!J204 -> 0 | K73: =Model!K204 -> 0 | L73: =Model!L204 -> -4187.6757 | M73: =Model!M204 -> -1826.8454
A74: PIK Interest (accretes to balance) | B74: =Assump_CapStructure!$V$42 -> 0.06 | F74: =F71*Assump_CapStructure!$V$42 -> 240 | G74: =G71*Assump_CapStructure!$V$42 -> 254.4 | H74: =H71*Assump_CapStructure!$V$42 -> 269.664 | I74: =I71*Assump_CapStructure!$V$42 -> 285.84384 | J74: =J71*Assump_CapStructure!$V$42 -> 302.99447 | K74: =K71*Assump_CapStructure!$V$42 -> 321.17414 | L74: =L71*Assump_CapStructure!$V$42 -> 340.44459 | M74: =M71*Assump_CapStructure!$V$42 -> 109.61072
A75: Ending Balance | E75: =Model!$K$13 -> 4000 | F75: =SUM(F71:F74) -> 4240 | G75: =SUM(G71:G74) -> 4494.4 | H75: =SUM(H71:H74) -> 4764.064 | I75: =SUM(I71:I74) -> 5049.9078 | J75: =SUM(J71:J74) -> 5352.9023 | K75: =SUM(K71:K74) -> 5674.0764 | L75: =SUM(L71:L74) -> 1826.8454 | M75: =SUM(M71:M74) -> 109.61072
A76: Cash Interest | B76: =Assump_CapStructure!$U$42 -> 0 | F76: =F71*(IF(Assump_CapStructure!$W$42="L +",Assump_CapStructure!$F$25,0)+Assump_CapStructure!$U$42) -> 0 | G76: =G71*(IF(Assump_CapStructure!$W$42="L +",Assump_CapStructure!$F$25,0)+Assump_CapStructure!$U$42) -> 0 | H76: =H71*(IF(Assump_CapStructure!$W$42="L +",Assump_CapStructure!$F$25,0)+Assump_CapStructure!$U$42) -> 0 | I76: =I71*(IF(Assump_CapStructure!$W$42="L +",Assump_CapStructure!$F$25,0)+Assump_CapStructure!$U$42) -> 0 | J76: =J71*(IF(Assump_CapStructure!$W$42="L +",Assump_CapStructure!$F$25,0)+Assump_CapStructure!$U$42) -> 0 | K76: =K71*(IF(Assump_CapStructure!$W$42="L +",Assump_CapStructure!$F$25,0)+Assump_CapStructure!$U$42) -> 0 | L76: =L71*(IF(Assump_CapStructure!$W$42="L +",Assump_CapStructure!$F$25,0)+Assump_CapStructure!$U$42) -> 0 | M76: =M71*(IF(Assump_CapStructure!$W$42="L +",Assump_CapStructure!$F$25,0)+Assump_CapStructure!$U$42) -> 0
A77: PIK Interest | F77: =F74 -> 240 | G77: =G74 -> 254.4 | H77: =H74 -> 269.664 | I77: =I74 -> 285.84384 | J77: =J74 -> 302.99447 | K77: =K74 -> 321.17414 | L77: =L74 -> 340.44459 | M77: =M74 -> 109.61072
A78: Total Interest | F78: =F76+F77 -> 240 | G78: =G76+G77 -> 254.4 | H78: =H76+H77 -> 269.664 | I78: =I76+I77 -> 285.84384 | J78: =J76+J77 -> 302.99447 | K78: =K76+K77 -> 321.17414 | L78: =L76+L77 -> 340.44459 | M78: =M76+M77 -> 109.61072
A80: SUBORDINATED NOTES
A81: Beginning Balance | F81: =Model!$K$14 -> 0 | G81: =F85 -> 0 | H81: =G85 -> 0 | I81: =H85 -> 0 | J81: =I85 -> 0 | K81: =J85 -> 0 | L81: =K85 -> 0 | M81: =L85 -> 0
A82: Mandatory Redemption | F82: =-MIN(F81,Model!$K$14*Assump_CapStructure!$X$43) -> 0 | G82: =-MIN(G81,Model!$K$14*Assump_CapStructure!$X$43) -> 0 | H82: =-MIN(H81,Model!$K$14*Assump_CapStructure!$X$43) -> 0 | I82: =-MIN(I81,Model!$K$14*Assump_CapStructure!$X$43) -> 0 | J82: =-MIN(J81,Model!$K$14*Assump_CapStructure!$X$43) -> 0 | K82: =-MIN(K81,Model!$K$14*Assump_CapStructure!$X$43) -> 0 | L82: =-MIN(L81,Model!$K$14*Assump_CapStructure!$X$43) -> 0 | M82: =-MIN(M81,Model!$K$14*Assump_CapStructure!$X$43) -> 0
A83: Voluntary Redemption (from Model sweep) | F83: =Model!F205 -> 0 | G83: =Model!G205 -> 0 | H83: =Model!H205 -> 0 | I83: =Model!I205 -> 0 | J83: =Model!J205 -> 0 | K83: =Model!K205 -> 0 | L83: =Model!L205 -> 0 | M83: =Model!M205 -> 0
A84: PIK Interest (accretes to balance) | B84: =Assump_CapStructure!$V$43 -> 0.03 | F84: =F81*Assump_CapStructure!$V$43 -> 0 | G84: =G81*Assump_CapStructure!$V$43 -> 0 | H84: =H81*Assump_CapStructure!$V$43 -> 0 | I84: =I81*Assump_CapStructure!$V$43 -> 0 | J84: =J81*Assump_CapStructure!$V$43 -> 0 | K84: =K81*Assump_CapStructure!$V$43 -> 0 | L84: =L81*Assump_CapStructure!$V$43 -> 0 | M84: =M81*Assump_CapStructure!$V$43 -> 0
A85: Ending Balance | E85: =Model!$K$14 -> 0 | F85: =SUM(F81:F84) -> 0 | G85: =SUM(G81:G84) -> 0 | H85: =SUM(H81:H84) -> 0 | I85: =SUM(I81:I84) -> 0 | J85: =SUM(J81:J84) -> 0 | K85: =SUM(K81:K84) -> 0 | L85: =SUM(L81:L84) -> 0 | M85: =SUM(M81:M84) -> 0
A86: Cash Interest | B86: =Assump_CapStructure!$U$43 -> 0.1 | F86: =F81*(IF(Assump_CapStructure!$W$43="L +",Assump_CapStructure!$F$25,0)+Assump_CapStructure!$U$43) -> 0 | G86: =G81*(IF(Assump_CapStructure!$W$43="L +",Assump_CapStructure!$F$25,0)+Assump_CapStructure!$U$43) -> 0 | H86: =H81*(IF(Assump_CapStructure!$W$43="L +",Assump_CapStructure!$F$25,0)+Assump_CapStructure!$U$43) -> 0 | I86: =I81*(IF(Assump_CapStructure!$W$43="L +",Assump_CapStructure!$F$25,0)+Assump_CapStructure!$U$43) -> 0 | J86: =J81*(IF(Assump_CapStructure!$W$43="L +",Assump_CapStructure!$F$25,0)+Assump_CapStructure!$U$43) -> 0 | K86: =K81*(IF(Assump_CapStructure!$W$43="L +",Assump_CapStructure!$F$25,0)+Assump_CapStructure!$U$43) -> 0 | L86: =L81*(IF(Assump_CapStructure!$W$43="L +",Assump_CapStructure!$F$25,0)+Assump_CapStructure!$U$43) -> 0 | M86: =M81*(IF(Assump_CapStructure!$W$43="L +",Assump_CapStructure!$F$25,0)+Assump_CapStructure!$U$43) -> 0
A87: PIK Interest | F87: =F84 -> 0 | G87: =G84 -> 0 | H87: =H84 -> 0 | I87: =I84 -> 0 | J87: =J84 -> 0 | K87: =K84 -> 0 | L87: =L84 -> 0 | M87: =M84 -> 0
A88: Total Interest | F88: =F86+F87 -> 0 | G88: =G86+G87 -> 0 | H88: =H86+H87 -> 0 | I88: =I86+I87 -> 0 | J88: =J86+J87 -> 0 | K88: =K86+K87 -> 0 | L88: =L86+L87 -> 0 | M88: =M86+M87 -> 0
A90: OTHER DEBT
A91: Beginning Balance | F91: =Model!$K$15 -> 0 | G91: =F95 -> 0 | H91: =G95 -> 0 | I91: =H95 -> 0 | J91: =I95 -> 0 | K91: =J95 -> 0 | L91: =K95 -> 0 | M91: =L95 -> 0
A92: Mandatory Redemption | F92: =-MIN(F91,Model!$K$15*Assump_CapStructure!$X$44) -> 0 | G92: =-MIN(G91,Model!$K$15*Assump_CapStructure!$X$44) -> 0 | H92: =-MIN(H91,Model!$K$15*Assump_CapStructure!$X$44) -> 0 | I92: =-MIN(I91,Model!$K$15*Assump_CapStructure!$X$44) -> 0 | J92: =-MIN(J91,Model!$K$15*Assump_CapStructure!$X$44) -> 0 | K92: =-MIN(K91,Model!$K$15*Assump_CapStructure!$X$44) -> 0 | L92: =-MIN(L91,Model!$K$15*Assump_CapStructure!$X$44) -> 0 | M92: =-MIN(M91,Model!$K$15*Assump_CapStructure!$X$44) -> 0
A93: Voluntary Redemption (from Model sweep) | F93: 0 | G93: 0 | H93: 0 | I93: 0 | J93: 0 | K93: 0 | L93: 0 | M93: 0
A94: PIK Interest (accretes to balance) | B94: =Assump_CapStructure!$V$44 -> 0 | F94: =F91*Assump_CapStructure!$V$44 -> 0 | G94: =G91*Assump_CapStructure!$V$44 -> 0 | H94: =H91*Assump_CapStructure!$V$44 -> 0 | I94: =I91*Assump_CapStructure!$V$44 -> 0 | J94: =J91*Assump_CapStructure!$V$44 -> 0 | K94: =K91*Assump_CapStructure!$V$44 -> 0 | L94: =L91*Assump_CapStructure!$V$44 -> 0 | M94: =M91*Assump_CapStructure!$V$44 -> 0
A95: Ending Balance | E95: =Model!$K$15 -> 0 | F95: =SUM(F91:F94) -> 0 | G95: =SUM(G91:G94) -> 0 | H95: =SUM(H91:H94) -> 0 | I95: =SUM(I91:I94) -> 0 | J95: =SUM(J91:J94) -> 0 | K95: =SUM(K91:K94) -> 0 | L95: =SUM(L91:L94) -> 0 | M95: =SUM(M91:M94) -> 0
A96: Cash Interest | B96: =Assump_CapStructure!$U$44 -> 0.08 | F96: =F91*(IF(Assump_CapStructure!$W$44="L +",Assump_CapStructure!$F$25,0)+Assump_CapStructure!$U$44) -> 0 | G96: =G91*(IF(Assump_CapStructure!$W$44="L +",Assump_CapStructure!$F$25,0)+Assump_CapStructure!$U$44) -> 0 | H96: =H91*(IF(Assump_CapStructure!$W$44="L +",Assump_CapStructure!$F$25,0)+Assump_CapStructure!$U$44) -> 0 | I96: =I91*(IF(Assump_CapStructure!$W$44="L +",Assump_CapStructure!$F$25,0)+Assump_CapStructure!$U$44) -> 0 | J96: =J91*(IF(Assump_CapStructure!$W$44="L +",Assump_CapStructure!$F$25,0)+Assump_CapStructure!$U$44) -> 0 | K96: =K91*(IF(Assump_CapStructure!$W$44="L +",Assump_CapStructure!$F$25,0)+Assump_CapStructure!$U$44) -> 0 | L96: =L91*(IF(Assump_CapStructure!$W$44="L +",Assump_CapStructure!$F$25,0)+Assump_CapStructure!$U$44) -> 0 | M96: =M91*(IF(Assump_CapStructure!$W$44="L +",Assump_CapStructure!$F$25,0)+Assump_CapStructure!$U$44) -> 0
A97: PIK Interest | F97: =F94 -> 0 | G97: =G94 -> 0 | H97: =H94 -> 0 | I97: =I94 -> 0 | J97: =J94 -> 0 | K97: =K94 -> 0 | L97: =L94 -> 0 | M97: =M94 -> 0
A98: Total Interest | F98: =F96+F97 -> 0 | G98: =G96+G97 -> 0 | H98: =H96+H97 -> 0 | I98: =I96+I97 -> 0 | J98: =J96+J97 -> 0 | K98: =K96+K97 -> 0 | L98: =L96+L97 -> 0 | M98: =M96+M97 -> 0
A100: PREFERRED EQUITY ACCRETION (MEMO - NOT DEBT)
A101: Beginning Balance | F101: =Model!$E$332 -> 20796.3 | G101: =F103 -> 22460.004 | H101: =G103 -> 24256.804 | I101: =H103 -> 26197.349 | J101: =I103 -> 28293.137 | K101: =J103 -> 30556.587 | L101: =K103 -> 33001.114 | M101: =L103 -> 35641.204
A102: PIK / Accretion | F102: =F101*Assump_CapStructure!$F$28 -> 1663.704 | G102: =G101*Assump_CapStructure!$F$28 -> 1796.8003 | H102: =H101*Assump_CapStructure!$F$28 -> 1940.5443 | I102: =I101*Assump_CapStructure!$F$28 -> 2095.7879 | J102: =J101*Assump_CapStructure!$F$28 -> 2263.4509 | K102: =K101*Assump_CapStructure!$F$28 -> 2444.527 | L102: =L101*Assump_CapStructure!$F$28 -> 2640.0892 | M102: =M101*Assump_CapStructure!$F$28 -> 2851.2963
A103: Ending Accreted Balance | F103: =F101+F102 -> 22460.004 | G103: =G101+G102 -> 24256.804 | H103: =H101+H102 -> 26197.349 | I103: =I101+I102 -> 28293.137 | J103: =J101+J102 -> 30556.587 | K103: =K101+K102 -> 33001.114 | L103: =L101+L102 -> 35641.204 | M103: =M101+M102 -> 38492.5
A105: CASH INTEREST:
A106: Revolver | F106: =F13 -> 0 | G106: =G13 -> 0 | H106: =H13 -> 0 | I106: =I13 -> 0 | J106: =J13 -> 0 | K106: =K13 -> 0 | L106: =L13 -> 0 | M106: =M13 -> 0
A107: Term Loan A | F107: =F26 -> 1770.525 | G107: =G26 -> 1524.6027 | H107: =H26 -> 1221.3493 | I107: =I26 -> 866.61807 | J107: =J26 -> 457.85939 | K107: =K26 -> 0 | L107: =L26 -> 0 | M107: =M26 -> 0
A108: Term Loan B | F108: =F36 -> 0 | G108: =G36 -> 0 | H108: =H36 -> 0 | I108: =I36 -> 0 | J108: =J36 -> 0 | K108: =K36 -> 0 | L108: =L36 -> 0 | M108: =M36 -> 0
A109: Second Lien | F109: =F46 -> 0 | G109: =G46 -> 0 | H109: =H46 -> 0 | I109: =I46 -> 0 | J109: =J46 -> 0 | K109: =K46 -> 0 | L109: =L46 -> 0 | M109: =M46 -> 0
A110: Senior Notes | F110: =F56 -> 0 | G110: =G56 -> 0 | H110: =H56 -> 0 | I110: =I56 -> 0 | J110: =J56 -> 0 | K110: =K56 -> 0 | L110: =L56 -> 0 | M110: =M56 -> 0
A111: Mezzanine Debt | F111: =F66 -> 865.59 | G111: =G66 -> 882.9018 | H111: =H66 -> 900.55984 | I111: =I66 -> 918.57103 | J111: =J66 -> 936.94245 | K111: =K66 -> 945.31733 | L111: =L66 -> 322.84605 | M111: =M66 -> 6.4569209
A112: Seller Note | F112: =F76 -> 0 | G112: =G76 -> 0 | H112: =H76 -> 0 | I112: =I76 -> 0 | J112: =J76 -> 0 | K112: =K76 -> 0 | L112: =L76 -> 0 | M112: =M76 -> 0
...

Sheet Operating Backup-->
A1: Operating Backup -->

Sheet Assump_Operating
A1: =Assump_CapStructure!$F$7 -> Project Kestrel | M1: ="Operating Case Running: "&CHOOSE(Assump_CapStructure!$K$5,"Management Case","Case II - No Growth, No Taxes","Case III - Downside Case, No Taxes","Upside Case","Flat Case") -> Operating Case Running: Management Case
A2: ="Prepared by: "&Assump_CapStructure!$F$8 -> Prepared by: Halvern | M2: ="Capital Structure Case: "&CHOOSE(Assump_CapStructure!$K$15,"Base Case - Senior + Mezz","Senior Only","Senior + Seller Note Upsized","All Equity","Unitranche","Case 6","Case 7","Case 8","Case 9","Case 10") -> Capital Structure Case: Base Case - Senior + Mezz
A3: =Assump_CapStructure!$F$11 -> ($ in 000s)
B5: =Model!B30 -> FY2022A | C5: =Model!C30 -> FY2023A | D5: =Model!D30 -> FY2024A | E5: =Model!E30 -> FY2025A | F5: =Model!F30 -> FY2026E | G5: =Model!G30 -> FY2027E | H5: =Model!H30 -> FY2028E | I5: =Model!I30 -> FY2029E | ... M5: =Model!M30 -> FY2033E
A7: INCOME STATEMENT
A8: Total Revenue
A9: Case 1 - Management Case | B9: 35245 | C9: 38240 | D9: 40516 | E9: 42624 | F9: =E9*(1+F10) -> 46033.92 | G9: =F9*(1+G10) -> 49348.362 | H9: =G9*(1+H10) -> 52556.006 | I9: =H9*(1+I10) -> 55709.366 | J9: =I9*(1+J10) -> 58773.381 | K9: =J9*(1+K10) -> 61712.05 | L9: =K9*(1+L10) -> 64489.093 | M9: =L9*(1+M10) -> 67068.656
A10: % Growth | C10: =C9/B9-1 -> 0.084976592 | D10: =D9/C9-1 -> 0.059518828 | E10: =E9/D9-1 -> 0.052028828 | F10: 0.08 | G10: 0.072 | H10: 0.065 | I10: 0.06 | J10: 0.055 | K10: 0.05 | L10: 0.045 | M10: 0.04
A12: Case 2 - Case II - No Growth, No Taxes | B12: =B9 -> 35245 | C12: =C9 -> 38240 | D12: =D9 -> 40516 | E12: =E9 -> 42624 | F12: =E12*(1+F13) -> 42624 | G12: =F12*(1+G13) -> 42624 | H12: =G12*(1+H13) -> 42624 | I12: =H12*(1+I13) -> 42624 | J12: =I12*(1+J13) -> 42624 | K12: =J12*(1+K13) -> 42624 | L12: =K12*(1+L13) -> 42624 | M12: =L12*(1+M13) -> 42624
A13: % Growth | C13: =C12/B12-1 -> 0.084976592 | D13: =D12/C12-1 -> 0.059518828 | E13: =E12/D12-1 -> 0.052028828 | F13: 0 | G13: 0 | H13: 0 | I13: 0 | J13: 0 | K13: 0 | L13: 0 | M13: 0
A15: Case 3 - Case III - Downside Case, No Taxes | B15: =B9 -> 35245 | C15: =C9 -> 38240 | D15: =D9 -> 40516 | E15: =E9 -> 42624 | F15: =E15*(1+F16) -> 40492.8 | G15: =F15*(1+G16) -> 39278.016 | H15: =G15*(1+H16) -> 39278.016 | I15: =H15*(1+I16) -> 39278.016 | J15: =I15*(1+J16) -> 39670.796 | K15: =J15*(1+K16) -> 40067.504 | L15: =K15*(1+L16) -> 40468.179 | M15: =L15*(1+M16) -> 40872.861
A16: % Growth | C16: =C15/B15-1 -> 0.084976592 | D16: =D15/C15-1 -> 0.059518828 | E16: =E15/D15-1 -> 0.052028828 | F16: -0.05 | G16: -0.03 | H16: 0 | I16: 0 | J16: 0.01 | K16: 0.01 | L16: 0.01 | M16: 0.01
A18: Case 4 - Upside Case | B18: =B9 -> 35245 | C18: =C9 -> 38240 | D18: =D9 -> 40516 | E18: =E9 -> 42624 | F18: =E18*(1+F19) -> 47738.88 | G18: =F18*(1+G19) -> 53467.546 | H18: =G18*(1+H19) -> 59348.976 | I18: =H18*(1+I19) -> 65283.873 | J18: =I18*(1+J19) -> 71159.422 | K18: =J18*(1+K19) -> 76852.176 | L18: =K18*(1+L19) -> 82231.828 | M18: =L18*(1+M19) -> 87165.737
A19: % Growth | C19: =C18/B18-1 -> 0.084976592 | D19: =D18/C18-1 -> 0.059518828 | E19: =E18/D18-1 -> 0.052028828 | F19: 0.12 | G19: 0.12 | H19: 0.11 | I19: 0.1 | J19: 0.09 | K19: 0.08 | L19: 0.07 | M19: 0.06
A21: Case 5 - Flat Case | B21: =B9 -> 35245 | C21: =C9 -> 38240 | D21: =D9 -> 40516 | E21: =E9 -> 42624 | F21: =E21*(1+F22) -> 42624 | G21: =F21*(1+G22) -> 42624 | H21: =G21*(1+H22) -> 42624 | I21: =H21*(1+I22) -> 42624 | J21: =I21*(1+J22) -> 42624 | K21: =J21*(1+K22) -> 42624 | L21: =K21*(1+L22) -> 42624 | M21: =L21*(1+M22) -> 42624
A22: % Growth | C22: =C21/B21-1 -> 0.084976592 | D22: =D21/C21-1 -> 0.059518828 | E22: =E21/D21-1 -> 0.052028828 | F22: 0 | G22: 0 | H22: 0 | I22: 0 | J22: 0 | K22: 0 | L22: 0 | M22: 0
A24: Total Revenue (selected case) | B24: =CHOOSE(Assump_CapStructure!$K$5,B9,B12,B15,B18,B21) -> 35245 | C24: =CHOOSE(Assump_CapStructure!$K$5,C9,C12,C15,C18,C21) -> 38240 | D24: =CHOOSE(Assump_CapStructure!$K$5,D9,D12,D15,D18,D21) -> 40516 | E24: =CHOOSE(Assump_CapStructure!$K$5,E9,E12,E15,E18,E21) -> 42624 | F24: =CHOOSE(Assump_CapStructure!$K$5,F9,F12,F15,F18,F21) -> 46033.92 | G24: =CHOOSE(Assump_CapStructure!$K$5,G9,G12,G15,G18,G21) -> 49348.362 | H24: =CHOOSE(Assump_CapStructure!$K$5,H9,H12,H15,H18,H21) -> 52556.006 | I24: =CHOOSE(Assump_CapStructure!$K$5,I9,I12,I15,I18,I21) -> 55709.366 | ... M24: =CHOOSE(Assump_CapStructure!$K$5,M9,M12,M15,M18,M21) -> 67068.656
A25: % Growth | C25: =C24/B24-1 -> 0.084976592 | D25: =D24/C24-1 -> 0.059518828 | E25: =E24/D24-1 -> 0.052028828 | F25: =F24/E24-1 -> 0.08 | G25: =G24/F24-1 -> 0.072 | H25: =H24/G24-1 -> 0.065 | I25: =I24/H24-1 -> 0.06 | J25: =J24/I24-1 -> 0.055 | ... M25: =M24/L24-1 -> 0.04
A27: COGS (excl. D&A)
A28: Case 1 - Management Case | B28: 23240 | C28: 25026 | D28: 26224 | E28: 28098 | F28: =F29*F9 -> 29922.048 | G28: =G29*G9 -> 31977.739 | H28: =H29*H9 -> 33951.18 | I28: =I29*I9 -> 35932.541 | J28: =J29*J9 -> 37850.058 | K28: =K29*K9 -> 39742.56 | L28: =L29*L9 -> 41466.487 | M28: =M29*M9 -> 43125.146
A29: % of Revenue | B29: =IF(B9=0,0,B28/B9) -> 0.65938431 | C29: =IF(C9=0,0,C28/C9) -> 0.65444561 | D29: =IF(D9=0,0,D28/D9) -> 0.64725047 | E29: =IF(E9=0,0,E28/E9) -> 0.65920608 | F29: 0.65 | G29: 0.648 | H29: 0.646 | I29: 0.645 | J29: 0.644 | K29: 0.644 | L29: 0.643 | M29: 0.643
A31: Case 2 - Case II - No Growth, No Taxes | B31: =B28 -> 23240 | C31: =C28 -> 25026 | D31: =D28 -> 26224 | E31: =E28 -> 28098 | F31: =F32*F12 -> 27918.72 | G31: =G32*G12 -> 27918.72 | H31: =H32*H12 -> 27918.72 | I31: =I32*I12 -> 27918.72 | J31: =J32*J12 -> 27918.72 | K31: =K32*K12 -> 27918.72 | L31: =L32*L12 -> 27918.72 | M31: =M32*M12 -> 27918.72
A32: % of Revenue | B32: =IF(B12=0,0,B31/B12) -> 0.65938431 | C32: =IF(C12=0,0,C31/C12) -> 0.65444561 | D32: =IF(D12=0,0,D31/D12) -> 0.64725047 | E32: =IF(E12=0,0,E31/E12) -> 0.65920608 | F32: 0.655 | G32: 0.655 | H32: 0.655 | I32: 0.655 | J32: 0.655 | K32: 0.655 | L32: 0.655 | M32: 0.655
A34: Case 3 - Case III - Downside Case, No Taxes | B34: =B28 -> 23240 | C34: =C28 -> 25026 | D34: =D28 -> 26224 | E34: =E28 -> 28098 | F34: =F35*F15 -> 27049.19 | G34: =G35*G15 -> 26316.271 | H34: =H35*H15 -> 26316.271 | I34: =I35*I15 -> 26237.715 | J34: =J35*J15 -> 26420.75 | K34: =K35*K15 -> 26644.89 | L34: =L35*L15 -> 26911.339 | M34: =M35*M15 -> 27180.453
A35: % of Revenue | B35: =IF(B15=0,0,B34/B15) -> 0.65938431 | C35: =IF(C15=0,0,C34/C15) -> 0.65444561 | D35: =IF(D15=0,0,D34/D15) -> 0.64725047 | E35: =IF(E15=0,0,E34/E15) -> 0.65920608 | F35: 0.668 | G35: 0.67 | H35: 0.67 | I35: 0.668 | J35: 0.666 | K35: 0.665 | L35: 0.665 | M35: 0.665
A37: Case 4 - Upside Case | B37: =B28 -> 23240 | C37: =C28 -> 25026 | D37: =D28 -> 26224 | E37: =E28 -> 28098 | F37: =F38*F18 -> 30839.316 | G37: =G38*G18 -> 34379.632 | H37: =H38*H18 -> 37983.344 | I37: =I38*I18 -> 41651.111 | J37: =J38*J18 -> 45257.392 | K37: =K38*K18 -> 48801.131 | L37: =L38*L18 -> 52217.211 | M37: =M38*M18 -> 55350.243
A38: % of Revenue | B38: =IF(B18=0,0,B37/B18) -> 0.65938431 | C38: =IF(C18=0,0,C37/C18) -> 0.65444561 | D38: =IF(D18=0,0,D37/D18) -> 0.64725047 | E38: =IF(E18=0,0,E37/E18) -> 0.65920608 | F38: 0.646 | G38: 0.643 | H38: 0.64 | I38: 0.638 | J38: 0.636 | K38: 0.635 | L38: 0.635 | M38: 0.635
A40: Case 5 - Flat Case | B40: =B28 -> 23240 | C40: =C28 -> 25026 | D40: =D28 -> 26224 | E40: =E28 -> 28098 | F40: =F41*F21 -> 28046.592 | G40: =G41*G21 -> 28131.84 | H40: =H41*H21 -> 28131.84 | I40: =I41*I21 -> 28131.84 | J40: =J41*J21 -> 28131.84 | K40: =K41*K21 -> 28131.84 | L40: =L41*L21 -> 28131.84 | M40: =M41*M21 -> 28131.84
A41: % of Revenue | B41: =IF(B21=0,0,B40/B21) -> 0.65938431 | C41: =IF(C21=0,0,C40/C21) -> 0.65444561 | D41: =IF(D21=0,0,D40/D21) -> 0.64725047 | E41: =IF(E21=0,0,E40/E21) -> 0.65920608 | F41: 0.658 | G41: 0.66 | H41: 0.66 | I41: 0.66 | J41: 0.66 | K41: 0.66 | L41: 0.66 | M41: 0.66
A43: COGS (excl. D&A) (selected case) | B43: =CHOOSE(Assump_CapStructure!$K$5,B28,B31,B34,B37,B40) -> 23240 | C43: =CHOOSE(Assump_CapStructure!$K$5,C28,C31,C34,C37,C40) -> 25026 | D43: =CHOOSE(Assump_CapStructure!$K$5,D28,D31,D34,D37,D40) -> 26224 | E43: =CHOOSE(Assump_CapStructure!$K$5,E28,E31,E34,E37,E40) -> 28098 | F43: =CHOOSE(Assump_CapStructure!$K$5,F28,F31,F34,F37,F40) -> 29922.048 | G43: =CHOOSE(Assump_CapStructure!$K$5,G28,G31,G34,G37,G40) -> 31977.739 | H43: =CHOOSE(Assump_CapStructure!$K$5,H28,H31,H34,H37,H40) -> 33951.18 | I43: =CHOOSE(Assump_CapStructure!$K$5,I28,I31,I34,I37,I40) -> 35932.541 | ... M43: =CHOOSE(Assump_CapStructure!$K$5,M28,M31,M34,M37,M40) -> 43125.146
A44: % of Revenue | B44: =IF(B24=0,0,B43/B24) -> 0.65938431 | C44: =IF(C24=0,0,C43/C24) -> 0.65444561 | D44: =IF(D24=0,0,D43/D24) -> 0.64725047 | E44: =IF(E24=0,0,E43/E24) -> 0.65920608 | F44: =IF(F24=0,0,F43/F24) -> 0.65 | G44: =IF(G24=0,0,G43/G24) -> 0.648 | H44: =IF(H24=0,0,H43/H24) -> 0.646 | I44: =IF(I24=0,0,I43/I24) -> 0.645 | ... M44: =IF(M24=0,0,M43/M24) -> 0.643
A46: SG&A (excl. Amortization; adjusted)
A47: Case 1 - Management Case | B47: 5718 | C47: 6253 | D47: 6369 | E47: 6657 | F47: =F48*F9 -> 7365.4272 | G47: =G48*G9 -> 7846.3896 | H47: =H48*H9 -> 8303.8489 | I47: =I48*I9 -> 8746.3705 | J47: =J48*J9 -> 9168.6475 | K47: =K48*K9 -> 9627.0799 | L47: =L48*L9 -> 9995.8094 | M47: =M48*M9 -> 10395.642
A48: % of Revenue | B48: =IF(B9=0,0,B47/B9) -> 0.16223578 | C48: =IF(C9=0,0,C47/C9) -> 0.16351987 | D48: =IF(D9=0,0,D47/D9) -> 0.15719716 | E48: =IF(E9=0,0,E47/E9) -> 0.15617962 | F48: 0.16 | G48: 0.159 | H48: 0.158 | I48: 0.157 | J48: 0.156 | K48: 0.156 | L48: 0.155 | M48: 0.155
A50: Case 2 - Case II - No Growth, No Taxes | B50: =B47 -> 5718 | C50: =C47 -> 6253 | D50: =D47 -> 6369 | E50: =E47 -> 6657 | F50: =F51*F12 -> 6905.088 | G50: =G51*G12 -> 6905.088 | H50: =H51*H12 -> 6905.088 | I50: =I51*I12 -> 6905.088 | J50: =J51*J12 -> 6905.088 | K50: =K51*K12 -> 6905.088 | L50: =L51*L12 -> 6905.088 | M50: =M51*M12 -> 6905.088
A51: % of Revenue | B51: =IF(B12=0,0,B50/B12) -> 0.16223578 | C51: =IF(C12=0,0,C50/C12) -> 0.16351987 | D51: =IF(D12=0,0,D50/D12) -> 0.15719716 | E51: =IF(E12=0,0,E50/E12) -> 0.15617962 | F51: 0.162 | G51: 0.162 | H51: 0.162 | I51: 0.162 | J51: 0.162 | K51: 0.162 | L51: 0.162 | M51: 0.162
A53: Case 3 - Case III - Downside Case, No Taxes | B53: =B47 -> 5718 | C53: =C47 -> 6253 | D53: =D47 -> 6369 | E53: =E47 -> 6657 | F53: =F54*F15 -> 6802.7904 | G53: =G54*G15 -> 6677.2627 | H53: =H54*H15 -> 6677.2627 | I53: =I54*I15 -> 6637.9847 | J53: =J54*J15 -> 6664.6938 | K53: =K54*K15 -> 6731.3407 | L53: =L54*L15 -> 6798.6541 | M53: =M54*M15 -> 6866.6406
A54: % of Revenue | B54: =IF(B15=0,0,B53/B15) -> 0.16223578 | C54: =IF(C15=0,0,C53/C15) -> 0.16351987 | D54: =IF(D15=0,0,D53/D15) -> 0.15719716 | E54: =IF(E15=0,0,E53/E15) -> 0.15617962 | F54: 0.168 | G54: 0.17 | H54: 0.17 | I54: 0.169 | J54: 0.168 | K54: 0.168 | L54: 0.168 | M54: 0.168
A56: Case 4 - Upside Case | B56: =B47 -> 5718 | C56: =C47 -> 6253 | D56: =D47 -> 6369 | E56: =E47 -> 6657 | F56: =F57*F18 -> 7542.743 | G56: =G57*G18 -> 8340.9371 | H56: =H57*H18 -> 9139.7422 | I56: =I57*I18 -> 9923.1487 | J56: =J57*J18 -> 10673.913 | K56: =K57*K18 -> 11527.826 | L56: =L57*L18 -> 12334.774 | M56: =M57*M18 -> 13074.861
A57: % of Revenue | B57: =IF(B18=0,0,B56/B18) -> 0.16223578 | C57: =IF(C18=0,0,C56/C18) -> 0.16351987 | D57: =IF(D18=0,0,D56/D18) -> 0.15719716 | E57: =IF(E18=0,0,E56/E18) -> 0.15617962 | F57: 0.158 | G57: 0.156 | H57: 0.154 | I57: 0.152 | J57: 0.15 | K57: 0.15 | L57: 0.15 | M57: 0.15
A59: Case 5 - Flat Case | B59: =B47 -> 5718 | C59: =C47 -> 6253 | D59: =D47 -> 6369 | E59: =E47 -> 6657 | F59: =F60*F21 -> 6947.712 | G59: =G60*G21 -> 6990.336 | H59: =H60*H21 -> 6990.336 | I59: =I60*I21 -> 6990.336 | J59: =J60*J21 -> 6990.336 | K59: =K60*K21 -> 6990.336 | L59: =L60*L21 -> 6990.336 | M59: =M60*M21 -> 6990.336
A60: % of Revenue | B60: =IF(B21=0,0,B59/B21) -> 0.16223578 | C60: =IF(C21=0,0,C59/C21) -> 0.16351987 | D60: =IF(D21=0,0,D59/D21) -> 0.15719716 | E60: =IF(E21=0,0,E59/E21) -> 0.15617962 | F60: 0.163 | G60: 0.164 | H60: 0.164 | I60: 0.164 | J60: 0.164 | K60: 0.164 | L60: 0.164 | M60: 0.164
A62: SG&A (excl. Amortization; adjusted) (selected case) | B62: =CHOOSE(Assump_CapStructure!$K$5,B47,B50,B53,B56,B59) -> 5718 | C62: =CHOOSE(Assump_CapStructure!$K$5,C47,C50,C53,C56,C59) -> 6253 | D62: =CHOOSE(Assump_CapStructure!$K$5,D47,D50,D53,D56,D59) -> 6369 | E62: =CHOOSE(Assump_CapStructure!$K$5,E47,E50,E53,E56,E59) -> 6657 | F62: =CHOOSE(Assump_CapStructure!$K$5,F47,F50,F53,F56,F59) -> 7365.4272 | G62: =CHOOSE(Assump_CapStructure!$K$5,G47,G50,G53,G56,G59) -> 7846.3896 | H62: =CHOOSE(Assump_CapStructure!$K$5,H47,H50,H53,H56,H59) -> 8303.8489 | I62: =CHOOSE(Assump_CapStructure!$K$5,I47,I50,I53,I56,I59) -> 8746.3705 | ... M62: =CHOOSE(Assump_CapStructure!$K$5,M47,M50,M53,M56,M59) -> 10395.642
A63: % of Revenue | B63: =IF(B24=0,0,B62/B24) -> 0.16223578 | C63: =IF(C24=0,0,C62/C24) -> 0.16351987 | D63: =IF(D24=0,0,D62/D24) -> 0.15719716 | E63: =IF(E24=0,0,E62/E24) -> 0.15617962 | F63: =IF(F24=0,0,F62/F24) -> 0.16 | G63: =IF(G24=0,0,G62/G24) -> 0.159 | H63: =IF(H24=0,0,H62/H24) -> 0.158 | I63: =IF(I24=0,0,I62/I24) -> 0.157 | ... M63: =IF(M24=0,0,M62/M24) -> 0.155
A65: EBITDA Adjustments (memo; not linked to Model)
A66: Case 1 - Management Case | B66: 387 | C66: 347 | D66: 318 | E66: 261 | F66: =F67*F9 -> 0 | G66: =G67*G9 -> 0 | H66: =H67*H9 -> 0 | I66: =I67*I9 -> 0 | J66: =J67*J9 -> 0 | K66: =K67*K9 -> 0 | L66: =L67*L9 -> 0 | M66: =M67*M9 -> 0
A67: % of Revenue | B67: =IF(B9=0,0,B66/B9) -> 0.010980281 | C67: =IF(C9=0,0,C66/C9) -> 0.0090742678 | D67: =IF(D9=0,0,D66/D9) -> 0.0078487511 | E67: =IF(E9=0,0,E66/E9) -> 0.0061233108 | F67: 0 | G67: 0 | H67: 0 | I67: 0 | J67: 0 | K67: 0 | L67: 0 | M67: 0
A69: Case 2 - Case II - No Growth, No Taxes | B69: =B66 -> 387 | C69: =C66 -> 347 | D69: =D66 -> 318 | E69: =E66 -> 261 | F69: =F70*F12 -> 0 | G69: =G70*G12 -> 0 | H69: =H70*H12 -> 0 | I69: =I70*I12 -> 0 | J69: =J70*J12 -> 0 | K69: =K70*K12 -> 0 | L69: =L70*L12 -> 0 | M69: =M70*M12 -> 0
A70: % of Revenue | B70: =IF(B12=0,0,B69/B12) -> 0.010980281 | C70: =IF(C12=0,0,C69/C12) -> 0.0090742678 | D70: =IF(D12=0,0,D69/D12) -> 0.0078487511 | E70: =IF(E12=0,0,E69/E12) -> 0.0061233108 | F70: 0 | G70: 0 | H70: 0 | I70: 0 | J70: 0 | K70: 0 | L70: 0 | M70: 0
A72: Case 3 - Case III - Downside Case, No Taxes | B72: =B66 -> 387 | C72: =C66 -> 347 | D72: =D66 -> 318 | E72: =E66 -> 261 | F72: =F73*F15 -> 0 | G72: =G73*G15 -> 0 | H72: =H73*H15 -> 0 | I72: =I73*I15 -> 0 | J72: =J73*J15 -> 0 | K72: =K73*K15 -> 0 | L72: =L73*L15 -> 0 | M72: =M73*M15 -> 0
A73: % of Revenue | B73: =IF(B15=0,0,B72/B15) -> 0.010980281 | C73: =IF(C15=0,0,C72/C15) -> 0.0090742678 | D73: =IF(D15=0,0,D72/D15) -> 0.0078487511 | E73: =IF(E15=0,0,E72/E15) -> 0.0061233108 | F73: 0 | G73: 0 | H73: 0 | I73: 0 | J73: 0 | K73: 0 | L73: 0 | M73: 0
A75: Case 4 - Upside Case | B75: =B66 -> 387 | C75: =C66 -> 347 | D75: =D66 -> 318 | E75: =E66 -> 261 | F75: =F76*F18 -> 0 | G75: =G76*G18 -> 0 | H75: =H76*H18 -> 0 | I75: =I76*I18 -> 0 | J75: =J76*J18 -> 0 | K75: =K76*K18 -> 0 | L75: =L76*L18 -> 0 | M75: =M76*M18 -> 0
A76: % of Revenue | B76: =IF(B18=0,0,B75/B18) -> 0.010980281 | C76: =IF(C18=0,0,C75/C18) -> 0.0090742678 | D76: =IF(D18=0,0,D75/D18) -> 0.0078487511 | E76: =IF(E18=0,0,E75/E18) -> 0.0061233108 | F76: 0 | G76: 0 | H76: 0 | I76: 0 | J76: 0 | K76: 0 | L76: 0 | M76: 0
A78: Case 5 - Flat Case | B78: =B66 -> 387 | C78: =C66 -> 347 | D78: =D66 -> 318 | E78: =E66 -> 261 | F78: =F79*F21 -> 0 | G78: =G79*G21 -> 0 | H78: =H79*H21 -> 0 | I78: =I79*I21 -> 0 | J78: =J79*J21 -> 0 | K78: =K79*K21 -> 0 | L78: =L79*L21 -> 0 | M78: =M79*M21 -> 0
A79: % of Revenue | B79: =IF(B21=0,0,B78/B21) -> 0.010980281 | C79: =IF(C21=0,0,C78/C21) -> 0.0090742678 | D79: =IF(D21=0,0,D78/D21) -> 0.0078487511 | E79: =IF(E21=0,0,E78/E21) -> 0.0061233108 | F79: 0 | G79: 0 | H79: 0 | I79: 0 | J79: 0 | K79: 0 | L79: 0 | M79: 0
A81: EBITDA Adjustments (memo; not linked to Model) (selected case) | B81: =CHOOSE(Assump_CapStructure!$K$5,B66,B69,B72,B75,B78) -> 387 | C81: =CHOOSE(Assump_CapStructure!$K$5,C66,C69,C72,C75,C78) -> 347 | D81: =CHOOSE(Assump_CapStructure!$K$5,D66,D69,D72,D75,D78) -> 318 | E81: =CHOOSE(Assump_CapStructure!$K$5,E66,E69,E72,E75,E78) -> 261 | F81: =CHOOSE(Assump_CapStructure!$K$5,F66,F69,F72,F75,F78) -> 0 | G81: =CHOOSE(Assump_CapStructure!$K$5,G66,G69,G72,G75,G78) -> 0 | H81: =CHOOSE(Assump_CapStructure!$K$5,H66,H69,H72,H75,H78) -> 0 | I81: =CHOOSE(Assump_CapStructure!$K$5,I66,I69,I72,I75,I78) -> 0 | ... M81: =CHOOSE(Assump_CapStructure!$K$5,M66,M69,M72,M75,M78) -> 0
A82: % of Revenue | B82: =IF(B24=0,0,B81/B24) -> 0.010980281 | C82: =IF(C24=0,0,C81/C24) -> 0.0090742678 | D82: =IF(D24=0,0,D81/D24) -> 0.0078487511 | E82: =IF(E24=0,0,E81/E24) -> 0.0061233108 | F82: =IF(F24=0,0,F81/F24) -> 0 | G82: =IF(G24=0,0,G81/G24) -> 0 | H82: =IF(H24=0,0,H81/H24) -> 0 | I82: =IF(I24=0,0,I81/I24) -> 0 | ... M82: =IF(M24=0,0,M81/M24) -> 0
A84: Depreciation & Amortization
A85: Case 1 - Management Case | B85: 976 | C85: 1015 | D85: 1104 | E85: 1153 | F85: =F86*F9 -> 1242.9158 | G85: =G86*G9 -> 1332.4058 | H85: =H86*H9 -> 1419.0122 | I85: =I86*I9 -> 1504.1529 | J85: =J86*J9 -> 1586.8813 | K85: =K86*K9 -> 1666.2254 | L85: =L86*L9 -> 1741.2055 | M85: =M86*M9 -> 1810.8537
A86: % of Revenue | B86: =IF(B9=0,0,B85/B9) -> 0.027691871 | C86: =IF(C9=0,0,C85/C9) -> 0.026542887 | D86: =IF(D9=0,0,D85/D9) -> 0.027248494 | E86: =IF(E9=0,0,E85/E9) -> 0.027050488 | F86: 0.027 | G86: 0.027 | H86: 0.027 | I86: 0.027 | J86: 0.027 | K86: 0.027 | L86: 0.027 | M86: 0.027
A88: Case 2 - Case II - No Growth, No Taxes | B88: =B85 -> 976 | C88: =C85 -> 1015 | D88: =D85 -> 1104 | E88: =E85 -> 1153 | F88: =F89*F12 -> 1150.848 | G88: =G89*G12 -> 1150.848 | H88: =H89*H12 -> 1150.848 | I88: =I89*I12 -> 1150.848 | J88: =J89*J12 -> 1150.848 | K88: =K89*K12 -> 1150.848 | L88: =L89*L12 -> 1150.848 | M88: =M89*M12 -> 1150.848
A89: % of Revenue | B89: =IF(B12=0,0,B88/B12) -> 0.027691871 | C89: =IF(C12=0,0,C88/C12) -> 0.026542887 | D89: =IF(D12=0,0,D88/D12) -> 0.027248494 | E89: =IF(E12=0,0,E88/E12) -> 0.027050488 | F89: 0.027 | G89: 0.027 | H89: 0.027 | I89: 0.027 | J89: 0.027 | K89: 0.027 | L89: 0.027 | M89: 0.027
A91: Case 3 - Case III - Downside Case, No Taxes | B91: =B85 -> 976 | C91: =C85 -> 1015 | D91: =D85 -> 1104 | E91: =E85 -> 1153 | F91: =F92*F15 -> 1093.3056 | G91: =G92*G15 -> 1060.5064 | H91: =H92*H15 -> 1060.5064 | I91: =I92*I15 -> 1060.5064 | J91: =J92*J15 -> 1071.1115 | K91: =K92*K15 -> 1081.8226 | L91: =L92*L15 -> 1092.6408 | M91: =M92*M15 -> 1103.5672
A92: % of Revenue | B92: =IF(B15=0,0,B91/B15) -> 0.027691871 | C92: =IF(C15=0,0,C91/C15) -> 0.026542887 | D92: =IF(D15=0,0,D91/D15) -> 0.027248494 | E92: =IF(E15=0,0,E91/E15) -> 0.027050488 | F92: 0.027 | G92: 0.027 | H92: 0.027 | I92: 0.027 | J92: 0.027 | K92: 0.027 | L92: 0.027 | M92: 0.027
A94: Case 4 - Upside Case | B94: =B85 -> 976 | C94: =C85 -> 1015 | D94: =D85 -> 1104 | E94: =E85 -> 1153 | F94: =F95*F18 -> 1288.9498 | G94: =G95*G18 -> 1443.6237 | H94: =H95*H18 -> 1602.4223 | I94: =I95*I18 -> 1762.6646 | J94: =J95*J18 -> 1921.3044 | K94: =K95*K18 -> 2075.0087 | L94: =L95*L18 -> 2220.2594 | M94: =M95*M18 -> 2353.4749
A95: % of Revenue | B95: =IF(B18=0,0,B94/B18) -> 0.027691871 | C95: =IF(C18=0,0,C94/C18) -> 0.026542887 | D95: =IF(D18=0,0,D94/D18) -> 0.027248494 | E95: =IF(E18=0,0,E94/E18) -> 0.027050488 | F95: 0.027 | G95: 0.027 | H95: 0.027 | I95: 0.027 | J95: 0.027 | K95: 0.027 | L95: 0.027 | M95: 0.027
A97: Case 5 - Flat Case | B97: =B85 -> 976 | C97: =C85 -> 1015 | D97: =D85 -> 1104 | E97: =E85 -> 1153 | F97: =F98*F21 -> 1150.848 | G97: =G98*G21 -> 1150.848 | H97: =H98*H21 -> 1150.848 | I97: =I98*I21 -> 1150.848 | J97: =J98*J21 -> 1150.848 | K97: =K98*K21 -> 1150.848 | L97: =L98*L21 -> 1150.848 | M97: =M98*M21 -> 1150.848
A98: % of Revenue | B98: =IF(B21=0,0,B97/B21) -> 0.027691871 | C98: =IF(C21=0,0,C97/C21) -> 0.026542887 | D98: =IF(D21=0,0,D97/D21) -> 0.027248494 | E98: =IF(E21=0,0,E97/E21) -> 0.027050488 | F98: 0.027 | G98: 0.027 | H98: 0.027 | I98: 0.027 | J98: 0.027 | K98: 0.027 | L98: 0.027 | M98: 0.027
A100: Depreciation & Amortization (selected case) | B100: =CHOOSE(Assump_CapStructure!$K$5,B85,B88,B91,B94,B97) -> 976 | C100: =CHOOSE(Assump_CapStructure!$K$5,C85,C88,C91,C94,C97) -> 1015 | D100: =CHOOSE(Assump_CapStructure!$K$5,D85,D88,D91,D94,D97) -> 1104 | E100: =CHOOSE(Assump_CapStructure!$K$5,E85,E88,E91,E94,E97) -> 1153 | F100: =CHOOSE(Assump_CapStructure!$K$5,F85,F88,F91,F94,F97) -> 1242.9158 | G100: =CHOOSE(Assump_CapStructure!$K$5,G85,G88,G91,G94,G97) -> 1332.4058 | H100: =CHOOSE(Assump_CapStructure!$K$5,H85,H88,H91,H94,H97) -> 1419.0122 | I100: =CHOOSE(Assump_CapStructure!$K$5,I85,I88,I91,I94,I97) -> 1504.1529 | ... M100: =CHOOSE(Assump_CapStructure!$K$5,M85,M88,M91,M94,M97) -> 1810.8537
A101: % of Revenue | B101: =IF(B24=0,0,B100/B24) -> 0.027691871 | C101: =IF(C24=0,0,C100/C24) -> 0.026542887 | D101: =IF(D24=0,0,D100/D24) -> 0.027248494 | E101: =IF(E24=0,0,E100/E24) -> 0.027050488 | F101: =IF(F24=0,0,F100/F24) -> 0.027 | G101: =IF(G24=0,0,G100/G24) -> 0.027 | H101: =IF(H24=0,0,H100/H24) -> 0.027 | I101: =IF(I24=0,0,I100/I24) -> 0.027 | ... M101: =IF(M24=0,0,M100/M24) -> 0.027
A103: Taxes Applied? (1=Yes, 0=No; "No Taxes" cases)
A104: Case 1 - Management Case | F104: 1
A105: Case 2 - Case II - No Growth, No Taxes | F105: 0
A106: Case 3 - Case III - Downside Case, No Taxes | F106: 0
A107: Case 4 - Upside Case | F107: 1
A108: Case 5 - Flat Case | F108: 1
A109: Taxes Applied (selected case) | F109: =CHOOSE(Assump_CapStructure!$K$5,F104,F105,F106,F107,F108) -> 1
A111: CASH FLOW
A112: Capital Expenditures
A113: Case 1 - Management Case | B113: 1058 | C113: 1032 | D113: 1116 | E113: 1175 | F113: =F114*F9 -> 1288.9498 | G113: =G114*G9 -> 1381.7541 | H113: =H114*H9 -> 1471.5682 | I113: =I114*I9 -> 1559.8623 | J113: =J114*J9 -> 1645.6547 | K113: =K114*K9 -> 1727.9374 | L113: =L114*L9 -> 1805.6946 | M113: =M114*M9 -> 1877.9224
A114: % of Revenue | B114: =IF(B9=0,0,B113/B9) -> 0.030018442 | C114: =IF(C9=0,0,C113/C9) -> 0.026987448 | D114: =IF(D9=0,0,D113/D9) -> 0.027544674 | E114: =IF(E9=0,0,E113/E9) -> 0.027566629 | F114: 0.028 | G114: 0.028 | H114: 0.028 | I114: 0.028 | J114: 0.028 | K114: 0.028 | L114: 0.028 | M114: 0.028
A116: Case 2 - Case II - No Growth, No Taxes | B116: =B113 -> 1058 | C116: =C113 -> 1032 | D116: =D113 -> 1116 | E116: =E113 -> 1175 | F116: =F117*F12 -> 1108.224 | G116: =G117*G12 -> 1108.224 | H116: =H117*H12 -> 1108.224 | I116: =I117*I12 -> 1108.224 | J116: =J117*J12 -> 1108.224 | K116: =K117*K12 -> 1108.224 | L116: =L117*L12 -> 1108.224 | M116: =M117*M12 -> 1108.224
A117: % of Revenue | B117: =IF(B12=0,0,B116/B12) -> 0.030018442 | C117: =IF(C12=0,0,C116/C12) -> 0.026987448 | D117: =IF(D12=0,0,D116/D12) -> 0.027544674 | E117: =IF(E12=0,0,E116/E12) -> 0.027566629 | F117: 0.026 | G117: 0.026 | H117: 0.026 | I117: 0.026 | J117: 0.026 | K117: 0.026 | L117: 0.026 | M117: 0.026
A119: Case 3 - Case III - Downside Case, No Taxes | B119: =B113 -> 1058 | C119: =C113 -> 1032 | D119: =D113 -> 1116 | E119: =E113 -> 1175 | F119: =F120*F15 -> 1012.32 | G119: =G120*G15 -> 981.9504 | H119: =H120*H15 -> 981.9504 | I119: =I120*I15 -> 981.9504 | J119: =J120*J15 -> 991.7699 | K119: =K120*K15 -> 1001.6876 | L119: =L120*L15 -> 1011.7045 | M119: =M120*M15 -> 1021.8215
A120: % of Revenue | B120: =IF(B15=0,0,B119/B15) -> 0.030018442 | C120: =IF(C15=0,0,C119/C15) -> 0.026987448 | D120: =IF(D15=0,0,D119/D15) -> 0.027544674 | E120: =IF(E15=0,0,E119/E15) -> 0.027566629 | F120: 0.025 | G120: 0.025 | H120: 0.025 | I120: 0.025 | J120: 0.025 | K120: 0.025 | L120: 0.025 | M120: 0.025
A122: Case 4 - Upside Case | B122: =B113 -> 1058 | C122: =C113 -> 1032 | D122: =D113 -> 1116 | E122: =E113 -> 1175 | F122: =F123*F18 -> 1479.9053 | G122: =G123*G18 -> 1657.4939 | H122: =H123*H18 -> 1839.8182 | I122: =I123*I18 -> 2023.8001 | J122: =J123*J18 -> 2205.9421 | K122: =K123*K18 -> 2382.4174 | L122: =L123*L18 -> 2549.1867 | M122: =M123*M18 -> 2702.1379
A123: % of Revenue | B123: =IF(B18=0,0,B122/B18) -> 0.030018442 | C123: =IF(C18=0,0,C122/C18) -> 0.026987448 | D123: =IF(D18=0,0,D122/D18) -> 0.027544674 | E123: =IF(E18=0,0,E122/E18) -> 0.027566629 | F123: 0.031 | G123: 0.031 | H123: 0.031 | I123: 0.031 | J123: 0.031 | K123: 0.031 | L123: 0.031 | M123: 0.031
A125: Case 5 - Flat Case | B125: =B113 -> 1058 | C125: =C113 -> 1032 | D125: =D113 -> 1116 | E125: =E113 -> 1175 | F125: =F126*F21 -> 1108.224 | G125: =G126*G21 -> 1108.224 | H125: =H126*H21 -> 1108.224 | I125: =I126*I21 -> 1108.224 | J125: =J126*J21 -> 1108.224 | K125: =K126*K21 -> 1108.224 | L125: =L126*L21 -> 1108.224 | M125: =M126*M21 -> 1108.224
A126: % of Revenue | B126: =IF(B21=0,0,B125/B21) -> 0.030018442 | C126: =IF(C21=0,0,C125/C21) -> 0.026987448 | D126: =IF(D21=0,0,D125/D21) -> 0.027544674 | E126: =IF(E21=0,0,E125/E21) -> 0.027566629 | F126: 0.026 | G126: 0.026 | H126: 0.026 | I126: 0.026 | J126: 0.026 | K126: 0.026 | L126: 0.026 | M126: 0.026
A128: Capital Expenditures (selected case) | B128: =CHOOSE(Assump_CapStructure!$K$5,B113,B116,B119,B122,B125) -> 1058 | C128: =CHOOSE(Assump_CapStructure!$K$5,C113,C116,C119,C122,C125) -> 1032 | D128: =CHOOSE(Assump_CapStructure!$K$5,D113,D116,D119,D122,D125) -> 1116 | E128: =CHOOSE(Assump_CapStructure!$K$5,E113,E116,E119,E122,E125) -> 1175 | F128: =CHOOSE(Assump_CapStructure!$K$5,F113,F116,F119,F122,F125) -> 1288.9498 | G128: =CHOOSE(Assump_CapStructure!$K$5,G113,G116,G119,G122,G125) -> 1381.7541 | H128: =CHOOSE(Assump_CapStructure!$K$5,H113,H116,H119,H122,H125) -> 1471.5682 | I128: =CHOOSE(Assump_CapStructure!$K$5,I113,I116,I119,I122,I125) -> 1559.8623 | ... M128: =CHOOSE(Assump_CapStructure!$K$5,M113,M116,M119,M122,M125) -> 1877.9224
A129: % of Revenue | B129: =IF(B24=0,0,B128/B24) -> 0.030018442 | C129: =IF(C24=0,0,C128/C24) -> 0.026987448 | D129: =IF(D24=0,0,D128/D24) -> 0.027544674 | E129: =IF(E24=0,0,E128/E24) -> 0.027566629 | F129: =IF(F24=0,0,F128/F24) -> 0.028 | G129: =IF(G24=0,0,G128/G24) -> 0.028 | H129: =IF(H24=0,0,H128/H24) -> 0.028 | I129: =IF(I24=0,0,I128/I24) -> 0.028 | ... M129: =IF(M24=0,0,M128/M24) -> 0.028
A131: WORKING CAPITAL
A132: ASSETS
A133: Accounts Receivable | B133: 4427 | C133: 4758 | D133: 4841 | E133: 5092 | F133: =F134/365*F24 -> 5612.3546 | G133: =G134/365*G24 -> 5948.8437 | H133: =H134/365*H24 -> 6407.513 | I133: =I134/365*I24 -> 6791.9638 | J133: =J134/365*J24 -> 7165.5218 | K133: =K134/365*K24 -> 7354.7238 | L133: =L134/365*L24 -> 7862.3688 | M133: =M134/365*M24 -> 8084.9887
A134: Days | B134: =B133/B24*365 -> 45.846361 | C134: =C133/C24*365 -> 45.41501 | D134: =D133/D24*365 -> 43.611536 | E134: =E133/E24*365 -> 43.604073 | F134: 44.5 | G134: 44 | H134: 44.5 | I134: 44.5 | J134: 44.5 | K134: 43.5 | L134: 44.5 | M134: 44
A135: % of Revenue | B135: =B133/B24 -> 0.12560647 | C135: =C133/C24 -> 0.12442469 | D135: =D133/D24 -> 0.11948366 | E135: =E133/E24 -> 0.11946321 | F135: =F133/F24 -> 0.12191781 | G135: =G133/G24 -> 0.12054795 | H135: =H133/H24 -> 0.12191781 | I135: =I133/I24 -> 0.12191781 | ... M135: =M133/M24 -> 0.12054795
A136: Inventory | B136: 3827 | C136: 4384 | D136: 4502 | E136: 4706 | F136: =F137/365*F43 -> 5082.6492 | G136: =G137/365*G43 -> 5388.03 | H136: =H137/365*H43 -> 5767.0497 | I136: =I137/365*I43 -> 6152.8324 | J136: =J137/365*J43 -> 6481.1742 | K136: =K137/365*K43 -> 6805.2329 | L136: =L137/365*L43 -> 7043.6224 | M136: =M137/365*M43 -> 7266.2917
A137: Days | B137: =B136/B43*365 -> 60.105637 | C137: =C136/C43*365 -> 63.939903 | D137: =D136/D43*365 -> 62.661303 | E137: =E136/E43*365 -> 61.132109 | F137: 62 | G137: 61.5 | H137: 62 | I137: 62.5 | J137: 62.5 | K137: 62.5 | L137: 62 | M137: 61.5
A138: % of Revenue | B138: =B136/B24 -> 0.10858278 | C138: =C136/C24 -> 0.11464435 | D138: =D136/D24 -> 0.1111166 | E138: =E136/E24 -> 0.11040728 | F138: =F136/F24 -> 0.11041096 | G138: =G136/G24 -> 0.10918356 | H138: =H136/H24 -> 0.10973151 | I138: =I136/I24 -> 0.11044521 | ... M138: =M136/M24 -> 0.1083411
A139: Prepaid and Other Advances | B139: 483 | C139: 470 | D139: 531 | E139: 560 | F139: =F140*F24 -> 598.44096 | G139: =G140*G24 -> 641.52871 | H139: =H140*H24 -> 683.22808 | I139: =I140*I24 -> 724.22176 | J139: =J140*J24 -> 764.05396 | K139: =K140*K24 -> 802.25665 | L139: =L140*L24 -> 838.3582 | M139: =M140*M24 -> 871.89253
...

Sheet Bid Materials-->
A1: Bid Materials -->

Sheet Summary_to delete
A1: Project Osprey
B3: Financial and Returns Summary ($ in millions)
B5: FYE December 31, | C5: 2019A | D5: 2020A | E5: 2021A | F5: 2022A | G5: 2023E | H5: 2024E | I5: 2025E | J5: 2026E | K5: 2027E
B6: Total Revenue | C6: 62.2 | D6: 66.4 | E6: 70.6 | F6: 76.3 | G6: 80.7 | H6: 87 | I6: 93.9 | J6: 98.8 | K6: 103.5
B7: % growth | D7: 0.068 | E7: 0.063 | F7: 0.081 | G7: 0.058 | H7: 0.078 | I7: 0.079 | J7: 0.052 | K7: 0.048
B8: Gross Profit | C8: 23.5 | D8: 24.1 | E8: 27.3 | F8: 27.8 | G8: 30.9 | H8: 31.6 | I8: 34.4 | J8: 38.1 | K8: 39.5
B9: % margin | C9: =C8/C6 -> 0.3778135 | D9: =D8/D6 -> 0.36295181 | E9: =E8/E6 -> 0.38668555 | F9: =F8/F6 -> 0.36435125 | G9: =G8/G6 -> 0.38289963 | H9: =H8/H6 -> 0.36321839 | I9: =I8/I6 -> 0.36634718 | J9: =J8/J6 -> 0.38562753 | K9: =K8/K6 -> 0.38164251
B10: Adj. EBITDA | C10: 9.8 | D10: 10.9 | E10: 11 | F10: 11.8 | G10: 12.7 | H10: 14 | I10: 14.5 | J10: 16 | K10: 17.6
B11: % margin | C11: =C10/C6 -> 0.15755627 | D11: =D10/D6 -> 0.16415663 | E11: =E10/E6 -> 0.15580737 | F11: =F10/F6 -> 0.15465269 | G11: =G10/G6 -> 0.15737299 | H11: =H10/H6 -> 0.16091954 | I11: =I10/I6 -> 0.1544196 | J11: =J10/J6 -> 0.16194332 | K11: =K10/K6 -> 0.17004831
B12: Capex | C12: 1.6 | D12: 1.8 | E12: 1.8 | F12: 1.6 | G12: 1.7 | H12: 2.2 | I12: 2.6 | J12: 2.9 | K12: 2.3
B13: Unlevered FCF | C13: 6.2 | D13: 5.7 | E13: 5.8 | F13: 6.2 | G13: 7 | H13: 7 | I13: 8.8 | J13: 9.2 | K13: 9.2
B16: Working Capital Assumptions
B17: AR days | C17: 52
B18: Inventory days | C18: 48
B19: AP days | C19: 35
B20: Accrued % of revenue | C20: 0.041
B22: 5-year IRR (2023) | C22: 0.238
B24: Enterprise Value Purchase Price Multiples (EV / EBITDA)
C25: Multiple | D25: % Premium | E25: 3-Year Avg.
B26: LTM | C26: 7.4 | D26: WRONG | E26: WRONG
B27: NTM | C27: 6.9 | D27: WRONG | E27: WRONG
B28: 2-Yr Fwd | C28: 6.5 | D28: WRONG | E28: WRONG
B29: Peer Median | C29: 8.1 | D29: WRONG | E29: WRONG
B30: Precedent Median | C30: 7.8 | D30: WRONG | E30: WRONG
B32: STALE - legacy Project Osprey summary carried over on the template; values are hard-coded and not linked. TO DELETE.

Sheet Ownership_
A1: =Assump_CapStructure!$F$7 -> Project Kestrel
A2: ="Prepared by: "&Assump_CapStructure!$F$8 -> Prepared by: Halvern
A3: =Assump_CapStructure!$F$11 -> ($ in 000s)
B5: Current Ownership Group and Rollover Equity
C7: Thomas | D7: Gregory | E7: Anne | F7: Total
C8: Marlbeck | D8: Marlbeck | E8: Marlbeck-Holt
B9: Current Ownership % | C9: =Consideration!C10 -> 0.55 | D9: =Consideration!D10 -> 0.3 | E9: =Consideration!E10 -> 0.15 | F9: =SUM(C9:E9) -> 1
B10: Total cash consideration (ex seller note) | C10: =C9*$F$10 -> 24387.55 | D10: =D9*$F$10 -> 13302.3 | E10: =E9*$F$10 -> 6651.15 | F10: =Consideration!H11 -> 44341
B12: SPONSOR HIGH END
B13: Rollover % of consideration | C13: 0.25 | D13: 0.25 | E13: 0.25
B14: Rollover $ | C14: =C13*C$10 -> 6096.8875 | D14: =D13*D$10 -> 3325.575 | E14: =E13*E$10 -> 1662.7875 | F14: =SUM(C14:E14) -> 11085.25
B15: New Equity Account | F15: =Model!$K$20-Model!$K$17+F14 -> 25324.05
B16: Sponsor Equity Check | F16: =F15-F14 -> 14238.8
B17: Newco Ownership % | C17: =C14/$F$15 -> 0.24075484 | D17: =D14/$F$15 -> 0.13132082 | E17: =E14/$F$15 -> 0.06566041 | F17: =SUM(C17:E17) -> 0.43773607
B19: SPONSOR LOW END
B20: Rollover % of consideration | C20: 0.15 | D20: 0.15 | E20: 0.15
B21: Rollover $ | C21: =C20*C$10 -> 3658.1325 | D21: =D20*D$10 -> 1995.345 | E21: =E20*E$10 -> 997.6725 | F21: =SUM(C21:E21) -> 6651.15
B22: New Equity Account | F22: =Model!$K$20-Model!$K$17+F21 -> 20889.95
B23: Sponsor Equity Check | F23: =F22-F21 -> 14238.8
B24: Newco Ownership % | C24: =C21/$F$22 -> 0.17511447 | D24: =D21/$F$22 -> 0.095516983 | E24: =E21/$F$22 -> 0.047758492 | F24: =SUM(C24:E24) -> 0.31838994
B26: MID RANGE
B27: Rollover % of consideration | C27: 0.2 | D27: 0.2 | E27: 0.2
B28: Rollover $ | C28: =C27*C$10 -> 4877.51 | D28: =D27*D$10 -> 2660.46 | E28: =E27*E$10 -> 1330.23 | F28: =SUM(C28:E28) -> 8868.2
B29: New Equity Account | F29: =Model!$K$20-Model!$K$17+F28 -> 23107
B30: Sponsor Equity Check | F30: =F29-F28 -> 14238.8
B31: Newco Ownership % | C31: =C28/$F$29 -> 0.21108365 | D31: =D28/$F$29 -> 0.11513654 | E31: =E28/$F$29 -> 0.057568269 | F31: =SUM(C31:E31) -> 0.38378846
B33: SELLER PROPOSAL
B34: Rollover % of consideration | C34: 0.3 | D34: 0.3 | E34: 0.3
B35: Rollover $ | C35: =C34*C$10 -> 7316.265 | D35: =D34*D$10 -> 3990.69 | E35: =E34*E$10 -> 1995.345 | F35: =SUM(C35:E35) -> 13302.3
B36: New Equity Account | F36: =Model!$K$20-Model!$K$17+F35 -> 27541.1
B37: Sponsor Equity Check | F37: =F36-F35 -> 14238.8
B38: Newco Ownership % | C38: =C35/$F$36 -> 0.26564898 | D38: =D35/$F$36 -> 0.14489944 | E38: =E35/$F$36 -> 0.072449721 | F38: =SUM(C38:E38) -> 0.48299814
B40: REVISED PROPOSAL
B41: Rollover % of consideration | C41: 0.2 | D41: 0.2 | E41: 0.2
B42: Rollover $ | C42: =C41*C$10 -> 4877.51 | D42: =D41*D$10 -> 2660.46 | E42: =E41*E$10 -> 1330.23 | F42: =SUM(C42:E42) -> 8868.2
B43: New Equity Account | F43: =Model!$K$20-Model!$K$17+F42 -> 23107
B44: Sponsor Equity Check | F44: =F43-F42 -> 14238.8
B45: Newco Ownership % | C45: =C42/$F$43 -> 0.21108365 | D45: =D42/$F$43 -> 0.11513654 | E45: =E42/$F$43 -> 0.057568269 | F45: =SUM(C45:E45) -> 0.38378846
B47: Consideration Summary (Revised Proposal) | H47: Delta vs. LOI | I47: Delta vs. Seller Proposal
B48: Cash proceeds | F48: =F10-F42 -> 35472.8 | H48: =F48-F60 -> -4652.2 | I48: =F48-F54 -> 4434.1
B49: Rollover equity | F49: =F42 -> 8868.2 | H49: =F49-F61 -> 218.2 | I49: =F49-F55 -> -4434.1
B50: Seller Note | F50: =Model!$K$13 -> 4000 | H50: =F50-F62 -> 0 | I50: =F50-F56 -> 0
B51: Total | F51: =SUM(F48:F50) -> 48341 | H51: =F51-F63 -> -4434 | I51: =F51-F57 -> 0
B53: Seller Proposal Consideration Summary
B54: Cash proceeds | F54: =F10-F35 -> 31038.7
B55: Rollover equity | F55: =F35 -> 13302.3
B56: Seller Note | F56: =Model!$K$13 -> 4000
B57: Total | F57: =SUM(F54:F56) -> 48341
B59: LOI Consideration Summary
B60: Cash proceeds | F60: 40125
B61: Rollover equity | F61: 8650
B62: Seller Note | F62: 4000
B63: Total | F63: =SUM(F60:F62) -> 52775

Sheet Sources & Uses
A1: =Assump_CapStructure!$F$7 -> Project Kestrel
A2: ="Prepared by: "&Assump_CapStructure!$F$8 -> Prepared by: Halvern
A3: =Assump_CapStructure!$F$11 -> ($ in 000s)
B5: Transaction Overview
B6: Sources and Uses - [ ] Proposed Transaction
B8: Uses | C8: $000s | D8: % Total | F8: Sources | G8: $000s | H8: % Total
B9: Cash to Seller | C9: =Consideration!$H$22+Model!$D$8 -> 42314.8 | D9: =C9/$C$15 -> 0.72230511 | F9: Revolver (3) | G9: =Model!$K$7 -> 0 | H9: =G9/$G$15 -> 0
B10: Rollover | C10: =Model!$K$17 -> 8868.2 | D10: =C10/$C$15 -> 0.15137839 | F10: Term Loan | G10: =Model!$K$8 -> 23607 | H10: =G10/$G$15 -> 0.40296673
B11: Seller Note | C11: =Model!$K$13 -> 4000 | D11: =C11/$C$15 -> 0.068279194 | F11: Mezzanine | G11: =Model!$K$12 -> 7869 | H11: =G11/$G$15 -> 0.13432224
B12: Total Enterprise Value before Warrant | C12: =SUM(C9:C11) -> 55183 | D12: =C12/$C$15 -> 0.94196269 | F12: Seller Note | G12: =Model!$K$13 -> 4000 | H12: =G12/$G$15 -> 0.068279194
B13: Transaction Expenses (4) | C13: =Model!$D$14 -> 2400 | D13: =C13/$C$15 -> 0.040967516 | F13: Rollover Equity | G13: =Model!$K$17 -> 8868.2 | H13: =G13/$G$15 -> 0.15137839
B14: Excess Cash on the Balance Sheet (5) | C14: =Model!$D$13 -> 1000 | D14: =C14/$C$15 -> 0.017069798 | F14: New Equity (1)(2) | G14: =Model!$K$18+Model!$K$19 -> 14238.8 | H14: =G14/$G$15 -> 0.24305345
B15: Total Uses | C15: =C12+C13+C14 -> 58583 | D15: =C15/$C$15 -> 1 | F15: Total Sources | G15: =SUM(G9:G14) -> 58583 | H15: =G15/$G$15 -> 1
B17: Check | C17: =G15-C15 -> 0
B19: Total Consideration: | F19: Net Debt:
B20: TEV before Warrant | C20: =C12 -> 55183 | F20: Funded Debt | G20: =G10+G11+G12 -> 35476
B21: Implied Real Estate Value Left with Seller | C21: 3150 | F21: Cash | G21: =-Model!$E$116 -> -1100
B22: Rollover Equity Incentive Warrant (7) | C22: ='Mgmt Equity'!$E$40 -> 5005.5026 | F22: Net Debt at Closing | G22: =G20+G21 -> 34376
B23: Total Consideration | C23: =SUM(C20:C22) -> 63338.503
B25: (1) New equity split 10% common / 90% preferred (8% accreting); seller rollover invested in the same classes.
B26: (2) New equity may be syndicated to co-investors alongside Halvern.
B27: (3) $8.0M revolver undrawn at close.
B28: (4) Purchaser transaction expenses (bank, legal, diligence, financing fees).
B29: (5) Excess cash left on the balance sheet for liquidity.
B30: (6) Seller note 6% PIK, subordinated.
B31: (7) Warrant value = present value midpoint at a 10% discount rate of an illustrative year-5 sale (see Mgmt Equity tab).

Sheet Capitalization
A1: =Assump_CapStructure!$F$7 -> Project Kestrel
A2: ="Prepared by: "&Assump_CapStructure!$F$8 -> Prepared by: Halvern
A3: =Assump_CapStructure!$F$11 -> ($ in 000s)
B5: Capitalization Chart for Bid Letter ($ in millions)
B7: Senior + Mezzanine Structure
C8: Drawn | D8: Committed | E8: xEBITDA (1)
B9: Revolving Credit Facility (2) | C9: =Model!$K$7/1000 -> 0 | D9: =Assump_CapStructure!$D$50/1000 -> 8 | E9: =D9/(Model!$E$85/1000) -> 1.0166476
B10: Senior Term Loans (2) | C10: =Model!$K$8/1000+Model!$K$9/1000 -> 23.607 | D10: =C10 -> 23.607 | E10: =D10/(Model!$E$85/1000) -> 3
B11: Mezzanine Loan | C11: =Model!$K$12/1000 -> 7.869 | D11: =C11 -> 7.869 | E11: =D11/(Model!$E$85/1000) -> 1
B12: Equity: From Seller (rollover + seller note) | C12: =Model!$K$17/1000+Model!$K$13/1000 -> 12.8682 | D12: =C12 -> 12.8682 | E12: =D12/(Model!$E$85/1000) -> 1.6353031
B13: Equity: From Purchaser | C13: =Model!$K$18/1000+Model!$K$19/1000 -> 14.2388 | D13: =C13 -> 14.2388 | E13: =D13/(Model!$E$85/1000) -> 1.8094802
B14: Total Capitalization | C14: =SUM(C9:C13) -> 58.583 | D14: =SUM(D9:D13) -> 66.583 | E14: =D14/(Model!$E$85/1000) -> 8.4614309
B16: % of Cap
B17: Total Debt | C17: =SUM(C9:C11)/C14 -> 0.53728897 | D17: =SUM(D9:D11)/D14 -> 0.59288407
B18: Total Equity | C18: =SUM(C12:C13)/C14 -> 0.46271103 | D18: =SUM(D12:D13)/D14 -> 0.40711593
B20: Capitalization with Net Debt:
B21: Cash on Balance Sheet | C21: =-Model!$E$116/1000 -> -1.1
B22: Total Net Debt Capitalization | C22: =C14+C21 -> 57.483
B23: % of Cap using Net Debt - Debt | C23: =(SUM(C9:C11)+C21)/C22 -> 0.52843449
B24: % of Cap using Net Debt - Equity | C24: =SUM(C12:C13)/C22 -> 0.47156551
B25: Net Debt xEBITDA | C25: =(SUM(C9:C11)+C21)/(Model!$E$85/1000) -> 3.860211
B27: Committed Debt Ranges (per term sheets)
C28: Low | D28: High
B29: Senior Term Loans | C29: =C10*0.9 -> 21.2463 | D29: =C10*1.1 -> 25.9677
B30: Mezzanine Loan | C30: =C11*0.85 -> 6.68865 | D30: =C11*1.15 -> 9.04935
B32: ="(1) EBITDA basis is FY2025A adj. EBITDA of $"&TEXT(Model!$E$85/1000,"0.0")&"M." -> (1) EBITDA basis is FY2025A adj. EBITDA of $7.9M.
B33: (2) Per term sheets from the senior lender; revolver commitment $8.0M, undrawn at close.

Sheet Ownership
A1: =Assump_CapStructure!$F$7 -> Project Kestrel
A2: ="Prepared by: "&Assump_CapStructure!$F$8 -> Prepared by: Halvern
A3: =Assump_CapStructure!$F$11 -> ($ in 000s)
B5: Proposed Transaction Overview
B6: Equity Ownership - Proposed Transaction (Pre-Warrant, Pre-Mgmt Equity)
C8: $000s | D8: %
B9: New Equity (1) | C9: =Model!$K$18+Model!$K$19 -> 14238.8 | D9: =C9/$C$13 -> 0.61621154
B10: Rollover Equity (1)(2) | C10: =Model!$K$17 -> 8868.2 | D10: =C10/$C$13 -> 0.38378846
B11: Rollover Equity Incentive Warrant (2) | C11: 0 | D11: =C11/$C$13 -> 0
B12: Management Equity Incentive (3) | C12: 0 | D12: =C12/$C$13 -> 0
B13: Total Equity Account | C13: =SUM(C9:C12) -> 23107 | D13: =C13/$C$13 -> 1
B15: (1) New equity and rollover invested in the same classes: 90% preferred (8% accreting) / 10% common.
B16: (2) Warrant issued to rollover holders, exercisable on a 3.0x return to new equity; shown at zero pre-exercise.
B17: (3) MEIP up to 15% of common (10% assumed in the Model) based on a 3.0x return to new equity net of warrant.

Sheet Mgmt Equity
A1: =Assump_CapStructure!$F$7 -> Project Kestrel
A2: ="Prepared by: "&Assump_CapStructure!$F$8 -> Prepared by: Halvern
A3: =Assump_CapStructure!$F$11 -> ($ in 000s)
B5: ILLUSTRATIVE VALUE OF MANAGEMENT EQUITY INCENTIVE ($ in 000s)
B7: MEIP Value at Exit (1) | C7: =Model!$F$230 -> 4030.706
B8: Basis (2) | C8: 0
B9: Capital Gain | C9: =C7-C8 -> 4030.706
B11: Profits-Interest Structure
B12: Tax on Capital Gain (3) | C12: =-C9*D12 -> -959.30803 | D12: 0.238
B13: Net Proceeds | C13: =C9+C12 -> 3071.398
B14: Net Proceeds Per Point of MEIP | C14: =C13/(Assump_CapStructure!$F$29*100) -> 307.1398
B16: Traditional Option Pool Structure
B17: Ordinary Income Tax (4) | C17: =-C9*D17 -> -1632.4359 | D17: 0.405
B18: Net Proceeds | C18: =C9+C17 -> 2398.2701
B19: Net Proceeds Per Point | C19: =C18/(Assump_CapStructure!$F$29*100) -> 239.82701
B21: AFTER-TAX DIFFERENTIAL | C21: =C13-C18 -> 673.1279
B22: After-tax differential per point | C22: =C14-C19 -> 67.31279
B24: (1) MEIP share of common profits at a 6.0x exit in FY2030E (Model, Gross Returns Summary).
B25: (2) Profits interest issued at a zero basis (liquidation threshold equal to the closing equity value).
B26: (3) 20% long-term capital gains rate plus 3.8% investment income surtax (illustrative).
B27: (4) 37% top ordinary income rate plus 3.5% blended regional rate (illustrative).
B30: Incentive Warrant and MEIP Common Equity Math ($ in 000s)
C31: Assumptions | D31: Ref | E31: Amount
B32: Equity Account (Sponsor + Rollover) | E32: =Model!$K$20 -> 23107
B33: Preferred Equity (90%) (1) | C33: =Assump_CapStructure!$F$31 -> 0.9 | E33: =E32*C33 -> 20796.3
B34: Common Equity (10%) | D34: a | E34: =E32-E33 -> 2310.7
B35: Common Equity w/ 20% Warrant Gross Up | C35: 0.2 | D35: b | E35: =E34/(1-C35) -> 2888.375
B36: Warrant Common Equity | D36: c | E36: =E35-E34 -> 577.675
B37: Common Equity w/ 15% MEIP Gross Up (Final Amount) | C37: 0.15 | D37: d | E37: =E35/(1-C37) -> 3398.0882
B38: MEIP Common Equity | D38: e | E38: =E37-E35 -> 509.71324
B39: 1 point out of 15 points of MEIP Equity | D39: f | E39: =E38/15 -> 33.980882
B40: Warrant PV (midpoint, 10% discount rate, illustrative year-5 sale) | C40: 0.1 | E40: =(Model!$F$226*C35)/(1+C40)^5 -> 5005.5026
B42: (1) Seller's rollover invested in the same classes (20% of both preferred and common).
