Workbook
Name Project_Name: "Project Larkspur"
Name Rev_Total: 'Revenue Build'!$I$41:$BP$41
Name QoE_Aug: 'QoE PF Adj. P&L Aug-26'!$AI$8
Name wrn.CIM: 'CIM Output'!$B$2:$K$40
Name \a: 'Historical & Projected P&L'!$J$8
Name \b: 'Historical & Projected P&L'!$BQ$8
Name Rev_2024: 'CIM Output'!$D$9
Name Rev_2025: 'CIM Output'!$E$9
Name Rev_2026: 'CIM Output'!$F$9
Name Rev_2027: 'CIM Output'!$G$9
Name Rev_2028: 'CIM Output'!$H$9
Name EBITDA_2024: 'CIM Output'!$D$36
Name EBITDA_2025: 'CIM Output'!$E$36
Name EBITDA_2026: 'CIM Output'!$F$36
Name EBITDA_2027: 'CIM Output'!$G$36
Name EBITDA_2028: 'CIM Output'!$H$36
Name Acc_Total: 'Revenue Build'!$I$51:$BP$51
Name Acc_Current: 'Revenue Build'!$I$6:$BP$6
Name Acc_SL: 'Revenue Build'!$I$24:$BP$24
Name Acc_New: 'Revenue Build'!$I$34:$BP$34
Name Months: 'Historical & Projected P&L'!$J$8:$BQ$8
Name Years: 'Historical & Projected P&L'!$J$7:$BQ$7
Name Model_Start: 'Historical & Projected P&L'!$J$8
Name Proj_Start: 'Historical & Projected P&L'!$AS$8
Name Model_End: 'Historical & Projected P&L'!$BQ$8
Name CIM_Table: 'CIM Output'!$B$3:$K$39
Name QoE_LTM: 'QoE PF Adj. P&L Aug-26'!$AK$8:$AK$118
Name QoE_Rev: 'QoE PF Adj. P&L Aug-26'!$D$15:$AI$15
Name QoE_EBITDA: 'QoE PF Adj. P&L Aug-26'!$D$108:$AI$108
Name SW_Build: 'Separate Line Item Builds'!$J$22:$BQ$22
Name SW_Increase: 'Separate Line Item Builds'!$AS$24:$BQ$24
Name Ins_Table: 'Separate Line Item Builds'!$C$46:$D$50
Name Holidays: 'Revenue Build'!$AQ$61:$AQ$70
Name GL_Data: 'GL 2026'!$B$5:$M$4548
Name SepNov_Map: 'Sep - Nov P&L'!$D$6:$D$83
Name SepNov_Sep: 'Sep - Nov P&L'!$I$6:$I$83
Name SepNov_Oct: 'Sep - Nov P&L'!$J$6:$J$83
Name SepNov_Nov: 'Sep - Nov P&L'!$K$6:$K$83
Name Cap_Max: 'Revenue Build'!$I$44
Name Coll_Rate: 'Revenue Build'!$I$56:$BP$56
Name Infl_M: 'Historical & Projected P&L'!$D$121
Name Sen_Living: 'Revenue Build'!$I$22:$BP$28
Name New_Team: 'Revenue Build'!$I$31:$BP$38
Name check_1: 'CIM Output'!$D$33:$H$33
Name check_2: 'CIM Output'!$D$39:$H$39
Name check_3: 'Historical & Projected P&L'!$J$117:$AO$117
Name Opex_Total: 'Historical & Projected P&L'!$D$95:$H$95
Name EBITDA_Row: 'Historical & Projected P&L'!$D$105:$H$105
Name Rev_Row: 'Historical & Projected P&L'!$D$10:$H$10
Name Assumptions_Block: 'Historical & Projected P&L'!$C$120:$BQ$211
Name Accessioner_Cost: 'Separate Line Item Builds'!$B$20
Name Acc_per_Accessioner: 'Separate Line Item Builds'!$B$29
Name NewRep_Pct: 'Separate Line Item Builds'!$B$32
Name Hires_Table: 'Separate Line Item Builds'!$C$13:$E$19
Name Ramp_Anchor: 'Revenue Build'!$AW$10
Name Ramp_Target: 'Revenue Build'!$BD$10
Name NewTeam_Ramp: 'Revenue Build'!$AU$32:$BF$32
Name Workdays: 'Revenue Build'!$I$9:$BP$9
Name Gross_Charges: 'Revenue Build'!$I$58:$BP$58
Name Units: 'Historical & Projected P&L'!$C$8

Sheet Cover
B4: Orivane Clinical Laboratories
B5: Financial Model
B6: QoE financials through Aug-26, Management reported Sep – Nov-26, projections from Dec-26
B8: Prepared by Falkmere Advisory – draft for discussion
B10: Notes / Disclaimer
B11: (1) All figures are synthetic and illustrative; no real company data.
B12: (2) Monthly model; annual roll-ups via SUMIFS on the year row. No debt schedule, no returns – CIM output only.
B13: (3) Workdays use NETWORKDAYS(prior month-end, month-end) as in the original build; holiday list applies from Dec-26.
B14: (4) Sep–Nov-26 S&W, payroll taxes and processing fees are restated from the reported gross payroll figure (see builds tab).
B15: (5) No circular references; fixed-cost projections = trailing 12-month average grown at a monthly inflation input.

Sheet CIM Output
B2: Orivane Clinical Laboratories – Summary Financials | J2: CAGR
C3: $ in actual | D3: 2024 | E3: 2025 | F3: 2026 | G3: 2027 | H3: 2028 | J3: 2024 - 2026 | K3: 2026 - 2028
B4: Summary Financials
B5: Total Accessions | D5: =+'Revenue Build'!C51 -> 85204 | E5: =+'Revenue Build'!D51 -> 92761 | F5: =+'Revenue Build'!E51 -> 101458 | G5: =+'Revenue Build'!F51 -> 113147 | H5: =+'Revenue Build'!G51 -> 136217 | J5: =+(F5/D5)^(1/(F$3-D$3))-1 -> 0.091222109 | K5: =+(H5/F5)^(1/(H$3-F$3))-1 -> 0.158704
B6: YoY % Growth | E6: =+IFERROR(E5/D5-1,) -> 0.088693019 | F6: =+IFERROR(F5/E5-1,) -> 0.093757075 | G6: =+IFERROR(G5/F5-1,) -> 0.11521023 | H6: =+IFERROR(H5/G5-1,) -> 0.20389405
B7: Implied Reimbursement per Accession | D7: =+IFERROR(D9/D5,) -> 149.1937 | E7: =+IFERROR(E9/E5,) -> 148.31017 | F7: =+IFERROR(F9/F5,) -> 147.38235 | G7: =+IFERROR(G9/G5,) -> 143.52708 | H7: =+IFERROR(H9/H5,) -> 139.07986
B9: Net Operating Revenue | D9: =+'Historical & Projected P&L'!D10 -> 12711900 | E9: =+'Historical & Projected P&L'!E10 -> 13757400 | F9: =+'Historical & Projected P&L'!F10 -> 14953118 | G9: =+'Historical & Projected P&L'!G10 -> 16239659 | H9: =+'Historical & Projected P&L'!H10 -> 18945041 | J9: =+(F9/D9)^(1/(F$3-D$3))-1 -> 0.08457765 | K9: =+(H9/F9)^(1/(H$3-F$3))-1 -> 0.12559433
B10: YoY % Growth | E10: =+IFERROR(E9/D9-1,) -> 0.08224577 | F10: =+IFERROR(F9/E9-1,) -> 0.086914554 | G10: =+IFERROR(G9/F9-1,) -> 0.086038284 | H10: =+IFERROR(H9/G9-1,) -> 0.16659109
B12: Operating Expenses
B13: Drugs & Medical Supplies
C14: Medical Supplies | D14: =+SUMIFS('Historical & Projected P&L'!D$10:D$115,'Historical & Projected P&L'!$C$10:$C$115,'CIM Output'!$C14) -> 317200 | E14: =+SUMIFS('Historical & Projected P&L'!E$10:E$115,'Historical & Projected P&L'!$C$10:$C$115,'CIM Output'!$C14) -> 343800 | F14: =+SUMIFS('Historical & Projected P&L'!F$10:F$115,'Historical & Projected P&L'!$C$10:$C$115,'CIM Output'!$C14) -> 430923.07 | G14: =+SUMIFS('Historical & Projected P&L'!G$10:G$115,'Historical & Projected P&L'!$C$10:$C$115,'CIM Output'!$C14) -> 414111.3 | H14: =+SUMIFS('Historical & Projected P&L'!H$10:H$115,'Historical & Projected P&L'!$C$10:$C$115,'CIM Output'!$C14) -> 483098.56
C15: Lab Supplies | D15: =+SUMIFS('Historical & Projected P&L'!D$10:D$115,'Historical & Projected P&L'!$C$10:$C$115,'CIM Output'!$C15) -> 1073300 | E15: =+SUMIFS('Historical & Projected P&L'!E$10:E$115,'Historical & Projected P&L'!$C$10:$C$115,'CIM Output'!$C15) -> 1164300 | F15: =+SUMIFS('Historical & Projected P&L'!F$10:F$115,'Historical & Projected P&L'!$C$10:$C$115,'CIM Output'!$C15) -> 1264791.2 | G15: =+SUMIFS('Historical & Projected P&L'!G$10:G$115,'Historical & Projected P&L'!$C$10:$C$115,'CIM Output'!$C15) -> 1403106.5 | H15: =+SUMIFS('Historical & Projected P&L'!H$10:H$115,'Historical & Projected P&L'!$C$10:$C$115,'CIM Output'!$C15) -> 1636851.6
C16: Drugs | D16: =+SUMIFS('Historical & Projected P&L'!D$10:D$115,'Historical & Projected P&L'!$C$10:$C$115,'CIM Output'!$C16) -> 114800 | E16: =+SUMIFS('Historical & Projected P&L'!E$10:E$115,'Historical & Projected P&L'!$C$10:$C$115,'CIM Output'!$C16) -> 123600 | F16: =+SUMIFS('Historical & Projected P&L'!F$10:F$115,'Historical & Projected P&L'!$C$10:$C$115,'CIM Output'!$C16) -> 100193.01 | G16: =+SUMIFS('Historical & Projected P&L'!G$10:G$115,'Historical & Projected P&L'!$C$10:$C$115,'CIM Output'!$C16) -> 144532.96 | H16: =+SUMIFS('Historical & Projected P&L'!H$10:H$115,'Historical & Projected P&L'!$C$10:$C$115,'CIM Output'!$C16) -> 168610.87
C17: Pharmacy | D17: =+SUMIFS('Historical & Projected P&L'!D$10:D$115,'Historical & Projected P&L'!$C$10:$C$115,'CIM Output'!$C17) -> 75600 | E17: =+SUMIFS('Historical & Projected P&L'!E$10:E$115,'Historical & Projected P&L'!$C$10:$C$115,'CIM Output'!$C17) -> 82400 | F17: =+SUMIFS('Historical & Projected P&L'!F$10:F$115,'Historical & Projected P&L'!$C$10:$C$115,'CIM Output'!$C17) -> 65089.829 | G17: =+SUMIFS('Historical & Projected P&L'!G$10:G$115,'Historical & Projected P&L'!$C$10:$C$115,'CIM Output'!$C17) -> 94190.022 | H17: =+SUMIFS('Historical & Projected P&L'!H$10:H$115,'Historical & Projected P&L'!$C$10:$C$115,'CIM Output'!$C17) -> 109881.24
B18: Total Drugs & Medical Supplies | D18: =SUM(D14:D17) -> 1580900 | E18: =SUM(E14:E17) -> 1714100 | F18: =SUM(F14:F17) -> 1860997.1 | G18: =SUM(G14:G17) -> 2055940.8 | H18: =SUM(H14:H17) -> 2398442.3
B20: Employee Salaries & Wages
C21: Salaries & Wages | D21: =+SUMIFS('Historical & Projected P&L'!D$10:D$115,'Historical & Projected P&L'!$C$10:$C$115,'CIM Output'!$C21) -> 3317600 | E21: =+SUMIFS('Historical & Projected P&L'!E$10:E$115,'Historical & Projected P&L'!$C$10:$C$115,'CIM Output'!$C21) -> 3509800 | F21: =+SUMIFS('Historical & Projected P&L'!F$10:F$115,'Historical & Projected P&L'!$C$10:$C$115,'CIM Output'!$C21) -> 3716855.6 | G21: =+SUMIFS('Historical & Projected P&L'!G$10:G$115,'Historical & Projected P&L'!$C$10:$C$115,'CIM Output'!$C21) -> 4327258.5 | H21: =+SUMIFS('Historical & Projected P&L'!H$10:H$115,'Historical & Projected P&L'!$C$10:$C$115,'CIM Output'!$C21) -> 4610459.6
C22: Contract Labor | D22: =+SUMIFS('Historical & Projected P&L'!D$10:D$115,'Historical & Projected P&L'!$C$10:$C$115,'CIM Output'!$C22) -> 187900 | E22: =+SUMIFS('Historical & Projected P&L'!E$10:E$115,'Historical & Projected P&L'!$C$10:$C$115,'CIM Output'!$C22) -> 205500 | F22: =+SUMIFS('Historical & Projected P&L'!F$10:F$115,'Historical & Projected P&L'!$C$10:$C$115,'CIM Output'!$C22) -> 249542.07 | G22: =+SUMIFS('Historical & Projected P&L'!G$10:G$115,'Historical & Projected P&L'!$C$10:$C$115,'CIM Output'!$C22) -> 241970.92 | H22: =+SUMIFS('Historical & Projected P&L'!H$10:H$115,'Historical & Projected P&L'!$C$10:$C$115,'CIM Output'!$C22) -> 282281.12
C23: Sales Rep Expense | D23: =+SUMIFS('Historical & Projected P&L'!D$10:D$115,'Historical & Projected P&L'!$C$10:$C$115,'CIM Output'!$C23) -> 636600 | E23: =+SUMIFS('Historical & Projected P&L'!E$10:E$115,'Historical & Projected P&L'!$C$10:$C$115,'CIM Output'!$C23) -> 684700 | F23: =+SUMIFS('Historical & Projected P&L'!F$10:F$115,'Historical & Projected P&L'!$C$10:$C$115,'CIM Output'!$C23) -> 747121.01 | G23: =+SUMIFS('Historical & Projected P&L'!G$10:G$115,'Historical & Projected P&L'!$C$10:$C$115,'CIM Output'!$C23) -> 873223.9 | H23: =+SUMIFS('Historical & Projected P&L'!H$10:H$115,'Historical & Projected P&L'!$C$10:$C$115,'CIM Output'!$C23) -> 1116103.7
C24: Other Personnel Costs | D24: =+SUMIFS('Historical & Projected P&L'!D$10:D$115,'Historical & Projected P&L'!$C$10:$C$115,'CIM Output'!$C24) -> 88400 | E24: =+SUMIFS('Historical & Projected P&L'!E$10:E$115,'Historical & Projected P&L'!$C$10:$C$115,'CIM Output'!$C24) -> 95900 | F24: =+SUMIFS('Historical & Projected P&L'!F$10:F$115,'Historical & Projected P&L'!$C$10:$C$115,'CIM Output'!$C24) -> 74791.667 | G24: =+SUMIFS('Historical & Projected P&L'!G$10:G$115,'Historical & Projected P&L'!$C$10:$C$115,'CIM Output'!$C24) -> 78467.515 | H24: =+SUMIFS('Historical & Projected P&L'!H$10:H$115,'Historical & Projected P&L'!$C$10:$C$115,'CIM Output'!$C24) -> 81827.338
B25: Total Employee Salaries & Wages | D25: =SUM(D21:D24) -> 4230500 | E25: =SUM(E21:E24) -> 4495900 | F25: =SUM(F21:F24) -> 4788310.3 | G25: =SUM(G21:G24) -> 5520920.9 | H25: =SUM(H21:H24) -> 6090671.7
B27: Laboratory Fees | D27: =+SUMIFS('Historical & Projected P&L'!D$10:D$115,'Historical & Projected P&L'!$C$10:$C$115,'CIM Output'!$B27) -> 729800 | E27: =+SUMIFS('Historical & Projected P&L'!E$10:E$115,'Historical & Projected P&L'!$C$10:$C$115,'CIM Output'!$B27) -> 792200 | F27: =+SUMIFS('Historical & Projected P&L'!F$10:F$115,'Historical & Projected P&L'!$C$10:$C$115,'CIM Output'!$B27) -> 863135.37 | G27: =+SUMIFS('Historical & Projected P&L'!G$10:G$115,'Historical & Projected P&L'!$C$10:$C$115,'CIM Output'!$B27) -> 948396.08 | H27: =+SUMIFS('Historical & Projected P&L'!H$10:H$115,'Historical & Projected P&L'!$C$10:$C$115,'CIM Output'!$B27) -> 1106390.4
B28: Billing & Collection Fees | D28: =+SUMIFS('Historical & Projected P&L'!D$10:D$115,'Historical & Projected P&L'!$C$10:$C$115,'CIM Output'!$B28) -> 448300 | E28: =+SUMIFS('Historical & Projected P&L'!E$10:E$115,'Historical & Projected P&L'!$C$10:$C$115,'CIM Output'!$B28) -> 476000 | F28: =+SUMIFS('Historical & Projected P&L'!F$10:F$115,'Historical & Projected P&L'!$C$10:$C$115,'CIM Output'!$B28) -> 581873.31 | G28: =+SUMIFS('Historical & Projected P&L'!G$10:G$115,'Historical & Projected P&L'!$C$10:$C$115,'CIM Output'!$B28) -> 578131.86 | H28: =+SUMIFS('Historical & Projected P&L'!H$10:H$115,'Historical & Projected P&L'!$C$10:$C$115,'CIM Output'!$B28) -> 674443.48
B29: Total Employee Taxes & Benefits | D29: =+SUMIFS('Historical & Projected P&L'!D$10:D$115,'Historical & Projected P&L'!$C$10:$C$115,'CIM Output'!$B29) -> 522000 | E29: =+SUMIFS('Historical & Projected P&L'!E$10:E$115,'Historical & Projected P&L'!$C$10:$C$115,'CIM Output'!$B29) -> 549300 | F29: =+SUMIFS('Historical & Projected P&L'!F$10:F$115,'Historical & Projected P&L'!$C$10:$C$115,'CIM Output'!$B29) -> 592903.9 | G29: =+SUMIFS('Historical & Projected P&L'!G$10:G$115,'Historical & Projected P&L'!$C$10:$C$115,'CIM Output'!$B29) -> 682997.79 | H29: =+SUMIFS('Historical & Projected P&L'!H$10:H$115,'Historical & Projected P&L'!$C$10:$C$115,'CIM Output'!$B29) -> 753482.15
B30: Total Occupancy Costs | D30: =+SUMIFS('Historical & Projected P&L'!D$10:D$115,'Historical & Projected P&L'!$C$10:$C$115,'CIM Output'!$B30) -> 710400 | E30: =+SUMIFS('Historical & Projected P&L'!E$10:E$115,'Historical & Projected P&L'!$C$10:$C$115,'CIM Output'!$B30) -> 768100 | F30: =+SUMIFS('Historical & Projected P&L'!F$10:F$115,'Historical & Projected P&L'!$C$10:$C$115,'CIM Output'!$B30) -> 806806.72 | G30: =+SUMIFS('Historical & Projected P&L'!G$10:G$115,'Historical & Projected P&L'!$C$10:$C$115,'CIM Output'!$B30) -> 825178.33 | H30: =+SUMIFS('Historical & Projected P&L'!H$10:H$115,'Historical & Projected P&L'!$C$10:$C$115,'CIM Output'!$B30) -> 860510.82
B31: All Other Operating Expenses | D31: =+'Historical & Projected P&L'!D95-(D18+D25+SUM(D27:D30)) -> 1996400 | E31: =+'Historical & Projected P&L'!E95-(E18+E25+SUM(E27:E30)) -> 2143600 | F31: =+'Historical & Projected P&L'!F95-(F18+F25+SUM(F27:F30)) -> 2237574.7 | G31: =+'Historical & Projected P&L'!G95-(G18+G25+SUM(G27:G30)) -> 2357629.1 | H31: =+'Historical & Projected P&L'!H95-(H18+H25+SUM(H27:H30)) -> 2594093
B32: Total Operating Expenses | D32: =+D18+D25+SUM(D27:D31) -> 10218300 | E32: =+E18+E25+SUM(E27:E31) -> 10939200 | F32: =+F18+F25+SUM(F27:F31) -> 11731601 | G32: =+G18+G25+SUM(G27:G31) -> 12969195 | H32: =+H18+H25+SUM(H27:H31) -> 14478034 | J32: =+(F32/D32)^(1/(F$3-D$3))-1 -> 0.071492969 | K32: =+(H32/F32)^(1/(H$3-F$3))-1 -> 0.11090301
B33: check | D33: =+D32-'Historical & Projected P&L'!D95 -> 0 | E33: =+E32-'Historical & Projected P&L'!E95 -> 0 | F33: =+F32-'Historical & Projected P&L'!F95 -> 0 | G33: =+G32-'Historical & Projected P&L'!G95 -> 0 | H33: =+H32-'Historical & Projected P&L'!H95 -> 0
B34: % of Revenue | D34: =+IFERROR(D32/D9,) -> 0.80383735 | E34: =+IFERROR(E32/E9,) -> 0.79515025 | F34: =+IFERROR(F32/F9,) -> 0.78455886 | G34: =+IFERROR(G32/G9,) -> 0.79861251 | H34: =+IFERROR(H32/H9,) -> 0.76421231
B36: EBITDA, as adjusted | D36: =+D9-D32-SUMIFS('Historical & Projected P&L'!D$10:D$115,'Historical & Projected P&L'!$C$10:$C$115,"Non-Operating Expense / (Income)")+SUMIFS('Historical & Projected P&L'!D$10:D$115,'Historical & Projected P&L'!$C$10:$C$115,"Non-Operating Income / (Expense)") -> 2475500 | E36: =+E9-E32-SUMIFS('Historical & Projected P&L'!E$10:E$115,'Historical & Projected P&L'!$C$10:$C$115,"Non-Operating Expense / (Income)")+SUMIFS('Historical & Projected P&L'!E$10:E$115,'Historical & Projected P&L'!$C$10:$C$115,"Non-Operating Income / (Expense)") -> 2800700 | F36: =+F9-F32-SUMIFS('Historical & Projected P&L'!F$10:F$115,'Historical & Projected P&L'!$C$10:$C$115,"Non-Operating Expense / (Income)")+SUMIFS('Historical & Projected P&L'!F$10:F$115,'Historical & Projected P&L'!$C$10:$C$115,"Non-Operating Income / (Expense)") -> 3207266.8 | G36: =+G9-G32-SUMIFS('Historical & Projected P&L'!G$10:G$115,'Historical & Projected P&L'!$C$10:$C$115,"Non-Operating Expense / (Income)")+SUMIFS('Historical & Projected P&L'!G$10:G$115,'Historical & Projected P&L'!$C$10:$C$115,"Non-Operating Income / (Expense)") -> 3255118.4 | H36: =+H9-H32-SUMIFS('Historical & Projected P&L'!H$10:H$115,'Historical & Projected P&L'!$C$10:$C$115,"Non-Operating Expense / (Income)")+SUMIFS('Historical & Projected P&L'!H$10:H$115,'Historical & Projected P&L'!$C$10:$C$115,"Non-Operating Income / (Expense)") -> 4451004.9 | J36: =+(F36/D36)^(1/(F$3-D$3))-1 -> 0.13824587 | K36: =+(H36/F36)^(1/(H$3-F$3))-1 -> 0.17804393
B37: YoY % Growth | E37: =+IFERROR(E36/D36-1,) -> 0.1313674 | F37: =+IFERROR(F36/E36-1,) -> 0.14516615 | G37: =+IFERROR(G36/F36-1,) -> 0.014919732 | H37: =+IFERROR(H36/G36-1,) -> 0.36738647
B38: % Margin | D38: =+IFERROR(D36/D9,) -> 0.19473879 | E38: =+IFERROR(E36/E9,) -> 0.20357771 | F38: =+IFERROR(F36/F9,) -> 0.21448816 | G38: =+IFERROR(G36/G9,) -> 0.20044254 | H38: =+IFERROR(H36/H9,) -> 0.234943
B39: check | D39: =+D36-'Historical & Projected P&L'!D105 -> 0 | E39: =+E36-'Historical & Projected P&L'!E105 -> 0 | F39: =+F36-'Historical & Projected P&L'!F105 -> 0 | G39: =+G36-'Historical & Projected P&L'!G105 -> 0 | H39: =+H36-'Historical & Projected P&L'!H105 -> 0
B40: (1) 2024–Aug-26 per QoE databook; Sep–Nov-26 management reported; Dec-26 onward projected. EBITDA as adjusted is net of non-operating items.

Sheet Historical & Projected P&L
A2: Orivane Clinical Laboratories, LLC
A3: Adj. P&L
A4: Accrual Basis
C6: Fiscal year ending December 31,
J7: =+YEAR(J8) -> 2024 | K7: =+YEAR(K8) -> 2024 | L7: =+YEAR(L8) -> 2024 | M7: =+YEAR(M8) -> 2024 | N7: =+YEAR(N8) -> 2024 | O7: =+YEAR(O8) -> 2024 | P7: =+YEAR(P8) -> 2024 | Q7: =+YEAR(Q8) -> 2024 | ... BQ7: =+YEAR(BQ8) -> 2028
C8: $ in actual | D8: 2024 | E8: 2025 | F8: 2026 | G8: 2027 | H8: 2028 | J8: 45322 | K8: =+EOMONTH(J8,1) -> 45351 | L8: =+EOMONTH(K8,1) -> 45382 | M8: =+EOMONTH(L8,1) -> 45412 | N8: =+EOMONTH(M8,1) -> 45443 | O8: =+EOMONTH(N8,1) -> 45473 | P8: =+EOMONTH(O8,1) -> 45504 | Q8: =+EOMONTH(P8,1) -> 45535 | R8: =+EOMONTH(Q8,1) -> 45565 | ... BQ8: =+EOMONTH(BP8,1) -> 47118
A9: Adjusted P&L
A10: x | C10: Net Operating Revenue | D10: =+SUMIFS($J10:$BQ10,$J$7:$BQ$7,D$8) -> 12711900 | E10: =+SUMIFS($J10:$BQ10,$J$7:$BQ$7,E$8) -> 13757400 | F10: =+SUMIFS($J10:$BQ10,$J$7:$BQ$7,F$8) -> 14953118 | G10: =+SUMIFS($J10:$BQ10,$J$7:$BQ$7,G$8) -> 16239659 | H10: =+SUMIFS($J10:$BQ10,$J$7:$BQ$7,H$8) -> 18945041 | J10: =+'QoE PF Adj. P&L Aug-26'!D15*1000 -> 1059600 | K10: =+'QoE PF Adj. P&L Aug-26'!E15*1000 -> 957100 | L10: =+'QoE PF Adj. P&L Aug-26'!F15*1000 -> 1053300 | M10: =+'QoE PF Adj. P&L Aug-26'!G15*1000 -> 1024700 | N10: =+'QoE PF Adj. P&L Aug-26'!H15*1000 -> 1153100 | O10: =+'QoE PF Adj. P&L Aug-26'!I15*1000 -> 972600 | P10: =+'QoE PF Adj. P&L Aug-26'!J15*1000 -> 1073500 | Q10: =+'QoE PF Adj. P&L Aug-26'!K15*1000 -> 1097400 | ... AO10: =+'QoE PF Adj. P&L Aug-26'!AI15*1000 -> 1233000 | AP10: =+SUMIFS('Sep - Nov P&L'!I:I,'Sep - Nov P&L'!$D:$D,$C10) -> 1311360.1 | AQ10: =+SUMIFS('Sep - Nov P&L'!J:J,'Sep - Nov P&L'!$D:$D,$C10) -> 1394034.4 | AR10: =+SUMIFS('Sep - Nov P&L'!K:K,'Sep - Nov P&L'!$D:$D,$C10) -> 1183374 | AS10: =+'Revenue Build'!AR41 -> 1291349.8 | AT10: =+'Revenue Build'!AS41 -> 1179018.3 | AU10: =+'Revenue Build'!AT41 -> 1122852.5 | AV10: =+'Revenue Build'!AU41 -> 1326493.8 | AW10: =+'Revenue Build'!AV41 -> 1352253.8 | AX10: =+'Revenue Build'!AW41 -> 1258146.3 | AY10: =+'Revenue Build'!AX41 -> 1344727.6 | AZ10: =+'Revenue Build'!AY41 -> 1371375.2 | ... BQ10: =+'Revenue Build'!BP41 -> 1563044.9
C11: YoY % Growth | E11: =+IFERROR(E10/D10-1,) -> 0.08224577 | F11: =+IFERROR(F10/E10-1,) -> 0.086914554 | G11: =+IFERROR(G10/F10-1,) -> 0.086038284 | H11: =+IFERROR(H10/G10-1,) -> 0.16659109
C13: Operating Expenses
C14: Employee Salaries & Wages
C15: Salaries & Wages | D15: =+SUMIFS($J15:$BQ15,$J$7:$BQ$7,D$8) -> 3317600 | E15: =+SUMIFS($J15:$BQ15,$J$7:$BQ$7,E$8) -> 3509800 | F15: =+SUMIFS($J15:$BQ15,$J$7:$BQ$7,F$8) -> 3716855.6 | G15: =+SUMIFS($J15:$BQ15,$J$7:$BQ$7,G$8) -> 4327258.5 | H15: =+SUMIFS($J15:$BQ15,$J$7:$BQ$7,H$8) -> 4610459.6 | J15: =+INDEX('QoE PF Adj. P&L Aug-26'!$D$11:$AI$108,MATCH($C15,'QoE PF Adj. P&L Aug-26'!$C$11:$C$108,0),MATCH(J$8,'QoE PF Adj. P&L Aug-26'!$D$8:$AI$8,0))*1000 -> 277600 | K15: =+INDEX('QoE PF Adj. P&L Aug-26'!$D$11:$AI$108,MATCH($C15,'QoE PF Adj. P&L Aug-26'!$C$11:$C$108,0),MATCH(K$8,'QoE PF Adj. P&L Aug-26'!$D$8:$AI$8,0))*1000 -> 272100 | L15: =+INDEX('QoE PF Adj. P&L Aug-26'!$D$11:$AI$108,MATCH($C15,'QoE PF Adj. P&L Aug-26'!$C$11:$C$108,0),MATCH(L$8,'QoE PF Adj. P&L Aug-26'!$D$8:$AI$8,0))*1000 -> 278100 | M15: =+INDEX('QoE PF Adj. P&L Aug-26'!$D$11:$AI$108,MATCH($C15,'QoE PF Adj. P&L Aug-26'!$C$11:$C$108,0),MATCH(M$8,'QoE PF Adj. P&L Aug-26'!$D$8:$AI$8,0))*1000 -> 280500 | N15: =+INDEX('QoE PF Adj. P&L Aug-26'!$D$11:$AI$108,MATCH($C15,'QoE PF Adj. P&L Aug-26'!$C$11:$C$108,0),MATCH(N$8,'QoE PF Adj. P&L Aug-26'!$D$8:$AI$8,0))*1000 -> 274300 | O15: =+INDEX('QoE PF Adj. P&L Aug-26'!$D$11:$AI$108,MATCH($C15,'QoE PF Adj. P&L Aug-26'!$C$11:$C$108,0),MATCH(O$8,'QoE PF Adj. P&L Aug-26'!$D$8:$AI$8,0))*1000 -> 276000 | P15: =+INDEX('QoE PF Adj. P&L Aug-26'!$D$11:$AI$108,MATCH($C15,'QoE PF Adj. P&L Aug-26'!$C$11:$C$108,0),MATCH(P$8,'QoE PF Adj. P&L Aug-26'!$D$8:$AI$8,0))*1000 -> 277800 | Q15: =+INDEX('QoE PF Adj. P&L Aug-26'!$D$11:$AI$108,MATCH($C15,'QoE PF Adj. P&L Aug-26'!$C$11:$C$108,0),MATCH(Q$8,'QoE PF Adj. P&L Aug-26'!$D$8:$AI$8,0))*1000 -> 276200 | ... AO15: =+INDEX('QoE PF Adj. P&L Aug-26'!$D$11:$AI$108,MATCH($C15,'QoE PF Adj. P&L Aug-26'!$C$11:$C$108,0),MATCH(AO$8,'QoE PF Adj. P&L Aug-26'!$D$8:$AI$8,0))*1000 -> 308500 | AP15: =+'Separate Line Item Builds'!AP61 -> 310028.94 | AQ15: =+'Separate Line Item Builds'!AQ61 -> 314092.79 | AR15: =+'Separate Line Item Builds'!AR61 -> 309783.59 | AS15: =+'Separate Line Item Builds'!AS61 -> 326450.26 | AT15: =+'Separate Line Item Builds'!AT61 -> 323243.77 | AU15: =+'Separate Line Item Builds'!AU61 -> 340743.77 | AV15: =+'Separate Line Item Builds'!AV61 -> 361993.77 | AW15: =+'Separate Line Item Builds'!AW61 -> 361993.77 | ... BQ15: =+'Separate Line Item Builds'!BQ61 -> 384566.08
B16: % rev | C16: Contract Labor | D16: =+SUMIFS($J16:$BQ16,$J$7:$BQ$7,D$8) -> 187900 | E16: =+SUMIFS($J16:$BQ16,$J$7:$BQ$7,E$8) -> 205500 | F16: =+SUMIFS($J16:$BQ16,$J$7:$BQ$7,F$8) -> 249542.07 | G16: =+SUMIFS($J16:$BQ16,$J$7:$BQ$7,G$8) -> 241970.92 | H16: =+SUMIFS($J16:$BQ16,$J$7:$BQ$7,H$8) -> 282281.12 | J16: =+INDEX('QoE PF Adj. P&L Aug-26'!$D$11:$AI$108,MATCH($C16,'QoE PF Adj. P&L Aug-26'!$C$11:$C$108,0),MATCH(J$8,'QoE PF Adj. P&L Aug-26'!$D$8:$AI$8,0))*1000 -> 15500 | K16: =+INDEX('QoE PF Adj. P&L Aug-26'!$D$11:$AI$108,MATCH($C16,'QoE PF Adj. P&L Aug-26'!$C$11:$C$108,0),MATCH(K$8,'QoE PF Adj. P&L Aug-26'!$D$8:$AI$8,0))*1000 -> 14300 | L16: =+INDEX('QoE PF Adj. P&L Aug-26'!$D$11:$AI$108,MATCH($C16,'QoE PF Adj. P&L Aug-26'!$C$11:$C$108,0),MATCH(L$8,'QoE PF Adj. P&L Aug-26'!$D$8:$AI$8,0))*1000 -> 15100 | M16: =+INDEX('QoE PF Adj. P&L Aug-26'!$D$11:$AI$108,MATCH($C16,'QoE PF Adj. P&L Aug-26'!$C$11:$C$108,0),MATCH(M$8,'QoE PF Adj. P&L Aug-26'!$D$8:$AI$8,0))*1000 -> 15400 | N16: =+INDEX('QoE PF Adj. P&L Aug-26'!$D$11:$AI$108,MATCH($C16,'QoE PF Adj. P&L Aug-26'!$C$11:$C$108,0),MATCH(N$8,'QoE PF Adj. P&L Aug-26'!$D$8:$AI$8,0))*1000 -> 16500 | O16: =+INDEX('QoE PF Adj. P&L Aug-26'!$D$11:$AI$108,MATCH($C16,'QoE PF Adj. P&L Aug-26'!$C$11:$C$108,0),MATCH(O$8,'QoE PF Adj. P&L Aug-26'!$D$8:$AI$8,0))*1000 -> 14800 | P16: =+INDEX('QoE PF Adj. P&L Aug-26'!$D$11:$AI$108,MATCH($C16,'QoE PF Adj. P&L Aug-26'!$C$11:$C$108,0),MATCH(P$8,'QoE PF Adj. P&L Aug-26'!$D$8:$AI$8,0))*1000 -> 15700 | Q16: =+INDEX('QoE PF Adj. P&L Aug-26'!$D$11:$AI$108,MATCH($C16,'QoE PF Adj. P&L Aug-26'!$C$11:$C$108,0),MATCH(Q$8,'QoE PF Adj. P&L Aug-26'!$D$8:$AI$8,0))*1000 -> 17000 | ... AO16: =+INDEX('QoE PF Adj. P&L Aug-26'!$D$11:$AI$108,MATCH($C16,'QoE PF Adj. P&L Aug-26'!$C$11:$C$108,0),MATCH(AO$8,'QoE PF Adj. P&L Aug-26'!$D$8:$AI$8,0))*1000 -> 18500 | AP16: =+SUMIFS('Sep - Nov P&L'!I:I,'Sep - Nov P&L'!$D:$D,$C16) -> 29625.63 | AQ16: =+SUMIFS('Sep - Nov P&L'!J:J,'Sep - Nov P&L'!$D:$D,$C16) -> 30177.2 | AR16: =+SUMIFS('Sep - Nov P&L'!K:K,'Sep - Nov P&L'!$D:$D,$C16) -> 26298.13 | AS16: =+AS$10*AS124 -> 19241.113 | AT16: =+AT$10*AT124 -> 17567.372 | AU16: =+AU$10*AU124 -> 16730.502 | AV16: =+AV$10*AV124 -> 19764.758 | AW16: =+AW$10*AW124 -> 20148.582 | AX16: =+AX$10*AX124 -> 18746.379 | AY16: =+AY$10*AY124 -> 20036.441 | AZ16: =+AZ$10*AZ124 -> 20433.49 | ... BQ16: =+BQ$10*BQ124 -> 23289.369
C17: Sales Rep Expense | D17: =+SUMIFS($J17:$BQ17,$J$7:$BQ$7,D$8) -> 636600 | E17: =+SUMIFS($J17:$BQ17,$J$7:$BQ$7,E$8) -> 684700 | F17: =+SUMIFS($J17:$BQ17,$J$7:$BQ$7,F$8) -> 747121.01 | G17: =+SUMIFS($J17:$BQ17,$J$7:$BQ$7,G$8) -> 873223.9 | H17: =+SUMIFS($J17:$BQ17,$J$7:$BQ$7,H$8) -> 1116103.7 | J17: =+INDEX('QoE PF Adj. P&L Aug-26'!$D$11:$AI$108,MATCH($C17,'QoE PF Adj. P&L Aug-26'!$C$11:$C$108,0),MATCH(J$8,'QoE PF Adj. P&L Aug-26'!$D$8:$AI$8,0))*1000 -> 51700 | K17: =+INDEX('QoE PF Adj. P&L Aug-26'!$D$11:$AI$108,MATCH($C17,'QoE PF Adj. P&L Aug-26'!$C$11:$C$108,0),MATCH(K$8,'QoE PF Adj. P&L Aug-26'!$D$8:$AI$8,0))*1000 -> 48600 | L17: =+INDEX('QoE PF Adj. P&L Aug-26'!$D$11:$AI$108,MATCH($C17,'QoE PF Adj. P&L Aug-26'!$C$11:$C$108,0),MATCH(L$8,'QoE PF Adj. P&L Aug-26'!$D$8:$AI$8,0))*1000 -> 53100 | M17: =+INDEX('QoE PF Adj. P&L Aug-26'!$D$11:$AI$108,MATCH($C17,'QoE PF Adj. P&L Aug-26'!$C$11:$C$108,0),MATCH(M$8,'QoE PF Adj. P&L Aug-26'!$D$8:$AI$8,0))*1000 -> 52300 | N17: =+INDEX('QoE PF Adj. P&L Aug-26'!$D$11:$AI$108,MATCH($C17,'QoE PF Adj. P&L Aug-26'!$C$11:$C$108,0),MATCH(N$8,'QoE PF Adj. P&L Aug-26'!$D$8:$AI$8,0))*1000 -> 57500 | O17: =+INDEX('QoE PF Adj. P&L Aug-26'!$D$11:$AI$108,MATCH($C17,'QoE PF Adj. P&L Aug-26'!$C$11:$C$108,0),MATCH(O$8,'QoE PF Adj. P&L Aug-26'!$D$8:$AI$8,0))*1000 -> 50200 | P17: =+INDEX('QoE PF Adj. P&L Aug-26'!$D$11:$AI$108,MATCH($C17,'QoE PF Adj. P&L Aug-26'!$C$11:$C$108,0),MATCH(P$8,'QoE PF Adj. P&L Aug-26'!$D$8:$AI$8,0))*1000 -> 54400 | Q17: =+INDEX('QoE PF Adj. P&L Aug-26'!$D$11:$AI$108,MATCH($C17,'QoE PF Adj. P&L Aug-26'!$C$11:$C$108,0),MATCH(Q$8,'QoE PF Adj. P&L Aug-26'!$D$8:$AI$8,0))*1000 -> 56300 | ... AO17: =+INDEX('QoE PF Adj. P&L Aug-26'!$D$11:$AI$108,MATCH($C17,'QoE PF Adj. P&L Aug-26'!$C$11:$C$108,0),MATCH(AO$8,'QoE PF Adj. P&L Aug-26'!$D$8:$AI$8,0))*1000 -> 63300 | AP17: =+SUMIFS('Sep - Nov P&L'!I:I,'Sep - Nov P&L'!$D:$D,$C17) -> 63206.61 | AQ17: =+SUMIFS('Sep - Nov P&L'!J:J,'Sep - Nov P&L'!$D:$D,$C17) -> 69262.96 | AR17: =+SUMIFS('Sep - Nov P&L'!K:K,'Sep - Nov P&L'!$D:$D,$C17) -> 59675.72 | AS17: =+'Separate Line Item Builds'!AS35 -> 59675.72 | AT17: =+'Separate Line Item Builds'!AT35 -> 61465.992 | AU17: =+'Separate Line Item Builds'!AU35 -> 61465.992 | AV17: =+'Separate Line Item Builds'!AV35 -> 64041.992 | AW17: =+'Separate Line Item Builds'!AW35 -> 66617.992 | AX17: =+'Separate Line Item Builds'!AX35 -> 68521.992 | AY17: =+'Separate Line Item Builds'!AY35 -> 71321.992 | AZ17: =+'Separate Line Item Builds'!AZ35 -> 73785.992 | ... BQ17: =+'Separate Line Item Builds'!BQ35 -> 92877.971
C18: Other Personnel Costs | D18: =+SUMIFS($J18:$BQ18,$J$7:$BQ$7,D$8) -> 88400 | E18: =+SUMIFS($J18:$BQ18,$J$7:$BQ$7,E$8) -> 95900 | F18: =+SUMIFS($J18:$BQ18,$J$7:$BQ$7,F$8) -> 74791.667 | G18: =+SUMIFS($J18:$BQ18,$J$7:$BQ$7,G$8) -> 78467.515 | H18: =+SUMIFS($J18:$BQ18,$J$7:$BQ$7,H$8) -> 81827.338 | J18: =+INDEX('QoE PF Adj. P&L Aug-26'!$D$11:$AI$108,MATCH($C18,'QoE PF Adj. P&L Aug-26'!$C$11:$C$108,0),MATCH(J$8,'QoE PF Adj. P&L Aug-26'!$D$8:$AI$8,0))*1000 -> 7100 | K18: =+INDEX('QoE PF Adj. P&L Aug-26'!$D$11:$AI$108,MATCH($C18,'QoE PF Adj. P&L Aug-26'!$C$11:$C$108,0),MATCH(K$8,'QoE PF Adj. P&L Aug-26'!$D$8:$AI$8,0))*1000 -> 7000 | L18: =+INDEX('QoE PF Adj. P&L Aug-26'!$D$11:$AI$108,MATCH($C18,'QoE PF Adj. P&L Aug-26'!$C$11:$C$108,0),MATCH(L$8,'QoE PF Adj. P&L Aug-26'!$D$8:$AI$8,0))*1000 -> 7700 | M18: =+INDEX('QoE PF Adj. P&L Aug-26'!$D$11:$AI$108,MATCH($C18,'QoE PF Adj. P&L Aug-26'!$C$11:$C$108,0),MATCH(M$8,'QoE PF Adj. P&L Aug-26'!$D$8:$AI$8,0))*1000 -> 7100 | N18: =+INDEX('QoE PF Adj. P&L Aug-26'!$D$11:$AI$108,MATCH($C18,'QoE PF Adj. P&L Aug-26'!$C$11:$C$108,0),MATCH(N$8,'QoE PF Adj. P&L Aug-26'!$D$8:$AI$8,0))*1000 -> 7000 | O18: =+INDEX('QoE PF Adj. P&L Aug-26'!$D$11:$AI$108,MATCH($C18,'QoE PF Adj. P&L Aug-26'!$C$11:$C$108,0),MATCH(O$8,'QoE PF Adj. P&L Aug-26'!$D$8:$AI$8,0))*1000 -> 7400 | P18: =+INDEX('QoE PF Adj. P&L Aug-26'!$D$11:$AI$108,MATCH($C18,'QoE PF Adj. P&L Aug-26'!$C$11:$C$108,0),MATCH(P$8,'QoE PF Adj. P&L Aug-26'!$D$8:$AI$8,0))*1000 -> 7400 | Q18: =+INDEX('QoE PF Adj. P&L Aug-26'!$D$11:$AI$108,MATCH($C18,'QoE PF Adj. P&L Aug-26'!$C$11:$C$108,0),MATCH(Q$8,'QoE PF Adj. P&L Aug-26'!$D$8:$AI$8,0))*1000 -> 7500 | ... AO18: =+INDEX('QoE PF Adj. P&L Aug-26'!$D$11:$AI$108,MATCH($C18,'QoE PF Adj. P&L Aug-26'!$C$11:$C$108,0),MATCH(AO$8,'QoE PF Adj. P&L Aug-26'!$D$8:$AI$8,0))*1000 -> 9300 | AP18: =+SUMIFS('Sep - Nov P&L'!I:I,'Sep - Nov P&L'!$D:$D,$C18) -> 0 | AQ18: =+SUMIFS('Sep - Nov P&L'!J:J,'Sep - Nov P&L'!$D:$D,$C18) -> 0 | AR18: =+SUMIFS('Sep - Nov P&L'!K:K,'Sep - Nov P&L'!$D:$D,$C18) -> 0 | AS18: =+AS126 -> 6391.6667 | AT18: =+AT126 -> 6414.0375 | AU18: =+AU126 -> 6436.4866 | AV18: =+AV126 -> 6459.0143 | AW18: =+AW126 -> 6481.6209 | AX18: =+AX126 -> 6504.3066 | AY18: =+AY126 -> 6527.0716 | AZ18: =+AZ126 -> 6549.9164 | ... BQ18: =+BQ126 -> 6950.7419
C19: Total Employee Salaries & Wages | D19: =+SUMIFS($J19:$BQ19,$J$7:$BQ$7,D$8) -> 4230500 | E19: =+SUMIFS($J19:$BQ19,$J$7:$BQ$7,E$8) -> 4495900 | F19: =+SUMIFS($J19:$BQ19,$J$7:$BQ$7,F$8) -> 4788310.3 | G19: =+SUMIFS($J19:$BQ19,$J$7:$BQ$7,G$8) -> 5520920.9 | H19: =+SUMIFS($J19:$BQ19,$J$7:$BQ$7,H$8) -> 6090671.7 | J19: =SUM(J15:J18) -> 351900 | K19: =SUM(K15:K18) -> 342000 | L19: =SUM(L15:L18) -> 354000 | M19: =SUM(M15:M18) -> 355300 | N19: =SUM(N15:N18) -> 355300 | O19: =SUM(O15:O18) -> 348400 | P19: =SUM(P15:P18) -> 355300 | Q19: =SUM(Q15:Q18) -> 357000 | ... BQ19: =SUM(BQ15:BQ18) -> 507684.16
C21: Employee Taxes & Benefits
C22: Payroll Taxes | D22: =+SUMIFS($J22:$BQ22,$J$7:$BQ$7,D$8) -> 266000 | E22: =+SUMIFS($J22:$BQ22,$J$7:$BQ$7,E$8) -> 279200 | F22: =+SUMIFS($J22:$BQ22,$J$7:$BQ$7,F$8) -> 304828.26 | G22: =+SUMIFS($J22:$BQ22,$J$7:$BQ$7,G$8) -> 351065.62 | H22: =+SUMIFS($J22:$BQ22,$J$7:$BQ$7,H$8) -> 387295.07 | J22: =+INDEX('QoE PF Adj. P&L Aug-26'!$D$11:$AI$108,MATCH($C22,'QoE PF Adj. P&L Aug-26'!$C$11:$C$108,0),MATCH(J$8,'QoE PF Adj. P&L Aug-26'!$D$8:$AI$8,0))*1000 -> 22600 | K22: =+INDEX('QoE PF Adj. P&L Aug-26'!$D$11:$AI$108,MATCH($C22,'QoE PF Adj. P&L Aug-26'!$C$11:$C$108,0),MATCH(K$8,'QoE PF Adj. P&L Aug-26'!$D$8:$AI$8,0))*1000 -> 22300 | L22: =+INDEX('QoE PF Adj. P&L Aug-26'!$D$11:$AI$108,MATCH($C22,'QoE PF Adj. P&L Aug-26'!$C$11:$C$108,0),MATCH(L$8,'QoE PF Adj. P&L Aug-26'!$D$8:$AI$8,0))*1000 -> 22000 | M22: =+INDEX('QoE PF Adj. P&L Aug-26'!$D$11:$AI$108,MATCH($C22,'QoE PF Adj. P&L Aug-26'!$C$11:$C$108,0),MATCH(M$8,'QoE PF Adj. P&L Aug-26'!$D$8:$AI$8,0))*1000 -> 22200 | N22: =+INDEX('QoE PF Adj. P&L Aug-26'!$D$11:$AI$108,MATCH($C22,'QoE PF Adj. P&L Aug-26'!$C$11:$C$108,0),MATCH(N$8,'QoE PF Adj. P&L Aug-26'!$D$8:$AI$8,0))*1000 -> 21300 | O22: =+INDEX('QoE PF Adj. P&L Aug-26'!$D$11:$AI$108,MATCH($C22,'QoE PF Adj. P&L Aug-26'!$C$11:$C$108,0),MATCH(O$8,'QoE PF Adj. P&L Aug-26'!$D$8:$AI$8,0))*1000 -> 22000 | P22: =+INDEX('QoE PF Adj. P&L Aug-26'!$D$11:$AI$108,MATCH($C22,'QoE PF Adj. P&L Aug-26'!$C$11:$C$108,0),MATCH(P$8,'QoE PF Adj. P&L Aug-26'!$D$8:$AI$8,0))*1000 -> 22500 | Q22: =+INDEX('QoE PF Adj. P&L Aug-26'!$D$11:$AI$108,MATCH($C22,'QoE PF Adj. P&L Aug-26'!$C$11:$C$108,0),MATCH(Q$8,'QoE PF Adj. P&L Aug-26'!$D$8:$AI$8,0))*1000 -> 21700 | ... AO22: =+INDEX('QoE PF Adj. P&L Aug-26'!$D$11:$AI$108,MATCH($C22,'QoE PF Adj. P&L Aug-26'!$C$11:$C$108,0),MATCH(AO$8,'QoE PF Adj. P&L Aug-26'!$D$8:$AI$8,0))*1000 -> 24600 | AP22: =+'Separate Line Item Builds'!AP62+SUMIFS('Sep - Nov P&L'!I:I,'Sep - Nov P&L'!$D:$D,$C22) -> 27311.904 | AQ22: =+'Separate Line Item Builds'!AQ62+SUMIFS('Sep - Nov P&L'!J:J,'Sep - Nov P&L'!$D:$D,$C22) -> 27642.963 | AR22: =+'Separate Line Item Builds'!AR62+SUMIFS('Sep - Nov P&L'!K:K,'Sep - Nov P&L'!$D:$D,$C22) -> 27290.378 | AS22: =+AS$19*AS130 -> 26183.013 | AT22: =+AT$19*AT130 -> 25987.951 | AU22: =+AU$19*AU130 -> 27048.957 | AV22: =+AV$19*AV130 -> 28758.386 | AW22: =+AW$19*AW130 -> 28948.034 | AX22: =+AX$19*AX130 -> 28981.384 | AY22: =+AY$19*AY130 -> 29518.461 | AZ22: =+AZ$19*AZ130 -> 29701.843 | ... BQ22: =+BQ$19*BQ130 -> 32282.741
C23: Employee Benefits | D23: =+SUMIFS($J23:$BQ23,$J$7:$BQ$7,D$8) -> 199300 | E23: =+SUMIFS($J23:$BQ23,$J$7:$BQ$7,E$8) -> 210500 | F23: =+SUMIFS($J23:$BQ23,$J$7:$BQ$7,F$8) -> 237778.87 | G23: =+SUMIFS($J23:$BQ23,$J$7:$BQ$7,G$8) -> 272626.67 | H23: =+SUMIFS($J23:$BQ23,$J$7:$BQ$7,H$8) -> 300761.34 | J23: =+INDEX('QoE PF Adj. P&L Aug-26'!$D$11:$AI$108,MATCH($C23,'QoE PF Adj. P&L Aug-26'!$C$11:$C$108,0),MATCH(J$8,'QoE PF Adj. P&L Aug-26'!$D$8:$AI$8,0))*1000 -> 16900 | K23: =+INDEX('QoE PF Adj. P&L Aug-26'!$D$11:$AI$108,MATCH($C23,'QoE PF Adj. P&L Aug-26'!$C$11:$C$108,0),MATCH(K$8,'QoE PF Adj. P&L Aug-26'!$D$8:$AI$8,0))*1000 -> 16600 | L23: =+INDEX('QoE PF Adj. P&L Aug-26'!$D$11:$AI$108,MATCH($C23,'QoE PF Adj. P&L Aug-26'!$C$11:$C$108,0),MATCH(L$8,'QoE PF Adj. P&L Aug-26'!$D$8:$AI$8,0))*1000 -> 16400 | M23: =+INDEX('QoE PF Adj. P&L Aug-26'!$D$11:$AI$108,MATCH($C23,'QoE PF Adj. P&L Aug-26'!$C$11:$C$108,0),MATCH(M$8,'QoE PF Adj. P&L Aug-26'!$D$8:$AI$8,0))*1000 -> 17100 | N23: =+INDEX('QoE PF Adj. P&L Aug-26'!$D$11:$AI$108,MATCH($C23,'QoE PF Adj. P&L Aug-26'!$C$11:$C$108,0),MATCH(N$8,'QoE PF Adj. P&L Aug-26'!$D$8:$AI$8,0))*1000 -> 16200 | O23: =+INDEX('QoE PF Adj. P&L Aug-26'!$D$11:$AI$108,MATCH($C23,'QoE PF Adj. P&L Aug-26'!$C$11:$C$108,0),MATCH(O$8,'QoE PF Adj. P&L Aug-26'!$D$8:$AI$8,0))*1000 -> 17000 | P23: =+INDEX('QoE PF Adj. P&L Aug-26'!$D$11:$AI$108,MATCH($C23,'QoE PF Adj. P&L Aug-26'!$C$11:$C$108,0),MATCH(P$8,'QoE PF Adj. P&L Aug-26'!$D$8:$AI$8,0))*1000 -> 16500 | Q23: =+INDEX('QoE PF Adj. P&L Aug-26'!$D$11:$AI$108,MATCH($C23,'QoE PF Adj. P&L Aug-26'!$C$11:$C$108,0),MATCH(Q$8,'QoE PF Adj. P&L Aug-26'!$D$8:$AI$8,0))*1000 -> 16700 | ... AO23: =+INDEX('QoE PF Adj. P&L Aug-26'!$D$11:$AI$108,MATCH($C23,'QoE PF Adj. P&L Aug-26'!$C$11:$C$108,0),MATCH(AO$8,'QoE PF Adj. P&L Aug-26'!$D$8:$AI$8,0))*1000 -> 18800 | AP23: =+SUMIFS('Sep - Nov P&L'!I:I,'Sep - Nov P&L'!$D:$D,$C23) -> 23121.22 | AQ23: =+SUMIFS('Sep - Nov P&L'!J:J,'Sep - Nov P&L'!$D:$D,$C23) -> 23283.72 | AR23: =+SUMIFS('Sep - Nov P&L'!K:K,'Sep - Nov P&L'!$D:$D,$C23) -> 23241.01 | AS23: =+AS$19*AS131 -> 20332.916 | AT23: =+AT$19*AT131 -> 20181.436 | AU23: =+AU$19*AU131 -> 21005.381 | AV23: =+AV$19*AV131 -> 22332.87 | AW23: =+AW$19*AW131 -> 22480.145 | AX23: =+AX$19*AX131 -> 22506.044 | AY23: =+AY$19*AY131 -> 22923.121 | AZ23: =+AZ$19*AZ131 -> 23065.529 | ... BQ23: =+BQ$19*BQ131 -> 25069.775
C24: Pension Plans | D24: =+SUMIFS($J24:$BQ24,$J$7:$BQ$7,D$8) -> 33600 | E24: =+SUMIFS($J24:$BQ24,$J$7:$BQ$7,E$8) -> 34800 | F24: =+SUMIFS($J24:$BQ24,$J$7:$BQ$7,F$8) -> 26891.197 | G24: =+SUMIFS($J24:$BQ24,$J$7:$BQ$7,G$8) -> 32061.512 | H24: =+SUMIFS($J24:$BQ24,$J$7:$BQ$7,H$8) -> 35370.212 | J24: =+INDEX('QoE PF Adj. P&L Aug-26'!$D$11:$AI$108,MATCH($C24,'QoE PF Adj. P&L Aug-26'!$C$11:$C$108,0),MATCH(J$8,'QoE PF Adj. P&L Aug-26'!$D$8:$AI$8,0))*1000 -> 2800 | K24: =+INDEX('QoE PF Adj. P&L Aug-26'!$D$11:$AI$108,MATCH($C24,'QoE PF Adj. P&L Aug-26'!$C$11:$C$108,0),MATCH(K$8,'QoE PF Adj. P&L Aug-26'!$D$8:$AI$8,0))*1000 -> 2800 | L24: =+INDEX('QoE PF Adj. P&L Aug-26'!$D$11:$AI$108,MATCH($C24,'QoE PF Adj. P&L Aug-26'!$C$11:$C$108,0),MATCH(L$8,'QoE PF Adj. P&L Aug-26'!$D$8:$AI$8,0))*1000 -> 2800 | M24: =+INDEX('QoE PF Adj. P&L Aug-26'!$D$11:$AI$108,MATCH($C24,'QoE PF Adj. P&L Aug-26'!$C$11:$C$108,0),MATCH(M$8,'QoE PF Adj. P&L Aug-26'!$D$8:$AI$8,0))*1000 -> 2900 | N24: =+INDEX('QoE PF Adj. P&L Aug-26'!$D$11:$AI$108,MATCH($C24,'QoE PF Adj. P&L Aug-26'!$C$11:$C$108,0),MATCH(N$8,'QoE PF Adj. P&L Aug-26'!$D$8:$AI$8,0))*1000 -> 2700 | O24: =+INDEX('QoE PF Adj. P&L Aug-26'!$D$11:$AI$108,MATCH($C24,'QoE PF Adj. P&L Aug-26'!$C$11:$C$108,0),MATCH(O$8,'QoE PF Adj. P&L Aug-26'!$D$8:$AI$8,0))*1000 -> 2800 | P24: =+INDEX('QoE PF Adj. P&L Aug-26'!$D$11:$AI$108,MATCH($C24,'QoE PF Adj. P&L Aug-26'!$C$11:$C$108,0),MATCH(P$8,'QoE PF Adj. P&L Aug-26'!$D$8:$AI$8,0))*1000 -> 2800 | Q24: =+INDEX('QoE PF Adj. P&L Aug-26'!$D$11:$AI$108,MATCH($C24,'QoE PF Adj. P&L Aug-26'!$C$11:$C$108,0),MATCH(Q$8,'QoE PF Adj. P&L Aug-26'!$D$8:$AI$8,0))*1000 -> 2800 | ... AO24: =+INDEX('QoE PF Adj. P&L Aug-26'!$D$11:$AI$108,MATCH($C24,'QoE PF Adj. P&L Aug-26'!$C$11:$C$108,0),MATCH(AO$8,'QoE PF Adj. P&L Aug-26'!$D$8:$AI$8,0))*1000 -> 3100 | AP24: =+SUMIFS('Sep - Nov P&L'!I:I,'Sep - Nov P&L'!$D:$D,$C24) -> 0 | AQ24: =+SUMIFS('Sep - Nov P&L'!J:J,'Sep - Nov P&L'!$D:$D,$C24) -> 0 | AR24: =+SUMIFS('Sep - Nov P&L'!K:K,'Sep - Nov P&L'!$D:$D,$C24) -> 0 | AS24: =+AS$19*AS132 -> 2391.1968 | AT24: =+AT$19*AT132 -> 2373.3825 | AU24: =+AU$19*AU132 -> 2470.2802 | AV24: =+AV$19*AV132 -> 2626.396 | AW24: =+AW$19*AW132 -> 2643.7158 | AX24: =+AX$19*AX132 -> 2646.7616 | AY24: =+AY$19*AY132 -> 2695.8108 | AZ24: =+AZ$19*AZ132 -> 2712.5583 | ... BQ24: =+BQ$19*BQ132 -> 2948.2621
C25: Other Personnel Expenses | D25: =+SUMIFS($J25:$BQ25,$J$7:$BQ$7,D$8) -> 9800 | E25: =+SUMIFS($J25:$BQ25,$J$7:$BQ$7,E$8) -> 10700 | F25: =+SUMIFS($J25:$BQ25,$J$7:$BQ$7,F$8) -> 7904.4149 | G25: =+SUMIFS($J25:$BQ25,$J$7:$BQ$7,G$8) -> 9444.8966 | H25: =+SUMIFS($J25:$BQ25,$J$7:$BQ$7,H$8) -> 10419.596 | J25: =+INDEX('QoE PF Adj. P&L Aug-26'!$D$11:$AI$108,MATCH($C25,'QoE PF Adj. P&L Aug-26'!$C$11:$C$108,0),MATCH(J$8,'QoE PF Adj. P&L Aug-26'!$D$8:$AI$8,0))*1000 -> 900 | K25: =+INDEX('QoE PF Adj. P&L Aug-26'!$D$11:$AI$108,MATCH($C25,'QoE PF Adj. P&L Aug-26'!$C$11:$C$108,0),MATCH(K$8,'QoE PF Adj. P&L Aug-26'!$D$8:$AI$8,0))*1000 -> 800 | L25: =+INDEX('QoE PF Adj. P&L Aug-26'!$D$11:$AI$108,MATCH($C25,'QoE PF Adj. P&L Aug-26'!$C$11:$C$108,0),MATCH(L$8,'QoE PF Adj. P&L Aug-26'!$D$8:$AI$8,0))*1000 -> 800 | M25: =+INDEX('QoE PF Adj. P&L Aug-26'!$D$11:$AI$108,MATCH($C25,'QoE PF Adj. P&L Aug-26'!$C$11:$C$108,0),MATCH(M$8,'QoE PF Adj. P&L Aug-26'!$D$8:$AI$8,0))*1000 -> 900 | N25: =+INDEX('QoE PF Adj. P&L Aug-26'!$D$11:$AI$108,MATCH($C25,'QoE PF Adj. P&L Aug-26'!$C$11:$C$108,0),MATCH(N$8,'QoE PF Adj. P&L Aug-26'!$D$8:$AI$8,0))*1000 -> 800 | O25: =+INDEX('QoE PF Adj. P&L Aug-26'!$D$11:$AI$108,MATCH($C25,'QoE PF Adj. P&L Aug-26'!$C$11:$C$108,0),MATCH(O$8,'QoE PF Adj. P&L Aug-26'!$D$8:$AI$8,0))*1000 -> 800 | P25: =+INDEX('QoE PF Adj. P&L Aug-26'!$D$11:$AI$108,MATCH($C25,'QoE PF Adj. P&L Aug-26'!$C$11:$C$108,0),MATCH(P$8,'QoE PF Adj. P&L Aug-26'!$D$8:$AI$8,0))*1000 -> 800 | Q25: =+INDEX('QoE PF Adj. P&L Aug-26'!$D$11:$AI$108,MATCH($C25,'QoE PF Adj. P&L Aug-26'!$C$11:$C$108,0),MATCH(Q$8,'QoE PF Adj. P&L Aug-26'!$D$8:$AI$8,0))*1000 -> 800 | ... AO25: =+INDEX('QoE PF Adj. P&L Aug-26'!$D$11:$AI$108,MATCH($C25,'QoE PF Adj. P&L Aug-26'!$C$11:$C$108,0),MATCH(AO$8,'QoE PF Adj. P&L Aug-26'!$D$8:$AI$8,0))*1000 -> 900 | AP25: =+SUMIFS('Sep - Nov P&L'!I:I,'Sep - Nov P&L'!$D:$D,$C25) -> 0 | AQ25: =+SUMIFS('Sep - Nov P&L'!J:J,'Sep - Nov P&L'!$D:$D,$C25) -> 0 | AR25: =+SUMIFS('Sep - Nov P&L'!K:K,'Sep - Nov P&L'!$D:$D,$C25) -> 0 | AS25: =+AS$19*AS133 -> 704.4149 | AT25: =+AT$19*AT133 -> 699.16703 | AU25: =+AU$19*AU133 -> 727.71182 | AV25: =+AV$19*AV133 -> 773.70146 | AW25: =+AW$19*AW133 -> 778.80364 | AX25: =+AX$19*AX133 -> 779.7009 | AY25: =+AY$19*AY133 -> 794.15014 | AZ25: =+AZ$19*AZ133 -> 799.08375 | ... BQ25: =+BQ$19*BQ133 -> 868.51895
C26: Payroll Processing Fee | D26: =+SUMIFS($J26:$BQ26,$J$7:$BQ$7,D$8) -> 13300 | E26: =+SUMIFS($J26:$BQ26,$J$7:$BQ$7,E$8) -> 14100 | F26: =+SUMIFS($J26:$BQ26,$J$7:$BQ$7,F$8) -> 15501.161 | G26: =+SUMIFS($J26:$BQ26,$J$7:$BQ$7,G$8) -> 17799.087 | H26: =+SUMIFS($J26:$BQ26,$J$7:$BQ$7,H$8) -> 19635.926 | J26: =+INDEX('QoE PF Adj. P&L Aug-26'!$D$11:$AI$108,MATCH($C26,'QoE PF Adj. P&L Aug-26'!$C$11:$C$108,0),MATCH(J$8,'QoE PF Adj. P&L Aug-26'!$D$8:$AI$8,0))*1000 -> 1100 | K26: =+INDEX('QoE PF Adj. P&L Aug-26'!$D$11:$AI$108,MATCH($C26,'QoE PF Adj. P&L Aug-26'!$C$11:$C$108,0),MATCH(K$8,'QoE PF Adj. P&L Aug-26'!$D$8:$AI$8,0))*1000 -> 1100 | L26: =+INDEX('QoE PF Adj. P&L Aug-26'!$D$11:$AI$108,MATCH($C26,'QoE PF Adj. P&L Aug-26'!$C$11:$C$108,0),MATCH(L$8,'QoE PF Adj. P&L Aug-26'!$D$8:$AI$8,0))*1000 -> 1100 | M26: =+INDEX('QoE PF Adj. P&L Aug-26'!$D$11:$AI$108,MATCH($C26,'QoE PF Adj. P&L Aug-26'!$C$11:$C$108,0),MATCH(M$8,'QoE PF Adj. P&L Aug-26'!$D$8:$AI$8,0))*1000 -> 1200 | N26: =+INDEX('QoE PF Adj. P&L Aug-26'!$D$11:$AI$108,MATCH($C26,'QoE PF Adj. P&L Aug-26'!$C$11:$C$108,0),MATCH(N$8,'QoE PF Adj. P&L Aug-26'!$D$8:$AI$8,0))*1000 -> 1100 | O26: =+INDEX('QoE PF Adj. P&L Aug-26'!$D$11:$AI$108,MATCH($C26,'QoE PF Adj. P&L Aug-26'!$C$11:$C$108,0),MATCH(O$8,'QoE PF Adj. P&L Aug-26'!$D$8:$AI$8,0))*1000 -> 1100 | P26: =+INDEX('QoE PF Adj. P&L Aug-26'!$D$11:$AI$108,MATCH($C26,'QoE PF Adj. P&L Aug-26'!$C$11:$C$108,0),MATCH(P$8,'QoE PF Adj. P&L Aug-26'!$D$8:$AI$8,0))*1000 -> 1100 | Q26: =+INDEX('QoE PF Adj. P&L Aug-26'!$D$11:$AI$108,MATCH($C26,'QoE PF Adj. P&L Aug-26'!$C$11:$C$108,0),MATCH(Q$8,'QoE PF Adj. P&L Aug-26'!$D$8:$AI$8,0))*1000 -> 1100 | ... AO26: =+INDEX('QoE PF Adj. P&L Aug-26'!$D$11:$AI$108,MATCH($C26,'QoE PF Adj. P&L Aug-26'!$C$11:$C$108,0),MATCH(AO$8,'QoE PF Adj. P&L Aug-26'!$D$8:$AI$8,0))*1000 -> 1200 | AP26: =+'Separate Line Item Builds'!AP63+SUMIFS('Sep - Nov P&L'!I:I,'Sep - Nov P&L'!$D:$D,$C26) -> 1486.7349 | AQ26: =+'Separate Line Item Builds'!AQ63+SUMIFS('Sep - Nov P&L'!J:J,'Sep - Nov P&L'!$D:$D,$C26) -> 1499.7325 | AR26: =+'Separate Line Item Builds'!AR63+SUMIFS('Sep - Nov P&L'!K:K,'Sep - Nov P&L'!$D:$D,$C26) -> 1487.2101 | AS26: =+SUM(AS$19,AS$22:AS$25)*AS134 -> 1327.4832 | AT26: =+SUM(AT$19,AT$22:AT$25)*AT134 -> 1317.5935 | AU26: =+SUM(AU$19,AU$22:AU$25)*AU134 -> 1371.3867 | AV26: =+SUM(AV$19,AV$22:AV$25)*AV134 -> 1458.0551 | AW26: =+SUM(AW$19,AW$22:AW$25)*AW134 -> 1467.6702 | AX26: =+SUM(AX$19,AX$22:AX$25)*AX134 -> 1469.3611 | AY26: =+SUM(AY$19,AY$22:AY$25)*AY134 -> 1496.591 | AZ26: =+SUM(AZ$19,AZ$22:AZ$25)*AZ134 -> 1505.8885 | ... BQ26: =+SUM(BQ$19,BQ$22:BQ$25)*BQ134 -> 1636.7404
C27: Total Employee Taxes & Benefits | D27: =+SUMIFS($J27:$BQ27,$J$7:$BQ$7,D$8) -> 522000 | E27: =+SUMIFS($J27:$BQ27,$J$7:$BQ$7,E$8) -> 549300 | F27: =+SUMIFS($J27:$BQ27,$J$7:$BQ$7,F$8) -> 592903.9 | G27: =+SUMIFS($J27:$BQ27,$J$7:$BQ$7,G$8) -> 682997.79 | H27: =+SUMIFS($J27:$BQ27,$J$7:$BQ$7,H$8) -> 753482.15 | J27: =SUM(J22:J26) -> 44300 | K27: =SUM(K22:K26) -> 43600 | L27: =SUM(L22:L26) -> 43100 | M27: =SUM(M22:M26) -> 44300 | N27: =SUM(N22:N26) -> 42100 | O27: =SUM(O22:O26) -> 43700 | P27: =SUM(P22:P26) -> 43700 | Q27: =SUM(Q22:Q26) -> 43100 | ... BQ27: =SUM(BQ22:BQ26) -> 62806.037
C29: Occupancy Costs
C30: Facility Rent | D30: =+SUMIFS($J30:$BQ30,$J$7:$BQ$7,D$8) -> 465000 | E30: =+SUMIFS($J30:$BQ30,$J$7:$BQ$7,E$8) -> 507800 | F30: =+SUMIFS($J30:$BQ30,$J$7:$BQ$7,F$8) -> 530311.8 | G30: =+SUMIFS($J30:$BQ30,$J$7:$BQ$7,G$8) -> 543295.01 | H30: =+SUMIFS($J30:$BQ30,$J$7:$BQ$7,H$8) -> 566557.82 | J30: =+INDEX('QoE PF Adj. P&L Aug-26'!$D$11:$AI$108,MATCH($C30,'QoE PF Adj. P&L Aug-26'!$C$11:$C$108,0),MATCH(J$8,'QoE PF Adj. P&L Aug-26'!$D$8:$AI$8,0))*1000 -> 38000 | K30: =+INDEX('QoE PF Adj. P&L Aug-26'!$D$11:$AI$108,MATCH($C30,'QoE PF Adj. P&L Aug-26'!$C$11:$C$108,0),MATCH(K$8,'QoE PF Adj. P&L Aug-26'!$D$8:$AI$8,0))*1000 -> 36300 | L30: =+INDEX('QoE PF Adj. P&L Aug-26'!$D$11:$AI$108,MATCH($C30,'QoE PF Adj. P&L Aug-26'!$C$11:$C$108,0),MATCH(L$8,'QoE PF Adj. P&L Aug-26'!$D$8:$AI$8,0))*1000 -> 39700 | M30: =+INDEX('QoE PF Adj. P&L Aug-26'!$D$11:$AI$108,MATCH($C30,'QoE PF Adj. P&L Aug-26'!$C$11:$C$108,0),MATCH(M$8,'QoE PF Adj. P&L Aug-26'!$D$8:$AI$8,0))*1000 -> 38800 | N30: =+INDEX('QoE PF Adj. P&L Aug-26'!$D$11:$AI$108,MATCH($C30,'QoE PF Adj. P&L Aug-26'!$C$11:$C$108,0),MATCH(N$8,'QoE PF Adj. P&L Aug-26'!$D$8:$AI$8,0))*1000 -> 40400 | O30: =+INDEX('QoE PF Adj. P&L Aug-26'!$D$11:$AI$108,MATCH($C30,'QoE PF Adj. P&L Aug-26'!$C$11:$C$108,0),MATCH(O$8,'QoE PF Adj. P&L Aug-26'!$D$8:$AI$8,0))*1000 -> 39000 | P30: =+INDEX('QoE PF Adj. P&L Aug-26'!$D$11:$AI$108,MATCH($C30,'QoE PF Adj. P&L Aug-26'!$C$11:$C$108,0),MATCH(P$8,'QoE PF Adj. P&L Aug-26'!$D$8:$AI$8,0))*1000 -> 38500 | Q30: =+INDEX('QoE PF Adj. P&L Aug-26'!$D$11:$AI$108,MATCH($C30,'QoE PF Adj. P&L Aug-26'!$C$11:$C$108,0),MATCH(Q$8,'QoE PF Adj. P&L Aug-26'!$D$8:$AI$8,0))*1000 -> 37700 | ... AO30: =+INDEX('QoE PF Adj. P&L Aug-26'!$D$11:$AI$108,MATCH($C30,'QoE PF Adj. P&L Aug-26'!$C$11:$C$108,0),MATCH(AO$8,'QoE PF Adj. P&L Aug-26'!$D$8:$AI$8,0))*1000 -> 42300 | AP30: =+SUMIFS('Sep - Nov P&L'!I:I,'Sep - Nov P&L'!$D:$D,$C30) -> 43353.99 | AQ30: =+SUMIFS('Sep - Nov P&L'!J:J,'Sep - Nov P&L'!$D:$D,$C30) -> 43742.9 | AR30: =+SUMIFS('Sep - Nov P&L'!K:K,'Sep - Nov P&L'!$D:$D,$C30) -> 45360.16 | AS30: =+AS138 -> 44254.754 | AT30: =+AT138 -> 44409.646 | AU30: =+AU138 -> 44565.08 | AV30: =+AV138 -> 44721.057 | AW30: =+AW138 -> 44877.581 | AX30: =+AX138 -> 45034.653 | AY30: =+AY138 -> 45192.274 | AZ30: =+AZ138 -> 45350.447 | ... BQ30: =+BQ138 -> 48125.691
C31: Utilities | D31: =+SUMIFS($J31:$BQ31,$J$7:$BQ$7,D$8) -> 77600 | E31: =+SUMIFS($J31:$BQ31,$J$7:$BQ$7,E$8) -> 81200 | F31: =+SUMIFS($J31:$BQ31,$J$7:$BQ$7,F$8) -> 87475.867 | G31: =+SUMIFS($J31:$BQ31,$J$7:$BQ$7,G$8) -> 88934.867 | H31: =+SUMIFS($J31:$BQ31,$J$7:$BQ$7,H$8) -> 92742.881 | J31: =+INDEX('QoE PF Adj. P&L Aug-26'!$D$11:$AI$108,MATCH($C31,'QoE PF Adj. P&L Aug-26'!$C$11:$C$108,0),MATCH(J$8,'QoE PF Adj. P&L Aug-26'!$D$8:$AI$8,0))*1000 -> 6300 | K31: =+INDEX('QoE PF Adj. P&L Aug-26'!$D$11:$AI$108,MATCH($C31,'QoE PF Adj. P&L Aug-26'!$C$11:$C$108,0),MATCH(K$8,'QoE PF Adj. P&L Aug-26'!$D$8:$AI$8,0))*1000 -> 6100 | L31: =+INDEX('QoE PF Adj. P&L Aug-26'!$D$11:$AI$108,MATCH($C31,'QoE PF Adj. P&L Aug-26'!$C$11:$C$108,0),MATCH(L$8,'QoE PF Adj. P&L Aug-26'!$D$8:$AI$8,0))*1000 -> 6600 | M31: =+INDEX('QoE PF Adj. P&L Aug-26'!$D$11:$AI$108,MATCH($C31,'QoE PF Adj. P&L Aug-26'!$C$11:$C$108,0),MATCH(M$8,'QoE PF Adj. P&L Aug-26'!$D$8:$AI$8,0))*1000 -> 6400 | N31: =+INDEX('QoE PF Adj. P&L Aug-26'!$D$11:$AI$108,MATCH($C31,'QoE PF Adj. P&L Aug-26'!$C$11:$C$108,0),MATCH(N$8,'QoE PF Adj. P&L Aug-26'!$D$8:$AI$8,0))*1000 -> 6400 | O31: =+INDEX('QoE PF Adj. P&L Aug-26'!$D$11:$AI$108,MATCH($C31,'QoE PF Adj. P&L Aug-26'!$C$11:$C$108,0),MATCH(O$8,'QoE PF Adj. P&L Aug-26'!$D$8:$AI$8,0))*1000 -> 6600 | P31: =+INDEX('QoE PF Adj. P&L Aug-26'!$D$11:$AI$108,MATCH($C31,'QoE PF Adj. P&L Aug-26'!$C$11:$C$108,0),MATCH(P$8,'QoE PF Adj. P&L Aug-26'!$D$8:$AI$8,0))*1000 -> 6200 | Q31: =+INDEX('QoE PF Adj. P&L Aug-26'!$D$11:$AI$108,MATCH($C31,'QoE PF Adj. P&L Aug-26'!$C$11:$C$108,0),MATCH(Q$8,'QoE PF Adj. P&L Aug-26'!$D$8:$AI$8,0))*1000 -> 6800 | ... AO31: =+INDEX('QoE PF Adj. P&L Aug-26'!$D$11:$AI$108,MATCH($C31,'QoE PF Adj. P&L Aug-26'!$C$11:$C$108,0),MATCH(AO$8,'QoE PF Adj. P&L Aug-26'!$D$8:$AI$8,0))*1000 -> 7300 | AP31: =+SUMIFS('Sep - Nov P&L'!I:I,'Sep - Nov P&L'!$D:$D,$C31) -> 7569.46 | AQ31: =+SUMIFS('Sep - Nov P&L'!J:J,'Sep - Nov P&L'!$D:$D,$C31) -> 7723.55 | AR31: =+SUMIFS('Sep - Nov P&L'!K:K,'Sep - Nov P&L'!$D:$D,$C31) -> 7138.56 | AS31: =+AS139 -> 7244.2975 | AT31: =+AT139 -> 7269.6525 | AU31: =+AU139 -> 7295.0963 | AV31: =+AV139 -> 7320.6292 | AW31: =+AW139 -> 7346.2514 | AX31: =+AX139 -> 7371.9632 | AY31: =+AY139 -> 7397.7651 | AZ31: =+AZ139 -> 7423.6573 | ... BQ31: =+BQ139 -> 7877.9518
C32: Janitorial | D32: =+SUMIFS($J32:$BQ32,$J$7:$BQ$7,D$8) -> 38600 | E32: =+SUMIFS($J32:$BQ32,$J$7:$BQ$7,E$8) -> 41200 | F32: =+SUMIFS($J32:$BQ32,$J$7:$BQ$7,F$8) -> 32141.667 | G32: =+SUMIFS($J32:$BQ32,$J$7:$BQ$7,G$8) -> 33658.165 | H32: =+SUMIFS($J32:$BQ32,$J$7:$BQ$7,H$8) -> 35099.341 | J32: =+INDEX('QoE PF Adj. P&L Aug-26'!$D$11:$AI$108,MATCH($C32,'QoE PF Adj. P&L Aug-26'!$C$11:$C$108,0),MATCH(J$8,'QoE PF Adj. P&L Aug-26'!$D$8:$AI$8,0))*1000 -> 3200 | K32: =+INDEX('QoE PF Adj. P&L Aug-26'!$D$11:$AI$108,MATCH($C32,'QoE PF Adj. P&L Aug-26'!$C$11:$C$108,0),MATCH(K$8,'QoE PF Adj. P&L Aug-26'!$D$8:$AI$8,0))*1000 -> 3000 | L32: =+INDEX('QoE PF Adj. P&L Aug-26'!$D$11:$AI$108,MATCH($C32,'QoE PF Adj. P&L Aug-26'!$C$11:$C$108,0),MATCH(L$8,'QoE PF Adj. P&L Aug-26'!$D$8:$AI$8,0))*1000 -> 3000 | M32: =+INDEX('QoE PF Adj. P&L Aug-26'!$D$11:$AI$108,MATCH($C32,'QoE PF Adj. P&L Aug-26'!$C$11:$C$108,0),MATCH(M$8,'QoE PF Adj. P&L Aug-26'!$D$8:$AI$8,0))*1000 -> 3100 | N32: =+INDEX('QoE PF Adj. P&L Aug-26'!$D$11:$AI$108,MATCH($C32,'QoE PF Adj. P&L Aug-26'!$C$11:$C$108,0),MATCH(N$8,'QoE PF Adj. P&L Aug-26'!$D$8:$AI$8,0))*1000 -> 3300 | O32: =+INDEX('QoE PF Adj. P&L Aug-26'!$D$11:$AI$108,MATCH($C32,'QoE PF Adj. P&L Aug-26'!$C$11:$C$108,0),MATCH(O$8,'QoE PF Adj. P&L Aug-26'!$D$8:$AI$8,0))*1000 -> 3200 | P32: =+INDEX('QoE PF Adj. P&L Aug-26'!$D$11:$AI$108,MATCH($C32,'QoE PF Adj. P&L Aug-26'!$C$11:$C$108,0),MATCH(P$8,'QoE PF Adj. P&L Aug-26'!$D$8:$AI$8,0))*1000 -> 3400 | Q32: =+INDEX('QoE PF Adj. P&L Aug-26'!$D$11:$AI$108,MATCH($C32,'QoE PF Adj. P&L Aug-26'!$C$11:$C$108,0),MATCH(Q$8,'QoE PF Adj. P&L Aug-26'!$D$8:$AI$8,0))*1000 -> 3000 | ... AO32: =+INDEX('QoE PF Adj. P&L Aug-26'!$D$11:$AI$108,MATCH($C32,'QoE PF Adj. P&L Aug-26'!$C$11:$C$108,0),MATCH(AO$8,'QoE PF Adj. P&L Aug-26'!$D$8:$AI$8,0))*1000 -> 3700 | AP32: =+SUMIFS('Sep - Nov P&L'!I:I,'Sep - Nov P&L'!$D:$D,$C32) -> 0 | AQ32: =+SUMIFS('Sep - Nov P&L'!J:J,'Sep - Nov P&L'!$D:$D,$C32) -> 0 | AR32: =+SUMIFS('Sep - Nov P&L'!K:K,'Sep - Nov P&L'!$D:$D,$C32) -> 0 | AS32: =+AS140 -> 2741.6667 | AT32: =+AT140 -> 2751.2625 | AU32: =+AU140 -> 2760.8919 | AV32: =+AV140 -> 2770.555 | AW32: =+AW140 -> 2780.252 | AX32: =+AX140 -> 2789.9829 | AY32: =+AY140 -> 2799.7478 | AZ32: =+AZ140 -> 2809.5469 | ... BQ32: =+BQ140 -> 2981.4786
C33: Security | D33: =+SUMIFS($J33:$BQ33,$J$7:$BQ$7,D$8) -> 12900 | E33: =+SUMIFS($J33:$BQ33,$J$7:$BQ$7,E$8) -> 14100 | F33: =+SUMIFS($J33:$BQ33,$J$7:$BQ$7,F$8) -> 10725 | G33: =+SUMIFS($J33:$BQ33,$J$7:$BQ$7,G$8) -> 11355.794 | H33: =+SUMIFS($J33:$BQ33,$J$7:$BQ$7,H$8) -> 11842.027 | J33: =+INDEX('QoE PF Adj. P&L Aug-26'!$D$11:$AI$108,MATCH($C33,'QoE PF Adj. P&L Aug-26'!$C$11:$C$108,0),MATCH(J$8,'QoE PF Adj. P&L Aug-26'!$D$8:$AI$8,0))*1000 -> 1000 | K33: =+INDEX('QoE PF Adj. P&L Aug-26'!$D$11:$AI$108,MATCH($C33,'QoE PF Adj. P&L Aug-26'!$C$11:$C$108,0),MATCH(K$8,'QoE PF Adj. P&L Aug-26'!$D$8:$AI$8,0))*1000 -> 1100 | L33: =+INDEX('QoE PF Adj. P&L Aug-26'!$D$11:$AI$108,MATCH($C33,'QoE PF Adj. P&L Aug-26'!$C$11:$C$108,0),MATCH(L$8,'QoE PF Adj. P&L Aug-26'!$D$8:$AI$8,0))*1000 -> 1000 | M33: =+INDEX('QoE PF Adj. P&L Aug-26'!$D$11:$AI$108,MATCH($C33,'QoE PF Adj. P&L Aug-26'!$C$11:$C$108,0),MATCH(M$8,'QoE PF Adj. P&L Aug-26'!$D$8:$AI$8,0))*1000 -> 1000 | N33: =+INDEX('QoE PF Adj. P&L Aug-26'!$D$11:$AI$108,MATCH($C33,'QoE PF Adj. P&L Aug-26'!$C$11:$C$108,0),MATCH(N$8,'QoE PF Adj. P&L Aug-26'!$D$8:$AI$8,0))*1000 -> 1100 | O33: =+INDEX('QoE PF Adj. P&L Aug-26'!$D$11:$AI$108,MATCH($C33,'QoE PF Adj. P&L Aug-26'!$C$11:$C$108,0),MATCH(O$8,'QoE PF Adj. P&L Aug-26'!$D$8:$AI$8,0))*1000 -> 1100 | P33: =+INDEX('QoE PF Adj. P&L Aug-26'!$D$11:$AI$108,MATCH($C33,'QoE PF Adj. P&L Aug-26'!$C$11:$C$108,0),MATCH(P$8,'QoE PF Adj. P&L Aug-26'!$D$8:$AI$8,0))*1000 -> 1100 | Q33: =+INDEX('QoE PF Adj. P&L Aug-26'!$D$11:$AI$108,MATCH($C33,'QoE PF Adj. P&L Aug-26'!$C$11:$C$108,0),MATCH(Q$8,'QoE PF Adj. P&L Aug-26'!$D$8:$AI$8,0))*1000 -> 1000 | ... AO33: =+INDEX('QoE PF Adj. P&L Aug-26'!$D$11:$AI$108,MATCH($C33,'QoE PF Adj. P&L Aug-26'!$C$11:$C$108,0),MATCH(AO$8,'QoE PF Adj. P&L Aug-26'!$D$8:$AI$8,0))*1000 -> 1300 | AP33: =+SUMIFS('Sep - Nov P&L'!I:I,'Sep - Nov P&L'!$D:$D,$C33) -> 0 | AQ33: =+SUMIFS('Sep - Nov P&L'!J:J,'Sep - Nov P&L'!$D:$D,$C33) -> 0 | AR33: =+SUMIFS('Sep - Nov P&L'!K:K,'Sep - Nov P&L'!$D:$D,$C33) -> 0 | AS33: =+AS141 -> 925 | AT33: =+AT141 -> 928.2375 | AU33: =+AU141 -> 931.48633 | AV33: =+AV141 -> 934.74653 | AW33: =+AW141 -> 938.01815 | AX33: =+AX141 -> 941.30121 | AY33: =+AY141 -> 944.59576 | AZ33: =+AZ141 -> 947.90185 | ... BQ33: =+BQ141 -> 1005.9092
C34: Other Facility Expenses | D34: =+SUMIFS($J34:$BQ34,$J$7:$BQ$7,D$8) -> 26200 | E34: =+SUMIFS($J34:$BQ34,$J$7:$BQ$7,E$8) -> 27500 | F34: =+SUMIFS($J34:$BQ34,$J$7:$BQ$7,F$8) -> 29028.139 | G34: =+SUMIFS($J34:$BQ34,$J$7:$BQ$7,G$8) -> 29679.125 | H34: =+SUMIFS($J34:$BQ34,$J$7:$BQ$7,H$8) -> 30949.926 | J34: =+INDEX('QoE PF Adj. P&L Aug-26'!$D$11:$AI$108,MATCH($C34,'QoE PF Adj. P&L Aug-26'!$C$11:$C$108,0),MATCH(J$8,'QoE PF Adj. P&L Aug-26'!$D$8:$AI$8,0))*1000 -> 2000 | K34: =+INDEX('QoE PF Adj. P&L Aug-26'!$D$11:$AI$108,MATCH($C34,'QoE PF Adj. P&L Aug-26'!$C$11:$C$108,0),MATCH(K$8,'QoE PF Adj. P&L Aug-26'!$D$8:$AI$8,0))*1000 -> 2000 | L34: =+INDEX('QoE PF Adj. P&L Aug-26'!$D$11:$AI$108,MATCH($C34,'QoE PF Adj. P&L Aug-26'!$C$11:$C$108,0),MATCH(L$8,'QoE PF Adj. P&L Aug-26'!$D$8:$AI$8,0))*1000 -> 2200 | M34: =+INDEX('QoE PF Adj. P&L Aug-26'!$D$11:$AI$108,MATCH($C34,'QoE PF Adj. P&L Aug-26'!$C$11:$C$108,0),MATCH(M$8,'QoE PF Adj. P&L Aug-26'!$D$8:$AI$8,0))*1000 -> 2200 | N34: =+INDEX('QoE PF Adj. P&L Aug-26'!$D$11:$AI$108,MATCH($C34,'QoE PF Adj. P&L Aug-26'!$C$11:$C$108,0),MATCH(N$8,'QoE PF Adj. P&L Aug-26'!$D$8:$AI$8,0))*1000 -> 2200 | O34: =+INDEX('QoE PF Adj. P&L Aug-26'!$D$11:$AI$108,MATCH($C34,'QoE PF Adj. P&L Aug-26'!$C$11:$C$108,0),MATCH(O$8,'QoE PF Adj. P&L Aug-26'!$D$8:$AI$8,0))*1000 -> 2100 | P34: =+INDEX('QoE PF Adj. P&L Aug-26'!$D$11:$AI$108,MATCH($C34,'QoE PF Adj. P&L Aug-26'!$C$11:$C$108,0),MATCH(P$8,'QoE PF Adj. P&L Aug-26'!$D$8:$AI$8,0))*1000 -> 2200 | Q34: =+INDEX('QoE PF Adj. P&L Aug-26'!$D$11:$AI$108,MATCH($C34,'QoE PF Adj. P&L Aug-26'!$C$11:$C$108,0),MATCH(Q$8,'QoE PF Adj. P&L Aug-26'!$D$8:$AI$8,0))*1000 -> 2300 | ... AO34: =+INDEX('QoE PF Adj. P&L Aug-26'!$D$11:$AI$108,MATCH($C34,'QoE PF Adj. P&L Aug-26'!$C$11:$C$108,0),MATCH(AO$8,'QoE PF Adj. P&L Aug-26'!$D$8:$AI$8,0))*1000 -> 2600 | AP34: =+SUMIFS('Sep - Nov P&L'!I:I,'Sep - Nov P&L'!$D:$D,$C34) -> 2388.26 | AQ34: =+SUMIFS('Sep - Nov P&L'!J:J,'Sep - Nov P&L'!$D:$D,$C34) -> 2510.58 | AR34: =+SUMIFS('Sep - Nov P&L'!K:K,'Sep - Nov P&L'!$D:$D,$C34) -> 2511.75 | AS34: =+AS142 -> 2417.5492 | AT34: =+AT142 -> 2426.0106 | AU34: =+AU142 -> 2434.5016 | AV34: =+AV142 -> 2443.0224 | AW34: =+AW142 -> 2451.573 | AX34: =+AX142 -> 2460.1535 | AY34: =+AY142 -> 2468.764 | AZ34: =+AZ142 -> 2477.4047 | ... BQ34: =+BQ142 -> 2629.0107
C35: Storage | D35: =+SUMIFS($J35:$BQ35,$J$7:$BQ$7,D$8) -> 13000 | E35: =+SUMIFS($J35:$BQ35,$J$7:$BQ$7,E$8) -> 13700 | F35: =+SUMIFS($J35:$BQ35,$J$7:$BQ$7,F$8) -> 10825 | G35: =+SUMIFS($J35:$BQ35,$J$7:$BQ$7,G$8) -> 11355.794 | H35: =+SUMIFS($J35:$BQ35,$J$7:$BQ$7,H$8) -> 11842.027 | J35: =+INDEX('QoE PF Adj. P&L Aug-26'!$D$11:$AI$108,MATCH($C35,'QoE PF Adj. P&L Aug-26'!$C$11:$C$108,0),MATCH(J$8,'QoE PF Adj. P&L Aug-26'!$D$8:$AI$8,0))*1000 -> 1100 | K35: =+INDEX('QoE PF Adj. P&L Aug-26'!$D$11:$AI$108,MATCH($C35,'QoE PF Adj. P&L Aug-26'!$C$11:$C$108,0),MATCH(K$8,'QoE PF Adj. P&L Aug-26'!$D$8:$AI$8,0))*1000 -> 1100 | L35: =+INDEX('QoE PF Adj. P&L Aug-26'!$D$11:$AI$108,MATCH($C35,'QoE PF Adj. P&L Aug-26'!$C$11:$C$108,0),MATCH(L$8,'QoE PF Adj. P&L Aug-26'!$D$8:$AI$8,0))*1000 -> 1100 | M35: =+INDEX('QoE PF Adj. P&L Aug-26'!$D$11:$AI$108,MATCH($C35,'QoE PF Adj. P&L Aug-26'!$C$11:$C$108,0),MATCH(M$8,'QoE PF Adj. P&L Aug-26'!$D$8:$AI$8,0))*1000 -> 1000 | N35: =+INDEX('QoE PF Adj. P&L Aug-26'!$D$11:$AI$108,MATCH($C35,'QoE PF Adj. P&L Aug-26'!$C$11:$C$108,0),MATCH(N$8,'QoE PF Adj. P&L Aug-26'!$D$8:$AI$8,0))*1000 -> 1100 | O35: =+INDEX('QoE PF Adj. P&L Aug-26'!$D$11:$AI$108,MATCH($C35,'QoE PF Adj. P&L Aug-26'!$C$11:$C$108,0),MATCH(O$8,'QoE PF Adj. P&L Aug-26'!$D$8:$AI$8,0))*1000 -> 1100 | P35: =+INDEX('QoE PF Adj. P&L Aug-26'!$D$11:$AI$108,MATCH($C35,'QoE PF Adj. P&L Aug-26'!$C$11:$C$108,0),MATCH(P$8,'QoE PF Adj. P&L Aug-26'!$D$8:$AI$8,0))*1000 -> 1100 | Q35: =+INDEX('QoE PF Adj. P&L Aug-26'!$D$11:$AI$108,MATCH($C35,'QoE PF Adj. P&L Aug-26'!$C$11:$C$108,0),MATCH(Q$8,'QoE PF Adj. P&L Aug-26'!$D$8:$AI$8,0))*1000 -> 1000 | ... AO35: =+INDEX('QoE PF Adj. P&L Aug-26'!$D$11:$AI$108,MATCH($C35,'QoE PF Adj. P&L Aug-26'!$C$11:$C$108,0),MATCH(AO$8,'QoE PF Adj. P&L Aug-26'!$D$8:$AI$8,0))*1000 -> 1200 | AP35: =+SUMIFS('Sep - Nov P&L'!I:I,'Sep - Nov P&L'!$D:$D,$C35) -> 0 | AQ35: =+SUMIFS('Sep - Nov P&L'!J:J,'Sep - Nov P&L'!$D:$D,$C35) -> 0 | AR35: =+SUMIFS('Sep - Nov P&L'!K:K,'Sep - Nov P&L'!$D:$D,$C35) -> 0 | AS35: =+AS143 -> 925 | AT35: =+AT143 -> 928.2375 | AU35: =+AU143 -> 931.48633 | AV35: =+AV143 -> 934.74653 | AW35: =+AW143 -> 938.01815 | AX35: =+AX143 -> 941.30121 | AY35: =+AY143 -> 944.59576 | AZ35: =+AZ143 -> 947.90185 | ... BQ35: =+BQ143 -> 1005.9092
C36: Facility Repairs & Maintenance | D36: =+SUMIFS($J36:$BQ36,$J$7:$BQ$7,D$8) -> 45100 | E36: =+SUMIFS($J36:$BQ36,$J$7:$BQ$7,E$8) -> 48100 | F36: =+SUMIFS($J36:$BQ36,$J$7:$BQ$7,F$8) -> 69385.306 | G36: =+SUMIFS($J36:$BQ36,$J$7:$BQ$7,G$8) -> 69395.76 | H36: =+SUMIFS($J36:$BQ36,$J$7:$BQ$7,H$8) -> 72367.148 | J36: =+INDEX('QoE PF Adj. P&L Aug-26'!$D$11:$AI$108,MATCH($C36,'QoE PF Adj. P&L Aug-26'!$C$11:$C$108,0),MATCH(J$8,'QoE PF Adj. P&L Aug-26'!$D$8:$AI$8,0))*1000 -> 3600 | K36: =+INDEX('QoE PF Adj. P&L Aug-26'!$D$11:$AI$108,MATCH($C36,'QoE PF Adj. P&L Aug-26'!$C$11:$C$108,0),MATCH(K$8,'QoE PF Adj. P&L Aug-26'!$D$8:$AI$8,0))*1000 -> 3600 | L36: =+INDEX('QoE PF Adj. P&L Aug-26'!$D$11:$AI$108,MATCH($C36,'QoE PF Adj. P&L Aug-26'!$C$11:$C$108,0),MATCH(L$8,'QoE PF Adj. P&L Aug-26'!$D$8:$AI$8,0))*1000 -> 3600 | M36: =+INDEX('QoE PF Adj. P&L Aug-26'!$D$11:$AI$108,MATCH($C36,'QoE PF Adj. P&L Aug-26'!$C$11:$C$108,0),MATCH(M$8,'QoE PF Adj. P&L Aug-26'!$D$8:$AI$8,0))*1000 -> 3600 | N36: =+INDEX('QoE PF Adj. P&L Aug-26'!$D$11:$AI$108,MATCH($C36,'QoE PF Adj. P&L Aug-26'!$C$11:$C$108,0),MATCH(N$8,'QoE PF Adj. P&L Aug-26'!$D$8:$AI$8,0))*1000 -> 3800 | O36: =+INDEX('QoE PF Adj. P&L Aug-26'!$D$11:$AI$108,MATCH($C36,'QoE PF Adj. P&L Aug-26'!$C$11:$C$108,0),MATCH(O$8,'QoE PF Adj. P&L Aug-26'!$D$8:$AI$8,0))*1000 -> 4000 | P36: =+INDEX('QoE PF Adj. P&L Aug-26'!$D$11:$AI$108,MATCH($C36,'QoE PF Adj. P&L Aug-26'!$C$11:$C$108,0),MATCH(P$8,'QoE PF Adj. P&L Aug-26'!$D$8:$AI$8,0))*1000 -> 4000 | Q36: =+INDEX('QoE PF Adj. P&L Aug-26'!$D$11:$AI$108,MATCH($C36,'QoE PF Adj. P&L Aug-26'!$C$11:$C$108,0),MATCH(Q$8,'QoE PF Adj. P&L Aug-26'!$D$8:$AI$8,0))*1000 -> 3500 | ... AO36: =+INDEX('QoE PF Adj. P&L Aug-26'!$D$11:$AI$108,MATCH($C36,'QoE PF Adj. P&L Aug-26'!$C$11:$C$108,0),MATCH(AO$8,'QoE PF Adj. P&L Aug-26'!$D$8:$AI$8,0))*1000 -> 4300 | AP36: =+SUMIFS('Sep - Nov P&L'!I:I,'Sep - Nov P&L'!$D:$D,$C36) -> 9552.87 | AQ36: =+SUMIFS('Sep - Nov P&L'!J:J,'Sep - Nov P&L'!$D:$D,$C36) -> 9671.37 | AR36: =+SUMIFS('Sep - Nov P&L'!K:K,'Sep - Nov P&L'!$D:$D,$C36) -> 9508.35 | AS36: =+AS144 -> 5652.7158 | AT36: =+AT144 -> 5672.5003 | AU36: =+AU144 -> 5692.3541 | AV36: =+AV144 -> 5712.2773 | AW36: =+AW144 -> 5732.2703 | AX36: =+AX144 -> 5752.3332 | AY36: =+AY144 -> 5772.4664 | AZ36: =+AZ144 -> 5792.67 | ... BQ36: =+BQ144 -> 6147.1555
C37: Waste Removal | D37: =+SUMIFS($J37:$BQ37,$J$7:$BQ$7,D$8) -> 32000 | E37: =+SUMIFS($J37:$BQ37,$J$7:$BQ$7,E$8) -> 34500 | F37: =+SUMIFS($J37:$BQ37,$J$7:$BQ$7,F$8) -> 36913.938 | G37: =+SUMIFS($J37:$BQ37,$J$7:$BQ$7,G$8) -> 37503.81 | H37: =+SUMIFS($J37:$BQ37,$J$7:$BQ$7,H$8) -> 39109.648 | J37: =+INDEX('QoE PF Adj. P&L Aug-26'!$D$11:$AI$108,MATCH($C37,'QoE PF Adj. P&L Aug-26'!$C$11:$C$108,0),MATCH(J$8,'QoE PF Adj. P&L Aug-26'!$D$8:$AI$8,0))*1000 -> 2500 | K37: =+INDEX('QoE PF Adj. P&L Aug-26'!$D$11:$AI$108,MATCH($C37,'QoE PF Adj. P&L Aug-26'!$C$11:$C$108,0),MATCH(K$8,'QoE PF Adj. P&L Aug-26'!$D$8:$AI$8,0))*1000 -> 2500 | L37: =+INDEX('QoE PF Adj. P&L Aug-26'!$D$11:$AI$108,MATCH($C37,'QoE PF Adj. P&L Aug-26'!$C$11:$C$108,0),MATCH(L$8,'QoE PF Adj. P&L Aug-26'!$D$8:$AI$8,0))*1000 -> 2600 | M37: =+INDEX('QoE PF Adj. P&L Aug-26'!$D$11:$AI$108,MATCH($C37,'QoE PF Adj. P&L Aug-26'!$C$11:$C$108,0),MATCH(M$8,'QoE PF Adj. P&L Aug-26'!$D$8:$AI$8,0))*1000 -> 2600 | N37: =+INDEX('QoE PF Adj. P&L Aug-26'!$D$11:$AI$108,MATCH($C37,'QoE PF Adj. P&L Aug-26'!$C$11:$C$108,0),MATCH(N$8,'QoE PF Adj. P&L Aug-26'!$D$8:$AI$8,0))*1000 -> 2800 | O37: =+INDEX('QoE PF Adj. P&L Aug-26'!$D$11:$AI$108,MATCH($C37,'QoE PF Adj. P&L Aug-26'!$C$11:$C$108,0),MATCH(O$8,'QoE PF Adj. P&L Aug-26'!$D$8:$AI$8,0))*1000 -> 2600 | P37: =+INDEX('QoE PF Adj. P&L Aug-26'!$D$11:$AI$108,MATCH($C37,'QoE PF Adj. P&L Aug-26'!$C$11:$C$108,0),MATCH(P$8,'QoE PF Adj. P&L Aug-26'!$D$8:$AI$8,0))*1000 -> 2700 | Q37: =+INDEX('QoE PF Adj. P&L Aug-26'!$D$11:$AI$108,MATCH($C37,'QoE PF Adj. P&L Aug-26'!$C$11:$C$108,0),MATCH(Q$8,'QoE PF Adj. P&L Aug-26'!$D$8:$AI$8,0))*1000 -> 2800 | ... AO37: =+INDEX('QoE PF Adj. P&L Aug-26'!$D$11:$AI$108,MATCH($C37,'QoE PF Adj. P&L Aug-26'!$C$11:$C$108,0),MATCH(AO$8,'QoE PF Adj. P&L Aug-26'!$D$8:$AI$8,0))*1000 -> 3000 | AP37: =+SUMIFS('Sep - Nov P&L'!I:I,'Sep - Nov P&L'!$D:$D,$C37) -> 3150.22 | AQ37: =+SUMIFS('Sep - Nov P&L'!J:J,'Sep - Nov P&L'!$D:$D,$C37) -> 3298.3 | AR37: =+SUMIFS('Sep - Nov P&L'!K:K,'Sep - Nov P&L'!$D:$D,$C37) -> 3010.5 | AS37: =+AS145 -> 3054.9183 | AT37: =+AT145 -> 3065.6105 | AU37: =+AU145 -> 3076.3402 | AV37: =+AV145 -> 3087.1074 | AW37: =+AW145 -> 3097.9123 | AX37: =+AX145 -> 3108.7549 | AY37: =+AY145 -> 3119.6356 | AZ37: =+AZ145 -> 3130.5543 | ... BQ37: =+BQ145 -> 3322.1302
C38: Total Occupancy Costs | D38: =+SUMIFS($J38:$BQ38,$J$7:$BQ$7,D$8) -> 710400 | E38: =+SUMIFS($J38:$BQ38,$J$7:$BQ$7,E$8) -> 768100 | F38: =+SUMIFS($J38:$BQ38,$J$7:$BQ$7,F$8) -> 806806.72 | G38: =+SUMIFS($J38:$BQ38,$J$7:$BQ$7,G$8) -> 825178.33 | H38: =+SUMIFS($J38:$BQ38,$J$7:$BQ$7,H$8) -> 860510.82 | J38: =SUM(J30:J37) -> 57700 | K38: =SUM(K30:K37) -> 55700 | L38: =SUM(L30:L37) -> 59800 | M38: =SUM(M30:M37) -> 58700 | N38: =SUM(N30:N37) -> 61100 | O38: =SUM(O30:O37) -> 59700 | P38: =SUM(P30:P37) -> 59200 | Q38: =SUM(Q30:Q37) -> 58100 | ... BQ38: =SUM(BQ30:BQ37) -> 73095.236
C40: Drugs & Medical Supplies
B41: % rev | C41: Medical Supplies | D41: =+SUMIFS($J41:$BQ41,$J$7:$BQ$7,D$8) -> 317200 | E41: =+SUMIFS($J41:$BQ41,$J$7:$BQ$7,E$8) -> 343800 | F41: =+SUMIFS($J41:$BQ41,$J$7:$BQ$7,F$8) -> 430923.07 | G41: =+SUMIFS($J41:$BQ41,$J$7:$BQ$7,G$8) -> 414111.3 | H41: =+SUMIFS($J41:$BQ41,$J$7:$BQ$7,H$8) -> 483098.56 | J41: =+INDEX('QoE PF Adj. P&L Aug-26'!$D$11:$AI$108,MATCH($C41,'QoE PF Adj. P&L Aug-26'!$C$11:$C$108,0),MATCH(J$8,'QoE PF Adj. P&L Aug-26'!$D$8:$AI$8,0))*1000 -> 26600 | K41: =+INDEX('QoE PF Adj. P&L Aug-26'!$D$11:$AI$108,MATCH($C41,'QoE PF Adj. P&L Aug-26'!$C$11:$C$108,0),MATCH(K$8,'QoE PF Adj. P&L Aug-26'!$D$8:$AI$8,0))*1000 -> 23500 | L41: =+INDEX('QoE PF Adj. P&L Aug-26'!$D$11:$AI$108,MATCH($C41,'QoE PF Adj. P&L Aug-26'!$C$11:$C$108,0),MATCH(L$8,'QoE PF Adj. P&L Aug-26'!$D$8:$AI$8,0))*1000 -> 25600 | M41: =+INDEX('QoE PF Adj. P&L Aug-26'!$D$11:$AI$108,MATCH($C41,'QoE PF Adj. P&L Aug-26'!$C$11:$C$108,0),MATCH(M$8,'QoE PF Adj. P&L Aug-26'!$D$8:$AI$8,0))*1000 -> 25900 | N41: =+INDEX('QoE PF Adj. P&L Aug-26'!$D$11:$AI$108,MATCH($C41,'QoE PF Adj. P&L Aug-26'!$C$11:$C$108,0),MATCH(N$8,'QoE PF Adj. P&L Aug-26'!$D$8:$AI$8,0))*1000 -> 28600 | O41: =+INDEX('QoE PF Adj. P&L Aug-26'!$D$11:$AI$108,MATCH($C41,'QoE PF Adj. P&L Aug-26'!$C$11:$C$108,0),MATCH(O$8,'QoE PF Adj. P&L Aug-26'!$D$8:$AI$8,0))*1000 -> 25100 | P41: =+INDEX('QoE PF Adj. P&L Aug-26'!$D$11:$AI$108,MATCH($C41,'QoE PF Adj. P&L Aug-26'!$C$11:$C$108,0),MATCH(P$8,'QoE PF Adj. P&L Aug-26'!$D$8:$AI$8,0))*1000 -> 25800 | Q41: =+INDEX('QoE PF Adj. P&L Aug-26'!$D$11:$AI$108,MATCH($C41,'QoE PF Adj. P&L Aug-26'!$C$11:$C$108,0),MATCH(Q$8,'QoE PF Adj. P&L Aug-26'!$D$8:$AI$8,0))*1000 -> 26500 | ... AO41: =+INDEX('QoE PF Adj. P&L Aug-26'!$D$11:$AI$108,MATCH($C41,'QoE PF Adj. P&L Aug-26'!$C$11:$C$108,0),MATCH(AO$8,'QoE PF Adj. P&L Aug-26'!$D$8:$AI$8,0))*1000 -> 29800 | AP41: =+SUMIFS('Sep - Nov P&L'!I:I,'Sep - Nov P&L'!$D:$D,$C41) -> 52039.5 | AQ41: =+SUMIFS('Sep - Nov P&L'!J:J,'Sep - Nov P&L'!$D:$D,$C41) -> 56217.96 | AR41: =+SUMIFS('Sep - Nov P&L'!K:K,'Sep - Nov P&L'!$D:$D,$C41) -> 46736.19 | AS41: =+AS$10*AS149 -> 32929.421 | AT41: =+AT$10*AT149 -> 30064.966 | AU41: =+AU$10*AU149 -> 28632.738 | AV41: =+AV$10*AV149 -> 33825.593 | AW41: =+AW$10*AW149 -> 34482.473 | AX41: =+AX$10*AX149 -> 32082.73 | AY41: =+AY$10*AY149 -> 34290.554 | AZ41: =+AZ$10*AZ149 -> 34970.066 | ... BQ41: =+BQ$10*BQ149 -> 39857.645
B42: % rev | C42: Lab Supplies | D42: =+SUMIFS($J42:$BQ42,$J$7:$BQ$7,D$8) -> 1073300 | E42: =+SUMIFS($J42:$BQ42,$J$7:$BQ$7,E$8) -> 1164300 | F42: =+SUMIFS($J42:$BQ42,$J$7:$BQ$7,F$8) -> 1264791.2 | G42: =+SUMIFS($J42:$BQ42,$J$7:$BQ$7,G$8) -> 1403106.5 | H42: =+SUMIFS($J42:$BQ42,$J$7:$BQ$7,H$8) -> 1636851.6 | J42: =+INDEX('QoE PF Adj. P&L Aug-26'!$D$11:$AI$108,MATCH($C42,'QoE PF Adj. P&L Aug-26'!$C$11:$C$108,0),MATCH(J$8,'QoE PF Adj. P&L Aug-26'!$D$8:$AI$8,0))*1000 -> 87200 | K42: =+INDEX('QoE PF Adj. P&L Aug-26'!$D$11:$AI$108,MATCH($C42,'QoE PF Adj. P&L Aug-26'!$C$11:$C$108,0),MATCH(K$8,'QoE PF Adj. P&L Aug-26'!$D$8:$AI$8,0))*1000 -> 80100 | L42: =+INDEX('QoE PF Adj. P&L Aug-26'!$D$11:$AI$108,MATCH($C42,'QoE PF Adj. P&L Aug-26'!$C$11:$C$108,0),MATCH(L$8,'QoE PF Adj. P&L Aug-26'!$D$8:$AI$8,0))*1000 -> 87900 | M42: =+INDEX('QoE PF Adj. P&L Aug-26'!$D$11:$AI$108,MATCH($C42,'QoE PF Adj. P&L Aug-26'!$C$11:$C$108,0),MATCH(M$8,'QoE PF Adj. P&L Aug-26'!$D$8:$AI$8,0))*1000 -> 86300 | N42: =+INDEX('QoE PF Adj. P&L Aug-26'!$D$11:$AI$108,MATCH($C42,'QoE PF Adj. P&L Aug-26'!$C$11:$C$108,0),MATCH(N$8,'QoE PF Adj. P&L Aug-26'!$D$8:$AI$8,0))*1000 -> 97000 | O42: =+INDEX('QoE PF Adj. P&L Aug-26'!$D$11:$AI$108,MATCH($C42,'QoE PF Adj. P&L Aug-26'!$C$11:$C$108,0),MATCH(O$8,'QoE PF Adj. P&L Aug-26'!$D$8:$AI$8,0))*1000 -> 80900 | P42: =+INDEX('QoE PF Adj. P&L Aug-26'!$D$11:$AI$108,MATCH($C42,'QoE PF Adj. P&L Aug-26'!$C$11:$C$108,0),MATCH(P$8,'QoE PF Adj. P&L Aug-26'!$D$8:$AI$8,0))*1000 -> 91800 | Q42: =+INDEX('QoE PF Adj. P&L Aug-26'!$D$11:$AI$108,MATCH($C42,'QoE PF Adj. P&L Aug-26'!$C$11:$C$108,0),MATCH(Q$8,'QoE PF Adj. P&L Aug-26'!$D$8:$AI$8,0))*1000 -> 95800 | ... AO42: =+INDEX('QoE PF Adj. P&L Aug-26'!$D$11:$AI$108,MATCH($C42,'QoE PF Adj. P&L Aug-26'!$C$11:$C$108,0),MATCH(AO$8,'QoE PF Adj. P&L Aug-26'!$D$8:$AI$8,0))*1000 -> 101100 | AP42: =+SUMIFS('Sep - Nov P&L'!I:I,'Sep - Nov P&L'!$D:$D,$C42) -> 106214.08 | AQ42: =+SUMIFS('Sep - Nov P&L'!J:J,'Sep - Nov P&L'!$D:$D,$C42) -> 119964.33 | AR42: =+SUMIFS('Sep - Nov P&L'!K:K,'Sep - Nov P&L'!$D:$D,$C42) -> 98240.19 | AS42: =+AS$10*AS150 -> 111572.63 | AT42: =+AT$10*AT150 -> 101867.18 | AU42: =+AU$10*AU150 -> 97014.454 | AV42: =+AV$10*AV150 -> 114609.07 | AW42: =+AW$10*AW150 -> 116834.73 | AX42: =+AX$10*AX150 -> 108703.84 | AY42: =+AY$10*AY150 -> 116184.47 | AZ42: =+AZ$10*AZ150 -> 118486.81 | ... BQ42: =+BQ$10*BQ150 -> 135047.08
B43: % rev | C43: Drugs | D43: =+SUMIFS($J43:$BQ43,$J$7:$BQ$7,D$8) -> 114800 | E43: =+SUMIFS($J43:$BQ43,$J$7:$BQ$7,E$8) -> 123600 | F43: =+SUMIFS($J43:$BQ43,$J$7:$BQ$7,F$8) -> 100193.01 | G43: =+SUMIFS($J43:$BQ43,$J$7:$BQ$7,G$8) -> 144532.96 | H43: =+SUMIFS($J43:$BQ43,$J$7:$BQ$7,H$8) -> 168610.87 | J43: =+INDEX('QoE PF Adj. P&L Aug-26'!$D$11:$AI$108,MATCH($C43,'QoE PF Adj. P&L Aug-26'!$C$11:$C$108,0),MATCH(J$8,'QoE PF Adj. P&L Aug-26'!$D$8:$AI$8,0))*1000 -> 9300 | K43: =+INDEX('QoE PF Adj. P&L Aug-26'!$D$11:$AI$108,MATCH($C43,'QoE PF Adj. P&L Aug-26'!$C$11:$C$108,0),MATCH(K$8,'QoE PF Adj. P&L Aug-26'!$D$8:$AI$8,0))*1000 -> 8800 | L43: =+INDEX('QoE PF Adj. P&L Aug-26'!$D$11:$AI$108,MATCH($C43,'QoE PF Adj. P&L Aug-26'!$C$11:$C$108,0),MATCH(L$8,'QoE PF Adj. P&L Aug-26'!$D$8:$AI$8,0))*1000 -> 9700 | M43: =+INDEX('QoE PF Adj. P&L Aug-26'!$D$11:$AI$108,MATCH($C43,'QoE PF Adj. P&L Aug-26'!$C$11:$C$108,0),MATCH(M$8,'QoE PF Adj. P&L Aug-26'!$D$8:$AI$8,0))*1000 -> 9100 | N43: =+INDEX('QoE PF Adj. P&L Aug-26'!$D$11:$AI$108,MATCH($C43,'QoE PF Adj. P&L Aug-26'!$C$11:$C$108,0),MATCH(N$8,'QoE PF Adj. P&L Aug-26'!$D$8:$AI$8,0))*1000 -> 10200 | O43: =+INDEX('QoE PF Adj. P&L Aug-26'!$D$11:$AI$108,MATCH($C43,'QoE PF Adj. P&L Aug-26'!$C$11:$C$108,0),MATCH(O$8,'QoE PF Adj. P&L Aug-26'!$D$8:$AI$8,0))*1000 -> 9200 | P43: =+INDEX('QoE PF Adj. P&L Aug-26'!$D$11:$AI$108,MATCH($C43,'QoE PF Adj. P&L Aug-26'!$C$11:$C$108,0),MATCH(P$8,'QoE PF Adj. P&L Aug-26'!$D$8:$AI$8,0))*1000 -> 9800 | Q43: =+INDEX('QoE PF Adj. P&L Aug-26'!$D$11:$AI$108,MATCH($C43,'QoE PF Adj. P&L Aug-26'!$C$11:$C$108,0),MATCH(Q$8,'QoE PF Adj. P&L Aug-26'!$D$8:$AI$8,0))*1000 -> 10100 | ... AO43: =+INDEX('QoE PF Adj. P&L Aug-26'!$D$11:$AI$108,MATCH($C43,'QoE PF Adj. P&L Aug-26'!$C$11:$C$108,0),MATCH(AO$8,'QoE PF Adj. P&L Aug-26'!$D$8:$AI$8,0))*1000 -> 10700 | AP43: =+SUMIFS('Sep - Nov P&L'!I:I,'Sep - Nov P&L'!$D:$D,$C43) -> 0 | AQ43: =+SUMIFS('Sep - Nov P&L'!J:J,'Sep - Nov P&L'!$D:$D,$C43) -> 0 | AR43: =+SUMIFS('Sep - Nov P&L'!K:K,'Sep - Nov P&L'!$D:$D,$C43) -> 0 | AS43: =+AS$10*AS151 -> 11493.014 | AT43: =+AT$10*AT151 -> 10493.263 | AU43: =+AU$10*AU151 -> 9993.387 | AV43: =+AV$10*AV151 -> 11805.795 | AW43: =+AW$10*AW151 -> 12035.059 | AX43: =+AX$10*AX151 -> 11197.502 | AY43: =+AY$10*AY151 -> 11968.076 | AZ43: =+AZ$10*AZ151 -> 12205.239 | ... BQ43: =+BQ$10*BQ151 -> 13911.1
B44: % rev | C44: Pharmacy | D44: =+SUMIFS($J44:$BQ44,$J$7:$BQ$7,D$8) -> 75600 | E44: =+SUMIFS($J44:$BQ44,$J$7:$BQ$7,E$8) -> 82400 | F44: =+SUMIFS($J44:$BQ44,$J$7:$BQ$7,F$8) -> 65089.829 | G44: =+SUMIFS($J44:$BQ44,$J$7:$BQ$7,G$8) -> 94190.022 | H44: =+SUMIFS($J44:$BQ44,$J$7:$BQ$7,H$8) -> 109881.24 | J44: =+INDEX('QoE PF Adj. P&L Aug-26'!$D$11:$AI$108,MATCH($C44,'QoE PF Adj. P&L Aug-26'!$C$11:$C$108,0),MATCH(J$8,'QoE PF Adj. P&L Aug-26'!$D$8:$AI$8,0))*1000 -> 6400 | K44: =+INDEX('QoE PF Adj. P&L Aug-26'!$D$11:$AI$108,MATCH($C44,'QoE PF Adj. P&L Aug-26'!$C$11:$C$108,0),MATCH(K$8,'QoE PF Adj. P&L Aug-26'!$D$8:$AI$8,0))*1000 -> 5500 | L44: =+INDEX('QoE PF Adj. P&L Aug-26'!$D$11:$AI$108,MATCH($C44,'QoE PF Adj. P&L Aug-26'!$C$11:$C$108,0),MATCH(L$8,'QoE PF Adj. P&L Aug-26'!$D$8:$AI$8,0))*1000 -> 6500 | M44: =+INDEX('QoE PF Adj. P&L Aug-26'!$D$11:$AI$108,MATCH($C44,'QoE PF Adj. P&L Aug-26'!$C$11:$C$108,0),MATCH(M$8,'QoE PF Adj. P&L Aug-26'!$D$8:$AI$8,0))*1000 -> 5900 | N44: =+INDEX('QoE PF Adj. P&L Aug-26'!$D$11:$AI$108,MATCH($C44,'QoE PF Adj. P&L Aug-26'!$C$11:$C$108,0),MATCH(N$8,'QoE PF Adj. P&L Aug-26'!$D$8:$AI$8,0))*1000 -> 7000 | O44: =+INDEX('QoE PF Adj. P&L Aug-26'!$D$11:$AI$108,MATCH($C44,'QoE PF Adj. P&L Aug-26'!$C$11:$C$108,0),MATCH(O$8,'QoE PF Adj. P&L Aug-26'!$D$8:$AI$8,0))*1000 -> 5900 | P44: =+INDEX('QoE PF Adj. P&L Aug-26'!$D$11:$AI$108,MATCH($C44,'QoE PF Adj. P&L Aug-26'!$C$11:$C$108,0),MATCH(P$8,'QoE PF Adj. P&L Aug-26'!$D$8:$AI$8,0))*1000 -> 6200 | Q44: =+INDEX('QoE PF Adj. P&L Aug-26'!$D$11:$AI$108,MATCH($C44,'QoE PF Adj. P&L Aug-26'!$C$11:$C$108,0),MATCH(Q$8,'QoE PF Adj. P&L Aug-26'!$D$8:$AI$8,0))*1000 -> 6300 | ... AO44: =+INDEX('QoE PF Adj. P&L Aug-26'!$D$11:$AI$108,MATCH($C44,'QoE PF Adj. P&L Aug-26'!$C$11:$C$108,0),MATCH(AO$8,'QoE PF Adj. P&L Aug-26'!$D$8:$AI$8,0))*1000 -> 7700 | AP44: =+SUMIFS('Sep - Nov P&L'!I:I,'Sep - Nov P&L'!$D:$D,$C44) -> 0 | AQ44: =+SUMIFS('Sep - Nov P&L'!J:J,'Sep - Nov P&L'!$D:$D,$C44) -> 0 | AR44: =+SUMIFS('Sep - Nov P&L'!K:K,'Sep - Nov P&L'!$D:$D,$C44) -> 0 | AS44: =+AS$10*AS152 -> 7489.8291 | AT44: =+AT$10*AT152 -> 6838.3059 | AU44: =+AU$10*AU152 -> 6512.5444 | AV44: =+AV$10*AV152 -> 7693.6643 | AW44: =+AW$10*AW152 -> 7843.0723 | AX44: =+AX$10*AX152 -> 7297.2483 | AY44: =+AY$10*AY152 -> 7799.4201 | AZ44: =+AZ$10*AZ152 -> 7953.9759 | ... BQ44: =+BQ$10*BQ152 -> 9065.6605
C45: Total Drugs & Medical Supplies | D45: =+SUMIFS($J45:$BQ45,$J$7:$BQ$7,D$8) -> 1580900 | E45: =+SUMIFS($J45:$BQ45,$J$7:$BQ$7,E$8) -> 1714100 | F45: =+SUMIFS($J45:$BQ45,$J$7:$BQ$7,F$8) -> 1860997.1 | G45: =+SUMIFS($J45:$BQ45,$J$7:$BQ$7,G$8) -> 2055940.8 | H45: =+SUMIFS($J45:$BQ45,$J$7:$BQ$7,H$8) -> 2398442.3 | J45: =SUM(J41:J44) -> 129500 | K45: =SUM(K41:K44) -> 117900 | L45: =SUM(L41:L44) -> 129700 | M45: =SUM(M41:M44) -> 127200 | N45: =SUM(N41:N44) -> 142800 | O45: =SUM(O41:O44) -> 121100 | P45: =SUM(P41:P44) -> 133600 | Q45: =SUM(Q41:Q44) -> 138700 | ... BQ45: =SUM(BQ41:BQ44) -> 197881.49
C47: Ancillary Services & Supplies
B48: % rev | C48: Laboratory Fees | D48: =+SUMIFS($J48:$BQ48,$J$7:$BQ$7,D$8) -> 729800 | E48: =+SUMIFS($J48:$BQ48,$J$7:$BQ$7,E$8) -> 792200 | F48: =+SUMIFS($J48:$BQ48,$J$7:$BQ$7,F$8) -> 863135.37 | G48: =+SUMIFS($J48:$BQ48,$J$7:$BQ$7,G$8) -> 948396.08 | H48: =+SUMIFS($J48:$BQ48,$J$7:$BQ$7,H$8) -> 1106390.4 | J48: =+INDEX('QoE PF Adj. P&L Aug-26'!$D$11:$AI$108,MATCH($C48,'QoE PF Adj. P&L Aug-26'!$C$11:$C$108,0),MATCH(J$8,'QoE PF Adj. P&L Aug-26'!$D$8:$AI$8,0))*1000 -> 59000 | K48: =+INDEX('QoE PF Adj. P&L Aug-26'!$D$11:$AI$108,MATCH($C48,'QoE PF Adj. P&L Aug-26'!$C$11:$C$108,0),MATCH(K$8,'QoE PF Adj. P&L Aug-26'!$D$8:$AI$8,0))*1000 -> 55800 | L48: =+INDEX('QoE PF Adj. P&L Aug-26'!$D$11:$AI$108,MATCH($C48,'QoE PF Adj. P&L Aug-26'!$C$11:$C$108,0),MATCH(L$8,'QoE PF Adj. P&L Aug-26'!$D$8:$AI$8,0))*1000 -> 59000 | M48: =+INDEX('QoE PF Adj. P&L Aug-26'!$D$11:$AI$108,MATCH($C48,'QoE PF Adj. P&L Aug-26'!$C$11:$C$108,0),MATCH(M$8,'QoE PF Adj. P&L Aug-26'!$D$8:$AI$8,0))*1000 -> 58400 | N48: =+INDEX('QoE PF Adj. P&L Aug-26'!$D$11:$AI$108,MATCH($C48,'QoE PF Adj. P&L Aug-26'!$C$11:$C$108,0),MATCH(N$8,'QoE PF Adj. P&L Aug-26'!$D$8:$AI$8,0))*1000 -> 69300 | O48: =+INDEX('QoE PF Adj. P&L Aug-26'!$D$11:$AI$108,MATCH($C48,'QoE PF Adj. P&L Aug-26'!$C$11:$C$108,0),MATCH(O$8,'QoE PF Adj. P&L Aug-26'!$D$8:$AI$8,0))*1000 -> 54700 | P48: =+INDEX('QoE PF Adj. P&L Aug-26'!$D$11:$AI$108,MATCH($C48,'QoE PF Adj. P&L Aug-26'!$C$11:$C$108,0),MATCH(P$8,'QoE PF Adj. P&L Aug-26'!$D$8:$AI$8,0))*1000 -> 64500 | Q48: =+INDEX('QoE PF Adj. P&L Aug-26'!$D$11:$AI$108,MATCH($C48,'QoE PF Adj. P&L Aug-26'!$C$11:$C$108,0),MATCH(Q$8,'QoE PF Adj. P&L Aug-26'!$D$8:$AI$8,0))*1000 -> 66000 | ... AO48: =+INDEX('QoE PF Adj. P&L Aug-26'!$D$11:$AI$108,MATCH($C48,'QoE PF Adj. P&L Aug-26'!$C$11:$C$108,0),MATCH(AO$8,'QoE PF Adj. P&L Aug-26'!$D$8:$AI$8,0))*1000 -> 74600 | AP48: =+SUMIFS('Sep - Nov P&L'!I:I,'Sep - Nov P&L'!$D:$D,$C48) -> 74758.7 | AQ48: =+SUMIFS('Sep - Nov P&L'!J:J,'Sep - Nov P&L'!$D:$D,$C48) -> 77001.36 | AR48: =+SUMIFS('Sep - Nov P&L'!K:K,'Sep - Nov P&L'!$D:$D,$C48) -> 69860.48 | AS48: =+AS$10*AS156 -> 75414.831 | AT48: =+AT$10*AT156 -> 68854.667 | AU48: =+AU$10*AU156 -> 65574.585 | AV48: =+AV$10*AV156 -> 77467.24 | AW48: =+AW$10*AW156 -> 78971.624 | AX48: =+AX$10*AX156 -> 73475.742 | AY48: =+AY$10*AY156 -> 78532.092 | AZ48: =+AZ$10*AZ156 -> 80088.309 | ... BQ48: =+BQ$10*BQ156 -> 91281.823
B49: % rev | C49: Other Lab Expenses | D49: =+SUMIFS($J49:$BQ49,$J$7:$BQ$7,D$8) -> 88500 | E49: =+SUMIFS($J49:$BQ49,$J$7:$BQ$7,E$8) -> 98100 | F49: =+SUMIFS($J49:$BQ49,$J$7:$BQ$7,F$8) -> 140439.59 | G49: =+SUMIFS($J49:$BQ49,$J$7:$BQ$7,G$8) -> 115301.58 | H49: =+SUMIFS($J49:$BQ49,$J$7:$BQ$7,H$8) -> 134509.79 | J49: =+INDEX('QoE PF Adj. P&L Aug-26'!$D$11:$AI$108,MATCH($C49,'QoE PF Adj. P&L Aug-26'!$C$11:$C$108,0),MATCH(J$8,'QoE PF Adj. P&L Aug-26'!$D$8:$AI$8,0))*1000 -> 7300 | K49: =+INDEX('QoE PF Adj. P&L Aug-26'!$D$11:$AI$108,MATCH($C49,'QoE PF Adj. P&L Aug-26'!$C$11:$C$108,0),MATCH(K$8,'QoE PF Adj. P&L Aug-26'!$D$8:$AI$8,0))*1000 -> 6600 | L49: =+INDEX('QoE PF Adj. P&L Aug-26'!$D$11:$AI$108,MATCH($C49,'QoE PF Adj. P&L Aug-26'!$C$11:$C$108,0),MATCH(L$8,'QoE PF Adj. P&L Aug-26'!$D$8:$AI$8,0))*1000 -> 7100 | M49: =+INDEX('QoE PF Adj. P&L Aug-26'!$D$11:$AI$108,MATCH($C49,'QoE PF Adj. P&L Aug-26'!$C$11:$C$108,0),MATCH(M$8,'QoE PF Adj. P&L Aug-26'!$D$8:$AI$8,0))*1000 -> 7300 | N49: =+INDEX('QoE PF Adj. P&L Aug-26'!$D$11:$AI$108,MATCH($C49,'QoE PF Adj. P&L Aug-26'!$C$11:$C$108,0),MATCH(N$8,'QoE PF Adj. P&L Aug-26'!$D$8:$AI$8,0))*1000 -> 7900 | O49: =+INDEX('QoE PF Adj. P&L Aug-26'!$D$11:$AI$108,MATCH($C49,'QoE PF Adj. P&L Aug-26'!$C$11:$C$108,0),MATCH(O$8,'QoE PF Adj. P&L Aug-26'!$D$8:$AI$8,0))*1000 -> 6500 | P49: =+INDEX('QoE PF Adj. P&L Aug-26'!$D$11:$AI$108,MATCH($C49,'QoE PF Adj. P&L Aug-26'!$C$11:$C$108,0),MATCH(P$8,'QoE PF Adj. P&L Aug-26'!$D$8:$AI$8,0))*1000 -> 7500 | Q49: =+INDEX('QoE PF Adj. P&L Aug-26'!$D$11:$AI$108,MATCH($C49,'QoE PF Adj. P&L Aug-26'!$C$11:$C$108,0),MATCH(Q$8,'QoE PF Adj. P&L Aug-26'!$D$8:$AI$8,0))*1000 -> 7700 | ... AO49: =+INDEX('QoE PF Adj. P&L Aug-26'!$D$11:$AI$108,MATCH($C49,'QoE PF Adj. P&L Aug-26'!$C$11:$C$108,0),MATCH(AO$8,'QoE PF Adj. P&L Aug-26'!$D$8:$AI$8,0))*1000 -> 8300 | AP49: =+SUMIFS('Sep - Nov P&L'!I:I,'Sep - Nov P&L'!$D:$D,$C49) -> 20978.31 | AQ49: =+SUMIFS('Sep - Nov P&L'!J:J,'Sep - Nov P&L'!$D:$D,$C49) -> 21804.08 | AR49: =+SUMIFS('Sep - Nov P&L'!K:K,'Sep - Nov P&L'!$D:$D,$C49) -> 19388.62 | AS49: =+AS$10*AS157 -> 9168.5839 | AT49: =+AT$10*AT157 -> 8371.0297 | AU49: =+AU$10*AU157 -> 7972.2526 | AV49: =+AV$10*AV157 -> 9418.1063 | AW49: =+AW$10*AW157 -> 9601.0023 | AX49: =+AX$10*AX157 -> 8932.8385 | AY49: =+AY$10*AY157 -> 9547.566 | AZ49: =+AZ$10*AZ157 -> 9736.7636 | ... BQ49: =+BQ$10*BQ157 -> 11097.619
B50: % rev | C50: CT & X-Ray | D50: =+SUMIFS($J50:$BQ50,$J$7:$BQ$7,D$8) -> 19100 | E50: =+SUMIFS($J50:$BQ50,$J$7:$BQ$7,E$8) -> 20900 | F50: =+SUMIFS($J50:$BQ50,$J$7:$BQ$7,F$8) -> 16537.025 | G50: =+SUMIFS($J50:$BQ50,$J$7:$BQ$7,G$8) -> 24359.488 | H50: =+SUMIFS($J50:$BQ50,$J$7:$BQ$7,H$8) -> 28417.562 | J50: =+INDEX('QoE PF Adj. P&L Aug-26'!$D$11:$AI$108,MATCH($C50,'QoE PF Adj. P&L Aug-26'!$C$11:$C$108,0),MATCH(J$8,'QoE PF Adj. P&L Aug-26'!$D$8:$AI$8,0))*1000 -> 1600 | K50: =+INDEX('QoE PF Adj. P&L Aug-26'!$D$11:$AI$108,MATCH($C50,'QoE PF Adj. P&L Aug-26'!$C$11:$C$108,0),MATCH(K$8,'QoE PF Adj. P&L Aug-26'!$D$8:$AI$8,0))*1000 -> 1500 | L50: =+INDEX('QoE PF Adj. P&L Aug-26'!$D$11:$AI$108,MATCH($C50,'QoE PF Adj. P&L Aug-26'!$C$11:$C$108,0),MATCH(L$8,'QoE PF Adj. P&L Aug-26'!$D$8:$AI$8,0))*1000 -> 1600 | M50: =+INDEX('QoE PF Adj. P&L Aug-26'!$D$11:$AI$108,MATCH($C50,'QoE PF Adj. P&L Aug-26'!$C$11:$C$108,0),MATCH(M$8,'QoE PF Adj. P&L Aug-26'!$D$8:$AI$8,0))*1000 -> 1600 | N50: =+INDEX('QoE PF Adj. P&L Aug-26'!$D$11:$AI$108,MATCH($C50,'QoE PF Adj. P&L Aug-26'!$C$11:$C$108,0),MATCH(N$8,'QoE PF Adj. P&L Aug-26'!$D$8:$AI$8,0))*1000 -> 1800 | O50: =+INDEX('QoE PF Adj. P&L Aug-26'!$D$11:$AI$108,MATCH($C50,'QoE PF Adj. P&L Aug-26'!$C$11:$C$108,0),MATCH(O$8,'QoE PF Adj. P&L Aug-26'!$D$8:$AI$8,0))*1000 -> 1400 | P50: =+INDEX('QoE PF Adj. P&L Aug-26'!$D$11:$AI$108,MATCH($C50,'QoE PF Adj. P&L Aug-26'!$C$11:$C$108,0),MATCH(P$8,'QoE PF Adj. P&L Aug-26'!$D$8:$AI$8,0))*1000 -> 1600 | Q50: =+INDEX('QoE PF Adj. P&L Aug-26'!$D$11:$AI$108,MATCH($C50,'QoE PF Adj. P&L Aug-26'!$C$11:$C$108,0),MATCH(Q$8,'QoE PF Adj. P&L Aug-26'!$D$8:$AI$8,0))*1000 -> 1600 | ... AO50: =+INDEX('QoE PF Adj. P&L Aug-26'!$D$11:$AI$108,MATCH($C50,'QoE PF Adj. P&L Aug-26'!$C$11:$C$108,0),MATCH(AO$8,'QoE PF Adj. P&L Aug-26'!$D$8:$AI$8,0))*1000 -> 1800 | AP50: =+SUMIFS('Sep - Nov P&L'!I:I,'Sep - Nov P&L'!$D:$D,$C50) -> 0 | AQ50: =+SUMIFS('Sep - Nov P&L'!J:J,'Sep - Nov P&L'!$D:$D,$C50) -> 0 | AR50: =+SUMIFS('Sep - Nov P&L'!K:K,'Sep - Nov P&L'!$D:$D,$C50) -> 0 | AS50: =+AS$10*AS158 -> 1937.0248 | AT50: =+AT$10*AT158 -> 1768.5274 | AU50: =+AU$10*AU158 -> 1684.2787 | AV50: =+AV$10*AV158 -> 1989.7408 | AW50: =+AW$10*AW158 -> 2028.3808 | AX50: =+AX$10*AX158 -> 1887.2194 | AY50: =+AY$10*AY158 -> 2017.0914 | AZ50: =+AZ$10*AZ158 -> 2057.0627 | ... BQ50: =+BQ$10*BQ158 -> 2344.5674
B51: % rev | C51: Net Anesthesia | D51: =+SUMIFS($J51:$BQ51,$J$7:$BQ$7,D$8) -> 6200 | E51: =+SUMIFS($J51:$BQ51,$J$7:$BQ$7,E$8) -> 7100 | F51: =+SUMIFS($J51:$BQ51,$J$7:$BQ$7,F$8) -> 5445.6749 | G51: =+SUMIFS($J51:$BQ51,$J$7:$BQ$7,G$8) -> 8119.8295 | H51: =+SUMIFS($J51:$BQ51,$J$7:$BQ$7,H$8) -> 9472.5207 | J51: =+INDEX('QoE PF Adj. P&L Aug-26'!$D$11:$AI$108,MATCH($C51,'QoE PF Adj. P&L Aug-26'!$C$11:$C$108,0),MATCH(J$8,'QoE PF Adj. P&L Aug-26'!$D$8:$AI$8,0))*1000 -> 500 | K51: =+INDEX('QoE PF Adj. P&L Aug-26'!$D$11:$AI$108,MATCH($C51,'QoE PF Adj. P&L Aug-26'!$C$11:$C$108,0),MATCH(K$8,'QoE PF Adj. P&L Aug-26'!$D$8:$AI$8,0))*1000 -> 500 | L51: =+INDEX('QoE PF Adj. P&L Aug-26'!$D$11:$AI$108,MATCH($C51,'QoE PF Adj. P&L Aug-26'!$C$11:$C$108,0),MATCH(L$8,'QoE PF Adj. P&L Aug-26'!$D$8:$AI$8,0))*1000 -> 500 | M51: =+INDEX('QoE PF Adj. P&L Aug-26'!$D$11:$AI$108,MATCH($C51,'QoE PF Adj. P&L Aug-26'!$C$11:$C$108,0),MATCH(M$8,'QoE PF Adj. P&L Aug-26'!$D$8:$AI$8,0))*1000 -> 500 | N51: =+INDEX('QoE PF Adj. P&L Aug-26'!$D$11:$AI$108,MATCH($C51,'QoE PF Adj. P&L Aug-26'!$C$11:$C$108,0),MATCH(N$8,'QoE PF Adj. P&L Aug-26'!$D$8:$AI$8,0))*1000 -> 600 | O51: =+INDEX('QoE PF Adj. P&L Aug-26'!$D$11:$AI$108,MATCH($C51,'QoE PF Adj. P&L Aug-26'!$C$11:$C$108,0),MATCH(O$8,'QoE PF Adj. P&L Aug-26'!$D$8:$AI$8,0))*1000 -> 500 | P51: =+INDEX('QoE PF Adj. P&L Aug-26'!$D$11:$AI$108,MATCH($C51,'QoE PF Adj. P&L Aug-26'!$C$11:$C$108,0),MATCH(P$8,'QoE PF Adj. P&L Aug-26'!$D$8:$AI$8,0))*1000 -> 500 | Q51: =+INDEX('QoE PF Adj. P&L Aug-26'!$D$11:$AI$108,MATCH($C51,'QoE PF Adj. P&L Aug-26'!$C$11:$C$108,0),MATCH(Q$8,'QoE PF Adj. P&L Aug-26'!$D$8:$AI$8,0))*1000 -> 500 | ... AO51: =+INDEX('QoE PF Adj. P&L Aug-26'!$D$11:$AI$108,MATCH($C51,'QoE PF Adj. P&L Aug-26'!$C$11:$C$108,0),MATCH(AO$8,'QoE PF Adj. P&L Aug-26'!$D$8:$AI$8,0))*1000 -> 600 | AP51: =+SUMIFS('Sep - Nov P&L'!I:I,'Sep - Nov P&L'!$D:$D,$C51) -> 0 | AQ51: =+SUMIFS('Sep - Nov P&L'!J:J,'Sep - Nov P&L'!$D:$D,$C51) -> 0 | AR51: =+SUMIFS('Sep - Nov P&L'!K:K,'Sep - Nov P&L'!$D:$D,$C51) -> 0 | AS51: =+AS$10*AS159 -> 645.67492 | AT51: =+AT$10*AT159 -> 589.50913 | AU51: =+AU$10*AU159 -> 561.42624 | AV51: =+AV$10*AV159 -> 663.24692 | AW51: =+AW$10*AW159 -> 676.12692 | AX51: =+AX$10*AX159 -> 629.07313 | AY51: =+AY$10*AY159 -> 672.3638 | AZ51: =+AZ$10*AZ159 -> 685.68758 | ... BQ51: =+BQ$10*BQ159 -> 781.52246
B52: % rev | C52: Transcription Expense | D52: =+SUMIFS($J52:$BQ52,$J$7:$BQ$7,D$8) -> 38200 | E52: =+SUMIFS($J52:$BQ52,$J$7:$BQ$7,E$8) -> 41100 | F52: =+SUMIFS($J52:$BQ52,$J$7:$BQ$7,F$8) -> 33074.05 | G52: =+SUMIFS($J52:$BQ52,$J$7:$BQ$7,G$8) -> 48718.977 | H52: =+SUMIFS($J52:$BQ52,$J$7:$BQ$7,H$8) -> 56835.124 | J52: =+INDEX('QoE PF Adj. P&L Aug-26'!$D$11:$AI$108,MATCH($C52,'QoE PF Adj. P&L Aug-26'!$C$11:$C$108,0),MATCH(J$8,'QoE PF Adj. P&L Aug-26'!$D$8:$AI$8,0))*1000 -> 3000 | K52: =+INDEX('QoE PF Adj. P&L Aug-26'!$D$11:$AI$108,MATCH($C52,'QoE PF Adj. P&L Aug-26'!$C$11:$C$108,0),MATCH(K$8,'QoE PF Adj. P&L Aug-26'!$D$8:$AI$8,0))*1000 -> 2900 | L52: =+INDEX('QoE PF Adj. P&L Aug-26'!$D$11:$AI$108,MATCH($C52,'QoE PF Adj. P&L Aug-26'!$C$11:$C$108,0),MATCH(L$8,'QoE PF Adj. P&L Aug-26'!$D$8:$AI$8,0))*1000 -> 3000 | M52: =+INDEX('QoE PF Adj. P&L Aug-26'!$D$11:$AI$108,MATCH($C52,'QoE PF Adj. P&L Aug-26'!$C$11:$C$108,0),MATCH(M$8,'QoE PF Adj. P&L Aug-26'!$D$8:$AI$8,0))*1000 -> 3200 | N52: =+INDEX('QoE PF Adj. P&L Aug-26'!$D$11:$AI$108,MATCH($C52,'QoE PF Adj. P&L Aug-26'!$C$11:$C$108,0),MATCH(N$8,'QoE PF Adj. P&L Aug-26'!$D$8:$AI$8,0))*1000 -> 3600 | O52: =+INDEX('QoE PF Adj. P&L Aug-26'!$D$11:$AI$108,MATCH($C52,'QoE PF Adj. P&L Aug-26'!$C$11:$C$108,0),MATCH(O$8,'QoE PF Adj. P&L Aug-26'!$D$8:$AI$8,0))*1000 -> 3000 | P52: =+INDEX('QoE PF Adj. P&L Aug-26'!$D$11:$AI$108,MATCH($C52,'QoE PF Adj. P&L Aug-26'!$C$11:$C$108,0),MATCH(P$8,'QoE PF Adj. P&L Aug-26'!$D$8:$AI$8,0))*1000 -> 3100 | Q52: =+INDEX('QoE PF Adj. P&L Aug-26'!$D$11:$AI$108,MATCH($C52,'QoE PF Adj. P&L Aug-26'!$C$11:$C$108,0),MATCH(Q$8,'QoE PF Adj. P&L Aug-26'!$D$8:$AI$8,0))*1000 -> 3200 | ... AO52: =+INDEX('QoE PF Adj. P&L Aug-26'!$D$11:$AI$108,MATCH($C52,'QoE PF Adj. P&L Aug-26'!$C$11:$C$108,0),MATCH(AO$8,'QoE PF Adj. P&L Aug-26'!$D$8:$AI$8,0))*1000 -> 3700 | AP52: =+SUMIFS('Sep - Nov P&L'!I:I,'Sep - Nov P&L'!$D:$D,$C52) -> 0 | AQ52: =+SUMIFS('Sep - Nov P&L'!J:J,'Sep - Nov P&L'!$D:$D,$C52) -> 0 | AR52: =+SUMIFS('Sep - Nov P&L'!K:K,'Sep - Nov P&L'!$D:$D,$C52) -> 0 | AS52: =+AS$10*AS160 -> 3874.0495 | AT52: =+AT$10*AT160 -> 3537.0548 | AU52: =+AU$10*AU160 -> 3368.5574 | AV52: =+AV$10*AV160 -> 3979.4815 | AW52: =+AW$10*AW160 -> 4056.7615 | AX52: =+AX$10*AX160 -> 3774.4388 | AY52: =+AY$10*AY160 -> 4034.1828 | AZ52: =+AZ$10*AZ160 -> 4114.1255 | ... BQ52: =+BQ$10*BQ160 -> 4689.1347
C53: Total Ancillary Services & Supplies | D53: =+SUMIFS($J53:$BQ53,$J$7:$BQ$7,D$8) -> 881800 | E53: =+SUMIFS($J53:$BQ53,$J$7:$BQ$7,E$8) -> 959400 | F53: =+SUMIFS($J53:$BQ53,$J$7:$BQ$7,F$8) -> 1058631.7 | G53: =+SUMIFS($J53:$BQ53,$J$7:$BQ$7,G$8) -> 1144896 | H53: =+SUMIFS($J53:$BQ53,$J$7:$BQ$7,H$8) -> 1335625.4 | J53: =SUM(J48:J52) -> 71400 | K53: =SUM(K48:K52) -> 67300 | L53: =SUM(L48:L52) -> 71200 | M53: =SUM(M48:M52) -> 71000 | N53: =SUM(N48:N52) -> 83200 | O53: =SUM(O48:O52) -> 66100 | P53: =SUM(P48:P52) -> 77200 | Q53: =SUM(Q48:Q52) -> 79000 | ... BQ53: =SUM(BQ48:BQ52) -> 110194.67
C55: Other Medical Costs
C56: Other Clinical Expenses | D56: =+SUMIFS($J56:$BQ56,$J$7:$BQ$7,D$8) -> 51600 | E56: =+SUMIFS($J56:$BQ56,$J$7:$BQ$7,E$8) -> 55300 | F56: =+SUMIFS($J56:$BQ56,$J$7:$BQ$7,F$8) -> 42866.667 | G56: =+SUMIFS($J56:$BQ56,$J$7:$BQ$7,G$8) -> 45013.959 | H56: =+SUMIFS($J56:$BQ56,$J$7:$BQ$7,H$8) -> 46941.367 | J56: =+INDEX('QoE PF Adj. P&L Aug-26'!$D$11:$AI$108,MATCH($C56,'QoE PF Adj. P&L Aug-26'!$C$11:$C$108,0),MATCH(J$8,'QoE PF Adj. P&L Aug-26'!$D$8:$AI$8,0))*1000 -> 4400 | K56: =+INDEX('QoE PF Adj. P&L Aug-26'!$D$11:$AI$108,MATCH($C56,'QoE PF Adj. P&L Aug-26'!$C$11:$C$108,0),MATCH(K$8,'QoE PF Adj. P&L Aug-26'!$D$8:$AI$8,0))*1000 -> 4300 | L56: =+INDEX('QoE PF Adj. P&L Aug-26'!$D$11:$AI$108,MATCH($C56,'QoE PF Adj. P&L Aug-26'!$C$11:$C$108,0),MATCH(L$8,'QoE PF Adj. P&L Aug-26'!$D$8:$AI$8,0))*1000 -> 4200 | M56: =+INDEX('QoE PF Adj. P&L Aug-26'!$D$11:$AI$108,MATCH($C56,'QoE PF Adj. P&L Aug-26'!$C$11:$C$108,0),MATCH(M$8,'QoE PF Adj. P&L Aug-26'!$D$8:$AI$8,0))*1000 -> 4300 | N56: =+INDEX('QoE PF Adj. P&L Aug-26'!$D$11:$AI$108,MATCH($C56,'QoE PF Adj. P&L Aug-26'!$C$11:$C$108,0),MATCH(N$8,'QoE PF Adj. P&L Aug-26'!$D$8:$AI$8,0))*1000 -> 4200 | O56: =+INDEX('QoE PF Adj. P&L Aug-26'!$D$11:$AI$108,MATCH($C56,'QoE PF Adj. P&L Aug-26'!$C$11:$C$108,0),MATCH(O$8,'QoE PF Adj. P&L Aug-26'!$D$8:$AI$8,0))*1000 -> 4400 | P56: =+INDEX('QoE PF Adj. P&L Aug-26'!$D$11:$AI$108,MATCH($C56,'QoE PF Adj. P&L Aug-26'!$C$11:$C$108,0),MATCH(P$8,'QoE PF Adj. P&L Aug-26'!$D$8:$AI$8,0))*1000 -> 4200 | Q56: =+INDEX('QoE PF Adj. P&L Aug-26'!$D$11:$AI$108,MATCH($C56,'QoE PF Adj. P&L Aug-26'!$C$11:$C$108,0),MATCH(Q$8,'QoE PF Adj. P&L Aug-26'!$D$8:$AI$8,0))*1000 -> 4500 | ... AO56: =+INDEX('QoE PF Adj. P&L Aug-26'!$D$11:$AI$108,MATCH($C56,'QoE PF Adj. P&L Aug-26'!$C$11:$C$108,0),MATCH(AO$8,'QoE PF Adj. P&L Aug-26'!$D$8:$AI$8,0))*1000 -> 4900 | AP56: =+SUMIFS('Sep - Nov P&L'!I:I,'Sep - Nov P&L'!$D:$D,$C56) -> 0 | AQ56: =+SUMIFS('Sep - Nov P&L'!J:J,'Sep - Nov P&L'!$D:$D,$C56) -> 0 | AR56: =+SUMIFS('Sep - Nov P&L'!K:K,'Sep - Nov P&L'!$D:$D,$C56) -> 0 | AS56: =+AS164 -> 3666.6667 | AT56: =+AT164 -> 3679.5 | AU56: =+AU164 -> 3692.3783 | AV56: =+AV164 -> 3705.3016 | AW56: =+AW164 -> 3718.2701 | AX56: =+AX164 -> 3731.2841 | AY56: =+AY164 -> 3744.3436 | AZ56: =+AZ164 -> 3757.4488 | ... BQ56: =+BQ164 -> 3987.3878
C57: Lab Equipment | D57: =+SUMIFS($J57:$BQ57,$J$7:$BQ$7,D$8) -> 58800 | E57: =+SUMIFS($J57:$BQ57,$J$7:$BQ$7,E$8) -> 61400 | F57: =+SUMIFS($J57:$BQ57,$J$7:$BQ$7,F$8) -> 66390.976 | G57: =+SUMIFS($J57:$BQ57,$J$7:$BQ$7,G$8) -> 67512.417 | H57: =+SUMIFS($J57:$BQ57,$J$7:$BQ$7,H$8) -> 70403.164 | J57: =+INDEX('QoE PF Adj. P&L Aug-26'!$D$11:$AI$108,MATCH($C57,'QoE PF Adj. P&L Aug-26'!$C$11:$C$108,0),MATCH(J$8,'QoE PF Adj. P&L Aug-26'!$D$8:$AI$8,0))*1000 -> 4500 | K57: =+INDEX('QoE PF Adj. P&L Aug-26'!$D$11:$AI$108,MATCH($C57,'QoE PF Adj. P&L Aug-26'!$C$11:$C$108,0),MATCH(K$8,'QoE PF Adj. P&L Aug-26'!$D$8:$AI$8,0))*1000 -> 4600 | L57: =+INDEX('QoE PF Adj. P&L Aug-26'!$D$11:$AI$108,MATCH($C57,'QoE PF Adj. P&L Aug-26'!$C$11:$C$108,0),MATCH(L$8,'QoE PF Adj. P&L Aug-26'!$D$8:$AI$8,0))*1000 -> 5000 | M57: =+INDEX('QoE PF Adj. P&L Aug-26'!$D$11:$AI$108,MATCH($C57,'QoE PF Adj. P&L Aug-26'!$C$11:$C$108,0),MATCH(M$8,'QoE PF Adj. P&L Aug-26'!$D$8:$AI$8,0))*1000 -> 4600 | N57: =+INDEX('QoE PF Adj. P&L Aug-26'!$D$11:$AI$108,MATCH($C57,'QoE PF Adj. P&L Aug-26'!$C$11:$C$108,0),MATCH(N$8,'QoE PF Adj. P&L Aug-26'!$D$8:$AI$8,0))*1000 -> 5100 | O57: =+INDEX('QoE PF Adj. P&L Aug-26'!$D$11:$AI$108,MATCH($C57,'QoE PF Adj. P&L Aug-26'!$C$11:$C$108,0),MATCH(O$8,'QoE PF Adj. P&L Aug-26'!$D$8:$AI$8,0))*1000 -> 5000 | P57: =+INDEX('QoE PF Adj. P&L Aug-26'!$D$11:$AI$108,MATCH($C57,'QoE PF Adj. P&L Aug-26'!$C$11:$C$108,0),MATCH(P$8,'QoE PF Adj. P&L Aug-26'!$D$8:$AI$8,0))*1000 -> 4900 | Q57: =+INDEX('QoE PF Adj. P&L Aug-26'!$D$11:$AI$108,MATCH($C57,'QoE PF Adj. P&L Aug-26'!$C$11:$C$108,0),MATCH(Q$8,'QoE PF Adj. P&L Aug-26'!$D$8:$AI$8,0))*1000 -> 5000 | ... AO57: =+INDEX('QoE PF Adj. P&L Aug-26'!$D$11:$AI$108,MATCH($C57,'QoE PF Adj. P&L Aug-26'!$C$11:$C$108,0),MATCH(AO$8,'QoE PF Adj. P&L Aug-26'!$D$8:$AI$8,0))*1000 -> 5800 | AP57: =+SUMIFS('Sep - Nov P&L'!I:I,'Sep - Nov P&L'!$D:$D,$C57) -> 5517.7 | AQ57: =+SUMIFS('Sep - Nov P&L'!J:J,'Sep - Nov P&L'!$D:$D,$C57) -> 5740.46 | AR57: =+SUMIFS('Sep - Nov P&L'!K:K,'Sep - Nov P&L'!$D:$D,$C57) -> 5333.51 | AS57: =+AS165 -> 5499.3058 | AT57: =+AT165 -> 5518.5534 | AU57: =+AU165 -> 5537.8683 | AV57: =+AV165 -> 5557.2509 | AW57: =+AW165 -> 5576.7013 | AX57: =+AX165 -> 5596.2197 | AY57: =+AY165 -> 5615.8065 | AZ57: =+AZ165 -> 5635.4618 | ... BQ57: =+BQ165 -> 5980.3268
C58: Lab Credentialing | D58: =+SUMIFS($J58:$BQ58,$J$7:$BQ$7,D$8) -> 19300 | E58: =+SUMIFS($J58:$BQ58,$J$7:$BQ$7,E$8) -> 20700 | F58: =+SUMIFS($J58:$BQ58,$J$7:$BQ$7,F$8) -> 22179.356 | G58: =+SUMIFS($J58:$BQ58,$J$7:$BQ$7,G$8) -> 22644.876 | H58: =+SUMIFS($J58:$BQ58,$J$7:$BQ$7,H$8) -> 23614.484 | J58: =+INDEX('QoE PF Adj. P&L Aug-26'!$D$11:$AI$108,MATCH($C58,'QoE PF Adj. P&L Aug-26'!$C$11:$C$108,0),MATCH(J$8,'QoE PF Adj. P&L Aug-26'!$D$8:$AI$8,0))*1000 -> 1600 | K58: =+INDEX('QoE PF Adj. P&L Aug-26'!$D$11:$AI$108,MATCH($C58,'QoE PF Adj. P&L Aug-26'!$C$11:$C$108,0),MATCH(K$8,'QoE PF Adj. P&L Aug-26'!$D$8:$AI$8,0))*1000 -> 1500 | L58: =+INDEX('QoE PF Adj. P&L Aug-26'!$D$11:$AI$108,MATCH($C58,'QoE PF Adj. P&L Aug-26'!$C$11:$C$108,0),MATCH(L$8,'QoE PF Adj. P&L Aug-26'!$D$8:$AI$8,0))*1000 -> 1600 | M58: =+INDEX('QoE PF Adj. P&L Aug-26'!$D$11:$AI$108,MATCH($C58,'QoE PF Adj. P&L Aug-26'!$C$11:$C$108,0),MATCH(M$8,'QoE PF Adj. P&L Aug-26'!$D$8:$AI$8,0))*1000 -> 1700 | N58: =+INDEX('QoE PF Adj. P&L Aug-26'!$D$11:$AI$108,MATCH($C58,'QoE PF Adj. P&L Aug-26'!$C$11:$C$108,0),MATCH(N$8,'QoE PF Adj. P&L Aug-26'!$D$8:$AI$8,0))*1000 -> 1700 | O58: =+INDEX('QoE PF Adj. P&L Aug-26'!$D$11:$AI$108,MATCH($C58,'QoE PF Adj. P&L Aug-26'!$C$11:$C$108,0),MATCH(O$8,'QoE PF Adj. P&L Aug-26'!$D$8:$AI$8,0))*1000 -> 1500 | P58: =+INDEX('QoE PF Adj. P&L Aug-26'!$D$11:$AI$108,MATCH($C58,'QoE PF Adj. P&L Aug-26'!$C$11:$C$108,0),MATCH(P$8,'QoE PF Adj. P&L Aug-26'!$D$8:$AI$8,0))*1000 -> 1500 | Q58: =+INDEX('QoE PF Adj. P&L Aug-26'!$D$11:$AI$108,MATCH($C58,'QoE PF Adj. P&L Aug-26'!$C$11:$C$108,0),MATCH(Q$8,'QoE PF Adj. P&L Aug-26'!$D$8:$AI$8,0))*1000 -> 1500 | ... AO58: =+INDEX('QoE PF Adj. P&L Aug-26'!$D$11:$AI$108,MATCH($C58,'QoE PF Adj. P&L Aug-26'!$C$11:$C$108,0),MATCH(AO$8,'QoE PF Adj. P&L Aug-26'!$D$8:$AI$8,0))*1000 -> 1800 | AP58: =+SUMIFS('Sep - Nov P&L'!I:I,'Sep - Nov P&L'!$D:$D,$C58) -> 1907.69 | AQ58: =+SUMIFS('Sep - Nov P&L'!J:J,'Sep - Nov P&L'!$D:$D,$C58) -> 1839.54 | AR58: =+SUMIFS('Sep - Nov P&L'!K:K,'Sep - Nov P&L'!$D:$D,$C58) -> 1887.56 | AS58: =+AS166 -> 1844.5658 | AT58: =+AT166 -> 1851.0218 | AU58: =+AU166 -> 1857.5004 | AV58: =+AV166 -> 1864.0016 | AW58: =+AW166 -> 1870.5256 | AX58: =+AX166 -> 1877.0725 | AY58: =+AY166 -> 1883.6422 | AZ58: =+AZ166 -> 1890.235 | ... BQ58: =+BQ166 -> 2005.9089
C59: Total Other Medical Costs | D59: =+SUMIFS($J59:$BQ59,$J$7:$BQ$7,D$8) -> 129700 | E59: =+SUMIFS($J59:$BQ59,$J$7:$BQ$7,E$8) -> 137400 | F59: =+SUMIFS($J59:$BQ59,$J$7:$BQ$7,F$8) -> 131437 | G59: =+SUMIFS($J59:$BQ59,$J$7:$BQ$7,G$8) -> 135171.25 | H59: =+SUMIFS($J59:$BQ59,$J$7:$BQ$7,H$8) -> 140959.02 | J59: =SUM(J56:J58) -> 10500 | K59: =SUM(K56:K58) -> 10400 | L59: =SUM(L56:L58) -> 10800 | M59: =SUM(M56:M58) -> 10600 | N59: =SUM(N56:N58) -> 11000 | O59: =SUM(O56:O58) -> 10900 | P59: =SUM(P56:P58) -> 10600 | Q59: =SUM(Q56:Q58) -> 11000 | ... BQ59: =SUM(BQ56:BQ58) -> 11973.623
C61: Insurance
C62: General Business | D62: =+SUMIFS($J62:$BQ62,$J$7:$BQ$7,D$8) -> 146100 | E62: =+SUMIFS($J62:$BQ62,$J$7:$BQ$7,E$8) -> 155500 | F62: =+SUMIFS($J62:$BQ62,$J$7:$BQ$7,F$8) -> 188908.98 | G62: =+SUMIFS($J62:$BQ62,$J$7:$BQ$7,G$8) -> 192166.67 | H62: =+SUMIFS($J62:$BQ62,$J$7:$BQ$7,H$8) -> 267166.67 | J62: =+INDEX('QoE PF Adj. P&L Aug-26'!$D$11:$AI$108,MATCH($C62,'QoE PF Adj. P&L Aug-26'!$C$11:$C$108,0),MATCH(J$8,'QoE PF Adj. P&L Aug-26'!$D$8:$AI$8,0))*1000 -> 12600 | K62: =+INDEX('QoE PF Adj. P&L Aug-26'!$D$11:$AI$108,MATCH($C62,'QoE PF Adj. P&L Aug-26'!$C$11:$C$108,0),MATCH(K$8,'QoE PF Adj. P&L Aug-26'!$D$8:$AI$8,0))*1000 -> 12100 | L62: =+INDEX('QoE PF Adj. P&L Aug-26'!$D$11:$AI$108,MATCH($C62,'QoE PF Adj. P&L Aug-26'!$C$11:$C$108,0),MATCH(L$8,'QoE PF Adj. P&L Aug-26'!$D$8:$AI$8,0))*1000 -> 11500 | M62: =+INDEX('QoE PF Adj. P&L Aug-26'!$D$11:$AI$108,MATCH($C62,'QoE PF Adj. P&L Aug-26'!$C$11:$C$108,0),MATCH(M$8,'QoE PF Adj. P&L Aug-26'!$D$8:$AI$8,0))*1000 -> 13000 | N62: =+INDEX('QoE PF Adj. P&L Aug-26'!$D$11:$AI$108,MATCH($C62,'QoE PF Adj. P&L Aug-26'!$C$11:$C$108,0),MATCH(N$8,'QoE PF Adj. P&L Aug-26'!$D$8:$AI$8,0))*1000 -> 11400 | O62: =+INDEX('QoE PF Adj. P&L Aug-26'!$D$11:$AI$108,MATCH($C62,'QoE PF Adj. P&L Aug-26'!$C$11:$C$108,0),MATCH(O$8,'QoE PF Adj. P&L Aug-26'!$D$8:$AI$8,0))*1000 -> 12500 | P62: =+INDEX('QoE PF Adj. P&L Aug-26'!$D$11:$AI$108,MATCH($C62,'QoE PF Adj. P&L Aug-26'!$C$11:$C$108,0),MATCH(P$8,'QoE PF Adj. P&L Aug-26'!$D$8:$AI$8,0))*1000 -> 11900 | Q62: =+INDEX('QoE PF Adj. P&L Aug-26'!$D$11:$AI$108,MATCH($C62,'QoE PF Adj. P&L Aug-26'!$C$11:$C$108,0),MATCH(Q$8,'QoE PF Adj. P&L Aug-26'!$D$8:$AI$8,0))*1000 -> 11600 | ... AO62: =+INDEX('QoE PF Adj. P&L Aug-26'!$D$11:$AI$108,MATCH($C62,'QoE PF Adj. P&L Aug-26'!$C$11:$C$108,0),MATCH(AO$8,'QoE PF Adj. P&L Aug-26'!$D$8:$AI$8,0))*1000 -> 13600 | AP62: =+SUMIFS('Sep - Nov P&L'!I:I,'Sep - Nov P&L'!$D:$D,$C62) -> 20403.37 | AQ62: =+SUMIFS('Sep - Nov P&L'!J:J,'Sep - Nov P&L'!$D:$D,$C62) -> 19957.11 | AR62: =+SUMIFS('Sep - Nov P&L'!K:K,'Sep - Nov P&L'!$D:$D,$C62) -> 21181.83 | AS62: =+'Separate Line Item Builds'!AS41 -> 15666.667 | AT62: =+'Separate Line Item Builds'!AT41 -> 15666.667 | AU62: =+'Separate Line Item Builds'!AU41 -> 15666.667 | AV62: =+'Separate Line Item Builds'!AV41 -> 15666.667 | AW62: =+'Separate Line Item Builds'!AW41 -> 15666.667 | AX62: =+'Separate Line Item Builds'!AX41 -> 15666.667 | AY62: =+'Separate Line Item Builds'!AY41 -> 15666.667 | AZ62: =+'Separate Line Item Builds'!AZ41 -> 15666.667 | ... BQ62: =+'Separate Line Item Builds'!BQ41 -> 24000
C63: Malpractice Insurance | D63: =+SUMIFS($J63:$BQ63,$J$7:$BQ$7,D$8) -> 31900 | E63: =+SUMIFS($J63:$BQ63,$J$7:$BQ$7,E$8) -> 33900 | F63: =+SUMIFS($J63:$BQ63,$J$7:$BQ$7,F$8) -> 26466.667 | G63: =+SUMIFS($J63:$BQ63,$J$7:$BQ$7,G$8) -> 27826.811 | H63: =+SUMIFS($J63:$BQ63,$J$7:$BQ$7,H$8) -> 29018.3 | J63: =+INDEX('QoE PF Adj. P&L Aug-26'!$D$11:$AI$108,MATCH($C63,'QoE PF Adj. P&L Aug-26'!$C$11:$C$108,0),MATCH(J$8,'QoE PF Adj. P&L Aug-26'!$D$8:$AI$8,0))*1000 -> 2500 | K63: =+INDEX('QoE PF Adj. P&L Aug-26'!$D$11:$AI$108,MATCH($C63,'QoE PF Adj. P&L Aug-26'!$C$11:$C$108,0),MATCH(K$8,'QoE PF Adj. P&L Aug-26'!$D$8:$AI$8,0))*1000 -> 2800 | L63: =+INDEX('QoE PF Adj. P&L Aug-26'!$D$11:$AI$108,MATCH($C63,'QoE PF Adj. P&L Aug-26'!$C$11:$C$108,0),MATCH(L$8,'QoE PF Adj. P&L Aug-26'!$D$8:$AI$8,0))*1000 -> 2500 | M63: =+INDEX('QoE PF Adj. P&L Aug-26'!$D$11:$AI$108,MATCH($C63,'QoE PF Adj. P&L Aug-26'!$C$11:$C$108,0),MATCH(M$8,'QoE PF Adj. P&L Aug-26'!$D$8:$AI$8,0))*1000 -> 2500 | N63: =+INDEX('QoE PF Adj. P&L Aug-26'!$D$11:$AI$108,MATCH($C63,'QoE PF Adj. P&L Aug-26'!$C$11:$C$108,0),MATCH(N$8,'QoE PF Adj. P&L Aug-26'!$D$8:$AI$8,0))*1000 -> 2600 | O63: =+INDEX('QoE PF Adj. P&L Aug-26'!$D$11:$AI$108,MATCH($C63,'QoE PF Adj. P&L Aug-26'!$C$11:$C$108,0),MATCH(O$8,'QoE PF Adj. P&L Aug-26'!$D$8:$AI$8,0))*1000 -> 2600 | P63: =+INDEX('QoE PF Adj. P&L Aug-26'!$D$11:$AI$108,MATCH($C63,'QoE PF Adj. P&L Aug-26'!$C$11:$C$108,0),MATCH(P$8,'QoE PF Adj. P&L Aug-26'!$D$8:$AI$8,0))*1000 -> 2600 | Q63: =+INDEX('QoE PF Adj. P&L Aug-26'!$D$11:$AI$108,MATCH($C63,'QoE PF Adj. P&L Aug-26'!$C$11:$C$108,0),MATCH(Q$8,'QoE PF Adj. P&L Aug-26'!$D$8:$AI$8,0))*1000 -> 2700 | ... AO63: =+INDEX('QoE PF Adj. P&L Aug-26'!$D$11:$AI$108,MATCH($C63,'QoE PF Adj. P&L Aug-26'!$C$11:$C$108,0),MATCH(AO$8,'QoE PF Adj. P&L Aug-26'!$D$8:$AI$8,0))*1000 -> 3000 | AP63: =+SUMIFS('Sep - Nov P&L'!I:I,'Sep - Nov P&L'!$D:$D,$C63) -> 0 | AQ63: =+SUMIFS('Sep - Nov P&L'!J:J,'Sep - Nov P&L'!$D:$D,$C63) -> 0 | AR63: =+SUMIFS('Sep - Nov P&L'!K:K,'Sep - Nov P&L'!$D:$D,$C63) -> 0 | AS63: =+AS171 -> 2266.6667 | AT63: =+AT171 -> 2274.6 | AU63: =+AU171 -> 2282.5611 | AV63: =+AV171 -> 2290.5501 | AW63: =+AW171 -> 2298.567 | AX63: =+AX171 -> 2306.612 | AY63: =+AY171 -> 2314.6851 | AZ63: =+AZ171 -> 2322.7865 | ... BQ63: =+BQ171 -> 2464.9306
C64: Liability Insurance | D64: =+SUMIFS($J64:$BQ64,$J$7:$BQ$7,D$8) -> 25900 | E64: =+SUMIFS($J64:$BQ64,$J$7:$BQ$7,E$8) -> 27100 | F64: =+SUMIFS($J64:$BQ64,$J$7:$BQ$7,F$8) -> 20575 | G64: =+SUMIFS($J64:$BQ64,$J$7:$BQ$7,G$8) -> 21790.848 | H64: =+SUMIFS($J64:$BQ64,$J$7:$BQ$7,H$8) -> 22723.889 | J64: =+INDEX('QoE PF Adj. P&L Aug-26'!$D$11:$AI$108,MATCH($C64,'QoE PF Adj. P&L Aug-26'!$C$11:$C$108,0),MATCH(J$8,'QoE PF Adj. P&L Aug-26'!$D$8:$AI$8,0))*1000 -> 2000 | K64: =+INDEX('QoE PF Adj. P&L Aug-26'!$D$11:$AI$108,MATCH($C64,'QoE PF Adj. P&L Aug-26'!$C$11:$C$108,0),MATCH(K$8,'QoE PF Adj. P&L Aug-26'!$D$8:$AI$8,0))*1000 -> 2000 | L64: =+INDEX('QoE PF Adj. P&L Aug-26'!$D$11:$AI$108,MATCH($C64,'QoE PF Adj. P&L Aug-26'!$C$11:$C$108,0),MATCH(L$8,'QoE PF Adj. P&L Aug-26'!$D$8:$AI$8,0))*1000 -> 2300 | M64: =+INDEX('QoE PF Adj. P&L Aug-26'!$D$11:$AI$108,MATCH($C64,'QoE PF Adj. P&L Aug-26'!$C$11:$C$108,0),MATCH(M$8,'QoE PF Adj. P&L Aug-26'!$D$8:$AI$8,0))*1000 -> 2100 | N64: =+INDEX('QoE PF Adj. P&L Aug-26'!$D$11:$AI$108,MATCH($C64,'QoE PF Adj. P&L Aug-26'!$C$11:$C$108,0),MATCH(N$8,'QoE PF Adj. P&L Aug-26'!$D$8:$AI$8,0))*1000 -> 2100 | O64: =+INDEX('QoE PF Adj. P&L Aug-26'!$D$11:$AI$108,MATCH($C64,'QoE PF Adj. P&L Aug-26'!$C$11:$C$108,0),MATCH(O$8,'QoE PF Adj. P&L Aug-26'!$D$8:$AI$8,0))*1000 -> 2200 | P64: =+INDEX('QoE PF Adj. P&L Aug-26'!$D$11:$AI$108,MATCH($C64,'QoE PF Adj. P&L Aug-26'!$C$11:$C$108,0),MATCH(P$8,'QoE PF Adj. P&L Aug-26'!$D$8:$AI$8,0))*1000 -> 2300 | Q64: =+INDEX('QoE PF Adj. P&L Aug-26'!$D$11:$AI$108,MATCH($C64,'QoE PF Adj. P&L Aug-26'!$C$11:$C$108,0),MATCH(Q$8,'QoE PF Adj. P&L Aug-26'!$D$8:$AI$8,0))*1000 -> 2200 | ... AO64: =+INDEX('QoE PF Adj. P&L Aug-26'!$D$11:$AI$108,MATCH($C64,'QoE PF Adj. P&L Aug-26'!$C$11:$C$108,0),MATCH(AO$8,'QoE PF Adj. P&L Aug-26'!$D$8:$AI$8,0))*1000 -> 2600 | AP64: =+SUMIFS('Sep - Nov P&L'!I:I,'Sep - Nov P&L'!$D:$D,$C64) -> 0 | AQ64: =+SUMIFS('Sep - Nov P&L'!J:J,'Sep - Nov P&L'!$D:$D,$C64) -> 0 | AR64: =+SUMIFS('Sep - Nov P&L'!K:K,'Sep - Nov P&L'!$D:$D,$C64) -> 0 | AS64: =+AS172 -> 1775 | AT64: =+AT172 -> 1781.2125 | AU64: =+AU172 -> 1787.4467 | AV64: =+AV172 -> 1793.7028 | AW64: =+AW172 -> 1799.9808 | AX64: =+AX172 -> 1806.2807 | AY64: =+AY172 -> 1812.6027 | AZ64: =+AZ172 -> 1818.9468 | ... BQ64: =+BQ172 -> 1930.2582
C65: Insurance Administration Fee | D65: =+SUMIFS($J65:$BQ65,$J$7:$BQ$7,D$8) -> 6300 | E65: =+SUMIFS($J65:$BQ65,$J$7:$BQ$7,E$8) -> 7000 | F65: =+SUMIFS($J65:$BQ65,$J$7:$BQ$7,F$8) -> 5250 | G65: =+SUMIFS($J65:$BQ65,$J$7:$BQ$7,G$8) -> 5524.4405 | H65: =+SUMIFS($J65:$BQ65,$J$7:$BQ$7,H$8) -> 5760.986 | J65: =+INDEX('QoE PF Adj. P&L Aug-26'!$D$11:$AI$108,MATCH($C65,'QoE PF Adj. P&L Aug-26'!$C$11:$C$108,0),MATCH(J$8,'QoE PF Adj. P&L Aug-26'!$D$8:$AI$8,0))*1000 -> 500 | K65: =+INDEX('QoE PF Adj. P&L Aug-26'!$D$11:$AI$108,MATCH($C65,'QoE PF Adj. P&L Aug-26'!$C$11:$C$108,0),MATCH(K$8,'QoE PF Adj. P&L Aug-26'!$D$8:$AI$8,0))*1000 -> 600 | L65: =+INDEX('QoE PF Adj. P&L Aug-26'!$D$11:$AI$108,MATCH($C65,'QoE PF Adj. P&L Aug-26'!$C$11:$C$108,0),MATCH(L$8,'QoE PF Adj. P&L Aug-26'!$D$8:$AI$8,0))*1000 -> 500 | M65: =+INDEX('QoE PF Adj. P&L Aug-26'!$D$11:$AI$108,MATCH($C65,'QoE PF Adj. P&L Aug-26'!$C$11:$C$108,0),MATCH(M$8,'QoE PF Adj. P&L Aug-26'!$D$8:$AI$8,0))*1000 -> 500 | N65: =+INDEX('QoE PF Adj. P&L Aug-26'!$D$11:$AI$108,MATCH($C65,'QoE PF Adj. P&L Aug-26'!$C$11:$C$108,0),MATCH(N$8,'QoE PF Adj. P&L Aug-26'!$D$8:$AI$8,0))*1000 -> 500 | O65: =+INDEX('QoE PF Adj. P&L Aug-26'!$D$11:$AI$108,MATCH($C65,'QoE PF Adj. P&L Aug-26'!$C$11:$C$108,0),MATCH(O$8,'QoE PF Adj. P&L Aug-26'!$D$8:$AI$8,0))*1000 -> 500 | P65: =+INDEX('QoE PF Adj. P&L Aug-26'!$D$11:$AI$108,MATCH($C65,'QoE PF Adj. P&L Aug-26'!$C$11:$C$108,0),MATCH(P$8,'QoE PF Adj. P&L Aug-26'!$D$8:$AI$8,0))*1000 -> 600 | Q65: =+INDEX('QoE PF Adj. P&L Aug-26'!$D$11:$AI$108,MATCH($C65,'QoE PF Adj. P&L Aug-26'!$C$11:$C$108,0),MATCH(Q$8,'QoE PF Adj. P&L Aug-26'!$D$8:$AI$8,0))*1000 -> 500 | ... AO65: =+INDEX('QoE PF Adj. P&L Aug-26'!$D$11:$AI$108,MATCH($C65,'QoE PF Adj. P&L Aug-26'!$C$11:$C$108,0),MATCH(AO$8,'QoE PF Adj. P&L Aug-26'!$D$8:$AI$8,0))*1000 -> 600 | AP65: =+SUMIFS('Sep - Nov P&L'!I:I,'Sep - Nov P&L'!$D:$D,$C65) -> 0 | AQ65: =+SUMIFS('Sep - Nov P&L'!J:J,'Sep - Nov P&L'!$D:$D,$C65) -> 0 | AR65: =+SUMIFS('Sep - Nov P&L'!K:K,'Sep - Nov P&L'!$D:$D,$C65) -> 0 | AS65: =+AS173 -> 450 | AT65: =+AT173 -> 451.575 | AU65: =+AU173 -> 453.15551 | AV65: =+AV173 -> 454.74156 | AW65: =+AW173 -> 456.33315 | AX65: =+AX173 -> 457.93032 | AY65: =+AY173 -> 459.53307 | AZ65: =+AZ173 -> 461.14144 | ... BQ65: =+BQ173 -> 489.36123
C66: Total Insurance | D66: =+SUMIFS($J66:$BQ66,$J$7:$BQ$7,D$8) -> 210200 | E66: =+SUMIFS($J66:$BQ66,$J$7:$BQ$7,E$8) -> 223500 | F66: =+SUMIFS($J66:$BQ66,$J$7:$BQ$7,F$8) -> 241200.64 | G66: =+SUMIFS($J66:$BQ66,$J$7:$BQ$7,G$8) -> 247308.77 | H66: =+SUMIFS($J66:$BQ66,$J$7:$BQ$7,H$8) -> 324669.84 | J66: =SUM(J62:J65) -> 17600 | K66: =SUM(K62:K65) -> 17500 | L66: =SUM(L62:L65) -> 16800 | M66: =SUM(M62:M65) -> 18100 | N66: =SUM(N62:N65) -> 16600 | O66: =SUM(O62:O65) -> 17800 | P66: =SUM(P62:P65) -> 17400 | Q66: =SUM(Q62:Q65) -> 17000 | ... BQ66: =SUM(BQ62:BQ65) -> 28884.55
C68: General & Administrative
C69: Advertising & Marketing | D69: =+SUMIFS($J69:$BQ69,$J$7:$BQ$7,D$8) -> 64100 | E69: =+SUMIFS($J69:$BQ69,$J$7:$BQ$7,E$8) -> 69300 | F69: =+SUMIFS($J69:$BQ69,$J$7:$BQ$7,F$8) -> 76055.193 | G69: =+SUMIFS($J69:$BQ69,$J$7:$BQ$7,G$8) -> 77677.592 | H69: =+SUMIFS($J69:$BQ69,$J$7:$BQ$7,H$8) -> 81003.592 | J69: =+INDEX('QoE PF Adj. P&L Aug-26'!$D$11:$AI$108,MATCH($C69,'QoE PF Adj. P&L Aug-26'!$C$11:$C$108,0),MATCH(J$8,'QoE PF Adj. P&L Aug-26'!$D$8:$AI$8,0))*1000 -> 4900 | K69: =+INDEX('QoE PF Adj. P&L Aug-26'!$D$11:$AI$108,MATCH($C69,'QoE PF Adj. P&L Aug-26'!$C$11:$C$108,0),MATCH(K$8,'QoE PF Adj. P&L Aug-26'!$D$8:$AI$8,0))*1000 -> 5200 | L69: =+INDEX('QoE PF Adj. P&L Aug-26'!$D$11:$AI$108,MATCH($C69,'QoE PF Adj. P&L Aug-26'!$C$11:$C$108,0),MATCH(L$8,'QoE PF Adj. P&L Aug-26'!$D$8:$AI$8,0))*1000 -> 5100 | M69: =+INDEX('QoE PF Adj. P&L Aug-26'!$D$11:$AI$108,MATCH($C69,'QoE PF Adj. P&L Aug-26'!$C$11:$C$108,0),MATCH(M$8,'QoE PF Adj. P&L Aug-26'!$D$8:$AI$8,0))*1000 -> 5200 | N69: =+INDEX('QoE PF Adj. P&L Aug-26'!$D$11:$AI$108,MATCH($C69,'QoE PF Adj. P&L Aug-26'!$C$11:$C$108,0),MATCH(N$8,'QoE PF Adj. P&L Aug-26'!$D$8:$AI$8,0))*1000 -> 5200 | O69: =+INDEX('QoE PF Adj. P&L Aug-26'!$D$11:$AI$108,MATCH($C69,'QoE PF Adj. P&L Aug-26'!$C$11:$C$108,0),MATCH(O$8,'QoE PF Adj. P&L Aug-26'!$D$8:$AI$8,0))*1000 -> 5700 | P69: =+INDEX('QoE PF Adj. P&L Aug-26'!$D$11:$AI$108,MATCH($C69,'QoE PF Adj. P&L Aug-26'!$C$11:$C$108,0),MATCH(P$8,'QoE PF Adj. P&L Aug-26'!$D$8:$AI$8,0))*1000 -> 5600 | Q69: =+INDEX('QoE PF Adj. P&L Aug-26'!$D$11:$AI$108,MATCH($C69,'QoE PF Adj. P&L Aug-26'!$C$11:$C$108,0),MATCH(Q$8,'QoE PF Adj. P&L Aug-26'!$D$8:$AI$8,0))*1000 -> 5700 | ... AO69: =+INDEX('QoE PF Adj. P&L Aug-26'!$D$11:$AI$108,MATCH($C69,'QoE PF Adj. P&L Aug-26'!$C$11:$C$108,0),MATCH(AO$8,'QoE PF Adj. P&L Aug-26'!$D$8:$AI$8,0))*1000 -> 6100 | AP69: =+SUMIFS('Sep - Nov P&L'!I:I,'Sep - Nov P&L'!$D:$D,$C69) -> 7295.68 | AQ69: =+SUMIFS('Sep - Nov P&L'!J:J,'Sep - Nov P&L'!$D:$D,$C69) -> 7411.76 | AR69: =+SUMIFS('Sep - Nov P&L'!K:K,'Sep - Nov P&L'!$D:$D,$C69) -> 7220.43 | AS69: =+AS177 -> 6327.3225 | AT69: =+AT177 -> 6349.4681 | AU69: =+AU177 -> 6371.6913 | AV69: =+AV177 -> 6393.9922 | AW69: =+AW177 -> 6416.3712 | AX69: =+AX177 -> 6438.8285 | AY69: =+AY177 -> 6461.3644 | AZ69: =+AZ177 -> 6483.9791 | ... BQ69: =+BQ177 -> 6880.7696
B70: % rev | C70: Bad Debt Expense | D70: =+SUMIFS($J70:$BQ70,$J$7:$BQ$7,D$8) -> 150500 | E70: =+SUMIFS($J70:$BQ70,$J$7:$BQ$7,E$8) -> 166500 | F70: =+SUMIFS($J70:$BQ70,$J$7:$BQ$7,F$8) -> 130596.2 | G70: =+SUMIFS($J70:$BQ70,$J$7:$BQ$7,G$8) -> 194875.91 | H70: =+SUMIFS($J70:$BQ70,$J$7:$BQ$7,H$8) -> 227340.5 | J70: =+INDEX('QoE PF Adj. P&L Aug-26'!$D$11:$AI$108,MATCH($C70,'QoE PF Adj. P&L Aug-26'!$C$11:$C$108,0),MATCH(J$8,'QoE PF Adj. P&L Aug-26'!$D$8:$AI$8,0))*1000 -> 12200 | K70: =+INDEX('QoE PF Adj. P&L Aug-26'!$D$11:$AI$108,MATCH($C70,'QoE PF Adj. P&L Aug-26'!$C$11:$C$108,0),MATCH(K$8,'QoE PF Adj. P&L Aug-26'!$D$8:$AI$8,0))*1000 -> 11700 | L70: =+INDEX('QoE PF Adj. P&L Aug-26'!$D$11:$AI$108,MATCH($C70,'QoE PF Adj. P&L Aug-26'!$C$11:$C$108,0),MATCH(L$8,'QoE PF Adj. P&L Aug-26'!$D$8:$AI$8,0))*1000 -> 12600 | M70: =+INDEX('QoE PF Adj. P&L Aug-26'!$D$11:$AI$108,MATCH($C70,'QoE PF Adj. P&L Aug-26'!$C$11:$C$108,0),MATCH(M$8,'QoE PF Adj. P&L Aug-26'!$D$8:$AI$8,0))*1000 -> 11700 | N70: =+INDEX('QoE PF Adj. P&L Aug-26'!$D$11:$AI$108,MATCH($C70,'QoE PF Adj. P&L Aug-26'!$C$11:$C$108,0),MATCH(N$8,'QoE PF Adj. P&L Aug-26'!$D$8:$AI$8,0))*1000 -> 13300 | O70: =+INDEX('QoE PF Adj. P&L Aug-26'!$D$11:$AI$108,MATCH($C70,'QoE PF Adj. P&L Aug-26'!$C$11:$C$108,0),MATCH(O$8,'QoE PF Adj. P&L Aug-26'!$D$8:$AI$8,0))*1000 -> 11600 | P70: =+INDEX('QoE PF Adj. P&L Aug-26'!$D$11:$AI$108,MATCH($C70,'QoE PF Adj. P&L Aug-26'!$C$11:$C$108,0),MATCH(P$8,'QoE PF Adj. P&L Aug-26'!$D$8:$AI$8,0))*1000 -> 13500 | Q70: =+INDEX('QoE PF Adj. P&L Aug-26'!$D$11:$AI$108,MATCH($C70,'QoE PF Adj. P&L Aug-26'!$C$11:$C$108,0),MATCH(Q$8,'QoE PF Adj. P&L Aug-26'!$D$8:$AI$8,0))*1000 -> 12700 | ... AO70: =+INDEX('QoE PF Adj. P&L Aug-26'!$D$11:$AI$108,MATCH($C70,'QoE PF Adj. P&L Aug-26'!$C$11:$C$108,0),MATCH(AO$8,'QoE PF Adj. P&L Aug-26'!$D$8:$AI$8,0))*1000 -> 14300 | AP70: =+SUMIFS('Sep - Nov P&L'!I:I,'Sep - Nov P&L'!$D:$D,$C70) -> 0 | AQ70: =+SUMIFS('Sep - Nov P&L'!J:J,'Sep - Nov P&L'!$D:$D,$C70) -> 0 | AR70: =+SUMIFS('Sep - Nov P&L'!K:K,'Sep - Nov P&L'!$D:$D,$C70) -> 0 | AS70: =+AS$10*AS178 -> 15496.198 | AT70: =+AT$10*AT178 -> 14148.219 | AU70: =+AU$10*AU178 -> 13474.23 | AV70: =+AV$10*AV178 -> 15917.926 | AW70: =+AW$10*AW178 -> 16227.046 | AX70: =+AX$10*AX178 -> 15097.755 | AY70: =+AY$10*AY178 -> 16136.731 | AZ70: =+AZ$10*AZ178 -> 16456.502 | ... BQ70: =+BQ$10*BQ178 -> 18756.539
B71: % rev | C71: Billing & Collection Fees | D71: =+SUMIFS($J71:$BQ71,$J$7:$BQ$7,D$8) -> 448300 | E71: =+SUMIFS($J71:$BQ71,$J$7:$BQ$7,E$8) -> 476000 | F71: =+SUMIFS($J71:$BQ71,$J$7:$BQ$7,F$8) -> 581873.31 | G71: =+SUMIFS($J71:$BQ71,$J$7:$BQ$7,G$8) -> 578131.86 | H71: =+SUMIFS($J71:$BQ71,$J$7:$BQ$7,H$8) -> 674443.48 | J71: =+INDEX('QoE PF Adj. P&L Aug-26'!$D$11:$AI$108,MATCH($C71,'QoE PF Adj. P&L Aug-26'!$C$11:$C$108,0),MATCH(J$8,'QoE PF Adj. P&L Aug-26'!$D$8:$AI$8,0))*1000 -> 38800 | K71: =+INDEX('QoE PF Adj. P&L Aug-26'!$D$11:$AI$108,MATCH($C71,'QoE PF Adj. P&L Aug-26'!$C$11:$C$108,0),MATCH(K$8,'QoE PF Adj. P&L Aug-26'!$D$8:$AI$8,0))*1000 -> 34700 | L71: =+INDEX('QoE PF Adj. P&L Aug-26'!$D$11:$AI$108,MATCH($C71,'QoE PF Adj. P&L Aug-26'!$C$11:$C$108,0),MATCH(L$8,'QoE PF Adj. P&L Aug-26'!$D$8:$AI$8,0))*1000 -> 38700 | M71: =+INDEX('QoE PF Adj. P&L Aug-26'!$D$11:$AI$108,MATCH($C71,'QoE PF Adj. P&L Aug-26'!$C$11:$C$108,0),MATCH(M$8,'QoE PF Adj. P&L Aug-26'!$D$8:$AI$8,0))*1000 -> 36700 | N71: =+INDEX('QoE PF Adj. P&L Aug-26'!$D$11:$AI$108,MATCH($C71,'QoE PF Adj. P&L Aug-26'!$C$11:$C$108,0),MATCH(N$8,'QoE PF Adj. P&L Aug-26'!$D$8:$AI$8,0))*1000 -> 38500 | O71: =+INDEX('QoE PF Adj. P&L Aug-26'!$D$11:$AI$108,MATCH($C71,'QoE PF Adj. P&L Aug-26'!$C$11:$C$108,0),MATCH(O$8,'QoE PF Adj. P&L Aug-26'!$D$8:$AI$8,0))*1000 -> 34900 | P71: =+INDEX('QoE PF Adj. P&L Aug-26'!$D$11:$AI$108,MATCH($C71,'QoE PF Adj. P&L Aug-26'!$C$11:$C$108,0),MATCH(P$8,'QoE PF Adj. P&L Aug-26'!$D$8:$AI$8,0))*1000 -> 39000 | Q71: =+INDEX('QoE PF Adj. P&L Aug-26'!$D$11:$AI$108,MATCH($C71,'QoE PF Adj. P&L Aug-26'!$C$11:$C$108,0),MATCH(Q$8,'QoE PF Adj. P&L Aug-26'!$D$8:$AI$8,0))*1000 -> 37600 | ... AO71: =+INDEX('QoE PF Adj. P&L Aug-26'!$D$11:$AI$108,MATCH($C71,'QoE PF Adj. P&L Aug-26'!$C$11:$C$108,0),MATCH(AO$8,'QoE PF Adj. P&L Aug-26'!$D$8:$AI$8,0))*1000 -> 41200 | AP71: =+SUMIFS('Sep - Nov P&L'!I:I,'Sep - Nov P&L'!$D:$D,$C71) -> 65891.98 | AQ71: =+SUMIFS('Sep - Nov P&L'!J:J,'Sep - Nov P&L'!$D:$D,$C71) -> 67735.91 | AR71: =+SUMIFS('Sep - Nov P&L'!K:K,'Sep - Nov P&L'!$D:$D,$C71) -> 60673.37 | AS71: =+AS$10*AS179 -> 45972.054 | AT71: =+AT$10*AT179 -> 41973.05 | AU71: =+AU$10*AU179 -> 39973.548 | AV71: =+AV$10*AV179 -> 47223.181 | AW71: =+AW$10*AW179 -> 48140.237 | AX71: =+AX$10*AX179 -> 44790.007 | AY71: =+AY$10*AY179 -> 47872.303 | AZ71: =+AZ$10*AZ179 -> 48820.956 | ... BQ71: =+BQ$10*BQ179 -> 55644.399
C72: Contract Services | D72: =+SUMIFS($J72:$BQ72,$J$7:$BQ$7,D$8) -> 65500 | E72: =+SUMIFS($J72:$BQ72,$J$7:$BQ$7,E$8) -> 69200 | F72: =+SUMIFS($J72:$BQ72,$J$7:$BQ$7,F$8) -> 54250 | G72: =+SUMIFS($J72:$BQ72,$J$7:$BQ$7,G$8) -> 57085.885 | H72: =+SUMIFS($J72:$BQ72,$J$7:$BQ$7,H$8) -> 59530.189 | J72: =+INDEX('QoE PF Adj. P&L Aug-26'!$D$11:$AI$108,MATCH($C72,'QoE PF Adj. P&L Aug-26'!$C$11:$C$108,0),MATCH(J$8,'QoE PF Adj. P&L Aug-26'!$D$8:$AI$8,0))*1000 -> 5300 | K72: =+INDEX('QoE PF Adj. P&L Aug-26'!$D$11:$AI$108,MATCH($C72,'QoE PF Adj. P&L Aug-26'!$C$11:$C$108,0),MATCH(K$8,'QoE PF Adj. P&L Aug-26'!$D$8:$AI$8,0))*1000 -> 5000 | L72: =+INDEX('QoE PF Adj. P&L Aug-26'!$D$11:$AI$108,MATCH($C72,'QoE PF Adj. P&L Aug-26'!$C$11:$C$108,0),MATCH(L$8,'QoE PF Adj. P&L Aug-26'!$D$8:$AI$8,0))*1000 -> 5100 | M72: =+INDEX('QoE PF Adj. P&L Aug-26'!$D$11:$AI$108,MATCH($C72,'QoE PF Adj. P&L Aug-26'!$C$11:$C$108,0),MATCH(M$8,'QoE PF Adj. P&L Aug-26'!$D$8:$AI$8,0))*1000 -> 5300 | N72: =+INDEX('QoE PF Adj. P&L Aug-26'!$D$11:$AI$108,MATCH($C72,'QoE PF Adj. P&L Aug-26'!$C$11:$C$108,0),MATCH(N$8,'QoE PF Adj. P&L Aug-26'!$D$8:$AI$8,0))*1000 -> 5600 | O72: =+INDEX('QoE PF Adj. P&L Aug-26'!$D$11:$AI$108,MATCH($C72,'QoE PF Adj. P&L Aug-26'!$C$11:$C$108,0),MATCH(O$8,'QoE PF Adj. P&L Aug-26'!$D$8:$AI$8,0))*1000 -> 5600 | P72: =+INDEX('QoE PF Adj. P&L Aug-26'!$D$11:$AI$108,MATCH($C72,'QoE PF Adj. P&L Aug-26'!$C$11:$C$108,0),MATCH(P$8,'QoE PF Adj. P&L Aug-26'!$D$8:$AI$8,0))*1000 -> 5600 | Q72: =+INDEX('QoE PF Adj. P&L Aug-26'!$D$11:$AI$108,MATCH($C72,'QoE PF Adj. P&L Aug-26'!$C$11:$C$108,0),MATCH(Q$8,'QoE PF Adj. P&L Aug-26'!$D$8:$AI$8,0))*1000 -> 5700 | ... AO72: =+INDEX('QoE PF Adj. P&L Aug-26'!$D$11:$AI$108,MATCH($C72,'QoE PF Adj. P&L Aug-26'!$C$11:$C$108,0),MATCH(AO$8,'QoE PF Adj. P&L Aug-26'!$D$8:$AI$8,0))*1000 -> 6700 | AP72: =+SUMIFS('Sep - Nov P&L'!I:I,'Sep - Nov P&L'!$D:$D,$C72) -> 0 | AQ72: =+SUMIFS('Sep - Nov P&L'!J:J,'Sep - Nov P&L'!$D:$D,$C72) -> 0 | AR72: =+SUMIFS('Sep - Nov P&L'!K:K,'Sep - Nov P&L'!$D:$D,$C72) -> 0 | AS72: =+AS180 -> 4650 | AT72: =+AT180 -> 4666.275 | AU72: =+AU180 -> 4682.607 | AV72: =+AV180 -> 4698.9961 | AW72: =+AW180 -> 4715.4426 | AX72: =+AX180 -> 4731.9466 | AY72: =+AY180 -> 4748.5084 | AZ72: =+AZ180 -> 4765.1282 | ... BQ72: =+BQ180 -> 5056.7327
C73: Dues & Subscriptions | D73: =+SUMIFS($J73:$BQ73,$J$7:$BQ$7,D$8) -> 19800 | E73: =+SUMIFS($J73:$BQ73,$J$7:$BQ$7,E$8) -> 20700 | F73: =+SUMIFS($J73:$BQ73,$J$7:$BQ$7,F$8) -> 21995.653 | G73: =+SUMIFS($J73:$BQ73,$J$7:$BQ$7,G$8) -> 22376.961 | H73: =+SUMIFS($J73:$BQ73,$J$7:$BQ$7,H$8) -> 23335.098 | J73: =+INDEX('QoE PF Adj. P&L Aug-26'!$D$11:$AI$108,MATCH($C73,'QoE PF Adj. P&L Aug-26'!$C$11:$C$108,0),MATCH(J$8,'QoE PF Adj. P&L Aug-26'!$D$8:$AI$8,0))*1000 -> 1500 | K73: =+INDEX('QoE PF Adj. P&L Aug-26'!$D$11:$AI$108,MATCH($C73,'QoE PF Adj. P&L Aug-26'!$C$11:$C$108,0),MATCH(K$8,'QoE PF Adj. P&L Aug-26'!$D$8:$AI$8,0))*1000 -> 1700 | L73: =+INDEX('QoE PF Adj. P&L Aug-26'!$D$11:$AI$108,MATCH($C73,'QoE PF Adj. P&L Aug-26'!$C$11:$C$108,0),MATCH(L$8,'QoE PF Adj. P&L Aug-26'!$D$8:$AI$8,0))*1000 -> 1700 | M73: =+INDEX('QoE PF Adj. P&L Aug-26'!$D$11:$AI$108,MATCH($C73,'QoE PF Adj. P&L Aug-26'!$C$11:$C$108,0),MATCH(M$8,'QoE PF Adj. P&L Aug-26'!$D$8:$AI$8,0))*1000 -> 1600 | N73: =+INDEX('QoE PF Adj. P&L Aug-26'!$D$11:$AI$108,MATCH($C73,'QoE PF Adj. P&L Aug-26'!$C$11:$C$108,0),MATCH(N$8,'QoE PF Adj. P&L Aug-26'!$D$8:$AI$8,0))*1000 -> 1700 | O73: =+INDEX('QoE PF Adj. P&L Aug-26'!$D$11:$AI$108,MATCH($C73,'QoE PF Adj. P&L Aug-26'!$C$11:$C$108,0),MATCH(O$8,'QoE PF Adj. P&L Aug-26'!$D$8:$AI$8,0))*1000 -> 1500 | P73: =+INDEX('QoE PF Adj. P&L Aug-26'!$D$11:$AI$108,MATCH($C73,'QoE PF Adj. P&L Aug-26'!$C$11:$C$108,0),MATCH(P$8,'QoE PF Adj. P&L Aug-26'!$D$8:$AI$8,0))*1000 -> 1700 | Q73: =+INDEX('QoE PF Adj. P&L Aug-26'!$D$11:$AI$108,MATCH($C73,'QoE PF Adj. P&L Aug-26'!$C$11:$C$108,0),MATCH(Q$8,'QoE PF Adj. P&L Aug-26'!$D$8:$AI$8,0))*1000 -> 1700 | ... AO73: =+INDEX('QoE PF Adj. P&L Aug-26'!$D$11:$AI$108,MATCH($C73,'QoE PF Adj. P&L Aug-26'!$C$11:$C$108,0),MATCH(AO$8,'QoE PF Adj. P&L Aug-26'!$D$8:$AI$8,0))*1000 -> 1800 | AP73: =+SUMIFS('Sep - Nov P&L'!I:I,'Sep - Nov P&L'!$D:$D,$C73) -> 1934.62 | AQ73: =+SUMIFS('Sep - Nov P&L'!J:J,'Sep - Nov P&L'!$D:$D,$C73) -> 1819.25 | AR73: =+SUMIFS('Sep - Nov P&L'!K:K,'Sep - Nov P&L'!$D:$D,$C73) -> 1919.04 | AS73: =+AS181 -> 1822.7425 | AT73: =+AT181 -> 1829.1221 | AU73: =+AU181 -> 1835.524 | AV73: =+AV181 -> 1841.9484 | AW73: =+AW181 -> 1848.3952 | AX73: =+AX181 -> 1854.8646 | AY73: =+AY181 -> 1861.3566 | AZ73: =+AZ181 -> 1867.8713 | ... BQ73: =+BQ181 -> 1982.1767
C74: Equipment Rentals | D74: =+SUMIFS($J74:$BQ74,$J$7:$BQ$7,D$8) -> 78400 | E74: =+SUMIFS($J74:$BQ74,$J$7:$BQ$7,E$8) -> 84300 | F74: =+SUMIFS($J74:$BQ74,$J$7:$BQ$7,F$8) -> 88241.68 | G74: =+SUMIFS($J74:$BQ74,$J$7:$BQ$7,G$8) -> 90224.67 | H74: =+SUMIFS($J74:$BQ74,$J$7:$BQ$7,H$8) -> 94087.911 | J74: =+INDEX('QoE PF Adj. P&L Aug-26'!$D$11:$AI$108,MATCH($C74,'QoE PF Adj. P&L Aug-26'!$C$11:$C$108,0),MATCH(J$8,'QoE PF Adj. P&L Aug-26'!$D$8:$AI$8,0))*1000 -> 6700 | K74: =+INDEX('QoE PF Adj. P&L Aug-26'!$D$11:$AI$108,MATCH($C74,'QoE PF Adj. P&L Aug-26'!$C$11:$C$108,0),MATCH(K$8,'QoE PF Adj. P&L Aug-26'!$D$8:$AI$8,0))*1000 -> 6500 | L74: =+INDEX('QoE PF Adj. P&L Aug-26'!$D$11:$AI$108,MATCH($C74,'QoE PF Adj. P&L Aug-26'!$C$11:$C$108,0),MATCH(L$8,'QoE PF Adj. P&L Aug-26'!$D$8:$AI$8,0))*1000 -> 6500 | M74: =+INDEX('QoE PF Adj. P&L Aug-26'!$D$11:$AI$108,MATCH($C74,'QoE PF Adj. P&L Aug-26'!$C$11:$C$108,0),MATCH(M$8,'QoE PF Adj. P&L Aug-26'!$D$8:$AI$8,0))*1000 -> 6800 | N74: =+INDEX('QoE PF Adj. P&L Aug-26'!$D$11:$AI$108,MATCH($C74,'QoE PF Adj. P&L Aug-26'!$C$11:$C$108,0),MATCH(N$8,'QoE PF Adj. P&L Aug-26'!$D$8:$AI$8,0))*1000 -> 6200 | O74: =+INDEX('QoE PF Adj. P&L Aug-26'!$D$11:$AI$108,MATCH($C74,'QoE PF Adj. P&L Aug-26'!$C$11:$C$108,0),MATCH(O$8,'QoE PF Adj. P&L Aug-26'!$D$8:$AI$8,0))*1000 -> 6000 | P74: =+INDEX('QoE PF Adj. P&L Aug-26'!$D$11:$AI$108,MATCH($C74,'QoE PF Adj. P&L Aug-26'!$C$11:$C$108,0),MATCH(P$8,'QoE PF Adj. P&L Aug-26'!$D$8:$AI$8,0))*1000 -> 6300 | Q74: =+INDEX('QoE PF Adj. P&L Aug-26'!$D$11:$AI$108,MATCH($C74,'QoE PF Adj. P&L Aug-26'!$C$11:$C$108,0),MATCH(Q$8,'QoE PF Adj. P&L Aug-26'!$D$8:$AI$8,0))*1000 -> 6800 | ... AO74: =+INDEX('QoE PF Adj. P&L Aug-26'!$D$11:$AI$108,MATCH($C74,'QoE PF Adj. P&L Aug-26'!$C$11:$C$108,0),MATCH(AO$8,'QoE PF Adj. P&L Aug-26'!$D$8:$AI$8,0))*1000 -> 8000 | AP74: =+SUMIFS('Sep - Nov P&L'!I:I,'Sep - Nov P&L'!$D:$D,$C74) -> 7426.4 | AQ74: =+SUMIFS('Sep - Nov P&L'!J:J,'Sep - Nov P&L'!$D:$D,$C74) -> 7102.3 | AR74: =+SUMIFS('Sep - Nov P&L'!K:K,'Sep - Nov P&L'!$D:$D,$C74) -> 7863.62 | AS74: =+AS182 -> 7349.36 | AT74: =+AT182 -> 7375.0828 | AU74: =+AU182 -> 7400.8955 | AV74: =+AV182 -> 7426.7987 | AW74: =+AW182 -> 7452.7925 | AX74: =+AX182 -> 7478.8773 | AY74: =+AY182 -> 7505.0533 | AZ74: =+AZ182 -> 7531.321 | ... BQ74: =+BQ182 -> 7992.2041
B75: % rev | C75: Finance, Bank, & Collection Charges | D75: =+SUMIFS($J75:$BQ75,$J$7:$BQ$7,D$8) -> 50700 | E75: =+SUMIFS($J75:$BQ75,$J$7:$BQ$7,E$8) -> 55400 | F75: =+SUMIFS($J75:$BQ75,$J$7:$BQ$7,F$8) -> 59958.229 | G75: =+SUMIFS($J75:$BQ75,$J$7:$BQ$7,G$8) -> 64958.636 | H75: =+SUMIFS($J75:$BQ75,$J$7:$BQ$7,H$8) -> 75780.166 | J75: =+INDEX('QoE PF Adj. P&L Aug-26'!$D$11:$AI$108,MATCH($C75,'QoE PF Adj. P&L Aug-26'!$C$11:$C$108,0),MATCH(J$8,'QoE PF Adj. P&L Aug-26'!$D$8:$AI$8,0))*1000 -> 4100 | K75: =+INDEX('QoE PF Adj. P&L Aug-26'!$D$11:$AI$108,MATCH($C75,'QoE PF Adj. P&L Aug-26'!$C$11:$C$108,0),MATCH(K$8,'QoE PF Adj. P&L Aug-26'!$D$8:$AI$8,0))*1000 -> 3800 | L75: =+INDEX('QoE PF Adj. P&L Aug-26'!$D$11:$AI$108,MATCH($C75,'QoE PF Adj. P&L Aug-26'!$C$11:$C$108,0),MATCH(L$8,'QoE PF Adj. P&L Aug-26'!$D$8:$AI$8,0))*1000 -> 4200 | M75: =+INDEX('QoE PF Adj. P&L Aug-26'!$D$11:$AI$108,MATCH($C75,'QoE PF Adj. P&L Aug-26'!$C$11:$C$108,0),MATCH(M$8,'QoE PF Adj. P&L Aug-26'!$D$8:$AI$8,0))*1000 -> 4000 | N75: =+INDEX('QoE PF Adj. P&L Aug-26'!$D$11:$AI$108,MATCH($C75,'QoE PF Adj. P&L Aug-26'!$C$11:$C$108,0),MATCH(N$8,'QoE PF Adj. P&L Aug-26'!$D$8:$AI$8,0))*1000 -> 4600 | O75: =+INDEX('QoE PF Adj. P&L Aug-26'!$D$11:$AI$108,MATCH($C75,'QoE PF Adj. P&L Aug-26'!$C$11:$C$108,0),MATCH(O$8,'QoE PF Adj. P&L Aug-26'!$D$8:$AI$8,0))*1000 -> 3800 | P75: =+INDEX('QoE PF Adj. P&L Aug-26'!$D$11:$AI$108,MATCH($C75,'QoE PF Adj. P&L Aug-26'!$C$11:$C$108,0),MATCH(P$8,'QoE PF Adj. P&L Aug-26'!$D$8:$AI$8,0))*1000 -> 4400 | Q75: =+INDEX('QoE PF Adj. P&L Aug-26'!$D$11:$AI$108,MATCH($C75,'QoE PF Adj. P&L Aug-26'!$C$11:$C$108,0),MATCH(Q$8,'QoE PF Adj. P&L Aug-26'!$D$8:$AI$8,0))*1000 -> 4400 | ... AO75: =+INDEX('QoE PF Adj. P&L Aug-26'!$D$11:$AI$108,MATCH($C75,'QoE PF Adj. P&L Aug-26'!$C$11:$C$108,0),MATCH(AO$8,'QoE PF Adj. P&L Aug-26'!$D$8:$AI$8,0))*1000 -> 5000 | AP75: =+SUMIFS('Sep - Nov P&L'!I:I,'Sep - Nov P&L'!$D:$D,$C75) -> 5448.63 | AQ75: =+SUMIFS('Sep - Nov P&L'!J:J,'Sep - Nov P&L'!$D:$D,$C75) -> 5660.23 | AR75: =+SUMIFS('Sep - Nov P&L'!K:K,'Sep - Nov P&L'!$D:$D,$C75) -> 4883.97 | AS75: =+AS$10*AS183 -> 5165.3994 | AT75: =+AT$10*AT183 -> 4716.0731 | AU75: =+AU$10*AU183 -> 4491.4099 | AV75: =+AV$10*AV183 -> 5305.9754 | AW75: =+AW$10*AW183 -> 5409.0154 | AX75: =+AX$10*AX183 -> 5032.5851 | AY75: =+AY$10*AY183 -> 5378.9104 | AZ75: =+AZ$10*AZ183 -> 5485.5006 | ... BQ75: =+BQ$10*BQ183 -> 6252.1797
C76: Information Technology Expense | D76: =+SUMIFS($J76:$BQ76,$J$7:$BQ$7,D$8) -> 194000 | E76: =+SUMIFS($J76:$BQ76,$J$7:$BQ$7,E$8) -> 203000 | F76: =+SUMIFS($J76:$BQ76,$J$7:$BQ$7,F$8) -> 237947 | G76: =+SUMIFS($J76:$BQ76,$J$7:$BQ$7,G$8) -> 241514.37 | H76: =+SUMIFS($J76:$BQ76,$J$7:$BQ$7,H$8) -> 251855.53 | J76: =+INDEX('QoE PF Adj. P&L Aug-26'!$D$11:$AI$108,MATCH($C76,'QoE PF Adj. P&L Aug-26'!$C$11:$C$108,0),MATCH(J$8,'QoE PF Adj. P&L Aug-26'!$D$8:$AI$8,0))*1000 -> 16000 | K76: =+INDEX('QoE PF Adj. P&L Aug-26'!$D$11:$AI$108,MATCH($C76,'QoE PF Adj. P&L Aug-26'!$C$11:$C$108,0),MATCH(K$8,'QoE PF Adj. P&L Aug-26'!$D$8:$AI$8,0))*1000 -> 15200 | L76: =+INDEX('QoE PF Adj. P&L Aug-26'!$D$11:$AI$108,MATCH($C76,'QoE PF Adj. P&L Aug-26'!$C$11:$C$108,0),MATCH(L$8,'QoE PF Adj. P&L Aug-26'!$D$8:$AI$8,0))*1000 -> 16000 | M76: =+INDEX('QoE PF Adj. P&L Aug-26'!$D$11:$AI$108,MATCH($C76,'QoE PF Adj. P&L Aug-26'!$C$11:$C$108,0),MATCH(M$8,'QoE PF Adj. P&L Aug-26'!$D$8:$AI$8,0))*1000 -> 16300 | N76: =+INDEX('QoE PF Adj. P&L Aug-26'!$D$11:$AI$108,MATCH($C76,'QoE PF Adj. P&L Aug-26'!$C$11:$C$108,0),MATCH(N$8,'QoE PF Adj. P&L Aug-26'!$D$8:$AI$8,0))*1000 -> 16400 | O76: =+INDEX('QoE PF Adj. P&L Aug-26'!$D$11:$AI$108,MATCH($C76,'QoE PF Adj. P&L Aug-26'!$C$11:$C$108,0),MATCH(O$8,'QoE PF Adj. P&L Aug-26'!$D$8:$AI$8,0))*1000 -> 15100 | P76: =+INDEX('QoE PF Adj. P&L Aug-26'!$D$11:$AI$108,MATCH($C76,'QoE PF Adj. P&L Aug-26'!$C$11:$C$108,0),MATCH(P$8,'QoE PF Adj. P&L Aug-26'!$D$8:$AI$8,0))*1000 -> 15100 | Q76: =+INDEX('QoE PF Adj. P&L Aug-26'!$D$11:$AI$108,MATCH($C76,'QoE PF Adj. P&L Aug-26'!$C$11:$C$108,0),MATCH(Q$8,'QoE PF Adj. P&L Aug-26'!$D$8:$AI$8,0))*1000 -> 16200 | ... AO76: =+INDEX('QoE PF Adj. P&L Aug-26'!$D$11:$AI$108,MATCH($C76,'QoE PF Adj. P&L Aug-26'!$C$11:$C$108,0),MATCH(AO$8,'QoE PF Adj. P&L Aug-26'!$D$8:$AI$8,0))*1000 -> 19200 | AP76: =+SUMIFS('Sep - Nov P&L'!I:I,'Sep - Nov P&L'!$D:$D,$C76) -> 24543.03 | AQ76: =+SUMIFS('Sep - Nov P&L'!J:J,'Sep - Nov P&L'!$D:$D,$C76) -> 22854.29 | AR76: =+SUMIFS('Sep - Nov P&L'!K:K,'Sep - Nov P&L'!$D:$D,$C76) -> 22776.83 | AS76: =+AS184 -> 19672.846 | AT76: =+AT184 -> 19741.701 | AU76: =+AU184 -> 19810.797 | AV76: =+AV184 -> 19880.135 | AW76: =+AW184 -> 19949.715 | AX76: =+AX184 -> 20019.539 | AY76: =+AY184 -> 20089.607 | AZ76: =+AZ184 -> 20159.921 | ... BQ76: =+BQ184 -> 21393.618
C77: Legal & Professional Fees | D77: =+SUMIFS($J77:$BQ77,$J$7:$BQ$7,D$8) -> 129800 | E77: =+SUMIFS($J77:$BQ77,$J$7:$BQ$7,E$8) -> 139700 | F77: =+SUMIFS($J77:$BQ77,$J$7:$BQ$7,F$8) -> 191147.98 | G77: =+SUMIFS($J77:$BQ77,$J$7:$BQ$7,G$8) -> 192220.29 | H77: =+SUMIFS($J77:$BQ77,$J$7:$BQ$7,H$8) -> 200450.78 | J77: =+INDEX('QoE PF Adj. P&L Aug-26'!$D$11:$AI$108,MATCH($C77,'QoE PF Adj. P&L Aug-26'!$C$11:$C$108,0),MATCH(J$8,'QoE PF Adj. P&L Aug-26'!$D$8:$AI$8,0))*1000 -> 10200 | K77: =+INDEX('QoE PF Adj. P&L Aug-26'!$D$11:$AI$108,MATCH($C77,'QoE PF Adj. P&L Aug-26'!$C$11:$C$108,0),MATCH(K$8,'QoE PF Adj. P&L Aug-26'!$D$8:$AI$8,0))*1000 -> 10000 | L77: =+INDEX('QoE PF Adj. P&L Aug-26'!$D$11:$AI$108,MATCH($C77,'QoE PF Adj. P&L Aug-26'!$C$11:$C$108,0),MATCH(L$8,'QoE PF Adj. P&L Aug-26'!$D$8:$AI$8,0))*1000 -> 10700 | M77: =+INDEX('QoE PF Adj. P&L Aug-26'!$D$11:$AI$108,MATCH($C77,'QoE PF Adj. P&L Aug-26'!$C$11:$C$108,0),MATCH(M$8,'QoE PF Adj. P&L Aug-26'!$D$8:$AI$8,0))*1000 -> 10900 | N77: =+INDEX('QoE PF Adj. P&L Aug-26'!$D$11:$AI$108,MATCH($C77,'QoE PF Adj. P&L Aug-26'!$C$11:$C$108,0),MATCH(N$8,'QoE PF Adj. P&L Aug-26'!$D$8:$AI$8,0))*1000 -> 11000 | O77: =+INDEX('QoE PF Adj. P&L Aug-26'!$D$11:$AI$108,MATCH($C77,'QoE PF Adj. P&L Aug-26'!$C$11:$C$108,0),MATCH(O$8,'QoE PF Adj. P&L Aug-26'!$D$8:$AI$8,0))*1000 -> 10900 | P77: =+INDEX('QoE PF Adj. P&L Aug-26'!$D$11:$AI$108,MATCH($C77,'QoE PF Adj. P&L Aug-26'!$C$11:$C$108,0),MATCH(P$8,'QoE PF Adj. P&L Aug-26'!$D$8:$AI$8,0))*1000 -> 10600 | Q77: =+INDEX('QoE PF Adj. P&L Aug-26'!$D$11:$AI$108,MATCH($C77,'QoE PF Adj. P&L Aug-26'!$C$11:$C$108,0),MATCH(Q$8,'QoE PF Adj. P&L Aug-26'!$D$8:$AI$8,0))*1000 -> 11200 | ... AO77: =+INDEX('QoE PF Adj. P&L Aug-26'!$D$11:$AI$108,MATCH($C77,'QoE PF Adj. P&L Aug-26'!$C$11:$C$108,0),MATCH(AO$8,'QoE PF Adj. P&L Aug-26'!$D$8:$AI$8,0))*1000 -> 12200 | AP77: =+SUMIFS('Sep - Nov P&L'!I:I,'Sep - Nov P&L'!$D:$D,$C77) -> 25796.95 | AQ77: =+SUMIFS('Sep - Nov P&L'!J:J,'Sep - Nov P&L'!$D:$D,$C77) -> 26927.53 | AR77: =+SUMIFS('Sep - Nov P&L'!K:K,'Sep - Nov P&L'!$D:$D,$C77) -> 26565.96 | AS77: =+AS185 -> 15657.537 | AT77: =+AT185 -> 15712.338 | AU77: =+AU185 -> 15767.331 | AV77: =+AV185 -> 15822.517 | AW77: =+AW185 -> 15877.896 | AX77: =+AX185 -> 15933.468 | AY77: =+AY185 -> 15989.235 | AZ77: =+AZ185 -> 16045.198 | ... BQ77: =+BQ185 -> 17027.092
C78: Management Fees | D78: =+SUMIFS($J78:$BQ78,$J$7:$BQ$7,D$8) -> 76700 | E78: =+SUMIFS($J78:$BQ78,$J$7:$BQ$7,E$8) -> 82100 | F78: =+SUMIFS($J78:$BQ78,$J$7:$BQ$7,F$8) -> 62275 | G78: =+SUMIFS($J78:$BQ78,$J$7:$BQ$7,G$8) -> 65986.372 | H78: =+SUMIFS($J78:$BQ78,$J$7:$BQ$7,H$8) -> 68811.777 | J78: =+INDEX('QoE PF Adj. P&L Aug-26'!$D$11:$AI$108,MATCH($C78,'QoE PF Adj. P&L Aug-26'!$C$11:$C$108,0),MATCH(J$8,'QoE PF Adj. P&L Aug-26'!$D$8:$AI$8,0))*1000 -> 6000 | K78: =+INDEX('QoE PF Adj. P&L Aug-26'!$D$11:$AI$108,MATCH($C78,'QoE PF Adj. P&L Aug-26'!$C$11:$C$108,0),MATCH(K$8,'QoE PF Adj. P&L Aug-26'!$D$8:$AI$8,0))*1000 -> 6300 | L78: =+INDEX('QoE PF Adj. P&L Aug-26'!$D$11:$AI$108,MATCH($C78,'QoE PF Adj. P&L Aug-26'!$C$11:$C$108,0),MATCH(L$8,'QoE PF Adj. P&L Aug-26'!$D$8:$AI$8,0))*1000 -> 6700 | M78: =+INDEX('QoE PF Adj. P&L Aug-26'!$D$11:$AI$108,MATCH($C78,'QoE PF Adj. P&L Aug-26'!$C$11:$C$108,0),MATCH(M$8,'QoE PF Adj. P&L Aug-26'!$D$8:$AI$8,0))*1000 -> 6000 | N78: =+INDEX('QoE PF Adj. P&L Aug-26'!$D$11:$AI$108,MATCH($C78,'QoE PF Adj. P&L Aug-26'!$C$11:$C$108,0),MATCH(N$8,'QoE PF Adj. P&L Aug-26'!$D$8:$AI$8,0))*1000 -> 6300 | O78: =+INDEX('QoE PF Adj. P&L Aug-26'!$D$11:$AI$108,MATCH($C78,'QoE PF Adj. P&L Aug-26'!$C$11:$C$108,0),MATCH(O$8,'QoE PF Adj. P&L Aug-26'!$D$8:$AI$8,0))*1000 -> 6400 | P78: =+INDEX('QoE PF Adj. P&L Aug-26'!$D$11:$AI$108,MATCH($C78,'QoE PF Adj. P&L Aug-26'!$C$11:$C$108,0),MATCH(P$8,'QoE PF Adj. P&L Aug-26'!$D$8:$AI$8,0))*1000 -> 6700 | Q78: =+INDEX('QoE PF Adj. P&L Aug-26'!$D$11:$AI$108,MATCH($C78,'QoE PF Adj. P&L Aug-26'!$C$11:$C$108,0),MATCH(Q$8,'QoE PF Adj. P&L Aug-26'!$D$8:$AI$8,0))*1000 -> 6100 | ... AO78: =+INDEX('QoE PF Adj. P&L Aug-26'!$D$11:$AI$108,MATCH($C78,'QoE PF Adj. P&L Aug-26'!$C$11:$C$108,0),MATCH(AO$8,'QoE PF Adj. P&L Aug-26'!$D$8:$AI$8,0))*1000 -> 7200 | AP78: =+SUMIFS('Sep - Nov P&L'!I:I,'Sep - Nov P&L'!$D:$D,$C78) -> 0 | AQ78: =+SUMIFS('Sep - Nov P&L'!J:J,'Sep - Nov P&L'!$D:$D,$C78) -> 0 | AR78: =+SUMIFS('Sep - Nov P&L'!K:K,'Sep - Nov P&L'!$D:$D,$C78) -> 0 | AS78: =+AS186 -> 5375 | AT78: =+AT186 -> 5393.8125 | AU78: =+AU186 -> 5412.6908 | AV78: =+AV186 -> 5431.6353 | AW78: =+AW186 -> 5450.646 | AX78: =+AX186 -> 5469.7232 | AY78: =+AY186 -> 5488.8673 | AZ78: =+AZ186 -> 5508.0783 | ... BQ78: =+BQ186 -> 5845.148
C79: Revenue Cycle Management Services | D79: =+SUMIFS($J79:$BQ79,$J$7:$BQ$7,D$8) -> 193800 | E79: =+SUMIFS($J79:$BQ79,$J$7:$BQ$7,E$8) -> 207800 | F79: =+SUMIFS($J79:$BQ79,$J$7:$BQ$7,F$8) -> 162858.33 | G79: =+SUMIFS($J79:$BQ79,$J$7:$BQ$7,G$8) -> 170132.31 | H79: =+SUMIFS($J79:$BQ79,$J$7:$BQ$7,H$8) -> 177417.03 | J79: =+INDEX('QoE PF Adj. P&L Aug-26'!$D$11:$AI$108,MATCH($C79,'QoE PF Adj. P&L Aug-26'!$C$11:$C$108,0),MATCH(J$8,'QoE PF Adj. P&L Aug-26'!$D$8:$AI$8,0))*1000 -> 15400 | K79: =+INDEX('QoE PF Adj. P&L Aug-26'!$D$11:$AI$108,MATCH($C79,'QoE PF Adj. P&L Aug-26'!$C$11:$C$108,0),MATCH(K$8,'QoE PF Adj. P&L Aug-26'!$D$8:$AI$8,0))*1000 -> 16400 | L79: =+INDEX('QoE PF Adj. P&L Aug-26'!$D$11:$AI$108,MATCH($C79,'QoE PF Adj. P&L Aug-26'!$C$11:$C$108,0),MATCH(L$8,'QoE PF Adj. P&L Aug-26'!$D$8:$AI$8,0))*1000 -> 15700 | M79: =+INDEX('QoE PF Adj. P&L Aug-26'!$D$11:$AI$108,MATCH($C79,'QoE PF Adj. P&L Aug-26'!$C$11:$C$108,0),MATCH(M$8,'QoE PF Adj. P&L Aug-26'!$D$8:$AI$8,0))*1000 -> 15100 | N79: =+INDEX('QoE PF Adj. P&L Aug-26'!$D$11:$AI$108,MATCH($C79,'QoE PF Adj. P&L Aug-26'!$C$11:$C$108,0),MATCH(N$8,'QoE PF Adj. P&L Aug-26'!$D$8:$AI$8,0))*1000 -> 16600 | O79: =+INDEX('QoE PF Adj. P&L Aug-26'!$D$11:$AI$108,MATCH($C79,'QoE PF Adj. P&L Aug-26'!$C$11:$C$108,0),MATCH(O$8,'QoE PF Adj. P&L Aug-26'!$D$8:$AI$8,0))*1000 -> 16100 | P79: =+INDEX('QoE PF Adj. P&L Aug-26'!$D$11:$AI$108,MATCH($C79,'QoE PF Adj. P&L Aug-26'!$C$11:$C$108,0),MATCH(P$8,'QoE PF Adj. P&L Aug-26'!$D$8:$AI$8,0))*1000 -> 16200 | Q79: =+INDEX('QoE PF Adj. P&L Aug-26'!$D$11:$AI$108,MATCH($C79,'QoE PF Adj. P&L Aug-26'!$C$11:$C$108,0),MATCH(Q$8,'QoE PF Adj. P&L Aug-26'!$D$8:$AI$8,0))*1000 -> 17200 | ... AO79: =+INDEX('QoE PF Adj. P&L Aug-26'!$D$11:$AI$108,MATCH($C79,'QoE PF Adj. P&L Aug-26'!$C$11:$C$108,0),MATCH(AO$8,'QoE PF Adj. P&L Aug-26'!$D$8:$AI$8,0))*1000 -> 19300 | AP79: =+SUMIFS('Sep - Nov P&L'!I:I,'Sep - Nov P&L'!$D:$D,$C79) -> 0 | AQ79: =+SUMIFS('Sep - Nov P&L'!J:J,'Sep - Nov P&L'!$D:$D,$C79) -> 0 | AR79: =+SUMIFS('Sep - Nov P&L'!K:K,'Sep - Nov P&L'!$D:$D,$C79) -> 0 | AS79: =+AS187 -> 13858.333 | AT79: =+AT187 -> 13906.837 | AU79: =+AU187 -> 13955.511 | AV79: =+AV187 -> 14004.356 | AW79: =+AW187 -> 14053.371 | AX79: =+AX187 -> 14102.558 | AY79: =+AY187 -> 14151.917 | AZ79: =+AZ187 -> 14201.448 | ... BQ79: =+BQ187 -> 15070.513
C80: Conferences & Meetings | D80: =+SUMIFS($J80:$BQ80,$J$7:$BQ$7,D$8) -> 12800 | E80: =+SUMIFS($J80:$BQ80,$J$7:$BQ$7,E$8) -> 13800 | F80: =+SUMIFS($J80:$BQ80,$J$7:$BQ$7,F$8) -> 10825 | G80: =+SUMIFS($J80:$BQ80,$J$7:$BQ$7,G$8) -> 11355.794 | H80: =+SUMIFS($J80:$BQ80,$J$7:$BQ$7,H$8) -> 11842.027 | J80: =+INDEX('QoE PF Adj. P&L Aug-26'!$D$11:$AI$108,MATCH($C80,'QoE PF Adj. P&L Aug-26'!$C$11:$C$108,0),MATCH(J$8,'QoE PF Adj. P&L Aug-26'!$D$8:$AI$8,0))*1000 -> 1000 | K80: =+INDEX('QoE PF Adj. P&L Aug-26'!$D$11:$AI$108,MATCH($C80,'QoE PF Adj. P&L Aug-26'!$C$11:$C$108,0),MATCH(K$8,'QoE PF Adj. P&L Aug-26'!$D$8:$AI$8,0))*1000 -> 1100 | L80: =+INDEX('QoE PF Adj. P&L Aug-26'!$D$11:$AI$108,MATCH($C80,'QoE PF Adj. P&L Aug-26'!$C$11:$C$108,0),MATCH(L$8,'QoE PF Adj. P&L Aug-26'!$D$8:$AI$8,0))*1000 -> 1000 | M80: =+INDEX('QoE PF Adj. P&L Aug-26'!$D$11:$AI$108,MATCH($C80,'QoE PF Adj. P&L Aug-26'!$C$11:$C$108,0),MATCH(M$8,'QoE PF Adj. P&L Aug-26'!$D$8:$AI$8,0))*1000 -> 1000 | N80: =+INDEX('QoE PF Adj. P&L Aug-26'!$D$11:$AI$108,MATCH($C80,'QoE PF Adj. P&L Aug-26'!$C$11:$C$108,0),MATCH(N$8,'QoE PF Adj. P&L Aug-26'!$D$8:$AI$8,0))*1000 -> 1100 | O80: =+INDEX('QoE PF Adj. P&L Aug-26'!$D$11:$AI$108,MATCH($C80,'QoE PF Adj. P&L Aug-26'!$C$11:$C$108,0),MATCH(O$8,'QoE PF Adj. P&L Aug-26'!$D$8:$AI$8,0))*1000 -> 1100 | P80: =+INDEX('QoE PF Adj. P&L Aug-26'!$D$11:$AI$108,MATCH($C80,'QoE PF Adj. P&L Aug-26'!$C$11:$C$108,0),MATCH(P$8,'QoE PF Adj. P&L Aug-26'!$D$8:$AI$8,0))*1000 -> 1100 | Q80: =+INDEX('QoE PF Adj. P&L Aug-26'!$D$11:$AI$108,MATCH($C80,'QoE PF Adj. P&L Aug-26'!$C$11:$C$108,0),MATCH(Q$8,'QoE PF Adj. P&L Aug-26'!$D$8:$AI$8,0))*1000 -> 1100 | ... AO80: =+INDEX('QoE PF Adj. P&L Aug-26'!$D$11:$AI$108,MATCH($C80,'QoE PF Adj. P&L Aug-26'!$C$11:$C$108,0),MATCH(AO$8,'QoE PF Adj. P&L Aug-26'!$D$8:$AI$8,0))*1000 -> 1200 | AP80: =+SUMIFS('Sep - Nov P&L'!I:I,'Sep - Nov P&L'!$D:$D,$C80) -> 0 | AQ80: =+SUMIFS('Sep - Nov P&L'!J:J,'Sep - Nov P&L'!$D:$D,$C80) -> 0 | AR80: =+SUMIFS('Sep - Nov P&L'!K:K,'Sep - Nov P&L'!$D:$D,$C80) -> 0 | AS80: =+AS188 -> 925 | AT80: =+AT188 -> 928.2375 | AU80: =+AU188 -> 931.48633 | AV80: =+AV188 -> 934.74653 | AW80: =+AW188 -> 938.01815 | AX80: =+AX188 -> 941.30121 | AY80: =+AY188 -> 944.59576 | AZ80: =+AZ188 -> 947.90185 | ... BQ80: =+BQ188 -> 1005.9092
C81: Mileage Reimbursement | D81: =+SUMIFS($J81:$BQ81,$J$7:$BQ$7,D$8) -> 19600 | E81: =+SUMIFS($J81:$BQ81,$J$7:$BQ$7,E$8) -> 21200 | F81: =+SUMIFS($J81:$BQ81,$J$7:$BQ$7,F$8) -> 15975 | G81: =+SUMIFS($J81:$BQ81,$J$7:$BQ$7,G$8) -> 16880.235 | H81: =+SUMIFS($J81:$BQ81,$J$7:$BQ$7,H$8) -> 17603.013 | J81: =+INDEX('QoE PF Adj. P&L Aug-26'!$D$11:$AI$108,MATCH($C81,'QoE PF Adj. P&L Aug-26'!$C$11:$C$108,0),MATCH(J$8,'QoE PF Adj. P&L Aug-26'!$D$8:$AI$8,0))*1000 -> 1600 | K81: =+INDEX('QoE PF Adj. P&L Aug-26'!$D$11:$AI$108,MATCH($C81,'QoE PF Adj. P&L Aug-26'!$C$11:$C$108,0),MATCH(K$8,'QoE PF Adj. P&L Aug-26'!$D$8:$AI$8,0))*1000 -> 1600 | L81: =+INDEX('QoE PF Adj. P&L Aug-26'!$D$11:$AI$108,MATCH($C81,'QoE PF Adj. P&L Aug-26'!$C$11:$C$108,0),MATCH(L$8,'QoE PF Adj. P&L Aug-26'!$D$8:$AI$8,0))*1000 -> 1600 | M81: =+INDEX('QoE PF Adj. P&L Aug-26'!$D$11:$AI$108,MATCH($C81,'QoE PF Adj. P&L Aug-26'!$C$11:$C$108,0),MATCH(M$8,'QoE PF Adj. P&L Aug-26'!$D$8:$AI$8,0))*1000 -> 1500 | N81: =+INDEX('QoE PF Adj. P&L Aug-26'!$D$11:$AI$108,MATCH($C81,'QoE PF Adj. P&L Aug-26'!$C$11:$C$108,0),MATCH(N$8,'QoE PF Adj. P&L Aug-26'!$D$8:$AI$8,0))*1000 -> 1600 | O81: =+INDEX('QoE PF Adj. P&L Aug-26'!$D$11:$AI$108,MATCH($C81,'QoE PF Adj. P&L Aug-26'!$C$11:$C$108,0),MATCH(O$8,'QoE PF Adj. P&L Aug-26'!$D$8:$AI$8,0))*1000 -> 1600 | P81: =+INDEX('QoE PF Adj. P&L Aug-26'!$D$11:$AI$108,MATCH($C81,'QoE PF Adj. P&L Aug-26'!$C$11:$C$108,0),MATCH(P$8,'QoE PF Adj. P&L Aug-26'!$D$8:$AI$8,0))*1000 -> 1700 | Q81: =+INDEX('QoE PF Adj. P&L Aug-26'!$D$11:$AI$108,MATCH($C81,'QoE PF Adj. P&L Aug-26'!$C$11:$C$108,0),MATCH(Q$8,'QoE PF Adj. P&L Aug-26'!$D$8:$AI$8,0))*1000 -> 1700 | ... AO81: =+INDEX('QoE PF Adj. P&L Aug-26'!$D$11:$AI$108,MATCH($C81,'QoE PF Adj. P&L Aug-26'!$C$11:$C$108,0),MATCH(AO$8,'QoE PF Adj. P&L Aug-26'!$D$8:$AI$8,0))*1000 -> 1900 | AP81: =+SUMIFS('Sep - Nov P&L'!I:I,'Sep - Nov P&L'!$D:$D,$C81) -> 0 | AQ81: =+SUMIFS('Sep - Nov P&L'!J:J,'Sep - Nov P&L'!$D:$D,$C81) -> 0 | AR81: =+SUMIFS('Sep - Nov P&L'!K:K,'Sep - Nov P&L'!$D:$D,$C81) -> 0 | AS81: =+AS189 -> 1375 | AT81: =+AT189 -> 1379.8125 | AU81: =+AU189 -> 1384.6418 | AV81: =+AV189 -> 1389.4881 | AW81: =+AW189 -> 1394.3513 | AX81: =+AX189 -> 1399.2315 | AY81: =+AY189 -> 1404.1288 | AZ81: =+AZ189 -> 1409.0433 | ... BQ81: =+BQ189 -> 1495.2704
C82: Office Expense, Supplies & Postage | D82: =+SUMIFS($J82:$BQ82,$J$7:$BQ$7,D$8) -> 44400 | E82: =+SUMIFS($J82:$BQ82,$J$7:$BQ$7,E$8) -> 48000 | F82: =+SUMIFS($J82:$BQ82,$J$7:$BQ$7,F$8) -> 51004.069 | G82: =+SUMIFS($J82:$BQ82,$J$7:$BQ$7,G$8) -> 52226.331 | H82: =+SUMIFS($J82:$BQ82,$J$7:$BQ$7,H$8) -> 54462.559 | J82: =+INDEX('QoE PF Adj. P&L Aug-26'!$D$11:$AI$108,MATCH($C82,'QoE PF Adj. P&L Aug-26'!$C$11:$C$108,0),MATCH(J$8,'QoE PF Adj. P&L Aug-26'!$D$8:$AI$8,0))*1000 -> 3600 | K82: =+INDEX('QoE PF Adj. P&L Aug-26'!$D$11:$AI$108,MATCH($C82,'QoE PF Adj. P&L Aug-26'!$C$11:$C$108,0),MATCH(K$8,'QoE PF Adj. P&L Aug-26'!$D$8:$AI$8,0))*1000 -> 3600 | L82: =+INDEX('QoE PF Adj. P&L Aug-26'!$D$11:$AI$108,MATCH($C82,'QoE PF Adj. P&L Aug-26'!$C$11:$C$108,0),MATCH(L$8,'QoE PF Adj. P&L Aug-26'!$D$8:$AI$8,0))*1000 -> 3700 | M82: =+INDEX('QoE PF Adj. P&L Aug-26'!$D$11:$AI$108,MATCH($C82,'QoE PF Adj. P&L Aug-26'!$C$11:$C$108,0),MATCH(M$8,'QoE PF Adj. P&L Aug-26'!$D$8:$AI$8,0))*1000 -> 3800 | N82: =+INDEX('QoE PF Adj. P&L Aug-26'!$D$11:$AI$108,MATCH($C82,'QoE PF Adj. P&L Aug-26'!$C$11:$C$108,0),MATCH(N$8,'QoE PF Adj. P&L Aug-26'!$D$8:$AI$8,0))*1000 -> 3500 | O82: =+INDEX('QoE PF Adj. P&L Aug-26'!$D$11:$AI$108,MATCH($C82,'QoE PF Adj. P&L Aug-26'!$C$11:$C$108,0),MATCH(O$8,'QoE PF Adj. P&L Aug-26'!$D$8:$AI$8,0))*1000 -> 3700 | P82: =+INDEX('QoE PF Adj. P&L Aug-26'!$D$11:$AI$108,MATCH($C82,'QoE PF Adj. P&L Aug-26'!$C$11:$C$108,0),MATCH(P$8,'QoE PF Adj. P&L Aug-26'!$D$8:$AI$8,0))*1000 -> 3800 | Q82: =+INDEX('QoE PF Adj. P&L Aug-26'!$D$11:$AI$108,MATCH($C82,'QoE PF Adj. P&L Aug-26'!$C$11:$C$108,0),MATCH(Q$8,'QoE PF Adj. P&L Aug-26'!$D$8:$AI$8,0))*1000 -> 3600 | ... AO82: =+INDEX('QoE PF Adj. P&L Aug-26'!$D$11:$AI$108,MATCH($C82,'QoE PF Adj. P&L Aug-26'!$C$11:$C$108,0),MATCH(AO$8,'QoE PF Adj. P&L Aug-26'!$D$8:$AI$8,0))*1000 -> 4500 | AP82: =+SUMIFS('Sep - Nov P&L'!I:I,'Sep - Nov P&L'!$D:$D,$C82) -> 4409.7 | AQ82: =+SUMIFS('Sep - Nov P&L'!J:J,'Sep - Nov P&L'!$D:$D,$C82) -> 4611.07 | AR82: =+SUMIFS('Sep - Nov P&L'!K:K,'Sep - Nov P&L'!$D:$D,$C82) -> 4229.14 | AS82: =+AS190 -> 4254.1592 | AT82: =+AT190 -> 4269.0487 | AU82: =+AU190 -> 4283.9904 | AV82: =+AV190 -> 4298.9844 | AW82: =+AW190 -> 4314.0308 | AX82: =+AX190 -> 4329.1299 | AY82: =+AY190 -> 4344.2819 | AZ82: =+AZ190 -> 4359.4869 | ... BQ82: =+BQ190 -> 4626.2679
C83: Other Operating Expenses | D83: =+SUMIFS($J83:$BQ83,$J$7:$BQ$7,D$8) -> 38800 | E83: =+SUMIFS($J83:$BQ83,$J$7:$BQ$7,E$8) -> 41300 | F83: =+SUMIFS($J83:$BQ83,$J$7:$BQ$7,F$8) -> 96651.155 | G83: =+SUMIFS($J83:$BQ83,$J$7:$BQ$7,G$8) -> 94577.623 | H83: =+SUMIFS($J83:$BQ83,$J$7:$BQ$7,H$8) -> 98627.248 | J83: =+INDEX('QoE PF Adj. P&L Aug-26'!$D$11:$AI$108,MATCH($C83,'QoE PF Adj. P&L Aug-26'!$C$11:$C$108,0),MATCH(J$8,'QoE PF Adj. P&L Aug-26'!$D$8:$AI$8,0))*1000 -> 3300 | K83: =+INDEX('QoE PF Adj. P&L Aug-26'!$D$11:$AI$108,MATCH($C83,'QoE PF Adj. P&L Aug-26'!$C$11:$C$108,0),MATCH(K$8,'QoE PF Adj. P&L Aug-26'!$D$8:$AI$8,0))*1000 -> 3400 | L83: =+INDEX('QoE PF Adj. P&L Aug-26'!$D$11:$AI$108,MATCH($C83,'QoE PF Adj. P&L Aug-26'!$C$11:$C$108,0),MATCH(L$8,'QoE PF Adj. P&L Aug-26'!$D$8:$AI$8,0))*1000 -> 3200 | M83: =+INDEX('QoE PF Adj. P&L Aug-26'!$D$11:$AI$108,MATCH($C83,'QoE PF Adj. P&L Aug-26'!$C$11:$C$108,0),MATCH(M$8,'QoE PF Adj. P&L Aug-26'!$D$8:$AI$8,0))*1000 -> 3300 | N83: =+INDEX('QoE PF Adj. P&L Aug-26'!$D$11:$AI$108,MATCH($C83,'QoE PF Adj. P&L Aug-26'!$C$11:$C$108,0),MATCH(N$8,'QoE PF Adj. P&L Aug-26'!$D$8:$AI$8,0))*1000 -> 3100 | O83: =+INDEX('QoE PF Adj. P&L Aug-26'!$D$11:$AI$108,MATCH($C83,'QoE PF Adj. P&L Aug-26'!$C$11:$C$108,0),MATCH(O$8,'QoE PF Adj. P&L Aug-26'!$D$8:$AI$8,0))*1000 -> 3400 | P83: =+INDEX('QoE PF Adj. P&L Aug-26'!$D$11:$AI$108,MATCH($C83,'QoE PF Adj. P&L Aug-26'!$C$11:$C$108,0),MATCH(P$8,'QoE PF Adj. P&L Aug-26'!$D$8:$AI$8,0))*1000 -> 3200 | Q83: =+INDEX('QoE PF Adj. P&L Aug-26'!$D$11:$AI$108,MATCH($C83,'QoE PF Adj. P&L Aug-26'!$C$11:$C$108,0),MATCH(Q$8,'QoE PF Adj. P&L Aug-26'!$D$8:$AI$8,0))*1000 -> 3000 | ... AO83: =+INDEX('QoE PF Adj. P&L Aug-26'!$D$11:$AI$108,MATCH($C83,'QoE PF Adj. P&L Aug-26'!$C$11:$C$108,0),MATCH(AO$8,'QoE PF Adj. P&L Aug-26'!$D$8:$AI$8,0))*1000 -> 3800 | AP83: =+SUMIFS('Sep - Nov P&L'!I:I,'Sep - Nov P&L'!$D:$D,$C83) -> 20633.75 | AQ83: =+SUMIFS('Sep - Nov P&L'!J:J,'Sep - Nov P&L'!$D:$D,$C83) -> 21555.33 | AR83: =+SUMIFS('Sep - Nov P&L'!K:K,'Sep - Nov P&L'!$D:$D,$C83) -> 17958.14 | AS83: =+AS191 -> 7703.935 | AT83: =+AT191 -> 7730.8988 | AU83: =+AU191 -> 7757.9569 | AV83: =+AV191 -> 7785.1098 | AW83: =+AW191 -> 7812.3577 | AX83: =+AX191 -> 7839.7009 | AY83: =+AY191 -> 7867.1399 | AZ83: =+AZ191 -> 7894.6748 | ... BQ83: =+BQ191 -> 8377.7935
C84: Repairs & Maintenance | D84: =+SUMIFS($J84:$BQ84,$J$7:$BQ$7,D$8) -> 38000 | E84: =+SUMIFS($J84:$BQ84,$J$7:$BQ$7,E$8) -> 41700 | F84: =+SUMIFS($J84:$BQ84,$J$7:$BQ$7,F$8) -> 43622.817 | G84: =+SUMIFS($J84:$BQ84,$J$7:$BQ$7,G$8) -> 44689.245 | H84: =+SUMIFS($J84:$BQ84,$J$7:$BQ$7,H$8) -> 46602.749 | J84: =+INDEX('QoE PF Adj. P&L Aug-26'!$D$11:$AI$108,MATCH($C84,'QoE PF Adj. P&L Aug-26'!$C$11:$C$108,0),MATCH(J$8,'QoE PF Adj. P&L Aug-26'!$D$8:$AI$8,0))*1000 -> 3000 | K84: =+INDEX('QoE PF Adj. P&L Aug-26'!$D$11:$AI$108,MATCH($C84,'QoE PF Adj. P&L Aug-26'!$C$11:$C$108,0),MATCH(K$8,'QoE PF Adj. P&L Aug-26'!$D$8:$AI$8,0))*1000 -> 3100 | L84: =+INDEX('QoE PF Adj. P&L Aug-26'!$D$11:$AI$108,MATCH($C84,'QoE PF Adj. P&L Aug-26'!$C$11:$C$108,0),MATCH(L$8,'QoE PF Adj. P&L Aug-26'!$D$8:$AI$8,0))*1000 -> 3100 | M84: =+INDEX('QoE PF Adj. P&L Aug-26'!$D$11:$AI$108,MATCH($C84,'QoE PF Adj. P&L Aug-26'!$C$11:$C$108,0),MATCH(M$8,'QoE PF Adj. P&L Aug-26'!$D$8:$AI$8,0))*1000 -> 3000 | N84: =+INDEX('QoE PF Adj. P&L Aug-26'!$D$11:$AI$108,MATCH($C84,'QoE PF Adj. P&L Aug-26'!$C$11:$C$108,0),MATCH(N$8,'QoE PF Adj. P&L Aug-26'!$D$8:$AI$8,0))*1000 -> 3200 | O84: =+INDEX('QoE PF Adj. P&L Aug-26'!$D$11:$AI$108,MATCH($C84,'QoE PF Adj. P&L Aug-26'!$C$11:$C$108,0),MATCH(O$8,'QoE PF Adj. P&L Aug-26'!$D$8:$AI$8,0))*1000 -> 3000 | P84: =+INDEX('QoE PF Adj. P&L Aug-26'!$D$11:$AI$108,MATCH($C84,'QoE PF Adj. P&L Aug-26'!$C$11:$C$108,0),MATCH(P$8,'QoE PF Adj. P&L Aug-26'!$D$8:$AI$8,0))*1000 -> 3000 | Q84: =+INDEX('QoE PF Adj. P&L Aug-26'!$D$11:$AI$108,MATCH($C84,'QoE PF Adj. P&L Aug-26'!$C$11:$C$108,0),MATCH(Q$8,'QoE PF Adj. P&L Aug-26'!$D$8:$AI$8,0))*1000 -> 3400 | ... AO84: =+INDEX('QoE PF Adj. P&L Aug-26'!$D$11:$AI$108,MATCH($C84,'QoE PF Adj. P&L Aug-26'!$C$11:$C$108,0),MATCH(AO$8,'QoE PF Adj. P&L Aug-26'!$D$8:$AI$8,0))*1000 -> 3500 | AP84: =+SUMIFS('Sep - Nov P&L'!I:I,'Sep - Nov P&L'!$D:$D,$C84) -> 3753.91 | AQ84: =+SUMIFS('Sep - Nov P&L'!J:J,'Sep - Nov P&L'!$D:$D,$C84) -> 3766.24 | AR84: =+SUMIFS('Sep - Nov P&L'!K:K,'Sep - Nov P&L'!$D:$D,$C84) -> 3562.45 | AS84: =+AS192 -> 3640.2167 | AT84: =+AT192 -> 3652.9574 | AU84: =+AU192 -> 3665.7428 | AV84: =+AV192 -> 3678.5729 | AW84: =+AW192 -> 3691.4479 | AX84: =+AX192 -> 3704.3679 | AY84: =+AY192 -> 3717.3332 | AZ84: =+AZ192 -> 3730.3439 | ... BQ84: =+BQ192 -> 3958.6242
C85: Taxes & Licenses | D85: =+SUMIFS($J85:$BQ85,$J$7:$BQ$7,D$8) -> 45400 | E85: =+SUMIFS($J85:$BQ85,$J$7:$BQ$7,E$8) -> 49400 | F85: =+SUMIFS($J85:$BQ85,$J$7:$BQ$7,F$8) -> 52426.692 | G85: =+SUMIFS($J85:$BQ85,$J$7:$BQ$7,G$8) -> 53569.783 | H85: =+SUMIFS($J85:$BQ85,$J$7:$BQ$7,H$8) -> 55863.534 | J85: =+INDEX('QoE PF Adj. P&L Aug-26'!$D$11:$AI$108,MATCH($C85,'QoE PF Adj. P&L Aug-26'!$C$11:$C$108,0),MATCH(J$8,'QoE PF Adj. P&L Aug-26'!$D$8:$AI$8,0))*1000 -> 3900 | K85: =+INDEX('QoE PF Adj. P&L Aug-26'!$D$11:$AI$108,MATCH($C85,'QoE PF Adj. P&L Aug-26'!$C$11:$C$108,0),MATCH(K$8,'QoE PF Adj. P&L Aug-26'!$D$8:$AI$8,0))*1000 -> 3800 | L85: =+INDEX('QoE PF Adj. P&L Aug-26'!$D$11:$AI$108,MATCH($C85,'QoE PF Adj. P&L Aug-26'!$C$11:$C$108,0),MATCH(L$8,'QoE PF Adj. P&L Aug-26'!$D$8:$AI$8,0))*1000 -> 3800 | M85: =+INDEX('QoE PF Adj. P&L Aug-26'!$D$11:$AI$108,MATCH($C85,'QoE PF Adj. P&L Aug-26'!$C$11:$C$108,0),MATCH(M$8,'QoE PF Adj. P&L Aug-26'!$D$8:$AI$8,0))*1000 -> 3600 | N85: =+INDEX('QoE PF Adj. P&L Aug-26'!$D$11:$AI$108,MATCH($C85,'QoE PF Adj. P&L Aug-26'!$C$11:$C$108,0),MATCH(N$8,'QoE PF Adj. P&L Aug-26'!$D$8:$AI$8,0))*1000 -> 3600 | O85: =+INDEX('QoE PF Adj. P&L Aug-26'!$D$11:$AI$108,MATCH($C85,'QoE PF Adj. P&L Aug-26'!$C$11:$C$108,0),MATCH(O$8,'QoE PF Adj. P&L Aug-26'!$D$8:$AI$8,0))*1000 -> 3700 | P85: =+INDEX('QoE PF Adj. P&L Aug-26'!$D$11:$AI$108,MATCH($C85,'QoE PF Adj. P&L Aug-26'!$C$11:$C$108,0),MATCH(P$8,'QoE PF Adj. P&L Aug-26'!$D$8:$AI$8,0))*1000 -> 3800 | Q85: =+INDEX('QoE PF Adj. P&L Aug-26'!$D$11:$AI$108,MATCH($C85,'QoE PF Adj. P&L Aug-26'!$C$11:$C$108,0),MATCH(Q$8,'QoE PF Adj. P&L Aug-26'!$D$8:$AI$8,0))*1000 -> 3900 | ... AO85: =+INDEX('QoE PF Adj. P&L Aug-26'!$D$11:$AI$108,MATCH($C85,'QoE PF Adj. P&L Aug-26'!$C$11:$C$108,0),MATCH(AO$8,'QoE PF Adj. P&L Aug-26'!$D$8:$AI$8,0))*1000 -> 4400 | AP85: =+SUMIFS('Sep - Nov P&L'!I:I,'Sep - Nov P&L'!$D:$D,$C85) -> 4313.94 | AQ85: =+SUMIFS('Sep - Nov P&L'!J:J,'Sep - Nov P&L'!$D:$D,$C85) -> 4498.46 | AR85: =+SUMIFS('Sep - Nov P&L'!K:K,'Sep - Nov P&L'!$D:$D,$C85) -> 4350.7 | AS85: =+AS193 -> 4363.5917 | AT85: =+AT193 -> 4378.8642 | AU85: =+AU193 -> 4394.1903 | AV85: =+AV193 -> 4409.5699 | AW85: =+AW193 -> 4425.0034 | AX85: =+AX193 -> 4440.4909 | AY85: =+AY193 -> 4456.0327 | AZ85: =+AZ193 -> 4471.6288 | ... BQ85: =+BQ193 -> 4745.2724
C86: Telephone & Message Services | D86: =+SUMIFS($J86:$BQ86,$J$7:$BQ$7,D$8) -> 52500 | E86: =+SUMIFS($J86:$BQ86,$J$7:$BQ$7,E$8) -> 55300 | F86: =+SUMIFS($J86:$BQ86,$J$7:$BQ$7,F$8) -> 42550 | G86: =+SUMIFS($J86:$BQ86,$J$7:$BQ$7,G$8) -> 44809.35 | H86: =+SUMIFS($J86:$BQ86,$J$7:$BQ$7,H$8) -> 46727.997 | J86: =+INDEX('QoE PF Adj. P&L Aug-26'!$D$11:$AI$108,MATCH($C86,'QoE PF Adj. P&L Aug-26'!$C$11:$C$108,0),MATCH(J$8,'QoE PF Adj. P&L Aug-26'!$D$8:$AI$8,0))*1000 -> 4400 | K86: =+INDEX('QoE PF Adj. P&L Aug-26'!$D$11:$AI$108,MATCH($C86,'QoE PF Adj. P&L Aug-26'!$C$11:$C$108,0),MATCH(K$8,'QoE PF Adj. P&L Aug-26'!$D$8:$AI$8,0))*1000 -> 4400 | L86: =+INDEX('QoE PF Adj. P&L Aug-26'!$D$11:$AI$108,MATCH($C86,'QoE PF Adj. P&L Aug-26'!$C$11:$C$108,0),MATCH(L$8,'QoE PF Adj. P&L Aug-26'!$D$8:$AI$8,0))*1000 -> 4500 | M86: =+INDEX('QoE PF Adj. P&L Aug-26'!$D$11:$AI$108,MATCH($C86,'QoE PF Adj. P&L Aug-26'!$C$11:$C$108,0),MATCH(M$8,'QoE PF Adj. P&L Aug-26'!$D$8:$AI$8,0))*1000 -> 4500 | N86: =+INDEX('QoE PF Adj. P&L Aug-26'!$D$11:$AI$108,MATCH($C86,'QoE PF Adj. P&L Aug-26'!$C$11:$C$108,0),MATCH(N$8,'QoE PF Adj. P&L Aug-26'!$D$8:$AI$8,0))*1000 -> 4000 | O86: =+INDEX('QoE PF Adj. P&L Aug-26'!$D$11:$AI$108,MATCH($C86,'QoE PF Adj. P&L Aug-26'!$C$11:$C$108,0),MATCH(O$8,'QoE PF Adj. P&L Aug-26'!$D$8:$AI$8,0))*1000 -> 4300 | P86: =+INDEX('QoE PF Adj. P&L Aug-26'!$D$11:$AI$108,MATCH($C86,'QoE PF Adj. P&L Aug-26'!$C$11:$C$108,0),MATCH(P$8,'QoE PF Adj. P&L Aug-26'!$D$8:$AI$8,0))*1000 -> 4300 | Q86: =+INDEX('QoE PF Adj. P&L Aug-26'!$D$11:$AI$108,MATCH($C86,'QoE PF Adj. P&L Aug-26'!$C$11:$C$108,0),MATCH(Q$8,'QoE PF Adj. P&L Aug-26'!$D$8:$AI$8,0))*1000 -> 4400 | ... AO86: =+INDEX('QoE PF Adj. P&L Aug-26'!$D$11:$AI$108,MATCH($C86,'QoE PF Adj. P&L Aug-26'!$C$11:$C$108,0),MATCH(AO$8,'QoE PF Adj. P&L Aug-26'!$D$8:$AI$8,0))*1000 -> 5100 | AP86: =+SUMIFS('Sep - Nov P&L'!I:I,'Sep - Nov P&L'!$D:$D,$C86) -> 0 | AQ86: =+SUMIFS('Sep - Nov P&L'!J:J,'Sep - Nov P&L'!$D:$D,$C86) -> 0 | AR86: =+SUMIFS('Sep - Nov P&L'!K:K,'Sep - Nov P&L'!$D:$D,$C86) -> 0 | AS86: =+AS194 -> 3650 | AT86: =+AT194 -> 3662.775 | AU86: =+AU194 -> 3675.5947 | AV86: =+AV194 -> 3688.4593 | AW86: =+AW194 -> 3701.3689 | AX86: =+AX194 -> 3714.3237 | AY86: =+AY194 -> 3727.3238 | AZ86: =+AZ194 -> 3740.3695 | ... BQ86: =+BQ194 -> 3969.2633
C87: Travel, Meals & Entertainment | D87: =+SUMIFS($J87:$BQ87,$J$7:$BQ$7,D$8) -> 38500 | E87: =+SUMIFS($J87:$BQ87,$J$7:$BQ$7,E$8) -> 41900 | F87: =+SUMIFS($J87:$BQ87,$J$7:$BQ$7,F$8) -> 44524.637 | G87: =+SUMIFS($J87:$BQ87,$J$7:$BQ$7,G$8) -> 45540.878 | H87: =+SUMIFS($J87:$BQ87,$J$7:$BQ$7,H$8) -> 47490.848 | J87: =+INDEX('QoE PF Adj. P&L Aug-26'!$D$11:$AI$108,MATCH($C87,'QoE PF Adj. P&L Aug-26'!$C$11:$C$108,0),MATCH(J$8,'QoE PF Adj. P&L Aug-26'!$D$8:$AI$8,0))*1000 -> 3100 | K87: =+INDEX('QoE PF Adj. P&L Aug-26'!$D$11:$AI$108,MATCH($C87,'QoE PF Adj. P&L Aug-26'!$C$11:$C$108,0),MATCH(K$8,'QoE PF Adj. P&L Aug-26'!$D$8:$AI$8,0))*1000 -> 3000 | L87: =+INDEX('QoE PF Adj. P&L Aug-26'!$D$11:$AI$108,MATCH($C87,'QoE PF Adj. P&L Aug-26'!$C$11:$C$108,0),MATCH(L$8,'QoE PF Adj. P&L Aug-26'!$D$8:$AI$8,0))*1000 -> 3100 | M87: =+INDEX('QoE PF Adj. P&L Aug-26'!$D$11:$AI$108,MATCH($C87,'QoE PF Adj. P&L Aug-26'!$C$11:$C$108,0),MATCH(M$8,'QoE PF Adj. P&L Aug-26'!$D$8:$AI$8,0))*1000 -> 3200 | N87: =+INDEX('QoE PF Adj. P&L Aug-26'!$D$11:$AI$108,MATCH($C87,'QoE PF Adj. P&L Aug-26'!$C$11:$C$108,0),MATCH(N$8,'QoE PF Adj. P&L Aug-26'!$D$8:$AI$8,0))*1000 -> 3100 | O87: =+INDEX('QoE PF Adj. P&L Aug-26'!$D$11:$AI$108,MATCH($C87,'QoE PF Adj. P&L Aug-26'!$C$11:$C$108,0),MATCH(O$8,'QoE PF Adj. P&L Aug-26'!$D$8:$AI$8,0))*1000 -> 3300 | P87: =+INDEX('QoE PF Adj. P&L Aug-26'!$D$11:$AI$108,MATCH($C87,'QoE PF Adj. P&L Aug-26'!$C$11:$C$108,0),MATCH(P$8,'QoE PF Adj. P&L Aug-26'!$D$8:$AI$8,0))*1000 -> 3400 | Q87: =+INDEX('QoE PF Adj. P&L Aug-26'!$D$11:$AI$108,MATCH($C87,'QoE PF Adj. P&L Aug-26'!$C$11:$C$108,0),MATCH(Q$8,'QoE PF Adj. P&L Aug-26'!$D$8:$AI$8,0))*1000 -> 3200 | ... AO87: =+INDEX('QoE PF Adj. P&L Aug-26'!$D$11:$AI$108,MATCH($C87,'QoE PF Adj. P&L Aug-26'!$C$11:$C$108,0),MATCH(AO$8,'QoE PF Adj. P&L Aug-26'!$D$8:$AI$8,0))*1000 -> 3500 | AP87: =+SUMIFS('Sep - Nov P&L'!I:I,'Sep - Nov P&L'!$D:$D,$C87) -> 3897.05 | AQ87: =+SUMIFS('Sep - Nov P&L'!J:J,'Sep - Nov P&L'!$D:$D,$C87) -> 3933.75 | AR87: =+SUMIFS('Sep - Nov P&L'!K:K,'Sep - Nov P&L'!$D:$D,$C87) -> 3784.25 | AS87: =+AS195 -> 3709.5875 | AT87: =+AT195 -> 3722.5711 | AU87: =+AU195 -> 3735.6001 | AV87: =+AV195 -> 3748.6747 | AW87: =+AW195 -> 3761.795 | AX87: =+AX195 -> 3774.9613 | AY87: =+AY195 -> 3788.1737 | AZ87: =+AZ195 -> 3801.4323 | ... BQ87: =+BQ195 -> 4034.0629
... C90: Quality Control | D90: =+SUMIFS($J90:$BQ90,$J$7:$BQ$7,D$8) -> 38100 | E90: =+SUMIFS($J90:$BQ90,$J$7:$BQ$7,E$8) -> 41100 | F90: =+SUMIFS($J90:$BQ90,$J$7:$BQ$7,F$8) -> 43950.579 | G90: =+SUMIFS($J90:$BQ90,$J$7:$BQ$7,G$8) -> 44998.767 | H90: =+SUMIFS($J90:$BQ90,$J$7:$BQ$7,H$8) -> 46925.525 | J90: =+INDEX('QoE PF Adj. P&L Aug-26'!$D$11:$AI$108,MATCH($C90,'QoE PF Adj. P&L Aug-26'!$C$11:$C$108,0),MATCH(J$8,'QoE PF Adj. P&L Aug-26'!$D$8:$AI$8,0))*1000 -> 3200 | K90: =+INDEX('QoE PF Adj. P&L Aug-26'!$D$11:$AI$108,MATCH($C90,'QoE PF Adj. P&L Aug-26'!$C$11:$C$108,0),MATCH(K$8,'QoE PF Adj. P&L Aug-26'!$D$8:$AI$8,0))*1000 -> 3300 | L90: =+INDEX('QoE PF Adj. P&L Aug-26'!$D$11:$AI$108,MATCH($C90,'QoE PF Adj. P&L Aug-26'!$C$11:$C$108,0),MATCH(L$8,'QoE PF Adj. P&L Aug-26'!$D$8:$AI$8,0))*1000 -> 3300 | M90: =+INDEX('QoE PF Adj. P&L Aug-26'!$D$11:$AI$108,MATCH($C90,'QoE PF Adj. P&L Aug-26'!$C$11:$C$108,0),MATCH(M$8,'QoE PF Adj. P&L Aug-26'!$D$8:$AI$8,0))*1000 -> 3100 | N90: =+INDEX('QoE PF Adj. P&L Aug-26'!$D$11:$AI$108,MATCH($C90,'QoE PF Adj. P&L Aug-26'!$C$11:$C$108,0),MATCH(N$8,'QoE PF Adj. P&L Aug-26'!$D$8:$AI$8,0))*1000 -> 3300 | O90: =+INDEX('QoE PF Adj. P&L Aug-26'!$D$11:$AI$108,MATCH($C90,'QoE PF Adj. P&L Aug-26'!$C$11:$C$108,0),MATCH(O$8,'QoE PF Adj. P&L Aug-26'!$D$8:$AI$8,0))*1000 -> 3300 | P90: =+INDEX('QoE PF Adj. P&L Aug-26'!$D$11:$AI$108,MATCH($C90,'QoE PF Adj. P&L Aug-26'!$C$11:$C$108,0),MATCH(P$8,'QoE PF Adj. P&L Aug-26'!$D$8:$AI$8,0))*1000 -> 3000 | Q90: =+INDEX('QoE PF Adj. P&L Aug-26'!$D$11:$AI$108,MATCH($C90,'QoE PF Adj. P&L Aug-26'!$C$11:$C$108,0),MATCH(Q$8,'QoE PF Adj. P&L Aug-26'!$D$8:$AI$8,0))*1000 -> 3100 | ... AO90: =+INDEX('QoE PF Adj. P&L Aug-26'!$D$11:$AI$108,MATCH($C90,'QoE PF Adj. P&L Aug-26'!$C$11:$C$108,0),MATCH(AO$8,'QoE PF Adj. P&L Aug-26'!$D$8:$AI$8,0))*1000 -> 3700 | AP90: =+SUMIFS('Sep - Nov P&L'!I:I,'Sep - Nov P&L'!$D:$D,$C90) -> 3882.98 | AQ90: =+SUMIFS('Sep - Nov P&L'!J:J,'Sep - Nov P&L'!$D:$D,$C90) -> 3777.36 | AR90: =+SUMIFS('Sep - Nov P&L'!K:K,'Sep - Nov P&L'!$D:$D,$C90) -> 4024.81 | AS90: =+AS198 -> 3665.4292 | AT90: =+AT198 -> 3678.2582 | AU90: =+AU198 -> 3691.1321 | AV90: =+AV198 -> 3704.051 | AW90: =+AW198 -> 3717.0152 | AX90: =+AX198 -> 3730.0248 | AY90: =+AY198 -> 3743.0799 | AZ90: =+AZ198 -> 3756.1806 | ... BQ90: =+BQ198 -> 3986.042
B91: % rev | C91: Delivery and Transportation | D91: =+SUMIFS($J91:$BQ91,$J$7:$BQ$7,D$8) -> 76300 | E91: =+SUMIFS($J91:$BQ91,$J$7:$BQ$7,E$8) -> 82000 | F91: =+SUMIFS($J91:$BQ91,$J$7:$BQ$7,F$8) -> 90166.354 | G91: =+SUMIFS($J91:$BQ91,$J$7:$BQ$7,G$8) -> 99061.919 | H91: =+SUMIFS($J91:$BQ91,$J$7:$BQ$7,H$8) -> 115564.75 | J91: =+INDEX('QoE PF Adj. P&L Aug-26'!$D$11:$AI$108,MATCH($C91,'QoE PF Adj. P&L Aug-26'!$C$11:$C$108,0),MATCH(J$8,'QoE PF Adj. P&L Aug-26'!$D$8:$AI$8,0))*1000 -> 6300 | K91: =+INDEX('QoE PF Adj. P&L Aug-26'!$D$11:$AI$108,MATCH($C91,'QoE PF Adj. P&L Aug-26'!$C$11:$C$108,0),MATCH(K$8,'QoE PF Adj. P&L Aug-26'!$D$8:$AI$8,0))*1000 -> 5900 | L91: =+INDEX('QoE PF Adj. P&L Aug-26'!$D$11:$AI$108,MATCH($C91,'QoE PF Adj. P&L Aug-26'!$C$11:$C$108,0),MATCH(L$8,'QoE PF Adj. P&L Aug-26'!$D$8:$AI$8,0))*1000 -> 6300 | M91: =+INDEX('QoE PF Adj. P&L Aug-26'!$D$11:$AI$108,MATCH($C91,'QoE PF Adj. P&L Aug-26'!$C$11:$C$108,0),MATCH(M$8,'QoE PF Adj. P&L Aug-26'!$D$8:$AI$8,0))*1000 -> 6100 | N91: =+INDEX('QoE PF Adj. P&L Aug-26'!$D$11:$AI$108,MATCH($C91,'QoE PF Adj. P&L Aug-26'!$C$11:$C$108,0),MATCH(N$8,'QoE PF Adj. P&L Aug-26'!$D$8:$AI$8,0))*1000 -> 6800 | O91: =+INDEX('QoE PF Adj. P&L Aug-26'!$D$11:$AI$108,MATCH($C91,'QoE PF Adj. P&L Aug-26'!$C$11:$C$108,0),MATCH(O$8,'QoE PF Adj. P&L Aug-26'!$D$8:$AI$8,0))*1000 -> 5700 | P91: =+INDEX('QoE PF Adj. P&L Aug-26'!$D$11:$AI$108,MATCH($C91,'QoE PF Adj. P&L Aug-26'!$C$11:$C$108,0),MATCH(P$8,'QoE PF Adj. P&L Aug-26'!$D$8:$AI$8,0))*1000 -> 6600 | Q91: =+INDEX('QoE PF Adj. P&L Aug-26'!$D$11:$AI$108,MATCH($C91,'QoE PF Adj. P&L Aug-26'!$C$11:$C$108,0),MATCH(Q$8,'QoE PF Adj. P&L Aug-26'!$D$8:$AI$8,0))*1000 -> 6900 | ... AO91: =+INDEX('QoE PF Adj. P&L Aug-26'!$D$11:$AI$108,MATCH($C91,'QoE PF Adj. P&L Aug-26'!$C$11:$C$108,0),MATCH(AO$8,'QoE PF Adj. P&L Aug-26'!$D$8:$AI$8,0))*1000 -> 7500 | AP91: =+SUMIFS('Sep - Nov P&L'!I:I,'Sep - Nov P&L'!$D:$D,$C91) -> 7570.09 | AQ91: =+SUMIFS('Sep - Nov P&L'!J:J,'Sep - Nov P&L'!$D:$D,$C91) -> 8438.76 | AR91: =+SUMIFS('Sep - Nov P&L'!K:K,'Sep - Nov P&L'!$D:$D,$C91) -> 7180.27 | AS91: =+AS$10*AS199 -> 7877.234 | AT91: =+AT$10*AT199 -> 7192.0114 | AU91: =+AU$10*AU199 -> 6849.4001 | AV91: =+AV$10*AV199 -> 8091.6124 | AW91: =+AW$10*AW199 -> 8248.7484 | AX91: =+AX$10*AX199 -> 7674.6922 | AY91: =+AY$10*AY199 -> 8202.8384 | AZ91: =+AZ$10*AZ199 -> 8365.3885 | ... BQ91: =+BQ$10*BQ199 -> 9534.574
C92: Recruitment Costs | D92: =+SUMIFS($J92:$BQ92,$J$7:$BQ$7,D$8) -> 25400 | E92: =+SUMIFS($J92:$BQ92,$J$7:$BQ$7,E$8) -> 27100 | F92: =+SUMIFS($J92:$BQ92,$J$7:$BQ$7,F$8) -> 29094.745 | G92: =+SUMIFS($J92:$BQ92,$J$7:$BQ$7,G$8) -> 29836.459 | H92: =+SUMIFS($J92:$BQ92,$J$7:$BQ$7,H$8) -> 31113.997 | J92: =+INDEX('QoE PF Adj. P&L Aug-26'!$D$11:$AI$108,MATCH($C92,'QoE PF Adj. P&L Aug-26'!$C$11:$C$108,0),MATCH(J$8,'QoE PF Adj. P&L Aug-26'!$D$8:$AI$8,0))*1000 -> 2100 | K92: =+INDEX('QoE PF Adj. P&L Aug-26'!$D$11:$AI$108,MATCH($C92,'QoE PF Adj. P&L Aug-26'!$C$11:$C$108,0),MATCH(K$8,'QoE PF Adj. P&L Aug-26'!$D$8:$AI$8,0))*1000 -> 2000 | L92: =+INDEX('QoE PF Adj. P&L Aug-26'!$D$11:$AI$108,MATCH($C92,'QoE PF Adj. P&L Aug-26'!$C$11:$C$108,0),MATCH(L$8,'QoE PF Adj. P&L Aug-26'!$D$8:$AI$8,0))*1000 -> 2000 | M92: =+INDEX('QoE PF Adj. P&L Aug-26'!$D$11:$AI$108,MATCH($C92,'QoE PF Adj. P&L Aug-26'!$C$11:$C$108,0),MATCH(M$8,'QoE PF Adj. P&L Aug-26'!$D$8:$AI$8,0))*1000 -> 2000 | N92: =+INDEX('QoE PF Adj. P&L Aug-26'!$D$11:$AI$108,MATCH($C92,'QoE PF Adj. P&L Aug-26'!$C$11:$C$108,0),MATCH(N$8,'QoE PF Adj. P&L Aug-26'!$D$8:$AI$8,0))*1000 -> 2200 | O92: =+INDEX('QoE PF Adj. P&L Aug-26'!$D$11:$AI$108,MATCH($C92,'QoE PF Adj. P&L Aug-26'!$C$11:$C$108,0),MATCH(O$8,'QoE PF Adj. P&L Aug-26'!$D$8:$AI$8,0))*1000 -> 2100 | P92: =+INDEX('QoE PF Adj. P&L Aug-26'!$D$11:$AI$108,MATCH($C92,'QoE PF Adj. P&L Aug-26'!$C$11:$C$108,0),MATCH(P$8,'QoE PF Adj. P&L Aug-26'!$D$8:$AI$8,0))*1000 -> 2100 | Q92: =+INDEX('QoE PF Adj. P&L Aug-26'!$D$11:$AI$108,MATCH($C92,'QoE PF Adj. P&L Aug-26'!$C$11:$C$108,0),MATCH(Q$8,'QoE PF Adj. P&L Aug-26'!$D$8:$AI$8,0))*1000 -> 2200 | ... AO92: =+INDEX('QoE PF Adj. P&L Aug-26'!$D$11:$AI$108,MATCH($C92,'QoE PF Adj. P&L Aug-26'!$C$11:$C$108,0),MATCH(AO$8,'QoE PF Adj. P&L Aug-26'!$D$8:$AI$8,0))*1000 -> 2600 | AP92: =+SUMIFS('Sep - Nov P&L'!I:I,'Sep - Nov P&L'!$D:$D,$C92) -> 2625.69 | AQ92: =+SUMIFS('Sep - Nov P&L'!J:J,'Sep - Nov P&L'!$D:$D,$C92) -> 2407.03 | AR92: =+SUMIFS('Sep - Nov P&L'!K:K,'Sep - Nov P&L'!$D:$D,$C92) -> 2431.66 | AS92: =+AS200 -> 2430.365 | AT92: =+AT200 -> 2438.8713 | AU92: =+AU200 -> 2447.4073 | AV92: =+AV200 -> 2455.9733 | AW92: =+AW200 -> 2464.5692 | AX92: =+AX200 -> 2473.1952 | AY92: =+AY200 -> 2481.8513 | AZ92: =+AZ200 -> 2490.5378 | ... BQ92: =+BQ200 -> 2642.9476
C93: Total General & Administrative | D93: =+SUMIFS($J93:$BQ93,$J$7:$BQ$7,D$8) -> 1952800 | E93: =+SUMIFS($J93:$BQ93,$J$7:$BQ$7,E$8) -> 2091500 | F93: =+SUMIFS($J93:$BQ93,$J$7:$BQ$7,F$8) -> 2251314 | G93: =+SUMIFS($J93:$BQ93,$J$7:$BQ$7,G$8) -> 2356781.1 | H93: =+SUMIFS($J93:$BQ93,$J$7:$BQ$7,H$8) -> 2573672.7 | J93: =SUM(J69:J92) -> 160700 | K93: =SUM(K69:K92) -> 156000 | L93: =SUM(L69:L92) -> 162900 | M93: =SUM(M69:M92) -> 158800 | N93: =SUM(N69:N92) -> 165000 | O93: =SUM(O69:O92) -> 156900 | P93: =SUM(P69:P92) -> 165000 | Q93: =SUM(Q69:Q92) -> 166100 | ... BQ93: =SUM(BQ69:BQ92) -> 215951.01
C95: Total Operating Expenses | D95: =+SUMIFS($J95:$BQ95,$J$7:$BQ$7,D$8) -> 10218300 | E95: =+SUMIFS($J95:$BQ95,$J$7:$BQ$7,E$8) -> 10939200 | F95: =+SUMIFS($J95:$BQ95,$J$7:$BQ$7,F$8) -> 11731601 | G95: =+SUMIFS($J95:$BQ95,$J$7:$BQ$7,G$8) -> 12969195 | H95: =+SUMIFS($J95:$BQ95,$J$7:$BQ$7,H$8) -> 14478034 | J95: =+J93+J66+J59+J53+J45+J38+J27+J19 -> 843600 | K95: =+K93+K66+K59+K53+K45+K38+K27+K19 -> 810400 | L95: =+L93+L66+L59+L53+L45+L38+L27+L19 -> 848300 | M95: =+M93+M66+M59+M53+M45+M38+M27+M19 -> 844000 | N95: =+N93+N66+N59+N53+N45+N38+N27+N19 -> 877100 | O95: =+O93+O66+O59+O53+O45+O38+O27+O19 -> 824600 | P95: =+P93+P66+P59+P53+P45+P38+P27+P19 -> 862000 | Q95: =+Q93+Q66+Q59+Q53+Q45+Q38+Q27+Q19 -> 870000 | ... BQ95: =+BQ93+BQ66+BQ59+BQ53+BQ45+BQ38+BQ27+BQ19 -> 1208470.8
C96: % of Revenue | D96: =+IFERROR(D95/D$10,) -> 0.80383735 | E96: =+IFERROR(E95/E$10,) -> 0.79515025 | F96: =+IFERROR(F95/F$10,) -> 0.78455886 | G96: =+IFERROR(G95/G$10,) -> 0.79861251 | H96: =+IFERROR(H95/H$10,) -> 0.76421231 | J96: =+IFERROR(J95/J$10,) -> 0.79614949 | K96: =+IFERROR(K95/K$10,) -> 0.84672448 | L96: =+IFERROR(L95/L$10,) -> 0.80537359 | M96: =+IFERROR(M95/M$10,) -> 0.8236557 | N96: =+IFERROR(N95/N$10,) -> 0.76064522 | O96: =+IFERROR(O95/O$10,) -> 0.84783056 | P96: =+IFERROR(P95/P$10,) -> 0.8029809 | Q96: =+IFERROR(Q95/Q$10,) -> 0.79278294 | ... BQ96: =+IFERROR(BQ95/BQ$10,) -> 0.77315166
C98: Operating Margin | D98: =+SUMIFS($J98:$BQ98,$J$7:$BQ$7,D$8) -> 2493600 | E98: =+SUMIFS($J98:$BQ98,$J$7:$BQ$7,E$8) -> 2818200 | F98: =+SUMIFS($J98:$BQ98,$J$7:$BQ$7,F$8) -> 3221516.8 | G98: =+SUMIFS($J98:$BQ98,$J$7:$BQ$7,G$8) -> 3270464.1 | H98: =+SUMIFS($J98:$BQ98,$J$7:$BQ$7,H$8) -> 4467007.6 | J98: =+J10-J95 -> 216000 | K98: =+K10-K95 -> 146700 | L98: =+L10-L95 -> 205000 | M98: =+M10-M95 -> 180700 | N98: =+N10-N95 -> 276000 | O98: =+O10-O95 -> 148000 | P98: =+P10-P95 -> 211500 | Q98: =+Q10-Q95 -> 227400 | ... BQ98: =+BQ10-BQ95 -> 354574.15
C99: YoY % Growth | E99: =+IFERROR(E98/D98-1,) -> 0.13017324 | F99: =+IFERROR(F98/E98-1,) -> 0.1431115 | G99: =+IFERROR(G98/F98-1,) -> 0.015193846 | H99: =+IFERROR(H98/G98-1,) -> 0.36586353
C100: % Margin | D100: =+IFERROR(D98/D$10,) -> 0.19616265 | E100: =+IFERROR(E98/E$10,) -> 0.20484975 | F100: =+IFERROR(F98/F$10,) -> 0.21544114 | G100: =+IFERROR(G98/G$10,) -> 0.20138749 | H100: =+IFERROR(H98/H$10,) -> 0.23578769 | J100: =+IFERROR(J98/J$10,) -> 0.20385051 | K100: =+IFERROR(K98/K$10,) -> 0.15327552 | L100: =+IFERROR(L98/L$10,) -> 0.19462641 | M100: =+IFERROR(M98/M$10,) -> 0.1763443 | N100: =+IFERROR(N98/N$10,) -> 0.23935478 | O100: =+IFERROR(O98/O$10,) -> 0.15216944 | P100: =+IFERROR(P98/P$10,) -> 0.1970191 | Q100: =+IFERROR(Q98/Q$10,) -> 0.20721706 | ... BQ100: =+IFERROR(BQ98/BQ$10,) -> 0.22684834
C102: Non-Operating Expense / (Income) | D102: =+SUMIFS($J102:$BQ102,$J$7:$BQ$7,D$8) -> 29400 | E102: =+SUMIFS($J102:$BQ102,$J$7:$BQ$7,E$8) -> 29300 | F102: =+SUMIFS($J102:$BQ102,$J$7:$BQ$7,F$8) -> 21808.333 | G102: =+SUMIFS($J102:$BQ102,$J$7:$BQ$7,G$8) -> 23427.72 | H102: =+SUMIFS($J102:$BQ102,$J$7:$BQ$7,H$8) -> 24430.848 | J102: =+INDEX('QoE PF Adj. P&L Aug-26'!$D$11:$AI$108,MATCH($C102,'QoE PF Adj. P&L Aug-26'!$C$11:$C$108,0),MATCH(J$8,'QoE PF Adj. P&L Aug-26'!$D$8:$AI$8,0))*1000 -> 2100 | K102: =+INDEX('QoE PF Adj. P&L Aug-26'!$D$11:$AI$108,MATCH($C102,'QoE PF Adj. P&L Aug-26'!$C$11:$C$108,0),MATCH(K$8,'QoE PF Adj. P&L Aug-26'!$D$8:$AI$8,0))*1000 -> 2300 | L102: =+INDEX('QoE PF Adj. P&L Aug-26'!$D$11:$AI$108,MATCH($C102,'QoE PF Adj. P&L Aug-26'!$C$11:$C$108,0),MATCH(L$8,'QoE PF Adj. P&L Aug-26'!$D$8:$AI$8,0))*1000 -> 3000 | M102: =+INDEX('QoE PF Adj. P&L Aug-26'!$D$11:$AI$108,MATCH($C102,'QoE PF Adj. P&L Aug-26'!$C$11:$C$108,0),MATCH(M$8,'QoE PF Adj. P&L Aug-26'!$D$8:$AI$8,0))*1000 -> 2500 | N102: =+INDEX('QoE PF Adj. P&L Aug-26'!$D$11:$AI$108,MATCH($C102,'QoE PF Adj. P&L Aug-26'!$C$11:$C$108,0),MATCH(N$8,'QoE PF Adj. P&L Aug-26'!$D$8:$AI$8,0))*1000 -> 1800 | O102: =+INDEX('QoE PF Adj. P&L Aug-26'!$D$11:$AI$108,MATCH($C102,'QoE PF Adj. P&L Aug-26'!$C$11:$C$108,0),MATCH(O$8,'QoE PF Adj. P&L Aug-26'!$D$8:$AI$8,0))*1000 -> 2400 | P102: =+INDEX('QoE PF Adj. P&L Aug-26'!$D$11:$AI$108,MATCH($C102,'QoE PF Adj. P&L Aug-26'!$C$11:$C$108,0),MATCH(P$8,'QoE PF Adj. P&L Aug-26'!$D$8:$AI$8,0))*1000 -> 2700 | Q102: =+INDEX('QoE PF Adj. P&L Aug-26'!$D$11:$AI$108,MATCH($C102,'QoE PF Adj. P&L Aug-26'!$C$11:$C$108,0),MATCH(Q$8,'QoE PF Adj. P&L Aug-26'!$D$8:$AI$8,0))*1000 -> 2600 | ... AO102: =+INDEX('QoE PF Adj. P&L Aug-26'!$D$11:$AI$108,MATCH($C102,'QoE PF Adj. P&L Aug-26'!$C$11:$C$108,0),MATCH(AO$8,'QoE PF Adj. P&L Aug-26'!$D$8:$AI$8,0))*1000 -> 2800 | AP102: =+SUMIFS('Sep - Nov P&L'!I:I,'Sep - Nov P&L'!$D:$D,$C102) -> 0 | AQ102: =+SUMIFS('Sep - Nov P&L'!J:J,'Sep - Nov P&L'!$D:$D,$C102) -> 0 | AR102: =+SUMIFS('Sep - Nov P&L'!K:K,'Sep - Nov P&L'!$D:$D,$C102) -> 0 | AS102: =+AS210 -> 1908.3333 | AT102: =+AT210 -> 1915.0125 | AU102: =+AU210 -> 1921.715 | AV102: =+AV210 -> 1928.441 | AW102: =+AW210 -> 1935.1906 | AX102: =+AX210 -> 1941.9638 | AY102: =+AY210 -> 1948.7606 | AZ102: =+AZ210 -> 1955.5813 | ... BQ102: =+BQ210 -> 2075.2541
C103: Non-Operating Income / (Expense) | D103: =+SUMIFS($J103:$BQ103,$J$7:$BQ$7,D$8) -> 11300 | E103: =+SUMIFS($J103:$BQ103,$J$7:$BQ$7,E$8) -> 11800 | F103: =+SUMIFS($J103:$BQ103,$J$7:$BQ$7,F$8) -> 7558.3333 | G103: =+SUMIFS($J103:$BQ103,$J$7:$BQ$7,G$8) -> 8082.0518 | H103: =+SUMIFS($J103:$BQ103,$J$7:$BQ$7,H$8) -> 8428.1091 | J103: =+INDEX('QoE PF Adj. P&L Aug-26'!$D$11:$AI$108,MATCH($C103,'QoE PF Adj. P&L Aug-26'!$C$11:$C$108,0),MATCH(J$8,'QoE PF Adj. P&L Aug-26'!$D$8:$AI$8,0))*1000 -> 900 | K103: =+INDEX('QoE PF Adj. P&L Aug-26'!$D$11:$AI$108,MATCH($C103,'QoE PF Adj. P&L Aug-26'!$C$11:$C$108,0),MATCH(K$8,'QoE PF Adj. P&L Aug-26'!$D$8:$AI$8,0))*1000 -> 800 | L103: =+INDEX('QoE PF Adj. P&L Aug-26'!$D$11:$AI$108,MATCH($C103,'QoE PF Adj. P&L Aug-26'!$C$11:$C$108,0),MATCH(L$8,'QoE PF Adj. P&L Aug-26'!$D$8:$AI$8,0))*1000 -> 1000 | M103: =+INDEX('QoE PF Adj. P&L Aug-26'!$D$11:$AI$108,MATCH($C103,'QoE PF Adj. P&L Aug-26'!$C$11:$C$108,0),MATCH(M$8,'QoE PF Adj. P&L Aug-26'!$D$8:$AI$8,0))*1000 -> 700 | N103: =+INDEX('QoE PF Adj. P&L Aug-26'!$D$11:$AI$108,MATCH($C103,'QoE PF Adj. P&L Aug-26'!$C$11:$C$108,0),MATCH(N$8,'QoE PF Adj. P&L Aug-26'!$D$8:$AI$8,0))*1000 -> 900 | O103: =+INDEX('QoE PF Adj. P&L Aug-26'!$D$11:$AI$108,MATCH($C103,'QoE PF Adj. P&L Aug-26'!$C$11:$C$108,0),MATCH(O$8,'QoE PF Adj. P&L Aug-26'!$D$8:$AI$8,0))*1000 -> 1000 | P103: =+INDEX('QoE PF Adj. P&L Aug-26'!$D$11:$AI$108,MATCH($C103,'QoE PF Adj. P&L Aug-26'!$C$11:$C$108,0),MATCH(P$8,'QoE PF Adj. P&L Aug-26'!$D$8:$AI$8,0))*1000 -> 700 | Q103: =+INDEX('QoE PF Adj. P&L Aug-26'!$D$11:$AI$108,MATCH($C103,'QoE PF Adj. P&L Aug-26'!$C$11:$C$108,0),MATCH(Q$8,'QoE PF Adj. P&L Aug-26'!$D$8:$AI$8,0))*1000 -> 1100 | ... AO103: =+INDEX('QoE PF Adj. P&L Aug-26'!$D$11:$AI$108,MATCH($C103,'QoE PF Adj. P&L Aug-26'!$C$11:$C$108,0),MATCH(AO$8,'QoE PF Adj. P&L Aug-26'!$D$8:$AI$8,0))*1000 -> 700 | AP103: =+SUMIFS('Sep - Nov P&L'!I:I,'Sep - Nov P&L'!$D:$D,$C103) -> 0 | AQ103: =+SUMIFS('Sep - Nov P&L'!J:J,'Sep - Nov P&L'!$D:$D,$C103) -> 0 | AR103: =+SUMIFS('Sep - Nov P&L'!K:K,'Sep - Nov P&L'!$D:$D,$C103) -> 0 | AS103: =+AS211 -> 658.33333 | AT103: =+AT211 -> 660.6375 | AU103: =+AU211 -> 662.94973 | AV103: =+AV211 -> 665.27006 | AW103: =+AW211 -> 667.5985 | AX103: =+AX211 -> 669.9351 | AY103: =+AY211 -> 672.27987 | AZ103: =+AZ211 -> 674.63285 | ... BQ103: =+BQ211 -> 715.91735
A105: x | C105: EBITDA | D105: =+SUMIFS($J105:$BQ105,$J$7:$BQ$7,D$8) -> 2475500 | E105: =+SUMIFS($J105:$BQ105,$J$7:$BQ$7,E$8) -> 2800700 | F105: =+SUMIFS($J105:$BQ105,$J$7:$BQ$7,F$8) -> 3207266.8 | G105: =+SUMIFS($J105:$BQ105,$J$7:$BQ$7,G$8) -> 3255118.4 | H105: =+SUMIFS($J105:$BQ105,$J$7:$BQ$7,H$8) -> 4451004.9 | J105: =+J98-J102+J103 -> 214800 | K105: =+K98-K102+K103 -> 145200 | L105: =+L98-L102+L103 -> 203000 | M105: =+M98-M102+M103 -> 178900 | N105: =+N98-N102+N103 -> 275100 | O105: =+O98-O102+O103 -> 146600 | P105: =+P98-P102+P103 -> 209500 | Q105: =+Q98-Q102+Q103 -> 225900 | ... BQ105: =+BQ98-BQ102+BQ103 -> 353214.81
C106: YoY % Growth | E106: =+IFERROR(E105/D105-1,) -> 0.1313674 | F106: =+IFERROR(F105/E105-1,) -> 0.14516615 | G106: =+IFERROR(G105/F105-1,) -> 0.014919732 | H106: =+IFERROR(H105/G105-1,) -> 0.36738647
C107: % Margin | D107: =+IFERROR(D105/D$10,) -> 0.19473879 | E107: =+IFERROR(E105/E$10,) -> 0.20357771 | F107: =+IFERROR(F105/F$10,) -> 0.21448816 | G107: =+IFERROR(G105/G$10,) -> 0.20044254 | H107: =+IFERROR(H105/H$10,) -> 0.234943 | J107: =+IFERROR(J105/J$10,) -> 0.20271801 | K107: =+IFERROR(K105/K$10,) -> 0.15170829 | L107: =+IFERROR(L105/L$10,) -> 0.19272762 | M107: =+IFERROR(M105/M$10,) -> 0.17458768 | N107: =+IFERROR(N105/N$10,) -> 0.23857428 | O107: =+IFERROR(O105/O$10,) -> 0.15073 | P107: =+IFERROR(P105/P$10,) -> 0.19515603 | Q107: =+IFERROR(Q105/Q$10,) -> 0.20585019 | ... BQ107: =+IFERROR(BQ105/BQ$10,) -> 0.22597867
C109: Other Expense
C110: Depreciation & Amortization Expense | D110: =+SUMIFS($J110:$BQ110,$J$7:$BQ$7,D$8) -> 248500 | E110: =+SUMIFS($J110:$BQ110,$J$7:$BQ$7,E$8) -> 261500 | F110: =+SUMIFS($J110:$BQ110,$J$7:$BQ$7,F$8) -> 188075 | G110: =+SUMIFS($J110:$BQ110,$J$7:$BQ$7,G$8) -> 196500 | H110: =+SUMIFS($J110:$BQ110,$J$7:$BQ$7,H$8) -> 196500 | J110: =+INDEX('QoE PF Adj. P&L Aug-26'!$D$111:$AI$118,MATCH($C110,'QoE PF Adj. P&L Aug-26'!$C$111:$C$118,0),MATCH(J$8,'QoE PF Adj. P&L Aug-26'!$D$8:$AI$8,0))*1000 -> 17800 | K110: =+INDEX('QoE PF Adj. P&L Aug-26'!$D$111:$AI$118,MATCH($C110,'QoE PF Adj. P&L Aug-26'!$C$111:$C$118,0),MATCH(K$8,'QoE PF Adj. P&L Aug-26'!$D$8:$AI$8,0))*1000 -> 17800 | L110: =+INDEX('QoE PF Adj. P&L Aug-26'!$D$111:$AI$118,MATCH($C110,'QoE PF Adj. P&L Aug-26'!$C$111:$C$118,0),MATCH(L$8,'QoE PF Adj. P&L Aug-26'!$D$8:$AI$8,0))*1000 -> 22900 | M110: =+INDEX('QoE PF Adj. P&L Aug-26'!$D$111:$AI$118,MATCH($C110,'QoE PF Adj. P&L Aug-26'!$C$111:$C$118,0),MATCH(M$8,'QoE PF Adj. P&L Aug-26'!$D$8:$AI$8,0))*1000 -> 18300 | N110: =+INDEX('QoE PF Adj. P&L Aug-26'!$D$111:$AI$118,MATCH($C110,'QoE PF Adj. P&L Aug-26'!$C$111:$C$118,0),MATCH(N$8,'QoE PF Adj. P&L Aug-26'!$D$8:$AI$8,0))*1000 -> 18400 | O110: =+INDEX('QoE PF Adj. P&L Aug-26'!$D$111:$AI$118,MATCH($C110,'QoE PF Adj. P&L Aug-26'!$C$111:$C$118,0),MATCH(O$8,'QoE PF Adj. P&L Aug-26'!$D$8:$AI$8,0))*1000 -> 23400 | P110: =+INDEX('QoE PF Adj. P&L Aug-26'!$D$111:$AI$118,MATCH($C110,'QoE PF Adj. P&L Aug-26'!$C$111:$C$118,0),MATCH(P$8,'QoE PF Adj. P&L Aug-26'!$D$8:$AI$8,0))*1000 -> 21200 | Q110: =+INDEX('QoE PF Adj. P&L Aug-26'!$D$111:$AI$118,MATCH($C110,'QoE PF Adj. P&L Aug-26'!$C$111:$C$118,0),MATCH(Q$8,'QoE PF Adj. P&L Aug-26'!$D$8:$AI$8,0))*1000 -> 21900 | ... AO110: =+INDEX('QoE PF Adj. P&L Aug-26'!$D$111:$AI$118,MATCH($C110,'QoE PF Adj. P&L Aug-26'!$C$111:$C$118,0),MATCH(AO$8,'QoE PF Adj. P&L Aug-26'!$D$8:$AI$8,0))*1000 -> 20900 | AP110: =+SUMIFS('Sep - Nov P&L'!I:I,'Sep - Nov P&L'!$D:$D,$C110) -> 0 | AQ110: =+SUMIFS('Sep - Nov P&L'!J:J,'Sep - Nov P&L'!$D:$D,$C110) -> 0 | AR110: =+SUMIFS('Sep - Nov P&L'!K:K,'Sep - Nov P&L'!$D:$D,$C110) -> 0 | AS110: =+AVERAGE(AG110:AR110) -> 16375 | AT110: =+AS110 -> 16375 | AU110: =+AT110 -> 16375 | AV110: =+AU110 -> 16375 | AW110: =+AV110 -> 16375 | AX110: =+AW110 -> 16375 | AY110: =+AX110 -> 16375 | AZ110: =+AY110 -> 16375 | BA110: =+AZ110 -> 16375 | ... BQ110: =+BP110 -> 16375
C111: Interest Income | D111: =+SUMIFS($J111:$BQ111,$J$7:$BQ$7,D$8) -> -5100 | E111: =+SUMIFS($J111:$BQ111,$J$7:$BQ$7,E$8) -> -5400 | F111: =+SUMIFS($J111:$BQ111,$J$7:$BQ$7,F$8) -> -5011.8917 | G111: =+SUMIFS($J111:$BQ111,$J$7:$BQ$7,G$8) -> -5087.9 | H111: =+SUMIFS($J111:$BQ111,$J$7:$BQ$7,H$8) -> -5087.9 | J111: =+INDEX('QoE PF Adj. P&L Aug-26'!$D$111:$AI$118,MATCH($C111,'QoE PF Adj. P&L Aug-26'!$C$111:$C$118,0),MATCH(J$8,'QoE PF Adj. P&L Aug-26'!$D$8:$AI$8,0))*1000 -> -400 | K111: =+INDEX('QoE PF Adj. P&L Aug-26'!$D$111:$AI$118,MATCH($C111,'QoE PF Adj. P&L Aug-26'!$C$111:$C$118,0),MATCH(K$8,'QoE PF Adj. P&L Aug-26'!$D$8:$AI$8,0))*1000 -> -500 | L111: =+INDEX('QoE PF Adj. P&L Aug-26'!$D$111:$AI$118,MATCH($C111,'QoE PF Adj. P&L Aug-26'!$C$111:$C$118,0),MATCH(L$8,'QoE PF Adj. P&L Aug-26'!$D$8:$AI$8,0))*1000 -> -400 | M111: =+INDEX('QoE PF Adj. P&L Aug-26'!$D$111:$AI$118,MATCH($C111,'QoE PF Adj. P&L Aug-26'!$C$111:$C$118,0),MATCH(M$8,'QoE PF Adj. P&L Aug-26'!$D$8:$AI$8,0))*1000 -> -400 | N111: =+INDEX('QoE PF Adj. P&L Aug-26'!$D$111:$AI$118,MATCH($C111,'QoE PF Adj. P&L Aug-26'!$C$111:$C$118,0),MATCH(N$8,'QoE PF Adj. P&L Aug-26'!$D$8:$AI$8,0))*1000 -> -400 | O111: =+INDEX('QoE PF Adj. P&L Aug-26'!$D$111:$AI$118,MATCH($C111,'QoE PF Adj. P&L Aug-26'!$C$111:$C$118,0),MATCH(O$8,'QoE PF Adj. P&L Aug-26'!$D$8:$AI$8,0))*1000 -> -400 | P111: =+INDEX('QoE PF Adj. P&L Aug-26'!$D$111:$AI$118,MATCH($C111,'QoE PF Adj. P&L Aug-26'!$C$111:$C$118,0),MATCH(P$8,'QoE PF Adj. P&L Aug-26'!$D$8:$AI$8,0))*1000 -> -400 | Q111: =+INDEX('QoE PF Adj. P&L Aug-26'!$D$111:$AI$118,MATCH($C111,'QoE PF Adj. P&L Aug-26'!$C$111:$C$118,0),MATCH(Q$8,'QoE PF Adj. P&L Aug-26'!$D$8:$AI$8,0))*1000 -> -500 | ... AO111: =+INDEX('QoE PF Adj. P&L Aug-26'!$D$111:$AI$118,MATCH($C111,'QoE PF Adj. P&L Aug-26'!$C$111:$C$118,0),MATCH(AO$8,'QoE PF Adj. P&L Aug-26'!$D$8:$AI$8,0))*1000 -> -400 | AP111: =+SUMIFS('Sep - Nov P&L'!I:I,'Sep - Nov P&L'!$D:$D,$C111) -> -407.27 | AQ111: =+SUMIFS('Sep - Nov P&L'!J:J,'Sep - Nov P&L'!$D:$D,$C111) -> -429.84 | AR111: =+SUMIFS('Sep - Nov P&L'!K:K,'Sep - Nov P&L'!$D:$D,$C111) -> -450.79 | AS111: =+AVERAGE(AG111:AR111) -> -423.99167 | AT111: =+AS111 -> -423.99167 | AU111: =+AT111 -> -423.99167 | AV111: =+AU111 -> -423.99167 | AW111: =+AV111 -> -423.99167 | AX111: =+AW111 -> -423.99167 | AY111: =+AX111 -> -423.99167 | AZ111: =+AY111 -> -423.99167 | BA111: =+AZ111 -> -423.99167 | ... BQ111: =+BP111 -> -423.99167
C112: Interest Expense | D112: =+SUMIFS($J112:$BQ112,$J$7:$BQ$7,D$8) -> 34600 | E112: =+SUMIFS($J112:$BQ112,$J$7:$BQ$7,E$8) -> 34000 | F112: =+SUMIFS($J112:$BQ112,$J$7:$BQ$7,F$8) -> 35458.36 | G112: =+SUMIFS($J112:$BQ112,$J$7:$BQ$7,G$8) -> 35684.64 | H112: =+SUMIFS($J112:$BQ112,$J$7:$BQ$7,H$8) -> 35684.64 | J112: =+INDEX('QoE PF Adj. P&L Aug-26'!$D$111:$AI$118,MATCH($C112,'QoE PF Adj. P&L Aug-26'!$C$111:$C$118,0),MATCH(J$8,'QoE PF Adj. P&L Aug-26'!$D$8:$AI$8,0))*1000 -> 2800 | K112: =+INDEX('QoE PF Adj. P&L Aug-26'!$D$111:$AI$118,MATCH($C112,'QoE PF Adj. P&L Aug-26'!$C$111:$C$118,0),MATCH(K$8,'QoE PF Adj. P&L Aug-26'!$D$8:$AI$8,0))*1000 -> 2800 | L112: =+INDEX('QoE PF Adj. P&L Aug-26'!$D$111:$AI$118,MATCH($C112,'QoE PF Adj. P&L Aug-26'!$C$111:$C$118,0),MATCH(L$8,'QoE PF Adj. P&L Aug-26'!$D$8:$AI$8,0))*1000 -> 3100 | M112: =+INDEX('QoE PF Adj. P&L Aug-26'!$D$111:$AI$118,MATCH($C112,'QoE PF Adj. P&L Aug-26'!$C$111:$C$118,0),MATCH(M$8,'QoE PF Adj. P&L Aug-26'!$D$8:$AI$8,0))*1000 -> 2700 | N112: =+INDEX('QoE PF Adj. P&L Aug-26'!$D$111:$AI$118,MATCH($C112,'QoE PF Adj. P&L Aug-26'!$C$111:$C$118,0),MATCH(N$8,'QoE PF Adj. P&L Aug-26'!$D$8:$AI$8,0))*1000 -> 3200 | O112: =+INDEX('QoE PF Adj. P&L Aug-26'!$D$111:$AI$118,MATCH($C112,'QoE PF Adj. P&L Aug-26'!$C$111:$C$118,0),MATCH(O$8,'QoE PF Adj. P&L Aug-26'!$D$8:$AI$8,0))*1000 -> 3200 | P112: =+INDEX('QoE PF Adj. P&L Aug-26'!$D$111:$AI$118,MATCH($C112,'QoE PF Adj. P&L Aug-26'!$C$111:$C$118,0),MATCH(P$8,'QoE PF Adj. P&L Aug-26'!$D$8:$AI$8,0))*1000 -> 2800 | Q112: =+INDEX('QoE PF Adj. P&L Aug-26'!$D$111:$AI$118,MATCH($C112,'QoE PF Adj. P&L Aug-26'!$C$111:$C$118,0),MATCH(Q$8,'QoE PF Adj. P&L Aug-26'!$D$8:$AI$8,0))*1000 -> 2800 | ... AO112: =+INDEX('QoE PF Adj. P&L Aug-26'!$D$111:$AI$118,MATCH($C112,'QoE PF Adj. P&L Aug-26'!$C$111:$C$118,0),MATCH(AO$8,'QoE PF Adj. P&L Aug-26'!$D$8:$AI$8,0))*1000 -> 2600 | AP112: =+SUMIFS('Sep - Nov P&L'!I:I,'Sep - Nov P&L'!$D:$D,$C112) -> 3128.52 | AQ112: =+SUMIFS('Sep - Nov P&L'!J:J,'Sep - Nov P&L'!$D:$D,$C112) -> 3152.9 | AR112: =+SUMIFS('Sep - Nov P&L'!K:K,'Sep - Nov P&L'!$D:$D,$C112) -> 2803.22 | AS112: =+AVERAGE(AG112:AR112) -> 2973.72 | AT112: =+AS112 -> 2973.72 | AU112: =+AT112 -> 2973.72 | AV112: =+AU112 -> 2973.72 | AW112: =+AV112 -> 2973.72 | AX112: =+AW112 -> 2973.72 | AY112: =+AX112 -> 2973.72 | AZ112: =+AY112 -> 2973.72 | BA112: =+AZ112 -> 2973.72 | ... BQ112: =+BP112 -> 2973.72
C113: Other Income - Non RCM Revenue | D113: =+SUMIFS($J113:$BQ113,$J$7:$BQ$7,D$8) -> -16500 | E113: =+SUMIFS($J113:$BQ113,$J$7:$BQ$7,E$8) -> -18400 | F113: =+SUMIFS($J113:$BQ113,$J$7:$BQ$7,F$8) -> -12925 | G113: =+SUMIFS($J113:$BQ113,$J$7:$BQ$7,G$8) -> -13500 | H113: =+SUMIFS($J113:$BQ113,$J$7:$BQ$7,H$8) -> -13500 | J113: =+INDEX('QoE PF Adj. P&L Aug-26'!$D$111:$AI$118,MATCH($C113,'QoE PF Adj. P&L Aug-26'!$C$111:$C$118,0),MATCH(J$8,'QoE PF Adj. P&L Aug-26'!$D$8:$AI$8,0))*1000 -> -1300 | K113: =+INDEX('QoE PF Adj. P&L Aug-26'!$D$111:$AI$118,MATCH($C113,'QoE PF Adj. P&L Aug-26'!$C$111:$C$118,0),MATCH(K$8,'QoE PF Adj. P&L Aug-26'!$D$8:$AI$8,0))*1000 -> -1500 | L113: =+INDEX('QoE PF Adj. P&L Aug-26'!$D$111:$AI$118,MATCH($C113,'QoE PF Adj. P&L Aug-26'!$C$111:$C$118,0),MATCH(L$8,'QoE PF Adj. P&L Aug-26'!$D$8:$AI$8,0))*1000 -> -1300 | M113: =+INDEX('QoE PF Adj. P&L Aug-26'!$D$111:$AI$118,MATCH($C113,'QoE PF Adj. P&L Aug-26'!$C$111:$C$118,0),MATCH(M$8,'QoE PF Adj. P&L Aug-26'!$D$8:$AI$8,0))*1000 -> -1300 | N113: =+INDEX('QoE PF Adj. P&L Aug-26'!$D$111:$AI$118,MATCH($C113,'QoE PF Adj. P&L Aug-26'!$C$111:$C$118,0),MATCH(N$8,'QoE PF Adj. P&L Aug-26'!$D$8:$AI$8,0))*1000 -> -1500 | O113: =+INDEX('QoE PF Adj. P&L Aug-26'!$D$111:$AI$118,MATCH($C113,'QoE PF Adj. P&L Aug-26'!$C$111:$C$118,0),MATCH(O$8,'QoE PF Adj. P&L Aug-26'!$D$8:$AI$8,0))*1000 -> -1300 | P113: =+INDEX('QoE PF Adj. P&L Aug-26'!$D$111:$AI$118,MATCH($C113,'QoE PF Adj. P&L Aug-26'!$C$111:$C$118,0),MATCH(P$8,'QoE PF Adj. P&L Aug-26'!$D$8:$AI$8,0))*1000 -> -1300 | Q113: =+INDEX('QoE PF Adj. P&L Aug-26'!$D$111:$AI$118,MATCH($C113,'QoE PF Adj. P&L Aug-26'!$C$111:$C$118,0),MATCH(Q$8,'QoE PF Adj. P&L Aug-26'!$D$8:$AI$8,0))*1000 -> -1400 | ... AO113: =+INDEX('QoE PF Adj. P&L Aug-26'!$D$111:$AI$118,MATCH($C113,'QoE PF Adj. P&L Aug-26'!$C$111:$C$118,0),MATCH(AO$8,'QoE PF Adj. P&L Aug-26'!$D$8:$AI$8,0))*1000 -> -1500 | AP113: =+SUMIFS('Sep - Nov P&L'!I:I,'Sep - Nov P&L'!$D:$D,$C113) -> 0 | AQ113: =+SUMIFS('Sep - Nov P&L'!J:J,'Sep - Nov P&L'!$D:$D,$C113) -> 0 | AR113: =+SUMIFS('Sep - Nov P&L'!K:K,'Sep - Nov P&L'!$D:$D,$C113) -> 0 | AS113: =+AVERAGE(AG113:AR113) -> -1125 | AT113: =+AS113 -> -1125 | AU113: =+AT113 -> -1125 | AV113: =+AU113 -> -1125 | AW113: =+AV113 -> -1125 | AX113: =+AW113 -> -1125 | AY113: =+AX113 -> -1125 | AZ113: =+AY113 -> -1125 | BA113: =+AZ113 -> -1125 | ... BQ113: =+BP113 -> -1125
C115: EBT | D115: =+SUMIFS($J115:$BQ115,$J$7:$BQ$7,D$8) -> 2214000 | E115: =+SUMIFS($J115:$BQ115,$J$7:$BQ$7,E$8) -> 2529000 | F115: =+SUMIFS($J115:$BQ115,$J$7:$BQ$7,F$8) -> 3001670.4 | G115: =+SUMIFS($J115:$BQ115,$J$7:$BQ$7,G$8) -> 3041521.7 | H115: =+SUMIFS($J115:$BQ115,$J$7:$BQ$7,H$8) -> 4237408.1 | J115: =+J105-SUM(J110:J113) -> 195900 | K115: =+K105-SUM(K110:K113) -> 126600 | L115: =+L105-SUM(L110:L113) -> 178700 | M115: =+M105-SUM(M110:M113) -> 159600 | N115: =+N105-SUM(N110:N113) -> 255400 | O115: =+O105-SUM(O110:O113) -> 121700 | P115: =+P105-SUM(P110:P113) -> 187200 | Q115: =+Q105-SUM(Q110:Q113) -> 203100 | ... BQ115: =+BQ105-SUM(BQ110:BQ113) -> 335415.08
C117: check | D117: =+D105-SUM('QoE PF Adj. P&L Aug-26'!D108:O108)*1000 -> 0 | E117: =+E105-SUM('QoE PF Adj. P&L Aug-26'!P108:AA108)*1000 -> 0 | J117: =+J105-'QoE PF Adj. P&L Aug-26'!D108*1000 -> 0 | K117: =+K105-'QoE PF Adj. P&L Aug-26'!E108*1000 -> 0 | L117: =+L105-'QoE PF Adj. P&L Aug-26'!F108*1000 -> 0 | M117: =+M105-'QoE PF Adj. P&L Aug-26'!G108*1000 -> 0 | N117: =+N105-'QoE PF Adj. P&L Aug-26'!H108*1000 -> 0 | O117: =+O105-'QoE PF Adj. P&L Aug-26'!I108*1000 -> 0 | P117: =+P105-'QoE PF Adj. P&L Aug-26'!J108*1000 -> 0 | Q117: =+Q105-'QoE PF Adj. P&L Aug-26'!K108*1000 -> 0 | ... AO117: =+AO105-'QoE PF Adj. P&L Aug-26'!AI108*1000 -> 0
A120: Assumptions
C121: Monthly inflation – fixed cost lines (applied from Jan-27) | D121: 0.0035 | E121: <-- hardcoded input
...

Sheet Separate Line Item Builds
A2: Orivane Clinical Laboratories, LLC
A3: Separate Line Item Builds
A5: Projections from Dec-26
J7: =+YEAR(J8) -> 2024 | K7: =+YEAR(K8) -> 2024 | L7: =+YEAR(L8) -> 2024 | M7: =+YEAR(M8) -> 2024 | N7: =+YEAR(N8) -> 2024 | O7: =+YEAR(O8) -> 2024 | P7: =+YEAR(P8) -> 2024 | Q7: =+YEAR(Q8) -> 2024 | ... BQ7: =+YEAR(BQ8) -> 2028
C8: $ in actual | D8: 2024 | E8: 2025 | F8: 2026 | G8: 2027 | H8: 2028 | J8: 45322 | K8: =+EOMONTH(J8,1) -> 45351 | L8: =+EOMONTH(K8,1) -> 45382 | M8: =+EOMONTH(L8,1) -> 45412 | N8: =+EOMONTH(M8,1) -> 45443 | O8: =+EOMONTH(N8,1) -> 45473 | P8: =+EOMONTH(O8,1) -> 45504 | Q8: =+EOMONTH(P8,1) -> 45535 | R8: =+EOMONTH(Q8,1) -> 45565 | ... BQ8: =+EOMONTH(BP8,1) -> 47118
A10: S&W
C11: Salaries & Wages (current staff) | D11: =+SUMIFS($J11:$BQ11,$J$7:$BQ$7,D$8) -> 3317600 | E11: =+SUMIFS($J11:$BQ11,$J$7:$BQ$7,E$8) -> 3509800 | F11: =+SUMIFS($J11:$BQ11,$J$7:$BQ$7,F$8) -> 3700188.9 | G11: =+SUMIFS($J11:$BQ11,$J$7:$BQ$7,G$8) -> 3828925.2 | H11: =+SUMIFS($J11:$BQ11,$J$7:$BQ$7,H$8) -> 3943792.9 | J11: =+'Historical & Projected P&L'!J15 -> 277600 | K11: =+'Historical & Projected P&L'!K15 -> 272100 | L11: =+'Historical & Projected P&L'!L15 -> 278100 | M11: =+'Historical & Projected P&L'!M15 -> 280500 | N11: =+'Historical & Projected P&L'!N15 -> 274300 | O11: =+'Historical & Projected P&L'!O15 -> 276000 | P11: =+'Historical & Projected P&L'!P15 -> 277800 | Q11: =+'Historical & Projected P&L'!Q15 -> 276200 | ... AR11: =+'Historical & Projected P&L'!AR15 -> 309783.59 | AS11: =+AR11*(1+AS$24) -> 309783.59 | AT11: =+AS11*(1+AT$24) -> 319077.1 | AU11: =+AT11*(1+AU$24) -> 319077.1 | AV11: =+AU11*(1+AV$24) -> 319077.1 | AW11: =+AV11*(1+AW$24) -> 319077.1 | AX11: =+AW11*(1+AX$24) -> 319077.1 | AY11: =+AX11*(1+AY$24) -> 319077.1 | AZ11: =+AY11*(1+AZ$24) -> 319077.1 | ... BQ11: =+BP11*(1+BQ$24) -> 328649.41
C12: New Hires (annual cost in col B; formulas start in the hire month)
B13: 180000 | C13: IT Lead ($180K, Mar-27) | D13: =+SUMIFS($J13:$BQ13,$J$7:$BQ$7,D$8) -> 0 | E13: =+SUMIFS($J13:$BQ13,$J$7:$BQ$7,E$8) -> 0 | F13: =+SUMIFS($J13:$BQ13,$J$7:$BQ$7,F$8) -> 0 | G13: =+SUMIFS($J13:$BQ13,$J$7:$BQ$7,G$8) -> 150000 | H13: =+SUMIFS($J13:$BQ13,$J$7:$BQ$7,H$8) -> 180000 | AV13: =+$B13/12 -> 15000 | AW13: =+$B13/12 -> 15000 | AX13: =+$B13/12 -> 15000 | AY13: =+$B13/12 -> 15000 | AZ13: =+$B13/12 -> 15000 | BA13: =+$B13/12 -> 15000 | BB13: =+$B13/12 -> 15000 | BC13: =+$B13/12 -> 15000 | ... BQ13: =+$B13/12 -> 15000
B14: 75000 | C14: Inventory Coordinator ($75K, Mar-27) | D14: =+SUMIFS($J14:$BQ14,$J$7:$BQ$7,D$8) -> 0 | E14: =+SUMIFS($J14:$BQ14,$J$7:$BQ$7,E$8) -> 0 | F14: =+SUMIFS($J14:$BQ14,$J$7:$BQ$7,F$8) -> 0 | G14: =+SUMIFS($J14:$BQ14,$J$7:$BQ$7,G$8) -> 62500 | H14: =+SUMIFS($J14:$BQ14,$J$7:$BQ$7,H$8) -> 75000 | AV14: =+$B14/12 -> 6250 | AW14: =+$B14/12 -> 6250 | AX14: =+$B14/12 -> 6250 | AY14: =+$B14/12 -> 6250 | AZ14: =+$B14/12 -> 6250 | BA14: =+$B14/12 -> 6250 | BB14: =+$B14/12 -> 6250 | BC14: =+$B14/12 -> 6250 | ... BQ14: =+$B14/12 -> 6250
B15: 110000 | C15: Processing / Shift Supervisor ($110K, Feb-27) | D15: =+SUMIFS($J15:$BQ15,$J$7:$BQ$7,D$8) -> 0 | E15: =+SUMIFS($J15:$BQ15,$J$7:$BQ$7,E$8) -> 0 | F15: =+SUMIFS($J15:$BQ15,$J$7:$BQ$7,F$8) -> 0 | G15: =+SUMIFS($J15:$BQ15,$J$7:$BQ$7,G$8) -> 100833.33 | H15: =+SUMIFS($J15:$BQ15,$J$7:$BQ$7,H$8) -> 110000 | AU15: =+$B15/12 -> 9166.6667 | AV15: =+$B15/12 -> 9166.6667 | AW15: =+$B15/12 -> 9166.6667 | AX15: =+$B15/12 -> 9166.6667 | AY15: =+$B15/12 -> 9166.6667 | AZ15: =+$B15/12 -> 9166.6667 | BA15: =+$B15/12 -> 9166.6667 | BB15: =+$B15/12 -> 9166.6667 | ... BQ15: =+$B15/12 -> 9166.6667
B16: 200000 | C16: Lab Manager ($200K, Dec-26) | D16: =+SUMIFS($J16:$BQ16,$J$7:$BQ$7,D$8) -> 0 | E16: =+SUMIFS($J16:$BQ16,$J$7:$BQ$7,E$8) -> 0 | F16: =+SUMIFS($J16:$BQ16,$J$7:$BQ$7,F$8) -> 16666.667 | G16: =+SUMIFS($J16:$BQ16,$J$7:$BQ$7,G$8) -> 200000 | H16: =+SUMIFS($J16:$BQ16,$J$7:$BQ$7,H$8) -> 200000 | AS16: =+$B16/12 -> 16666.667 | AT16: =+$B16/12 -> 16666.667 | AU16: =+$B16/12 -> 16666.667 | AV16: =+$B16/12 -> 16666.667 | AW16: =+$B16/12 -> 16666.667 | AX16: =+$B16/12 -> 16666.667 | AY16: =+$B16/12 -> 16666.667 | AZ16: =+$B16/12 -> 16666.667 | ... BQ16: =+$B16/12 -> 16666.667
C17: Medical Director – working through year-end then leaving | D17: =+SUMIFS($J17:$BQ17,$J$7:$BQ$7,D$8) -> 0 | E17: =+SUMIFS($J17:$BQ17,$J$7:$BQ$7,E$8) -> 0 | F17: =+SUMIFS($J17:$BQ17,$J$7:$BQ$7,F$8) -> 0 | G17: =+SUMIFS($J17:$BQ17,$J$7:$BQ$7,G$8) -> -150000 | H17: =+SUMIFS($J17:$BQ17,$J$7:$BQ$7,H$8) -> -150000 | AT17: =-150000/12 -> -12500 | AU17: =-150000/12 -> -12500 | AV17: =-150000/12 -> -12500 | AW17: =-150000/12 -> -12500 | AX17: =-150000/12 -> -12500 | AY17: =-150000/12 -> -12500 | AZ17: =-150000/12 -> -12500 | BA17: =-150000/12 -> -12500 | ... BQ17: =-150000/12 -> -12500
B18: 50000 | C18: Courier 1 ($50K, Feb-27) | D18: =+SUMIFS($J18:$BQ18,$J$7:$BQ$7,D$8) -> 0 | E18: =+SUMIFS($J18:$BQ18,$J$7:$BQ$7,E$8) -> 0 | F18: =+SUMIFS($J18:$BQ18,$J$7:$BQ$7,F$8) -> 0 | G18: =+SUMIFS($J18:$BQ18,$J$7:$BQ$7,G$8) -> 45833.333 | H18: =+SUMIFS($J18:$BQ18,$J$7:$BQ$7,H$8) -> 50000 | AU18: =+$B18/12 -> 4166.6667 | AV18: =+$B18/12 -> 4166.6667 | AW18: =+$B18/12 -> 4166.6667 | AX18: =+$B18/12 -> 4166.6667 | AY18: =+$B18/12 -> 4166.6667 | AZ18: =+$B18/12 -> 4166.6667 | BA18: =+$B18/12 -> 4166.6667 | BB18: =+$B18/12 -> 4166.6667 | ... BQ18: =+$B18/12 -> 4166.6667
B19: 50000 | C19: Courier 2 ($50K, Feb-27) | D19: =+SUMIFS($J19:$BQ19,$J$7:$BQ$7,D$8) -> 0 | E19: =+SUMIFS($J19:$BQ19,$J$7:$BQ$7,E$8) -> 0 | F19: =+SUMIFS($J19:$BQ19,$J$7:$BQ$7,F$8) -> 0 | G19: =+SUMIFS($J19:$BQ19,$J$7:$BQ$7,G$8) -> 45833.333 | H19: =+SUMIFS($J19:$BQ19,$J$7:$BQ$7,H$8) -> 50000 | AU19: =+$B19/12 -> 4166.6667 | AV19: =+$B19/12 -> 4166.6667 | AW19: =+$B19/12 -> 4166.6667 | AX19: =+$B19/12 -> 4166.6667 | AY19: =+$B19/12 -> 4166.6667 | AZ19: =+$B19/12 -> 4166.6667 | BA19: =+$B19/12 -> 4166.6667 | BB19: =+$B19/12 -> 4166.6667 | ... BQ19: =+$B19/12 -> 4166.6667
B20: 52000 | C20: New Accessioners | D20: =+SUMIFS($J20:$BQ20,$J$7:$BQ$7,D$8) -> 0 | E20: =+SUMIFS($J20:$BQ20,$J$7:$BQ$7,E$8) -> 0 | F20: =+SUMIFS($J20:$BQ20,$J$7:$BQ$7,F$8) -> 0 | G20: =+SUMIFS($J20:$BQ20,$J$7:$BQ$7,G$8) -> 43333.333 | H20: =+SUMIFS($J20:$BQ20,$J$7:$BQ$7,H$8) -> 151666.67 | AS20: =+AS29*($B$20/12) -> 0 | AT20: =+AT29*($B$20/12) -> 0 | AU20: =+AU29*($B$20/12) -> 0 | AV20: =+AV29*($B$20/12) -> 0 | AW20: =+AW29*($B$20/12) -> 0 | AX20: =+AX29*($B$20/12) -> 0 | AY20: =+AY29*($B$20/12) -> 4333.3333 | AZ20: =+AZ29*($B$20/12) -> 4333.3333 | ... BQ20: =+BQ29*($B$20/12) -> 13000
C22: Total Salaries & Wages | D22: =+SUMIFS($J22:$BQ22,$J$7:$BQ$7,D$8) -> 3317600 | E22: =+SUMIFS($J22:$BQ22,$J$7:$BQ$7,E$8) -> 3509800 | F22: =+SUMIFS($J22:$BQ22,$J$7:$BQ$7,F$8) -> 3716855.6 | G22: =+SUMIFS($J22:$BQ22,$J$7:$BQ$7,G$8) -> 4327258.5 | H22: =+SUMIFS($J22:$BQ22,$J$7:$BQ$7,H$8) -> 4610459.6 | J22: =SUM(J11:J20) -> 277600 | K22: =SUM(K11:K20) -> 272100 | L22: =SUM(L11:L20) -> 278100 | M22: =SUM(M11:M20) -> 280500 | N22: =SUM(N11:N20) -> 274300 | O22: =SUM(O11:O20) -> 276000 | P22: =SUM(P11:P20) -> 277800 | Q22: =SUM(Q11:Q20) -> 276200 | ... BQ22: =SUM(BQ11:BQ20) -> 384566.08
C24: % Increase (merit, each Jan) | AS24: 0 | AT24: 0.03 | BF24: 0.03
C26: Daily Accession Count | J26: =+'Revenue Build'!I46 -> 308.73913 | K26: =+'Revenue Build'!J46 -> 291.27273 | L26: =+'Revenue Build'!K46 -> 320.90909 | M26: =+'Revenue Build'!L46 -> 314.36364 | N26: =+'Revenue Build'!M46 -> 320.375 | O26: =+'Revenue Build'!N46 -> 314.61905 | P26: =+'Revenue Build'!O46 -> 316.47826 | Q26: =+'Revenue Build'!P46 -> 316.65217 | ... BQ26: =+'Revenue Build'!BP46 -> 511
C27: Monthly Daily Accession Variance | AR27: base | AS27: =+AS26-AR26 -> -4.2364123 | AT27: =+AT26-AS26 -> 0 | AU27: =+AU26-AT26 -> 0 | AV27: =+AV26-AU26 -> 14 | AW27: =+AW26-AV26 -> 10 | AX27: =+AX26-AW26 -> 10 | AY27: =+AY26-AX26 -> 10.591596 | AZ27: =+AZ26-AY26 -> 10.591596 | ... BQ27: =+BQ26-BP26 -> 0
C28: Rolling Amount | AR28: 0 | AS28: =+AR28+AS27 -> -4.2364123 | AT28: =+AS28+AT27 -> -4.2364123 | AU28: =+AT28+AU27 -> -4.2364123 | AV28: =+AU28+AV27 -> 9.7635877 | AW28: =+AV28+AW27 -> 19.763588 | AX28: =+AW28+AX27 -> 29.763588 | AY28: =+AX28+AY27 -> 40.355184 | AZ28: =+AY28+AZ27 -> 50.94678 | ... BQ28: =+BP28+BQ27 -> 126.90476
B29: 40 | C29: Accessioners Needed | D29: <-- accessions per accessioner per day (B29) | AS29: =+MAX(0,INT(AS28/$B$29)) -> 0 | AT29: =+MAX(0,INT(AT28/$B$29)) -> 0 | AU29: =+MAX(0,INT(AU28/$B$29)) -> 0 | AV29: =+MAX(0,INT(AV28/$B$29)) -> 0 | AW29: =+MAX(0,INT(AW28/$B$29)) -> 0 | AX29: =+MAX(0,INT(AX28/$B$29)) -> 0 | AY29: =+MAX(0,INT(AY28/$B$29)) -> 1 | AZ29: =+MAX(0,INT(AZ28/$B$29)) -> 1 | ... BQ29: =+MAX(0,INT(BQ28/$B$29)) -> 3
A31: Sales Reps
B32: 0.1 | C32: Sales Rep Expense (current staff) | D32: =+SUMIFS($J32:$BQ32,$J$7:$BQ$7,D$8) -> 636600 | E32: =+SUMIFS($J32:$BQ32,$J$7:$BQ$7,E$8) -> 684700 | F32: =+SUMIFS($J32:$BQ32,$J$7:$BQ$7,F$8) -> 747121.01 | G32: =+SUMIFS($J32:$BQ32,$J$7:$BQ$7,G$8) -> 737591.9 | H32: =+SUMIFS($J32:$BQ32,$J$7:$BQ$7,H$8) -> 759719.66 | J32: =+'Historical & Projected P&L'!J17 -> 51700 | K32: =+'Historical & Projected P&L'!K17 -> 48600 | L32: =+'Historical & Projected P&L'!L17 -> 53100 | M32: =+'Historical & Projected P&L'!M17 -> 52300 | N32: =+'Historical & Projected P&L'!N17 -> 57500 | O32: =+'Historical & Projected P&L'!O17 -> 50200 | P32: =+'Historical & Projected P&L'!P17 -> 54400 | Q32: =+'Historical & Projected P&L'!Q17 -> 56300 | ... AR32: =+'Historical & Projected P&L'!AR17 -> 59675.72 | AS32: =+AR32*(1+AS$24) -> 59675.72 | AT32: =+AS32*(1+AT$24) -> 61465.992 | AU32: =+AT32*(1+AU$24) -> 61465.992 | AV32: =+AU32*(1+AV$24) -> 61465.992 | AW32: =+AV32*(1+AW$24) -> 61465.992 | AX32: =+AW32*(1+AX$24) -> 61465.992 | AY32: =+AX32*(1+AY$24) -> 61465.992 | AZ32: =+AY32*(1+AZ$24) -> 61465.992 | ... BQ32: =+BP32*(1+BQ$24) -> 63309.971
C34: New Sales Reps | D34: =+SUMIFS($J34:$BQ34,$J$7:$BQ$7,D$8) -> 0 | E34: =+SUMIFS($J34:$BQ34,$J$7:$BQ$7,E$8) -> 0 | F34: =+SUMIFS($J34:$BQ34,$J$7:$BQ$7,F$8) -> 0 | G34: =+SUMIFS($J34:$BQ34,$J$7:$BQ$7,G$8) -> 135632 | H34: =+SUMIFS($J34:$BQ34,$J$7:$BQ$7,H$8) -> 356384 | AS34: =+AS38*$B$32 -> 0 | AT34: =+AT38*$B$32 -> 0 | AU34: =+AU38*$B$32 -> 0 | AV34: =+AV38*$B$32 -> 2576 | AW34: =+AW38*$B$32 -> 5152 | AX34: =+AX38*$B$32 -> 7056 | AY34: =+AY38*$B$32 -> 9856 | AZ34: =+AZ38*$B$32 -> 12320 | ... BQ34: =+BQ38*$B$32 -> 29568
C35: Total Sales Rep Expense | D35: =+SUMIFS($J35:$BQ35,$J$7:$BQ$7,D$8) -> 636600 | E35: =+SUMIFS($J35:$BQ35,$J$7:$BQ$7,E$8) -> 684700 | F35: =+SUMIFS($J35:$BQ35,$J$7:$BQ$7,F$8) -> 747121.01 | G35: =+SUMIFS($J35:$BQ35,$J$7:$BQ$7,G$8) -> 873223.9 | H35: =+SUMIFS($J35:$BQ35,$J$7:$BQ$7,H$8) -> 1116103.7 | J35: =+J32+J34 -> 51700 | K35: =+K32+K34 -> 48600 | L35: =+L32+L34 -> 53100 | M35: =+M32+M34 -> 52300 | N35: =+N32+N34 -> 57500 | O35: =+O32+O34 -> 50200 | P35: =+P32+P34 -> 54400 | Q35: =+Q32+Q34 -> 56300 | ... BQ35: =+BQ32+BQ34 -> 92877.971
C37: Revenue (current sales team) | D37: =+SUMIFS($J37:$BQ37,$J$7:$BQ$7,D$8) -> 12711900 | E37: =+SUMIFS($J37:$BQ37,$J$7:$BQ$7,E$8) -> 13757400 | F37: =+SUMIFS($J37:$BQ37,$J$7:$BQ$7,F$8) -> 14953118 | G37: =+SUMIFS($J37:$BQ37,$J$7:$BQ$7,G$8) -> 14883339 | H37: =+SUMIFS($J37:$BQ37,$J$7:$BQ$7,H$8) -> 15381201 | J37: =+'Revenue Build'!I14+'Revenue Build'!I28 -> 1059600 | K37: =+'Revenue Build'!J14+'Revenue Build'!J28 -> 957100 | L37: =+'Revenue Build'!K14+'Revenue Build'!K28 -> 1053300 | M37: =+'Revenue Build'!L14+'Revenue Build'!L28 -> 1024700 | N37: =+'Revenue Build'!M14+'Revenue Build'!M28 -> 1153100 | O37: =+'Revenue Build'!N14+'Revenue Build'!N28 -> 972600 | P37: =+'Revenue Build'!O14+'Revenue Build'!O28 -> 1073500 | Q37: =+'Revenue Build'!P14+'Revenue Build'!P28 -> 1097400 | ... BQ37: =+'Revenue Build'!BP14+'Revenue Build'!BP28 -> 1267364.9
C38: Revenue (new sales team) | D38: =+SUMIFS($J38:$BQ38,$J$7:$BQ$7,D$8) -> 0 | E38: =+SUMIFS($J38:$BQ38,$J$7:$BQ$7,E$8) -> 0 | F38: =+SUMIFS($J38:$BQ38,$J$7:$BQ$7,F$8) -> 0 | G38: =+SUMIFS($J38:$BQ38,$J$7:$BQ$7,G$8) -> 1356320 | H38: =+SUMIFS($J38:$BQ38,$J$7:$BQ$7,H$8) -> 3563840 | J38: =+'Revenue Build'!I38 -> 0 | K38: =+'Revenue Build'!J38 -> 0 | L38: =+'Revenue Build'!K38 -> 0 | M38: =+'Revenue Build'!L38 -> 0 | N38: =+'Revenue Build'!M38 -> 0 | O38: =+'Revenue Build'!N38 -> 0 | P38: =+'Revenue Build'!O38 -> 0 | Q38: =+'Revenue Build'!P38 -> 0 | ... BQ38: =+'Revenue Build'!BP38 -> 295680
A40: Business Insurance
C41: General Business | D41: =+SUMIFS($J41:$BQ41,$J$7:$BQ$7,D$8) -> 146100 | E41: =+SUMIFS($J41:$BQ41,$J$7:$BQ$7,E$8) -> 155500 | F41: =+SUMIFS($J41:$BQ41,$J$7:$BQ$7,F$8) -> 188908.98 | G41: =+SUMIFS($J41:$BQ41,$J$7:$BQ$7,G$8) -> 192166.67 | H41: =+SUMIFS($J41:$BQ41,$J$7:$BQ$7,H$8) -> 267166.67 | J41: =+'Historical & Projected P&L'!J62 -> 12600 | K41: =+'Historical & Projected P&L'!K62 -> 12100 | L41: =+'Historical & Projected P&L'!L62 -> 11500 | M41: =+'Historical & Projected P&L'!M62 -> 13000 | N41: =+'Historical & Projected P&L'!N62 -> 11400 | O41: =+'Historical & Projected P&L'!O62 -> 12500 | P41: =+'Historical & Projected P&L'!P62 -> 11900 | Q41: =+'Historical & Projected P&L'!Q62 -> 11600 | ... AR41: =+'Historical & Projected P&L'!AR62 -> 21181.83 | AS41: =+LOOKUP(AS43,$C$46:$C$50,$D$46:$D$50)/12 -> 15666.667 | AT41: =+LOOKUP(AT43,$C$46:$C$50,$D$46:$D$50)/12 -> 15666.667 | AU41: =+LOOKUP(AU43,$C$46:$C$50,$D$46:$D$50)/12 -> 15666.667 | AV41: =+LOOKUP(AV43,$C$46:$C$50,$D$46:$D$50)/12 -> 15666.667 | AW41: =+LOOKUP(AW43,$C$46:$C$50,$D$46:$D$50)/12 -> 15666.667 | AX41: =+LOOKUP(AX43,$C$46:$C$50,$D$46:$D$50)/12 -> 15666.667 | AY41: =+LOOKUP(AY43,$C$46:$C$50,$D$46:$D$50)/12 -> 15666.667 | AZ41: =+LOOKUP(AZ43,$C$46:$C$50,$D$46:$D$50)/12 -> 15666.667 | ... BQ41: =+LOOKUP(BQ43,$C$46:$C$50,$D$46:$D$50)/12 -> 24000
C42: Net Revenue | D42: =+SUMIFS($J42:$BQ42,$J$7:$BQ$7,D$8) -> 12711900 | E42: =+SUMIFS($J42:$BQ42,$J$7:$BQ$7,E$8) -> 13757400 | F42: =+SUMIFS($J42:$BQ42,$J$7:$BQ$7,F$8) -> 14953118 | G42: =+SUMIFS($J42:$BQ42,$J$7:$BQ$7,G$8) -> 16239659 | H42: =+SUMIFS($J42:$BQ42,$J$7:$BQ$7,H$8) -> 18945041 | J42: =+'Historical & Projected P&L'!J10 -> 1059600 | K42: =+'Historical & Projected P&L'!K10 -> 957100 | L42: =+'Historical & Projected P&L'!L10 -> 1053300 | M42: =+'Historical & Projected P&L'!M10 -> 1024700 | N42: =+'Historical & Projected P&L'!N10 -> 1153100 | O42: =+'Historical & Projected P&L'!O10 -> 972600 | P42: =+'Historical & Projected P&L'!P10 -> 1073500 | Q42: =+'Historical & Projected P&L'!Q10 -> 1097400 | ... BQ42: =+'Historical & Projected P&L'!BQ10 -> 1563044.9
C43: TTM Rev | U43: =SUM(J42:U42) -> 12711900 | V43: =SUM(K42:V42) -> 12809600 | W43: =SUM(L42:W42) -> 12796400 | X43: =SUM(M42:X42) -> 12825000 | Y43: =SUM(N42:Y42) -> 12971400 | Z43: =SUM(O42:Z42) -> 13025100 | AA43: =SUM(P42:AA42) -> 13109700 | AB43: =SUM(Q42:AB42) -> 13244100 | ... BQ43: =SUM(BF42:BQ42) -> 18945041
B45: TTM rev >= | C45: Thresholds | D45: Annual premium
C46: 0 | D46: 88000
C47: 12000000 | D47: =+D46+50000 -> 138000
C48: 14000000 | D48: =+D47+50000 -> 188000
C49: 16000000 | D49: =+D48+50000 -> 238000
C50: 18000000 | D50: =+D49+50000 -> 288000
A52: Other Payroll Items
C53: S&W (reported gross, including taxes & processing, in Sep–Nov) | J53: =+'Historical & Projected P&L'!J15 -> 277600 | K53: =+'Historical & Projected P&L'!K15 -> 272100 | L53: =+'Historical & Projected P&L'!L15 -> 278100 | M53: =+'Historical & Projected P&L'!M15 -> 280500 | N53: =+'Historical & Projected P&L'!N15 -> 274300 | O53: =+'Historical & Projected P&L'!O15 -> 276000 | P53: =+'Historical & Projected P&L'!P15 -> 277800 | Q53: =+'Historical & Projected P&L'!Q15 -> 276200 | ... AO53: =+'Historical & Projected P&L'!AO15 -> 308500 | AP53: =+'Sep - Nov P&L'!E60 -> 336098.26 | AQ53: =+'Sep - Nov P&L'!F60 -> 340503.83 | AR53: =+'Sep - Nov P&L'!G60 -> 335832.28
C54: Payroll taxes | J54: =+'Historical & Projected P&L'!J22 -> 22600 | K54: =+'Historical & Projected P&L'!K22 -> 22300 | L54: =+'Historical & Projected P&L'!L22 -> 22000 | M54: =+'Historical & Projected P&L'!M22 -> 22200 | N54: =+'Historical & Projected P&L'!N22 -> 21300 | O54: =+'Historical & Projected P&L'!O22 -> 22000 | P54: =+'Historical & Projected P&L'!P22 -> 22500 | Q54: =+'Historical & Projected P&L'!Q22 -> 21700 | ... AO54: =+'Historical & Projected P&L'!AO22 -> 24600
C55: Payroll processing fees | J55: =+'Historical & Projected P&L'!J26 -> 1100 | K55: =+'Historical & Projected P&L'!K26 -> 1100 | L55: =+'Historical & Projected P&L'!L26 -> 1100 | M55: =+'Historical & Projected P&L'!M26 -> 1200 | N55: =+'Historical & Projected P&L'!N26 -> 1100 | O55: =+'Historical & Projected P&L'!O26 -> 1100 | P55: =+'Historical & Projected P&L'!P26 -> 1100 | Q55: =+'Historical & Projected P&L'!Q26 -> 1100 | ... AO55: =+'Historical & Projected P&L'!AO26 -> 1200
C57: % of S&W
C58: Payroll taxes | J58: =+IFERROR(J54/J53,) -> 0.081412104 | K58: =+IFERROR(K54/K53,) -> 0.081955164 | L58: =+IFERROR(L54/L53,) -> 0.079108234 | M58: =+IFERROR(M54/M53,) -> 0.079144385 | N58: =+IFERROR(N54/N53,) -> 0.077652206 | O58: =+IFERROR(O54/O53,) -> 0.079710145 | P58: =+IFERROR(P54/P53,) -> 0.080993521 | Q58: =+IFERROR(Q54/Q53,) -> 0.078566256 | ... AO58: =+IFERROR(AO54/AO53,) -> 0.079740681 | AP58: =+AVERAGE(AD58:AO58) -> 0.080113276 | AQ58: =+AP58 -> 0.080113276 | AR58: =+AQ58 -> 0.080113276
C59: Payroll processing fees | J59: =+IFERROR(J55/J53,) -> 0.003962536 | K59: =+IFERROR(K55/K53,) -> 0.0040426314 | L59: =+IFERROR(L55/L53,) -> 0.0039554117 | M59: =+IFERROR(M55/M53,) -> 0.0042780749 | N59: =+IFERROR(N55/N53,) -> 0.0040102078 | O59: =+IFERROR(O55/O53,) -> 0.0039855072 | P59: =+IFERROR(P55/P53,) -> 0.0039596832 | Q59: =+IFERROR(Q55/Q53,) -> 0.0039826213 | ... AO59: =+IFERROR(AO55/AO53,) -> 0.0038897893 | AP59: =+AVERAGE(AD59:AO59) -> 0.0039734514 | AQ59: =+AP59 -> 0.0039734514 | AR59: =+AQ59 -> 0.0039734514
C61: Restated S&W | D61: =+SUMIFS($J61:$BQ61,$J$7:$BQ$7,D$8) -> 0 | E61: =+SUMIFS($J61:$BQ61,$J$7:$BQ$7,E$8) -> 0 | F61: =+SUMIFS($J61:$BQ61,$J$7:$BQ$7,F$8) -> 1260355.6 | G61: =+SUMIFS($J61:$BQ61,$J$7:$BQ$7,G$8) -> 4327258.5 | H61: =+SUMIFS($J61:$BQ61,$J$7:$BQ$7,H$8) -> 4610459.6 | AP61: =+AP53-SUM(AP62:AP63) -> 310028.94 | AQ61: =+AQ53-SUM(AQ62:AQ63) -> 314092.79 | AR61: =+AR53-SUM(AR62:AR63) -> 309783.59 | AS61: =+AS22 -> 326450.26 | AT61: =+AT22 -> 323243.77 | AU61: =+AU22 -> 340743.77 | AV61: =+AV22 -> 361993.77 | AW61: =+AW22 -> 361993.77 | AX61: =+AX22 -> 361993.77 | AY61: =+AY22 -> 366327.1 | AZ61: =+AZ22 -> 366327.1 | ... BQ61: =+BQ22 -> 384566.08
C62: Payroll taxes | AP62: =+AP$53/(1+AP$58+AP$59)*AP58 -> 24837.434 | AQ62: =+AQ$53/(1+AQ$58+AQ$59)*AQ58 -> 25163.003 | AR62: =+AR$53/(1+AR$58+AR$59)*AR58 -> 24817.778
C63: Payroll processing fees | AP63: =+AP$53/(1+AP$58+AP$59)*AP59 -> 1231.8849 | AQ63: =+AQ$53/(1+AQ$58+AQ$59)*AQ59 -> 1248.0325 | AR63: =+AR$53/(1+AR$58+AR$59)*AR59 -> 1230.9101

Sheet QoE PF Adj. P&L Aug-26
B1: Pro Forma Adjusted Income Statement - Combined
B2: =+Project_Name -> Project Larkspur
B4: Orivane Clinical Laboratories, LLC
B7: Pro Forma Adjusted P&L
C8: $ in Thousands | D8: 45322 | E8: =+EOMONTH(D8,1) -> 45351 | F8: =+EOMONTH(E8,1) -> 45382 | G8: =+EOMONTH(F8,1) -> 45412 | H8: =+EOMONTH(G8,1) -> 45443 | I8: =+EOMONTH(H8,1) -> 45473 | J8: =+EOMONTH(I8,1) -> 45504 | K8: =+EOMONTH(J8,1) -> 45535 | L8: =+EOMONTH(K8,1) -> 45565 | ... AI8: =+EOMONTH(AH8,1) -> 46265 | AK8: LTM Aug-26
C9: Revenues
C10: Operating Revenue
C11: Net Fee-for-Service | D11: 1152.1 | E11: 1042.1 | F11: 1152.9 | G11: 1120.7 | H11: 1250.5 | I11: 1058.9 | J11: 1171.7 | K11: 1199.4 | L11: 1098.8 | M11: 1331.5 | N11: 1148.6 | O11: 1118 | P11: 1259.4 | Q11: 1022.8 | R11: 1177.2 | S11: 1279.9 | T11: 1318.2 | U11: 1151.7 | V11: 1317.4 | W11: 1254.1 | X11: 1259.3 | Y11: 1448 | Z11: 1223.3 | AA11: 1285.6 | AB11: 1345 | AC11: 1137.1 | AD11: 1353.8 | AE11: 1395.9 | AF11: 1364.5 | AG11: 1293.1 | AH11: 1413.7 | AI11: 1349.7 | AK11: =SUM(X11:AI11) -> 15869
C12: Adjustments & Refunds | D12: -57.2 | E12: -49.1 | F12: -58.2 | G12: -58.9 | H12: -59.5 | I12: -51 | J12: -56.6 | K12: -58.6 | L12: -51.9 | M12: -69.1 | N12: -53.6 | O12: -59.4 | P12: -61.7 | Q12: -48.1 | R12: -53.7 | S12: -70.4 | T12: -69.5 | U12: -54.9 | V12: -63.1 | W12: -59.1 | X12: -67.7 | Y12: -76 | Z12: -56.1 | AA12: -67.6 | AB12: -68.5 | AC12: -56.9 | AD12: -74.3 | AE12: -64.4 | AF12: -67.1 | AG12: -63.2 | AH12: -74.2 | AI12: -70.6 | AK12: =SUM(X12:AI12) -> -806.6
C13: Provision for Bad Debt Expense | D13: -41.2 | E13: -42.7 | F13: -46.6 | G13: -43.5 | H13: -46.1 | I13: -41.1 | J13: -48.3 | K13: -48.8 | L13: -39.3 | M13: -46.8 | N13: -39.6 | O13: -43.6 | P13: -48.3 | Q13: -36.5 | R13: -47.4 | S13: -45.9 | T13: -47.9 | U13: -46.9 | V13: -53.9 | W13: -49.9 | X13: -46.2 | Y13: -54.6 | Z13: -50.2 | AA13: -46.6 | AB13: -50.6 | AC13: -43.4 | AD13: -46.7 | AE13: -48.8 | AF13: -55.1 | AG13: -49.5 | AH13: -50.9 | AI13: -52.5 | AK13: =SUM(X13:AI13) -> -595.1
C14: Other Operating Revenue | D14: 5.9 | E14: 6.8 | F14: 5.2 | G14: 6.4 | H14: 8.2 | I14: 5.8 | J14: 6.7 | K14: 5.4 | L14: 6.5 | M14: 6 | N14: 7.4 | O14: 7.1 | P14: 7.9 | Q14: 5.7 | R14: 5.8 | S14: 7.5 | T14: 6 | U14: 7.3 | V14: 7.5 | W14: 6 | X14: 6.4 | Y14: 8.8 | Z14: 6.1 | AA14: 7.7 | AB14: 8.2 | AC14: 7.1 | AD14: 6 | AE14: 6.4 | AF14: 6.1 | AG14: 7.6 | AH14: 9.1 | AI14: 6.4 | AK14: =SUM(X14:AI14) -> 85.9
C15: Total Net Operating Revenue | D15: =SUM(D11:D14) -> 1059.6 | E15: =SUM(E11:E14) -> 957.1 | F15: =SUM(F11:F14) -> 1053.3 | G15: =SUM(G11:G14) -> 1024.7 | H15: =SUM(H11:H14) -> 1153.1 | I15: =SUM(I11:I14) -> 972.6 | J15: =SUM(J11:J14) -> 1073.5 | K15: =SUM(K11:K14) -> 1097.4 | ... AI15: =SUM(AI11:AI14) -> 1233 | AK15: =SUM(X15:AI15) -> 14553.2
C16: Growth | E16: =+IFERROR(E15/D15-1,"n/a") -> -0.096734617 | F16: =+IFERROR(F15/E15-1,"n/a") -> 0.10051196 | G16: =+IFERROR(G15/F15-1,"n/a") -> -0.027152758 | H16: =+IFERROR(H15/G15-1,"n/a") -> 0.12530497 | I16: =+IFERROR(I15/H15-1,"n/a") -> -0.15653456 | J16: =+IFERROR(J15/I15-1,"n/a") -> 0.10374255 | K16: =+IFERROR(K15/J15-1,"n/a") -> 0.022263624 | L16: =+IFERROR(L15/K15-1,"n/a") -> -0.075906689 | ... AI16: =+IFERROR(AI15/AH15-1,"n/a") -> -0.04985744
C18: Operating Expenses
C19: Employee Salaries & Wages
C20: Salaries & Wages | D20: 277.6 | E20: 272.1 | F20: 278.1 | G20: 280.5 | H20: 274.3 | I20: 276 | J20: 277.8 | K20: 276.2 | L20: 278.3 | M20: 274.3 | N20: 276.3 | O20: 276.1 | P20: 288.3 | Q20: 287.8 | R20: 284.2 | S20: 285.7 | T20: 293.9 | U20: 294.2 | V20: 293.7 | W20: 288.9 | X20: 296.9 | Y20: 296.4 | Z20: 298.5 | AA20: 301.3 | AB20: 311.8 | AC20: 303.2 | AD20: 303.4 | AE20: 304.7 | AF20: 312.1 | AG20: 305.9 | AH20: 306.9 | AI20: 308.5 | AK20: =SUM(X20:AI20) -> 3649.6
C21: Contract Labor | D21: 15.5 | E21: 14.3 | F21: 15.1 | G21: 15.4 | H21: 16.5 | I21: 14.8 | J21: 15.7 | K21: 17 | L21: 14.5 | M21: 19.1 | N21: 15.3 | O21: 14.7 | P21: 17.3 | Q21: 14.6 | R21: 16.3 | S21: 18.3 | T21: 17.9 | U21: 15.5 | V21: 18.3 | W21: 16.5 | X21: 18 | Y21: 19.1 | Z21: 16.2 | AA21: 17.5 | AB21: 18 | AC21: 16.3 | AD21: 18.1 | AE21: 18.9 | AF21: 18.1 | AG21: 17.3 | AH21: 19 | AI21: 18.5 | AK21: =SUM(X21:AI21) -> 215
C22: Sales Rep Expense | D22: 51.7 | E22: 48.6 | F22: 53.1 | G22: 52.3 | H22: 57.5 | I22: 50.2 | J22: 54.4 | K22: 56.3 | L22: 50.5 | M22: 58.9 | N22: 53.3 | O22: 49.8 | P22: 56.9 | Q22: 46.7 | R22: 53.9 | S22: 58.2 | T22: 58.5 | U22: 51.4 | V22: 60.7 | W22: 56.4 | X22: 58 | Y22: 67.3 | Z22: 56.1 | AA22: 60.6 | AB22: 63.8 | AC22: 53.5 | AD22: 62 | AE22: 65 | AF22: 60.9 | AG22: 60.4 | AH22: 66.4 | AI22: 63.3 | AK22: =SUM(X22:AI22) -> 737.3
C23: Other Personnel Costs | D23: 7.1 | E23: 7 | F23: 7.7 | G23: 7.1 | H23: 7 | I23: 7.4 | J23: 7.4 | K23: 7.5 | L23: 7.3 | M23: 7.3 | N23: 7.9 | O23: 7.7 | P23: 7.8 | Q23: 7.9 | R23: 8.3 | S23: 8.1 | T23: 8.5 | U23: 7.8 | V23: 7.9 | W23: 7.8 | X23: 7.7 | Y23: 7.8 | Z23: 8 | AA23: 8.3 | AB23: 8.9 | AC23: 8.3 | AD23: 7.9 | AE23: 8.3 | AF23: 8.1 | AG23: 8.7 | AH23: 8.9 | AI23: 9.3 | AK23: =SUM(X23:AI23) -> 100.2
C24: Total Employee Salaries & Wages | D24: =SUM(D20:D23) -> 351.9 | E24: =SUM(E20:E23) -> 342 | F24: =SUM(F20:F23) -> 354 | G24: =SUM(G20:G23) -> 355.3 | H24: =SUM(H20:H23) -> 355.3 | I24: =SUM(I20:I23) -> 348.4 | J24: =SUM(J20:J23) -> 355.3 | K24: =SUM(K20:K23) -> 357 | ... AI24: =SUM(AI20:AI23) -> 399.6 | AK24: =SUM(X24:AI24) -> 4702.1
C26: Employee Taxes & Benefits
C27: Payroll Taxes | D27: 22.6 | E27: 22.3 | F27: 22 | G27: 22.2 | H27: 21.3 | I27: 22 | J27: 22.5 | K27: 21.7 | L27: 22.1 | M27: 22.6 | N27: 22.2 | O27: 22.5 | P27: 23.2 | Q27: 22.5 | R27: 22.3 | S27: 22.5 | T27: 22.9 | U27: 24.1 | V27: 23.1 | W27: 22.6 | X27: 23.7 | Y27: 23.9 | Z27: 24 | AA27: 24.4 | AB27: 25.5 | AC27: 24 | AD27: 24.1 | AE27: 23.9 | AF27: 25.6 | AG27: 24.1 | AH27: 24.6 | AI27: 24.6 | AK27: =SUM(X27:AI27) -> 292.4
C28: Employee Benefits | D28: 16.9 | E28: 16.6 | F28: 16.4 | G28: 17.1 | H28: 16.2 | I28: 17 | J28: 16.5 | K28: 16.7 | L28: 16.5 | M28: 16.3 | N28: 16.6 | O28: 16.5 | P28: 16.9 | Q28: 16.8 | R28: 17.2 | S28: 17.2 | T28: 18.1 | U28: 17.7 | V28: 17.7 | W28: 17.6 | X28: 17.3 | Y28: 17.7 | Z28: 18.3 | AA28: 18 | AB28: 18.2 | AC28: 18 | AD28: 18.5 | AE28: 18.7 | AF28: 18.8 | AG28: 18.5 | AH28: 18.3 | AI28: 18.8 | AK28: =SUM(X28:AI28) -> 219.1
C29: Pension Plans | D29: 2.8 | E29: 2.8 | F29: 2.8 | G29: 2.9 | H29: 2.7 | I29: 2.8 | J29: 2.8 | K29: 2.8 | L29: 2.8 | M29: 2.8 | N29: 2.8 | O29: 2.8 | P29: 2.9 | Q29: 2.8 | R29: 2.8 | S29: 2.8 | T29: 3 | U29: 2.9 | V29: 2.9 | W29: 2.8 | X29: 3 | Y29: 2.9 | Z29: 3 | AA29: 3 | AB29: 3 | AC29: 3 | AD29: 3.1 | AE29: 3.1 | AF29: 3.1 | AG29: 3 | AH29: 3.1 | AI29: 3.1 | AK29: =SUM(X29:AI29) -> 36.4
C30: Other Personnel Expenses | D30: 0.9 | E30: 0.8 | F30: 0.8 | G30: 0.9 | H30: 0.8 | I30: 0.8 | J30: 0.8 | K30: 0.8 | L30: 0.8 | M30: 0.8 | N30: 0.8 | O30: 0.8 | P30: 0.9 | Q30: 0.9 | R30: 0.8 | S30: 0.9 | T30: 0.9 | U30: 0.9 | V30: 0.9 | W30: 0.9 | X30: 0.9 | Y30: 0.9 | Z30: 0.9 | AA30: 0.9 | AB30: 0.9 | AC30: 0.9 | AD30: 0.9 | AE30: 0.9 | AF30: 0.9 | AG30: 0.9 | AH30: 0.9 | AI30: 0.9 | AK30: =SUM(X30:AI30) -> 10.8
C31: Payroll Processing Fee | D31: 1.1 | E31: 1.1 | F31: 1.1 | G31: 1.2 | H31: 1.1 | I31: 1.1 | J31: 1.1 | K31: 1.1 | L31: 1.1 | M31: 1.1 | N31: 1.1 | O31: 1.1 | P31: 1.2 | Q31: 1.2 | R31: 1.1 | S31: 1.1 | T31: 1.2 | U31: 1.2 | V31: 1.2 | W31: 1.1 | X31: 1.2 | Y31: 1.2 | Z31: 1.2 | AA31: 1.2 | AB31: 1.3 | AC31: 1.2 | AD31: 1.2 | AE31: 1.2 | AF31: 1.2 | AG31: 1.2 | AH31: 1.2 | AI31: 1.2 | AK31: =SUM(X31:AI31) -> 14.5
