Workbook
Name \a: Cover!$C$3
Name \b: Control!$E$5
Name \p: Control!$E$11
Name \z: Control!$E$12
Name _Key1: '6. AHG (Combined Entity)'!$G$7
Name _Key2: '2. Tallowick (Combined Entity)'!$G$7
Name _Order1: Control!$E$10
Name _Sort: Control!$E$9
Name wrn.Summary.: 'Transaction Summary'!$C$3
Name wrn.Waterfall.: 'SPV Waterfall'!$C$3
Name wrn.AHG.: '6. AHG (Combined Entity)'!$C$3
Name FX_LCA: Control!$E$17
Name FX_LCB: Control!$E$22
Name RefDate: Control!$E$11
Name TxDate: Control!$E$12
Name MgmtFee: Control!$E$27
Name GP_Commit: Control!$E$33
Name Hurdle_T2: Control!$E$39
Name Hurdle_T4: Control!$E$51
Name Hurdle_T5: Control!$E$57
Name Carry_T3: Control!$E$44
Name Carry_T4: Control!$E$50
Name Carry_T5: Control!$E$56
Name CircuitBreaker: Control!$E$5
Name MHG_Rev: '6. AHG (Combined Entity)'!$G$202:$R$202
Name MHG_EBITDA: '6. AHG (Combined Entity)'!$G$211:$R$211
Name MHG_NI: '6. AHG (Combined Entity)'!$G$224:$R$224
Name MHG_Cash: '6. AHG (Combined Entity)'!$G$250:$R$250
Name MHG_NetDebt: '6. AHG (Combined Entity)'!$G$304:$R$304
Name MHG_BSCheck: '6. AHG (Combined Entity)'!$G$273:$R$273
Name MHG_TaxRate: '6. AHG (Combined Entity)'!$N$12
Name MHG_Toggle2027: '6. AHG (Combined Entity)'!$E$47
Name MHG_Toggle2031: '6. AHG (Combined Entity)'!$E$95
Name MHG_FollowOn: '6. AHG (Combined Entity)'!$G$195:$R$195
Name MHG_Div: '6. AHG (Combined Entity)'!$G$312:$R$312
Name Tall_Rev: '2. Tallowick (Combined Entity)'!$G$199:$R$199
Name Tall_EBITDA: '2. Tallowick (Combined Entity)'!$G$208:$R$208
Name Tall_NI: '2. Tallowick (Combined Entity)'!$G$217:$R$217
Name Tall_Cash: '2. Tallowick (Combined Entity)'!$G$227:$R$227
Name Tall_NetDebt: '2. Tallowick (Combined Entity)'!$G$271:$R$271
Name Tall_BSCheck: '2. Tallowick (Combined Entity)'!$G$241:$R$241
Name Tall_Toggle2027: '2. Tallowick (Combined Entity)'!$E$53
Name Tall_FollowOn: '2. Tallowick (Combined Entity)'!$G$192:$R$192
Name AHG_EntryMult: '7. Entry & Exit'!$E$19
Name AHG_ExitMult: '7. Entry & Exit'!$E$63
Name AHG_NAVPricing: '7. Entry & Exit'!$E$13
Name AHG_EqV: '7. Entry & Exit'!$E$25
Name AHG_Price: '7. Entry & Exit'!$E$28
Name AHG_CF_IRR: '7. Entry & Exit'!$E$96
Name AHG_CF_MoIC: '7. Entry & Exit'!$E$95
Name AHG_CF_Flows: '7. Entry & Exit'!$G$94:$S$94
Name Tall_EntryMult: '3. Entry & Exit'!$E$19
Name Tall_ExitMult: '3. Entry & Exit'!$E$61
Name Tall_NAVPricing: '3. Entry & Exit'!$E$13
Name Tall_EqV: '3. Entry & Exit'!$E$25
Name Tall_Price: '3. Entry & Exit'!$E$28
Name Tall_CF_IRR: '3. Entry & Exit'!$E$91
Name Tall_CF_MoIC: '3. Entry & Exit'!$E$90
Name Tall_CF_Flows: '3. Entry & Exit'!$G$89:$S$89
Name TS_Sources: 'Transaction Summary'!$E$32

Sheet Cover
C3: Project Dunecrest
C4: Continuation-fund transaction model – Kessport Frontier Managers Limited
C5: Tabs:
C7: Cover / Disclaimer / Control
C9: AHG Company Section (tabs 1–7): entity builds, combined entity, entry & exit
C11: Tallowick Company Section (tabs 1–3): build, combined entity, entry & exit
C13: Transaction Summary
C15: SPV Waterfall
C17: Instructions
C19: Inputs (can be amended by user) | D19: 12345
C20: Outputs (cannot be amended by user) | D20: =D19*2 -> 24690

Sheet Disclaimer
C3: =Cover!$C$3 -> Project Dunecrest | D3: Confidential
C5: This document is not a marketing communication. It has been prepared by Kessport Frontier Managers Limited solely for discussion with existing limited partners of Kessport Frontier Fund II in connection with a proposed continuation-fund transaction (Project Dunecrest) under which interests in Arvenna Health Group and Tallowick Consumer Products would be transferred to the Dunecrest Continuation Fund. It does not constitute an offer or a solicitation to acquire or subscribe for any interest in any fund or company. Figures are illustrative and unaudited; projections are based on assumptions that may not be realised and actual results may differ materially. Interest on debt is computed on opening balances; the model contains no circular references. Nothing in this document should be relied upon as investment, legal or tax advice.

Sheet Control
C3: =Cover!$C$3 -> Project Dunecrest | D3: Confidential
C4: Circuit Breaker
C5: Circuit Breaker (1 = on) | E5: 1
C7: Transaction Assumptions:
C9: Sponsor | E9: Kessport Frontier Managers Limited
C10: Funds | E10: Fund II
C11: Reference Date | E11: 46203
C12: Transaction Date | E12: 46387
C14: Portfolio Company Assumptions:
C15: Arvenna Health Group:
C16: Currency | E16: LCA
C17: Currency Conversion to USD | E17: 0.235
C18: Converted Currency | E18: USD
C20: Tallowick:
C21: Currency | E21: LCB
C22: Currency Conversion to USD | E22: 0.0125
C23: Converted Currency | E23: USD
C25: New SPV Economics:
C26: Management Fee | E26: On net invested capital
C27: Management Fee p.a (%) | E27: 0.0175
C29: Reinvested GP Economics ($M) | E29: 5.2
C30: Rolling LPs (% of Continuation Fund) | E30: 0.41
C32: Tier 1: Return of Capital
C33: GP Proceeds Allocation (GP commitment %) | E33: 0.02
C34: LP Proceeds Allocation | E34: =1-E33 -> 0.98
C36: Tier 2: Preferred Return to LPs
C37: GP Proceeds Allocation | E37: 0
C38: LP Proceeds Allocation | E38: =1-E37 -> 1
C39: IRR Threshold | E39: 0.08
C40: MOIC Threshold | E40: 1
C42: Tier 3: Catch-Up & Carried Interest
C43: GP Catch-Up | E43: 1
C44: GP Carried Interest | E44: 0.1
C45: IRR Threshold | E45: 0.08
C46: MOIC Threshold | E46: 1.5
C48: Tier 4: Catch-Up & Carried Interest
C49: GP Catch-Up | E49: 1
C50: GP Carried Interest | E50: 0.15
C51: IRR Threshold | E51: 0.15
C52: MOIC Threshold | E52: 2
C54: Tier 5: Catch-Up & Carried Interest
C55: GP Catch-Up | E55: 1
C56: GP Carried Interest | E56: 0.2
C57: IRR Threshold | E57: 0.2
C58: MOIC Threshold | E58: 2.5

Sheet 1. AHG Central
C3: =Cover!$C$3 -> Project Dunecrest | D3: Confidential
C4: AHG Central – Operating Build
C6: Fiscal Year Ending | G6: 43830 | H6: 44196 | I6: 44561 | J6: 44926 | K6: =EOMONTH(J6,12) -> 45291 | L6: =EOMONTH(K6,12) -> 45657 | M6: =EOMONTH(L6,12) -> 46022 | N6: =EOMONTH(M6,12) -> 46387 | O6: =EOMONTH(N6,12) -> 46752 | P6: =EOMONTH(O6,12) -> 47118 | Q6: =EOMONTH(P6,12) -> 47483 | R6: =EOMONTH(Q6,12) -> 47848
C7: Fiscal Year | G7: =YEAR(G6) -> 2019 | H7: =YEAR(H6) -> 2020 | I7: =YEAR(I6) -> 2021 | J7: =YEAR(J6) -> 2022 | K7: =YEAR(K6) -> 2023 | L7: =YEAR(L6) -> 2024 | M7: =YEAR(M6) -> 2025 | N7: =YEAR(N6) -> 2026 | ... R7: =YEAR(R6) -> 2030
C8: Actual / Estimate | G8: =IF(G6<=Control!$E$11,"A","E") -> A | H8: =IF(H6<=Control!$E$11,"A","E") -> A | I8: =IF(I6<=Control!$E$11,"A","E") -> A | J8: =IF(J6<=Control!$E$11,"A","E") -> A | K8: =IF(K6<=Control!$E$11,"A","E") -> A | L8: =IF(L6<=Control!$E$11,"A","E") -> A | M8: =IF(M6<=Control!$E$11,"A","E") -> A | N8: =IF(N6<=Control!$E$11,"A","E") -> E | ... R8: =IF(R6<=Control!$E$11,"A","E") -> E
C10: Supporting Data
C11: A | D11: Revenue Build | E11: ="("&Control!$E$16&" in Actual)" -> (LCA in Actual)
C12: Laboratory:
C13: # of Tests | G13: 104371 | H13: 95978 | I13: 103537 | J13: 110725 | K13: 121389 | L13: 128622 | M13: 136349 | N13: =M13*(1+N14) -> 142484.7 | O13: =N13*(1+O14) -> 149039 | P13: =O13*(1+P14) -> 160962.12 | Q13: =P13*(1+Q14) -> 175126.79 | R13: =Q13*(1+R14) -> 188261.3
C14: Growth (%) | G14: =IFERROR(G13/F13-1,"N/A") -> N/A | H14: =IFERROR(H13/G13-1,"N/A") -> -0.080415058 | I14: =IFERROR(I13/H13-1,"N/A") -> 0.078757632 | J14: =IFERROR(J13/I13-1,"N/A") -> 0.069424457 | K14: =IFERROR(K13/J13-1,"N/A") -> 0.09631068 | L14: =IFERROR(L13/K13-1,"N/A") -> 0.0595853 | M14: =IFERROR(M13/L13-1,"N/A") -> 0.060075259 | N14: 0.045 | O14: 0.046 | P14: 0.08 | Q14: 0.088 | R14: 0.075
C15: Gross Revenue [per Test] (LCA) | G15: 37 | H15: 38 | I15: 41 | J15: 43 | K15: 45 | L15: 47 | M15: 50 | N15: =M15*(1+N16) -> 52.9 | O15: =N15*(1+O16) -> 55.9682 | P15: =O15*(1+P16) -> 58.990483 | Q15: =P15*(1+Q16) -> 62.29395 | R15: =Q15*(1+R16) -> 66.405351
C16: Growth (%) | G16: =IFERROR(G15/F15-1,"N/A") -> N/A | H16: =IFERROR(H15/G15-1,"N/A") -> 0.027027027 | I16: =IFERROR(I15/H15-1,"N/A") -> 0.078947368 | J16: =IFERROR(J15/I15-1,"N/A") -> 0.048780488 | K16: =IFERROR(K15/J15-1,"N/A") -> 0.046511628 | L16: =IFERROR(L15/K15-1,"N/A") -> 0.044444444 | M16: =IFERROR(M15/L15-1,"N/A") -> 0.063829787 | N16: 0.058 | O16: 0.058 | P16: 0.054 | Q16: 0.056 | R16: 0.066
C17: Revenue | G17: =G13*G15 -> 3861727 | H17: =H13*H15 -> 3647164 | I17: =I13*I15 -> 4245017 | J17: =J13*J15 -> 4761175 | K17: =K13*K15 -> 5462505 | L17: =L13*L15 -> 6045234 | M17: =M13*M15 -> 6817450 | N17: =N13*N15 -> 7537440.9 | ... R17: =R13*R15 -> 12501557
C19: Radiology:
C20: # of Tests | G20: 26516 | H20: 25439 | I20: 27841 | J20: 30119 | K20: 31770 | L20: 33965 | M20: 36270 | N20: =M20*(1+N21) -> 38518.74 | O20: =N20*(1+O21) -> 40329.121 | P20: =O20*(1+P21) -> 42910.185 | Q20: =P20*(1+Q21) -> 45913.897 | R20: =Q20*(1+R21) -> 49770.665
C21: Growth (%) | G21: =IFERROR(G20/F20-1,"N/A") -> N/A | H21: =IFERROR(H20/G20-1,"N/A") -> -0.040616986 | I21: =IFERROR(I20/H20-1,"N/A") -> 0.094421951 | J21: =IFERROR(J20/I20-1,"N/A") -> 0.081821774 | K21: =IFERROR(K20/J20-1,"N/A") -> 0.054815897 | L21: =IFERROR(L20/K20-1,"N/A") -> 0.069090337 | M21: =IFERROR(M20/L20-1,"N/A") -> 0.067863978 | N21: 0.062 | O21: 0.047 | P21: 0.064 | Q21: 0.07 | R21: 0.084
C22: Gross Revenue [per Test] (LCA) | G22: 120 | H22: 121 | I22: 127 | J22: 136 | K22: 147 | L22: 155 | M22: 170 | N22: =M22*(1+N23) -> 177.14 | O22: =N22*(1+O23) -> 187.94554 | P22: =O22*(1+P23) -> 196.96693 | Q22: =P22*(1+Q23) -> 205.63347 | R22: =Q22*(1+R23) -> 220.02781
C23: Growth (%) | G23: =IFERROR(G22/F22-1,"N/A") -> N/A | H23: =IFERROR(H22/G22-1,"N/A") -> 0.0083333333 | I23: =IFERROR(I22/H22-1,"N/A") -> 0.049586777 | J23: =IFERROR(J22/I22-1,"N/A") -> 0.070866142 | K23: =IFERROR(K22/J22-1,"N/A") -> 0.080882353 | L23: =IFERROR(L22/K22-1,"N/A") -> 0.054421769 | M23: =IFERROR(M22/L22-1,"N/A") -> 0.096774194 | N23: 0.042 | O23: 0.061 | P23: 0.048 | Q23: 0.044 | R23: 0.07
C24: Revenue | G24: =G20*G22 -> 3181920 | H24: =H20*H22 -> 3078119 | I24: =I20*I22 -> 3535807 | J24: =J20*J22 -> 4096184 | K24: =K20*K22 -> 4670190 | L24: =L20*L22 -> 5264575 | M24: =M20*M22 -> 6165900 | N24: =N20*N22 -> 6823209.6 | ... R24: =R20*R22 -> 10950931
C26: Endoscopy:
C27: # of Visits | G27: 1831 | H27: 1709 | I27: 1814 | J27: 1969 | K27: 2062 | L27: 2203 | M27: 2347 | N27: =M27*(1+N28) -> 2504.249 | O27: =N27*(1+O28) -> 2702.0847 | P27: =O27*(1+P28) -> 2858.8056 | Q27: =P27*(1+Q28) -> 3027.4751 | R27: =Q27*(1+R28) -> 3175.8214
C28: Growth (%) | G28: =IFERROR(G27/F27-1,"N/A") -> N/A | H28: =IFERROR(H27/G27-1,"N/A") -> -0.066630257 | I28: =IFERROR(I27/H27-1,"N/A") -> 0.061439438 | J28: =IFERROR(J27/I27-1,"N/A") -> 0.085446527 | K28: =IFERROR(K27/J27-1,"N/A") -> 0.047232098 | L28: =IFERROR(L27/K27-1,"N/A") -> 0.068380213 | M28: =IFERROR(M27/L27-1,"N/A") -> 0.065365411 | N28: 0.067 | O28: 0.079 | P28: 0.058 | Q28: 0.059 | R28: 0.049
C29: Gross Revenue [per Visit] (LCA) | G29: 740 | H29: 769 | I29: 808 | J29: 888 | K29: 934 | L29: 1013 | M29: 1105 | N29: =M29*(1+N30) -> 1164.67 | O29: =N29*(1+O30) -> 1233.3855 | P29: =O29*(1+P30) -> 1319.7225 | Q29: =P29*(1+Q30) -> 1410.7834 | R29: =Q29*(1+R30) -> 1495.4304
C30: Growth (%) | G30: =IFERROR(G29/F29-1,"N/A") -> N/A | H30: =IFERROR(H29/G29-1,"N/A") -> 0.039189189 | I30: =IFERROR(I29/H29-1,"N/A") -> 0.050715215 | J30: =IFERROR(J29/I29-1,"N/A") -> 0.099009901 | K30: =IFERROR(K29/J29-1,"N/A") -> 0.051801802 | L30: =IFERROR(L29/K29-1,"N/A") -> 0.084582441 | M30: =IFERROR(M29/L29-1,"N/A") -> 0.090819348 | N30: 0.054 | O30: 0.059 | P30: 0.07 | Q30: 0.069 | R30: 0.06
C31: Revenue | G31: =G27*G29 -> 1354940 | H31: =H27*H29 -> 1314221 | I31: =I27*I29 -> 1465712 | J31: =J27*J29 -> 1748472 | K31: =K27*K29 -> 1925908 | L31: =L27*L29 -> 2231639 | M31: =M27*M29 -> 2593435 | N31: =N27*N29 -> 2916623.7 | ... R31: =R27*R29 -> 4749219.8
C33: Physiotherapy:
C34: # of Patients | G34: 5603 | H34: 5184 | I34: 5596 | J34: 5788 | K34: 6353 | L34: 6895 | M34: 7535 | N34: =M34*(1+N35) -> 7919.285 | O34: =N34*(1+O35) -> 8323.1685 | P34: =O34*(1+P35) -> 8672.7416 | Q34: =P34*(1+Q35) -> 9175.7606 | R34: =Q34*(1+R35) -> 9735.482
C35: Growth (%) | G35: =IFERROR(G34/F34-1,"N/A") -> N/A | H35: =IFERROR(H34/G34-1,"N/A") -> -0.074781367 | I35: =IFERROR(I34/H34-1,"N/A") -> 0.079475309 | J35: =IFERROR(J34/I34-1,"N/A") -> 0.034310222 | K35: =IFERROR(K34/J34-1,"N/A") -> 0.097615757 | L35: =IFERROR(L34/K34-1,"N/A") -> 0.085314025 | M35: =IFERROR(M34/L34-1,"N/A") -> 0.092820885 | N35: 0.051 | O35: 0.051 | P35: 0.042 | Q35: 0.058 | R35: 0.061
C36: Gross Revenue [per Patient] (LCA) | G36: 104 | H36: 107 | I36: 111 | J36: 120 | K36: 134 | L36: 144 | M36: 156 | N36: =M36*(1+N37) -> 163.8 | O36: =N36*(1+O37) -> 175.1022 | P36: =O36*(1+P37) -> 185.43323 | Q36: =P36*(1+Q37) -> 195.07576 | R36: =Q36*(1+R37) -> 206.58523
C37: Growth (%) | G37: =IFERROR(G36/F36-1,"N/A") -> N/A | H37: =IFERROR(H36/G36-1,"N/A") -> 0.028846154 | I37: =IFERROR(I36/H36-1,"N/A") -> 0.037383178 | J37: =IFERROR(J36/I36-1,"N/A") -> 0.081081081 | K37: =IFERROR(K36/J36-1,"N/A") -> 0.11666667 | L37: =IFERROR(L36/K36-1,"N/A") -> 0.074626866 | M37: =IFERROR(M36/L36-1,"N/A") -> 0.083333333 | N37: 0.05 | O37: 0.069 | P37: 0.059 | Q37: 0.052 | R37: 0.059
C38: Revenue | G38: =G34*G36 -> 582712 | H38: =H34*H36 -> 554688 | I38: =I34*I36 -> 621156 | J38: =J34*J36 -> 694560 | K38: =K34*K36 -> 851302 | L38: =L34*L36 -> 992880 | M38: =M34*M36 -> 1175460 | N38: =N34*N36 -> 1297178.9 | ... R38: =R34*R36 -> 2011206.8
C40: IVF:
C41: # of Patients | G41: 240 | H41: 218 | I41: 238 | J41: 259 | K41: 282 | L41: 308 | M41: 335 | N41: =M41*(1+N42) -> 349.74 | O41: =N41*(1+O42) -> 369.67518 | P41: =O41*(1+P42) -> 390.00731 | Q41: =P41*(1+Q42) -> 416.91782 | R41: =Q41*(1+R42) -> 448.18666
C42: Growth (%) | G42: =IFERROR(G41/F41-1,"N/A") -> N/A | H42: =IFERROR(H41/G41-1,"N/A") -> -0.091666667 | I42: =IFERROR(I41/H41-1,"N/A") -> 0.091743119 | J42: =IFERROR(J41/I41-1,"N/A") -> 0.088235294 | K42: =IFERROR(K41/J41-1,"N/A") -> 0.088803089 | L42: =IFERROR(L41/K41-1,"N/A") -> 0.092198582 | M42: =IFERROR(M41/L41-1,"N/A") -> 0.087662338 | N42: 0.044 | O42: 0.057 | P42: 0.055 | Q42: 0.069 | R42: 0.075
C43: Gross Revenue [per Patient] (LCA) | G43: 3968 | H43: 4025 | I43: 4222 | J43: 4423 | K43: 4706 | L43: 5167 | M43: 5518 | N43: =M43*(1+N44) -> 5815.972 | O43: =N43*(1+O44) -> 6159.1143 | P43: =O43*(1+P44) -> 6473.2292 | Q43: =P43*(1+Q44) -> 6777.471 | R43: =Q43*(1+R44) -> 7218.0066
C44: Growth (%) | G44: =IFERROR(G43/F43-1,"N/A") -> N/A | H44: =IFERROR(H43/G43-1,"N/A") -> 0.014364919 | I44: =IFERROR(I43/H43-1,"N/A") -> 0.048944099 | J44: =IFERROR(J43/I43-1,"N/A") -> 0.047607769 | K44: =IFERROR(K43/J43-1,"N/A") -> 0.063983721 | L44: =IFERROR(L43/K43-1,"N/A") -> 0.097960051 | M44: =IFERROR(M43/L43-1,"N/A") -> 0.067931101 | N44: 0.054 | O44: 0.059 | P44: 0.051 | Q44: 0.047 | R44: 0.065
C45: Revenue | G45: =G41*G43 -> 952320 | H45: =H41*H43 -> 877450 | I45: =I41*I43 -> 1004836 | J45: =J41*J43 -> 1145557 | K45: =K41*K43 -> 1327092 | L45: =L41*L43 -> 1591436 | M45: =M41*M43 -> 1848530 | N45: =N41*N43 -> 2034078 | ... R45: =R41*R43 -> 3235014.2
C47: Anapath:
C48: # of Patients | G48: 7417 | H48: 6961 | I48: 7592 | J48: 8178 | K48: 9185 | L48: 10117 | M48: 11179 | N48: =M48*(1+N49) -> 12017.425 | O48: =N48*(1+O49) -> 12954.784 | P48: =O48*(1+P49) -> 13615.478 | Q48: =P48*(1+Q49) -> 14486.869 | R48: =Q48*(1+R49) -> 15515.436
C49: Growth (%) | G49: =IFERROR(G48/F48-1,"N/A") -> N/A | H49: =IFERROR(H48/G48-1,"N/A") -> -0.061480383 | I49: =IFERROR(I48/H48-1,"N/A") -> 0.090647895 | J49: =IFERROR(J48/I48-1,"N/A") -> 0.077186512 | K49: =IFERROR(K48/J48-1,"N/A") -> 0.12313524 | L49: =IFERROR(L48/K48-1,"N/A") -> 0.10146979 | M49: =IFERROR(M48/L48-1,"N/A") -> 0.10497183 | N49: 0.075 | O49: 0.078 | P49: 0.051 | Q49: 0.064 | R49: 0.071
C50: Gross Revenue [per Patient] (LCA) | G50: 128 | H50: 125 | I50: 129 | J50: 135 | K50: 144 | L50: 156 | M50: 169 | N50: =M50*(1+N51) -> 177.281 | O50: =N50*(1+O51) -> 186.67689 | P50: =O50*(1+P51) -> 194.14397 | Q50: =P50*(1+Q51) -> 202.88045 | R50: =Q50*(1+R51) -> 214.64751
C51: Growth (%) | G51: =IFERROR(G50/F50-1,"N/A") -> N/A | H51: =IFERROR(H50/G50-1,"N/A") -> -0.0234375 | I51: =IFERROR(I50/H50-1,"N/A") -> 0.032 | J51: =IFERROR(J50/I50-1,"N/A") -> 0.046511628 | K51: =IFERROR(K50/J50-1,"N/A") -> 0.066666667 | L51: =IFERROR(L50/K50-1,"N/A") -> 0.083333333 | M51: =IFERROR(M50/L50-1,"N/A") -> 0.083333333 | N51: 0.049 | O51: 0.053 | P51: 0.04 | Q51: 0.045 | R51: 0.058
C52: Revenue | G52: =G48*G50 -> 949376 | H52: =H48*H50 -> 870125 | I52: =I48*I50 -> 979368 | J52: =J48*J50 -> 1104030 | K52: =K48*K50 -> 1322640 | L52: =L48*L50 -> 1578252 | M52: =M48*M50 -> 1889251 | N52: =N48*N50 -> 2130461.1 | ... R52: =R48*R50 -> 3330349.8
C54: Surgery:
C55: # of Surgeries | G55: 3926 | H55: 3671 | I55: 3956 | J55: 4304 | K55: 4734 | L55: 5063 | M55: 5382 | N55: =M55*(1+N56) -> 5613.426 | O55: =N55*(1+O56) -> 6068.1135 | P55: =O55*(1+P56) -> 6377.5873 | Q55: =P55*(1+Q56) -> 6760.2425 | R55: =Q55*(1+R56) -> 7145.5764
C56: Growth (%) | G56: =IFERROR(G55/F55-1,"N/A") -> N/A | H56: =IFERROR(H55/G55-1,"N/A") -> -0.064951605 | I56: =IFERROR(I55/H55-1,"N/A") -> 0.077635522 | J56: =IFERROR(J55/I55-1,"N/A") -> 0.087967644 | K56: =IFERROR(K55/J55-1,"N/A") -> 0.099907063 | L56: =IFERROR(L55/K55-1,"N/A") -> 0.069497254 | M56: =IFERROR(M55/L55-1,"N/A") -> 0.063006123 | N56: 0.043 | O56: 0.081 | P56: 0.051 | Q56: 0.06 | R56: 0.057
C57: Gross Revenue [per Surgery] (LCA) | G57: 2107 | H57: 2173 | I57: 2403 | J57: 2514 | K57: 2642 | L57: 2781 | M57: 2943 | N57: =M57*(1+N58) -> 3107.808 | O57: =N57*(1+O58) -> 3312.9233 | P57: =O57*(1+P58) -> 3501.76 | Q57: =P57*(1+Q58) -> 3690.855 | R57: =Q57*(1+R58) -> 3890.1612
C58: Growth (%) | G58: =IFERROR(G57/F57-1,"N/A") -> N/A | H58: =IFERROR(H57/G57-1,"N/A") -> 0.031324158 | I58: =IFERROR(I57/H57-1,"N/A") -> 0.10584445 | J58: =IFERROR(J57/I57-1,"N/A") -> 0.04619226 | K58: =IFERROR(K57/J57-1,"N/A") -> 0.050914877 | L58: =IFERROR(L57/K57-1,"N/A") -> 0.052611658 | M58: =IFERROR(M57/L57-1,"N/A") -> 0.058252427 | N58: 0.056 | O58: 0.066 | P58: 0.057 | Q58: 0.054 | R58: 0.054
C59: Revenue | G59: =G55*G57 -> 8272082 | H59: =H55*H57 -> 7977083 | I59: =I55*I57 -> 9506268 | J59: =J55*J57 -> 10820256 | K59: =K55*K57 -> 12507228 | L59: =L55*L57 -> 14080203 | M59: =M55*M57 -> 15839226 | N59: =N55*N57 -> 17445450 | ... R59: =R55*R57 -> 27797444
C61: Cardiac Cath:
C62: # of Surgeries | G62: 375 | H62: 355 | I62: 371 | J62: 412 | K62: 443 | L62: 492 | M62: 556 | N62: =M62*(1+N63) -> 582.132 | O62: =N62*(1+O63) -> 621.71698 | P62: =O62*(1+P63) -> 649.07252 | Q62: =P62*(1+Q63) -> 702.29647 | R62: =Q62*(1+R63) -> 743.02967
C63: Growth (%) | G63: =IFERROR(G62/F62-1,"N/A") -> N/A | H63: =IFERROR(H62/G62-1,"N/A") -> -0.053333333 | I63: =IFERROR(I62/H62-1,"N/A") -> 0.045070423 | J63: =IFERROR(J62/I62-1,"N/A") -> 0.11051213 | K63: =IFERROR(K62/J62-1,"N/A") -> 0.075242718 | L63: =IFERROR(L62/K62-1,"N/A") -> 0.11060948 | M63: =IFERROR(M62/L62-1,"N/A") -> 0.1300813 | N63: 0.047 | O63: 0.068 | P63: 0.044 | Q63: 0.082 | R63: 0.058
C64: Gross Revenue [per Surgery] (LCA) | G64: 4308 | H64: 4400 | I64: 4789 | J64: 4898 | K64: 5339 | L64: 5902 | M64: 6194 | N64: =M64*(1+N65) -> 6571.834 | O64: =N64*(1+O65) -> 6847.851 | P64: =O64*(1+P65) -> 7231.3307 | Q64: =P64*(1+Q65) -> 7585.6659 | R64: =Q64*(1+R65) -> 8010.4632
C65: Growth (%) | G65: =IFERROR(G64/F64-1,"N/A") -> N/A | H65: =IFERROR(H64/G64-1,"N/A") -> 0.021355617 | I65: =IFERROR(I64/H64-1,"N/A") -> 0.088409091 | J65: =IFERROR(J64/I64-1,"N/A") -> 0.022760493 | K65: =IFERROR(K64/J64-1,"N/A") -> 0.09003675 | L65: =IFERROR(L64/K64-1,"N/A") -> 0.10545046 | M65: =IFERROR(M64/L64-1,"N/A") -> 0.049474754 | N65: 0.061 | O65: 0.042 | P65: 0.056 | Q65: 0.049 | R65: 0.056
C66: Revenue | G66: =G62*G64 -> 1615500 | H66: =H62*H64 -> 1562000 | I66: =I62*I64 -> 1776719 | J66: =J62*J64 -> 2017976 | K66: =K62*K64 -> 2365177 | L66: =L62*L64 -> 2903784 | M66: =M62*M64 -> 3443864 | N66: =N62*N64 -> 3825674.9 | ... R66: =R62*R64 -> 5952011.8
C68: Heart Test:
C69: # of Tests | G69: 4988 | H69: 4726 | I69: 5191 | J69: 5688 | K69: 6158 | L69: 6695 | M69: 7380 | N69: =M69*(1+N70) -> 7844.94 | O69: =N69*(1+O70) -> 8292.1016 | P69: =O69*(1+P70) -> 8880.8408 | Q69: =P69*(1+Q70) -> 9440.3338 | R69: =Q69*(1+R70) -> 10242.762
C70: Growth (%) | G70: =IFERROR(G69/F69-1,"N/A") -> N/A | H70: =IFERROR(H69/G69-1,"N/A") -> -0.052526063 | I70: =IFERROR(I69/H69-1,"N/A") -> 0.098391875 | J70: =IFERROR(J69/I69-1,"N/A") -> 0.095742631 | K70: =IFERROR(K69/J69-1,"N/A") -> 0.082630098 | L70: =IFERROR(L69/K69-1,"N/A") -> 0.087203638 | M70: =IFERROR(M69/L69-1,"N/A") -> 0.10231516 | N70: 0.063 | O70: 0.057 | P70: 0.071 | Q70: 0.063 | R70: 0.085
C71: Gross Revenue [per Test] (LCA) | G71: 211 | H71: 219 | I71: 228 | J71: 241 | K71: 259 | L71: 265 | M71: 277 | N71: =M71*(1+N72) -> 295.559 | O71: =N71*(1+O72) -> 309.45027 | P71: =O71*(1+P72) -> 326.47004 | Q71: =P71*(1+Q72) -> 343.44648 | R71: =Q71*(1+R72) -> 360.96225
C72: Growth (%) | G72: =IFERROR(G71/F71-1,"N/A") -> N/A | H72: =IFERROR(H71/G71-1,"N/A") -> 0.037914692 | I72: =IFERROR(I71/H71-1,"N/A") -> 0.04109589 | J72: =IFERROR(J71/I71-1,"N/A") -> 0.057017544 | K72: =IFERROR(K71/J71-1,"N/A") -> 0.074688797 | L72: =IFERROR(L71/K71-1,"N/A") -> 0.023166023 | M72: =IFERROR(M71/L71-1,"N/A") -> 0.045283019 | N72: 0.067 | O72: 0.047 | P72: 0.055 | Q72: 0.052 | R72: 0.051
C73: Revenue | G73: =G69*G71 -> 1052468 | H73: =H69*H71 -> 1034994 | I73: =I69*I71 -> 1183548 | J73: =J69*J71 -> 1370808 | K73: =K69*K71 -> 1594922 | L73: =L69*L71 -> 1774175 | M73: =M69*M71 -> 2044260 | N73: =N69*N71 -> 2318642.6 | ... R73: =R69*R71 -> 3697250.5
C75: Emergency:
C76: # of Visits | G76: 16679 | H76: 15800 | I76: 16691 | J76: 18341 | K76: 19896 | L76: 21576 | M76: 22982 | N76: =M76*(1+N77) -> 24246.01 | O76: =N76*(1+O77) -> 25846.247 | P76: =O76*(1+P77) -> 27086.866 | Q76: =P76*(1+Q77) -> 28278.689 | R76: =Q76*(1+R77) -> 30145.082
C77: Growth (%) | G77: =IFERROR(G76/F76-1,"N/A") -> N/A | H77: =IFERROR(H76/G76-1,"N/A") -> -0.052701001 | I77: =IFERROR(I76/H76-1,"N/A") -> 0.056392405 | J77: =IFERROR(J76/I76-1,"N/A") -> 0.098855671 | K77: =IFERROR(K76/J76-1,"N/A") -> 0.084782727 | L77: =IFERROR(L76/K76-1,"N/A") -> 0.084439083 | M77: =IFERROR(M76/L76-1,"N/A") -> 0.065164998 | N77: 0.055 | O77: 0.066 | P77: 0.048 | Q77: 0.044 | R77: 0.066
C78: Gross Revenue [per Visit] (LCA) | G78: 152 | H78: 158 | I78: 161 | J78: 171 | K78: 177 | L78: 186 | M78: 197 | N78: =M78*(1+N79) -> 210.396 | O78: =N78*(1+O79) -> 220.9158 | P78: =O78*(1+P79) -> 229.75243 | Q78: =P78*(1+Q79) -> 245.14584 | R78: =Q78*(1+R79) -> 258.13857
C79: Growth (%) | G79: =IFERROR(G78/F78-1,"N/A") -> N/A | H79: =IFERROR(H78/G78-1,"N/A") -> 0.039473684 | I79: =IFERROR(I78/H78-1,"N/A") -> 0.018987342 | J79: =IFERROR(J78/I78-1,"N/A") -> 0.062111801 | K79: =IFERROR(K78/J78-1,"N/A") -> 0.035087719 | L79: =IFERROR(L78/K78-1,"N/A") -> 0.050847458 | M79: =IFERROR(M78/L78-1,"N/A") -> 0.059139785 | N79: 0.068 | O79: 0.05 | P79: 0.04 | Q79: 0.067 | R79: 0.053
C80: Revenue | G80: =G76*G78 -> 2535208 | H80: =H76*H78 -> 2496400 | I80: =I76*I78 -> 2687251 | J80: =J76*J78 -> 3136311 | K80: =K76*K78 -> 3521592 | L80: =L76*L78 -> 4013136 | M80: =M76*M78 -> 4527454 | N80: =N76*N78 -> 5101263.5 | ... R80: =R76*R78 -> 7781608.5
C82: Accommodation:
C83: # of Beds | G83: 168 | H83: 168 | I83: 168 | J83: 168 | K83: 176 | L83: 176 | M83: 176 | N83: =M83 -> 176 | O83: =N83 -> 176 | P83: =O83 -> 176 | Q83: =P83 -> 176 | R83: =Q83 -> 176
C84: Available Beds a Night | G84: =G83*360 -> 60480 | H84: =H83*360 -> 60480 | I84: =I83*360 -> 60480 | J84: =J83*360 -> 60480 | K84: =K83*360 -> 63360 | L84: =L83*360 -> 63360 | M84: =M83*360 -> 63360 | N84: =N83*360 -> 63360 | ... R84: =R83*360 -> 63360
C85: # of Occupied bed nights | G85: 45282 | H85: 39881 | I85: 43843 | J85: 41924 | K85: 48487 | L85: 45538 | M85: 47982 | N85: =N84*N86 -> 48723.84 | O85: =O84*O86 -> 49484.16 | P85: =P84*P86 -> 50244.48 | Q85: =Q84*Q86 -> 50688 | R85: =R84*R86 -> 50688
C86: Occupancy Ratio (%) | G86: =IFERROR(G85/G84,"N/A") -> 0.74871032 | H86: =IFERROR(H85/H84,"N/A") -> 0.65940807 | I86: =IFERROR(I85/I84,"N/A") -> 0.72491733 | J86: =IFERROR(J85/J84,"N/A") -> 0.69318783 | K86: =IFERROR(K85/K84,"N/A") -> 0.76526199 | L86: =IFERROR(L85/L84,"N/A") -> 0.71871843 | M86: =IFERROR(M85/M84,"N/A") -> 0.75729167 | N86: 0.769 | O86: 0.781 | P86: 0.793 | Q86: 0.8 | R86: 0.8
C87: Gross Revenue [per bed night] (LCA) | G87: 322 | H87: 327 | I87: 345 | J87: 369 | K87: 405 | L87: 438 | M87: 474 | N87: =M87*(1+N88) -> 499.122 | O87: =N87*(1+O88) -> 523.57898 | P87: =O87*(1+P88) -> 550.28151 | Q87: =P87*(1+Q88) -> 576.14474 | R87: =Q87*(1+R88) -> 603.22354
C88: Growth (%) | G88: =IFERROR(G87/F87-1,"N/A") -> N/A | H88: =IFERROR(H87/G87-1,"N/A") -> 0.01552795 | I88: =IFERROR(I87/H87-1,"N/A") -> 0.055045872 | J88: =IFERROR(J87/I87-1,"N/A") -> 0.069565217 | K88: =IFERROR(K87/J87-1,"N/A") -> 0.097560976 | L88: =IFERROR(L87/K87-1,"N/A") -> 0.081481481 | M88: =IFERROR(M87/L87-1,"N/A") -> 0.082191781 | N88: 0.053 | O88: 0.049 | P88: 0.051 | Q88: 0.047 | R88: 0.047
C89: Revenue | G89: =G85*G87 -> 14580804 | H89: =H85*H87 -> 13041087 | I89: =I85*I87 -> 15125835 | J89: =J85*J87 -> 15469956 | K89: =K85*K87 -> 19637235 | L89: =L85*L87 -> 19945644 | M89: =M85*M87 -> 22743468 | N89: =N85*N87 -> 24319140 | ... R89: =R85*R87 -> 30576195
C91: Radiotherapy:
C92: # of Sessions | G92: 0 | H92: 0 | I92: 0 | J92: 0 | K92: 0 | L92: 0 | M92: 0 | N92: =M92*(1+N93) -> 0 | O92: =N92*(1+O93) -> 0 | P92: =O92*(1+P93) -> 0 | Q92: =P92*(1+Q93) -> 0 | R92: =Q92*(1+R93) -> 0
C93: Growth (%) | G93: =IFERROR(G92/F92-1,"N/A") -> N/A | H93: =IFERROR(H92/G92-1,"N/A") -> N/A | I93: =IFERROR(I92/H92-1,"N/A") -> N/A | J93: =IFERROR(J92/I92-1,"N/A") -> N/A | K93: =IFERROR(K92/J92-1,"N/A") -> N/A | L93: =IFERROR(L92/K92-1,"N/A") -> N/A | M93: =IFERROR(M92/L92-1,"N/A") -> N/A | N93: 0 | O93: 0 | P93: 0 | Q93: 0 | R93: 0
C94: Gross Revenue [per Session] (LCA) | G94: 881 | H94: 884 | I94: 941 | J94: 1013 | K94: 1109 | L94: 1148 | M94: 1280 | N94: =M94*(1+N95) -> 1367.04 | O94: =N94*(1+O95) -> 1424.4557 | P94: =O94*(1+P95) -> 1504.2252 | Q94: =P94*(1+Q95) -> 1567.4027 | R94: =Q94*(1+R95) -> 1633.2336
C95: Growth (%) | G95: =IFERROR(G94/F94-1,"N/A") -> N/A | H95: =IFERROR(H94/G94-1,"N/A") -> 0.0034052213 | I95: =IFERROR(I94/H94-1,"N/A") -> 0.064479638 | J95: =IFERROR(J94/I94-1,"N/A") -> 0.076514346 | K95: =IFERROR(K94/J94-1,"N/A") -> 0.094768016 | L95: =IFERROR(L94/K94-1,"N/A") -> 0.035166817 | M95: =IFERROR(M94/L94-1,"N/A") -> 0.11498258 | N95: 0.068 | O95: 0.042 | P95: 0.056 | Q95: 0.042 | R95: 0.042
C96: Revenue | G96: =G92*G94 -> 0 | H96: =H92*H94 -> 0 | I96: =I92*I94 -> 0 | J96: =J92*J94 -> 0 | K96: =K92*K94 -> 0 | L96: =L92*L94 -> 0 | M96: =M92*M94 -> 0 | N96: =N92*N94 -> 0 | ... R96: =R92*R94 -> 0
C98: Nursing Fees:
C99: # of Visits | G99: 9059 | H99: 8456 | I99: 9185 | J99: 9995 | K99: 11164 | L99: 11596 | M99: 12385 | N99: =M99*(1+N100) -> 13338.645 | O99: =N99*(1+O100) -> 14218.996 | P99: =O99*(1+P100) -> 14858.85 | Q99: =P99*(1+Q100) -> 15958.405 | R99: =Q99*(1+R100) -> 16596.742
C100: Growth (%) | G100: =IFERROR(G99/F99-1,"N/A") -> N/A | H100: =IFERROR(H99/G99-1,"N/A") -> -0.066563638 | I100: =IFERROR(I99/H99-1,"N/A") -> 0.086210974 | J100: =IFERROR(J99/I99-1,"N/A") -> 0.088187262 | K100: =IFERROR(K99/J99-1,"N/A") -> 0.11695848 | L100: =IFERROR(L99/K99-1,"N/A") -> 0.038695808 | M100: =IFERROR(M99/L99-1,"N/A") -> 0.068040704 | N100: 0.077 | O100: 0.066 | P100: 0.045 | Q100: 0.074 | R100: 0.04
C101: Gross Revenue [per Visit] (LCA) | G101: 79 | H101: 82 | I101: 91 | J101: 99 | K101: 108 | L101: 117 | M101: 125 | N101: =M101*(1+N102) -> 131 | O101: =N101*(1+O102) -> 139.122 | P101: =O101*(1+P102) -> 148.72142 | Q101: =P101*(1+Q102) -> 159.13192 | R101: =Q101*(1+R102) -> 166.77025
C102: Growth (%) | G102: =IFERROR(G101/F101-1,"N/A") -> N/A | H102: =IFERROR(H101/G101-1,"N/A") -> 0.037974684 | I102: =IFERROR(I101/H101-1,"N/A") -> 0.1097561 | J102: =IFERROR(J101/I101-1,"N/A") -> 0.087912088 | K102: =IFERROR(K101/J101-1,"N/A") -> 0.090909091 | L102: =IFERROR(L101/K101-1,"N/A") -> 0.083333333 | M102: =IFERROR(M101/L101-1,"N/A") -> 0.068376068 | N102: 0.048 | O102: 0.062 | P102: 0.069 | Q102: 0.07 | R102: 0.048
C103: Revenue | G103: =G99*G101 -> 715661 | H103: =H99*H101 -> 693392 | I103: =I99*I101 -> 835835 | J103: =J99*J101 -> 989505 | K103: =K99*K101 -> 1205712 | L103: =L99*L101 -> 1356732 | M103: =M99*M101 -> 1548125 | N103: =N99*N101 -> 1747362.5 | ... R103: =R99*R101 -> 2767842.7
C105: Pharmacy:
C106: Gross Revenue (LCA) | G106: 2196000 | H106: 2127000 | I106: 2419000 | J106: 2724000 | K106: 3035000 | L106: 3531000 | M106: 3805000 | N106: =N108*(N17+N24+N31+N38+N45+N52+N59+N66+N73+N80+N89+N96+N103) -> 6509708.2 | O106: =O108*(O17+O24+O31+O38+O45+O52+O59+O66+O73+O80+O89+O96+O103) -> 6960327.5 | P106: =P108*(P17+P24+P31+P38+P45+P52+P59+P66+P73+P80+P89+P96+P103) -> 8505325.1 | Q106: =Q108*(Q17+Q24+Q31+Q38+Q45+Q52+Q59+Q66+Q73+Q80+Q89+Q96+Q103) -> 9393555.1 | R106: =R108*(R17+R24+R31+R38+R45+R52+R59+R66+R73+R80+R89+R96+R103) -> 10266206
C107: Growth (%) | G107: =IFERROR(G106/F106-1,"N/A") -> N/A | H107: =IFERROR(H106/G106-1,"N/A") -> -0.031420765 | I107: =IFERROR(I106/H106-1,"N/A") -> 0.13728256 | J107: =IFERROR(J106/I106-1,"N/A") -> 0.12608516 | K107: =IFERROR(K106/J106-1,"N/A") -> 0.11417034 | L107: =IFERROR(L106/K106-1,"N/A") -> 0.16342669 | M107: =IFERROR(M106/L106-1,"N/A") -> 0.077598414 | N107: =IFERROR(N106/M106-1,"N/A") -> 0.71083002 | ... R107: =IFERROR(R106/Q106-1,"N/A") -> 0.092898913
C108: % of Other Hospital Revenue | G108: =IFERROR(G106/(G17+G24+G31+G38+G45+G52+G59+G66+G73+G80+G89+G96+G103),"N/A") -> 0.055378026 | H108: =IFERROR(H106/(H17+H24+H31+H38+H45+H52+H59+H66+H73+H80+H89+H96+H103),"N/A") -> 0.057259425 | I108: =IFERROR(I106/(I17+I24+I31+I38+I45+I52+I59+I66+I73+I80+I89+I96+I103),"N/A") -> 0.056298559 | J108: =IFERROR(J106/(J17+J24+J31+J38+J45+J52+J59+J66+J73+J80+J89+J96+J103),"N/A") -> 0.05752322 | K108: =IFERROR(K106/(K17+K24+K31+K38+K45+K52+K59+K66+K73+K80+K89+K96+K103),"N/A") -> 0.053820165 | L108: =IFERROR(L106/(L17+L24+L31+L38+L45+L52+L59+L66+L73+L80+L89+L96+L103),"N/A") -> 0.057156556 | M108: =IFERROR(M106/(M17+M24+M31+M38+M45+M52+M59+M66+M73+M80+M89+M96+M103),"N/A") -> 0.053867394 | N108: 0.084 | O108: 0.081 | P108: 0.09 | Q108: 0.09 | R108: 0.089
C109: Revenue | G109: =G106 -> 2196000 | H109: =H106 -> 2127000 | I109: =I106 -> 2419000 | J109: =J106 -> 2724000 | K109: =K106 -> 3035000 | L109: =L106 -> 3531000 | M109: =M106 -> 3805000 | N109: =N106 -> 6509708.2 | ... R109: =R106 -> 10266206
C111: Total Hospital Revenue (LCA) | G111: =G17+G24+G31+G38+G45+G52+G59+G66+G73+G80+G89+G96+G103+G109 -> 41850718 | H111: =H17+H24+H31+H38+H45+H52+H59+H66+H73+H80+H89+H96+H103+H109 -> 39273723 | I111: =I17+I24+I31+I38+I45+I52+I59+I66+I73+I80+I89+I96+I103+I109 -> 45386352 | J111: =J17+J24+J31+J38+J45+J52+J59+J66+J73+J80+J89+J96+J103+J109 -> 50078790 | K111: =K17+K24+K31+K38+K45+K52+K59+K66+K73+K80+K89+K96+K103+K109 -> 59426503 | L111: =L17+L24+L31+L38+L45+L52+L59+L66+L73+L80+L89+L96+L103+L109 -> 65308690 | M111: =M17+M24+M31+M38+M45+M52+M59+M66+M73+M80+M89+M96+M103+M109 -> 74441423 | N111: =N17+N24+N31+N38+N45+N52+N59+N66+N73+N80+N89+N96+N103+N109 -> 84006235 | ... R111: =R17+R24+R31+R38+R45+R52+R59+R66+R73+R80+R89+R96+R103+R109 -> 1.2561684e+08
C113: B | D113: Cost Assumptions
C114: Expenses:
C115: COGS – % of Sales (%) | G115: =IFERROR(G116/G111,"N/A") -> 0.28723522 | H115: =IFERROR(H116/H111,"N/A") -> 0.30455478 | I115: =IFERROR(I116/I111,"N/A") -> 0.28226547 | J115: =IFERROR(J116/J111,"N/A") -> 0.31638145 | K115: =IFERROR(K116/K111,"N/A") -> 0.29051011 | L115: =IFERROR(L116/L111,"N/A") -> 0.30576329 | M115: =IFERROR(M116/M111,"N/A") -> 0.30478998 | N115: 0.2959 | O115: 0.3005 | P115: 0.287 | Q115: 0.2909 | R115: 0.2888
C116: COGS (LCA) | G116: 12021000 | H116: 11961000 | I116: 12811000 | J116: 15844000 | K116: 17264000 | L116: 19969000 | M116: 22689000 | N116: =N115*N111 -> 24857445 | O116: =O115*O111 -> 27913534 | P116: =P115*P111 -> 29563565 | Q116: =Q115*Q111 -> 33094643 | R116: =R115*R111 -> 36278142
C117: Payroll – % of Sales (%) | G117: =IFERROR(G118/G111,"N/A") -> 0.33590822 | H117: =IFERROR(H118/H111,"N/A") -> 0.32051965 | I117: =IFERROR(I118/I111,"N/A") -> 0.31419137 | J117: =IFERROR(J118/J111,"N/A") -> 0.314125 | K117: =IFERROR(K118/K111,"N/A") -> 0.33015572 | L117: =IFERROR(L118/L111,"N/A") -> 0.34264965 | M117: =IFERROR(M118/M111,"N/A") -> 0.32434899 | N117: 0.336 | O117: 0.3206 | P117: 0.3264 | Q117: 0.3238 | R117: 0.3305
C118: Payroll (LCA) | G118: 14058000 | H118: 12588000 | I118: 14260000 | J118: 15731000 | K118: 19620000 | L118: 22378000 | M118: 24145000 | N118: =N117*N111 -> 28226095 | O118: =O117*O111 -> 29780629 | P118: =P117*P111 -> 33622117 | Q118: =Q117*Q111 -> 36837557 | R118: =R117*R111 -> 41516365
C119: OPEX – % of Sales (%) | G119: =IFERROR(G120/G111,"N/A") -> 0.14546943 | H119: =IFERROR(H120/H111,"N/A") -> 0.13978812 | I119: =IFERROR(I120/I111,"N/A") -> 0.14696048 | J119: =IFERROR(J120/J111,"N/A") -> 0.14571039 | K119: =IFERROR(K120/K111,"N/A") -> 0.14072846 | L119: =IFERROR(L120/L111,"N/A") -> 0.14843354 | M119: =IFERROR(M120/M111,"N/A") -> 0.13327257 | N119: 0.1445 | O119: 0.14 | P119: 0.1369 | Q119: 0.1447 | R119: 0.1448
...

Sheet 2. AHG Coast
C3: =Cover!$C$3 -> Project Dunecrest | D3: Confidential
C4: AHG Coast – Operating Build
C6: Fiscal Year Ending | G6: 43830 | H6: 44196 | I6: 44561 | J6: 44926 | K6: =EOMONTH(J6,12) -> 45291 | L6: =EOMONTH(K6,12) -> 45657 | M6: =EOMONTH(L6,12) -> 46022 | N6: =EOMONTH(M6,12) -> 46387 | O6: =EOMONTH(N6,12) -> 46752 | P6: =EOMONTH(O6,12) -> 47118 | Q6: =EOMONTH(P6,12) -> 47483 | R6: =EOMONTH(Q6,12) -> 47848
C7: Fiscal Year | G7: =YEAR(G6) -> 2019 | H7: =YEAR(H6) -> 2020 | I7: =YEAR(I6) -> 2021 | J7: =YEAR(J6) -> 2022 | K7: =YEAR(K6) -> 2023 | L7: =YEAR(L6) -> 2024 | M7: =YEAR(M6) -> 2025 | N7: =YEAR(N6) -> 2026 | ... R7: =YEAR(R6) -> 2030
C8: Actual / Estimate | G8: =IF(G6<=Control!$E$11,"A","E") -> A | H8: =IF(H6<=Control!$E$11,"A","E") -> A | I8: =IF(I6<=Control!$E$11,"A","E") -> A | J8: =IF(J6<=Control!$E$11,"A","E") -> A | K8: =IF(K6<=Control!$E$11,"A","E") -> A | L8: =IF(L6<=Control!$E$11,"A","E") -> A | M8: =IF(M6<=Control!$E$11,"A","E") -> A | N8: =IF(N6<=Control!$E$11,"A","E") -> E | ... R8: =IF(R6<=Control!$E$11,"A","E") -> E
C10: Supporting Data
C11: A | D11: Revenue Build | E11: ="("&Control!$E$16&" in Actual)" -> (LCA in Actual)
C12: Laboratory:
C13: # of Tests | G13: 71942 | H13: 66041 | I13: 73822 | J13: 82138 | K13: 89179 | L13: 100453 | M13: 111021 | N13: =M13*(1+N14) -> 116905.11 | O13: =N13*(1+O14) -> 125322.28 | P13: =O13*(1+P14) -> 135724.03 | Q13: =P13*(1+Q14) -> 141152.99 | R13: =Q13*(1+R14) -> 153574.45
C14: Growth (%) | G14: =IFERROR(G13/F13-1,"N/A") -> N/A | H14: =IFERROR(H13/G13-1,"N/A") -> -0.082024409 | I14: =IFERROR(I13/H13-1,"N/A") -> 0.11782075 | J14: =IFERROR(J13/I13-1,"N/A") -> 0.11264935 | K14: =IFERROR(K13/J13-1,"N/A") -> 0.08572159 | L14: =IFERROR(L13/K13-1,"N/A") -> 0.1264199 | M14: =IFERROR(M13/L13-1,"N/A") -> 0.10520343 | N14: 0.053 | O14: 0.072 | P14: 0.083 | Q14: 0.04 | R14: 0.088
C15: Gross Revenue [per Test] (LCA) | G15: 36 | H15: 38 | I15: 41 | J15: 45 | K15: 47 | L15: 52 | M15: 57 | N15: =M15*(1+N16) -> 60.192 | O15: =N15*(1+O16) -> 63.081216 | P15: =O15*(1+P16) -> 65.982952 | Q15: =P15*(1+Q16) -> 69.414065 | R15: =Q15*(1+R16) -> 73.440081
C16: Growth (%) | G16: =IFERROR(G15/F15-1,"N/A") -> N/A | H16: =IFERROR(H15/G15-1,"N/A") -> 0.055555556 | I16: =IFERROR(I15/H15-1,"N/A") -> 0.078947368 | J16: =IFERROR(J15/I15-1,"N/A") -> 0.097560976 | K16: =IFERROR(K15/J15-1,"N/A") -> 0.044444444 | L16: =IFERROR(L15/K15-1,"N/A") -> 0.10638298 | M16: =IFERROR(M15/L15-1,"N/A") -> 0.096153846 | N16: 0.056 | O16: 0.048 | P16: 0.046 | Q16: 0.052 | R16: 0.058
C17: Revenue | G17: =G13*G15 -> 2589912 | H17: =H13*H15 -> 2509558 | I17: =I13*I15 -> 3026702 | J17: =J13*J15 -> 3696210 | K17: =K13*K15 -> 4191413 | L17: =L13*L15 -> 5223556 | M17: =M13*M15 -> 6328197 | N17: =N13*N15 -> 7036752.6 | ... R17: =R13*R15 -> 11278520
C19: Radiology:
C20: # of Tests | G20: 18306 | H20: 16987 | I20: 18274 | J20: 19518 | K20: 21243 | L20: 22998 | M20: 24489 | N20: =M20*(1+N21) -> 26056.296 | O20: =N20*(1+O21) -> 27463.336 | P20: =O20*(1+P21) -> 28809.039 | Q20: =P20*(1+Q21) -> 30739.245 | R20: =Q20*(1+R21) -> 32214.729
C21: Growth (%) | G21: =IFERROR(G20/F20-1,"N/A") -> N/A | H21: =IFERROR(H20/G20-1,"N/A") -> -0.072052879 | I21: =IFERROR(I20/H20-1,"N/A") -> 0.075763819 | J21: =IFERROR(J20/I20-1,"N/A") -> 0.06807486 | K21: =IFERROR(K20/J20-1,"N/A") -> 0.088379957 | L21: =IFERROR(L20/K20-1,"N/A") -> 0.08261545 | M21: =IFERROR(M20/L20-1,"N/A") -> 0.064831724 | N21: 0.064 | O21: 0.054 | P21: 0.049 | Q21: 0.067 | R21: 0.048
C22: Gross Revenue [per Test] (LCA) | G22: 115 | H22: 117 | I22: 123 | J22: 126 | K22: 130 | L22: 140 | M22: 145 | N22: =M22*(1+N23) -> 150.8 | O22: =N22*(1+O23) -> 157.2844 | P22: =O22*(1+P23) -> 164.04763 | Q22: =P22*(1+Q23) -> 171.59382 | R22: =Q22*(1+R23) -> 183.2622
C23: Growth (%) | G23: =IFERROR(G22/F22-1,"N/A") -> N/A | H23: =IFERROR(H22/G22-1,"N/A") -> 0.017391304 | I23: =IFERROR(I22/H22-1,"N/A") -> 0.051282051 | J23: =IFERROR(J22/I22-1,"N/A") -> 0.024390244 | K23: =IFERROR(K22/J22-1,"N/A") -> 0.031746032 | L23: =IFERROR(L22/K22-1,"N/A") -> 0.076923077 | M23: =IFERROR(M22/L22-1,"N/A") -> 0.035714286 | N23: 0.04 | O23: 0.043 | P23: 0.043 | Q23: 0.046 | R23: 0.068
C24: Revenue | G24: =G20*G22 -> 2105190 | H24: =H20*H22 -> 1987479 | I24: =I20*I22 -> 2247702 | J24: =J20*J22 -> 2459268 | K24: =K20*K22 -> 2761590 | L24: =L20*L22 -> 3219720 | M24: =M20*M22 -> 3550905 | N24: =N20*N22 -> 3929289.4 | ... R24: =R20*R22 -> 5903742.1
C26: Endoscopy:
C27: # of Visits | G27: 1241 | H27: 1153 | I27: 1230 | J27: 1330 | K27: 1444 | L27: 1545 | M27: 1720 | N27: =M27*(1+N28) -> 1823.2 | O27: =N27*(1+O28) -> 1919.8296 | P27: =O27*(1+P28) -> 2040.7789 | Q27: =P27*(1+Q28) -> 2144.8586 | R27: =Q27*(1+R28) -> 2320.737
C28: Growth (%) | G28: =IFERROR(G27/F27-1,"N/A") -> N/A | H28: =IFERROR(H27/G27-1,"N/A") -> -0.070910556 | I28: =IFERROR(I27/H27-1,"N/A") -> 0.066782307 | J28: =IFERROR(J27/I27-1,"N/A") -> 0.081300813 | K28: =IFERROR(K27/J27-1,"N/A") -> 0.085714286 | L28: =IFERROR(L27/K27-1,"N/A") -> 0.069944598 | M28: =IFERROR(M27/L27-1,"N/A") -> 0.11326861 | N28: 0.06 | O28: 0.053 | P28: 0.063 | Q28: 0.051 | R28: 0.082
C29: Gross Revenue [per Visit] (LCA) | G29: 774 | H29: 802 | I29: 869 | J29: 897 | K29: 948 | L29: 985 | M29: 1073 | N29: =M29*(1+N30) -> 1123.431 | O29: =N29*(1+O30) -> 1175.1088 | P29: =O29*(1+P30) -> 1239.7398 | Q29: =P29*(1+Q30) -> 1289.3294 | R29: =Q29*(1+R30) -> 1377.0038
C30: Growth (%) | G30: =IFERROR(G29/F29-1,"N/A") -> N/A | H30: =IFERROR(H29/G29-1,"N/A") -> 0.036175711 | I30: =IFERROR(I29/H29-1,"N/A") -> 0.083541147 | J30: =IFERROR(J29/I29-1,"N/A") -> 0.032220944 | K30: =IFERROR(K29/J29-1,"N/A") -> 0.056856187 | L30: =IFERROR(L29/K29-1,"N/A") -> 0.039029536 | M30: =IFERROR(M29/L29-1,"N/A") -> 0.089340102 | N30: 0.047 | O30: 0.046 | P30: 0.055 | Q30: 0.04 | R30: 0.068
C31: Revenue | G31: =G27*G29 -> 960534 | H31: =H27*H29 -> 924706 | I31: =I27*I29 -> 1068870 | J31: =J27*J29 -> 1193010 | K31: =K27*K29 -> 1368912 | L31: =L27*L29 -> 1521825 | M31: =M27*M29 -> 1845560 | N31: =N27*N29 -> 2048239.4 | ... R31: =R27*R29 -> 3195663.7
C33: Physiotherapy:
C34: # of Patients | G34: 3784 | H34: 3468 | I34: 3841 | J34: 4183 | K34: 4642 | L34: 4960 | M34: 5529 | N34: =M34*(1+N35) -> 5910.501 | O34: =N34*(1+O35) -> 6430.6251 | P34: =O34*(1+P35) -> 6932.2138 | Q34: =P34*(1+Q35) -> 7459.0621 | R34: =Q34*(1+R35) -> 8055.7871
C35: Growth (%) | G35: =IFERROR(G34/F34-1,"N/A") -> N/A | H35: =IFERROR(H34/G34-1,"N/A") -> -0.083509514 | I35: =IFERROR(I34/H34-1,"N/A") -> 0.10755479 | J35: =IFERROR(J34/I34-1,"N/A") -> 0.089039313 | K35: =IFERROR(K34/J34-1,"N/A") -> 0.10972986 | L35: =IFERROR(L34/K34-1,"N/A") -> 0.068504955 | M35: =IFERROR(M34/L34-1,"N/A") -> 0.11471774 | N35: 0.069 | O35: 0.088 | P35: 0.078 | Q35: 0.076 | R35: 0.08
C36: Gross Revenue [per Patient] (LCA) | G36: 104 | H36: 106 | I36: 111 | J36: 118 | K36: 124 | L36: 128 | M36: 142 | N36: =M36*(1+N37) -> 151.372 | O36: =N36*(1+O37) -> 159.39472 | P36: =O36*(1+P37) -> 166.40808 | Q36: =P36*(1+Q37) -> 174.56208 | R36: =Q36*(1+R37) -> 185.55949
C37: Growth (%) | G37: =IFERROR(G36/F36-1,"N/A") -> N/A | H37: =IFERROR(H36/G36-1,"N/A") -> 0.019230769 | I37: =IFERROR(I36/H36-1,"N/A") -> 0.047169811 | J37: =IFERROR(J36/I36-1,"N/A") -> 0.063063063 | K37: =IFERROR(K36/J36-1,"N/A") -> 0.050847458 | L37: =IFERROR(L36/K36-1,"N/A") -> 0.032258065 | M37: =IFERROR(M36/L36-1,"N/A") -> 0.109375 | N37: 0.066 | O37: 0.053 | P37: 0.044 | Q37: 0.049 | R37: 0.063
C38: Revenue | G38: =G34*G36 -> 393536 | H38: =H34*H36 -> 367608 | I38: =I34*I36 -> 426351 | J38: =J34*J36 -> 493594 | K38: =K34*K36 -> 575608 | L38: =L34*L36 -> 634880 | M38: =M34*M36 -> 785118 | N38: =N34*N36 -> 894684.36 | ... R38: =R34*R36 -> 1494827.7
C40: IVF:
C41: # of Patients | G41: 0 | H41: 0 | I41: 0 | J41: 0 | K41: 0 | L41: 0 | M41: 0 | N41: =M41*(1+N42) -> 0 | O41: =N41*(1+O42) -> 0 | P41: =O41*(1+P42) -> 0 | Q41: =P41*(1+Q42) -> 0 | R41: =Q41*(1+R42) -> 0
C42: Growth (%) | G42: =IFERROR(G41/F41-1,"N/A") -> N/A | H42: =IFERROR(H41/G41-1,"N/A") -> N/A | I42: =IFERROR(I41/H41-1,"N/A") -> N/A | J42: =IFERROR(J41/I41-1,"N/A") -> N/A | K42: =IFERROR(K41/J41-1,"N/A") -> N/A | L42: =IFERROR(L41/K41-1,"N/A") -> N/A | M42: =IFERROR(M41/L41-1,"N/A") -> N/A | N42: 0 | O42: 0 | P42: 0 | Q42: 0 | R42: 0
C43: Gross Revenue [per Patient] (LCA) | G43: 3860 | H43: 3854 | I43: 4006 | J43: 4154 | K43: 4389 | L43: 4698 | M43: 5086 | N43: =M43*(1+N44) -> 5304.698 | O43: =N43*(1+O44) -> 5548.7141 | P43: =O43*(1+P44) -> 5815.0524 | Q43: =P43*(1+Q44) -> 6210.4759 | R43: =Q43*(1+R44) -> 6514.7893
C44: Growth (%) | G44: =IFERROR(G43/F43-1,"N/A") -> N/A | H44: =IFERROR(H43/G43-1,"N/A") -> -0.0015544041 | I44: =IFERROR(I43/H43-1,"N/A") -> 0.039439543 | J44: =IFERROR(J43/I43-1,"N/A") -> 0.036944583 | K44: =IFERROR(K43/J43-1,"N/A") -> 0.056571979 | L44: =IFERROR(L43/K43-1,"N/A") -> 0.070403281 | M44: =IFERROR(M43/L43-1,"N/A") -> 0.082588335 | N44: 0.043 | O44: 0.046 | P44: 0.048 | Q44: 0.068 | R44: 0.049
C45: Revenue | G45: =G41*G43 -> 0 | H45: =H41*H43 -> 0 | I45: =I41*I43 -> 0 | J45: =J41*J43 -> 0 | K45: =K41*K43 -> 0 | L45: =L41*L43 -> 0 | M45: =M41*M43 -> 0 | N45: =N41*N43 -> 0 | ... R45: =R41*R43 -> 0
C47: Anapath:
C48: # of Patients | G48: 5286 | H48: 4911 | I48: 5362 | J48: 5881 | K48: 6277 | L48: 6722 | M48: 7105 | N48: =M48*(1+N49) -> 7424.725 | O48: =N48*(1+O49) -> 8033.5525 | P48: =O48*(1+P49) -> 8395.0623 | Q48: =P48*(1+Q49) -> 8974.3216 | R48: =Q48*(1+R49) -> 9432.012
C49: Growth (%) | G49: =IFERROR(G48/F48-1,"N/A") -> N/A | H49: =IFERROR(H48/G48-1,"N/A") -> -0.070942111 | I49: =IFERROR(I48/H48-1,"N/A") -> 0.091834657 | J49: =IFERROR(J48/I48-1,"N/A") -> 0.096792242 | K49: =IFERROR(K48/J48-1,"N/A") -> 0.067335487 | L49: =IFERROR(L48/K48-1,"N/A") -> 0.070893739 | M49: =IFERROR(M48/L48-1,"N/A") -> 0.05697709 | N49: 0.045 | O49: 0.082 | P49: 0.045 | Q49: 0.069 | R49: 0.051
C50: Gross Revenue [per Patient] (LCA) | G50: 131 | H50: 138 | I50: 151 | J50: 163 | K50: 177 | L50: 192 | M50: 204 | N50: =M50*(1+N51) -> 217.056 | O50: =N50*(1+O51) -> 228.55997 | P50: =O50*(1+P51) -> 243.18781 | Q50: =P50*(1+Q51) -> 258.26545 | R50: =Q50*(1+R51) -> 272.47005
C51: Growth (%) | G51: =IFERROR(G50/F50-1,"N/A") -> N/A | H51: =IFERROR(H50/G50-1,"N/A") -> 0.053435115 | I51: =IFERROR(I50/H50-1,"N/A") -> 0.094202899 | J51: =IFERROR(J50/I50-1,"N/A") -> 0.079470199 | K51: =IFERROR(K50/J50-1,"N/A") -> 0.085889571 | L51: =IFERROR(L50/K50-1,"N/A") -> 0.084745763 | M51: =IFERROR(M50/L50-1,"N/A") -> 0.0625 | N51: 0.064 | O51: 0.053 | P51: 0.064 | Q51: 0.062 | R51: 0.055
C52: Revenue | G52: =G48*G50 -> 692466 | H52: =H48*H50 -> 677718 | I52: =I48*I50 -> 809662 | J52: =J48*J50 -> 958603 | K52: =K48*K50 -> 1111029 | L52: =L48*L50 -> 1290624 | M52: =M48*M50 -> 1449420 | N52: =N48*N50 -> 1611581.1 | ... R52: =R48*R50 -> 2569940.8
C54: Surgery:
C55: # of Surgeries | G55: 2806 | H55: 2560 | I55: 2814 | J55: 3094 | K55: 3237 | L55: 3526 | M55: 3875 | N55: =M55*(1+N56) -> 4041.625 | O55: =N55*(1+O56) -> 4312.4139 | P55: =O55*(1+P56) -> 4502.1601 | Q55: =P55*(1+Q56) -> 4790.2983 | R55: =Q55*(1+R56) -> 5025.0229
C56: Growth (%) | G56: =IFERROR(G55/F55-1,"N/A") -> N/A | H56: =IFERROR(H55/G55-1,"N/A") -> -0.08766928 | I56: =IFERROR(I55/H55-1,"N/A") -> 0.09921875 | J56: =IFERROR(J55/I55-1,"N/A") -> 0.099502488 | K56: =IFERROR(K55/J55-1,"N/A") -> 0.046218487 | L56: =IFERROR(L55/K55-1,"N/A") -> 0.089280198 | M56: =IFERROR(M55/L55-1,"N/A") -> 0.098979013 | N56: 0.043 | O56: 0.067 | P56: 0.044 | Q56: 0.064 | R56: 0.049
C57: Gross Revenue [per Surgery] (LCA) | G57: 2007 | H57: 2066 | I57: 2212 | J57: 2429 | K57: 2557 | L57: 2738 | M57: 2981 | N57: =M57*(1+N58) -> 3159.86 | O57: =N57*(1+O58) -> 3358.9312 | P57: =O57*(1+P58) -> 3563.826 | Q57: =P57*(1+Q58) -> 3763.4002 | R57: =Q57*(1+R58) -> 4008.0213
C58: Growth (%) | G58: =IFERROR(G57/F57-1,"N/A") -> N/A | H58: =IFERROR(H57/G57-1,"N/A") -> 0.02939711 | I58: =IFERROR(I57/H57-1,"N/A") -> 0.070667957 | J58: =IFERROR(J57/I57-1,"N/A") -> 0.098101266 | K58: =IFERROR(K57/J57-1,"N/A") -> 0.052696583 | L58: =IFERROR(L57/K57-1,"N/A") -> 0.070786077 | M58: =IFERROR(M57/L57-1,"N/A") -> 0.088750913 | N58: 0.06 | O58: 0.063 | P58: 0.061 | Q58: 0.056 | R58: 0.065
C59: Revenue | G59: =G55*G57 -> 5631642 | H59: =H55*H57 -> 5288960 | I59: =I55*I57 -> 6224568 | J59: =J55*J57 -> 7515326 | K59: =K55*K57 -> 8277009 | L59: =L55*L57 -> 9654188 | M59: =M55*M57 -> 11551375 | N59: =N55*N57 -> 12770969 | ... R59: =R55*R57 -> 20140399
C61: Cardiac Cath:
C62: # of Surgeries | G62: 0 | H62: 0 | I62: 0 | J62: 0 | K62: 0 | L62: 0 | M62: 0 | N62: =M62*(1+N63) -> 0 | O62: =N62*(1+O63) -> 0 | P62: =O62*(1+P63) -> 0 | Q62: =P62*(1+Q63) -> 0 | R62: =Q62*(1+R63) -> 0
C63: Growth (%) | G63: =IFERROR(G62/F62-1,"N/A") -> N/A | H63: =IFERROR(H62/G62-1,"N/A") -> N/A | I63: =IFERROR(I62/H62-1,"N/A") -> N/A | J63: =IFERROR(J62/I62-1,"N/A") -> N/A | K63: =IFERROR(K62/J62-1,"N/A") -> N/A | L63: =IFERROR(L62/K62-1,"N/A") -> N/A | M63: =IFERROR(M62/L62-1,"N/A") -> N/A | N63: 0 | O63: 0 | P63: 0 | Q63: 0 | R63: 0
C64: Gross Revenue [per Surgery] (LCA) | G64: 4395 | H64: 4540 | I64: 4898 | J64: 5108 | K64: 5443 | L64: 5659 | M64: 6116 | N64: =M64*(1+N65) -> 6464.612 | O64: =N64*(1+O65) -> 6839.5595 | P64: =O64*(1+P65) -> 7154.1792 | Q64: =P64*(1+Q65) -> 7590.5842 | R64: =Q64*(1+R65) -> 8076.3816
C65: Growth (%) | G65: =IFERROR(G64/F64-1,"N/A") -> N/A | H65: =IFERROR(H64/G64-1,"N/A") -> 0.032992036 | I65: =IFERROR(I64/H64-1,"N/A") -> 0.078854626 | J65: =IFERROR(J64/I64-1,"N/A") -> 0.042874643 | K65: =IFERROR(K64/J64-1,"N/A") -> 0.065583399 | L65: =IFERROR(L64/K64-1,"N/A") -> 0.039683998 | M65: =IFERROR(M64/L64-1,"N/A") -> 0.080756317 | N65: 0.057 | O65: 0.058 | P65: 0.046 | Q65: 0.061 | R65: 0.064
C66: Revenue | G66: =G62*G64 -> 0 | H66: =H62*H64 -> 0 | I66: =I62*I64 -> 0 | J66: =J62*J64 -> 0 | K66: =K62*K64 -> 0 | L66: =L62*L64 -> 0 | M66: =M62*M64 -> 0 | N66: =N62*N64 -> 0 | ... R66: =R62*R64 -> 0
C68: Heart Test:
C69: # of Tests | G69: 3395 | H69: 3186 | I69: 3487 | J69: 3871 | K69: 4258 | L69: 4548 | M69: 4886 | N69: =M69*(1+N70) -> 5257.336 | O69: =N69*(1+O70) -> 5614.8348 | P69: =O69*(1+P70) -> 5946.1101 | Q69: =P69*(1+Q70) -> 6267.2 | R69: =Q69*(1+R70) -> 6712.1713
C70: Growth (%) | G70: =IFERROR(G69/F69-1,"N/A") -> N/A | H70: =IFERROR(H69/G69-1,"N/A") -> -0.061561119 | I70: =IFERROR(I69/H69-1,"N/A") -> 0.094475832 | J70: =IFERROR(J69/I69-1,"N/A") -> 0.11012332 | K70: =IFERROR(K69/J69-1,"N/A") -> 0.099974167 | L70: =IFERROR(L69/K69-1,"N/A") -> 0.068107093 | M70: =IFERROR(M69/L69-1,"N/A") -> 0.074318382 | N70: 0.076 | O70: 0.068 | P70: 0.059 | Q70: 0.054 | R70: 0.071
C71: Gross Revenue [per Test] (LCA) | G71: 213 | H71: 212 | I71: 225 | J71: 239 | K71: 257 | L71: 277 | M71: 302 | N71: =M71*(1+N72) -> 320.422 | O71: =N71*(1+O72) -> 340.60859 | P71: =O71*(1+P72) -> 355.25476 | Q71: =P71*(1+Q72) -> 376.57004 | R71: =Q71*(1+R72) -> 395.39854
C72: Growth (%) | G72: =IFERROR(G71/F71-1,"N/A") -> N/A | H72: =IFERROR(H71/G71-1,"N/A") -> -0.0046948357 | I72: =IFERROR(I71/H71-1,"N/A") -> 0.061320755 | J72: =IFERROR(J71/I71-1,"N/A") -> 0.062222222 | K72: =IFERROR(K71/J71-1,"N/A") -> 0.075313808 | L72: =IFERROR(L71/K71-1,"N/A") -> 0.077821012 | M72: =IFERROR(M71/L71-1,"N/A") -> 0.090252708 | N72: 0.061 | O72: 0.063 | P72: 0.043 | Q72: 0.06 | R72: 0.05
C73: Revenue | G73: =G69*G71 -> 723135 | H73: =H69*H71 -> 675432 | I73: =I69*I71 -> 784575 | J73: =J69*J71 -> 925169 | K73: =K69*K71 -> 1094306 | L73: =L69*L71 -> 1259796 | M73: =M69*M71 -> 1475572 | N73: =N69*N71 -> 1684566.1 | ... R73: =R69*R71 -> 2653982.7
C75: Emergency:
C76: # of Visits | G76: 11588 | H76: 10538 | I76: 11134 | J76: 11546 | K76: 12384 | L76: 13731 | M76: 15234 | N76: =M76*(1+N77) -> 16269.912 | O76: =N76*(1+O77) -> 17115.947 | P76: =O76*(1+P77) -> 18314.064 | Q76: =P76*(1+Q77) -> 19907.387 | R76: =Q76*(1+R77) -> 21320.812
C77: Growth (%) | G77: =IFERROR(G76/F76-1,"N/A") -> N/A | H77: =IFERROR(H76/G76-1,"N/A") -> -0.090610977 | I77: =IFERROR(I76/H76-1,"N/A") -> 0.056557221 | J77: =IFERROR(J76/I76-1,"N/A") -> 0.037003772 | K77: =IFERROR(K76/J76-1,"N/A") -> 0.072579248 | L77: =IFERROR(L76/K76-1,"N/A") -> 0.10876938 | M77: =IFERROR(M76/L76-1,"N/A") -> 0.10946035 | N77: 0.068 | O77: 0.052 | P77: 0.07 | Q77: 0.087 | R77: 0.071
C78: Gross Revenue [per Visit] (LCA) | G78: 151 | H78: 155 | I78: 172 | J78: 193 | K78: 205 | L78: 217 | M78: 240 | N78: =M78*(1+N79) -> 255.36 | O78: =N78*(1+O79) -> 268.38336 | P78: =O78*(1+P79) -> 279.92384 | Q78: =P78*(1+Q79) -> 296.71928 | R78: =Q78*(1+R79) -> 316.00603
C79: Growth (%) | G79: =IFERROR(G78/F78-1,"N/A") -> N/A | H79: =IFERROR(H78/G78-1,"N/A") -> 0.026490066 | I79: =IFERROR(I78/H78-1,"N/A") -> 0.10967742 | J79: =IFERROR(J78/I78-1,"N/A") -> 0.12209302 | K79: =IFERROR(K78/J78-1,"N/A") -> 0.062176166 | L79: =IFERROR(L78/K78-1,"N/A") -> 0.058536585 | M79: =IFERROR(M78/L78-1,"N/A") -> 0.10599078 | N79: 0.064 | O79: 0.051 | P79: 0.043 | Q79: 0.06 | R79: 0.065
C80: Revenue | G80: =G76*G78 -> 1749788 | H80: =H76*H78 -> 1633390 | I80: =I76*I78 -> 1915048 | J80: =J76*J78 -> 2228378 | K80: =K76*K78 -> 2538720 | L80: =L76*L78 -> 2979627 | M80: =M76*M78 -> 3656160 | N80: =N76*N78 -> 4154684.7 | ... R80: =R76*R78 -> 6737505
C82: Accommodation:
C83: # of Beds | G83: 112 | H83: 112 | I83: 112 | J83: 112 | K83: 120 | L83: 120 | M83: 120 | N83: =M83 -> 120 | O83: =N83 -> 120 | P83: =O83 -> 120 | Q83: =P83 -> 120 | R83: =Q83 -> 120
C84: Available Beds a Night | G84: =G83*360 -> 40320 | H84: =H83*360 -> 40320 | I84: =I83*360 -> 40320 | J84: =J83*360 -> 40320 | K84: =K83*360 -> 43200 | L84: =L83*360 -> 43200 | M84: =M83*360 -> 43200 | N84: =N83*360 -> 43200 | ... R84: =R83*360 -> 43200
C85: # of Occupied bed nights | G85: 27539 | H85: 25204 | I85: 27138 | J85: 27068 | K85: 30584 | L85: 28672 | M85: 28489 | N85: =N84*N86 -> 28987.2 | O85: =O84*O86 -> 29505.6 | P85: =P84*P86 -> 30024 | Q85: =Q84*Q86 -> 30542.4 | R85: =R84*R86 -> 31060.8
C86: Occupancy Ratio (%) | G86: =IFERROR(G85/G84,"N/A") -> 0.68301091 | H86: =IFERROR(H85/H84,"N/A") -> 0.62509921 | I86: =IFERROR(I85/I84,"N/A") -> 0.67306548 | J86: =IFERROR(J85/J84,"N/A") -> 0.67132937 | K86: =IFERROR(K85/K84,"N/A") -> 0.70796296 | L86: =IFERROR(L85/L84,"N/A") -> 0.6637037 | M86: =IFERROR(M85/M84,"N/A") -> 0.65946759 | N86: 0.671 | O86: 0.683 | P86: 0.695 | Q86: 0.707 | R86: 0.719
C87: Gross Revenue [per bed night] (LCA) | G87: 335 | H87: 334 | I87: 359 | J87: 383 | K87: 420 | L87: 447 | M87: 483 | N87: =M87*(1+N88) -> 510.531 | O87: =N87*(1+O88) -> 536.56808 | P87: =O87*(1+P88) -> 561.25021 | Q87: =P87*(1+Q88) -> 594.92523 | R87: =Q87*(1+R88) -> 634.19029
C88: Growth (%) | G88: =IFERROR(G87/F87-1,"N/A") -> N/A | H88: =IFERROR(H87/G87-1,"N/A") -> -0.0029850746 | I88: =IFERROR(I87/H87-1,"N/A") -> 0.074850299 | J88: =IFERROR(J87/I87-1,"N/A") -> 0.066852368 | K88: =IFERROR(K87/J87-1,"N/A") -> 0.096605744 | L88: =IFERROR(L87/K87-1,"N/A") -> 0.064285714 | M88: =IFERROR(M87/L87-1,"N/A") -> 0.080536913 | N88: 0.057 | O88: 0.051 | P88: 0.046 | Q88: 0.06 | R88: 0.066
C89: Revenue | G89: =G85*G87 -> 9225565 | H89: =H85*H87 -> 8418136 | I89: =I85*I87 -> 9742542 | J89: =J85*J87 -> 10367044 | K89: =K85*K87 -> 12845280 | L89: =L85*L87 -> 12816384 | M89: =M85*M87 -> 13760187 | N89: =N85*N87 -> 14798864 | ... R89: =R85*R87 -> 19698458
C91: Radiotherapy:
C92: # of Sessions | G92: 0 | H92: 0 | I92: 0 | J92: 0 | K92: 0 | L92: 0 | M92: 0 | N92: =M92*(1+N93) -> 0 | O92: =N92*(1+O93) -> 0 | P92: =O92*(1+P93) -> 0 | Q92: =P92*(1+Q93) -> 0 | R92: =Q92*(1+R93) -> 0
C93: Growth (%) | G93: =IFERROR(G92/F92-1,"N/A") -> N/A | H93: =IFERROR(H92/G92-1,"N/A") -> N/A | I93: =IFERROR(I92/H92-1,"N/A") -> N/A | J93: =IFERROR(J92/I92-1,"N/A") -> N/A | K93: =IFERROR(K92/J92-1,"N/A") -> N/A | L93: =IFERROR(L92/K92-1,"N/A") -> N/A | M93: =IFERROR(M92/L92-1,"N/A") -> N/A | N93: 0 | O93: 0 | P93: 0 | Q93: 0 | R93: 0
C94: Gross Revenue [per Session] (LCA) | G94: 923 | H94: 937 | I94: 1033 | J94: 1089 | K94: 1169 | L94: 1202 | M94: 1249 | N94: =M94*(1+N95) -> 1311.45 | O94: =N94*(1+O95) -> 1375.711 | P94: =O94*(1+P95) -> 1443.1209 | Q94: =P94*(1+Q95) -> 1535.4806 | R94: =Q94*(1+R95) -> 1613.7901
C95: Growth (%) | G95: =IFERROR(G94/F94-1,"N/A") -> N/A | H95: =IFERROR(H94/G94-1,"N/A") -> 0.015167931 | I95: =IFERROR(I94/H94-1,"N/A") -> 0.10245464 | J95: =IFERROR(J94/I94-1,"N/A") -> 0.054211036 | K95: =IFERROR(K94/J94-1,"N/A") -> 0.073461892 | L95: =IFERROR(L94/K94-1,"N/A") -> 0.028229256 | M95: =IFERROR(M94/L94-1,"N/A") -> 0.039101498 | N95: 0.05 | O95: 0.049 | P95: 0.049 | Q95: 0.064 | R95: 0.051
C96: Revenue | G96: =G92*G94 -> 0 | H96: =H92*H94 -> 0 | I96: =I92*I94 -> 0 | J96: =J92*J94 -> 0 | K96: =K92*K94 -> 0 | L96: =L92*L94 -> 0 | M96: =M92*M94 -> 0 | N96: =N92*N94 -> 0 | ... R96: =R92*R94 -> 0
C98: Nursing Fees:
C99: # of Visits | G99: 6241 | H99: 6014 | I99: 6570 | J99: 7093 | K99: 7678 | L99: 8532 | M99: 9362 | N99: =M99*(1+N100) -> 9979.892 | O99: =N99*(1+O100) -> 10768.303 | P99: =O99*(1+P100) -> 11694.378 | Q99: =P99*(1+Q100) -> 12700.094 | R99: =Q99*(1+R100) -> 13830.402
C100: Growth (%) | G100: =IFERROR(G99/F99-1,"N/A") -> N/A | H100: =IFERROR(H99/G99-1,"N/A") -> -0.036372376 | I100: =IFERROR(I99/H99-1,"N/A") -> 0.092450948 | J100: =IFERROR(J99/I99-1,"N/A") -> 0.079604262 | K100: =IFERROR(K99/J99-1,"N/A") -> 0.08247568 | L100: =IFERROR(L99/K99-1,"N/A") -> 0.11122688 | M100: =IFERROR(M99/L99-1,"N/A") -> 0.097280825 | N100: 0.066 | O100: 0.079 | P100: 0.086 | Q100: 0.086 | R100: 0.089
C101: Gross Revenue [per Visit] (LCA) | G101: 78 | H101: 79 | I101: 87 | J101: 97 | K101: 104 | L101: 110 | M101: 118 | N101: =M101*(1+N102) -> 125.67 | O101: =N101*(1+O102) -> 131.32515 | P101: =O101*(1+P102) -> 139.07333 | Q101: =P101*(1+Q102) -> 148.39125 | R101: =Q101*(1+R102) -> 156.25598
C102: Growth (%) | G102: =IFERROR(G101/F101-1,"N/A") -> N/A | H102: =IFERROR(H101/G101-1,"N/A") -> 0.012820513 | I102: =IFERROR(I101/H101-1,"N/A") -> 0.10126582 | J102: =IFERROR(J101/I101-1,"N/A") -> 0.11494253 | K102: =IFERROR(K101/J101-1,"N/A") -> 0.072164948 | L102: =IFERROR(L101/K101-1,"N/A") -> 0.057692308 | M102: =IFERROR(M101/L101-1,"N/A") -> 0.072727273 | N102: 0.065 | O102: 0.045 | P102: 0.059 | Q102: 0.067 | R102: 0.053
C103: Revenue | G103: =G99*G101 -> 486798 | H103: =H99*H101 -> 475106 | I103: =I99*I101 -> 571590 | J103: =J99*J101 -> 688021 | K103: =K99*K101 -> 798512 | L103: =L99*L101 -> 938520 | M103: =M99*M101 -> 1104716 | N103: =N99*N101 -> 1254173 | ... R103: =R99*R101 -> 2161083.1
C105: Pharmacy:
C106: Gross Revenue (LCA) | G106: 1565000 | H106: 1528000 | I106: 1743000 | J106: 2060000 | K106: 2219000 | L106: 2549000 | M106: 2951000 | N106: =N108*(N17+N24+N31+N38+N45+N52+N59+N66+N73+N80+N89+N96+N103) -> 3964520.5 | O106: =O108*(O17+O24+O31+O38+O45+O52+O59+O66+O73+O80+O89+O96+O103) -> 4724241.4 | P106: =P108*(P17+P24+P31+P38+P45+P52+P59+P66+P73+P80+P89+P96+P103) -> 4954600.7 | Q106: =Q108*(Q17+Q24+Q31+Q38+Q45+Q52+Q59+Q66+Q73+Q80+Q89+Q96+Q103) -> 5695847.3 | R106: =R108*(R17+R24+R31+R38+R45+R52+R59+R66+R73+R80+R89+R96+R103) -> 6142563.9
C107: Growth (%) | G107: =IFERROR(G106/F106-1,"N/A") -> N/A | H107: =IFERROR(H106/G106-1,"N/A") -> -0.023642173 | I107: =IFERROR(I106/H106-1,"N/A") -> 0.14070681 | J107: =IFERROR(J106/I106-1,"N/A") -> 0.18187034 | K107: =IFERROR(K106/J106-1,"N/A") -> 0.077184466 | L107: =IFERROR(L106/K106-1,"N/A") -> 0.14871564 | M107: =IFERROR(M106/L106-1,"N/A") -> 0.15770891 | N107: =IFERROR(N106/M106-1,"N/A") -> 0.34344986 | ... R107: =IFERROR(R106/Q106-1,"N/A") -> 0.078428478
C108: % of Other Hospital Revenue | G108: =IFERROR(G106/(G17+G24+G31+G38+G45+G52+G59+G66+G73+G80+G89+G96+G103),"N/A") -> 0.063725219 | H108: =IFERROR(H106/(H17+H24+H31+H38+H45+H52+H59+H66+H73+H80+H89+H96+H103),"N/A") -> 0.066556051 | I108: =IFERROR(I106/(I17+I24+I31+I38+I45+I52+I59+I66+I73+I80+I89+I96+I103),"N/A") -> 0.064994606 | J108: =IFERROR(J106/(J17+J24+J31+J38+J45+J52+J59+J66+J73+J80+J89+J96+J103),"N/A") -> 0.067486501 | K108: =IFERROR(K106/(K17+K24+K31+K38+K45+K52+K59+K66+K73+K80+K89+K96+K103),"N/A") -> 0.0623974 | L108: =IFERROR(L106/(L17+L24+L31+L38+L45+L52+L59+L66+L73+L80+L89+L96+L103),"N/A") -> 0.064467798 | M108: =IFERROR(M106/(M17+M24+M31+M38+M45+M52+M59+M66+M73+M80+M89+M96+M103),"N/A") -> 0.064846867 | N108: 0.079 | O108: 0.085 | P108: 0.081 | Q108: 0.084 | R108: 0.081
C109: Revenue | G109: =G106 -> 1565000 | H109: =H106 -> 1528000 | I109: =I106 -> 1743000 | J109: =J106 -> 2060000 | K109: =K106 -> 2219000 | L109: =L106 -> 2549000 | M109: =M106 -> 2951000 | N109: =N106 -> 3964520.5 | ... R109: =R106 -> 6142563.9
C111: Total Hospital Revenue (LCA) | G111: =G17+G24+G31+G38+G45+G52+G59+G66+G73+G80+G89+G96+G103+G109 -> 26123566 | H111: =H17+H24+H31+H38+H45+H52+H59+H66+H73+H80+H89+H96+H103+H109 -> 24486093 | I111: =I17+I24+I31+I38+I45+I52+I59+I66+I73+I80+I89+I96+I103+I109 -> 28560610 | J111: =J17+J24+J31+J38+J45+J52+J59+J66+J73+J80+J89+J96+J103+J109 -> 32584623 | K111: =K17+K24+K31+K38+K45+K52+K59+K66+K73+K80+K89+K96+K103+K109 -> 37781379 | L111: =L17+L24+L31+L38+L45+L52+L59+L66+L73+L80+L89+L96+L103+L109 -> 42088120 | M111: =M17+M24+M31+M38+M45+M52+M59+M66+M73+M80+M89+M96+M103+M109 -> 48458210 | N111: =N17+N24+N31+N38+N45+N52+N59+N66+N73+N80+N89+N96+N103+N109 -> 54148325 | ... R111: =R17+R24+R31+R38+R45+R52+R59+R66+R73+R80+R89+R96+R103+R109 -> 81976686
C113: B | D113: Cost Assumptions
C114: Expenses:
C115: COGS – % of Sales (%) | G115: =IFERROR(G116/G111,"N/A") -> 0.312821 | H115: =IFERROR(H116/H111,"N/A") -> 0.28820441 | I115: =IFERROR(I116/I111,"N/A") -> 0.30146415 | J115: =IFERROR(J116/J111,"N/A") -> 0.29210097 | K115: =IFERROR(K116/K111,"N/A") -> 0.29376905 | L115: =IFERROR(L116/L111,"N/A") -> 0.29644945 | M115: =IFERROR(M116/M111,"N/A") -> 0.30050635 | N115: 0.2947 | O115: 0.3018 | P115: 0.2924 | Q115: 0.3004 | R115: 0.3037
C116: COGS (LCA) | G116: 8172000 | H116: 7057000 | I116: 8610000 | J116: 9518000 | K116: 11099000 | L116: 12477000 | M116: 14562000 | N116: =N115*N111 -> 15957511 | O116: =O115*O111 -> 18199612 | P116: =P115*P111 -> 19334222 | Q116: =Q115*Q111 -> 22080467 | R116: =R115*R111 -> 24896320
C117: Payroll – % of Sales (%) | G117: =IFERROR(G118/G111,"N/A") -> 0.34214318 | H117: =IFERROR(H118/H111,"N/A") -> 0.32953399 | I117: =IFERROR(I118/I111,"N/A") -> 0.32831932 | J117: =IFERROR(J118/J111,"N/A") -> 0.33966942 | K117: =IFERROR(K118/K111,"N/A") -> 0.31769619 | L117: =IFERROR(L118/L111,"N/A") -> 0.33662706 | M117: =IFERROR(M118/M111,"N/A") -> 0.33618658 | N117: 0.3301 | O117: 0.3361 | P117: 0.321 | Q117: 0.3212 | R117: 0.3338
C118: Payroll (LCA) | G118: 8938000 | H118: 8069000 | I118: 9377000 | J118: 11068000 | K118: 12003000 | L118: 14168000 | M118: 16291000 | N118: =N117*N111 -> 17874362 | O118: =O117*O111 -> 20268024 | P118: =P117*P111 -> 21225326 | Q118: =Q117*Q111 -> 23609341 | R118: =R117*R111 -> 27363818
C119: OPEX – % of Sales (%) | G119: =IFERROR(G120/G111,"N/A") -> 0.1408307 | H119: =IFERROR(H120/H111,"N/A") -> 0.14216233 | I119: =IFERROR(I120/I111,"N/A") -> 0.14390449 | J119: =IFERROR(J120/J111,"N/A") -> 0.14411706 | K119: =IFERROR(K120/K111,"N/A") -> 0.14311283 | L119: =IFERROR(L120/L111,"N/A") -> 0.14113246 | M119: =IFERROR(M120/M111,"N/A") -> 0.14061601 | N119: 0.1403 | O119: 0.1431 | P119: 0.1368 | Q119: 0.1444 | R119: 0.1379
...

Sheet 3. AHG North
C3: =Cover!$C$3 -> Project Dunecrest | D3: Confidential
C4: AHG North – Operating Build
C6: Fiscal Year Ending | G6: 43830 | H6: 44196 | I6: 44561 | J6: 44926 | K6: =EOMONTH(J6,12) -> 45291 | L6: =EOMONTH(K6,12) -> 45657 | M6: =EOMONTH(L6,12) -> 46022 | N6: =EOMONTH(M6,12) -> 46387 | O6: =EOMONTH(N6,12) -> 46752 | P6: =EOMONTH(O6,12) -> 47118 | Q6: =EOMONTH(P6,12) -> 47483 | R6: =EOMONTH(Q6,12) -> 47848
C7: Fiscal Year | G7: =YEAR(G6) -> 2019 | H7: =YEAR(H6) -> 2020 | I7: =YEAR(I6) -> 2021 | J7: =YEAR(J6) -> 2022 | K7: =YEAR(K6) -> 2023 | L7: =YEAR(L6) -> 2024 | M7: =YEAR(M6) -> 2025 | N7: =YEAR(N6) -> 2026 | ... R7: =YEAR(R6) -> 2030
C8: Actual / Estimate | G8: =IF(G6<=Control!$E$11,"A","E") -> A | H8: =IF(H6<=Control!$E$11,"A","E") -> A | I8: =IF(I6<=Control!$E$11,"A","E") -> A | J8: =IF(J6<=Control!$E$11,"A","E") -> A | K8: =IF(K6<=Control!$E$11,"A","E") -> A | L8: =IF(L6<=Control!$E$11,"A","E") -> A | M8: =IF(M6<=Control!$E$11,"A","E") -> A | N8: =IF(N6<=Control!$E$11,"A","E") -> E | ... R8: =IF(R6<=Control!$E$11,"A","E") -> E
C10: Supporting Data
C11: A | D11: Revenue Build | E11: ="("&Control!$E$16&" in Actual)" -> (LCA in Actual)
C12: Laboratory:
C13: # of Tests | G13: 86794 | H13: 81290 | I13: 89725 | J13: 96714 | K13: 100874 | L13: 108543 | M13: 116434 | N13: =M13*(1+N14) -> 123070.74 | O13: =N13*(1+O14) -> 129347.35 | P13: =O13*(1+P14) -> 135426.67 | Q13: =P13*(1+Q14) -> 143687.7 | R13: =Q13*(1+R14) -> 156332.22
C14: Growth (%) | G14: =IFERROR(G13/F13-1,"N/A") -> N/A | H14: =IFERROR(H13/G13-1,"N/A") -> -0.063414522 | I14: =IFERROR(I13/H13-1,"N/A") -> 0.1037643 | J14: =IFERROR(J13/I13-1,"N/A") -> 0.077893564 | K14: =IFERROR(K13/J13-1,"N/A") -> 0.043013421 | L14: =IFERROR(L13/K13-1,"N/A") -> 0.076025537 | M14: =IFERROR(M13/L13-1,"N/A") -> 0.072699299 | N14: 0.057 | O14: 0.051 | P14: 0.047 | Q14: 0.061 | R14: 0.088
C15: Gross Revenue [per Test] (LCA) | G15: 35 | H15: 36 | I15: 39 | J15: 42 | K15: 47 | L15: 50 | M15: 54 | N15: =M15*(1+N16) -> 56.862 | O15: =N15*(1+O16) -> 59.7051 | P15: =O15*(1+P16) -> 63.765047 | Q15: =P15*(1+Q16) -> 66.825769 | R15: =Q15*(1+R16) -> 71.436747
C16: Growth (%) | G16: =IFERROR(G15/F15-1,"N/A") -> N/A | H16: =IFERROR(H15/G15-1,"N/A") -> 0.028571429 | I16: =IFERROR(I15/H15-1,"N/A") -> 0.083333333 | J16: =IFERROR(J15/I15-1,"N/A") -> 0.076923077 | K16: =IFERROR(K15/J15-1,"N/A") -> 0.11904762 | L16: =IFERROR(L15/K15-1,"N/A") -> 0.063829787 | M16: =IFERROR(M15/L15-1,"N/A") -> 0.08 | N16: 0.053 | O16: 0.05 | P16: 0.068 | Q16: 0.048 | R16: 0.069
C17: Revenue | G17: =G13*G15 -> 3037790 | H17: =H13*H15 -> 2926440 | I17: =I13*I15 -> 3499275 | J17: =J13*J15 -> 4061988 | K17: =K13*K15 -> 4741078 | L17: =L13*L15 -> 5427150 | M17: =M13*M15 -> 6287436 | N17: =N13*N15 -> 6998048.3 | ... R17: =R13*R15 -> 11167865
C19: Radiology:
C20: # of Tests | G20: 21800 | H20: 19729 | I20: 21601 | J20: 23313 | K20: 24821 | L20: 25868 | M20: 28657 | N20: =M20*(1+N21) -> 30548.362 | O20: =N20*(1+O21) -> 32503.457 | P20: =O20*(1+P21) -> 34161.133 | Q20: =P20*(1+Q21) -> 36996.508 | R20: =Q20*(1+R21) -> 39623.26
C21: Growth (%) | G21: =IFERROR(G20/F20-1,"N/A") -> N/A | H21: =IFERROR(H20/G20-1,"N/A") -> -0.095 | I21: =IFERROR(I20/H20-1,"N/A") -> 0.094885701 | J21: =IFERROR(J20/I20-1,"N/A") -> 0.07925559 | K21: =IFERROR(K20/J20-1,"N/A") -> 0.06468494 | L21: =IFERROR(L20/K20-1,"N/A") -> 0.042182023 | M21: =IFERROR(M20/L20-1,"N/A") -> 0.10781661 | N21: 0.066 | O21: 0.064 | P21: 0.051 | Q21: 0.083 | R21: 0.071
C22: Gross Revenue [per Test] (LCA) | G22: 116 | H22: 114 | I22: 121 | J22: 131 | K22: 143 | L22: 153 | M22: 162 | N22: =M22*(1+N23) -> 169.938 | O22: =N22*(1+O23) -> 180.64409 | P22: =O22*(1+P23) -> 188.59243 | Q22: =P22*(1+Q23) -> 196.70191 | R22: =Q22*(1+R23) -> 207.91392
C23: Growth (%) | G23: =IFERROR(G22/F22-1,"N/A") -> N/A | H23: =IFERROR(H22/G22-1,"N/A") -> -0.017241379 | I23: =IFERROR(I22/H22-1,"N/A") -> 0.061403509 | J23: =IFERROR(J22/I22-1,"N/A") -> 0.082644628 | K23: =IFERROR(K22/J22-1,"N/A") -> 0.091603053 | L23: =IFERROR(L22/K22-1,"N/A") -> 0.06993007 | M23: =IFERROR(M22/L22-1,"N/A") -> 0.058823529 | N23: 0.049 | O23: 0.063 | P23: 0.044 | Q23: 0.043 | R23: 0.057
C24: Revenue | G24: =G20*G22 -> 2528800 | H24: =H20*H22 -> 2249106 | I24: =I20*I22 -> 2613721 | J24: =J20*J22 -> 3054003 | K24: =K20*K22 -> 3549403 | L24: =L20*L22 -> 3957804 | M24: =M20*M22 -> 4642434 | N24: =N20*N22 -> 5191327.5 | ... R24: =R20*R22 -> 8238227.1
C26: Endoscopy:
C27: # of Visits | G27: 1542 | H27: 1451 | I27: 1582 | J27: 1670 | K27: 1843 | L27: 1952 | M27: 2089 | N27: =M27*(1+N28) -> 2210.162 | O27: =N27*(1+O28) -> 2364.8733 | P27: =O27*(1+P28) -> 2572.9822 | Q27: =P27*(1+Q28) -> 2704.2043 | R27: =Q27*(1+R28) -> 2820.4851
C28: Growth (%) | G28: =IFERROR(G27/F27-1,"N/A") -> N/A | H28: =IFERROR(H27/G27-1,"N/A") -> -0.059014267 | I28: =IFERROR(I27/H27-1,"N/A") -> 0.090282564 | J28: =IFERROR(J27/I27-1,"N/A") -> 0.05562579 | K28: =IFERROR(K27/J27-1,"N/A") -> 0.10359281 | L28: =IFERROR(L27/K27-1,"N/A") -> 0.059142702 | M28: =IFERROR(M27/L27-1,"N/A") -> 0.070184426 | N28: 0.058 | O28: 0.07 | P28: 0.088 | Q28: 0.051 | R28: 0.043
C29: Gross Revenue [per Visit] (LCA) | G29: 777 | H29: 791 | I29: 839 | J29: 898 | K29: 942 | L29: 984 | M29: 1077 | N29: =M29*(1+N30) -> 1139.466 | O29: =N29*(1+O30) -> 1219.2286 | P29: =O29*(1+P30) -> 1300.9169 | Q29: =P29*(1+Q30) -> 1368.5646 | R29: =Q29*(1+R30) -> 1446.5728
C30: Growth (%) | G30: =IFERROR(G29/F29-1,"N/A") -> N/A | H30: =IFERROR(H29/G29-1,"N/A") -> 0.018018018 | I30: =IFERROR(I29/H29-1,"N/A") -> 0.06068268 | J30: =IFERROR(J29/I29-1,"N/A") -> 0.070321812 | K30: =IFERROR(K29/J29-1,"N/A") -> 0.048997773 | L30: =IFERROR(L29/K29-1,"N/A") -> 0.044585987 | M30: =IFERROR(M29/L29-1,"N/A") -> 0.094512195 | N30: 0.058 | O30: 0.07 | P30: 0.067 | Q30: 0.052 | R30: 0.057
C31: Revenue | G31: =G27*G29 -> 1198134 | H31: =H27*H29 -> 1147741 | I31: =I27*I29 -> 1327298 | J31: =J27*J29 -> 1499660 | K31: =K27*K29 -> 1736106 | L31: =L27*L29 -> 1920768 | M31: =M27*M29 -> 2249853 | N31: =N27*N29 -> 2518404.5 | ... R31: =R27*R29 -> 4080037
C33: Physiotherapy:
C34: # of Patients | G34: 4412 | H34: 4102 | I34: 4506 | J34: 4959 | K34: 5512 | L34: 5798 | M34: 6293 | N34: =M34*(1+N35) -> 6582.478 | O34: =N34*(1+O35) -> 7062.9989 | P34: =O34*(1+P35) -> 7635.1018 | Q34: =P34*(1+Q35) -> 8177.194 | R34: =Q34*(1+R35) -> 8545.1678
C35: Growth (%) | G35: =IFERROR(G34/F34-1,"N/A") -> N/A | H35: =IFERROR(H34/G34-1,"N/A") -> -0.070262919 | I35: =IFERROR(I34/H34-1,"N/A") -> 0.098488542 | J35: =IFERROR(J34/I34-1,"N/A") -> 0.10053262 | K35: =IFERROR(K34/J34-1,"N/A") -> 0.11151442 | L35: =IFERROR(L34/K34-1,"N/A") -> 0.051886792 | M35: =IFERROR(M34/L34-1,"N/A") -> 0.085374267 | N35: 0.046 | O35: 0.073 | P35: 0.081 | Q35: 0.071 | R35: 0.045
C36: Gross Revenue [per Patient] (LCA) | G36: 105 | H36: 106 | I36: 111 | J36: 118 | K36: 128 | L36: 131 | M36: 138 | N36: =M36*(1+N37) -> 147.246 | O36: =N36*(1+O37) -> 154.90279 | P36: =O36*(1+P37) -> 164.97147 | Q36: =P36*(1+Q37) -> 173.38502 | R36: =Q36*(1+R37) -> 180.66719
C37: Growth (%) | G37: =IFERROR(G36/F36-1,"N/A") -> N/A | H37: =IFERROR(H36/G36-1,"N/A") -> 0.0095238095 | I37: =IFERROR(I36/H36-1,"N/A") -> 0.047169811 | J37: =IFERROR(J36/I36-1,"N/A") -> 0.063063063 | K37: =IFERROR(K36/J36-1,"N/A") -> 0.084745763 | L37: =IFERROR(L36/K36-1,"N/A") -> 0.0234375 | M37: =IFERROR(M36/L36-1,"N/A") -> 0.053435115 | N37: 0.067 | O37: 0.052 | P37: 0.065 | Q37: 0.051 | R37: 0.042
C38: Revenue | G38: =G34*G36 -> 463260 | H38: =H34*H36 -> 434812 | I38: =I34*I36 -> 500166 | J38: =J34*J36 -> 585162 | K38: =K34*K36 -> 705536 | L38: =L34*L36 -> 759538 | M38: =M34*M36 -> 868434 | N38: =N34*N36 -> 969243.56 | ... R38: =R34*R36 -> 1543831.4
C40: IVF:
C41: # of Patients | G41: 0 | H41: 0 | I41: 0 | J41: 0 | K41: 0 | L41: 0 | M41: 0 | N41: =M41*(1+N42) -> 0 | O41: =N41*(1+O42) -> 0 | P41: =O41*(1+P42) -> 0 | Q41: =P41*(1+Q42) -> 0 | R41: =Q41*(1+R42) -> 0
C42: Growth (%) | G42: =IFERROR(G41/F41-1,"N/A") -> N/A | H42: =IFERROR(H41/G41-1,"N/A") -> N/A | I42: =IFERROR(I41/H41-1,"N/A") -> N/A | J42: =IFERROR(J41/I41-1,"N/A") -> N/A | K42: =IFERROR(K41/J41-1,"N/A") -> N/A | L42: =IFERROR(L41/K41-1,"N/A") -> N/A | M42: =IFERROR(M41/L41-1,"N/A") -> N/A | N42: 0 | O42: 0 | P42: 0 | Q42: 0 | R42: 0
C43: Gross Revenue [per Patient] (LCA) | G43: 3933 | H43: 3970 | I43: 4128 | J43: 4401 | K43: 4681 | L43: 4864 | M43: 5008 | N43: =M43*(1+N44) -> 5308.48 | O43: =N43*(1+O44) -> 5642.9142 | P43: =O43*(1+P44) -> 5936.3458 | Q43: =P43*(1+Q44) -> 6298.4629 | R43: =Q43*(1+R44) -> 6644.8783
C44: Growth (%) | G44: =IFERROR(G43/F43-1,"N/A") -> N/A | H44: =IFERROR(H43/G43-1,"N/A") -> 0.0094075769 | I44: =IFERROR(I43/H43-1,"N/A") -> 0.039798489 | J44: =IFERROR(J43/I43-1,"N/A") -> 0.066133721 | K44: =IFERROR(K43/J43-1,"N/A") -> 0.063621904 | L44: =IFERROR(L43/K43-1,"N/A") -> 0.039094211 | M44: =IFERROR(M43/L43-1,"N/A") -> 0.029605263 | N44: 0.06 | O44: 0.063 | P44: 0.052 | Q44: 0.061 | R44: 0.055
C45: Revenue | G45: =G41*G43 -> 0 | H45: =H41*H43 -> 0 | I45: =I41*I43 -> 0 | J45: =J41*J43 -> 0 | K45: =K41*K43 -> 0 | L45: =L41*L43 -> 0 | M45: =M41*M43 -> 0 | N45: =N41*N43 -> 0 | ... R45: =R41*R43 -> 0
C47: Anapath:
C48: # of Patients | G48: 5969 | H48: 5421 | I48: 5896 | J48: 6412 | K48: 6919 | L48: 7639 | M48: 8207 | N48: =M48*(1+N49) -> 8904.595 | O48: =N48*(1+O49) -> 9563.535 | P48: =O48*(1+P49) -> 10051.275 | Q48: =P48*(1+Q49) -> 10573.942 | R48: =Q48*(1+R49) -> 11155.508
C49: Growth (%) | G49: =IFERROR(G48/F48-1,"N/A") -> N/A | H49: =IFERROR(H48/G48-1,"N/A") -> -0.091807673 | I49: =IFERROR(I48/H48-1,"N/A") -> 0.08762221 | J49: =IFERROR(J48/I48-1,"N/A") -> 0.087516961 | K49: =IFERROR(K48/J48-1,"N/A") -> 0.079070493 | L49: =IFERROR(L48/K48-1,"N/A") -> 0.10406128 | M49: =IFERROR(M48/L48-1,"N/A") -> 0.074355282 | N49: 0.085 | O49: 0.074 | P49: 0.051 | Q49: 0.052 | R49: 0.055
C50: Gross Revenue [per Patient] (LCA) | G50: 131 | H50: 133 | I50: 138 | J50: 147 | K50: 152 | L50: 168 | M50: 177 | N50: =M50*(1+N51) -> 187.443 | O50: =N50*(1+O51) -> 195.50305 | P50: =O50*(1+P51) -> 204.69169 | Q50: =P50*(1+Q51) -> 218.40604 | R50: =Q50*(1+R51) -> 229.32634
C51: Growth (%) | G51: =IFERROR(G50/F50-1,"N/A") -> N/A | H51: =IFERROR(H50/G50-1,"N/A") -> 0.015267176 | I51: =IFERROR(I50/H50-1,"N/A") -> 0.037593985 | J51: =IFERROR(J50/I50-1,"N/A") -> 0.065217391 | K51: =IFERROR(K50/J50-1,"N/A") -> 0.034013605 | L51: =IFERROR(L50/K50-1,"N/A") -> 0.10526316 | M51: =IFERROR(M50/L50-1,"N/A") -> 0.053571429 | N51: 0.059 | O51: 0.043 | P51: 0.047 | Q51: 0.067 | R51: 0.05
C52: Revenue | G52: =G48*G50 -> 781939 | H52: =H48*H50 -> 720993 | I52: =I48*I50 -> 813648 | J52: =J48*J50 -> 942564 | K52: =K48*K50 -> 1051688 | L52: =L48*L50 -> 1283352 | M52: =M48*M50 -> 1452639 | N52: =N48*N50 -> 1669104 | ... R52: =R48*R50 -> 2558251.9
C54: Surgery:
C55: # of Surgeries | G55: 3200 | H55: 2973 | I55: 3266 | J55: 3588 | K55: 3786 | L55: 4010 | M55: 4221 | N55: =M55*(1+N56) -> 4537.575 | O55: =N55*(1+O56) -> 4896.0434 | P55: =O55*(1+P56) -> 5175.1179 | Q55: =P55*(1+Q56) -> 5609.8278 | R55: =Q55*(1+R56) -> 5884.7094
C56: Growth (%) | G56: =IFERROR(G55/F55-1,"N/A") -> N/A | H56: =IFERROR(H55/G55-1,"N/A") -> -0.0709375 | I56: =IFERROR(I55/H55-1,"N/A") -> 0.09855365 | J56: =IFERROR(J55/I55-1,"N/A") -> 0.098591549 | K56: =IFERROR(K55/J55-1,"N/A") -> 0.055183946 | L56: =IFERROR(L55/K55-1,"N/A") -> 0.059165346 | M56: =IFERROR(M55/L55-1,"N/A") -> 0.052618454 | N56: 0.075 | O56: 0.079 | P56: 0.057 | Q56: 0.084 | R56: 0.049
C57: Gross Revenue [per Surgery] (LCA) | G57: 2017 | H57: 2061 | I57: 2232 | J57: 2373 | K57: 2498 | L57: 2612 | M57: 2856 | N57: =M57*(1+N58) -> 3010.224 | O57: =N57*(1+O58) -> 3175.7863 | P57: =O57*(1+P58) -> 3337.7514 | Q57: =P57*(1+Q58) -> 3521.3278 | R57: =Q57*(1+R58) -> 3718.5221
C58: Growth (%) | G58: =IFERROR(G57/F57-1,"N/A") -> N/A | H58: =IFERROR(H57/G57-1,"N/A") -> 0.021814576 | I58: =IFERROR(I57/H57-1,"N/A") -> 0.082969432 | J58: =IFERROR(J57/I57-1,"N/A") -> 0.063172043 | K58: =IFERROR(K57/J57-1,"N/A") -> 0.052675938 | L58: =IFERROR(L57/K57-1,"N/A") -> 0.045636509 | M58: =IFERROR(M57/L57-1,"N/A") -> 0.093415008 | N58: 0.054 | O58: 0.055 | P58: 0.051 | Q58: 0.055 | R58: 0.056
C59: Revenue | G59: =G55*G57 -> 6454400 | H59: =H55*H57 -> 6127353 | I59: =I55*I57 -> 7289712 | J59: =J55*J57 -> 8514324 | K59: =K55*K57 -> 9457428 | L59: =L55*L57 -> 10474120 | M59: =M55*M57 -> 12055176 | N59: =N55*N57 -> 13659117 | ... R59: =R55*R57 -> 21882422
C61: Cardiac Cath:
C62: # of Surgeries | G62: 293 | H62: 273 | I62: 289 | J62: 314 | K62: 346 | L62: 372 | M62: 405 | N62: =M62*(1+N63) -> 437.805 | O62: =N62*(1+O63) -> 470.64038 | P62: =O62*(1+P63) -> 508.29161 | Q62: =P62*(1+Q63) -> 539.29739 | R62: =Q62*(1+R63) -> 580.82329
C63: Growth (%) | G63: =IFERROR(G62/F62-1,"N/A") -> N/A | H63: =IFERROR(H62/G62-1,"N/A") -> -0.068259386 | I63: =IFERROR(I62/H62-1,"N/A") -> 0.058608059 | J63: =IFERROR(J62/I62-1,"N/A") -> 0.08650519 | K63: =IFERROR(K62/J62-1,"N/A") -> 0.10191083 | L63: =IFERROR(L62/K62-1,"N/A") -> 0.075144509 | M63: =IFERROR(M62/L62-1,"N/A") -> 0.088709677 | N63: 0.081 | O63: 0.075 | P63: 0.08 | Q63: 0.061 | R63: 0.077
C64: Gross Revenue [per Surgery] (LCA) | G64: 4239 | H64: 4226 | I64: 4409 | J64: 4810 | K64: 5292 | L64: 5687 | M64: 5950 | N64: =M64*(1+N65) -> 6211.8 | O64: =N64*(1+O65) -> 6553.449 | P64: =O64*(1+P65) -> 6874.568 | Q64: =P64*(1+Q65) -> 7293.9166 | R64: =Q64*(1+R65) -> 7607.5551
C65: Growth (%) | G65: =IFERROR(G64/F64-1,"N/A") -> N/A | H65: =IFERROR(H64/G64-1,"N/A") -> -0.003066761 | I65: =IFERROR(I64/H64-1,"N/A") -> 0.04330336 | J65: =IFERROR(J64/I64-1,"N/A") -> 0.090950329 | K65: =IFERROR(K64/J64-1,"N/A") -> 0.1002079 | L65: =IFERROR(L64/K64-1,"N/A") -> 0.074640967 | M65: =IFERROR(M64/L64-1,"N/A") -> 0.046245824 | N65: 0.044 | O65: 0.055 | P65: 0.049 | Q65: 0.061 | R65: 0.043
C66: Revenue | G66: =G62*G64 -> 1242027 | H66: =H62*H64 -> 1153698 | I66: =I62*I64 -> 1274201 | J66: =J62*J64 -> 1510340 | K66: =K62*K64 -> 1831032 | L66: =L62*L64 -> 2115564 | M66: =M62*M64 -> 2409750 | N66: =N62*N64 -> 2719557.1 | ... R66: =R62*R64 -> 4418645.2
C68: Heart Test:
C69: # of Tests | G69: 4083 | H69: 3796 | I69: 4117 | J69: 4349 | K69: 4661 | L69: 5047 | M69: 5608 | N69: =M69*(1+N70) -> 5927.656 | O69: =N69*(1+O70) -> 6224.0388 | P69: =O69*(1+P70) -> 6684.6177 | Q69: =P69*(1+Q70) -> 6978.7408 | R69: =Q69*(1+R70) -> 7467.2527
C70: Growth (%) | G70: =IFERROR(G69/F69-1,"N/A") -> N/A | H70: =IFERROR(H69/G69-1,"N/A") -> -0.070291452 | I70: =IFERROR(I69/H69-1,"N/A") -> 0.084562698 | J70: =IFERROR(J69/I69-1,"N/A") -> 0.056351712 | K70: =IFERROR(K69/J69-1,"N/A") -> 0.07174063 | L70: =IFERROR(L69/K69-1,"N/A") -> 0.082814847 | M70: =IFERROR(M69/L69-1,"N/A") -> 0.11115514 | N70: 0.057 | O70: 0.05 | P70: 0.074 | Q70: 0.044 | R70: 0.07
C71: Gross Revenue [per Test] (LCA) | G71: 213 | H71: 214 | I71: 226 | J71: 233 | K71: 247 | L71: 261 | M71: 293 | N71: =M71*(1+N72) -> 312.924 | O71: =N71*(1+O72) -> 333.88991 | P71: =O71*(1+P72) -> 349.91662 | Q71: =P71*(1+Q72) -> 366.01279 | R71: =Q71*(1+R72) -> 381.75134
C72: Growth (%) | G72: =IFERROR(G71/F71-1,"N/A") -> N/A | H72: =IFERROR(H71/G71-1,"N/A") -> 0.0046948357 | I72: =IFERROR(I71/H71-1,"N/A") -> 0.056074766 | J72: =IFERROR(J71/I71-1,"N/A") -> 0.030973451 | K72: =IFERROR(K71/J71-1,"N/A") -> 0.060085837 | L72: =IFERROR(L71/K71-1,"N/A") -> 0.056680162 | M72: =IFERROR(M71/L71-1,"N/A") -> 0.12260536 | N72: 0.068 | O72: 0.067 | P72: 0.048 | Q72: 0.046 | R72: 0.043
C73: Revenue | G73: =G69*G71 -> 869679 | H73: =H69*H71 -> 812344 | I73: =I69*I71 -> 930442 | J73: =J69*J71 -> 1013317 | K73: =K69*K71 -> 1151267 | L73: =L69*L71 -> 1317267 | M73: =M69*M71 -> 1643144 | N73: =N69*N71 -> 1854905.8 | ... R73: =R69*R71 -> 2850633.7
C75: Emergency:
C76: # of Visits | G76: 14069 | H76: 13115 | I76: 13986 | J76: 15535 | K76: 16371 | L76: 17413 | M76: 18984 | N76: =M76*(1+N77) -> 19781.328 | O76: =N76*(1+O77) -> 20790.176 | P76: =O76*(1+P77) -> 22287.068 | Q76: =P76*(1+Q77) -> 23713.441 | R76: =Q76*(1+R77) -> 25515.662
C77: Growth (%) | G77: =IFERROR(G76/F76-1,"N/A") -> N/A | H77: =IFERROR(H76/G76-1,"N/A") -> -0.067808657 | I77: =IFERROR(I76/H76-1,"N/A") -> 0.066412505 | J77: =IFERROR(J76/I76-1,"N/A") -> 0.11075361 | K77: =IFERROR(K76/J76-1,"N/A") -> 0.053813968 | L77: =IFERROR(L76/K76-1,"N/A") -> 0.063649136 | M77: =IFERROR(M76/L76-1,"N/A") -> 0.090219951 | N77: 0.042 | O77: 0.051 | P77: 0.072 | Q77: 0.064 | R77: 0.076
C78: Gross Revenue [per Visit] (LCA) | G78: 156 | H78: 162 | I78: 172 | J78: 181 | K78: 193 | L78: 204 | M78: 216 | N78: =M78*(1+N79) -> 229.392 | O78: =N78*(1+O79) -> 239.48525 | P78: =O78*(1+P79) -> 252.17797 | Q78: =P78*(1+Q79) -> 263.52597 | R78: =Q78*(1+R79) -> 281.70927
C79: Growth (%) | G79: =IFERROR(G78/F78-1,"N/A") -> N/A | H79: =IFERROR(H78/G78-1,"N/A") -> 0.038461538 | I79: =IFERROR(I78/H78-1,"N/A") -> 0.061728395 | J79: =IFERROR(J78/I78-1,"N/A") -> 0.052325581 | K79: =IFERROR(K78/J78-1,"N/A") -> 0.066298343 | L79: =IFERROR(L78/K78-1,"N/A") -> 0.056994819 | M79: =IFERROR(M78/L78-1,"N/A") -> 0.058823529 | N79: 0.062 | O79: 0.044 | P79: 0.053 | Q79: 0.045 | R79: 0.069
C80: Revenue | G80: =G76*G78 -> 2194764 | H80: =H76*H78 -> 2124630 | I80: =I76*I78 -> 2405592 | J80: =J76*J78 -> 2811835 | K80: =K76*K78 -> 3159603 | L80: =L76*L78 -> 3552252 | M80: =M76*M78 -> 4100544 | N80: =N76*N78 -> 4537678.4 | ... R80: =R76*R78 -> 7187998.5
C82: Accommodation:
C83: # of Beds | G83: 134 | H83: 134 | I83: 134 | J83: 134 | K83: 142 | L83: 142 | M83: 142 | N83: =M83 -> 142 | O83: =N83 -> 142 | P83: =O83 -> 142 | Q83: =P83 -> 142 | R83: =Q83 -> 142
C84: Available Beds a Night | G84: =G83*360 -> 48240 | H84: =H83*360 -> 48240 | I84: =I83*360 -> 48240 | J84: =J83*360 -> 48240 | K84: =K83*360 -> 51120 | L84: =L83*360 -> 51120 | M84: =M83*360 -> 51120 | N84: =N83*360 -> 51120 | ... R84: =R83*360 -> 51120
C85: # of Occupied bed nights | G85: 34444 | H85: 29426 | I85: 32090 | J85: 34421 | K85: 35332 | L85: 36682 | M85: 36921 | N85: =N84*N86 -> 37522.08 | O85: =O84*O86 -> 38135.52 | P85: =P84*P86 -> 38748.96 | Q85: =Q84*Q86 -> 39362.4 | R85: =R84*R86 -> 39975.84
C86: Occupancy Ratio (%) | G86: =IFERROR(G85/G84,"N/A") -> 0.71401327 | H86: =IFERROR(H85/H84,"N/A") -> 0.60999171 | I86: =IFERROR(I85/I84,"N/A") -> 0.66521559 | J86: =IFERROR(J85/J84,"N/A") -> 0.71353648 | K86: =IFERROR(K85/K84,"N/A") -> 0.69115806 | L86: =IFERROR(L85/L84,"N/A") -> 0.71756651 | M86: =IFERROR(M85/M84,"N/A") -> 0.72224178 | N86: 0.734 | O86: 0.746 | P86: 0.758 | Q86: 0.77 | R86: 0.782
C87: Gross Revenue [per bed night] (LCA) | G87: 332 | H87: 352 | I87: 366 | J87: 396 | K87: 441 | L87: 457 | M87: 472 | N87: =M87*(1+N88) -> 505.04 | O87: =N87*(1+O88) -> 531.80712 | P87: =O87*(1+P88) -> 561.58832 | Q87: =P87*(1+Q88) -> 600.8995 | R87: =Q87*(1+R88) -> 633.34807
C88: Growth (%) | G88: =IFERROR(G87/F87-1,"N/A") -> N/A | H88: =IFERROR(H87/G87-1,"N/A") -> 0.060240964 | I88: =IFERROR(I87/H87-1,"N/A") -> 0.039772727 | J88: =IFERROR(J87/I87-1,"N/A") -> 0.081967213 | K88: =IFERROR(K87/J87-1,"N/A") -> 0.11363636 | L88: =IFERROR(L87/K87-1,"N/A") -> 0.036281179 | M88: =IFERROR(M87/L87-1,"N/A") -> 0.032822757 | N88: 0.07 | O88: 0.053 | P88: 0.056 | Q88: 0.07 | R88: 0.054
C89: Revenue | G89: =G85*G87 -> 11435408 | H89: =H85*H87 -> 10357952 | I89: =I85*I87 -> 11744940 | J89: =J85*J87 -> 13630716 | K89: =K85*K87 -> 15581412 | L89: =L85*L87 -> 16763674 | M89: =M85*M87 -> 17426712 | N89: =N85*N87 -> 18950151 | ... R89: =R85*R87 -> 25318621
C91: Radiotherapy:
C92: # of Sessions | G92: =G117 -> 4063 | H92: =H117 -> 3465 | I92: =I117 -> 4598 | J92: =J117 -> 5368 | K92: =K117 -> 5832 | L92: =L117 -> 6396 | M92: =M117 -> 6588 | N92: =N117 -> 6917.4 | ... R92: =R117 -> 8408.1429
C93: Growth (%) | G93: =IFERROR(G92/F92-1,"N/A") -> N/A | H93: =IFERROR(H92/G92-1,"N/A") -> -0.14718189 | I93: =IFERROR(I92/H92-1,"N/A") -> 0.32698413 | J93: =IFERROR(J92/I92-1,"N/A") -> 0.16746411 | K93: =IFERROR(K92/J92-1,"N/A") -> 0.086438152 | L93: =IFERROR(L92/K92-1,"N/A") -> 0.096707819 | M93: =IFERROR(M92/L92-1,"N/A") -> 0.030018762 | N93: =IFERROR(N92/M92-1,"N/A") -> 0.05 | ... R93: =IFERROR(R92/Q92-1,"N/A") -> 0.05
C94: Gross Revenue [per Session] (LCA) | G94: =G118 -> 962 | H94: =H118 -> 1000 | I94: =I118 -> 1039 | J94: =J118 -> 1120 | K94: =K118 -> 1177 | L94: =L118 -> 1262 | M94: =M118 -> 1340 | N94: =N118 -> 1413.7 | ... R94: =R118 -> 1734.633
C95: Growth (%) | G95: =IFERROR(G94/F94-1,"N/A") -> N/A | H95: =IFERROR(H94/G94-1,"N/A") -> 0.03950104 | I95: =IFERROR(I94/H94-1,"N/A") -> 0.039 | J95: =IFERROR(J94/I94-1,"N/A") -> 0.077959577 | K95: =IFERROR(K94/J94-1,"N/A") -> 0.050892857 | L95: =IFERROR(L94/K94-1,"N/A") -> 0.072217502 | M95: =IFERROR(M94/L94-1,"N/A") -> 0.061806656 | N95: =IFERROR(N94/M94-1,"N/A") -> 0.055 | ... R95: =IFERROR(R94/Q94-1,"N/A") -> 0.048
C96: Revenue | G96: =G120 -> 3908606 | H96: =H120 -> 3465000 | I96: =I120 -> 4777322 | J96: =J120 -> 6012160 | K96: =K120 -> 6864264 | L96: =L120 -> 8071752 | M96: =M120 -> 8827920 | N96: =N120 -> 9779128.4 | ... R96: =R120 -> 14585042
C98: Nursing Fees:
C99: # of Visits | G99: 7369 | H99: 6610 | I99: 7003 | J99: 7387 | K99: 8132 | L99: 8746 | M99: 9660 | N99: =M99*(1+N100) -> 10220.28 | O99: =N99*(1+O100) -> 10659.752 | P99: =O99*(1+P100) -> 11150.101 | Q99: =P99*(1+Q100) -> 11952.908 | R99: =Q99*(1+R100) -> 12933.046
C100: Growth (%) | G100: =IFERROR(G99/F99-1,"N/A") -> N/A | H100: =IFERROR(H99/G99-1,"N/A") -> -0.10299905 | I100: =IFERROR(I99/H99-1,"N/A") -> 0.059455371 | J100: =IFERROR(J99/I99-1,"N/A") -> 0.054833643 | K100: =IFERROR(K99/J99-1,"N/A") -> 0.10085285 | L100: =IFERROR(L99/K99-1,"N/A") -> 0.075504181 | M100: =IFERROR(M99/L99-1,"N/A") -> 0.10450492 | N100: 0.058 | O100: 0.043 | P100: 0.046 | Q100: 0.072 | R100: 0.082
C101: Gross Revenue [per Visit] (LCA) | G101: 76 | H101: 75 | I101: 82 | J101: 90 | K101: 95 | L101: 97 | M101: 106 | N101: =M101*(1+N102) -> 110.452 | O101: =N101*(1+O102) -> 118.07319 | P101: =O101*(1+P102) -> 124.44914 | Q101: =P101*(1+Q102) -> 129.676 | R101: =Q101*(1+R102) -> 137.84559
C102: Growth (%) | G102: =IFERROR(G101/F101-1,"N/A") -> N/A | H102: =IFERROR(H101/G101-1,"N/A") -> -0.013157895 | I102: =IFERROR(I101/H101-1,"N/A") -> 0.093333333 | J102: =IFERROR(J101/I101-1,"N/A") -> 0.097560976 | K102: =IFERROR(K101/J101-1,"N/A") -> 0.055555556 | L102: =IFERROR(L101/K101-1,"N/A") -> 0.021052632 | M102: =IFERROR(M101/L101-1,"N/A") -> 0.092783505 | N102: 0.042 | O102: 0.069 | P102: 0.054 | Q102: 0.042 | R102: 0.063
C103: Revenue | G103: =G99*G101 -> 560044 | H103: =H99*H101 -> 495750 | I103: =I99*I101 -> 574246 | J103: =J99*J101 -> 664830 | K103: =K99*K101 -> 772540 | L103: =L99*L101 -> 848362 | M103: =M99*M101 -> 1023960 | N103: =N99*N101 -> 1128850.4 | ... R103: =R99*R101 -> 1782763.4
C105: Pharmacy:
C106: Gross Revenue (LCA) | G106: 1818000 | H106: 1712000 | I106: 1887000 | J106: 2101000 | K106: 2457000 | L106: 2861000 | M106: 3195000 | N106: =N108*(N17+N24+N31+N38+N45+N52+N59+N66+N73+N80+N89+N96+N103) -> 5947918.9 | O106: =O108*(O17+O24+O31+O38+O45+O52+O59+O66+O73+O80+O89+O96+O103) -> 6507727 | P106: =P108*(P17+P24+P31+P38+P45+P52+P59+P66+P73+P80+P89+P96+P103) -> 6854860.6 | Q106: =Q108*(Q17+Q24+Q31+Q38+Q45+Q52+Q59+Q66+Q73+Q80+Q89+Q96+Q103) -> 7810961.5 | R106: =R108*(R17+R24+R31+R38+R45+R52+R59+R66+R73+R80+R89+R96+R103) -> 8871604.4
C107: Growth (%) | G107: =IFERROR(G106/F106-1,"N/A") -> N/A | H107: =IFERROR(H106/G106-1,"N/A") -> -0.058305831 | I107: =IFERROR(I106/H106-1,"N/A") -> 0.10221963 | J107: =IFERROR(J106/I106-1,"N/A") -> 0.11340753 | K107: =IFERROR(K106/J106-1,"N/A") -> 0.16944312 | L107: =IFERROR(L106/K106-1,"N/A") -> 0.16442816 | M107: =IFERROR(M106/L106-1,"N/A") -> 0.1167424 | N107: =IFERROR(N106/M106-1,"N/A") -> 0.86163346 | ... R107: =IFERROR(R106/Q106-1,"N/A") -> 0.13578903
C108: % of Other Hospital Revenue | G108: =IFERROR(G106/(G17+G24+G31+G38+G45+G52+G59+G66+G73+G80+G89+G96+G103),"N/A") -> 0.05242993 | H108: =IFERROR(H106/(H17+H24+H31+H38+H45+H52+H59+H66+H73+H80+H89+H96+H103),"N/A") -> 0.053473566 | I108: =IFERROR(I106/(I17+I24+I31+I38+I45+I52+I59+I66+I73+I80+I89+I96+I103),"N/A") -> 0.049986009 | J108: =IFERROR(J106/(J17+J24+J31+J38+J45+J52+J59+J66+J73+J80+J89+J96+J103),"N/A") -> 0.047425674 | K108: =IFERROR(K106/(K17+K24+K31+K38+K45+K52+K59+K66+K73+K80+K89+K96+K103),"N/A") -> 0.04855601 | L108: =IFERROR(L106/(L17+L24+L31+L38+L45+L52+L59+L66+L73+L80+L89+L96+L103),"N/A") -> 0.050644695 | M108: =IFERROR(M106/(M17+M24+M31+M38+M45+M52+M59+M66+M73+M80+M89+M96+M103),"N/A") -> 0.050723946 | N108: 0.085 | O108: 0.084 | P108: 0.08 | Q108: 0.082 | R108: 0.084
C109: Revenue | G109: =G106 -> 1818000 | H109: =H106 -> 1712000 | I109: =I106 -> 1887000 | J109: =J106 -> 2101000 | K109: =K106 -> 2457000 | L109: =L106 -> 2861000 | M109: =M106 -> 3195000 | N109: =N106 -> 5947918.9 | ... R109: =R106 -> 8871604.4
C111: Operations:
C112: Maximum Number of Patients per Day | G112: 36 | H112: 36 | I112: 36 | J112: 36 | K112: 36 | L112: 36 | M112: 36 | N112: =M112 -> 36 | O112: =N112 -> 36 | P112: =O112 -> 36 | Q112: =P112 -> 36 | R112: =Q112 -> 36
C113: Number of Patients on Machine per Day | G113: 17 | H113: 15 | I113: 19 | J113: 22 | K113: 24 | L113: 26 | M113: 27 | N113: =MIN(N112,M113*(1+N114)) -> 28.35 | O113: =MIN(O112,N113*(1+O114)) -> 29.7675 | P113: =MIN(P112,O113*(1+P114)) -> 31.255875 | Q113: =MIN(Q112,P113*(1+Q114)) -> 32.818669 | R113: =MIN(R112,Q113*(1+R114)) -> 34.459602
C114: Growth (%) | G114: =IFERROR(G113/F113-1,"N/A") -> N/A | H114: =IFERROR(H113/G113-1,"N/A") -> -0.11764706 | I114: =IFERROR(I113/H113-1,"N/A") -> 0.26666667 | J114: =IFERROR(J113/I113-1,"N/A") -> 0.15789474 | K114: =IFERROR(K113/J113-1,"N/A") -> 0.090909091 | L114: =IFERROR(L113/K113-1,"N/A") -> 0.083333333 | M114: =IFERROR(M113/L113-1,"N/A") -> 0.038461538 | N114: 0.05 | O114: 0.05 | P114: 0.05 | Q114: 0.05 | R114: 0.05
C115: Number of Theoretical Working Days per Year | G115: 261 | H115: 261 | I115: 261 | J115: 261 | K115: 261 | L115: 261 | M115: 261 | N115: =M115 -> 261 | O115: =N115 -> 261 | P115: =O115 -> 261 | Q115: =P115 -> 261 | R115: =Q115 -> 261
C116: Adjusted Number of Working Days per Year | G116: 239 | H116: 231 | I116: 242 | J116: 244 | K116: 243 | L116: 246 | M116: 244 | N116: =M116 -> 244 | O116: =N116 -> 244 | P116: =O116 -> 244 | Q116: =P116 -> 244 | R116: =Q116 -> 244
C117: Number of Annual Sessions | G117: =G113*G116 -> 4063 | H117: =H113*H116 -> 3465 | I117: =I113*I116 -> 4598 | J117: =J113*J116 -> 5368 | K117: =K113*K116 -> 5832 | L117: =L113*L116 -> 6396 | M117: =M113*M116 -> 6588 | N117: =N113*N116 -> 6917.4 | ... R117: =R113*R116 -> 8408.1429
C118: Session Price (LCA) | G118: 962 | H118: 1000 | I118: 1039 | J118: 1120 | K118: 1177 | L118: 1262 | M118: 1340 | N118: =M118*(1+N119) -> 1413.7 | O118: =N118*(1+O119) -> 1487.2124 | P118: =O118*(1+P119) -> 1582.394 | Q118: =P118*(1+Q119) -> 1655.1841 | R118: =Q118*(1+R119) -> 1734.633
...

Sheet 4. AHG Park
C3: =Cover!$C$3 -> Project Dunecrest | D3: Confidential
C4: AHG Park – Operating Build
C6: Fiscal Year Ending | G6: 43830 | H6: 44196 | I6: 44561 | J6: 44926 | K6: =EOMONTH(J6,12) -> 45291 | L6: =EOMONTH(K6,12) -> 45657 | M6: =EOMONTH(L6,12) -> 46022 | N6: =EOMONTH(M6,12) -> 46387 | O6: =EOMONTH(N6,12) -> 46752 | P6: =EOMONTH(O6,12) -> 47118 | Q6: =EOMONTH(P6,12) -> 47483 | R6: =EOMONTH(Q6,12) -> 47848
C7: Fiscal Year | G7: =YEAR(G6) -> 2019 | H7: =YEAR(H6) -> 2020 | I7: =YEAR(I6) -> 2021 | J7: =YEAR(J6) -> 2022 | K7: =YEAR(K6) -> 2023 | L7: =YEAR(L6) -> 2024 | M7: =YEAR(M6) -> 2025 | N7: =YEAR(N6) -> 2026 | ... R7: =YEAR(R6) -> 2030
C8: Actual / Estimate | G8: =IF(G6<=Control!$E$11,"A","E") -> A | H8: =IF(H6<=Control!$E$11,"A","E") -> A | I8: =IF(I6<=Control!$E$11,"A","E") -> A | J8: =IF(J6<=Control!$E$11,"A","E") -> A | K8: =IF(K6<=Control!$E$11,"A","E") -> A | L8: =IF(L6<=Control!$E$11,"A","E") -> A | M8: =IF(M6<=Control!$E$11,"A","E") -> A | N8: =IF(N6<=Control!$E$11,"A","E") -> E | ... R8: =IF(R6<=Control!$E$11,"A","E") -> E
C10: Supporting Data
C11: A | D11: Revenue Build | E11: ="("&Control!$E$16&" in Actual)" -> (LCA in Actual)
C12: Laboratory:
C13: # of Tests | G13: 65182 | H13: 59935 | I13: 63531 | J13: 69282 | K13: 76441 | L13: 82362 | M13: 90213 | N13: =M13*(1+N14) -> 95084.502 | O13: =N13*(1+O14) -> 102881.43 | P13: =O13*(1+P14) -> 107305.33 | Q13: =P13*(1+Q14) -> 116962.81 | R13: =Q13*(1+R14) -> 124565.4
C14: Growth (%) | G14: =IFERROR(G13/F13-1,"N/A") -> N/A | H14: =IFERROR(H13/G13-1,"N/A") -> -0.080497683 | I14: =IFERROR(I13/H13-1,"N/A") -> 0.059998332 | J14: =IFERROR(J13/I13-1,"N/A") -> 0.090522737 | K14: =IFERROR(K13/J13-1,"N/A") -> 0.10333131 | L14: =IFERROR(L13/K13-1,"N/A") -> 0.077458432 | M14: =IFERROR(M13/L13-1,"N/A") -> 0.095323086 | N14: 0.054 | O14: 0.082 | P14: 0.043 | Q14: 0.09 | R14: 0.065
C15: Gross Revenue [per Test] (LCA) | G15: 36 | H15: 38 | I15: 42 | J15: 46 | K15: 48 | L15: 52 | M15: 55 | N15: =M15*(1+N16) -> 57.915 | O15: =N15*(1+O16) -> 61.3899 | P15: =O15*(1+P16) -> 64.213835 | Q15: =P15*(1+Q16) -> 66.910816 | R15: =Q15*(1+R16) -> 70.256357
C16: Growth (%) | G16: =IFERROR(G15/F15-1,"N/A") -> N/A | H16: =IFERROR(H15/G15-1,"N/A") -> 0.055555556 | I16: =IFERROR(I15/H15-1,"N/A") -> 0.10526316 | J16: =IFERROR(J15/I15-1,"N/A") -> 0.095238095 | K16: =IFERROR(K15/J15-1,"N/A") -> 0.043478261 | L16: =IFERROR(L15/K15-1,"N/A") -> 0.083333333 | M16: =IFERROR(M15/L15-1,"N/A") -> 0.057692308 | N16: 0.053 | O16: 0.06 | P16: 0.046 | Q16: 0.042 | R16: 0.05
C17: Revenue | G17: =G13*G15 -> 2346552 | H17: =H13*H15 -> 2277530 | I17: =I13*I15 -> 2668302 | J17: =J13*J15 -> 3186972 | K17: =K13*K15 -> 3669168 | L17: =L13*L15 -> 4282824 | M17: =M13*M15 -> 4961715 | N17: =N13*N15 -> 5506818.9 | ... R17: =R13*R15 -> 8751510.9
C19: Radiology:
C20: # of Tests | G20: 16802 | H20: 15984 | I20: 17340 | J20: 18721 | K20: 19759 | L20: 21541 | M20: 23467 | N20: =M20*(1+N21) -> 24616.883 | O20: =N20*(1+O21) -> 26020.045 | P20: =O20*(1+P21) -> 27269.008 | Q20: =P20*(1+Q21) -> 28986.955 | R20: =Q20*(1+R21) -> 31508.82
C21: Growth (%) | G21: =IFERROR(G20/F20-1,"N/A") -> N/A | H21: =IFERROR(H20/G20-1,"N/A") -> -0.04868468 | I21: =IFERROR(I20/H20-1,"N/A") -> 0.084834835 | J21: =IFERROR(J20/I20-1,"N/A") -> 0.079642445 | K21: =IFERROR(K20/J20-1,"N/A") -> 0.055445756 | L21: =IFERROR(L20/K20-1,"N/A") -> 0.09018675 | M21: =IFERROR(M20/L20-1,"N/A") -> 0.089410891 | N21: 0.049 | O21: 0.057 | P21: 0.048 | Q21: 0.063 | R21: 0.087
C22: Gross Revenue [per Test] (LCA) | G22: 116 | H22: 115 | I22: 125 | J22: 130 | K22: 137 | L22: 143 | M22: 152 | N22: =M22*(1+N23) -> 161.576 | O22: =N22*(1+O23) -> 169.6548 | P22: =O22*(1+P23) -> 178.47685 | Q22: =P22*(1+Q23) -> 188.29308 | R22: =Q22*(1+R23) -> 197.70773
C23: Growth (%) | G23: =IFERROR(G22/F22-1,"N/A") -> N/A | H23: =IFERROR(H22/G22-1,"N/A") -> -0.0086206897 | I23: =IFERROR(I22/H22-1,"N/A") -> 0.086956522 | J23: =IFERROR(J22/I22-1,"N/A") -> 0.04 | K23: =IFERROR(K22/J22-1,"N/A") -> 0.053846154 | L23: =IFERROR(L22/K22-1,"N/A") -> 0.04379562 | M23: =IFERROR(M22/L22-1,"N/A") -> 0.062937063 | N23: 0.063 | O23: 0.05 | P23: 0.052 | Q23: 0.055 | R23: 0.05
C24: Revenue | G24: =G20*G22 -> 1949032 | H24: =H20*H22 -> 1838160 | I24: =I20*I22 -> 2167500 | J24: =J20*J22 -> 2433730 | K24: =K20*K22 -> 2706983 | L24: =L20*L22 -> 3080363 | M24: =M20*M22 -> 3566984 | N24: =N20*N22 -> 3977497.5 | ... R24: =R20*R22 -> 6229537.3
C26: Endoscopy:
C27: # of Visits | G27: 0 | H27: 0 | I27: 0 | J27: 0 | K27: 0 | L27: 0 | M27: 0 | N27: =M27*(1+N28) -> 0 | O27: =N27*(1+O28) -> 0 | P27: =O27*(1+P28) -> 0 | Q27: =P27*(1+Q28) -> 0 | R27: =Q27*(1+R28) -> 0
C28: Growth (%) | G28: =IFERROR(G27/F27-1,"N/A") -> N/A | H28: =IFERROR(H27/G27-1,"N/A") -> N/A | I28: =IFERROR(I27/H27-1,"N/A") -> N/A | J28: =IFERROR(J27/I27-1,"N/A") -> N/A | K28: =IFERROR(K27/J27-1,"N/A") -> N/A | L28: =IFERROR(L27/K27-1,"N/A") -> N/A | M28: =IFERROR(M27/L27-1,"N/A") -> N/A | N28: 0 | O28: 0 | P28: 0 | Q28: 0 | R28: 0
C29: Gross Revenue [per Visit] (LCA) | G29: 745 | H29: 756 | I29: 808 | J29: 858 | K29: 943 | L29: 1034 | M29: 1087 | N29: =M29*(1+N30) -> 1147.872 | O29: =N29*(1+O30) -> 1193.7869 | P29: =O29*(1+P30) -> 1267.8017 | Q29: =P29*(1+Q30) -> 1323.5849 | R29: =Q29*(1+R30) -> 1412.2651
C30: Growth (%) | G30: =IFERROR(G29/F29-1,"N/A") -> N/A | H30: =IFERROR(H29/G29-1,"N/A") -> 0.014765101 | I30: =IFERROR(I29/H29-1,"N/A") -> 0.068783069 | J30: =IFERROR(J29/I29-1,"N/A") -> 0.061881188 | K30: =IFERROR(K29/J29-1,"N/A") -> 0.099067599 | L30: =IFERROR(L29/K29-1,"N/A") -> 0.09650053 | M30: =IFERROR(M29/L29-1,"N/A") -> 0.051257253 | N30: 0.056 | O30: 0.04 | P30: 0.062 | Q30: 0.044 | R30: 0.067
C31: Revenue | G31: =G27*G29 -> 0 | H31: =H27*H29 -> 0 | I31: =I27*I29 -> 0 | J31: =J27*J29 -> 0 | K31: =K27*K29 -> 0 | L31: =L27*L29 -> 0 | M31: =M27*M29 -> 0 | N31: =N27*N29 -> 0 | ... R31: =R27*R29 -> 0
C33: Physiotherapy:
C34: # of Patients | G34: 3334 | H34: 3048 | I34: 3317 | J34: 3728 | K34: 3975 | L34: 4373 | M34: 4931 | N34: =M34*(1+N35) -> 5310.687 | O34: =N34*(1+O35) -> 5756.7847 | P34: =O34*(1+P35) -> 5987.0561 | Q34: =P34*(1+Q35) -> 6507.93 | R34: =Q34*(1+R35) -> 6983.0089
C35: Growth (%) | G35: =IFERROR(G34/F34-1,"N/A") -> N/A | H35: =IFERROR(H34/G34-1,"N/A") -> -0.085782843 | I35: =IFERROR(I34/H34-1,"N/A") -> 0.088254593 | J35: =IFERROR(J34/I34-1,"N/A") -> 0.12390715 | K35: =IFERROR(K34/J34-1,"N/A") -> 0.066255365 | L35: =IFERROR(L34/K34-1,"N/A") -> 0.10012579 | M35: =IFERROR(M34/L34-1,"N/A") -> 0.12760119 | N35: 0.077 | O35: 0.084 | P35: 0.04 | Q35: 0.087 | R35: 0.073
C36: Gross Revenue [per Patient] (LCA) | G36: 104 | H36: 104 | I36: 109 | J36: 117 | K36: 129 | L36: 138 | M36: 143 | N36: =M36*(1+N37) -> 151.866 | O36: =N36*(1+O37) -> 161.43356 | P36: =O36*(1+P37) -> 172.41104 | Q36: =P36*(1+Q37) -> 180.68677 | R36: =Q36*(1+R37) -> 190.98592
C37: Growth (%) | G37: =IFERROR(G36/F36-1,"N/A") -> N/A | H37: =IFERROR(H36/G36-1,"N/A") -> 0 | I37: =IFERROR(I36/H36-1,"N/A") -> 0.048076923 | J37: =IFERROR(J36/I36-1,"N/A") -> 0.073394495 | K37: =IFERROR(K36/J36-1,"N/A") -> 0.1025641 | L37: =IFERROR(L36/K36-1,"N/A") -> 0.069767442 | M37: =IFERROR(M36/L36-1,"N/A") -> 0.036231884 | N37: 0.062 | O37: 0.063 | P37: 0.068 | Q37: 0.048 | R37: 0.057
C38: Revenue | G38: =G34*G36 -> 346736 | H38: =H34*H36 -> 316992 | I38: =I34*I36 -> 361553 | J38: =J34*J36 -> 436176 | K38: =K34*K36 -> 512775 | L38: =L34*L36 -> 603474 | M38: =M34*M36 -> 705133 | N38: =N34*N36 -> 806512.79 | ... R38: =R34*R36 -> 1333656.3
C40: IVF:
C41: # of Patients | G41: 150 | H41: 142 | I41: 158 | J41: 168 | K41: 187 | L41: 207 | M41: 219 | N41: =M41*(1+N42) -> 236.958 | O41: =N41*(1+O42) -> 248.09503 | P41: =O41*(1+P42) -> 267.94263 | Q41: =P41*(1+Q42) -> 285.62684 | R41: =Q41*(1+R42) -> 310.19075
C42: Growth (%) | G42: =IFERROR(G41/F41-1,"N/A") -> N/A | H42: =IFERROR(H41/G41-1,"N/A") -> -0.053333333 | I42: =IFERROR(I41/H41-1,"N/A") -> 0.11267606 | J42: =IFERROR(J41/I41-1,"N/A") -> 0.063291139 | K42: =IFERROR(K41/J41-1,"N/A") -> 0.11309524 | L42: =IFERROR(L41/K41-1,"N/A") -> 0.10695187 | M42: =IFERROR(M41/L41-1,"N/A") -> 0.057971014 | N42: 0.082 | O42: 0.047 | P42: 0.08 | Q42: 0.066 | R42: 0.086
C43: Gross Revenue [per Patient] (LCA) | G43: 3952 | H43: 3936 | I43: 4194 | J43: 4392 | K43: 4744 | L43: 4983 | M43: 5183 | N43: =M43*(1+N44) -> 5426.601 | O43: =N43*(1+O44) -> 5784.7567 | P43: =O43*(1+P44) -> 6091.3488 | Q43: =P43*(1+Q44) -> 6383.7335 | R43: =Q43*(1+R44) -> 6811.4437
C44: Growth (%) | G44: =IFERROR(G43/F43-1,"N/A") -> N/A | H44: =IFERROR(H43/G43-1,"N/A") -> -0.004048583 | I44: =IFERROR(I43/H43-1,"N/A") -> 0.06554878 | J44: =IFERROR(J43/I43-1,"N/A") -> 0.0472103 | K44: =IFERROR(K43/J43-1,"N/A") -> 0.080145719 | L44: =IFERROR(L43/K43-1,"N/A") -> 0.050379427 | M44: =IFERROR(M43/L43-1,"N/A") -> 0.040136464 | N44: 0.047 | O44: 0.066 | P44: 0.053 | Q44: 0.048 | R44: 0.067
C45: Revenue | G45: =G41*G43 -> 592800 | H45: =H41*H43 -> 558912 | I45: =I41*I43 -> 662652 | J45: =J41*J43 -> 737856 | K45: =K41*K43 -> 887128 | L45: =L41*L43 -> 1031481 | M45: =M41*M43 -> 1135077 | N45: =N41*N43 -> 1285876.5 | ... R45: =R41*R43 -> 2112846.8
C47: Anapath:
C48: # of Patients | G48: 4428 | H48: 4204 | I48: 4465 | J48: 4686 | K48: 5080 | L48: 5552 | M48: 5957 | N48: =M48*(1+N49) -> 6373.99 | O48: =N48*(1+O49) -> 6711.8115 | P48: =O48*(1+P49) -> 7174.9265 | Q48: =P48*(1+Q49) -> 7648.4716 | R48: =Q48*(1+R49) -> 8267.9978
C49: Growth (%) | G49: =IFERROR(G48/F48-1,"N/A") -> N/A | H49: =IFERROR(H48/G48-1,"N/A") -> -0.050587173 | I49: =IFERROR(I48/H48-1,"N/A") -> 0.06208373 | J49: =IFERROR(J48/I48-1,"N/A") -> 0.049496081 | K49: =IFERROR(K48/J48-1,"N/A") -> 0.084080239 | L49: =IFERROR(L48/K48-1,"N/A") -> 0.092913386 | M49: =IFERROR(M48/L48-1,"N/A") -> 0.072946686 | N49: 0.07 | O49: 0.053 | P49: 0.069 | Q49: 0.066 | R49: 0.081
C50: Gross Revenue [per Patient] (LCA) | G50: 126 | H50: 125 | I50: 137 | J50: 149 | K50: 161 | L50: 172 | M50: 180 | N50: =M50*(1+N51) -> 192.42 | O50: =N50*(1+O51) -> 205.69698 | P50: =O50*(1+P51) -> 216.59892 | Q50: =P50*(1+Q51) -> 229.59486 | R50: =Q50*(1+R51) -> 243.37055
C51: Growth (%) | G51: =IFERROR(G50/F50-1,"N/A") -> N/A | H51: =IFERROR(H50/G50-1,"N/A") -> -0.0079365079 | I51: =IFERROR(I50/H50-1,"N/A") -> 0.096 | J51: =IFERROR(J50/I50-1,"N/A") -> 0.087591241 | K51: =IFERROR(K50/J50-1,"N/A") -> 0.080536913 | L51: =IFERROR(L50/K50-1,"N/A") -> 0.068322981 | M51: =IFERROR(M50/L50-1,"N/A") -> 0.046511628 | N51: 0.069 | O51: 0.069 | P51: 0.053 | Q51: 0.06 | R51: 0.06
C52: Revenue | G52: =G48*G50 -> 557928 | H52: =H48*H50 -> 525500 | I52: =I48*I50 -> 611705 | J52: =J48*J50 -> 698214 | K52: =K48*K50 -> 817880 | L52: =L48*L50 -> 954944 | M52: =M48*M50 -> 1072260 | N52: =N48*N50 -> 1226483.2 | ... R52: =R48*R50 -> 2012187.1
C54: Surgery:
C55: # of Surgeries | G55: 2403 | H55: 2227 | I55: 2427 | J55: 2634 | K55: 2817 | L55: 3041 | M55: 3216 | N55: =M55*(1+N56) -> 3367.152 | O55: =N55*(1+O56) -> 3548.9782 | P55: =O55*(1+P56) -> 3822.2495 | Q55: =P55*(1+Q56) -> 4082.1625 | R55: =Q55*(1+R56) -> 4404.6533
C56: Growth (%) | G56: =IFERROR(G55/F55-1,"N/A") -> N/A | H56: =IFERROR(H55/G55-1,"N/A") -> -0.073241781 | I56: =IFERROR(I55/H55-1,"N/A") -> 0.089806915 | J56: =IFERROR(J55/I55-1,"N/A") -> 0.085290482 | K56: =IFERROR(K55/J55-1,"N/A") -> 0.069476082 | L56: =IFERROR(L55/K55-1,"N/A") -> 0.079517217 | M56: =IFERROR(M55/L55-1,"N/A") -> 0.05754686 | N56: 0.047 | O56: 0.054 | P56: 0.077 | Q56: 0.068 | R56: 0.079
C57: Gross Revenue [per Surgery] (LCA) | G57: 2052 | H57: 2146 | I57: 2313 | J57: 2504 | K57: 2616 | L57: 2857 | M57: 3011 | N57: =M57*(1+N58) -> 3143.484 | O57: =N57*(1+O58) -> 3288.0843 | P57: =O57*(1+P58) -> 3462.3527 | Q57: =P57*(1+Q58) -> 3666.6315 | R57: =Q57*(1+R58) -> 3908.6292
C58: Growth (%) | G58: =IFERROR(G57/F57-1,"N/A") -> N/A | H58: =IFERROR(H57/G57-1,"N/A") -> 0.045808967 | I58: =IFERROR(I57/H57-1,"N/A") -> 0.077819199 | J58: =IFERROR(J57/I57-1,"N/A") -> 0.08257674 | K58: =IFERROR(K57/J57-1,"N/A") -> 0.044728435 | L58: =IFERROR(L57/K57-1,"N/A") -> 0.092125382 | M58: =IFERROR(M57/L57-1,"N/A") -> 0.053902695 | N58: 0.044 | O58: 0.046 | P58: 0.053 | Q58: 0.059 | R58: 0.066
C59: Revenue | G59: =G55*G57 -> 4930956 | H59: =H55*H57 -> 4779142 | I59: =I55*I57 -> 5613651 | J59: =J55*J57 -> 6595536 | K59: =K55*K57 -> 7369272 | L59: =L55*L57 -> 8688137 | M59: =M55*M57 -> 9683376 | N59: =N55*N57 -> 10584588 | ... R59: =R55*R57 -> 17216157
C61: Cardiac Cath:
C62: # of Surgeries | G62: 0 | H62: 0 | I62: 0 | J62: 0 | K62: 0 | L62: 0 | M62: 0 | N62: =M62*(1+N63) -> 0 | O62: =N62*(1+O63) -> 0 | P62: =O62*(1+P63) -> 0 | Q62: =P62*(1+Q63) -> 0 | R62: =Q62*(1+R63) -> 0
C63: Growth (%) | G63: =IFERROR(G62/F62-1,"N/A") -> N/A | H63: =IFERROR(H62/G62-1,"N/A") -> N/A | I63: =IFERROR(I62/H62-1,"N/A") -> N/A | J63: =IFERROR(J62/I62-1,"N/A") -> N/A | K63: =IFERROR(K62/J62-1,"N/A") -> N/A | L63: =IFERROR(L62/K62-1,"N/A") -> N/A | M63: =IFERROR(M62/L62-1,"N/A") -> N/A | N63: 0 | O63: 0 | P63: 0 | Q63: 0 | R63: 0
C64: Gross Revenue [per Surgery] (LCA) | G64: 4224 | H64: 4161 | I64: 4584 | J64: 5088 | K64: 5240 | L64: 5746 | M64: 6111 | N64: =M64*(1+N65) -> 6453.216 | O64: =N64*(1+O65) -> 6750.0639 | P64: =O64*(1+P65) -> 7215.8183 | Q64: =P64*(1+Q65) -> 7684.8465 | R64: =Q64*(1+R65) -> 8176.6767
C65: Growth (%) | G65: =IFERROR(G64/F64-1,"N/A") -> N/A | H65: =IFERROR(H64/G64-1,"N/A") -> -0.014914773 | I65: =IFERROR(I64/H64-1,"N/A") -> 0.10165826 | J65: =IFERROR(J64/I64-1,"N/A") -> 0.10994764 | K65: =IFERROR(K64/J64-1,"N/A") -> 0.029874214 | L65: =IFERROR(L64/K64-1,"N/A") -> 0.096564885 | M65: =IFERROR(M64/L64-1,"N/A") -> 0.06352245 | N65: 0.056 | O65: 0.046 | P65: 0.069 | Q65: 0.065 | R65: 0.064
C66: Revenue | G66: =G62*G64 -> 0 | H66: =H62*H64 -> 0 | I66: =I62*I64 -> 0 | J66: =J62*J64 -> 0 | K66: =K62*K64 -> 0 | L66: =L62*L64 -> 0 | M66: =M62*M64 -> 0 | N66: =N62*N64 -> 0 | ... R66: =R62*R64 -> 0
C68: Heart Test:
C69: # of Tests | G69: 2976 | H69: 2875 | I69: 3113 | J69: 3232 | K69: 3505 | L69: 3692 | M69: 3905 | N69: =M69*(1+N70) -> 4252.545 | O69: =N69*(1+O70) -> 4537.4655 | P69: =O69*(1+P70) -> 4764.3388 | Q69: =P69*(1+Q70) -> 4993.0271 | R69: =Q69*(1+R70) -> 5332.5529
C70: Growth (%) | G70: =IFERROR(G69/F69-1,"N/A") -> N/A | H70: =IFERROR(H69/G69-1,"N/A") -> -0.033938172 | I70: =IFERROR(I69/H69-1,"N/A") -> 0.082782609 | J70: =IFERROR(J69/I69-1,"N/A") -> 0.038226791 | K70: =IFERROR(K69/J69-1,"N/A") -> 0.084467822 | L70: =IFERROR(L69/K69-1,"N/A") -> 0.053352354 | M70: =IFERROR(M69/L69-1,"N/A") -> 0.057692308 | N70: 0.089 | O70: 0.067 | P70: 0.05 | Q70: 0.048 | R70: 0.068
C71: Gross Revenue [per Test] (LCA) | G71: 219 | H71: 229 | I71: 253 | J71: 271 | K71: 296 | L71: 317 | M71: 331 | N71: =M71*(1+N72) -> 345.564 | O71: =N71*(1+O72) -> 362.49664 | P71: =O71*(1+P72) -> 386.05892 | Q71: =P71*(1+Q72) -> 407.29216 | R71: =Q71*(1+R72) -> 428.47135
C72: Growth (%) | G72: =IFERROR(G71/F71-1,"N/A") -> N/A | H72: =IFERROR(H71/G71-1,"N/A") -> 0.0456621 | I72: =IFERROR(I71/H71-1,"N/A") -> 0.10480349 | J72: =IFERROR(J71/I71-1,"N/A") -> 0.071146245 | K72: =IFERROR(K71/J71-1,"N/A") -> 0.092250923 | L72: =IFERROR(L71/K71-1,"N/A") -> 0.070945946 | M72: =IFERROR(M71/L71-1,"N/A") -> 0.044164038 | N72: 0.044 | O72: 0.049 | P72: 0.065 | Q72: 0.055 | R72: 0.052
C73: Revenue | G73: =G69*G71 -> 651744 | H73: =H69*H71 -> 658375 | I73: =I69*I71 -> 787589 | J73: =J69*J71 -> 875872 | K73: =K69*K71 -> 1037480 | L73: =L69*L71 -> 1170364 | M73: =M69*M71 -> 1292555 | N73: =N69*N71 -> 1469526.5 | ... R73: =R69*R71 -> 2284846.1
C75: Emergency:
C76: # of Visits | G76: 10636 | H76: 9924 | I76: 10481 | J76: 11443 | K76: 12320 | L76: 13474 | M76: 14402 | N76: =M76*(1+N77) -> 15654.974 | O76: =N76*(1+O77) -> 16562.962 | P76: =O76*(1+P77) -> 17341.422 | Q76: =P76*(1+Q77) -> 18035.079 | R76: =Q76*(1+R77) -> 19297.534
C77: Growth (%) | G77: =IFERROR(G76/F76-1,"N/A") -> N/A | H77: =IFERROR(H76/G76-1,"N/A") -> -0.06694246 | I77: =IFERROR(I76/H76-1,"N/A") -> 0.056126562 | J77: =IFERROR(J76/I76-1,"N/A") -> 0.091785135 | K77: =IFERROR(K76/J76-1,"N/A") -> 0.076640741 | L77: =IFERROR(L76/K76-1,"N/A") -> 0.093668831 | M77: =IFERROR(M76/L76-1,"N/A") -> 0.068873386 | N77: 0.087 | O77: 0.058 | P77: 0.047 | Q77: 0.04 | R77: 0.07
C78: Gross Revenue [per Visit] (LCA) | G78: 156 | H78: 163 | I78: 172 | J78: 187 | K78: 201 | L78: 214 | M78: 234 | N78: =M78*(1+N79) -> 249.444 | O78: =N78*(1+O79) -> 262.91398 | P78: =O78*(1+P79) -> 281.31795 | Q78: =P78*(1+Q79) -> 300.16626 | R78: =Q78*(1+R79) -> 319.07673
C79: Growth (%) | G79: =IFERROR(G78/F78-1,"N/A") -> N/A | H79: =IFERROR(H78/G78-1,"N/A") -> 0.044871795 | I79: =IFERROR(I78/H78-1,"N/A") -> 0.055214724 | J79: =IFERROR(J78/I78-1,"N/A") -> 0.087209302 | K79: =IFERROR(K78/J78-1,"N/A") -> 0.07486631 | L79: =IFERROR(L78/K78-1,"N/A") -> 0.064676617 | M79: =IFERROR(M78/L78-1,"N/A") -> 0.093457944 | N79: 0.066 | O79: 0.054 | P79: 0.07 | Q79: 0.067 | R79: 0.063
C80: Revenue | G80: =G76*G78 -> 1659216 | H80: =H76*H78 -> 1617612 | I80: =I76*I78 -> 1802732 | J80: =J76*J78 -> 2139841 | K80: =K76*K78 -> 2476320 | L80: =L76*L78 -> 2883436 | M80: =M76*M78 -> 3370068 | N80: =N76*N78 -> 3905039.3 | ... R80: =R76*R78 -> 6157394.1
C82: Accommodation:
C83: # of Beds | G83: 96 | H83: 96 | I83: 96 | J83: 96 | K83: 104 | L83: 104 | M83: 104 | N83: =M83 -> 104 | O83: =N83 -> 104 | P83: =O83 -> 104 | Q83: =P83 -> 104 | R83: =Q83 -> 104
C84: Available Beds a Night | G84: =G83*360 -> 34560 | H84: =H83*360 -> 34560 | I84: =I83*360 -> 34560 | J84: =J83*360 -> 34560 | K84: =K83*360 -> 37440 | L84: =L83*360 -> 37440 | M84: =M83*360 -> 37440 | N84: =N83*360 -> 37440 | ... R84: =R83*360 -> 37440
C85: # of Occupied bed nights | G85: 23182 | H85: 19008 | I85: 20772 | J85: 22772 | K85: 22783 | L85: 23143 | M85: 23763 | N85: =N84*N86 -> 24223.68 | O85: =O84*O86 -> 24672.96 | P85: =P84*P86 -> 25122.24 | Q85: =Q84*Q86 -> 25571.52 | R85: =R84*R86 -> 26020.8
C86: Occupancy Ratio (%) | G86: =IFERROR(G85/G84,"N/A") -> 0.67077546 | H86: =IFERROR(H85/H84,"N/A") -> 0.55 | I86: =IFERROR(I85/I84,"N/A") -> 0.60104167 | J86: =IFERROR(J85/J84,"N/A") -> 0.65891204 | K86: =IFERROR(K85/K84,"N/A") -> 0.6085203 | L86: =IFERROR(L85/L84,"N/A") -> 0.61813568 | M86: =IFERROR(M85/M84,"N/A") -> 0.63469551 | N86: 0.647 | O86: 0.659 | P86: 0.671 | Q86: 0.683 | R86: 0.695
C87: Gross Revenue [per bed night] (LCA) | G87: 339 | H87: 353 | I87: 378 | J87: 406 | K87: 435 | L87: 468 | M87: 501 | N87: =M87*(1+N88) -> 528.555 | O87: =N87*(1+O88) -> 563.96818 | P87: =O87*(1+P88) -> 602.31802 | Q87: =P87*(1+Q88) -> 642.67333 | R87: =Q87*(1+R88) -> 685.08977
C88: Growth (%) | G88: =IFERROR(G87/F87-1,"N/A") -> N/A | H88: =IFERROR(H87/G87-1,"N/A") -> 0.041297935 | I88: =IFERROR(I87/H87-1,"N/A") -> 0.07082153 | J88: =IFERROR(J87/I87-1,"N/A") -> 0.074074074 | K88: =IFERROR(K87/J87-1,"N/A") -> 0.071428571 | L88: =IFERROR(L87/K87-1,"N/A") -> 0.075862069 | M88: =IFERROR(M87/L87-1,"N/A") -> 0.070512821 | N88: 0.055 | O88: 0.067 | P88: 0.068 | Q88: 0.067 | R88: 0.066
C89: Revenue | G89: =G85*G87 -> 7858698 | H89: =H85*H87 -> 6709824 | I89: =I85*I87 -> 7851816 | J89: =J85*J87 -> 9245432 | K89: =K85*K87 -> 9910605 | L89: =L85*L87 -> 10830924 | M89: =M85*M87 -> 11905263 | N89: =N85*N87 -> 12803547 | ... R89: =R85*R87 -> 17826584
C91: Radiotherapy:
C92: # of Sessions | G92: 0 | H92: 0 | I92: 0 | J92: 0 | K92: 0 | L92: 0 | M92: 0 | N92: =M92*(1+N93) -> 0 | O92: =N92*(1+O93) -> 0 | P92: =O92*(1+P93) -> 0 | Q92: =P92*(1+Q93) -> 0 | R92: =Q92*(1+R93) -> 0
C93: Growth (%) | G93: =IFERROR(G92/F92-1,"N/A") -> N/A | H93: =IFERROR(H92/G92-1,"N/A") -> N/A | I93: =IFERROR(I92/H92-1,"N/A") -> N/A | J93: =IFERROR(J92/I92-1,"N/A") -> N/A | K93: =IFERROR(K92/J92-1,"N/A") -> N/A | L93: =IFERROR(L92/K92-1,"N/A") -> N/A | M93: =IFERROR(M92/L92-1,"N/A") -> N/A | N93: 0 | O93: 0 | P93: 0 | Q93: 0 | R93: 0
C94: Gross Revenue [per Session] (LCA) | G94: 902 | H94: 904 | I94: 967 | J94: 1044 | K94: 1104 | L94: 1170 | M94: 1303 | N94: =M94*(1+N95) -> 1386.392 | O94: =N94*(1+O95) -> 1462.6436 | P94: =O94*(1+P95) -> 1528.4625 | Q94: =P94*(1+Q95) -> 1630.8695 | R94: =Q94*(1+R95) -> 1725.4599
C95: Growth (%) | G95: =IFERROR(G94/F94-1,"N/A") -> N/A | H95: =IFERROR(H94/G94-1,"N/A") -> 0.0022172949 | I95: =IFERROR(I94/H94-1,"N/A") -> 0.069690265 | J95: =IFERROR(J94/I94-1,"N/A") -> 0.079627715 | K95: =IFERROR(K94/J94-1,"N/A") -> 0.057471264 | L95: =IFERROR(L94/K94-1,"N/A") -> 0.059782609 | M95: =IFERROR(M94/L94-1,"N/A") -> 0.11367521 | N95: 0.064 | O95: 0.055 | P95: 0.045 | Q95: 0.067 | R95: 0.058
C96: Revenue | G96: =G92*G94 -> 0 | H96: =H92*H94 -> 0 | I96: =I92*I94 -> 0 | J96: =J92*J94 -> 0 | K96: =K92*K94 -> 0 | L96: =L92*L94 -> 0 | M96: =M92*M94 -> 0 | N96: =N92*N94 -> 0 | ... R96: =R92*R94 -> 0
C98: Nursing Fees:
C99: # of Visits | G99: 5452 | H99: 5154 | I99: 5686 | J99: 6351 | K99: 7041 | L99: 7473 | M99: 7836 | N99: =M99*(1+N100) -> 8313.996 | O99: =N99*(1+O100) -> 8970.8017 | P99: =O99*(1+P100) -> 9446.2542 | Q99: =P99*(1+Q100) -> 10277.525 | R99: =Q99*(1+R100) -> 10976.396
C100: Growth (%) | G100: =IFERROR(G99/F99-1,"N/A") -> N/A | H100: =IFERROR(H99/G99-1,"N/A") -> -0.054658841 | I100: =IFERROR(I99/H99-1,"N/A") -> 0.1032208 | J100: =IFERROR(J99/I99-1,"N/A") -> 0.11695392 | K100: =IFERROR(K99/J99-1,"N/A") -> 0.10864431 | L100: =IFERROR(L99/K99-1,"N/A") -> 0.061354921 | M100: =IFERROR(M99/L99-1,"N/A") -> 0.04857487 | N100: 0.061 | O100: 0.079 | P100: 0.053 | Q100: 0.088 | R100: 0.068
C101: Gross Revenue [per Visit] (LCA) | G101: 77 | H101: 78 | I101: 85 | J101: 93 | K101: 104 | L101: 111 | M101: 119 | N101: =M101*(1+N102) -> 125.783 | O101: =N101*(1+O102) -> 134.08468 | P101: =O101*(1+P102) -> 139.85032 | Q101: =P101*(1+Q102) -> 147.68194 | R101: =Q101*(1+R102) -> 154.91835
C102: Growth (%) | G102: =IFERROR(G101/F101-1,"N/A") -> N/A | H102: =IFERROR(H101/G101-1,"N/A") -> 0.012987013 | I102: =IFERROR(I101/H101-1,"N/A") -> 0.08974359 | J102: =IFERROR(J101/I101-1,"N/A") -> 0.094117647 | K102: =IFERROR(K101/J101-1,"N/A") -> 0.11827957 | L102: =IFERROR(L101/K101-1,"N/A") -> 0.067307692 | M102: =IFERROR(M101/L101-1,"N/A") -> 0.072072072 | N102: 0.057 | O102: 0.066 | P102: 0.043 | Q102: 0.056 | R102: 0.049
C103: Revenue | G103: =G99*G101 -> 419804 | H103: =H99*H101 -> 402012 | I103: =I99*I101 -> 483310 | J103: =J99*J101 -> 590643 | K103: =K99*K101 -> 732264 | L103: =L99*L101 -> 829503 | M103: =M99*M101 -> 932484 | N103: =N99*N101 -> 1045759.4 | ... R103: =R99*R101 -> 1700445.2
C105: Pharmacy:
C106: Gross Revenue (LCA) | G106: 1372000 | H106: 1335000 | I106: 1524000 | J106: 1693000 | K106: 1949000 | L106: 2140000 | M106: 2450000 | N106: =N108*(N17+N24+N31+N38+N45+N52+N59+N66+N73+N80+N89+N96+N103) -> 3877660.1 | O106: =O108*(O17+O24+O31+O38+O45+O52+O59+O66+O73+O80+O89+O96+O103) -> 3686421.5 | P106: =P108*(P17+P24+P31+P38+P45+P52+P59+P66+P73+P80+P89+P96+P103) -> 4504697.7 | Q106: =Q108*(Q17+Q24+Q31+Q38+Q45+Q52+Q59+Q66+Q73+Q80+Q89+Q96+Q103) -> 5256567 | R106: =R108*(R17+R24+R31+R38+R45+R52+R59+R66+R73+R80+R89+R96+R103) -> 5184388
C107: Growth (%) | G107: =IFERROR(G106/F106-1,"N/A") -> N/A | H107: =IFERROR(H106/G106-1,"N/A") -> -0.02696793 | I107: =IFERROR(I106/H106-1,"N/A") -> 0.14157303 | J107: =IFERROR(J106/I106-1,"N/A") -> 0.11089239 | K107: =IFERROR(K106/J106-1,"N/A") -> 0.15121087 | L107: =IFERROR(L106/K106-1,"N/A") -> 0.097998974 | M107: =IFERROR(M106/L106-1,"N/A") -> 0.14485981 | N107: =IFERROR(N106/M106-1,"N/A") -> 0.58271842 | ... R107: =IFERROR(R106/Q106-1,"N/A") -> -0.013731199
C108: % of Other Hospital Revenue | G108: =IFERROR(G106/(G17+G24+G31+G38+G45+G52+G59+G66+G73+G80+G89+G96+G103),"N/A") -> 0.064372449 | H108: =IFERROR(H106/(H17+H24+H31+H38+H45+H52+H59+H66+H73+H80+H89+H96+H103),"N/A") -> 0.067821378 | I108: =IFERROR(I106/(I17+I24+I31+I38+I45+I52+I59+I66+I73+I80+I89+I96+I103),"N/A") -> 0.066229742 | J108: =IFERROR(J106/(J17+J24+J31+J38+J45+J52+J59+J66+J73+J80+J89+J96+J103),"N/A") -> 0.062842721 | K108: =IFERROR(K106/(K17+K24+K31+K38+K45+K52+K59+K66+K73+K80+K89+K96+K103),"N/A") -> 0.064708104 | L108: =IFERROR(L106/(L17+L24+L31+L38+L45+L52+L59+L66+L73+L80+L89+L96+L103),"N/A") -> 0.062289971 | M108: =IFERROR(M106/(M17+M24+M31+M38+M45+M52+M59+M66+M73+M80+M89+M96+M103),"N/A") -> 0.06343056 | N108: 0.091 | O108: 0.078 | P108: 0.086 | Q108: 0.09 | R108: 0.079
C109: Revenue | G109: =G106 -> 1372000 | H109: =H106 -> 1335000 | I109: =I106 -> 1524000 | J109: =J106 -> 1693000 | K109: =K106 -> 1949000 | L109: =L106 -> 2140000 | M109: =M106 -> 2450000 | N109: =N106 -> 3877660.1 | ... R109: =R106 -> 5184388
C111: Total Hospital Revenue (LCA) | G111: =G17+G24+G31+G38+G45+G52+G59+G66+G73+G80+G89+G96+G103+G109 -> 22685466 | H111: =H17+H24+H31+H38+H45+H52+H59+H66+H73+H80+H89+H96+H103+H109 -> 21019059 | I111: =I17+I24+I31+I38+I45+I52+I59+I66+I73+I80+I89+I96+I103+I109 -> 24534810 | J111: =J17+J24+J31+J38+J45+J52+J59+J66+J73+J80+J89+J96+J103+J109 -> 28633272 | K111: =K17+K24+K31+K38+K45+K52+K59+K66+K73+K80+K89+K96+K103+K109 -> 32068875 | L111: =L17+L24+L31+L38+L45+L52+L59+L66+L73+L80+L89+L96+L103+L109 -> 36495450 | M111: =M17+M24+M31+M38+M45+M52+M59+M66+M73+M80+M89+M96+M103+M109 -> 41074915 | N111: =N17+N24+N31+N38+N45+N52+N59+N66+N73+N80+N89+N96+N103+N109 -> 46489310 | ... R111: =R17+R24+R31+R38+R45+R52+R59+R66+R73+R80+R89+R96+R103+R109 -> 70809553
C113: B | D113: Cost Assumptions
C114: Expenses:
C115: COGS – % of Sales (%) | G115: =IFERROR(G116/G111,"N/A") -> 0.30869985 | H115: =IFERROR(H116/H111,"N/A") -> 0.28593097 | I115: =IFERROR(I116/I111,"N/A") -> 0.28881414 | J115: =IFERROR(J116/J111,"N/A") -> 0.30785863 | K115: =IFERROR(K116/K111,"N/A") -> 0.29433524 | L115: =IFERROR(L116/L111,"N/A") -> 0.30296927 | M115: =IFERROR(M116/M111,"N/A") -> 0.29261168 | N115: 0.2934 | O115: 0.2929 | P115: 0.2933 | Q115: 0.2937 | R115: 0.2897
C116: COGS (LCA) | G116: 7003000 | H116: 6010000 | I116: 7086000 | J116: 8815000 | K116: 9439000 | L116: 11057000 | M116: 12019000 | N116: =N115*N111 -> 13639963 | O116: =O115*O111 -> 14922738 | P116: =P115*P111 -> 16684342 | Q116: =Q115*Q111 -> 18697784 | R116: =R115*R111 -> 20513527
C117: Payroll – % of Sales (%) | G117: =IFERROR(G118/G111,"N/A") -> 0.33109304 | H117: =IFERROR(H118/H111,"N/A") -> 0.34801748 | I117: =IFERROR(I118/I111,"N/A") -> 0.32504837 | J117: =IFERROR(J118/J111,"N/A") -> 0.33523937 | K117: =IFERROR(K118/K111,"N/A") -> 0.32607942 | L117: =IFERROR(L118/L111,"N/A") -> 0.34831739 | M117: =IFERROR(M118/M111,"N/A") -> 0.32428552 | N117: 0.3281 | O117: 0.3346 | P117: 0.3313 | Q117: 0.323 | R117: 0.3323
C118: Payroll (LCA) | G118: 7511000 | H118: 7315000 | I118: 7975000 | J118: 9599000 | K118: 10457000 | L118: 12712000 | M118: 13320000 | N118: =N117*N111 -> 15253143 | O118: =O117*O111 -> 17047280 | P118: =P117*P111 -> 18845969 | Q118: =Q117*Q111 -> 20563106 | R118: =R117*R111 -> 23530014
C119: OPEX – % of Sales (%) | G119: =IFERROR(G120/G111,"N/A") -> 0.14119172 | H119: =IFERROR(H120/H111,"N/A") -> 0.14125276 | I119: =IFERROR(I120/I111,"N/A") -> 0.1411464 | J119: =IFERROR(J120/J111,"N/A") -> 0.13714814 | K119: =IFERROR(K120/K111,"N/A") -> 0.13966814 | L119: =IFERROR(L120/L111,"N/A") -> 0.13996265 | M119: =IFERROR(M120/M111,"N/A") -> 0.14154625 | N119: 0.1418 | O119: 0.1431 | P119: 0.1406 | Q119: 0.1398 | R119: 0.1385
...

Sheet 5. AHG Diagnostics
C3: =Cover!$C$3 -> Project Dunecrest | D3: Confidential
C4: AHG Diagnostics – Simplified Build (lab & imaging)
C6: Fiscal Year Ending | G6: 43830 | H6: 44196 | I6: 44561 | J6: 44926 | K6: =EOMONTH(J6,12) -> 45291 | L6: =EOMONTH(K6,12) -> 45657 | M6: =EOMONTH(L6,12) -> 46022 | N6: =EOMONTH(M6,12) -> 46387 | O6: =EOMONTH(N6,12) -> 46752 | P6: =EOMONTH(O6,12) -> 47118 | Q6: =EOMONTH(P6,12) -> 47483 | R6: =EOMONTH(Q6,12) -> 47848
C7: Fiscal Year | G7: =YEAR(G6) -> 2019 | H7: =YEAR(H6) -> 2020 | I7: =YEAR(I6) -> 2021 | J7: =YEAR(J6) -> 2022 | K7: =YEAR(K6) -> 2023 | L7: =YEAR(L6) -> 2024 | M7: =YEAR(M6) -> 2025 | N7: =YEAR(N6) -> 2026 | ... R7: =YEAR(R6) -> 2030
C8: Actual / Estimate | G8: =IF(G6<=Control!$E$11,"A","E") -> A | H8: =IF(H6<=Control!$E$11,"A","E") -> A | I8: =IF(I6<=Control!$E$11,"A","E") -> A | J8: =IF(J6<=Control!$E$11,"A","E") -> A | K8: =IF(K6<=Control!$E$11,"A","E") -> A | L8: =IF(L6<=Control!$E$11,"A","E") -> A | M8: =IF(M6<=Control!$E$11,"A","E") -> A | N8: =IF(N6<=Control!$E$11,"A","E") -> E | ... R8: =IF(R6<=Control!$E$11,"A","E") -> E
C10: Supporting Data
C11: A | D11: Revenue & Cost Build | E11: ="("&Control!$E$16&" in Actual)" -> (LCA in Actual)
C12: Revenue (LCA) | G12: 4607000 | H12: 4570000 | I12: 5078000 | J12: 5705000 | K12: 6297000 | L12: 7180000 | M12: 8024000 | N12: =M12*(1+N13) -> 9059096 | O12: =N12*(1+O13) -> 10191483 | P12: =O12*(1+P13) -> 11465418 | Q12: =P12*(1+Q13) -> 12623426 | R12: =Q12*(1+R13) -> 14213977
C13: Growth (%) | G13: =IFERROR(G12/F12-1,"N/A") -> N/A | H13: =IFERROR(H12/G12-1,"N/A") -> -0.0080312568 | I13: =IFERROR(I12/H12-1,"N/A") -> 0.11115974 | J13: =IFERROR(J12/I12-1,"N/A") -> 0.12347381 | K13: =IFERROR(K12/J12-1,"N/A") -> 0.10376862 | L13: =IFERROR(L12/K12-1,"N/A") -> 0.1402255 | M13: =IFERROR(M12/L12-1,"N/A") -> 0.11754875 | N13: 0.129 | O13: 0.125 | P13: 0.125 | Q13: 0.101 | R13: 0.126
C15: Expenses:
C16: COGS – % of Sales (%) | G16: =IFERROR(G17/G12,"N/A") -> 0.36305622 | H16: =IFERROR(H17/H12,"N/A") -> 0.33715536 | I16: =IFERROR(I17/I12,"N/A") -> 0.3551792 | J16: =IFERROR(J17/J12,"N/A") -> 0.36394391 | K16: =IFERROR(K17/K12,"N/A") -> 0.3476735 | L16: =IFERROR(L17/L12,"N/A") -> 0.37551532 | M16: =IFERROR(M17/M12,"N/A") -> 0.37452642 | N16: 0.3655 | O16: 0.3616 | P16: 0.3501 | Q16: 0.3537 | R16: 0.3504
C17: COGS (LCA) | G17: 1672600 | H17: 1540800 | I17: 1803600 | J17: 2076300 | K17: 2189300 | L17: 2696200 | M17: 3005200 | N17: =N16*N12 -> 3311099.6 | O17: =O16*O12 -> 3685240.3 | P17: =P16*P12 -> 4014043 | Q17: =Q16*Q12 -> 4464905.6 | R17: =R16*R12 -> 4980577.6
C18: Payroll – % of Sales (%) | G18: =IFERROR(G19/G12,"N/A") -> 0.22821793 | H18: =IFERROR(H19/H12,"N/A") -> 0.23098468 | I18: =IFERROR(I19/I12,"N/A") -> 0.24202442 | J18: =IFERROR(J19/J12,"N/A") -> 0.23162138 | K18: =IFERROR(K19/K12,"N/A") -> 0.25202477 | L18: =IFERROR(L19/L12,"N/A") -> 0.24151811 | M18: =IFERROR(M19/M12,"N/A") -> 0.25021186 | N18: 0.237 | O18: 0.2358 | P18: 0.2422 | Q18: 0.2363 | R18: 0.2339
C19: Payroll (LCA) | G19: 1051400 | H19: 1055600 | I19: 1229000 | J19: 1321400 | K19: 1587000 | L19: 1734100 | M19: 2007700 | N19: =N18*N12 -> 2147005.8 | O19: =O18*O12 -> 2403151.7 | P19: =P18*P12 -> 2776924.3 | Q19: =Q18*Q12 -> 2982915.5 | R19: =R18*R12 -> 3324649.3
C20: OPEX – % of Sales (%) | G20: =IFERROR(G21/G12,"N/A") -> 0.10692425 | H20: =IFERROR(H21/H12,"N/A") -> 0.11207877 | I20: =IFERROR(I21/I12,"N/A") -> 0.10748326 | J20: =IFERROR(J21/J12,"N/A") -> 0.11905346 | K20: =IFERROR(K21/K12,"N/A") -> 0.113165 | L20: =IFERROR(L21/L12,"N/A") -> 0.10857939 | M20: =IFERROR(M21/M12,"N/A") -> 0.10595713 | N20: 0.1071 | O20: 0.1074 | P20: 0.1112 | Q20: 0.1105 | R20: 0.1076
C21: OPEX (LCA) | G21: 492600 | H21: 512200 | I21: 545800 | J21: 679200 | K21: 712600 | L21: 779600 | M21: 850200 | N21: =N20*N12 -> 970229.18 | O21: =O20*O12 -> 1094565.3 | P21: =P20*P12 -> 1274954.5 | Q21: =Q20*Q12 -> 1394888.5 | R21: =R20*R12 -> 1529424
C22: Provision – % of Sales (%) | G22: =IFERROR(G23/G12,"N/A") -> 0.0082266117 | H22: =IFERROR(H23/H12,"N/A") -> 0.0084901532 | I22: =IFERROR(I23/I12,"N/A") -> 0.0076211107 | J22: =IFERROR(J23/J12,"N/A") -> 0.0083260298 | K22: =IFERROR(K23/K12,"N/A") -> 0.0077338415 | L22: =IFERROR(L23/L12,"N/A") -> 0.0080640669 | M22: =IFERROR(M23/M12,"N/A") -> 0.0077642074 | N22: 0.0081 | O22: 0.0079 | P22: 0.0078 | Q22: 0.0081 | R22: 0.0078
C23: Provision (LCA) | G23: 37900 | H23: 38800 | I23: 38700 | J23: 47500 | K23: 48700 | L23: 57900 | M23: 62300 | N23: =N22*N12 -> 73378.678 | O23: =O22*O12 -> 80512.716 | P23: =P22*P12 -> 89430.263 | Q23: =Q22*Q12 -> 102249.75 | R23: =R22*R12 -> 110869.02
C24: Depreciation & Amortization – % of Sales (%) | G24: =IFERROR(G25/G12,"N/A") -> 0.052637291 | H24: =IFERROR(H25/H12,"N/A") -> 0.057833698 | I24: =IFERROR(I25/I12,"N/A") -> 0.054430878 | J24: =IFERROR(J25/J12,"N/A") -> 0.052988606 | K24: =IFERROR(K25/K12,"N/A") -> 0.051993013 | L24: =IFERROR(L25/L12,"N/A") -> 0.056114206 | M24: =IFERROR(M25/M12,"N/A") -> 0.055358923 | N24: 0.0541 | O24: 0.056 | P24: 0.0546 | Q24: 0.0541 | R24: 0.0546
C25: Depreciation & Amortization (LCA) | G25: 242500 | H25: 264300 | I25: 276400 | J25: 302300 | K25: 327400 | L25: 402900 | M25: 444200 | N25: =N24*N12 -> 490097.09 | O25: =O24*O12 -> 570723.05 | P25: =P24*P12 -> 626011.84 | Q25: =Q24*Q12 -> 682927.33 | R25: =R24*R12 -> 776083.16
C26: Goodwill, Trademark & PPA Amortization – % of Sales (%) | G26: =IFERROR(G27/G12,"N/A") -> 0 | H26: =IFERROR(H27/H12,"N/A") -> 0 | I26: =IFERROR(I27/I12,"N/A") -> 0 | J26: =IFERROR(J27/J12,"N/A") -> 0 | K26: =IFERROR(K27/K12,"N/A") -> 0 | L26: =IFERROR(L27/L12,"N/A") -> 0 | M26: =IFERROR(M27/M12,"N/A") -> 0 | N26: 0 | O26: 0 | P26: 0 | Q26: 0 | R26: 0
C27: Goodwill, Trademark & PPA Amortization (LCA) | G27: 0 | H27: 0 | I27: 0 | J27: 0 | K27: 0 | L27: 0 | M27: 0 | N27: =N26*N12 -> 0 | O27: =O26*O12 -> 0 | P27: =P26*P12 -> 0 | Q27: =Q26*Q12 -> 0 | R27: =R26*R12 -> 0
C29: Financial Statements
C30: B | D30: Income Statement
E31: ="("&Control!$E$18&" in Actual)" -> (USD in Actual)
C32: Revenue | G32: =G12*Control!$E$17 -> 1082645 | H32: =H12*Control!$E$17 -> 1073950 | I32: =I12*Control!$E$17 -> 1193330 | J32: =J12*Control!$E$17 -> 1340675 | K32: =K12*Control!$E$17 -> 1479795 | L32: =L12*Control!$E$17 -> 1687300 | M32: =M12*Control!$E$17 -> 1885640 | N32: =N12*Control!$E$17 -> 2128887.6 | ... R32: =R12*Control!$E$17 -> 3340284.7
C33: Growth (%) | G33: =IFERROR(G32/F32-1,"N/A") -> N/A | H33: =IFERROR(H32/G32-1,"N/A") -> -0.0080312568 | I33: =IFERROR(I32/H32-1,"N/A") -> 0.11115974 | J33: =IFERROR(J32/I32-1,"N/A") -> 0.12347381 | K33: =IFERROR(K32/J32-1,"N/A") -> 0.10376862 | L33: =IFERROR(L32/K32-1,"N/A") -> 0.1402255 | M33: =IFERROR(M32/L32-1,"N/A") -> 0.11754875 | N33: =IFERROR(N32/M32-1,"N/A") -> 0.129 | ... R33: =IFERROR(R32/Q32-1,"N/A") -> 0.126
C34: (-) COGS | G34: =-G17*Control!$E$17 -> -393061 | H34: =-H17*Control!$E$17 -> -362088 | I34: =-I17*Control!$E$17 -> -423846 | J34: =-J17*Control!$E$17 -> -487930.5 | K34: =-K17*Control!$E$17 -> -514485.5 | L34: =-L17*Control!$E$17 -> -633607 | M34: =-M17*Control!$E$17 -> -706222 | N34: =-N17*Control!$E$17 -> -778108.4 | ... R34: =-R17*Control!$E$17 -> -1170435.7
C35: Gross Margin | G35: =G32+G34 -> 689584 | H35: =H32+H34 -> 711862 | I35: =I32+I34 -> 769484 | J35: =J32+J34 -> 852744.5 | K35: =K32+K34 -> 965309.5 | L35: =L32+L34 -> 1053693 | M35: =M32+M34 -> 1179418 | N35: =N32+N34 -> 1350779.2 | ... R35: =R32+R34 -> 2169848.9
C36: Margin (%) | G36: =IFERROR(G35/G$32,"N/A") -> 0.63694378 | H36: =IFERROR(H35/H$32,"N/A") -> 0.66284464 | I36: =IFERROR(I35/I$32,"N/A") -> 0.6448208 | J36: =IFERROR(J35/J$32,"N/A") -> 0.63605609 | K36: =IFERROR(K35/K$32,"N/A") -> 0.6523265 | L36: =IFERROR(L35/L$32,"N/A") -> 0.62448468 | M36: =IFERROR(M35/M$32,"N/A") -> 0.62547358 | N36: =IFERROR(N35/N$32,"N/A") -> 0.6345 | ... R36: =IFERROR(R35/R$32,"N/A") -> 0.6496
C37: (-) Payroll | G37: =-G19*Control!$E$17 -> -247079 | H37: =-H19*Control!$E$17 -> -248066 | I37: =-I19*Control!$E$17 -> -288815 | J37: =-J19*Control!$E$17 -> -310529 | K37: =-K19*Control!$E$17 -> -372945 | L37: =-L19*Control!$E$17 -> -407513.5 | M37: =-M19*Control!$E$17 -> -471809.5 | N37: =-N19*Control!$E$17 -> -504546.35 | ... R37: =-R19*Control!$E$17 -> -781292.58
C38: (-) OPEX | G38: =-G21*Control!$E$17 -> -115761 | H38: =-H21*Control!$E$17 -> -120367 | I38: =-I21*Control!$E$17 -> -128263 | J38: =-J21*Control!$E$17 -> -159612 | K38: =-K21*Control!$E$17 -> -167461 | L38: =-L21*Control!$E$17 -> -183206 | M38: =-M21*Control!$E$17 -> -199797 | N38: =-N21*Control!$E$17 -> -228003.86 | ... R38: =-R21*Control!$E$17 -> -359414.63
C39: (-) Provision | G39: =-G23*Control!$E$17 -> -8906.5 | H39: =-H23*Control!$E$17 -> -9118 | I39: =-I23*Control!$E$17 -> -9094.5 | J39: =-J23*Control!$E$17 -> -11162.5 | K39: =-K23*Control!$E$17 -> -11444.5 | L39: =-L23*Control!$E$17 -> -13606.5 | M39: =-M23*Control!$E$17 -> -14640.5 | N39: =-N23*Control!$E$17 -> -17243.989 | ... R39: =-R23*Control!$E$17 -> -26054.22
C40: EBITDA | G40: =G35+G37+G38+G39 -> 317837.5 | H40: =H35+H37+H38+H39 -> 334311 | I40: =I35+I37+I38+I39 -> 343311.5 | J40: =J35+J37+J38+J39 -> 371441 | K40: =K35+K37+K38+K39 -> 413459 | L40: =L35+L37+L38+L39 -> 449367 | M40: =M35+M37+M38+M39 -> 493171 | N40: =N35+N37+N38+N39 -> 600984.96 | ... R40: =R35+R37+R38+R39 -> 1003087.5
C41: Margin (%) | G41: =IFERROR(G40/G$32,"N/A") -> 0.29357499 | H41: =IFERROR(H40/H$32,"N/A") -> 0.31129103 | I41: =IFERROR(I40/I$32,"N/A") -> 0.287692 | J41: =IFERROR(J40/J$32,"N/A") -> 0.27705521 | K41: =IFERROR(K40/K$32,"N/A") -> 0.27940289 | L41: =IFERROR(L40/L$32,"N/A") -> 0.26632312 | M41: =IFERROR(M40/M$32,"N/A") -> 0.26154038 | N41: =IFERROR(N40/N$32,"N/A") -> 0.2823 | ... R41: =IFERROR(R40/R$32,"N/A") -> 0.3003
C42: (-) D&A | G42: =-G25*Control!$E$17 -> -56987.5 | H42: =-H25*Control!$E$17 -> -62110.5 | I42: =-I25*Control!$E$17 -> -64954 | J42: =-J25*Control!$E$17 -> -71040.5 | K42: =-K25*Control!$E$17 -> -76939 | L42: =-L25*Control!$E$17 -> -94681.5 | M42: =-M25*Control!$E$17 -> -104387 | N42: =-N25*Control!$E$17 -> -115172.82 | ... R42: =-R25*Control!$E$17 -> -182379.54
C43: (-) Goodwill, Trademark & PPA Amortization | G43: =-G27*Control!$E$17 -> 0 | H43: =-H27*Control!$E$17 -> 0 | I43: =-I27*Control!$E$17 -> 0 | J43: =-J27*Control!$E$17 -> 0 | K43: =-K27*Control!$E$17 -> 0 | L43: =-L27*Control!$E$17 -> 0 | M43: =-M27*Control!$E$17 -> 0 | N43: =-N27*Control!$E$17 -> 0 | ... R43: =-R27*Control!$E$17 -> 0
C44: EBIT | G44: =G40+G42+G43 -> 260850 | H44: =H40+H42+H43 -> 272200.5 | I44: =I40+I42+I43 -> 278357.5 | J44: =J40+J42+J43 -> 300400.5 | K44: =K40+K42+K43 -> 336520 | L44: =L40+L42+L43 -> 354685.5 | M44: =M40+M42+M43 -> 388784 | N44: =N40+N42+N43 -> 485812.14 | ... R44: =R40+R42+R43 -> 820707.94
C45: Margin (%) | G45: =IFERROR(G44/G$32,"N/A") -> 0.2409377 | H45: =IFERROR(H44/H$32,"N/A") -> 0.25345733 | I45: =IFERROR(I44/I$32,"N/A") -> 0.23326113 | J45: =IFERROR(J44/J$32,"N/A") -> 0.22406661 | K45: =IFERROR(K44/K$32,"N/A") -> 0.22740988 | L45: =IFERROR(L44/L$32,"N/A") -> 0.21020891 | M45: =IFERROR(M44/M$32,"N/A") -> 0.20618146 | N45: =IFERROR(N44/N$32,"N/A") -> 0.2282 | ... R45: =IFERROR(R44/R$32,"N/A") -> 0.2457

Sheet 6. AHG (Combined Entity)
C3: =Cover!$C$3 -> Project Dunecrest | D3: Confidential
C4: Arvenna Health Group – Combined Entity (USD)
C6: Fiscal Year Ending | G6: 43830 | H6: 44196 | I6: 44561 | J6: 44926 | K6: =EOMONTH(J6,12) -> 45291 | L6: =EOMONTH(K6,12) -> 45657 | M6: =EOMONTH(L6,12) -> 46022 | N6: =EOMONTH(M6,12) -> 46387 | O6: =EOMONTH(N6,12) -> 46752 | P6: =EOMONTH(O6,12) -> 47118 | Q6: =EOMONTH(P6,12) -> 47483 | R6: =EOMONTH(Q6,12) -> 47848
C7: Fiscal Year | G7: =YEAR(G6) -> 2019 | H7: =YEAR(H6) -> 2020 | I7: =YEAR(I6) -> 2021 | J7: =YEAR(J6) -> 2022 | K7: =YEAR(K6) -> 2023 | L7: =YEAR(L6) -> 2024 | M7: =YEAR(M6) -> 2025 | N7: =YEAR(N6) -> 2026 | ... R7: =YEAR(R6) -> 2030
C8: Actual / Estimate | G8: =IF(G6<=Control!$E$11,"A","E") -> A | H8: =IF(H6<=Control!$E$11,"A","E") -> A | I8: =IF(I6<=Control!$E$11,"A","E") -> A | J8: =IF(J6<=Control!$E$11,"A","E") -> A | K8: =IF(K6<=Control!$E$11,"A","E") -> A | L8: =IF(L6<=Control!$E$11,"A","E") -> A | M8: =IF(M6<=Control!$E$11,"A","E") -> A | N8: =IF(N6<=Control!$E$11,"A","E") -> E | ... R8: =IF(R6<=Control!$E$11,"A","E") -> E
C10: Supporting Assumptions
C11: A | D11: Supporting Assumptions | E11: ="("&Control!$E$18&" in Actual)" -> (USD in Actual)
C12: Tax Rate (%) | G12: 0.211 | H12: 0.23 | I12: 0.219 | J12: 0.234 | K12: 0.228 | L12: 0.221 | M12: 0.228 | N12: 0.225 | O12: 0.225 | P12: 0.225 | Q12: 0.225 | R12: 0.225
C13: Non-Current Assets:
C14: Goodwill – % of Gross Goodwill Amortised / Impaired (%) | G14: N/A | H14: =IFERROR(-H216/G228,"N/A") -> 0.013962364 | I14: =IFERROR(-I216/H228,"N/A") -> 0.016597192 | J14: =IFERROR(-J216/I228,"N/A") -> 0.017893026 | K14: =IFERROR(-K216/J228,"N/A") -> 0.020468365 | L14: =IFERROR(-L216/K228,"N/A") -> 0.022056027 | M14: =IFERROR(-M216/L228,"N/A") -> 0.025866906 | N14: =IFERROR(-N216/M228,"N/A") -> 0.028745314 | O14: =IFERROR(-O216/N228,"N/A") -> 0.032220595 | ... R14: =IFERROR(-R216/Q228,"N/A") -> 0.014807205
C15: Goodwill – Accumulated Provisions (memo) | G15: =G229 -> -700000 | H15: =H229 -> -940000 | I15: =I229 -> -1140000 | J15: =J229 -> -1422000 | K15: =K229 -> -1586000 | L15: =L229 -> -1853000 | M15: =M229 -> -2067000 | N15: =N229 -> -2344018.6 | ... R15: =R229 -> -3807334.3
C16: Intangible Assets – Growth (%) | G16: N/A | H16: =IFERROR(H231/G231-1,"N/A") -> 0.088867501 | I16: =IFERROR(I231/H231-1,"N/A") -> 0.016499705 | J16: =IFERROR(J231/I231-1,"N/A") -> 0.069855072 | K16: =IFERROR(K231/J231-1,"N/A") -> 0.050934706 | L16: =IFERROR(L231/K231-1,"N/A") -> 0.025006445 | M16: =IFERROR(M231/L231-1,"N/A") -> 0.048038229 | N16: 0.02 | O16: 0.02 | P16: 0.02 | Q16: 0.02 | R16: 0.02
C17: Intangible Assets – % of Gross Depreciated (%) | G17: N/A | H17: =IFERROR(-(H232-G232)/G231,"N/A") -> 0.061918511 | I17: =IFERROR(-(I232-H232)/H231,"N/A") -> 0.034472599 | J17: =IFERROR(-(J232-I232)/I231,"N/A") -> 0.062028986 | K17: =IFERROR(-(K232-J232)/J231,"N/A") -> 0.04199404 | L17: =IFERROR(-(L232-K232)/K231,"N/A") -> 0.033513792 | M17: =IFERROR(-(M232-L232)/L231,"N/A") -> 0.054074447 | N17: 0.08 | O17: 0.08 | P17: 0.08 | Q17: 0.08 | R17: 0.08
C18: Intangible Assets – Accumulated Depreciation (memo) | G18: =G232 -> -881000 | H18: =H232 -> -1074000 | I18: =I232 -> -1191000 | J18: =J232 -> -1405000 | K18: =K232 -> -1560000 | L18: =L232 -> -1690000 | M18: =M232 -> -1905000 | N18: =N232 -> -2238360 | ... R18: =R232 -> -3639818.8
C19: Tangible Assets – Growth (%) (implied) | G19: N/A | H19: =IFERROR(H234/G234-1,"N/A") -> 0.061980713 | I19: =IFERROR(I234/H234-1,"N/A") -> 0.080443476 | J19: =IFERROR(J234/I234-1,"N/A") -> 0.046603456 | K19: =IFERROR(K234/J234-1,"N/A") -> 0.042896172 | L19: =IFERROR(L234/K234-1,"N/A") -> 0.021512815 | M19: =IFERROR(M234/L234-1,"N/A") -> 0.064578083 | N19: =IFERROR(N234/M234-1,"N/A") -> 0.040281964 | O19: =IFERROR(O234/N234-1,"N/A") -> 0.04362799 | ... R19: =IFERROR(R234/Q234-1,"N/A") -> 0.051031722
C20: Tangible Assets – % of Gross Depreciated (%) (implied) | G20: N/A | H20: =IFERROR(-(H235-G235)/G234,"N/A") -> 0.048530728 | I20: =IFERROR(-(I235-H235)/H234,"N/A") -> 0.03747342 | J20: =IFERROR(-(J235-I235)/I234,"N/A") -> 0.014828935 | K20: =IFERROR(-(K235-J235)/J234,"N/A") -> 0.043026268 | L20: =IFERROR(-(L235-K235)/K234,"N/A") -> 0.036561579 | M20: =IFERROR(-(M235-L235)/L234,"N/A") -> 0.0043740355 | N20: =IFERROR(-(N235-M235)/M234,"N/A") -> 0.026947623 | O20: =IFERROR(-(O235-N235)/N234,"N/A") -> 0.030937955 | ... R20: =IFERROR(-(R235-Q235)/Q234,"N/A") -> 0.039640447
C21: Tangible Assets – Accumulated Depreciation (memo) | G21: =G235 -> -25292000 | H21: =H235 -> -28709000 | I21: =I235 -> -31511000 | J21: =J235 -> -32709000 | K21: =K235 -> -36347000 | L21: =L235 -> -39571000 | M21: =M235 -> -39965000 | N21: =N235 -> -42549115 | ... R21: =R235 -> -57721419
C22: Net Financial Assets (% of Sales) | G22: =IFERROR(G237/G115,"N/A") -> 0.036068553 | H22: =IFERROR(H237/H115,"N/A") -> 0.037518212 | I22: =IFERROR(I237/I115,"N/A") -> 0.03638982 | J22: =IFERROR(J237/J115,"N/A") -> 0.036086888 | K22: =IFERROR(K237/K115,"N/A") -> 0.037570981 | L22: =IFERROR(L237/L115,"N/A") -> 0.03572767 | M22: =IFERROR(M237/M115,"N/A") -> 0.03661866 | N22: 0.035 | O22: 0.035 | P22: 0.035 | Q22: 0.035 | R22: 0.035
C23: Yield on Net Financial Assets (%) | G23: N/A | H23: =IFERROR(H219/G237,"N/A") -> 0.037924702 | I23: =IFERROR(I219/H237,"N/A") -> 0.04573055 | J23: =IFERROR(J219/I237,"N/A") -> 0.046147404 | K23: =IFERROR(K219/J237,"N/A") -> 0.046858832 | L23: =IFERROR(L219/K237,"N/A") -> 0.041288344 | M23: =IFERROR(M219/L237,"N/A") -> 0.045638359 | N23: 0.045 | O23: 0.045 | P23: 0.045 | Q23: 0.045 | R23: 0.045
C24: Current Assets:
C25: Inventories – DIO (days of COGS) | G25: =IFERROR(G240/(G202-G207)*365,"N/A") -> 54.433349 | H25: =IFERROR(H240/(H202-H207)*365,"N/A") -> 53.732564 | I25: =IFERROR(I240/(I202-I207)*365,"N/A") -> 54.752755 | J25: =IFERROR(J240/(J202-J207)*365,"N/A") -> 51.789976 | K25: =IFERROR(K240/(K202-K207)*365,"N/A") -> 56.031307 | L25: =IFERROR(L240/(L202-L207)*365,"N/A") -> 53.96302 | M25: =IFERROR(M240/(M202-M207)*365,"N/A") -> 52.583165 | N25: 52 | O25: 51 | P25: 50 | Q25: 50 | R25: 49
C26: Inventories – % Provision | G26: =IFERROR(-G241/G240,"N/A") -> 0.05112782 | H26: =IFERROR(-H241/H240,"N/A") -> 0.050202429 | I26: =IFERROR(-I241/I240,"N/A") -> 0.051282051 | J26: =IFERROR(-J241/J240,"N/A") -> 0.050122249 | K26: =IFERROR(-K241/K240,"N/A") -> 0.048893464 | L26: =IFERROR(-L241/L240,"N/A") -> 0.049060064 | M26: =IFERROR(-M241/M240,"N/A") -> 0.049958368 | N26: 0.05 | O26: 0.05 | P26: 0.05 | Q26: 0.05 | R26: 0.05
C27: Receivables – DSO (days of Revenue) | G27: =IFERROR(G243/G202*365,"N/A") -> 66.393296 | H27: =IFERROR(H243/H202*365,"N/A") -> 66.378937 | I27: =IFERROR(I243/I202*365,"N/A") -> 65.666102 | J27: =IFERROR(J243/J202*365,"N/A") -> 67.60117 | K27: =IFERROR(K243/K202*365,"N/A") -> 67.254592 | L27: =IFERROR(L243/L202*365,"N/A") -> 66.24263 | M27: =IFERROR(M243/M202*365,"N/A") -> 67.400357 | N27: 64 | O27: 63 | P27: 62 | Q27: 61 | R27: 60
C28: Receivables – % Provision | G28: =IFERROR(-G244/G243,"N/A") -> 0.071740714 | H28: =IFERROR(-H244/H243,"N/A") -> 0.070855353 | I28: =IFERROR(-I244/I243,"N/A") -> 0.075385397 | J28: =IFERROR(-J244/J243,"N/A") -> 0.072292627 | K28: =IFERROR(-K244/K243,"N/A") -> 0.069176883 | L28: =IFERROR(-L244/L243,"N/A") -> 0.072671443 | M28: =IFERROR(-M244/M243,"N/A") -> 0.072343781 | N28: 0.072 | O28: 0.072 | P28: 0.072 | Q28: 0.072 | R28: 0.072
C29: Other Current Assets (% of Sales) | G29: =IFERROR(G246/G202,"N/A") -> 0.042229022 | H29: =IFERROR(H246/H202,"N/A") -> 0.041896523 | I29: =IFERROR(I246/I202,"N/A") -> 0.041388087 | J29: =IFERROR(J246/J202,"N/A") -> 0.04067443 | K29: =IFERROR(K246/K202,"N/A") -> 0.040452192 | L29: =IFERROR(L246/L202,"N/A") -> 0.041465563 | M29: =IFERROR(M246/M202,"N/A") -> 0.040859291 | N29: 0.04 | O29: 0.04 | P29: 0.04 | Q29: 0.04 | R29: 0.04
C30: Other Current Assets – % Provision | G30: =IFERROR(-G247/G246,"N/A") -> 0.034509804 | H30: =IFERROR(-H247/H246,"N/A") -> 0.035683942 | I30: =IFERROR(-I247/I246,"N/A") -> 0.03460972 | J30: =IFERROR(-J247/J246,"N/A") -> 0.036065574 | K30: =IFERROR(-K247/K246,"N/A") -> 0.035897436 | L30: =IFERROR(-L247/L246,"N/A") -> 0.035340966 | M30: =IFERROR(-M247/M246,"N/A") -> 0.03518931 | N30: 0.035 | O30: 0.035 | P30: 0.035 | Q30: 0.035 | R30: 0.035
C31: Current Liabilities:
C32: Accounts Payable – DPO (days of COGS) | G32: =IFERROR(G259/(G202-G207)*365,"N/A") -> 95.851808 | H32: =IFERROR(H259/(H202-H207)*365,"N/A") -> 92.976915 | I32: =IFERROR(I259/(I202-I207)*365,"N/A") -> 97.439414 | J32: =IFERROR(J259/(J202-J207)*365,"N/A") -> 88.068284 | K32: =IFERROR(K259/(K202-K207)*365,"N/A") -> 96.317326 | L32: =IFERROR(L259/(L202-L207)*365,"N/A") -> 92.660022 | M32: =IFERROR(M259/(M202-M207)*365,"N/A") -> 93.695232 | N32: 88 | O32: 86 | P32: 85 | Q32: 85 | R32: 84
C33: Other Current Liabilities (% of Sales) | G33: =IFERROR(G260/G202,"N/A") -> 0.050376739 | H33: =IFERROR(H260/H202,"N/A") -> 0.051222682 | I33: =IFERROR(I260/I202,"N/A") -> 0.050500781 | J33: =IFERROR(J260/J202,"N/A") -> 0.051769882 | K33: =IFERROR(K260/K202,"N/A") -> 0.052484126 | L33: =IFERROR(L260/L202,"N/A") -> 0.051599755 | M33: =IFERROR(M260/M202,"N/A") -> 0.051105963 | N33: 0.05 | O33: 0.05 | P33: 0.05 | Q33: 0.05 | R33: 0.05
C34: Short Term Financial Liabilities – Mandatory Paydown (%) | G34: N/A | H34: =IFERROR(1-H261/G261,"N/A") -> -0.0019712757 | I34: =IFERROR(1-I261/H261,"N/A") -> 0.012928612 | J34: =IFERROR(1-J261/I261,"N/A") -> -0.1893508 | K34: =IFERROR(1-K261/J261,"N/A") -> -0.027052909 | L34: =IFERROR(1-L261/K261,"N/A") -> -0.00093240093 | M34: =IFERROR(1-M261/L261,"N/A") -> 0.096180717 | N34: 0.25 | O34: 0.25 | P34: 0.25 | Q34: 0.25 | R34: 0.25
C35: Short Term Financial Liabilities – Aggregate Interest Rate (%) | G35: N/A | H35: =IFERROR(-H218/G303,"N/A") -> 0.093945652 | I35: =IFERROR(-I218/H303,"N/A") -> 0.094078839 | J35: =IFERROR(-J218/I303,"N/A") -> 0.093114532 | K35: =IFERROR(-K218/J303,"N/A") -> 0.095012927 | L35: =IFERROR(-L218/K303,"N/A") -> 0.09294392 | M35: =IFERROR(-M218/L303,"N/A") -> 0.091011686 | N35: 0.105 | O35: 0.105 | P35: 0.105 | Q35: 0.105 | R35: 0.105
C36: Non-Current Liabilities:
C37: Non-Current Loan – Mandatory Paydown (% Previous Year) | G37: N/A | H37: =IFERROR(1-H255/G255,"N/A") -> -0.011573984 | I37: =IFERROR(1-I255/H255,"N/A") -> 0.052353802 | J37: =IFERROR(1-J255/I255,"N/A") -> 0.028984918 | K37: =IFERROR(1-K255/J255,"N/A") -> 0.024198275 | L37: =IFERROR(1-L255/K255,"N/A") -> 0.039557234 | M37: =IFERROR(1-M255/L255,"N/A") -> 0.041231127 | N37: 0.1 | O37: 0.1 | P37: 0.1 | Q37: 0.1 | R37: 0.1
C38: Non-Current Loan – Aggregate Interest Rate (%) | G38: N/A | H38: =IFERROR(-H218/G303,"N/A") -> 0.093945652 | I38: =IFERROR(-I218/H303,"N/A") -> 0.094078839 | J38: =IFERROR(-J218/I303,"N/A") -> 0.093114532 | K38: =IFERROR(-K218/J303,"N/A") -> 0.095012927 | L38: =IFERROR(-L218/K303,"N/A") -> 0.09294392 | M38: =IFERROR(-M218/L303,"N/A") -> 0.091011686 | N38: 0.092 | O38: 0.092 | P38: 0.092 | Q38: 0.092 | R38: 0.092
C39: Other Long Term Liabilities (% Growth) | G39: N/A | H39: =IFERROR(H256/G256-1,"N/A") -> -0.074003795 | I39: =IFERROR(I256/H256-1,"N/A") -> 0.18852459 | J39: =IFERROR(J256/I256-1,"N/A") -> 0.15086207 | K39: =IFERROR(K256/J256-1,"N/A") -> 0.16629213 | L39: =IFERROR(L256/K256-1,"N/A") -> 0.094412331 | M39: =IFERROR(M256/L256-1,"N/A") -> 0.094483568 | N39: 0.03 | O39: 0.03 | P39: 0.03 | Q39: 0.03 | R39: 0.03
C40: Organic CAPEX:
C41: CAPEX (USD) | G41: 2105000 | H41: 1963000 | I41: 1868000 | J41: 2726000 | K41: 2829000 | L41: 3475000 | M41: 3106000 | N41: =N42*N115 -> 3862798.7 | O41: =O42*O115 -> 4139030.7 | P41: =P42*P115 -> 4428547.1 | Q41: =Q42*Q115 -> 4672215 | R41: =R42*R115 -> 5193606.2
C42: CAPEX (% of Sales) | G42: =IFERROR(G41/G115,"N/A") -> 0.069719287 | H42: =IFERROR(H41/H115,"N/A") -> 0.069875 | I42: =IFERROR(I41/I115,"N/A") -> 0.056931478 | J42: =IFERROR(J41/J115,"N/A") -> 0.072707211 | K42: =IFERROR(K41/K115,"N/A") -> 0.06520755 | L42: =IFERROR(L41/L115,"N/A") -> 0.071723659 | M42: =IFERROR(M41/M115,"N/A") -> 0.056529602 | N42: 0.062 | O42: 0.06 | P42: 0.058 | Q42: 0.055 | R42: 0.055
C43: Minimum Cash Sweep:
C44: Minimum Cash (% of Revenue) | G44: =IFERROR(G250/G202,"N/A") -> 0.049482477 | H44: =IFERROR(H250/H202,"N/A") -> 0.048802153 | I44: =IFERROR(I250/I202,"N/A") -> 0.045685378 | J44: =IFERROR(J250/J202,"N/A") -> 0.037127087 | K44: =IFERROR(K250/K202,"N/A") -> 0.05435115 | L44: =IFERROR(L250/L202,"N/A") -> 0.033292162 | M44: =IFERROR(M250/M202,"N/A") -> 0.04788454 | N44: 0.025 | O44: 0.025 | P44: 0.025 | Q44: 0.025 | R44: 0.025
C46: 2027 Add-On Acquisitions:
C47: Toggle (On / Off) | E47: 1
C48: Acquired EBITDA (USD) | E48: 1350000
C49: EBITDA Multiple | E49: 6.2
C50: Follow-On Equity Financed (%) | E50: 0.55
C51: Sales Growth (%) | E51: 0.08
C52: Gross Profit Margin (%) | E52: 0.55
C53: EBITDA Margin (%) | E53: 0.19
C54: CAPEX (% of Sales) | E54: 0.03
C55: D&A (% of CAPEX) | E55: 0.8
C56: Change in NWC (% of Sales) | E56: 0.015
C58: 2028 Add-On Acquisitions:
C59: Toggle (On / Off) | E59: 1
C60: Acquired EBITDA (USD) | E60: 1050000
C61: EBITDA Multiple | E61: 6.5
C62: Follow-On Equity Financed (%) | E62: 0.6
C63: Sales Growth (%) | E63: 0.075
C64: Gross Profit Margin (%) | E64: 0.53
C65: EBITDA Margin (%) | E65: 0.185
C66: CAPEX (% of Sales) | E66: 0.03
C67: D&A (% of CAPEX) | E67: 0.8
C68: Change in NWC (% of Sales) | E68: 0.015
C70: 2029 Add-On Acquisitions:
C71: Toggle (On / Off) | E71: 1
C72: Acquired EBITDA (USD) | E72: 620000
C73: EBITDA Multiple | E73: 5.8
C74: Follow-On Equity Financed (%) | E74: 0.5
C75: Sales Growth (%) | E75: 0.07
C76: Gross Profit Margin (%) | E76: 0.52
C77: EBITDA Margin (%) | E77: 0.18
C78: CAPEX (% of Sales) | E78: 0.028
C79: D&A (% of CAPEX) | E79: 0.8
C80: Change in NWC (% of Sales) | E80: 0.012
C82: 2030 Add-On Acquisitions:
C83: Toggle (On / Off) | E83: 1
C84: Acquired EBITDA (USD) | E84: 380000
C85: EBITDA Multiple | E85: 6
C86: Follow-On Equity Financed (%) | E86: 0.5
C87: Sales Growth (%) | E87: 0.07
C88: Gross Profit Margin (%) | E88: 0.5
C89: EBITDA Margin (%) | E89: 0.17
C90: CAPEX (% of Sales) | E90: 0.028
C91: D&A (% of CAPEX) | E91: 0.8
C92: Change in NWC (% of Sales) | E92: 0.012
C94: 2031 Add-On Acquisitions:
C95: Toggle (On / Off) | E95: 0 | F95: TO UPDATE – beyond model horizon
C96: Acquired EBITDA (USD) | E96: 900000
C97: EBITDA Multiple | E97: 6
C98: Follow-On Equity Financed (%) | E98: 0.6
C99: Sales Growth (%) | E99: 0.07
C100: Gross Profit Margin (%) | E100: 0.5
C101: EBITDA Margin (%) | E101: 0.18
C102: CAPEX (% of Sales) | E102: 0.03
C103: D&A (% of CAPEX) | E103: 0.8
C104: Change in NWC (% of Sales) | E104: 0.015
C106: Financial Statements
C107: A | D107: Organic Business Income Statement
C108: Revenue:
C109: AHG Central | G109: ='1. AHG Central'!G146 -> 9834918.7 | H109: ='1. AHG Central'!H146 -> 9229324.9 | I109: ='1. AHG Central'!I146 -> 10665793 | J109: ='1. AHG Central'!J146 -> 11768516 | K109: ='1. AHG Central'!K146 -> 13965228 | L109: ='1. AHG Central'!L146 -> 15347542 | M109: ='1. AHG Central'!M146 -> 17493734 | N109: ='1. AHG Central'!N146 -> 19741465 | ... R109: ='1. AHG Central'!R146 -> 29519957
C110: AHG Coast | G110: ='2. AHG Coast'!G146 -> 6139038 | H110: ='2. AHG Coast'!H146 -> 5754231.9 | I110: ='2. AHG Coast'!I146 -> 6711743.3 | J110: ='2. AHG Coast'!J146 -> 7657386.4 | K110: ='2. AHG Coast'!K146 -> 8878624.1 | L110: ='2. AHG Coast'!L146 -> 9890708.2 | M110: ='2. AHG Coast'!M146 -> 11387679 | N110: ='2. AHG Coast'!N146 -> 12724856 | ... R110: ='2. AHG Coast'!R146 -> 19264521
...

Sheet 7. Entry & Exit
C3: =Cover!$C$3 -> Project Dunecrest | D3: Confidential
C4: Arvenna Health Group – Entry & Exit Valuation (USD)
C6: Fiscal Year Ending | G6: ='6. AHG (Combined Entity)'!G6 -> 43830 | H6: ='6. AHG (Combined Entity)'!H6 -> 44196 | I6: ='6. AHG (Combined Entity)'!I6 -> 44561 | J6: ='6. AHG (Combined Entity)'!J6 -> 44926 | K6: ='6. AHG (Combined Entity)'!K6 -> 45291 | L6: ='6. AHG (Combined Entity)'!L6 -> 45657 | M6: ='6. AHG (Combined Entity)'!M6 -> 46022 | N6: ='6. AHG (Combined Entity)'!N6 -> 46387 | ... R6: ='6. AHG (Combined Entity)'!R6 -> 47848 | S6: =EOMONTH(R6,12) -> 48213
C7: Fiscal Year | G7: =YEAR(G6) -> 2019 | H7: =YEAR(H6) -> 2020 | I7: =YEAR(I6) -> 2021 | J7: =YEAR(J6) -> 2022 | K7: =YEAR(K6) -> 2023 | L7: =YEAR(L6) -> 2024 | M7: =YEAR(M6) -> 2025 | N7: =YEAR(N6) -> 2026 | ... S7: =YEAR(S6) -> 2031
C8: Actual / Estimate | G8: =IF(G6<=Control!$E$11,"A","E") -> A | H8: =IF(H6<=Control!$E$11,"A","E") -> A | I8: =IF(I6<=Control!$E$11,"A","E") -> A | J8: =IF(J6<=Control!$E$11,"A","E") -> A | K8: =IF(K6<=Control!$E$11,"A","E") -> A | L8: =IF(L6<=Control!$E$11,"A","E") -> A | M8: =IF(M6<=Control!$E$11,"A","E") -> A | N8: =IF(N6<=Control!$E$11,"A","E") -> E | ... S8: =IF(S6<=Control!$E$11,"A","E") -> E
C10: Entry Assumptions
C11: A | D11: Entry Valuation | E11: ="("&Control!$E$18&" in Actual)" -> (USD in Actual)
C12: Entry Assumptions:
C13: NAV Pricing (%) | E13: 0.94
C14: Follow-On Capital Commitment – Continuation Fund (USD) | E14: 10000000
C15: Follow-On Capital Drawn per Combined Entity Schedule (memo, fund share) | E15: =SUM('6. AHG (Combined Entity)'!G195:R195)*E26 -> 6749170
C17: Entry Valuation:
C18: LTM Q2'26 EBITDA (1) | E18: =('6. AHG (Combined Entity)'!M211+'6. AHG (Combined Entity)'!N211)/2 -> 13795151
C19: Multiple (x LTM EBITDA) | E19: 8
C20: Total Enterprise Value | E20: =E18*E19 -> 1.1036121e+08
C21: (-) Gross Debt | E21: =-'6. AHG (Combined Entity)'!N303 -> -23552450
C22: (-) Minority Interest | E22: =-'6. AHG (Combined Entity)'!N270 -> -4369000
C23: (+) Cash | E23: ='6. AHG (Combined Entity)'!N250 -> 2606206.1
C24: (+) Adjustments | E24: -640000
C25: Total Equity Value | E25: =E20+SUM(E21:E24) -> 84405963
C26: Fund Ownership (%) | E26: 0.58
C27: Fund Equity Value | E27: =E25*E26 -> 48955459
C28: Purchase Price (Fund Equity Value x NAV Pricing) | E28: =E27*E13 -> 46018131
C29: Pricing to NAV (%) | E29: =IFERROR(E28/E27,0) -> 0.94
C31: B | D31: Capitalization and Sources & Uses
C32: Pre-Capitalization:
C33: Adjusted Net Debt:
C34: Gross Debt | E34: =-E21 -> 23552450
C35: (-) Cash | E35: =-E23 -> -2606206.1
C36: (-)/(+) Adjustments (Minority Interest, Other) | E36: =-(SUM(E21:E24)-E21-E23) -> 5009000
C37: Adjusted Net Debt | E37: =SUM(E34:E36) -> 25955244
C38: Equity Value:
C39: Kessport Frontier Fund II | D39: =E26 -> 0.58 | E39: =$E$25*D39 -> 48955459
C40: Kessport Frontier Fund III | D40: 0.12 | E40: =$E$25*D40 -> 10128716
C41: DFI Partner 1 | D41: 0.15 | E41: =$E$25*D41 -> 12660894
C42: DFI Partner 2 | D42: 0.15 | E42: =$E$25*D42 -> 12660894
C43: Total Equity Value | D43: =SUM(D39:D42) -> 1 | E43: =SUM(E39:E42) -> 84405963
C44: Total Enterprise Value | E44: =E37+E43 -> 1.1036121e+08
C46: Post-Capitalization:
C47: Adjusted Net Debt:
C48: Gross Debt | E48: =E34 -> 23552450
C49: (-) Cash | E49: =E35 -> -2606206.1
C50: (-)/(+) Adjustments | E50: =E36 -> 5009000
C51: Adjusted Net Debt | E51: =SUM(E48:E50) -> 25955244
C52: Equity Value:
C53: Dunecrest Continuation Fund (acquires the Fund II stake) | D53: =D39 -> 0.58 | E53: =E39 -> 48955459
C54: Other Shareholders | D54: =SUM(D40:D42) -> 0.42 | E54: =SUM(E40:E42) -> 35450505
C55: Total Equity Value | E55: =E53+E54 -> 84405963
C56: Total Enterprise Value | E56: =E51+E55 -> 1.1036121e+08
C57: Check (Post – Pre TEV) | E57: =E56-E44 -> 0
C59: Exit Assumptions
C60: A | D60: Exit Valuation
C61: Exit Date | E61: 48213
C62: Exit Path | E62: M&A
C63: Exit EBITDA Multiple (x) | E63: 8.5
C65: Total Cash Flows (100% basis):
C66: Exit EBITDA (2030E EBITDA grown at the 2030E growth rate) (2) | S66: ='6. AHG (Combined Entity)'!R211*(1+'6. AHG (Combined Entity)'!R203) -> 29193072
C67: Exit Multiple (x) | S67: =$E$63 -> 8.5
C68: Exit TEV | S68: =S66*S67 -> 2.4814111e+08
C69: (-) Net Debt / (+) Net Cash (2030E balance) (2) | S69: =-'6. AHG (Combined Entity)'!R304 -> -5431779.5
C70: (-) Minority Interest | S70: =-'6. AHG (Combined Entity)'!R270 -> -4369000
C71: Exit Equity Value | S71: =SUM(S68:S70) -> 2.3834033e+08
C73: Total Cash Flows:
C74: (-) Initial Investment | G74: =IF(G$7=YEAR(Control!$E$12),-$E$25,0) -> 0 | H74: =IF(H$7=YEAR(Control!$E$12),-$E$25,0) -> 0 | I74: =IF(I$7=YEAR(Control!$E$12),-$E$25,0) -> 0 | J74: =IF(J$7=YEAR(Control!$E$12),-$E$25,0) -> 0 | K74: =IF(K$7=YEAR(Control!$E$12),-$E$25,0) -> 0 | L74: =IF(L$7=YEAR(Control!$E$12),-$E$25,0) -> 0 | M74: =IF(M$7=YEAR(Control!$E$12),-$E$25,0) -> 0 | N74: =IF(N$7=YEAR(Control!$E$12),-$E$25,0) -> -84405963 | ... S74: =IF(S$7=YEAR(Control!$E$12),-$E$25,0) -> 0
C75: (-) Follow-On Capital | G75: =IF(G$7>YEAR(Control!$E$12),-'6. AHG (Combined Entity)'!G195,0) -> 0 | H75: =IF(H$7>YEAR(Control!$E$12),-'6. AHG (Combined Entity)'!H195,0) -> 0 | I75: =IF(I$7>YEAR(Control!$E$12),-'6. AHG (Combined Entity)'!I195,0) -> 0 | J75: =IF(J$7>YEAR(Control!$E$12),-'6. AHG (Combined Entity)'!J195,0) -> 0 | K75: =IF(K$7>YEAR(Control!$E$12),-'6. AHG (Combined Entity)'!K195,0) -> 0 | L75: =IF(L$7>YEAR(Control!$E$12),-'6. AHG (Combined Entity)'!L195,0) -> 0 | M75: =IF(M$7>YEAR(Control!$E$12),-'6. AHG (Combined Entity)'!M195,0) -> 0 | N75: =IF(N$7>YEAR(Control!$E$12),-'6. AHG (Combined Entity)'!N195,0) -> 0 | ... R75: =IF(R$7>YEAR(Control!$E$12),-'6. AHG (Combined Entity)'!R195,0) -> -1140000 | S75: 0
C76: (+) Interim Proceeds (Dividends) | G76: =IF(G$7>YEAR(Control!$E$12),'6. AHG (Combined Entity)'!G312,0) -> 0 | H76: =IF(H$7>YEAR(Control!$E$12),'6. AHG (Combined Entity)'!H312,0) -> 0 | I76: =IF(I$7>YEAR(Control!$E$12),'6. AHG (Combined Entity)'!I312,0) -> 0 | J76: =IF(J$7>YEAR(Control!$E$12),'6. AHG (Combined Entity)'!J312,0) -> 0 | K76: =IF(K$7>YEAR(Control!$E$12),'6. AHG (Combined Entity)'!K312,0) -> 0 | L76: =IF(L$7>YEAR(Control!$E$12),'6. AHG (Combined Entity)'!L312,0) -> 0 | M76: =IF(M$7>YEAR(Control!$E$12),'6. AHG (Combined Entity)'!M312,0) -> 0 | N76: =IF(N$7>YEAR(Control!$E$12),'6. AHG (Combined Entity)'!N312,0) -> 0 | ... R76: =IF(R$7>YEAR(Control!$E$12),'6. AHG (Combined Entity)'!R312,0) -> 3754029.3 | S76: 0
C77: (+) Exit Value | G77: =IF(G$6=$E$61,S71,0) -> 0 | H77: =IF(H$6=$E$61,S71,0) -> 0 | I77: =IF(I$6=$E$61,S71,0) -> 0 | J77: =IF(J$6=$E$61,S71,0) -> 0 | K77: =IF(K$6=$E$61,S71,0) -> 0 | L77: =IF(L$6=$E$61,S71,0) -> 0 | M77: =IF(M$6=$E$61,S71,0) -> 0 | N77: =IF(N$6=$E$61,S71,0) -> 0 | O77: =IF(O$6=$E$61,S71,0) -> 0 | P77: =IF(P$6=$E$61,S71,0) -> 0 | Q77: =IF(Q$6=$E$61,S71,0) -> 0 | R77: =IF(R$6=$E$61,S71,0) -> 0 | S77: =IF(S$6=$E$61,S71,0) -> 2.3834033e+08
C78: Total Cash Flows | G78: =SUM(G74:G77) -> 0 | H78: =SUM(H74:H77) -> 0 | I78: =SUM(I74:I77) -> 0 | J78: =SUM(J74:J77) -> 0 | K78: =SUM(K74:K77) -> 0 | L78: =SUM(L74:L77) -> 0 | M78: =SUM(M74:M77) -> 0 | N78: =SUM(N74:N77) -> -84405963 | ... S78: =SUM(S74:S77) -> 2.3834033e+08
C79: Gross MoIC | E79: =IFERROR(SUMIF(G78:S78,">0")/-SUMIF(G78:S78,"<0"),0) -> 2.7331034
C80: Gross IRR | E80: =IFERROR(XIRR(G78:S78,G$6:S$6),0) -> 0.22678103
C82: Total Investment:
C83: Kessport Frontier Fund II | E83: =E39 -> 48955459
C84: Kessport Frontier Fund III | E84: =E40 -> 10128716
C85: DFI Partner 1 | E85: =E41 -> 12660894
C86: DFI Partner 2 | E86: =E42 -> 12660894
C87: Total Investment | E87: =SUM(E83:E86) -> 84405963
C89: Continuation Fund Cash Flows:
C90: (-) Initial Investment (Purchase Price at NAV Pricing) | G90: =IF(G$7=YEAR(Control!$E$12),-$E$28,0) -> 0 | H90: =IF(H$7=YEAR(Control!$E$12),-$E$28,0) -> 0 | I90: =IF(I$7=YEAR(Control!$E$12),-$E$28,0) -> 0 | J90: =IF(J$7=YEAR(Control!$E$12),-$E$28,0) -> 0 | K90: =IF(K$7=YEAR(Control!$E$12),-$E$28,0) -> 0 | L90: =IF(L$7=YEAR(Control!$E$12),-$E$28,0) -> 0 | M90: =IF(M$7=YEAR(Control!$E$12),-$E$28,0) -> 0 | N90: =IF(N$7=YEAR(Control!$E$12),-$E$28,0) -> -46018131 | ... S90: =IF(S$7=YEAR(Control!$E$12),-$E$28,0) -> 0
C91: (-) Follow-On Capital (fund share) | G91: =G75*$E$26 -> 0 | H91: =H75*$E$26 -> 0 | I91: =I75*$E$26 -> 0 | J91: =J75*$E$26 -> 0 | K91: =K75*$E$26 -> 0 | L91: =L75*$E$26 -> 0 | M91: =M75*$E$26 -> 0 | N91: =N75*$E$26 -> 0 | ... S91: =S75*$E$26 -> 0
C92: (+) Interim Proceeds | G92: =G76*$E$26 -> 0 | H92: =H76*$E$26 -> 0 | I92: =I76*$E$26 -> 0 | J92: =J76*$E$26 -> 0 | K92: =K76*$E$26 -> 0 | L92: =L76*$E$26 -> 0 | M92: =M76*$E$26 -> 0 | N92: =N76*$E$26 -> 0 | ... S92: =S76*$E$26 -> 0
C93: (+) Exit Value | G93: =G77*$E$26 -> 0 | H93: =H77*$E$26 -> 0 | I93: =I77*$E$26 -> 0 | J93: =J77*$E$26 -> 0 | K93: =K77*$E$26 -> 0 | L93: =L77*$E$26 -> 0 | M93: =M77*$E$26 -> 0 | N93: =N77*$E$26 -> 0 | ... S93: =S77*$E$26 -> 1.3823739e+08
C94: Total Cash Flows | G94: =SUM(G90:G93) -> 0 | H94: =SUM(H90:H93) -> 0 | I94: =SUM(I90:I93) -> 0 | J94: =SUM(J90:J93) -> 0 | K94: =SUM(K90:K93) -> 0 | L94: =SUM(L90:L93) -> 0 | M94: =SUM(M90:M93) -> 0 | N94: =SUM(N90:N93) -> -46018131 | ... S94: =SUM(S90:S93) -> 1.3823739e+08
C95: Gross MoIC | E95: =IFERROR(SUMIF(G94:S94,">0")/-SUMIF(G94:S94,"<0"),0) -> 2.898624
C96: Gross IRR | E96: =IFERROR(XIRR(G94:S94,G$6:S$6),0) -> 0.24170964
C98: Notes:
C99: (1) LTM Q2'26 EBITDA approximated as the average of FY2025A and FY2026E EBITDA.
C100: (2) Exit at 31-Dec-2031: exit EBITDA = FY2030E EBITDA grown one year at the FY2030E revenue growth rate; net debt and minorities at the FY2030E balance (last modelled year).

Sheet 1. Tallowick
C3: =Cover!$C$3 -> Project Dunecrest | D3: Confidential
C4: Tallowick Consumer Products – Operating Build
C6: Fiscal Year Ending | G6: 43830 | H6: 44196 | I6: 44561 | J6: 44926 | K6: =EOMONTH(J6,12) -> 45291 | L6: =EOMONTH(K6,12) -> 45657 | M6: =EOMONTH(L6,12) -> 46022 | N6: =EOMONTH(M6,12) -> 46387 | O6: =EOMONTH(N6,12) -> 46752 | P6: =EOMONTH(O6,12) -> 47118 | Q6: =EOMONTH(P6,12) -> 47483 | R6: =EOMONTH(Q6,12) -> 47848
C7: Fiscal Year | G7: =YEAR(G6) -> 2019 | H7: =YEAR(H6) -> 2020 | I7: =YEAR(I6) -> 2021 | J7: =YEAR(J6) -> 2022 | K7: =YEAR(K6) -> 2023 | L7: =YEAR(L6) -> 2024 | M7: =YEAR(M6) -> 2025 | N7: =YEAR(N6) -> 2026 | ... R7: =YEAR(R6) -> 2030
C8: Actual / Estimate | G8: =IF(G6<=Control!$E$11,"A","E") -> A | H8: =IF(H6<=Control!$E$11,"A","E") -> A | I8: =IF(I6<=Control!$E$11,"A","E") -> A | J8: =IF(J6<=Control!$E$11,"A","E") -> A | K8: =IF(K6<=Control!$E$11,"A","E") -> A | L8: =IF(L6<=Control!$E$11,"A","E") -> A | M8: =IF(M6<=Control!$E$11,"A","E") -> A | N8: =IF(N6<=Control!$E$11,"A","E") -> E | ... R8: =IF(R6<=Control!$E$11,"A","E") -> E
C10: Supporting Data
C11: A | D11: Revenue & Cost Build | E11: ="("&Control!$E$21&" in Actual)" -> (LCB in Actual)
C14: Revenue (LCB) | G14: 7111938000 | H14: 6793697000 | I14: 7398425000 | J14: 7898080000 | K14: 8798482000 | L14: 9679592000 | M14: 10611703000 | N14: =M14*(1+N15) -> 11312075398 | O14: =N14*(1+O15) -> 1.2149169e+10 | P14: =O14*(1+P15) -> 1.3036058e+10 | Q14: =P14*(1+Q15) -> 1.4039835e+10 | R14: =Q14*(1+R15) -> 1.5008583e+10
C15: Growth (%) | G15: =IFERROR(G14/F14-1,"N/A") -> N/A | H15: =IFERROR(H14/G14-1,"N/A") -> -0.044747437 | I15: =IFERROR(I14/H14-1,"N/A") -> 0.089013096 | J15: =IFERROR(J14/I14-1,"N/A") -> 0.06753532 | K15: =IFERROR(K14/J14-1,"N/A") -> 0.11400264 | L15: =IFERROR(L14/K14-1,"N/A") -> 0.10014341 | M15: =IFERROR(M14/L14-1,"N/A") -> 0.096296517 | N15: ='2. Tallowick (Combined Entity)'!N12 -> 0.066 | O15: ='2. Tallowick (Combined Entity)'!O12 -> 0.074 | P15: ='2. Tallowick (Combined Entity)'!P12 -> 0.073 | Q15: ='2. Tallowick (Combined Entity)'!Q12 -> 0.077 | R15: ='2. Tallowick (Combined Entity)'!R12 -> 0.069
C17: Expenses:
C18: COGS – % of Sales (%) | G18: =IFERROR(G19/G14,"N/A") -> 0.59916313 | H18: =IFERROR(H19/H14,"N/A") -> 0.58639133 | I18: =IFERROR(I19/I14,"N/A") -> 0.63885273 | J18: =IFERROR(J19/J14,"N/A") -> 0.64192981 | K18: =IFERROR(K19/K14,"N/A") -> 0.64500035 | L18: =IFERROR(L19/L14,"N/A") -> 0.63301676 | M18: =IFERROR(M19/M14,"N/A") -> 0.6379533 | N18: ='2. Tallowick (Combined Entity)'!N14 -> 0.6136 | O18: ='2. Tallowick (Combined Entity)'!O14 -> 0.6094 | P18: ='2. Tallowick (Combined Entity)'!P14 -> 0.6089 | Q18: ='2. Tallowick (Combined Entity)'!Q14 -> 0.6154 | R18: ='2. Tallowick (Combined Entity)'!R14 -> 0.622
C19: COGS (LCB) | G19: 4261211000 | H19: 3983765000 | I19: 4726504000 | J19: 5070013000 | K19: 5675024000 | L19: 6127344000 | M19: 6769771000 | N19: =N18*N14 -> 6.9410895e+09 | O19: =O18*O14 -> 7.4037036e+09 | P19: =P18*P14 -> 7.9376559e+09 | Q19: =Q18*Q14 -> 8.6401143e+09 | R19: =R18*R14 -> 9.3353389e+09
C20: Other Costs – % of Sales (%) | G20: =IFERROR(G21/G14,"N/A") -> 0.041628737 | H20: =IFERROR(H21/H14,"N/A") -> 0.040311336 | I20: =IFERROR(I21/I14,"N/A") -> 0.039072776 | J20: =IFERROR(J21/J14,"N/A") -> 0.041116702 | K20: =IFERROR(K21/K14,"N/A") -> 0.040949677 | L20: =IFERROR(L21/L14,"N/A") -> 0.038803082 | M20: =IFERROR(M21/M14,"N/A") -> 0.038737892 | N20: ='2. Tallowick (Combined Entity)'!N15 -> 0.04 | O20: ='2. Tallowick (Combined Entity)'!O15 -> 0.0399 | P20: ='2. Tallowick (Combined Entity)'!P15 -> 0.0399 | Q20: ='2. Tallowick (Combined Entity)'!Q15 -> 0.0402 | R20: ='2. Tallowick (Combined Entity)'!R15 -> 0.0398
C21: Other Costs (LCB) | G21: 296061000 | H21: 273863000 | I21: 289077000 | J21: 324743000 | K21: 360295000 | L21: 375598000 | M21: 411075000 | N21: =N20*N14 -> 4.5248302e+08 | O21: =O20*O14 -> 4.8475184e+08 | P21: =P20*P14 -> 5.2013873e+08 | Q21: =Q20*Q14 -> 5.6440136e+08 | R21: =R20*R14 -> 5.9734162e+08
C22: Trade Promotions – % of Sales (%) | G22: =IFERROR(G23/G14,"N/A") -> 0.054500756 | H22: =IFERROR(H23/H14,"N/A") -> 0.053293074 | I22: =IFERROR(I23/I14,"N/A") -> 0.055178231 | J22: =IFERROR(J23/J14,"N/A") -> 0.056714923 | K22: =IFERROR(K23/K14,"N/A") -> 0.052667267 | L22: =IFERROR(L23/L14,"N/A") -> 0.052968348 | M22: =IFERROR(M23/M14,"N/A") -> 0.052194167 | N22: ='2. Tallowick (Combined Entity)'!N16 -> 0.054 | O22: ='2. Tallowick (Combined Entity)'!O16 -> 0.0545 | P22: ='2. Tallowick (Combined Entity)'!P16 -> 0.0553 | Q22: ='2. Tallowick (Combined Entity)'!Q16 -> 0.0549 | R22: ='2. Tallowick (Combined Entity)'!R16 -> 0.0546
C23: Trade Promotions (LCB) | G23: 387606000 | H23: 362057000 | I23: 408232000 | J23: 447939000 | K23: 463392000 | L23: 512712000 | M23: 553869000 | N23: =N22*N14 -> 6.1085207e+08 | O23: =O22*O14 -> 6.6212971e+08 | P23: =P22*P14 -> 7.2089402e+08 | Q23: =Q22*Q14 -> 7.7078693e+08 | R23: =R22*R14 -> 8.1946865e+08
C24: Marketing Costs – % of Sales (%) | G24: =IFERROR(G25/G14,"N/A") -> 0.033816662 | H24: =IFERROR(H25/H14,"N/A") -> 0.033042245 | I24: =IFERROR(I25/I14,"N/A") -> 0.034053464 | J24: =IFERROR(J25/J14,"N/A") -> 0.037680297 | K24: =IFERROR(K25/K14,"N/A") -> 0.035852094 | L24: =IFERROR(L25/L14,"N/A") -> 0.033936864 | M24: =IFERROR(M25/M14,"N/A") -> 0.036182034 | N24: ='2. Tallowick (Combined Entity)'!N17 -> 0.0352 | O24: ='2. Tallowick (Combined Entity)'!O17 -> 0.0348 | P24: ='2. Tallowick (Combined Entity)'!P17 -> 0.0352 | Q24: ='2. Tallowick (Combined Entity)'!Q17 -> 0.0345 | R24: ='2. Tallowick (Combined Entity)'!R17 -> 0.0348
C25: Marketing Costs (LCB) | G25: 240502000 | H25: 224479000 | I25: 251942000 | J25: 297602000 | K25: 315444000 | L25: 328495000 | M25: 383953000 | N25: =N24*N14 -> 3.9818505e+08 | O25: =O24*O14 -> 4.2279108e+08 | P25: =P24*P14 -> 4.5886925e+08 | Q25: =Q24*Q14 -> 4.843743e+08 | R25: =R24*R14 -> 5.222987e+08
C26: Staff Costs – % of Sales (%) | G26: =IFERROR(G27/G14,"N/A") -> 0.090254161 | H26: =IFERROR(H27/H14,"N/A") -> 0.083947223 | I26: =IFERROR(I27/I14,"N/A") -> 0.086338106 | J26: =IFERROR(J27/J14,"N/A") -> 0.08601179 | K26: =IFERROR(K27/K14,"N/A") -> 0.095766633 | L26: =IFERROR(L27/L14,"N/A") -> 0.092024127 | M26: =IFERROR(M27/M14,"N/A") -> 0.088317398 | N26: ='2. Tallowick (Combined Entity)'!N18 -> 0.0896 | O26: ='2. Tallowick (Combined Entity)'!O18 -> 0.0905 | P26: ='2. Tallowick (Combined Entity)'!P18 -> 0.0892 | Q26: ='2. Tallowick (Combined Entity)'!Q18 -> 0.0906 | R26: ='2. Tallowick (Combined Entity)'!R18 -> 0.0909
C27: Staff Costs (LCB) | G27: 641882000 | H27: 570312000 | I27: 638766000 | J27: 679328000 | K27: 842601000 | L27: 890756000 | M27: 937198000 | N27: =N26*N14 -> 1.013562e+09 | O27: =O26*O14 -> 1.0994998e+09 | P27: =P26*P14 -> 1.1628164e+09 | Q27: =Q26*Q14 -> 1.272009e+09 | R27: =R26*R14 -> 1.3642802e+09
C28: Taxes (operating) – % of Sales (%) | G28: =IFERROR(G29/G14,"N/A") -> 0.0097409454 | H28: =IFERROR(H29/H14,"N/A") -> 0.009745651 | I28: =IFERROR(I29/I14,"N/A") -> 0.010132832 | J28: =IFERROR(J29/J14,"N/A") -> 0.0097367968 | K28: =IFERROR(K29/K14,"N/A") -> 0.009983313 | L28: =IFERROR(L29/L14,"N/A") -> 0.010106934 | M28: =IFERROR(M29/M14,"N/A") -> 0.010026666 | N28: ='2. Tallowick (Combined Entity)'!N19 -> 0.0098 | O28: ='2. Tallowick (Combined Entity)'!O19 -> 0.01 | P28: ='2. Tallowick (Combined Entity)'!P19 -> 0.0099 | Q28: ='2. Tallowick (Combined Entity)'!Q19 -> 0.0101 | R28: ='2. Tallowick (Combined Entity)'!R19 -> 0.01
C29: Taxes (operating) (LCB) | G29: 69277000 | H29: 66209000 | I29: 74967000 | J29: 76902000 | K29: 87838000 | L29: 97831000 | M29: 106400000 | N29: =N28*N14 -> 1.1085834e+08 | O29: =O28*O14 -> 1.2149169e+08 | P29: =P28*P14 -> 1.2905698e+08 | Q29: =Q28*Q14 -> 1.4180233e+08 | R29: =R28*R14 -> 1.5008583e+08
C30: D&A – % of Sales (%) | G30: =IFERROR(G31/G14,"N/A") -> 0.028081516 | H30: =IFERROR(H31/H14,"N/A") -> 0.026986485 | I30: =IFERROR(I31/I14,"N/A") -> 0.029878792 | J30: =IFERROR(J31/J14,"N/A") -> 0.028259653 | K30: =IFERROR(K31/K14,"N/A") -> 0.029991196 | L30: =IFERROR(L31/L14,"N/A") -> 0.02812071 | M30: =IFERROR(M31/M14,"N/A") -> 0.026603458 | N30: ='2. Tallowick (Combined Entity)'!N20 -> 0.0275 | O30: ='2. Tallowick (Combined Entity)'!O20 -> 0.0279 | P30: ='2. Tallowick (Combined Entity)'!P20 -> 0.0279 | Q30: ='2. Tallowick (Combined Entity)'!Q20 -> 0.0278 | R30: ='2. Tallowick (Combined Entity)'!R20 -> 0.0277
C31: D&A (LCB) | G31: 199714000 | H31: 183338000 | I31: 221056000 | J31: 223197000 | K31: 263877000 | L31: 272197000 | M31: 282308000 | N31: =N30*N14 -> 3.1108207e+08 | O31: =O30*O14 -> 3.3896181e+08 | P31: =P30*P14 -> 3.6370603e+08 | Q31: =Q30*Q14 -> 3.9030741e+08 | R31: =R30*R14 -> 4.1573776e+08
C34: Financial Statements
C35: B | D35: Income Statement
E36: ="("&Control!$E$23&" in Actual)" -> (USD in Actual)
C37: Revenue | G37: =G14*Control!$E$22 -> 88899225 | H37: =H14*Control!$E$22 -> 84921212 | I37: =I14*Control!$E$22 -> 92480312 | J37: =J14*Control!$E$22 -> 98726000 | K37: =K14*Control!$E$22 -> 109981025 | L37: =L14*Control!$E$22 -> 120994900 | M37: =M14*Control!$E$22 -> 1.3264629e+08 | N37: =N14*Control!$E$22 -> 1.4140094e+08 | ... R37: =R14*Control!$E$22 -> 1.8760729e+08
C38: Growth (%) | G38: =IFERROR(G37/F37-1,"N/A") -> N/A | H38: =IFERROR(H37/G37-1,"N/A") -> -0.044747437 | I38: =IFERROR(I37/H37-1,"N/A") -> 0.089013096 | J38: =IFERROR(J37/I37-1,"N/A") -> 0.06753532 | K38: =IFERROR(K37/J37-1,"N/A") -> 0.11400264 | L38: =IFERROR(L37/K37-1,"N/A") -> 0.10014341 | M38: =IFERROR(M37/L37-1,"N/A") -> 0.096296517 | N38: =IFERROR(N37/M37-1,"N/A") -> 0.066 | ... R38: =IFERROR(R37/Q37-1,"N/A") -> 0.069
C39: (-) COGS | G39: =-G19*Control!$E$22 -> -53265138 | H39: =-H19*Control!$E$22 -> -49797062 | I39: =-I19*Control!$E$22 -> -59081300 | J39: =-J19*Control!$E$22 -> -63375162 | K39: =-K19*Control!$E$22 -> -70937800 | L39: =-L19*Control!$E$22 -> -76591800 | M39: =-M19*Control!$E$22 -> -84622138 | N39: =-N19*Control!$E$22 -> -86763618 | ... R39: =-R19*Control!$E$22 -> -1.1669174e+08
C40: Gross Margin | G40: =G37+G39 -> 35634088 | H40: =H37+H39 -> 35124150 | I40: =I37+I39 -> 33399012 | J40: =J37+J39 -> 35350838 | K40: =K37+K39 -> 39043225 | L40: =L37+L39 -> 44403100 | M40: =M37+M39 -> 48024150 | N40: =N37+N39 -> 54637324 | ... R40: =R37+R39 -> 70915557
C41: Margin (%) | G41: =IFERROR(G40/G$37,"N/A") -> 0.40083687 | H41: =IFERROR(H40/H$37,"N/A") -> 0.41360867 | I41: =IFERROR(I40/I$37,"N/A") -> 0.36114727 | J41: =IFERROR(J40/J$37,"N/A") -> 0.35807019 | K41: =IFERROR(K40/K$37,"N/A") -> 0.35499965 | L41: =IFERROR(L40/L$37,"N/A") -> 0.36698324 | M41: =IFERROR(M40/M$37,"N/A") -> 0.3620467 | N41: =IFERROR(N40/N$37,"N/A") -> 0.3864 | ... R41: =IFERROR(R40/R$37,"N/A") -> 0.378
C42: (-) Other Costs | G42: =-G21*Control!$E$22 -> -3700762.5 | H42: =-H21*Control!$E$22 -> -3423287.5 | I42: =-I21*Control!$E$22 -> -3613462.5 | J42: =-J21*Control!$E$22 -> -4059287.5 | K42: =-K21*Control!$E$22 -> -4503687.5 | L42: =-L21*Control!$E$22 -> -4694975 | M42: =-M21*Control!$E$22 -> -5138437.5 | N42: =-N21*Control!$E$22 -> -5656037.7 | ... R42: =-R21*Control!$E$22 -> -7466770.2
C43: (-) Trade Promotions | G43: =-G23*Control!$E$22 -> -4845075 | H43: =-H23*Control!$E$22 -> -4525712.5 | I43: =-I23*Control!$E$22 -> -5102900 | J43: =-J23*Control!$E$22 -> -5599237.5 | K43: =-K23*Control!$E$22 -> -5792400 | L43: =-L23*Control!$E$22 -> -6408900 | M43: =-M23*Control!$E$22 -> -6923362.5 | N43: =-N23*Control!$E$22 -> -7635650.9 | ... R43: =-R23*Control!$E$22 -> -10243358
C44: (-) Marketing Costs | G44: =-G25*Control!$E$22 -> -3006275 | H44: =-H25*Control!$E$22 -> -2805987.5 | I44: =-I25*Control!$E$22 -> -3149275 | J44: =-J25*Control!$E$22 -> -3720025 | K44: =-K25*Control!$E$22 -> -3943050 | L44: =-L25*Control!$E$22 -> -4106187.5 | M44: =-M25*Control!$E$22 -> -4799412.5 | N44: =-N25*Control!$E$22 -> -4977313.2 | ... R44: =-R25*Control!$E$22 -> -6528733.8
C45: (-) Staff Costs | G45: =-G27*Control!$E$22 -> -8023525 | H45: =-H27*Control!$E$22 -> -7128900 | I45: =-I27*Control!$E$22 -> -7984575 | J45: =-J27*Control!$E$22 -> -8491600 | K45: =-K27*Control!$E$22 -> -10532512 | L45: =-L27*Control!$E$22 -> -11134450 | M45: =-M27*Control!$E$22 -> -11714975 | N45: =-N27*Control!$E$22 -> -12669524 | ... R45: =-R27*Control!$E$22 -> -17053503
C46: (-) Taxes (operating) | G46: =-G29*Control!$E$22 -> -865962.5 | H46: =-H29*Control!$E$22 -> -827612.5 | I46: =-I29*Control!$E$22 -> -937087.5 | J46: =-J29*Control!$E$22 -> -961275 | K46: =-K29*Control!$E$22 -> -1097975 | L46: =-L29*Control!$E$22 -> -1222887.5 | M46: =-M29*Control!$E$22 -> -1330000 | N46: =-N29*Control!$E$22 -> -1385729.2 | ... R46: =-R29*Control!$E$22 -> -1876072.9
C47: EBITDA | G47: =G40+G42+G43+G44+G45+G46 -> 15192488 | H47: =H40+H42+H43+H44+H45+H46 -> 16412650 | I47: =I40+I42+I43+I44+I45+I46 -> 12611712 | J47: =J40+J42+J43+J44+J45+J46 -> 12519412 | K47: =K40+K42+K43+K44+K45+K46 -> 13173600 | L47: =L40+L42+L43+L44+L45+L46 -> 16835700 | M47: =M40+M42+M43+M44+M45+M46 -> 18117962 | N47: =N40+N42+N43+N44+N45+N46 -> 22313069 | ... R47: =R40+R42+R43+R44+R45+R46 -> 27747119
C48: Margin (%) | G48: =IFERROR(G47/G$37,"N/A") -> 0.17089561 | H48: =IFERROR(H47/H$37,"N/A") -> 0.19326914 | I48: =IFERROR(I47/I$37,"N/A") -> 0.13637186 | J48: =IFERROR(J47/J$37,"N/A") -> 0.12680968 | K48: =IFERROR(K47/K$37,"N/A") -> 0.11978066 | L48: =IFERROR(L47/L$37,"N/A") -> 0.13914388 | M48: =IFERROR(M47/M$37,"N/A") -> 0.13658854 | N48: =IFERROR(N47/N$37,"N/A") -> 0.1578 | ... R48: =IFERROR(R47/R$37,"N/A") -> 0.1479
C49: (-) D&A | G49: =-G31*Control!$E$22 -> -2496425 | H49: =-H31*Control!$E$22 -> -2291725 | I49: =-I31*Control!$E$22 -> -2763200 | J49: =-J31*Control!$E$22 -> -2789962.5 | K49: =-K31*Control!$E$22 -> -3298462.5 | L49: =-L31*Control!$E$22 -> -3402462.5 | M49: =-M31*Control!$E$22 -> -3528850 | N49: =-N31*Control!$E$22 -> -3888525.9 | ... R49: =-R31*Control!$E$22 -> -5196722
C50: EBIT | G50: =G47+G49 -> 12696062 | H50: =H47+H49 -> 14120925 | I50: =I47+I49 -> 9848512.5 | J50: =J47+J49 -> 9729450 | K50: =K47+K49 -> 9875137.5 | L50: =L47+L49 -> 13433238 | M50: =M47+M49 -> 14589112 | N50: =N47+N49 -> 18424543 | ... R50: =R47+R49 -> 22550397
C51: Margin (%) | G51: =IFERROR(G50/G$37,"N/A") -> 0.1428141 | H51: =IFERROR(H50/H$37,"N/A") -> 0.16628266 | I51: =IFERROR(I50/I$37,"N/A") -> 0.10649307 | J51: =IFERROR(J50/J$37,"N/A") -> 0.098550027 | K51: =IFERROR(K50/K$37,"N/A") -> 0.089789466 | L51: =IFERROR(L50/L$37,"N/A") -> 0.11102317 | M51: =IFERROR(M50/M$37,"N/A") -> 0.10998508 | N51: =IFERROR(N50/N$37,"N/A") -> 0.1303 | ... R51: =IFERROR(R50/R$37,"N/A") -> 0.1202

Sheet 2. Tallowick (Combined Entity)
C3: =Cover!$C$3 -> Project Dunecrest | D3: Confidential
C4: Tallowick Consumer Products – Combined Entity (USD)
C6: Fiscal Year Ending | G6: 43830 | H6: 44196 | I6: 44561 | J6: 44926 | K6: =EOMONTH(J6,12) -> 45291 | L6: =EOMONTH(K6,12) -> 45657 | M6: =EOMONTH(L6,12) -> 46022 | N6: =EOMONTH(M6,12) -> 46387 | O6: =EOMONTH(N6,12) -> 46752 | P6: =EOMONTH(O6,12) -> 47118 | Q6: =EOMONTH(P6,12) -> 47483 | R6: =EOMONTH(Q6,12) -> 47848
C7: Fiscal Year | G7: =YEAR(G6) -> 2019 | H7: =YEAR(H6) -> 2020 | I7: =YEAR(I6) -> 2021 | J7: =YEAR(J6) -> 2022 | K7: =YEAR(K6) -> 2023 | L7: =YEAR(L6) -> 2024 | M7: =YEAR(M6) -> 2025 | N7: =YEAR(N6) -> 2026 | ... R7: =YEAR(R6) -> 2030
C8: Actual / Estimate | G8: =IF(G6<=Control!$E$11,"A","E") -> A | H8: =IF(H6<=Control!$E$11,"A","E") -> A | I8: =IF(I6<=Control!$E$11,"A","E") -> A | J8: =IF(J6<=Control!$E$11,"A","E") -> A | K8: =IF(K6<=Control!$E$11,"A","E") -> A | L8: =IF(L6<=Control!$E$11,"A","E") -> A | M8: =IF(M6<=Control!$E$11,"A","E") -> A | N8: =IF(N6<=Control!$E$11,"A","E") -> E | ... R8: =IF(R6<=Control!$E$11,"A","E") -> E
C10: Supporting Assumptions
C11: A | D11: Supporting Assumptions | E11: ="("&Control!$E$23&" in Actual)" -> (USD in Actual)
C12: Revenue Growth (%) | G12: ='1. Tallowick'!G15 -> N/A | H12: ='1. Tallowick'!H15 -> -0.044747437 | I12: ='1. Tallowick'!I15 -> 0.089013096 | J12: ='1. Tallowick'!J15 -> 0.06753532 | K12: ='1. Tallowick'!K15 -> 0.11400264 | L12: ='1. Tallowick'!L15 -> 0.10014341 | M12: ='1. Tallowick'!M15 -> 0.096296517 | N12: 0.066 | O12: 0.074 | P12: 0.073 | Q12: 0.077 | R12: 0.069
C13: Expenses (% of Sales):
C14: COGS | G14: ='1. Tallowick'!G18 -> 0.59916313 | H14: ='1. Tallowick'!H18 -> 0.58639133 | I14: ='1. Tallowick'!I18 -> 0.63885273 | J14: ='1. Tallowick'!J18 -> 0.64192981 | K14: ='1. Tallowick'!K18 -> 0.64500035 | L14: ='1. Tallowick'!L18 -> 0.63301676 | M14: ='1. Tallowick'!M18 -> 0.6379533 | N14: 0.6136 | O14: 0.6094 | P14: 0.6089 | Q14: 0.6154 | R14: 0.622
C15: Other Costs | G15: ='1. Tallowick'!G20 -> 0.041628737 | H15: ='1. Tallowick'!H20 -> 0.040311336 | I15: ='1. Tallowick'!I20 -> 0.039072776 | J15: ='1. Tallowick'!J20 -> 0.041116702 | K15: ='1. Tallowick'!K20 -> 0.040949677 | L15: ='1. Tallowick'!L20 -> 0.038803082 | M15: ='1. Tallowick'!M20 -> 0.038737892 | N15: 0.04 | O15: 0.0399 | P15: 0.0399 | Q15: 0.0402 | R15: 0.0398
C16: Trade Promotions | G16: ='1. Tallowick'!G22 -> 0.054500756 | H16: ='1. Tallowick'!H22 -> 0.053293074 | I16: ='1. Tallowick'!I22 -> 0.055178231 | J16: ='1. Tallowick'!J22 -> 0.056714923 | K16: ='1. Tallowick'!K22 -> 0.052667267 | L16: ='1. Tallowick'!L22 -> 0.052968348 | M16: ='1. Tallowick'!M22 -> 0.052194167 | N16: 0.054 | O16: 0.0545 | P16: 0.0553 | Q16: 0.0549 | R16: 0.0546
C17: Marketing Costs | G17: ='1. Tallowick'!G24 -> 0.033816662 | H17: ='1. Tallowick'!H24 -> 0.033042245 | I17: ='1. Tallowick'!I24 -> 0.034053464 | J17: ='1. Tallowick'!J24 -> 0.037680297 | K17: ='1. Tallowick'!K24 -> 0.035852094 | L17: ='1. Tallowick'!L24 -> 0.033936864 | M17: ='1. Tallowick'!M24 -> 0.036182034 | N17: 0.0352 | O17: 0.0348 | P17: 0.0352 | Q17: 0.0345 | R17: 0.0348
C18: Staff Costs | G18: ='1. Tallowick'!G26 -> 0.090254161 | H18: ='1. Tallowick'!H26 -> 0.083947223 | I18: ='1. Tallowick'!I26 -> 0.086338106 | J18: ='1. Tallowick'!J26 -> 0.08601179 | K18: ='1. Tallowick'!K26 -> 0.095766633 | L18: ='1. Tallowick'!L26 -> 0.092024127 | M18: ='1. Tallowick'!M26 -> 0.088317398 | N18: 0.0896 | O18: 0.0905 | P18: 0.0892 | Q18: 0.0906 | R18: 0.0909
C19: Taxes (operating) | G19: ='1. Tallowick'!G28 -> 0.0097409454 | H19: ='1. Tallowick'!H28 -> 0.009745651 | I19: ='1. Tallowick'!I28 -> 0.010132832 | J19: ='1. Tallowick'!J28 -> 0.0097367968 | K19: ='1. Tallowick'!K28 -> 0.009983313 | L19: ='1. Tallowick'!L28 -> 0.010106934 | M19: ='1. Tallowick'!M28 -> 0.010026666 | N19: 0.0098 | O19: 0.01 | P19: 0.0099 | Q19: 0.0101 | R19: 0.01
C20: D&A | G20: ='1. Tallowick'!G30 -> 0.028081516 | H20: ='1. Tallowick'!H30 -> 0.026986485 | I20: ='1. Tallowick'!I30 -> 0.029878792 | J20: ='1. Tallowick'!J30 -> 0.028259653 | K20: ='1. Tallowick'!K30 -> 0.029991196 | L20: ='1. Tallowick'!L30 -> 0.02812071 | M20: ='1. Tallowick'!M30 -> 0.026603458 | N20: 0.0275 | O20: 0.0279 | P20: 0.0279 | Q20: 0.0278 | R20: 0.0277
C21: Tax Rate (%) | G21: 0.243 | H21: 0.259 | I21: 0.25 | J21: 0.248 | K21: 0.24 | L21: 0.243 | M21: 0.249 | N21: 0.25 | O21: 0.25 | P21: 0.25 | Q21: 0.25 | R21: 0.25
C22: Non-Current Assets:
C23: Gross Tangible & Intangible Assets (memo) | G23: =G221 -> 23975000 | H23: =H221 -> 25867000 | I23: =I221 -> 29000000 | J23: =J221 -> 30667000 | K23: =K221 -> 33251000 | L23: =L221 -> 35655000 | M23: =M221 -> 37517000 | N23: =N221 -> 42324632 | ... R23: =R221 -> 72400329
C24: Depreciation % of Gross (implied) | G24: N/A | H24: =IFERROR(H25/G221,"N/A") -> 0.095588113 | I24: =IFERROR(I25/H221,"N/A") -> 0.10682337 | J24: =IFERROR(J25/I221,"N/A") -> 0.096205603 | K24: =IFERROR(K25/J221,"N/A") -> 0.10755739 | L24: =IFERROR(L25/K221,"N/A") -> 0.10232662 | M24: =IFERROR(M25/L221,"N/A") -> 0.098972094 | N24: =IFERROR(N25/M221,"N/A") -> 0.10364704 | O24: =IFERROR(O25/N221,"N/A") -> 0.10223415 | ... R24: =IFERROR(R25/Q221,"N/A") -> 0.082049088
C25: Annual Depreciation (memo) | G25: =-G210 -> 2496425 | H25: =-H210 -> 2291725 | I25: =-I210 -> 2763200 | J25: =-J210 -> 2789962.5 | K25: =-K210 -> 3298462.5 | L25: =-L210 -> 3402462.5 | M25: =-M210 -> 3528850 | N25: =-(N210+N211) -> 3888525.9 | O25: =-(O210+O211) -> 4327022.7 | P25: =-(P210+P211) -> 4722625.3 | Q25: =-(Q210+Q211) -> 5117160.5 | R25: =-(R210+R211) -> 5450795.4
C26: Accumulated Depreciation (memo) | G26: =G222 -> -9671000 | H26: =H222 -> -10975000 | I26: =I222 -> -11710000 | J26: =J222 -> -13604000 | K26: =K222 -> -14858000 | L26: =L222 -> -15785000 | M26: =M222 -> -16582000 | N26: =N222 -> -20470526 | ... R26: =R222 -> -40088130
C27: Current Assets:
C28: Inventories in Days of Purchases | G28: =IFERROR(G224/-G116*365,"N/A") -> 42.44446 | H28: =IFERROR(H224/-H116*365,"N/A") -> 44.132422 | I28: =IFERROR(I224/-I116*365,"N/A") -> 40.712544 | J28: =IFERROR(J224/-J116*365,"N/A") -> 39.32487 | K28: =IFERROR(K224/-K116*365,"N/A") -> 38.88343 | L28: =IFERROR(L224/-L116*365,"N/A") -> 40.545071 | M28: =IFERROR(M224/-M116*365,"N/A") -> 38.470253 | N28: 66 | O28: 65 | P28: 64 | Q28: 63 | R28: 62
C29: Inventory (memo) | G29: =G224 -> 6194000 | H29: =H224 -> 6021000 | I29: =I224 -> 6590000 | J29: =J224 -> 6828000 | K29: =K224 -> 7557000 | L29: =L224 -> 8508000 | M29: =M224 -> 8919000 | N29: =N224 -> 15688764 | ... R29: =R224 -> 19821610
C30: Receivables in Days of Revenues | G30: =IFERROR(G225/G199*365,"N/A") -> 21.789335 | H30: =IFERROR(H225/H199*365,"N/A") -> 23.020632 | I30: =IFERROR(I225/I199*365,"N/A") -> 22.899252 | J30: =IFERROR(J225/J199*365,"N/A") -> 23.35089 | K30: =IFERROR(K225/K199*365,"N/A") -> 23.105167 | L30: =IFERROR(L225/L199*365,"N/A") -> 21.93109 | M30: =IFERROR(M225/M199*365,"N/A") -> 21.60068 | N30: 39 | O30: 38 | P30: 38 | Q30: 37 | R30: 37
C31: Accounts Receivable (memo) | G31: =G225 -> 5307000 | H31: =H225 -> 5356000 | I31: =I225 -> 5802000 | J31: =J225 -> 6316000 | K31: =K225 -> 6962000 | L31: =L225 -> 7270000 | M31: =M225 -> 7850000 | N31: =N225 -> 15108594 | ... R31: =R225 -> 20179492
C32: Days Other Current Assets Outstanding | G32: =IFERROR(G226/G199*365,"N/A") -> 5.5551103 | H32: =IFERROR(H226/H199*365,"N/A") -> 5.5488492 | I32: =IFERROR(I226/I199*365,"N/A") -> 5.84519 | J32: =IFERROR(J226/J199*365,"N/A") -> 5.6898385 | K32: =IFERROR(K226/K199*365,"N/A") -> 5.4759446 | L32: =IFERROR(L226/L199*365,"N/A") -> 5.6984633 | M32: =IFERROR(M226/M199*365,"N/A") -> 5.4373176 | N32: 10 | O32: 10 | P32: 10 | Q32: 10 | R32: 10
C33: Other Current Assets (memo) | G33: =G226 -> 1353000 | H33: =H226 -> 1291000 | I33: =I226 -> 1481000 | J33: =J226 -> 1539000 | K33: =K226 -> 1650000 | L33: =L226 -> 1889000 | M33: =M226 -> 1976000 | N33: =N226 -> 3873998.4 | ... R33: =R226 -> 6134858.7
C34: Current Liabilities:
C35: Accounts Payable in Days of Purchases & Opex | G35: =IFERROR(G232/-(G116+G118)*365,"N/A") -> 39.757557 | H35: =IFERROR(H232/-(H116+H118)*365,"N/A") -> 40.8822 | I35: =IFERROR(I232/-(I116+I118)*365,"N/A") -> 37.085235 | J35: =IFERROR(J232/-(J116+J118)*365,"N/A") -> 38.93329 | K35: =IFERROR(K232/-(K116+K118)*365,"N/A") -> 36.770219 | L35: =IFERROR(L232/-(L116+L118)*365,"N/A") -> 37.529721 | M35: =IFERROR(M232/-(M116+M118)*365,"N/A") -> 36.381841 | N35: 64 | O35: 63 | P35: 63 | Q35: 62 | R35: 62
C36: Accounts Payable (memo) | G36: =G232 -> 6205000 | H36: =H232 -> 5961000 | I36: =I232 -> 6370000 | J36: =J232 -> 7193000 | K36: =K232 -> 7600000 | L36: =L232 -> 8358000 | M36: =M232 -> 8947000 | N36: =N232 -> 16205090 | ... R36: =R232 -> 21089938
C37: Days Other Current Liabilities Outstanding | G37: =IFERROR(G233/G199*365,"N/A") -> 8.5646416 | H37: =IFERROR(H233/H199*365,"N/A") -> 8.5618184 | I37: =IFERROR(I233/I199*365,"N/A") -> 8.5250577 | J37: =IFERROR(J233/J199*365,"N/A") -> 8.5403035 | K37: =IFERROR(K233/K199*365,"N/A") -> 8.469461 | L37: =IFERROR(L233/L199*365,"N/A") -> 8.4074205 | M37: =IFERROR(M233/M199*365,"N/A") -> 8.0981912 | N37: 15 | O37: 15 | P37: 15 | Q37: 15 | R37: 15
C38: Other Current Liabilities (memo) | G38: =G233 -> 2086000 | H38: =H233 -> 1992000 | I38: =I233 -> 2160000 | J38: =J233 -> 2310000 | K38: =K233 -> 2552000 | L38: =L233 -> 2787000 | M38: =M233 -> 2943000 | N38: =N233 -> 5810997.6 | ... R38: =R233 -> 8180874.9
C39: Non-Current Liabilities:
C40: New Loans (USD) | G40: 0 | H40: 0 | I40: 0 | J40: 0 | K40: 0 | L40: 0 | M40: 0 | N40: 0 | O40: 2250000 | P40: 0 | Q40: 0 | R40: 0
C41: Mandatory Paydown of Existing Loans (% Previous Year) | G41: N/A | H41: =IFERROR(1-H230/G230,"N/A") -> 0.084059633 | I41: =IFERROR(1-I230/H230,"N/A") -> 0.10542131 | J41: =IFERROR(1-J230/I230,"N/A") -> 0.072218334 | K41: =IFERROR(1-K230/J230,"N/A") -> 0.090209685 | L41: =IFERROR(1-L230/K230,"N/A") -> 0.10910297 | M41: =IFERROR(1-M230/L230,"N/A") -> 0.16117625 | N41: 0.2 | O41: 0.2 | P41: 0.2 | Q41: 0.2 | R41: 0.2
C42: Interest Rate (%) | G42: N/A | H42: =IFERROR(-H213/G230,"N/A") -> 0.10745413 | I42: =IFERROR(-I213/H230,"N/A") -> 0.10642294 | J42: =IFERROR(-J213/I230,"N/A") -> 0.11028691 | K42: =IFERROR(-K213/J230,"N/A") -> 0.11193242 | L42: =IFERROR(-L213/K230,"N/A") -> 0.10993202 | M42: =IFERROR(-M213/L230,"N/A") -> 0.097710776 | N42: 0.115 | O42: 0.115 | P42: 0.115 | Q42: 0.115 | R42: 0.115
C43: Average Debt Balance (memo only; interest uses opening balance) | G43: =G230 -> 8720000 | H43: =AVERAGE(G230,H230) -> 8353500 | I43: =AVERAGE(H230,I230) -> 7566000 | J43: =AVERAGE(I230,J230) -> 6887000 | K43: =AVERAGE(J230,K230) -> 6330000 | L43: =AVERAGE(K230,L230) -> 5702000 | M43: =AVERAGE(L230,M230) -> 4940000 | N43: =AVERAGE(M230,N230) -> 4056300 | O43: =AVERAGE(N230,O230) -> 4370040 | ... R43: =AVERAGE(Q230,R230) -> 2957460.5
C44: Yield on Cash (%) | G44: N/A | H44: =IFERROR(H214/G227,"N/A") -> 0.020238418 | I44: =IFERROR(I214/H227,"N/A") -> 0.025240055 | J44: =IFERROR(J214/I227,"N/A") -> 0.042040545 | K44: =IFERROR(K214/J227,"N/A") -> 0.017420266 | L44: =IFERROR(L214/K227,"N/A") -> 0.036057554 | M44: =IFERROR(M214/L227,"N/A") -> 0.035178754 | N44: 0.03 | O44: 0.03 | P44: 0.03 | Q44: 0.03 | R44: 0.03
C45: Other Non-Current Liabilities (% Growth) | G45: N/A | H45: =IFERROR(H231/G231-1,"N/A") -> -0.058823529 | I45: =IFERROR(I231/H231-1,"N/A") -> 0.11270492 | J45: =IFERROR(J231/I231-1,"N/A") -> 0.050644567 | K45: =IFERROR(K231/J231-1,"N/A") -> 0.086765995 | L45: =IFERROR(L231/K231-1,"N/A") -> 0.094354839 | M45: =IFERROR(M231/L231-1,"N/A") -> 0.13633014 | N45: 0.02 | O45: 0.02 | P45: 0.02 | Q45: 0.02 | R45: 0.02
C46: Organic CAPEX:
C47: CAPEX (USD) | G47: 1883000 | H47: 1534000 | I47: 1879000 | J47: 2103000 | K47: 2060000 | L47: 2541000 | M47: 2475000 | N47: =N48*N114 -> 4807632 | O47: =O48*O114 -> 5011532.2 | P47: =P48*P114 -> 5214423.3 | Q47: =Q48*Q114 -> 5615933.9 | R47: =R48*R114 -> 5628218.8
C48: CAPEX (% of Sales) | G48: =IFERROR(G47/G114,"N/A") -> 0.021181287 | H48: =IFERROR(H47/H114,"N/A") -> 0.018063802 | I48: =IFERROR(I47/I114,"N/A") -> 0.020317838 | J48: =IFERROR(J47/J114,"N/A") -> 0.02130138 | K48: =IFERROR(K47/K114,"N/A") -> 0.018730504 | L48: =IFERROR(L47/L114,"N/A") -> 0.021000885 | M48: =IFERROR(M47/M114,"N/A") -> 0.018658645 | N48: 0.034 | O48: 0.033 | P48: 0.032 | Q48: 0.032 | R48: 0.03
C49: Minimum Cash Sweep:
C50: Minimum Cash (% of Revenue) | G50: =IFERROR(G227/G199,"N/A") -> 0.041518922 | H50: =IFERROR(H227/H199,"N/A") -> 0.03433771 | I50: =IFERROR(I227/I199,"N/A") -> 0.032536655 | J50: =IFERROR(J227/J199,"N/A") -> 0.050179284 | K50: =IFERROR(K227/K199,"N/A") -> 0.031596359 | L50: =IFERROR(L227/L199,"N/A") -> 0.040456251 | M50: =IFERROR(M227/M199,"N/A") -> 0.052063274 | N50: 0.03 | O50: 0.03 | P50: 0.03 | Q50: 0.03 | R50: 0.03
C52: 2027 Add-On Acquisitions:
C53: Toggle (On / Off) | E53: 1
C54: Acquired EBITDA (USD) | E54: 560000
C55: EBITDA Multiple | E55: 5.6
C56: Follow-On Equity Financed (%) | E56: 0.6
C57: Sales Growth (%) | E57: 0.07
C58: Gross Profit Margin (%) | E58: 0.36
C59: EBITDA Margin (%) | E59: 0.14
C60: CAPEX (% of Sales) | E60: 0.03
C61: D&A (% of CAPEX) | E61: 0.75
C62: Change in NWC (% of Sales) | E62: 0.02
C64: 2028 Add-On Acquisitions:
C65: Toggle (On / Off) | E65: 1
C66: Acquired EBITDA (USD) | E66: 480000
C67: EBITDA Multiple | E67: 5.8
C68: Follow-On Equity Financed (%) | E68: 0.65
C69: Sales Growth (%) | E69: 0.065
C70: Gross Profit Margin (%) | E70: 0.35
C71: EBITDA Margin (%) | E71: 0.135
C72: CAPEX (% of Sales) | E72: 0.03
C73: D&A (% of CAPEX) | E73: 0.75
C74: Change in NWC (% of Sales) | E74: 0.02
C76: 2029 Add-On Acquisitions:
C77: Toggle (On / Off) | E77: 1
C78: Acquired EBITDA (USD) | E78: 310000
C79: EBITDA Multiple | E79: 5.4
C80: Follow-On Equity Financed (%) | E80: 0.6
C81: Sales Growth (%) | E81: 0.06
C82: Gross Profit Margin (%) | E82: 0.35
C83: EBITDA Margin (%) | E83: 0.13
C84: CAPEX (% of Sales) | E84: 0.028
C85: D&A (% of CAPEX) | E85: 0.75
C86: Change in NWC (% of Sales) | E86: 0.02
C88: 2030 Add-On Acquisitions:
C89: Toggle (On / Off) | E89: 0
C90: Acquired EBITDA (USD) | E90: 250000
C91: EBITDA Multiple | E91: 5.5
C92: Follow-On Equity Financed (%) | E92: 0.6
C93: Sales Growth (%) | E93: 0.06
C94: Gross Profit Margin (%) | E94: 0.34
C95: EBITDA Margin (%) | E95: 0.13
C96: CAPEX (% of Sales) | E96: 0.028
C97: D&A (% of CAPEX) | E97: 0.75
C98: Change in NWC (% of Sales) | E98: 0.02
C100: 2031 Add-On Acquisitions:
C101: Toggle (On / Off) | E101: 0 | F101: TO UPDATE – beyond model horizon
C102: Acquired EBITDA (USD) | E102: 400000
C103: EBITDA Multiple | E103: 5.5
C104: Follow-On Equity Financed (%) | E104: 0.6
C105: Sales Growth (%) | E105: 0.06
C106: Gross Profit Margin (%) | E106: 0.34
C107: EBITDA Margin (%) | E107: 0.13
C108: CAPEX (% of Sales) | E108: 0.03
C109: D&A (% of CAPEX) | E109: 0.75
...

Sheet 3. Entry & Exit
C3: =Cover!$C$3 -> Project Dunecrest | D3: Confidential
C4: Tallowick Consumer Products – Entry & Exit Valuation (USD)
C6: Fiscal Year Ending | G6: ='2. Tallowick (Combined Entity)'!G6 -> 43830 | H6: ='2. Tallowick (Combined Entity)'!H6 -> 44196 | I6: ='2. Tallowick (Combined Entity)'!I6 -> 44561 | J6: ='2. Tallowick (Combined Entity)'!J6 -> 44926 | K6: ='2. Tallowick (Combined Entity)'!K6 -> 45291 | L6: ='2. Tallowick (Combined Entity)'!L6 -> 45657 | M6: ='2. Tallowick (Combined Entity)'!M6 -> 46022 | N6: ='2. Tallowick (Combined Entity)'!N6 -> 46387 | ... R6: ='2. Tallowick (Combined Entity)'!R6 -> 47848 | S6: =EOMONTH(R6,12) -> 48213
C7: Fiscal Year | G7: =YEAR(G6) -> 2019 | H7: =YEAR(H6) -> 2020 | I7: =YEAR(I6) -> 2021 | J7: =YEAR(J6) -> 2022 | K7: =YEAR(K6) -> 2023 | L7: =YEAR(L6) -> 2024 | M7: =YEAR(M6) -> 2025 | N7: =YEAR(N6) -> 2026 | ... S7: =YEAR(S6) -> 2031
C8: Actual / Estimate | G8: =IF(G6<=Control!$E$11,"A","E") -> A | H8: =IF(H6<=Control!$E$11,"A","E") -> A | I8: =IF(I6<=Control!$E$11,"A","E") -> A | J8: =IF(J6<=Control!$E$11,"A","E") -> A | K8: =IF(K6<=Control!$E$11,"A","E") -> A | L8: =IF(L6<=Control!$E$11,"A","E") -> A | M8: =IF(M6<=Control!$E$11,"A","E") -> A | N8: =IF(N6<=Control!$E$11,"A","E") -> E | ... S8: =IF(S6<=Control!$E$11,"A","E") -> E
C10: Entry Assumptions
C11: A | D11: Entry Valuation | E11: ="("&Control!$E$18&" in Actual)" -> (USD in Actual)
C12: Entry Assumptions:
C13: NAV Pricing (%) | E13: 0.93
C14: Follow-On Capital Commitment – Continuation Fund (USD) | E14: 4000000
C15: Follow-On Capital Drawn per Combined Entity Schedule (memo, fund share) | E15: =SUM('2. Tallowick (Combined Entity)'!G192:R192)*E26 -> 3474744
C17: Entry Valuation:
C18: LTM Q2'26 EBITDA (1) | E18: =('2. Tallowick (Combined Entity)'!M208+'2. Tallowick (Combined Entity)'!N208)/2 -> 20215516
C19: Multiple (x LTM EBITDA) | E19: 7
C20: Total Enterprise Value | E20: =E18*E19 -> 1.4150861e+08
C21: (-) Gross Debt | E21: =-'2. Tallowick (Combined Entity)'!N270 -> -3605600
C22: (-) CIT on Sale | E22: -2150000
C23: (-) Dividends (declared but unpaid) | E23: -1480000
C24: (+) Cash | E24: ='2. Tallowick (Combined Entity)'!N227 -> 7555393.8
C25: Total Equity Value | E25: =E20+SUM(E21:E24) -> 1.418284e+08
C26: Fund Ownership (%) | E26: 0.74
C27: Fund Equity Value | E27: =E25*E26 -> 1.0495302e+08
C28: Purchase Price (Fund Equity Value x NAV Pricing) | E28: =E27*E13 -> 97606307
C29: Pricing to NAV (%) | E29: =IFERROR(E28/E27,0) -> 0.93
C31: B | D31: Capitalization and Sources & Uses
C32: Pre-Capitalization:
C33: Adjusted Net Debt:
C34: Gross Debt | E34: =-E21 -> 3605600
C35: (-) Cash | E35: =-E24 -> -7555393.8
C36: (-)/(+) Adjustments (CIT, Unpaid Dividends) | E36: =-(SUM(E21:E24)-E21-E24) -> 3630000
C37: Adjusted Net Debt | E37: =SUM(E34:E36) -> -319793.75
C38: Equity Value:
C39: Kessport Frontier Fund II | D39: =E26 -> 0.74 | E39: =$E$25*D39 -> 1.0495302e+08
C40: Management | D40: 0.26 | E40: =$E$25*D40 -> 36875385
C41: Total Equity Value | D41: =SUM(D39:D40) -> 1 | E41: =SUM(E39:E40) -> 1.418284e+08
C42: Total Enterprise Value | E42: =E37+E41 -> 1.4150861e+08
C44: Post-Capitalization:
C45: Adjusted Net Debt:
C46: Gross Debt | E46: =E34 -> 3605600
C47: (-) Cash | E47: =E35 -> -7555393.8
C48: (-)/(+) Adjustments | E48: =E36 -> 3630000
C49: Adjusted Net Debt | E49: =SUM(E46:E48) -> -319793.75
C50: Equity Value:
C51: Dunecrest Continuation Fund (acquires the Fund II stake) | D51: =D39 -> 0.74 | E51: =E39 -> 1.0495302e+08
C52: Management | D52: =SUM(D40:D40) -> 0.26 | E52: =SUM(E40:E40) -> 36875385
C53: Total Equity Value | E53: =E51+E52 -> 1.418284e+08
C54: Total Enterprise Value | E54: =E49+E53 -> 1.4150861e+08
C55: Check (Post – Pre TEV) | E55: =E54-E42 -> 0
C57: Exit Assumptions
C58: A | D58: Exit Valuation
C59: Exit Date | E59: 48213
C60: Exit Path | E60: M&A
C61: Exit EBITDA Multiple (x) | E61: 7.5
C63: Total Cash Flows (100% basis):
C64: Exit EBITDA (2030E EBITDA grown at the 2030E growth rate) (2) | S64: ='2. Tallowick (Combined Entity)'!R208*(1+'2. Tallowick (Combined Entity)'!R200) -> 31323257
C65: Exit Multiple (x) | S65: =$E$61 -> 7.5
C66: Exit TEV | S66: =S64*S65 -> 2.3492443e+08
C67: (-) Net Debt / (+) Net Cash (2030E balance) (2) | S67: =-'2. Tallowick (Combined Entity)'!R271 -> 30468351
C68: Exit Equity Value | S68: =SUM(S66:S67) -> 2.6539278e+08
C70: Total Cash Flows:
C71: (-) Initial Investment | G71: =IF(G$7=YEAR(Control!$E$12),-$E$25,0) -> 0 | H71: =IF(H$7=YEAR(Control!$E$12),-$E$25,0) -> 0 | I71: =IF(I$7=YEAR(Control!$E$12),-$E$25,0) -> 0 | J71: =IF(J$7=YEAR(Control!$E$12),-$E$25,0) -> 0 | K71: =IF(K$7=YEAR(Control!$E$12),-$E$25,0) -> 0 | L71: =IF(L$7=YEAR(Control!$E$12),-$E$25,0) -> 0 | M71: =IF(M$7=YEAR(Control!$E$12),-$E$25,0) -> 0 | N71: =IF(N$7=YEAR(Control!$E$12),-$E$25,0) -> -1.418284e+08 | ... S71: =IF(S$7=YEAR(Control!$E$12),-$E$25,0) -> 0
C72: (-) Follow-On Capital | G72: =IF(G$7>YEAR(Control!$E$12),-'2. Tallowick (Combined Entity)'!G192,0) -> 0 | H72: =IF(H$7>YEAR(Control!$E$12),-'2. Tallowick (Combined Entity)'!H192,0) -> 0 | I72: =IF(I$7>YEAR(Control!$E$12),-'2. Tallowick (Combined Entity)'!I192,0) -> 0 | J72: =IF(J$7>YEAR(Control!$E$12),-'2. Tallowick (Combined Entity)'!J192,0) -> 0 | K72: =IF(K$7>YEAR(Control!$E$12),-'2. Tallowick (Combined Entity)'!K192,0) -> 0 | L72: =IF(L$7>YEAR(Control!$E$12),-'2. Tallowick (Combined Entity)'!L192,0) -> 0 | M72: =IF(M$7>YEAR(Control!$E$12),-'2. Tallowick (Combined Entity)'!M192,0) -> 0 | N72: =IF(N$7>YEAR(Control!$E$12),-'2. Tallowick (Combined Entity)'!N192,0) -> 0 | ... R72: =IF(R$7>YEAR(Control!$E$12),-'2. Tallowick (Combined Entity)'!R192,0) -> 0 | S72: 0
C73: (+) Interim Proceeds (Dividends) | G73: =IF(G$7>YEAR(Control!$E$12),'2. Tallowick (Combined Entity)'!G279,0) -> 0 | H73: =IF(H$7>YEAR(Control!$E$12),'2. Tallowick (Combined Entity)'!H279,0) -> 0 | I73: =IF(I$7>YEAR(Control!$E$12),'2. Tallowick (Combined Entity)'!I279,0) -> 0 | J73: =IF(J$7>YEAR(Control!$E$12),'2. Tallowick (Combined Entity)'!J279,0) -> 0 | K73: =IF(K$7>YEAR(Control!$E$12),'2. Tallowick (Combined Entity)'!K279,0) -> 0 | L73: =IF(L$7>YEAR(Control!$E$12),'2. Tallowick (Combined Entity)'!L279,0) -> 0 | M73: =IF(M$7>YEAR(Control!$E$12),'2. Tallowick (Combined Entity)'!M279,0) -> 0 | N73: =IF(N$7>YEAR(Control!$E$12),'2. Tallowick (Combined Entity)'!N279,0) -> 0 | ... R73: =IF(R$7>YEAR(Control!$E$12),'2. Tallowick (Combined Entity)'!R279,0) -> 8831828.1 | S73: 0
C74: (+) Exit Value | G74: =IF(G$6=$E$59,S68,0) -> 0 | H74: =IF(H$6=$E$59,S68,0) -> 0 | I74: =IF(I$6=$E$59,S68,0) -> 0 | J74: =IF(J$6=$E$59,S68,0) -> 0 | K74: =IF(K$6=$E$59,S68,0) -> 0 | L74: =IF(L$6=$E$59,S68,0) -> 0 | M74: =IF(M$6=$E$59,S68,0) -> 0 | N74: =IF(N$6=$E$59,S68,0) -> 0 | O74: =IF(O$6=$E$59,S68,0) -> 0 | P74: =IF(P$6=$E$59,S68,0) -> 0 | Q74: =IF(Q$6=$E$59,S68,0) -> 0 | R74: =IF(R$6=$E$59,S68,0) -> 0 | S74: =IF(S$6=$E$59,S68,0) -> 2.6539278e+08
C75: Total Cash Flows | G75: =SUM(G71:G74) -> 0 | H75: =SUM(H71:H74) -> 0 | I75: =SUM(I71:I74) -> 0 | J75: =SUM(J71:J74) -> 0 | K75: =SUM(K71:K74) -> 0 | L75: =SUM(L71:L74) -> 0 | M75: =SUM(M71:M74) -> 0 | N75: =SUM(N71:N74) -> -1.418284e+08 | ... S75: =SUM(S71:S74) -> 2.6539278e+08
C76: Gross MoIC | E76: =IFERROR(SUMIF(G75:S75,">0")/-SUMIF(G75:S75,"<0"),0) -> 2.0620229
C77: Gross IRR | E77: =IFERROR(XIRR(G75:S75,G$6:S$6),0) -> 0.16469879
C79: Total Investment:
C80: Kessport Frontier Fund II | E80: =E39 -> 1.0495302e+08
C81: Owner 2 (Management) | E81: =E40 -> 36875385
C82: Total Investment | E82: =SUM(E80:E81) -> 1.418284e+08
C84: Continuation Fund Cash Flows:
C85: (-) Initial Investment (Purchase Price at NAV Pricing) | G85: =IF(G$7=YEAR(Control!$E$12),-$E$28,0) -> 0 | H85: =IF(H$7=YEAR(Control!$E$12),-$E$28,0) -> 0 | I85: =IF(I$7=YEAR(Control!$E$12),-$E$28,0) -> 0 | J85: =IF(J$7=YEAR(Control!$E$12),-$E$28,0) -> 0 | K85: =IF(K$7=YEAR(Control!$E$12),-$E$28,0) -> 0 | L85: =IF(L$7=YEAR(Control!$E$12),-$E$28,0) -> 0 | M85: =IF(M$7=YEAR(Control!$E$12),-$E$28,0) -> 0 | N85: =IF(N$7=YEAR(Control!$E$12),-$E$28,0) -> -97606307 | ... S85: =IF(S$7=YEAR(Control!$E$12),-$E$28,0) -> 0
C86: (-) Follow-On Capital (fund share) | G86: =G72*$E$26 -> 0 | H86: =H72*$E$26 -> 0 | I86: =I72*$E$26 -> 0 | J86: =J72*$E$26 -> 0 | K86: =K72*$E$26 -> 0 | L86: =L72*$E$26 -> 0 | M86: =M72*$E$26 -> 0 | N86: =N72*$E$26 -> 0 | ... S86: =S72*$E$26 -> 0
C87: (+) Interim Proceeds | G87: =G73*$E$26 -> 0 | H87: =H73*$E$26 -> 0 | I87: =I73*$E$26 -> 0 | J87: =J73*$E$26 -> 0 | K87: =K73*$E$26 -> 0 | L87: =L73*$E$26 -> 0 | M87: =M73*$E$26 -> 0 | N87: =N73*$E$26 -> 0 | ... S87: =S73*$E$26 -> 0
C88: (+) Exit Value | G88: =G74*$E$26 -> 0 | H88: =H74*$E$26 -> 0 | I88: =I74*$E$26 -> 0 | J88: =J74*$E$26 -> 0 | K88: =K74*$E$26 -> 0 | L88: =L74*$E$26 -> 0 | M88: =M74*$E$26 -> 0 | N88: =N74*$E$26 -> 0 | ... S88: =S74*$E$26 -> 1.9639065e+08
C89: Total Cash Flows | G89: =SUM(G85:G88) -> 0 | H89: =SUM(H85:H88) -> 0 | I89: =SUM(I85:I88) -> 0 | J89: =SUM(J85:J88) -> 0 | K89: =SUM(K85:K88) -> 0 | L89: =SUM(L85:L88) -> 0 | M89: =SUM(M85:M88) -> 0 | N89: =SUM(N85:N88) -> -97606307 | ... S89: =SUM(S85:S88) -> 1.9639065e+08
C90: Gross MoIC | E90: =IFERROR(SUMIF(G89:S89,">0")/-SUMIF(G89:S89,"<0"),0) -> 2.2172289
C91: Gross IRR | E91: =IFERROR(XIRR(G89:S89,G$6:S$6),0) -> 0.18287839
C93: Notes:
C94: (1) LTM Q2'26 EBITDA approximated as the average of FY2025A and FY2026E EBITDA.
C95: (2) Exit at 31-Dec-2031: exit EBITDA = FY2030E EBITDA grown one year at the FY2030E revenue growth rate; net debt and minorities at the FY2030E balance (last modelled year).

Sheet Transaction Summary
C3: =Cover!$C$3 -> Project Dunecrest | D3: Confidential
C4: Dunecrest Continuation Fund – Transaction Summary (USD)
C5: =IF(Control!$E$5=1,"Circuit breaker: ON – model live","Circuit breaker: OFF – outputs suspended") -> Circuit breaker: ON – model live
C6: Fiscal Year Ending | G6: =Control!$E$12 -> 46387 | H6: =EOMONTH(G6,12) -> 46752 | I6: =EOMONTH(H6,12) -> 47118 | J6: =EOMONTH(I6,12) -> 47483 | K6: =EOMONTH(J6,12) -> 47848 | L6: =EOMONTH(K6,12) -> 48213
C7: Fiscal Year | G7: =IF(G6=Control!$E$12,"Entry","FY"&TEXT(YEAR(G6),"0")&"E") -> Entry | H7: =IF(H6=Control!$E$12,"Entry","FY"&TEXT(YEAR(H6),"0")&"E") -> FY2027E | I7: =IF(I6=Control!$E$12,"Entry","FY"&TEXT(YEAR(I6),"0")&"E") -> FY2028E | J7: =IF(J6=Control!$E$12,"Entry","FY"&TEXT(YEAR(J6),"0")&"E") -> FY2029E | K7: =IF(K6=Control!$E$12,"Entry","FY"&TEXT(YEAR(K6),"0")&"E") -> FY2030E | L7: =IF(L6=Control!$E$12,"Entry","FY"&TEXT(YEAR(L6),"0")&"E") -> FY2031E
C8: Year | G8: =YEAR(G6) -> 2026 | H8: =YEAR(H6) -> 2027 | I8: =YEAR(I6) -> 2028 | J8: =YEAR(J6) -> 2029 | K8: =YEAR(K6) -> 2030 | L8: =YEAR(L6) -> 2031
C10: Portfolio Summary
C11: A | D11: Portfolio Summary
C12: Investment Information:
C13: Investment | E13: Entry Date | F13: Ownership (%) | G13: Currency
C14: Arvenna Health Group | E14: =Control!$E$12 -> 46387 | F14: ='7. Entry & Exit'!$E$26 -> 0.58 | G14: =Control!$E$16 -> LCA
C15: Tallowick Consumer Products | E15: =Control!$E$12 -> 46387 | F15: ='3. Entry & Exit'!$E$26 -> 0.74 | G15: =Control!$E$21 -> LCB
C17: Investment Summary:
C18: Investment | E18: Cost | F18: NAV | G18: Pricing (%) | H18: Acquired Equity
C19: Arvenna Health Group | E19: 31420000 | F19: ='7. Entry & Exit'!$E$27 -> 48955459 | G19: =IFERROR(H19/F19,0) -> 0.94 | H19: ='7. Entry & Exit'!$E$28 -> 46018131
C20: Tallowick Consumer Products | E20: 27860000 | F20: ='3. Entry & Exit'!$E$27 -> 1.0495302e+08 | G20: =IFERROR(H20/F20,0) -> 0.93 | H20: ='3. Entry & Exit'!$E$28 -> 97606307
C21: Total | E21: =SUM(E19:E20) -> 59280000 | F21: =SUM(F19:F20) -> 1.5390848e+08 | G21: =IFERROR(H21/F21,0) -> 0.93318082 | H21: =SUM(H19:H20) -> 1.4362444e+08
C23: B | D23: Continuation Fund Sources & Uses
C24: Sources:
C25: Continuation Fund:
C26: Funded Equity | E26: =E36+E37+E42 -> 1.4506068e+08
C27: of which: Rolling LPs (Fund II investors rolling) | E27: =E26*Control!$E$30 -> 59474880
C28: of which: Reinvested GP Economics | E28: =Control!$E$29*1000000 -> 5200000
C29: of which: New LPs (secondary buyers) | E29: =E26-E27-E28 -> 80385803
C30: Follow-On Equity | E30: =E39+E40 -> 10223914
C31: Management Fees & Expenses | E31: =SUM('SPV Waterfall'!$G$53:$AA$53) -> 12430972
C32: Total Sources | E32: =E26+E30+E31 -> 1.6771557e+08
C34: Uses:
C35: Acquired Equity:
C36: Arvenna Health Group | E36: =H19 -> 46018131
C37: Tallowick Consumer Products | E37: =H20 -> 97606307
C38: Follow-On Capital:
C39: Arvenna Health Group | E39: =-SUM('7. Entry & Exit'!$G$91:$S$91) -> 6749170
C40: Tallowick Consumer Products | E40: =-SUM('3. Entry & Exit'!$G$86:$S$86) -> 3474744
C41: Management Fees & Expenses | E41: =SUM('SPV Waterfall'!$G$53:$AA$53) -> 12430972
C42: Buy-Side Transaction Fees | D42: 0.01 | E42: =D42*(E36+E37) -> 1436244.4
C43: Total Uses | E43: =SUM(E36:E42) -> 1.6771557e+08
C44: Check (Sources – Uses) | E44: =ROUND(E32-E43,2) -> 0
C46: Cash Flow Summary
C47: A | D47: Continuation Fund Cash Flows
C48: Initial Investment:
C49: Arvenna Health Group | G49: =SUMIFS('7. Entry & Exit'!$G$90:$S$90,'7. Entry & Exit'!$G$7:$S$7,G$8) -> -46018131 | H49: =SUMIFS('7. Entry & Exit'!$G$90:$S$90,'7. Entry & Exit'!$G$7:$S$7,H$8) -> 0 | I49: =SUMIFS('7. Entry & Exit'!$G$90:$S$90,'7. Entry & Exit'!$G$7:$S$7,I$8) -> 0 | J49: =SUMIFS('7. Entry & Exit'!$G$90:$S$90,'7. Entry & Exit'!$G$7:$S$7,J$8) -> 0 | K49: =SUMIFS('7. Entry & Exit'!$G$90:$S$90,'7. Entry & Exit'!$G$7:$S$7,K$8) -> 0 | L49: =SUMIFS('7. Entry & Exit'!$G$90:$S$90,'7. Entry & Exit'!$G$7:$S$7,L$8) -> 0
C50: Tallowick Consumer Products | G50: =SUMIFS('3. Entry & Exit'!$G$85:$S$85,'3. Entry & Exit'!$G$7:$S$7,G$8) -> -97606307 | H50: =SUMIFS('3. Entry & Exit'!$G$85:$S$85,'3. Entry & Exit'!$G$7:$S$7,H$8) -> 0 | I50: =SUMIFS('3. Entry & Exit'!$G$85:$S$85,'3. Entry & Exit'!$G$7:$S$7,I$8) -> 0 | J50: =SUMIFS('3. Entry & Exit'!$G$85:$S$85,'3. Entry & Exit'!$G$7:$S$7,J$8) -> 0 | K50: =SUMIFS('3. Entry & Exit'!$G$85:$S$85,'3. Entry & Exit'!$G$7:$S$7,K$8) -> 0 | L50: =SUMIFS('3. Entry & Exit'!$G$85:$S$85,'3. Entry & Exit'!$G$7:$S$7,L$8) -> 0
C51: Initial Transaction Fees | G51: =-IF(G$6=Control!$E$12,$E$42,0) -> -1436244.4 | H51: =-IF(H$6=Control!$E$12,$E$42,0) -> 0 | I51: =-IF(I$6=Control!$E$12,$E$42,0) -> 0 | J51: =-IF(J$6=Control!$E$12,$E$42,0) -> 0 | K51: =-IF(K$6=Control!$E$12,$E$42,0) -> 0 | L51: =-IF(L$6=Control!$E$12,$E$42,0) -> 0
C52: Total | G52: =SUM(G49:G51) -> -1.4506068e+08 | H52: =SUM(H49:H51) -> 0 | I52: =SUM(I49:I51) -> 0 | J52: =SUM(J49:J51) -> 0 | K52: =SUM(K49:K51) -> 0 | L52: =SUM(L49:L51) -> 0
C54: Follow-On Capital Deployed:
C55: Arvenna Health Group | G55: =SUMIFS('7. Entry & Exit'!$G$91:$S$91,'7. Entry & Exit'!$G$7:$S$7,G$8) -> 0 | H55: =SUMIFS('7. Entry & Exit'!$G$91:$S$91,'7. Entry & Exit'!$G$7:$S$7,H$8) -> -2670030 | I55: =SUMIFS('7. Entry & Exit'!$G$91:$S$91,'7. Entry & Exit'!$G$7:$S$7,I$8) -> -2375100 | J55: =SUMIFS('7. Entry & Exit'!$G$91:$S$91,'7. Entry & Exit'!$G$7:$S$7,J$8) -> -1042840 | K55: =SUMIFS('7. Entry & Exit'!$G$91:$S$91,'7. Entry & Exit'!$G$7:$S$7,K$8) -> -661200 | L55: =SUMIFS('7. Entry & Exit'!$G$91:$S$91,'7. Entry & Exit'!$G$7:$S$7,L$8) -> 0
C56: Tallowick Consumer Products | G56: =SUMIFS('3. Entry & Exit'!$G$86:$S$86,'3. Entry & Exit'!$G$7:$S$7,G$8) -> 0 | H56: =SUMIFS('3. Entry & Exit'!$G$86:$S$86,'3. Entry & Exit'!$G$7:$S$7,H$8) -> -1392384 | I56: =SUMIFS('3. Entry & Exit'!$G$86:$S$86,'3. Entry & Exit'!$G$7:$S$7,I$8) -> -1339104 | J56: =SUMIFS('3. Entry & Exit'!$G$86:$S$86,'3. Entry & Exit'!$G$7:$S$7,J$8) -> -743256 | K56: =SUMIFS('3. Entry & Exit'!$G$86:$S$86,'3. Entry & Exit'!$G$7:$S$7,K$8) -> 0 | L56: =SUMIFS('3. Entry & Exit'!$G$86:$S$86,'3. Entry & Exit'!$G$7:$S$7,L$8) -> 0
C57: Total | G57: =SUM(G55:G56) -> 0 | H57: =SUM(H55:H56) -> -4062414 | I57: =SUM(I55:I56) -> -3714204 | J57: =SUM(J55:J56) -> -1786096 | K57: =SUM(K55:K56) -> -661200 | L57: =SUM(L55:L56) -> 0
C59: Interim Proceeds:
C60: Arvenna Health Group | G60: =SUMIFS('7. Entry & Exit'!$G$92:$S$92,'7. Entry & Exit'!$G$7:$S$7,G$8) -> 0 | H60: =SUMIFS('7. Entry & Exit'!$G$92:$S$92,'7. Entry & Exit'!$G$7:$S$7,H$8) -> 1095516.1 | I60: =SUMIFS('7. Entry & Exit'!$G$92:$S$92,'7. Entry & Exit'!$G$7:$S$7,I$8) -> 1466101.7 | J60: =SUMIFS('7. Entry & Exit'!$G$92:$S$92,'7. Entry & Exit'!$G$7:$S$7,J$8) -> 1877338.2 | K60: =SUMIFS('7. Entry & Exit'!$G$92:$S$92,'7. Entry & Exit'!$G$7:$S$7,K$8) -> 2177337 | L60: =SUMIFS('7. Entry & Exit'!$G$92:$S$92,'7. Entry & Exit'!$G$7:$S$7,L$8) -> 0
C61: Tallowick Consumer Products | G61: =SUMIFS('3. Entry & Exit'!$G$87:$S$87,'3. Entry & Exit'!$G$7:$S$7,G$8) -> 0 | H61: =SUMIFS('3. Entry & Exit'!$G$87:$S$87,'3. Entry & Exit'!$G$7:$S$7,H$8) -> 5026473.4 | I61: =SUMIFS('3. Entry & Exit'!$G$87:$S$87,'3. Entry & Exit'!$G$7:$S$7,I$8) -> 5683203.1 | J61: =SUMIFS('3. Entry & Exit'!$G$87:$S$87,'3. Entry & Exit'!$G$7:$S$7,J$8) -> 6254389.7 | K61: =SUMIFS('3. Entry & Exit'!$G$87:$S$87,'3. Entry & Exit'!$G$7:$S$7,K$8) -> 6535552.8 | L61: =SUMIFS('3. Entry & Exit'!$G$87:$S$87,'3. Entry & Exit'!$G$7:$S$7,L$8) -> 0
C62: Total | G62: =SUM(G60:G61) -> 0 | H62: =SUM(H60:H61) -> 6121989.5 | I62: =SUM(I60:I61) -> 7149304.8 | J62: =SUM(J60:J61) -> 8131727.9 | K62: =SUM(K60:K61) -> 8712889.8 | L62: =SUM(L60:L61) -> 0
C64: Exit Proceeds:
C65: Arvenna Health Group | G65: =SUMIFS('7. Entry & Exit'!$G$93:$S$93,'7. Entry & Exit'!$G$7:$S$7,G$8) -> 0 | H65: =SUMIFS('7. Entry & Exit'!$G$93:$S$93,'7. Entry & Exit'!$G$7:$S$7,H$8) -> 0 | I65: =SUMIFS('7. Entry & Exit'!$G$93:$S$93,'7. Entry & Exit'!$G$7:$S$7,I$8) -> 0 | J65: =SUMIFS('7. Entry & Exit'!$G$93:$S$93,'7. Entry & Exit'!$G$7:$S$7,J$8) -> 0 | K65: =SUMIFS('7. Entry & Exit'!$G$93:$S$93,'7. Entry & Exit'!$G$7:$S$7,K$8) -> 0 | L65: =SUMIFS('7. Entry & Exit'!$G$93:$S$93,'7. Entry & Exit'!$G$7:$S$7,L$8) -> 1.3823739e+08
C66: Tallowick Consumer Products | G66: =SUMIFS('3. Entry & Exit'!$G$88:$S$88,'3. Entry & Exit'!$G$7:$S$7,G$8) -> 0 | H66: =SUMIFS('3. Entry & Exit'!$G$88:$S$88,'3. Entry & Exit'!$G$7:$S$7,H$8) -> 0 | I66: =SUMIFS('3. Entry & Exit'!$G$88:$S$88,'3. Entry & Exit'!$G$7:$S$7,I$8) -> 0 | J66: =SUMIFS('3. Entry & Exit'!$G$88:$S$88,'3. Entry & Exit'!$G$7:$S$7,J$8) -> 0 | K66: =SUMIFS('3. Entry & Exit'!$G$88:$S$88,'3. Entry & Exit'!$G$7:$S$7,K$8) -> 0 | L66: =SUMIFS('3. Entry & Exit'!$G$88:$S$88,'3. Entry & Exit'!$G$7:$S$7,L$8) -> 1.9639065e+08
C67: Total | G67: =SUM(G65:G66) -> 0 | H67: =SUM(H65:H66) -> 0 | I67: =SUM(I65:I66) -> 0 | J67: =SUM(J65:J66) -> 0 | K67: =SUM(K65:K66) -> 0 | L67: =SUM(L65:L66) -> 3.3462805e+08
C69: Total Cash Flows:
C70: Initial Investment | G70: =G52 -> -1.4506068e+08 | H70: =H52 -> 0 | I70: =I52 -> 0 | J70: =J52 -> 0 | K70: =K52 -> 0 | L70: =L52 -> 0
C71: Follow-On Capital | G71: =G57 -> 0 | H71: =H57 -> -4062414 | I71: =I57 -> -3714204 | J71: =J57 -> -1786096 | K71: =K57 -> -661200 | L71: =L57 -> 0
C72: Interim Proceeds | G72: =G62 -> 0 | H72: =H62 -> 6121989.5 | I72: =I62 -> 7149304.8 | J72: =J62 -> 8131727.9 | K72: =K62 -> 8712889.8 | L72: =L62 -> 0
C73: Exit Proceeds | G73: =G67 -> 0 | H73: =H67 -> 0 | I73: =I67 -> 0 | J73: =J67 -> 0 | K73: =K67 -> 0 | L73: =L67 -> 3.3462805e+08
C74: Total Continuation Fund Cash Flows | G74: =SUM(G70:G73) -> -1.4506068e+08 | H74: =SUM(H70:H73) -> 2059575.5 | I74: =SUM(I70:I73) -> 3435100.8 | J74: =SUM(J70:J73) -> 6345631.9 | K74: =SUM(K70:K73) -> 8051689.8 | L74: =SUM(L70:L73) -> 3.3462805e+08
C76: Gross MoIC | E76: =IFERROR(SUMIF(G74:L74,">0")/-SUMIF(G74:L74,"<0"),0) -> 2.443943
C77: Gross IRR | E77: =IFERROR(XIRR(G74:L74,G$6:L$6),0) -> 0.20171449
C79: Notes:
C80: (1) Management fees & expenses are shown as a source and a use (funded by LP contributions over the life of the SPV; see SPV Waterfall).
